Workbook

Sheet 人物卡
B1: 电脑推荐使用excel2010及以后版本或WPS打开本卡，使用横轴滚动条可以看见更多东西，手机推荐使用WPS
B2: 调查员信息 | S2: 年龄补正： | V2: =附表!D37 -> 教育进步*1 | AA2: 属性 | AC2: 已用点数: | AG2: =U3+U5+U7+AA3+AA5+AA7+AG3+AG5+AG7 -> 605 | AL2: #VALUE! | AU2: 您的角色可能（只是可能！）
B3: 姓名 | E3: 艾迪安·多雷 | S3: 力量 STR | U3: 90 | W3: =INT(U3/2) -> 45 | Y3: 敏捷 DEX | AA3: 40 | AC3: =INT(AA3/2) -> 20 | AE3: 意志 POW | AG3: 75 | AI3: =INT(AG3/2) -> 37 | AU3: =IF(U3=0,"",IF(U3<=15,"虚弱，孱弱",IF(U3<=40,"力量弱小",IF(U3<=60,"有正常人的力量",IF(U3<=80,"超乎常人的力量",IF(U3<100,"超乎超乎常人的力量")))))) -> 超乎超乎常人的力量 | BC3: =IF(AA3=0,"",IF(AA3<=20,"很不灵活",IF(AA3<=40,"不是很灵活",IF(AA3<=60,"普通人水平",IF(AA3<=80,"是一位运动健将",IF(AA3<100,"高速而灵活,可以达成超凡的技艺")))))) -> 不是很灵活 | BK3: =IF(AG3=0,"",IF(AG3<=20,"尔不过玩物",IF(AG3<=40,"痴愚盲目",IF(AG3<=60,"如常人一般会有一定自制力",IF(AG3<=80,"我心如铁，心坚石穿",IF(AG3<100,"泰山崩于面而色不变",IF(AG3<140,"钢铁之心，还能看见鬼","你怕是个假人吧"))))))) -> 我心如铁，心坚石穿
B4: 玩家 | E4: Kanra | J4: 时代 | M4: 1920s | W4: =INT(U3/5) -> 18 | AC4: =INT(AA3/5) -> 8 | AI4: =INT(AG3/5) -> 15
B5: 职业 | E5: 探险家 | J5: 职业序号 | M5: 218 | S5: 体质 CON | U5: 50 | W5: =INT(U5/2) -> 25 | Y5: 外貌 APP | AA5: 65 | AC5: =INT(AA5/2) -> 32 | AE5: 教育 知识 | AG5: 65 | AI5: =INT(AG5/2) -> 32 | AU5: =IF(U5=0,"",IF(U5<=20,"常年患病在身",IF(U5<=40,"体弱多病",IF(U5<=60,"不会生什么大毛病",IF(U5<=80,"健硕，浑身湿透也不会感冒",IF(U5<100,"身体素质极好，精神抖擞")))))) -> 不会生什么大毛病 | BC5: =IF(AA5=0,"",IF(AA5<=20,"用脸就能恐惧敌人。。或队友",IF(AA5<=40,"有些难看",IF(AA5<=60,"人群之中谁也不会看你一眼之后就忘不掉你容颜",IF(AA5<=80,"五官端正，仪表堂堂",IF(AA5<100,"沉鱼落雁，闭月羞花")))))) -> 五官端正，仪表堂堂 | BK5: =IF(AG5=0,"",IF(AG5<=20,"目不识丁",IF(AG5<=40,"小学毕业",IF(AG5<=60,"高中毕业",IF(AG5<=80,"是重点大学的学生，或是普通大学的研究生",IF(AG5<100,"饱读诗书，满腹经纶")))))) -> 是重点大学的学生，或是普通大学的研究生
B6: 年龄 | E6: 31 | J6: 性别 | M6: 男 | W6: =INT(U5/5) -> 10 | AC6: =INT(AA5/5) -> 13 | AI6: =INT(AG5/5) -> 13
B7: 住地 | E7: 法国 里昂 | J7: 故乡 | M7: 法国 格勒诺布尔 | S7: 体型 SIZ | U7: 70 | W7: =INT(U7/2) -> 35 | Y7: 智力 灵感 | AA7: 80 | AC7: =INT(AA7/2) -> 40 | AE7: 幸运 Luck | AG7: 70 | AI7: =INT(AG7/2) -> 35 | AU7: =IF(U7=0,"",IF(U7<=20,"孩童，身短体瘦",IF(U7<=40,"乙女身材",IF(U7<=60,"普遍身高155-175",IF(U7<=80,"不是高就是胖",IF(U7<=100,"大号的人",IF(U7<150,"听说你正在申请身高世界记录？",IF(U7<180,"你可能是一头牛",IF(U7<200,"你已经是历史上最重的人类了","过分了喂！"))))))))) -> 不是高就是胖 | BC7: =IF(AA7=0,"",IF(AA7<=20,"脑子是个好东西，可惜。。。",IF(AA7<=40,"宛如智障",IF(AA7<=60,"有着普通人的灵光一现",IF(AA7<=80,"可以自主进行发明创造",IF(AA7<100,"天才级水准")))))) -> 可以自主进行发明创造 | BK7: =IF(AG7=0,"",IF(AG7<=20,"克夫克妻",IF(AG7<=40,"霉运连连",IF(AG7<=60,"命格平庸",IF(AG7<=80,"在马路边捡到100块",IF(AG7<100,"被幸运女神所眷顾")))))) -> 在马路边捡到100块
B8: 现时间 | G8: 1980 | J8: 1月 | L8: 1日 | N8: 0：00 | W8: =INT(U7/5) -> 14 | AC8: =INT(AA7/5) -> 16 | AI8: =INT(AG7/5) -> 14
B9: =IF(F9=0,"","任意特长数：") | F9: =INDEX(本职技能!$A$2:$HX$69,MATCH("任意特长",本职技能!$A$2:$A$75,0),MATCH($M$5,本职技能!$A$1:$HX$1,0)) -> 0 | K9: =INDEX(本职技能!$A$2:$HX$69,MATCH("☆",本职技能!$A$2:$A$75,0),MATCH($M$5,本职技能!$A$1:$HX$1,0)) -> 0 | T9: =INDEX(本职技能!$A$2:$HX$69,MATCH("⊙",本职技能!$A$2:$A$75,0),MATCH($M$5,本职技能!$A$1:$HX$1,0)) -> 0 | AC9: =INDEX(本职技能!$A$2:$HX$69,MATCH("☯",本职技能!$A$2:$A$75,0),MATCH($M$5,本职技能!$A$1:$HX$1,0)) -> 0 | AL9: =INDEX(本职技能!$A$2:$HX$69,MATCH("※",本职技能!$A$2:$A$75,0),MATCH($M$5,本职技能!$A$1:$HX$1,0)) -> 0
B10: 生命值 Hit Points | E10: =G10 -> 12 | G10: =INT((U5+U7)/10) -> 12 | I10: 状态: | K10: 理智 Sanity | N10: =AG3 -> 75 | P10: =99-R27 -> 99 | R10: 状态: | T10: 魔法 Magic Points | W10: =Y10 -> 15 | Y10: =INT(AG3/5) -> 15 | AA10: 每h恢复 | AC10: 移动力 MOV | AF10: =AI11+8 -> 8 | AI10: 调整值 | AK10: 护甲 Armor | AN10: =IF($AN12=0,"0",VLOOKUP($AN12,'防具表 载具表'!B2:J82,2,FALSE)) -> 0 | AR10: 覆盖部位 | AT10: =IF($AN12=0,"",VLOOKUP($AN12,'防具表 载具表'!B2:I101,4,FALSE)) -> 0
I11: 健康 | R11: 清醒 | AA11: =IF(AG3="","",INT(AG3/100+1)) -> 1 | AI11: =附表!C9 -> 0
B12: 重伤值: | D12: =CEILING(G10/2,1) -> 6 | F12: 临时生命值： | I12: 0 | K12: 今日损失 : | N12: 0 | P12: 剩余： | R12: =N10-N12 -> 75 | T12: 使用过的魔法： | AC12: 移动方式 | AE12: 步式 | AG12: 护甲减值 | AI12: 关 | AK12: 护甲类型 : | AN12: 请看【防具表】
B13: =IF(M5=0," ","["&LOOKUP(M5,职业列表!A2:A232,职业列表!B2:B232)&"]的本职技能："&LOOKUP(M5,职业列表!A2:A232,职业列表!G2:G232)) -> [探险家]的本职技能：人类学，考古学，估价，科学（生物学），攀爬，急救，射击（手枪、来复枪），格斗（斗殴），博物学，导航，其他语言（任意），驾驶（小艇，船，热气球），骑术，潜行，侦查，游泳，追踪
B14: 技能表
B15: 成功标 | D15: 本职 | F15: 技能名称 | J15: 初始 | L15: 成长 | N15: 职业 | P15: 兴趣 | R15: 成功率 普通/困难/极难 | X15: 成功标 | Z15: 本职 | AB15: 技能名称 | AF15: 初始 | AH15: 成长 | AJ15: 职业 | AL15: 兴趣 | AN15: 成功率 普通/困难/极难
B16: ☐ | D16: =IF(ISTEXT(IFERROR(VLOOKUP(人物卡!F16,人物卡!BJ18:BR22,1,FALSE),IFERROR(VLOOKUP(人物卡!F16,人物卡!BA18:BC22,1,FALSE),0))),"★",INDEX(本职技能!$A$2:$HX$76,MATCH(人物卡!F16,本职技能!$A$2:$A$75,0),MATCH(人物卡!$M$5,本职技能!$A$1:$HX$1,0))) -> 0 | F16: 会计 | J16: 5 | R16: =SUM(J16:P16) -> 5 | T16: =INT(R16/2) -> 2 | V16: =INT(R16/5) -> 1 | X16: ☐ | Z16: =IF(ISTEXT(IFERROR(VLOOKUP(人物卡!AB16,人物卡!BJ18:BR22,1,FALSE),IFERROR(VLOOKUP(人物卡!AB16,人物卡!BA18:BC22,1,FALSE),0))),"★",INDEX(本职技能!$A$2:$HX$76,MATCH(人物卡!AB16,本职技能!$A$2:$A$75,0),MATCH(人物卡!$M$5,本职技能!$A$1:$HX$1,0))) -> 0 | AB16: 法律 | AF16: 5 | AN16: =SUM(AF16:AL16) -> 5 | AP16: =INT(AN16/2) -> 2 | AR16: =INT(AN16/5) -> 1
B17: ☐ | D17: =IF(ISTEXT(IFERROR(VLOOKUP(人物卡!F17,人物卡!BJ18:BR22,1,FALSE),IFERROR(VLOOKUP(人物卡!F17,人物卡!BA18:BC22,1,FALSE),0))),"★",INDEX(本职技能!$A$2:$HX$76,MATCH(人物卡!F17,本职技能!$A$2:$A$75,0),MATCH(人物卡!$M$5,本职技能!$A$1:$HX$1,0))) -> ★ | F17: 人类学 | J17: 1 | R17: =SUM(J17:P17) -> 1 | T17: =INT(R17/2) -> 0 | V17: =INT(R17/5) -> 0 | X17: ☐ | Z17: =IF(ISTEXT(IFERROR(VLOOKUP(人物卡!AB17,人物卡!BJ18:BR22,1,FALSE),IFERROR(VLOOKUP(人物卡!AB17,人物卡!BA18:BC22,1,FALSE),0))),"★",INDEX(本职技能!$A$2:$HX$76,MATCH(人物卡!AB17,本职技能!$A$2:$A$75,0),MATCH(人物卡!$M$5,本职技能!$A$1:$HX$1,0))) -> 0 | AB17: 图书馆使用 | AF17: 20 | AN17: =SUM(AF17:AL17) -> 20 | AP17: =INT(AN17/2) -> 10 | AR17: =INT(AN17/5) -> 4 | AU17: 你现在有这么多 | BA17: 那么你分配到了哪里?
B18: ☐ | D18: =IF(ISTEXT(IFERROR(VLOOKUP(人物卡!F18,人物卡!BJ18:BR22,1,FALSE),IFERROR(VLOOKUP(人物卡!F18,人物卡!BA18:BC22,1,FALSE),0))),"★",INDEX(本职技能!$A$2:$HX$76,MATCH(人物卡!F18,本职技能!$A$2:$A$75,0),MATCH(人物卡!$M$5,本职技能!$A$1:$HX$1,0))) -> ★ | F18: 估价 | J18: 5 | R18: =SUM(J18:P18) -> 5 | T18: =INT(R18/2) -> 2 | V18: =INT(R18/5) -> 1 | X18: ☐ | Z18: =IF(ISTEXT(IFERROR(VLOOKUP(人物卡!AB18,人物卡!BJ18:BR22,1,FALSE),IFERROR(VLOOKUP(人物卡!AB18,人物卡!BA18:BC22,1,FALSE),0))),"★",INDEX(本职技能!$A$2:$HX$76,MATCH(人物卡!AB18,本职技能!$A$2:$A$75,0),MATCH(人物卡!$M$5,本职技能!$A$1:$HX$1,0))) -> 0 | AB18: 聆听 | AF18: 20 | AL18: 29 | AN18: =SUM(AF18:AL18) -> 49 | AP18: =INT(AN18/2) -> 24 | AR18: =INT(AN18/5) -> 9 | AU18: 任意特长
B19: ☐ | D19: =IF(ISTEXT(IFERROR(VLOOKUP(人物卡!F19,人物卡!BJ18:BR22,1,FALSE),IFERROR(VLOOKUP(人物卡!F19,人物卡!BA18:BC22,1,FALSE),0))),"★",INDEX(本职技能!$A$2:$HX$76,MATCH(人物卡!F19,本职技能!$A$2:$A$75,0),MATCH(人物卡!$M$5,本职技能!$A$1:$HX$1,0))) -> ★ | F19: 考古学 | J19: 1 | R19: =SUM(J19:P19) -> 1 | T19: =INT(R19/2) -> 0 | V19: =INT(R19/5) -> 0 | X19: ☐ | Z19: =IF(ISTEXT(IFERROR(VLOOKUP(人物卡!AB19,人物卡!BJ18:BR22,1,FALSE),IFERROR(VLOOKUP(人物卡!AB19,人物卡!BA18:BC22,1,FALSE),0))),"★",INDEX(本职技能!$A$2:$HX$76,MATCH(人物卡!AB19,本职技能!$A$2:$A$75,0),MATCH(人物卡!$M$5,本职技能!$A$1:$HX$1,0))) -> 0 | AB19: 锁匠 | AF19: 1 | AN19: =SUM(AF19:AL19) -> 1 | AP19: =INT(AN19/2) -> 0 | AR19: =INT(AN19/5) -> 0 | AU19: =附表!AD25 -> 无
B20: ☐ | D20: =IF(ISTEXT(IFERROR(VLOOKUP(人物卡!F20,人物卡!BJ18:BR22,1,FALSE),IFERROR(VLOOKUP(人物卡!F20,人物卡!BA18:BC22,1,FALSE),0))),"★",INDEX(本职技能!$A$2:$HX$76,MATCH(人物卡!F20,本职技能!$A$2:$A$75,0),MATCH(人物卡!$M$5,本职技能!$A$1:$HX$1,0))) -> 0 | F20: 技艺① | J20: =IF(ISBLANK(AU26),5,IF(H20=AU26,BA26,5)) -> 5 | R20: =J20+L20+N20+P20 -> 5 | T20: =INT(R20/2) -> 2 | V20: =INT(R20/5) -> 1 | X20: ☐ | Z20: =IF(ISTEXT(IFERROR(VLOOKUP(人物卡!AB20,人物卡!BJ18:BR22,1,FALSE),IFERROR(VLOOKUP(人物卡!AB20,人物卡!BA18:BC22,1,FALSE),0))),"★",INDEX(本职技能!$A$2:$HX$76,MATCH(人物卡!AB20,本职技能!$A$2:$A$75,0),MATCH(人物卡!$M$5,本职技能!$A$1:$HX$1,0))) -> 0 | AB20: 机械维修 | AF20: 10 | AN20: =SUM(AF20:AL20) -> 10 | AP20: =INT(AN20/2) -> 5 | AR20: =INT(AN20/5) -> 2
B21: ☐ | D21: =IF(ISTEXT(IFERROR(VLOOKUP(人物卡!F21,人物卡!BJ18:BR22,1,FALSE),IFERROR(VLOOKUP(人物卡!F21,人物卡!BA18:BC22,1,FALSE),0))),"★",INDEX(本职技能!$A$2:$HX$76,MATCH(人物卡!F21,本职技能!$A$2:$A$75,0),MATCH(人物卡!$M$5,本职技能!$A$1:$HX$1,0))) -> 0 | F21: 技艺② | J21: =IF(ISBLANK(AU26),5,IF(H21=AU26,BA26,5)) -> 5 | R21: =P21+N21+L21+J21 -> 5 | T21: =INT(R21/2) -> 2 | V21: =INT(R21/5) -> 1 | X21: ☐ | Z21: =IF(ISTEXT(IFERROR(VLOOKUP(人物卡!AB21,人物卡!BJ18:BR22,1,FALSE),IFERROR(VLOOKUP(人物卡!AB21,人物卡!BA18:BC22,1,FALSE),0))),"★",INDEX(本职技能!$A$2:$HX$76,MATCH(人物卡!AB21,本职技能!$A$2:$A$75,0),MATCH(人物卡!$M$5,本职技能!$A$1:$HX$1,0))) -> 0 | AB21: 医学 | AF21: 1 | AN21: =SUM(AF21:AL21) -> 1 | AP21: =INT(AN21/2) -> 0 | AR21: =INT(AN21/5) -> 0
B22: ☐ | D22: =IF(ISTEXT(IFERROR(VLOOKUP(人物卡!F22,人物卡!BJ18:BR22,1,FALSE),IFERROR(VLOOKUP(人物卡!F22,人物卡!BA18:BC22,1,FALSE),0))),"★",INDEX(本职技能!$A$2:$HX$76,MATCH(人物卡!F22,本职技能!$A$2:$A$75,0),MATCH(人物卡!$M$5,本职技能!$A$1:$HX$1,0))) -> 0 | F22: 技艺③ | J22: =IF(ISBLANK(AU26),5,IF(H22=AU26,BA26,5)) -> 5 | R22: =P22+N22+L22+J22 -> 5 | T22: =INT(R22/2) -> 2 | V22: =INT(R22/5) -> 1 | X22: ☐ | Z22: =IF(ISTEXT(IFERROR(VLOOKUP(人物卡!AB22,人物卡!BJ18:BR22,1,FALSE),IFERROR(VLOOKUP(人物卡!AB22,人物卡!BA18:BC22,1,FALSE),0))),"★",INDEX(本职技能!$A$2:$HX$76,MATCH(人物卡!AB22,本职技能!$A$2:$A$75,0),MATCH(人物卡!$M$5,本职技能!$A$1:$HX$1,0))) -> ★ | AB22: 博物学 | AF22: 10 | AJ22: 40 | AN22: =SUM(AF22:AL22) -> 50 | AP22: =INT(AN22/2) -> 25 | AR22: =INT(AN22/5) -> 10
B23: ☐ | D23: =IF(ISTEXT(IFERROR(VLOOKUP(人物卡!F23,人物卡!BJ18:BR22,1,FALSE),IFERROR(VLOOKUP(人物卡!F23,人物卡!BA18:BC22,1,FALSE),0))),"★",INDEX(本职技能!$A$2:$HX$76,MATCH(人物卡!F23,本职技能!$A$2:$A$75,0),MATCH(人物卡!$M$5,本职技能!$A$1:$HX$1,0))) -> 0 | F23: 取悦 | J23: 15 | N23: 5 | P23: 29 | R23: =SUM(J23:P23) -> 49 | T23: =INT(R23/2) -> 24 | V23: =INT(R23/5) -> 9 | X23: ☐ | Z23: =IF(ISTEXT(IFERROR(VLOOKUP(人物卡!AB23,人物卡!BJ18:BR22,1,FALSE),IFERROR(VLOOKUP(人物卡!AB23,人物卡!BA18:BC22,1,FALSE),0))),"★",INDEX(本职技能!$A$2:$HX$76,MATCH(人物卡!AB23,本职技能!$A$2:$A$75,0),MATCH(人物卡!$M$5,本职技能!$A$1:$HX$1,0))) -> ★ | AB23: 导航 | AF23: 10 | AN23: =SUM(AF23:AL23) -> 10 | AP23: =INT(AN23/2) -> 5 | AR23: =INT(AN23/5) -> 2 | AU23: 请将你选择的任意特长写在上方栏内，这样既方便你写卡又方便KP审卡
B24: ☐ | D24: =IF(ISTEXT(IFERROR(VLOOKUP(人物卡!F24,人物卡!BJ18:BR22,1,FALSE),IFERROR(VLOOKUP(人物卡!F24,人物卡!BA18:BC22,1,FALSE),0))),"★",INDEX(本职技能!$A$2:$HX$76,MATCH(人物卡!F24,本职技能!$A$2:$A$75,0),MATCH(人物卡!$M$5,本职技能!$A$1:$HX$1,0))) -> ★ | F24: 攀爬 | J24: 20 | R24: =SUM(J24:P24) -> 20 | T24: =INT(R24/2) -> 10 | V24: =INT(R24/5) -> 4 | X24: ☐ | Z24: =IF(ISTEXT(IFERROR(VLOOKUP(人物卡!AB24,人物卡!BJ18:BR22,1,FALSE),IFERROR(VLOOKUP(人物卡!AB24,人物卡!BA18:BC22,1,FALSE),0))),"★",INDEX(本职技能!$A$2:$HX$76,MATCH(人物卡!AB24,本职技能!$A$2:$A$75,0),MATCH(人物卡!$M$5,本职技能!$A$1:$HX$1,0))) -> 0 | AB24: 神秘学 | AF24: 5 | AN24: =SUM(AF24:AL24) -> 5 | AP24: =INT(AN24/2) -> 2 | AR24: =INT(AN24/5) -> 1 | AU24: 自定义子技能 | BC24: 自定义经历包 | BK24: 自定义状态
B25: ☐ | D25: =IF(ISTEXT(IFERROR(VLOOKUP(人物卡!F25,人物卡!BJ18:BR22,1,FALSE),IFERROR(VLOOKUP(人物卡!F25,人物卡!BA18:BC22,1,FALSE),0))),"★",INDEX(本职技能!$A$2:$HX$76,MATCH(人物卡!F25,本职技能!$A$2:$A$75,0),MATCH(人物卡!$M$5,本职技能!$A$1:$HX$1,0))) -> 0 | F25: 计算机使用 Ω | J25: 5 | R25: =SUM(J25:P25) -> 5 | T25: =INT(R25/2) -> 2 | V25: =INT(R25/5) -> 1 | X25: ☐ | Z25: =IF(ISTEXT(IFERROR(VLOOKUP(人物卡!AB25,人物卡!BJ18:BR22,1,FALSE),IFERROR(VLOOKUP(人物卡!AB25,人物卡!BA18:BC22,1,FALSE),0))),"★",INDEX(本职技能!$A$2:$HX$76,MATCH(人物卡!AB25,本职技能!$A$2:$A$75,0),MATCH(人物卡!$M$5,本职技能!$A$1:$HX$1,0))) -> 0 | AB25: 操作重型机械 | AF25: 1 | AN25: =SUM(AF25:AL25) -> 1 | AP25: =INT(AN25/2) -> 0 | AR25: =INT(AN25/5) -> 0 | AU25: 技艺技能名称 | BA25: 基础值 | BC25: 经历包名称 | BK25: 状态名称(例:生病、精神分裂)
B26: —— | D26: ★ | F26: 信用评级 | J26: 0 | N26: 50 | R26: =SUM(J26:P26) -> 50 | T26: =INT(R26/2) -> 25 | V26: =INT(R26/5) -> 10 | X26: ☐ | Z26: =IF(ISTEXT(IFERROR(VLOOKUP(人物卡!AB26,人物卡!BJ18:BR22,1,FALSE),IFERROR(VLOOKUP(人物卡!AB26,人物卡!BA18:BC22,1,FALSE),0))),"★",INDEX(本职技能!$A$2:$HX$76,MATCH(人物卡!AB26,本职技能!$A$2:$A$75,0),MATCH(人物卡!$M$5,本职技能!$A$1:$HX$1,0))) -> 0 | AB26: 说服 | AF26: 10 | AL26: 39 | AN26: =SUM(AF26:AL26) -> 49 | AP26: =INT(AN26/2) -> 24 | AR26: =INT(AN26/5) -> 9
B27: —— | D27: =IF(ISTEXT(IFERROR(VLOOKUP(F27,人物卡!BJ18:BR22,1,FALSE),IFERROR(VLOOKUP(F27,人物卡!BA18:BC22,1,FALSE),0))),"★",INDEX(本职技能!$A$2:$HX$76,MATCH(F27,本职技能!$A$2:$A$75,0),MATCH(人物卡!$M$5,本职技能!$A$1:$HX$1,0))) -> 0 | F27: 克苏鲁神话 | J27: 0 | N27: —— | P27: —— | R27: =SUM(J27:P27) -> 0 | T27: =INT(R27/2) -> 0 | V27: =INT(R27/5) -> 0 | X27: ☐ | Z27: =IF(ISTEXT(IFERROR(VLOOKUP(人物卡!AB27,人物卡!BJ18:BR22,1,FALSE),IFERROR(VLOOKUP(人物卡!AB27,人物卡!BA18:BC22,1,FALSE),0))),"★",INDEX(本职技能!$A$2:$HX$76,MATCH(人物卡!AB27,本职技能!$A$2:$A$75,0),MATCH(人物卡!$M$5,本职技能!$A$1:$HX$1,0))) -> 艇船球 | AB27: 驾驶： | AF27: =IF(ISBLANK(AU32),1,IF(AD27=AU32,BA32,1)) -> 1 | AN27: =SUM(AF27:AL27) -> 1 | AP27: =INT(AN27/2) -> 0 | AR27: =INT(AN27/5) -> 0 | AU27: 格斗技能名称 | BA27: 基础值 | BC27: san值减少 | BG27: 技能增长 | BK27: 身体状态 | BO27: 精神状态
B28: ☐ | D28: =IF(ISTEXT(IFERROR(VLOOKUP(人物卡!F28,人物卡!BJ18:BR22,1,FALSE),IFERROR(VLOOKUP(人物卡!F28,人物卡!BA18:BC22,1,FALSE),0))),"★",INDEX(本职技能!$A$2:$HX$76,MATCH(人物卡!F28,本职技能!$A$2:$A$75,0),MATCH(人物卡!$M$5,本职技能!$A$1:$HX$1,0))) -> 0 | F28: 乔装 | J28: 5 | R28: =SUM(J28:P28) -> 5 | T28: =INT(R28/2) -> 2 | V28: =INT(R28/5) -> 1 | X28: ☐ | Z28: =IF(ISTEXT(IFERROR(VLOOKUP(人物卡!AB28,人物卡!BJ18:BR22,1,FALSE),IFERROR(VLOOKUP(人物卡!AB28,人物卡!BA18:BC22,1,FALSE),0))),"★",INDEX(本职技能!$A$2:$HX$76,MATCH(人物卡!AB28,本职技能!$A$2:$A$75,0),MATCH(人物卡!$M$5,本职技能!$A$1:$HX$1,0))) -> 0 | AB28: 精神分析 | AF28: 1 | AN28: =SUM(AF28:AL28) -> 1 | AP28: =INT(AN28/2) -> 0 | AR28: =INT(AN28/5) -> 0
B29: ☐ | D29: =IF(ISTEXT(IFERROR(VLOOKUP(人物卡!F29,人物卡!BJ18:BR22,1,FALSE),IFERROR(VLOOKUP(人物卡!F29,人物卡!BA18:BC22,1,FALSE),0))),"★",INDEX(本职技能!$A$2:$HX$76,MATCH(人物卡!F29,本职技能!$A$2:$A$75,0),MATCH(人物卡!$M$5,本职技能!$A$1:$HX$1,0))) -> 0 | F29: 闪避 | J29: =INT(附表!J14/2) -> 20 | P29: 24 | R29: =SUM(J29:P29) -> 44 | T29: =INT(R29/2) -> 22 | V29: =INT(R29/5) -> 8 | X29: ☐ | Z29: =IF(ISTEXT(IFERROR(VLOOKUP(人物卡!AB29,人物卡!BJ18:BR22,1,FALSE),IFERROR(VLOOKUP(人物卡!AB29,人物卡!BA18:BC22,1,FALSE),0))),"★",INDEX(本职技能!$A$2:$HX$76,MATCH(人物卡!AB29,本职技能!$A$2:$A$75,0),MATCH(人物卡!$M$5,本职技能!$A$1:$HX$1,0))) -> 0 | AB29: 心理学 | AF29: 10 | AL29: 39 | AN29: =SUM(AF29:AL29) -> 49 | AP29: =INT(AN29/2) -> 24 | AR29: =INT(AN29/5) -> 9 | AU29: 射击技能名称 | BA29: 基础值 | BC29: 备注
B30: ☐ | D30: =IF(ISTEXT(IFERROR(VLOOKUP(人物卡!F30,人物卡!BJ18:BR22,1,FALSE),IFERROR(VLOOKUP(人物卡!F30,人物卡!BA18:BC22,1,FALSE),0))),"★",INDEX(本职技能!$A$2:$HX$76,MATCH(人物卡!F30,本职技能!$A$2:$A$75,0),MATCH(人物卡!$M$5,本职技能!$A$1:$HX$1,0))) -> 0 | F30: 汽车驾驶 | J30: 20 | R30: =SUM(J30:P30) -> 20 | T30: =INT(R30/2) -> 10 | V30: =INT(R30/5) -> 4 | X30: ☐ | Z30: =IF(ISTEXT(IFERROR(VLOOKUP(人物卡!AB30,人物卡!BJ18:BR22,1,FALSE),IFERROR(VLOOKUP(人物卡!AB30,人物卡!BA18:BC22,1,FALSE),0))),"★",INDEX(本职技能!$A$2:$HX$76,MATCH(人物卡!AB30,本职技能!$A$2:$A$75,0),MATCH(人物卡!$M$5,本职技能!$A$1:$HX$1,0))) -> ★ | AB30: 骑术 | AF30: 5 | AN30: =SUM(AF30:AL30) -> 5 | AP30: =INT(AN30/2) -> 2 | AR30: =INT(AN30/5) -> 1
B31: ☐ | D31: =IF(ISTEXT(IFERROR(VLOOKUP(人物卡!F31,人物卡!BJ18:BR22,1,FALSE),IFERROR(VLOOKUP(人物卡!F31,人物卡!BA18:BC22,1,FALSE),0))),"★",INDEX(本职技能!$A$2:$HX$76,MATCH(人物卡!F31,本职技能!$A$2:$A$75,0),MATCH(人物卡!$M$5,本职技能!$A$1:$HX$1,0))) -> 0 | F31: 电气维修 | J31: 10 | R31: =SUM(J31:P31) -> 10 | T31: =INT(R31/2) -> 5 | V31: =INT(R31/5) -> 2 | X31: ☐ | Z31: =IF(ISTEXT(IFERROR(VLOOKUP(人物卡!AB31,人物卡!BJ18:BR22,1,FALSE),IFERROR(VLOOKUP(人物卡!AB31,人物卡!BA18:BC22,1,FALSE),0))),"★",INDEX(本职技能!$A$2:$HX$76,MATCH(人物卡!AB31,本职技能!$A$2:$A$75,0),MATCH(人物卡!$M$5,本职技能!$A$1:$HX$1,0))) -> 生物 | AB31: 科学① | AF31: =IF(ISBLANK(AU34),IF(AD31="数学",10,1),IF(AD31=AU34,BA34,1)) -> 1 | AN31: =AF31+AH31+AL31+AJ31 -> 1 | AP31: =INT(AN31/2) -> 0 | AR31: =INT(AN31/5) -> 0 | AU31: 驾驶技能名称 | BA31: 基础值
B32: ☐ | D32: =IF(ISTEXT(IFERROR(VLOOKUP(人物卡!F32,人物卡!BJ18:BR22,1,FALSE),IFERROR(VLOOKUP(人物卡!F32,人物卡!BA18:BC22,1,FALSE),0))),"★",INDEX(本职技能!$A$2:$HX$76,MATCH(人物卡!F32,本职技能!$A$2:$A$75,0),MATCH(人物卡!$M$5,本职技能!$A$1:$HX$1,0))) -> 0 | F32: 电子学 Ω | J32: 1 | R32: =SUM(J32:P32) -> 1 | T32: =INT(R32/2) -> 0 | V32: =INT(R32/5) -> 0 | X32: ☐ | Z32: =IF(ISTEXT(IFERROR(VLOOKUP(人物卡!AB32,人物卡!BJ18:BR22,1,FALSE),IFERROR(VLOOKUP(人物卡!AB32,人物卡!BA18:BC22,1,FALSE),0))),"★",INDEX(本职技能!$A$2:$HX$76,MATCH(人物卡!AB32,本职技能!$A$2:$A$75,0),MATCH(人物卡!$M$5,本职技能!$A$1:$HX$1,0))) -> 0 | AB32: 科学② | AF32: =IF(ISBLANK(AU34),IF(AD32="数学",10,1),IF(AD32=AU34,BA34,1)) -> 1 | AN32: =AL32+AJ32+AF32+AH32 -> 1 | AP32: =INT(AN32/2) -> 0 | AR32: =INT(AN32/5) -> 0
B33: ☐ | D33: =IF(ISTEXT(IFERROR(VLOOKUP(人物卡!F33,人物卡!BJ18:BR22,1,FALSE),IFERROR(VLOOKUP(人物卡!F33,人物卡!BA18:BC22,1,FALSE),0))),"★",INDEX(本职技能!$A$2:$HX$76,MATCH(人物卡!F33,本职技能!$A$2:$A$75,0),MATCH(人物卡!$M$5,本职技能!$A$1:$HX$1,0))) -> 0 | F33: 话术 | J33: 5 | R33: =SUM(J33:P33) -> 5 | T33: =INT(R33/2) -> 2 | V33: =INT(R33/5) -> 1 | X33: ☐ | Z33: =IF(ISTEXT(IFERROR(VLOOKUP(人物卡!AB33,人物卡!BJ18:BR22,1,FALSE),IFERROR(VLOOKUP(人物卡!AB33,人物卡!BA18:BC22,1,FALSE),0))),"★",INDEX(本职技能!$A$2:$HX$76,MATCH(人物卡!AB33,本职技能!$A$2:$A$75,0),MATCH(人物卡!$M$5,本职技能!$A$1:$HX$1,0))) -> 0 | AB33: 科学③ | AF33: =IF(ISBLANK(AU34),IF(AD33="数学",10,1),IF(AD33=AU34,BA34,1)) -> 1 | AN33: =AF33+AH33+AJ33+AL33 -> 1 | AP33: =INT(AN33/2) -> 0 | AR33: =INT(AN33/5) -> 0 | AU33: 科学技能名称 | BA33: 基础值
B34: ☐ | D34: =IF(ISTEXT(IFERROR(VLOOKUP(人物卡!F34,人物卡!BJ18:BR22,1,FALSE),IFERROR(VLOOKUP(人物卡!F34,人物卡!BA18:BC22,1,FALSE),0))),"★",INDEX(本职技能!$A$2:$HX$76,MATCH(人物卡!F34,本职技能!$A$2:$A$75,0),MATCH(人物卡!$M$5,本职技能!$A$1:$HX$1,0))) -> ★ | F34: 格斗： | H34: 斗殴 | J34: 25 | N34: 40 | R34: =SUM(J34:P34) -> 65 | T34: =INT(R34/2) -> 32 | V34: =INT(R34/5) -> 13 | X34: ☐ | Z34: =IF(ISTEXT(IFERROR(VLOOKUP(人物卡!AB34,人物卡!BJ18:BR22,1,FALSE),IFERROR(VLOOKUP(人物卡!AB34,人物卡!BA18:BC22,1,FALSE),0))),"★",INDEX(本职技能!$A$2:$HX$76,MATCH(人物卡!AB34,本职技能!$A$2:$A$75,0),MATCH(人物卡!$M$5,本职技能!$A$1:$HX$1,0))) -> 0 | AB34: 妙手 | AF34: 10 | AN34: =SUM(AF34:AL34) -> 10 | AP34: =INT(AN34/2) -> 5 | AR34: =INT(AN34/5) -> 2
B35: ☐ | D35: =IF(ISTEXT(IFERROR(VLOOKUP(人物卡!F35,人物卡!BJ18:BR22,1,FALSE),IFERROR(VLOOKUP(人物卡!F35,人物卡!BA18:BC22,1,FALSE),0))),"★",INDEX(本职技能!$A$2:$HX$76,MATCH(人物卡!F35,本职技能!$A$2:$A$75,0),MATCH(人物卡!$M$5,本职技能!$A$1:$HX$1,0))) -> 0 | F35: 格斗① | J35: =附表!C11 -> 0 | R35: =J35+L35+N35+P35 -> 0 | T35: =INT(R35/2) -> 0 | V35: =INT(R35/5) -> 0 | X35: ☐ | Z35: =IF(ISTEXT(IFERROR(VLOOKUP(人物卡!AB35,人物卡!BJ18:BR22,1,FALSE),IFERROR(VLOOKUP(人物卡!AB35,人物卡!BA18:BC22,1,FALSE),0))),"★",INDEX(本职技能!$A$2:$HX$76,MATCH(人物卡!AB35,本职技能!$A$2:$A$75,0),MATCH(人物卡!$M$5,本职技能!$A$1:$HX$1,0))) -> ★ | AB35: 侦查 | AF35: 25 | AJ35: 45 | AN35: =SUM(AF35:AL35) -> 70 | AP35: =INT(AN35/2) -> 35 | AR35: =INT(AN35/5) -> 14 | AU35: 自定义年龄补正 | BK35: 自定义货币
B36: ☐ | D36: =IF(ISTEXT(IFERROR(VLOOKUP(F36,人物卡!BJ18:BR22,1,FALSE),IFERROR(VLOOKUP(F36,人物卡!BA18:BC22,1,FALSE),0))),"★",INDEX(本职技能!$A$2:$HX$76,MATCH(F36,本职技能!$A$2:$A$75,0),MATCH(人物卡!$M$5,本职技能!$A$1:$HX$1,0))) -> 0 | F36: 格斗② | J36: =附表!C12 -> 0 | R36: =J36+L36+P36+N36 -> 0 | T36: =INT(R36/2) -> 0 | V36: =INT(R36/5) -> 0 | X36: ☐ | Z36: =IF(ISTEXT(IFERROR(VLOOKUP(人物卡!AB36,人物卡!BJ18:BR22,1,FALSE),IFERROR(VLOOKUP(人物卡!AB36,人物卡!BA18:BC22,1,FALSE),0))),"★",INDEX(本职技能!$A$2:$HX$76,MATCH(人物卡!AB36,本职技能!$A$2:$A$75,0),MATCH(人物卡!$M$5,本职技能!$A$1:$HX$1,0))) -> ★ | AB36: 潜行 | AF36: 20 | AJ36: 40 | AN36: =SUM(AF36:AL36) -> 60 | AP36: =INT(AN36/2) -> 30 | AR36: =INT(AN36/5) -> 12 | AU36: 年龄补正 | BK36: 货币名称 | BO36: 与美元的汇率
B37: ☐ | D37: =IF(ISTEXT(IFERROR(VLOOKUP(F37,人物卡!BJ18:BR22,1,FALSE),IFERROR(VLOOKUP(F37,人物卡!BA18:BC22,1,FALSE),0))),"★",INDEX(本职技能!$A$2:$HX$76,MATCH(F37,本职技能!$A$2:$A$75,0),MATCH(人物卡!$M$5,本职技能!$A$1:$HX$1,0))) -> 0 | F37: 格斗③ | J37: =附表!C13 -> 0 | R37: =P37+N37+L37+J37 -> 0 | T37: =INT(R37/2) -> 0 | V37: =INT(R37/5) -> 0 | X37: ☐ | Z37: =IF(ISTEXT(IFERROR(VLOOKUP(人物卡!AB37,人物卡!BJ18:BR22,1,FALSE),IFERROR(VLOOKUP(人物卡!AB37,人物卡!BA18:BC22,1,FALSE),0))),"★",INDEX(本职技能!$A$2:$HX$76,MATCH(人物卡!AB37,本职技能!$A$2:$A$75,0),MATCH(人物卡!$M$5,本职技能!$A$1:$HX$1,0))) -> 0 | AB37: 生存： | AF37: 10 | AN37: =SUM(AF37:AL37) -> 10 | AP37: =INT(AN37/2) -> 5 | AR37: =INT(AN37/5) -> 2
B38: ☐ | D38: =IF(ISTEXT(IFERROR(VLOOKUP(人物卡!F38,人物卡!BJ18:BR22,1,FALSE),IFERROR(VLOOKUP(人物卡!F38,人物卡!BA18:BC22,1,FALSE),0))),"★",INDEX(本职技能!$A$2:$HX$76,MATCH(人物卡!F38,本职技能!$A$2:$A$75,0),MATCH(人物卡!$M$5,本职技能!$A$1:$HX$1,0))) -> ★ | F38: 射击： | H38: 手枪 | J38: 20 | N38: 50 | R38: =SUM(J38:P38) -> 70 | T38: =INT(R38/2) -> 35 | V38: =INT(R38/5) -> 14 | X38: ☐ | Z38: =IF(ISTEXT(IFERROR(VLOOKUP(人物卡!AB38,人物卡!BJ18:BR22,1,FALSE),IFERROR(VLOOKUP(人物卡!AB38,人物卡!BA18:BC22,1,FALSE),0))),"★",INDEX(本职技能!$A$2:$HX$76,MATCH(人物卡!AB38,本职技能!$A$2:$A$75,0),MATCH(人物卡!$M$5,本职技能!$A$1:$HX$1,0))) -> ★ | AB38: 游泳 | AF38: 20 | AN38: =SUM(AF38:AL38) -> 20 | AP38: =INT(AN38/2) -> 10 | AR38: =INT(AN38/5) -> 4 | AU38: 推 荐 关 系 人 | AV38: =IF(M5=0," ",""&LOOKUP(M5,职业列表!A2:A232,职业列表!K2:K232))
B39: ☐ | D39: =IF(ISTEXT(IFERROR(VLOOKUP(人物卡!F39,人物卡!BJ18:BR22,1,FALSE),IFERROR(VLOOKUP(人物卡!F39,人物卡!BA18:BC22,1,FALSE),0))),"★",INDEX(本职技能!$A$2:$HX$76,MATCH(人物卡!F39,本职技能!$A$2:$A$75,0),MATCH(人物卡!$M$5,本职技能!$A$1:$HX$1,0))) -> 来复 | F39: 射击① | J39: =附表!E11 -> 0 | R39: =P39+N39+L39+J39 -> 0 | T39: =INT(R39/2) -> 0 | V39: =INT(R39/5) -> 0 | X39: ☐ | Z39: =IF(ISTEXT(IFERROR(VLOOKUP(人物卡!AB39,人物卡!BJ18:BR22,1,FALSE),IFERROR(VLOOKUP(人物卡!AB39,人物卡!BA18:BC22,1,FALSE),0))),"★",INDEX(本职技能!$A$2:$HX$76,MATCH(人物卡!AB39,本职技能!$A$2:$A$75,0),MATCH(人物卡!$M$5,本职技能!$A$1:$HX$1,0))) -> 0 | AB39: 投掷 | AF39: 20 | AN39: =SUM(AF39:AL39) -> 20 | AP39: =INT(AN39/2) -> 10 | AR39: =INT(AN39/5) -> 4
B40: ☐ | D40: =IF(ISTEXT(IFERROR(VLOOKUP(F40,人物卡!BJ18:BR22,1,FALSE),IFERROR(VLOOKUP(F40,人物卡!BA18:BC22,1,FALSE),0))),"★",INDEX(本职技能!$A$2:$HX$76,MATCH(F40,本职技能!$A$2:$A$75,0),MATCH(人物卡!$M$5,本职技能!$A$1:$HX$1,0))) -> 0 | F40: 射击② | J40: =附表!E12 -> 0 | R40: =P40+N40+L40+J40 -> 0 | T40: =INT(R40/2) -> 0 | V40: =INT(R40/5) -> 0 | X40: ☐ | Z40: =IF(ISTEXT(IFERROR(VLOOKUP(人物卡!AB40,人物卡!BJ18:BR22,1,FALSE),IFERROR(VLOOKUP(人物卡!AB40,人物卡!BA18:BC22,1,FALSE),0))),"★",INDEX(本职技能!$A$2:$HX$76,MATCH(人物卡!AB40,本职技能!$A$2:$A$75,0),MATCH(人物卡!$M$5,本职技能!$A$1:$HX$1,0))) -> ★ | AB40: 追踪 | AF40: 10 | AJ40: 40 | AN40: =SUM(AF40:AL40) -> 50 | AP40: =INT(AN40/2) -> 25 | AR40: =INT(AN40/5) -> 10
B41: ☐ | D41: =IF(ISTEXT(IFERROR(VLOOKUP(F41,人物卡!BJ18:BR22,1,FALSE),IFERROR(VLOOKUP(F41,人物卡!BA18:BC22,1,FALSE),0))),"★",INDEX(本职技能!$A$2:$HX$76,MATCH(F41,本职技能!$A$2:$A$75,0),MATCH(人物卡!$M$5,本职技能!$A$1:$HX$1,0))) -> 0 | F41: 射击③ | J41: =附表!E13 -> 0 | R41: =P41+N41+L41+J41 -> 0 | T41: =INT(R41/2) -> 0 | V41: =INT(R41/5) -> 0 | X41: ☐ | Z41: =IF(ISTEXT(IFERROR(VLOOKUP(人物卡!AB41,人物卡!BJ18:BR22,1,FALSE),IFERROR(VLOOKUP(人物卡!AB41,人物卡!BA18:BC22,1,FALSE),0))),"★",INDEX(本职技能!$A$2:$HX$76,MATCH(人物卡!AB41,本职技能!$A$2:$A$75,0),MATCH(人物卡!$M$5,本职技能!$A$1:$HX$1,0))) -> 0 | AB41: 驯兽 | AF41: 5 | AN41: =SUM(AF41:AL41) -> 5 | AP41: =INT(AN41/2) -> 2 | AR41: =INT(AN41/5) -> 1
B42: ☐ | D42: =IF(ISTEXT(IFERROR(VLOOKUP(人物卡!F42,人物卡!BJ18:BR22,1,FALSE),IFERROR(VLOOKUP(人物卡!F42,人物卡!BA18:BC22,1,FALSE),0))),"★",INDEX(本职技能!$A$2:$HX$76,MATCH(人物卡!F42,本职技能!$A$2:$A$75,0),MATCH(人物卡!$M$5,本职技能!$A$1:$HX$1,0))) -> ★ | F42: 急救 | J42: 30 | R42: =SUM(J42:P42) -> 30 | T42: =INT(R42/2) -> 15 | V42: =INT(R42/5) -> 6 | X42: ☐ | Z42: =IF(ISTEXT(IFERROR(VLOOKUP(人物卡!AB42,人物卡!BJ18:BR22,1,FALSE),IFERROR(VLOOKUP(人物卡!AB42,人物卡!BA18:BC22,1,FALSE),0))),"★",INDEX(本职技能!$A$2:$HX$76,MATCH(人物卡!AB42,本职技能!$A$2:$A$75,0),MATCH(人物卡!$M$5,本职技能!$A$1:$HX$1,0))) -> 0 | AB42: 潜水 | AF42: 1 | AN42: =SUM(AF42:AL42) -> 1 | AP42: =INT(AN42/2) -> 0 | AR42: =INT(AN42/5) -> 0
B43: ☐ | D43: =IF(ISTEXT(IFERROR(VLOOKUP(人物卡!F43,人物卡!BJ18:BR22,1,FALSE),IFERROR(VLOOKUP(人物卡!F43,人物卡!BA18:BC22,1,FALSE),0))),"★",INDEX(本职技能!$A$2:$HX$76,MATCH(人物卡!F43,本职技能!$A$2:$A$75,0),MATCH(人物卡!$M$5,本职技能!$A$1:$HX$1,0))) -> 0 | F43: 历史 | J43: 5 | R43: =SUM(J43:P43) -> 5 | T43: =INT(R43/2) -> 2 | V43: =INT(R43/5) -> 1 | X43: ☐ | Z43: =IF(ISTEXT(IFERROR(VLOOKUP(人物卡!AB43,人物卡!BJ18:BR22,1,FALSE),IFERROR(VLOOKUP(人物卡!AB43,人物卡!BA18:BC22,1,FALSE),0))),"★",INDEX(本职技能!$A$2:$HX$76,MATCH(人物卡!AB43,本职技能!$A$2:$A$75,0),MATCH(人物卡!$M$5,本职技能!$A$1:$HX$1,0))) -> 0 | AB43: 爆破 | AF43: 1 | AN43: =SUM(AF43:AL43) -> 1 | AP43: =INT(AN43/2) -> 0 | AR43: =INT(AN43/5) -> 0 | AU43: 职业介绍
B44: ☐ | D44: =IF(ISTEXT(IFERROR(VLOOKUP(人物卡!F44,人物卡!BJ18:BR22,1,FALSE),IFERROR(VLOOKUP(人物卡!F44,人物卡!BA18:BC22,1,FALSE),0))),"★",INDEX(本职技能!$A$2:$HX$76,MATCH(人物卡!F44,本职技能!$A$2:$A$75,0),MATCH(人物卡!$M$5,本职技能!$A$1:$HX$1,0))) -> 0 | F44: 恐吓 | J44: 15 | R44: =SUM(J44:P44) -> 15 | T44: =INT(R44/2) -> 7 | V44: =INT(R44/5) -> 3 | X44: ☐ | Z44: =IF(ISTEXT(IFERROR(VLOOKUP(人物卡!AB44,人物卡!BJ18:BR22,1,FALSE),IFERROR(VLOOKUP(人物卡!AB44,人物卡!BA18:BC22,1,FALSE),0))),"★",INDEX(本职技能!$A$2:$HX$76,MATCH(人物卡!AB44,本职技能!$A$2:$A$75,0),MATCH(人物卡!$M$5,本职技能!$A$1:$HX$1,0))) -> 0 | AB44: 读唇 | AF44: 1 | AN44: =SUM(AF44:AL44) -> 1 | AP44: =INT(AN44/2) -> 0 | AR44: =INT(AN44/5) -> 0 | AU44: =IF(M5=0," ",""&LOOKUP(M5,职业列表!A2:A232,职业列表!M2:M232)) -> 《克苏鲁煤气灯》1980s职业，使用前请征得KP同意。
B45: ☐ | D45: =IF(ISTEXT(IFERROR(VLOOKUP(人物卡!F45,人物卡!BJ18:BR22,1,FALSE),IFERROR(VLOOKUP(人物卡!F45,人物卡!BA18:BC22,1,FALSE),0))),"★",INDEX(本职技能!$A$2:$HX$76,MATCH(人物卡!F45,本职技能!$A$2:$A$75,0),MATCH(人物卡!$M$5,本职技能!$A$1:$HX$1,0))) -> 0 | F45: 跳跃 | J45: 20 | R45: =SUM(J45:P45) -> 20 | T45: =INT(R45/2) -> 10 | V45: =INT(R45/5) -> 4 | X45: ☐ | Z45: =IF(ISTEXT(IFERROR(VLOOKUP(人物卡!AB45,人物卡!BJ18:BR22,1,FALSE),IFERROR(VLOOKUP(人物卡!AB45,人物卡!BA18:BC22,1,FALSE),0))),"★",INDEX(本职技能!$A$2:$HX$76,MATCH(人物卡!AB45,本职技能!$A$2:$A$75,0),MATCH(人物卡!$M$5,本职技能!$A$1:$HX$1,0))) -> 0 | AB45: 催眠 | AF45: 1 | AN45: =SUM(AF45:AL45) -> 1 | AP45: =INT(AN45/2) -> 0 | AR45: =INT(AN45/5) -> 0
B46: ☐ | D46: =IF(ISTEXT(IFERROR(VLOOKUP(人物卡!F46,人物卡!BJ18:BR22,1,FALSE),IFERROR(VLOOKUP(人物卡!F46,人物卡!BA18:BC22,1,FALSE),0))),"★",INDEX(本职技能!$A$2:$HX$76,MATCH(人物卡!F46,本职技能!$A$2:$A$75,0),MATCH(人物卡!$M$5,本职技能!$A$1:$HX$1,0))) -> ★ | F46: 外语① | J46: 1 | R46: =SUM(J46:P46) -> 1 | T46: =INT(R46/2) -> 0 | V46: =INT(R46/5) -> 0 | X46: ☐ | Z46: =IF(ISTEXT(IFERROR(VLOOKUP(人物卡!AB46,人物卡!BJ18:BR22,1,FALSE),IFERROR(VLOOKUP(人物卡!AB46,人物卡!BA18:BC22,1,FALSE),0))),"★",INDEX(本职技能!$A$2:$HX$76,MATCH(人物卡!AB46,本职技能!$A$2:$A$75,0),MATCH(人物卡!$M$5,本职技能!$A$1:$HX$1,0))) -> 0 | AB46: 炮术 | AF46: 1 | AN46: =SUM(AF46:AL46) -> 1 | AP46: =INT(AN46/2) -> 0 | AR46: =INT(AN46/5) -> 0
B47: ☐ | D47: =IF(ISTEXT(IFERROR(VLOOKUP(人物卡!F47,人物卡!BJ18:BR22,1,FALSE),IFERROR(VLOOKUP(人物卡!F47,人物卡!BA18:BC22,1,FALSE),0))),"★",INDEX(本职技能!$A$2:$HX$76,MATCH(人物卡!F47,本职技能!$A$2:$A$75,0),MATCH(人物卡!$M$5,本职技能!$A$1:$HX$1,0))) -> 0 | F47: 外语② | J47: 1 | R47: =SUM(J47:P47) -> 1 | T47: =INT(R47/2) -> 0 | V47: =INT(R47/5) -> 0 | X47: ☐ | Z47: =IF(ISTEXT(IFERROR(VLOOKUP(人物卡!AB47,人物卡!BJ18:BR22,1,FALSE),IFERROR(VLOOKUP(人物卡!AB47,人物卡!BA18:BC22,1,FALSE),0))),"★",INDEX(本职技能!$A$2:$HX$76,MATCH(人物卡!AB47,本职技能!$A$2:$A$75,0),MATCH(人物卡!$M$5,本职技能!$A$1:$HX$1,0))) -> 0 | AB47: 学识： | AF47: 1 | AN47: =SUM(AF47:AL47) -> 1 | AP47: =INT(AN47/2) -> 0 | AR47: =INT(AN47/5) -> 0
B48: ☐ | D48: =IF(ISTEXT(IFERROR(VLOOKUP(F48,人物卡!BJ18:BR22,1,FALSE),IFERROR(VLOOKUP(F48,人物卡!BA18:BC22,1,FALSE),0))),"★",INDEX(本职技能!$A$2:$HX$76,MATCH(F48,本职技能!$A$2:$A$75,0),MATCH(人物卡!$M$5,本职技能!$A$1:$HX$1,0))) -> 0 | F48: 外语③ | J48: 1 | R48: =SUM(J48:P48) -> 1 | T48: =INT(R48/2) -> 0 | V48: =INT(R48/5) -> 0 | X48: ☐ | Z48: =IF(ISTEXT(IFERROR(VLOOKUP(AB48,人物卡!BJ18:BR22,1,FALSE),IFERROR(VLOOKUP(AB48,人物卡!BA18:BC22,1,FALSE),0))),"★",INDEX(本职技能!$A$2:$HX$76,MATCH(AB48,本职技能!$A$2:$A$75,0),MATCH(人物卡!$M$5,本职技能!$A$1:$HX$1,0))) -> 0 | AB48: 自定义技能 | AN48: =SUM(AF48:AL48) -> 0 | AP48: =INT(AN48/2) -> 0 | AR48: =INT(AN48/5) -> 0
B49: ☐ | D49: =IF(ISTEXT(IFERROR(VLOOKUP(人物卡!F49,人物卡!BJ18:BR22,1,FALSE),IFERROR(VLOOKUP(人物卡!F49,人物卡!BA18:BC22,1,FALSE),0))),"★",INDEX(本职技能!$A$2:$HX$76,MATCH(人物卡!F49,本职技能!$A$2:$A$75,0),MATCH(人物卡!$M$5,本职技能!$A$1:$HX$1,0))) -> 0 | F49: 母语 | J49: =AG5 -> 65 | R49: =SUM(J49:P49) -> 65 | T49: =INT(R49/2) -> 32 | V49: =INT(R49/5) -> 13 | X49: ☐ | Z49: =IF(ISTEXT(IFERROR(VLOOKUP(AB49,人物卡!BJ18:BR22,1,FALSE),IFERROR(VLOOKUP(AB49,人物卡!BA18:BC22,1,FALSE),0))),"★",INDEX(本职技能!$A$2:$HX$76,MATCH(AB49,本职技能!$A$2:$A$75,0),MATCH(人物卡!$M$5,本职技能!$A$1:$HX$1,0))) -> 0 | AN49: =SUM(AF49:AL49) -> 0 | AP49: =INT(AN49/2) -> 0 | AR49: =INT(AN49/5) -> 0
B50: =IF(M5=0,"","职业信用范围："&LOOKUP(M5,职业列表!A2:A232,职业列表!D2:D232)) -> 职业信用范围：45-70 | J50: =IF(M5=0,"","本职属性："&附表!J52&" ")&IF(M5=0,"",IF(AND(附表!J53-SUM(N16:O49,AJ16:AK49)=0,AA7+AA7-SUM(P16:Q49,AL16:AM49)=0),"",("剩余职业点="&附表!J53-SUM(N16:O49,AJ16:AK49))&" 剩余兴趣点="&AA7+AA7-SUM(P16:Q49,AL16:AM49)&IF(F113=附表!B26,""," 剩余经历包点="&IF(ISNUMBER(附表!D34),附表!D34-SUM(L16:M49,AH16:AI49),附表!D34)))) -> 本职属性：[教育×2＋外貌或敏捷或力量×2]
B51: 武器表 | AM51: 格斗
B52: 武器名称 | G52: 类型 | M52: 使用技能 | Q52: 成功率 | W52: 伤害 | AA52: 基础射程 | AC52: 贯穿 | AE52: 次数 | AG52: 装弹量 | AJ52: 故障值 | AM52: 伤害加值 Damage Bonus | AP52: =附表!P9 -> +1D4
B55: 好用的刀 | G55: 小型刀具(弹簧折叠刀等) | M55: =IF($G55=0,IF(M54="←请选择类型","","←请选择类型"),VLOOKUP($G55,'武器列表 战斗'!$B$2:$I$105,2,FALSE)) -> 斗殴 | Q55: =附表!AV16 -> 65 | S55: =IF(Q55="","",INT(Q55/2)) -> 32 | U55: =IF(Q55="","",INT(Q55/5)) -> 13 | W55: =IF($G55=0,"",VLOOKUP($G55,'武器列表 战斗'!$B$2:$I$105,3,FALSE)) -> 1D4+DB | AA55: =IF($G55=0,"",VLOOKUP($G55,'武器列表 战斗'!$B$2:$I$105,4,FALSE)) -> 接触 | AC55: =IF($G55=0,"",VLOOKUP($G55,'武器列表 战斗'!$B$2:$I$105,5,FALSE)) -> √ | AE55: =IF($G55=0,"",VLOOKUP($G55,'武器列表 战斗'!$B$2:$I$105,6,FALSE)) -> 1 | AG55: =IF($G55=0,"",VLOOKUP($G55,'武器列表 战斗'!$B$2:$I$105,7,FALSE)) -> —— | AJ55: =IF($G55=0,"",VLOOKUP($G55,'武器列表 战斗'!$B$2:$I$105,8,FALSE)) -> —— | AM55: 体格 Build | AP55: =附表!P7 -> 1
B56: 好用的枪 | G56: .357 马格南左轮 | M56: =IF($G56=0,IF(OR(M54="←请选择类型",M55="←请选择类型"),"","←请选择类型"),VLOOKUP($G56,'武器列表 战斗'!$B$2:$I$105,2,FALSE)) -> 手枪 | Q56: =附表!AV17 -> 70 | S56: =IF(Q56="","",INT(Q56/2)) -> 35 | U56: =IF(Q56="","",INT(Q56/5)) -> 14 | W56: =IF($G56=0,"",VLOOKUP($G56,'武器列表 战斗'!$B$2:$I$105,3,FALSE)) -> 1D8+1D4 | AA56: =IF($G56=0,"",VLOOKUP($G56,'武器列表 战斗'!$B$2:$I$105,4,FALSE)) -> 15 | AC56: =IF($G56=0,"",VLOOKUP($G56,'武器列表 战斗'!$B$2:$I$105,5,FALSE)) -> √ | AE56: =IF($G56=0,"",VLOOKUP($G56,'武器列表 战斗'!$B$2:$I$105,6,FALSE)) -> 1(3) | AG56: =IF($G56=0,"",VLOOKUP($G56,'武器列表 战斗'!$B$2:$I$105,7,FALSE)) -> 6 | AJ56: =IF($G56=0,"",VLOOKUP($G56,'武器列表 战斗'!$B$2:$I$105,8,FALSE)) -> 100
AM57: 闪避 Dodge | AP57: =R29 -> 44 | AR57: =T29 -> 22
AR58: =V29 -> 8
B60: 资产 | W60: 背景故事
B61: 信用评级 | F61: 生活水平 | I61: 消费水平 | L61: 其他资产 | O61: 当前现金($) | S61: 单位 | W61: 形象描述 | AA61: 肩背宽阔的青年，体格健壮，深棕色头发，灰绿色眼睛，以相貌而言，乍一看，人们会认为他应当是流连于酒场的生意人，碰巧有些运动爱好。然而，他的手积满了厚茧 | AR61: 关键 连接
B62: =附表!Z223 -> 50%/25%/10% | F62: =附表!Z225 -> 小康 | I62: =附表!AE240 -> 50 | L62: =附表!AG240 -> 2.5万 | O62: =附表!AF240 -> 250 | S62: 美元 | AU62: =IF(附表!AE22="仅显示1890_2012","时代介绍仅显示1890_2012这段时间","时代介绍") -> 时代介绍
B63: =IF(R26<=0,"连贫穷都够不上的人才能够叫做身无分文。住所：大概只有睡大街。旅行：步行，扒车或逃票上火车轮船。",IF(R26<=9,"刚好买得起最廉价的屋顶，每天能够吃到一餐廉价食物。住所：最最最廉价的出租屋或睡袋旅馆。旅行：最便宜的公众运输方式。反正只要赶便宜就对了，与之相伴的是不可靠。",IF(R26<=49,"舒适的生活水平，一日三餐，偶尔下馆子。住所：普通的家或公寓，无论是租赁还是自购。外出住普通的旅馆。旅行：会使用普通的旅行方式，不会用最高级。在现代来看，大概会有一辆自己的小车。",IF(R26<=89,"小康级别已经可以享受奢侈品的舒适了。住所：真材实料的住地，也许会有一些仆人（管家，主妇，清洁工，园丁，等等）。乡下估计还有小别墅。会住昂贵的宾馆。旅行：头等舱。会买高档车或同等的交通工具。",IF(R26<=98,"富裕级别就是享受超级奢侈品的时候了。住所：豪华住所和有着大量仆人的庭院。乡下和别处有着别墅是定番。住总统套房。旅行：头等舱。现代社会估摸还会有很多豪车。",IF(R26=99,"与富裕差不多，但钱已经只是一个代号了。你将是世界上最富有的人。","请正确分配您的技能点！")))))) -> 小康级别已经可以享受奢侈品的舒适了。住所：真材实料的住地，也许会有一些仆人（管家，主妇，清洁工，园丁，等等）。乡下估计还有小别墅。会住昂贵的宾馆。旅行：头等舱。会买高档车或同等的交通工具。 | W63: 思想与信念 | AA63: 未知并不可怖——无知才是。 | AR63: ☐ | AU63: 年代 | AZ63: 国际重大历史进程 | BF63: 中国重大历史进程 | BL63: 年代
AU64: =IF(E8="公元","A.C."&G8,"B.C."&G8) -> B.C.1980 | AZ64: =附表!AF22 -> 莫斯科奥运会 | BF64: =附表!AI22 -> —— | BL64: =附表!AL22 -> 二十世纪 八十年代
W65: 重要之人 | AA65: 父母。一对体面的中产家庭夫妇，对儿子常年探险这件事既骄傲又头疼。尽管他们支持他的旅行，仍然一直希望他“能找份真正的工作”。 | AR65: ☐ | AZ65: =附表!AG22 -> 0 | BF65: =附表!AJ22 -> 0 | BL65: =附表!AM22 -> 庚申猴年
AZ66: =附表!AH22 -> 0 | BF66: =附表!AK22 -> 0 | BL66: =附表!AN22 -> 中华人民共和国31周年
W67: 意义非凡之地 | AA67: 韦科尔山地，少年时代第一次独自探险的地方 | AR67: ☐ | AU67: 新闻
B68: 其他资产表 | AU68: =附表!AO22 -> 美国每盎司黄金达到802 美元 美国通胀率33 年来最高 银行业放松管制 圣海伦火山喷发死亡超过50 人 伊朗人质解救失败 波兰团结公会成立 亚马逊淘金热 杜比C型降噪器 美国公债9080 亿美元 美国人口2.265 亿
B69: 交通工具 | F69: 住所 | J69: 奢侈品 | N69: 股票/证券等 | R69: 其他 | W69: 宝贵之物 | AA69: 一枚老式机械腕表，父母的礼物，从不跑慢 | AR69: ☐
B70: 租车 | F70: 里昂的住处 | J70: 手表 | N70: 存款
W71: 特质 | AA71: 好奇心胜过了自保意识 | AR71: ☐
W73: 伤口和疤痕 | AA73: 左侧肋骨附近有一道不规则旧疤，一次攀岩事故留下的 | AR73: ☐
B75: 2000 | F75: 8000 | J75: 5000 | N75: 10000 | R75: 0 | W75: 恐惧症和躁狂症 | AA75: 极其不喜欢被困在无法自主离开的地方，却没有发展成幽闭恐惧。他可以进入极狭窄的洞穴，因为他确信自己知道出口在哪里。 | AR75: ☐
B76: ="资产总和："&SUM(B75:U75) -> 资产总和：25000 | N76: ="剩余资产值："&IF(附表!AG230="没有",0-SUM(B75:U75),附表!AG230-SUM(B75:U75)) -> 剩余资产值：0
B77: 随身物品（使用右侧栏位需要背包） | W77: 十四岁那年，艾迪安与朋友在韦科尔山徒步时失足滚下山崖。幸运的是，他最后只摔断了一根肋骨，外加满身擦伤。 获救后，父亲问他当时是不是吓坏了。艾迪安想了一会儿，发现自己并没怎么害怕。坠落时，他甚至还有心思判断该用哪里着地，停下来后的第一件事也是检查自己还能不能动。第二件事——噢，他那时候在想：这里的云真好看。 这让十四岁的艾迪安第一次意识到，自己似乎没什么恐惧心。后来，他开始主动寻找那些别人避之不及的地方：废弃矿洞、地下河、无人山区，以及地图上只有一片空白的角落。 成年后，艾迪安成为了一名探险家。家里对此颇有微词，他则认为这比坐办公室适合自己。 如今，他的探索版图从欧洲一路扩展到了另一块大陆。美国的阿巴拉契亚山脉是个不错的开始。
B78: 状态 | D78: 部位 | F78: 物品名称 | N78: 背包格↓
B79: 显露 | D79: 躯———— | F79: 大衣
D80: 颈部 | F80: 银质项链
B81: 隐藏 | D81: 衣服内 | F81: 护照、钱包
D82: 衣服内 | F82: 公路地图
D83: 裤兜 | F83: 打火机
D84: 衣兜 | F84: 车钥匙
D85: 衣兜 | F85: 烟盒
B86: 隐藏 | D86: 衣服内 | F86: 小型手电筒
B87: 隐藏 | D87: 衣服内 | F87: 瑞士军刀
D88: 裤兜 | F88: 零钱
D89: 衣服内 | F89: 防水笔记本与水笔
D90: 衣服内 | F90: 手枪
D91: 衣服内 | F91: 指南针
B95: 调查员经历 | W95: 神话相关
B96: 经历模组 | J96: 人物变化描述 | W96: 第三类接触（古籍、咒文、神话知识等）
B97: 例：【毒汤】 | J97: SAN-6,HP-2,侦查+2 | W97: 遇到了 | AA97: 获得的结果 | AK97: 备注 | AR97: 累计
B98: 例：如果此处空间不够 | J98: 可以前去【成长表】进行填写 | W98: 例：米-戈 | AA98: 克苏鲁+3，克苏鲁(疯)+5，SAN-6，SAN(信)-8 | AK98: 第一次神话疯狂，相信者规则激活 | AR98: 6
W99: 例：修格斯 | AA99: 克苏鲁+7，克苏鲁(疯)+1，SAN-5 | AK99: 第二次神话疯狂 | AR99: 5
AU104: 杂项
AU105: =附表!AP22 -> 总统： 吉米·卡特（民主党）
W112: 法术一览
B113: 有故事的调查员经历包： | F113: 无 | J113: ="SAN值减少"&附表!C34&" 备注："&附表!E34 -> SAN值减少 备注： | W113: 编号 | Y113: 法术名称 | AC113: 使用代价 | AH113: 作用
W114: 例：1 | Y114: 灰色束缚 | AC114: 8mp 1d6san 1h | AH114: 可以控制死去的人，直到腐烂为止
B118: 快速参考规则
B119: 技能和属性检定 成功等级 | F119: 大失败 | L119: 失败 | N119: 成功 | P119: 困难 | R119: 极难 | T119: 大成功
F120: 技能成功率≥50为100 否则为96-100 | L120: >技能 | N120: ≤技能 | P120: 1/2值 | R120: 1/5值 | T120: 1
B122: 孤注一掷：使用孤注一掷来重投上一次检定结果，需要合理的解释重掷原因，战斗和理智检定不能执行孤注一掷。
...

Sheet 简化卡 骰娘导入
B2: =人物卡!E3&"，"&人物卡!M6&"，"&人物卡!E6&"岁"&"，"&人物卡!E5&"，"&人物卡!M4&"，"&"现居："&人物卡!E7&"，"&人物卡!M7&"人" -> 艾迪安·多雷，男，31岁，探险家，1920s，现居：法国 里昂，法国 格勒诺布尔人 | N2: 技能 | Z2: 当前时间
B3: STR | C3: =附表!G14 -> 90 | D3: =INT(C3/2) -> 45 | E3: DEX | F3: =附表!J14 -> 40 | G3: =INT(F3/2) -> 20 | H3: POW | I3: =附表!M14 -> 75 | J3: =INT(I3/2) -> 37 | K3: INT | L3: =附表!L14 -> 80 | M3: =INT(L3/2) -> 40 | N3: =IF(Q3=0,"",人物卡!F16) | Q3: =IF(人物卡!R16-人物卡!J16=0,0,人物卡!R16) -> 0 | R3: =INT(Q3/2) -> 0 | S3: =INT(Q3/5) -> 0 | T3: =IF(W3=0,"",人物卡!AB16) | W3: =IF(人物卡!AN16-人物卡!AF16=0,0,人物卡!AN16) -> 0 | X3: =INT(W3/2) -> 0 | Y3: =INT(W3/5) -> 0 | Z3: =人物卡!E8 -> 0 | AA3: =人物卡!G8 -> 1980 | AC3: =人物卡!J8 -> 1月 | AD3: =人物卡!N8 -> 0：00
D4: =INT(C3/5) -> 18 | G4: =INT(F3/5) -> 8 | J4: =INT(I3/5) -> 15 | M4: =INT(L3/5) -> 16 | N4: =IF(Q4=0,"",人物卡!F17) | Q4: =IF(人物卡!R17-人物卡!J17=0,0,人物卡!R17) -> 0 | R4: =INT(Q4/2) -> 0 | S4: =INT(Q4/5) -> 0 | T4: =IF(W4=0,"",人物卡!AB17) | W4: =IF(人物卡!AN17-人物卡!AF17=0,0,人物卡!AN17) -> 0 | X4: =INT(W4/2) -> 0 | Y4: =INT(W4/5) -> 0 | AC4: =人物卡!L8 -> 1日
B5: CON | C5: =附表!H14 -> 50 | D5: =INT(C5/2) -> 25 | E5: APP | F5: =附表!K14 -> 65 | G5: =INT(F5/2) -> 32 | H5: EDU | I5: =附表!N14 -> 65 | J5: =INT(I5/2) -> 32 | K5: SIZ | L5: =附表!I14 -> 70 | M5: =INT(L5/2) -> 35 | N5: =IF(Q5=0,"",人物卡!F18) | Q5: =IF(人物卡!R18-人物卡!J18=0,0,人物卡!R18) -> 0 | R5: =INT(Q5/2) -> 0 | S5: =INT(Q5/5) -> 0 | T5: =IF(W5=0,"",人物卡!AB18) -> 聆听 | W5: =IF(人物卡!AN18-人物卡!AF18=0,0,人物卡!AN18) -> 49 | X5: =INT(W5/2) -> 24 | Y5: =INT(W5/5) -> 9 | Z5: 调查员伙伴
D6: =INT(C5/5) -> 10 | G6: =INT(F5/5) -> 13 | J6: =INT(I5/5) -> 13 | M6: =INT(L5/5) -> 14 | N6: =IF(Q6=0,"",人物卡!F19) | Q6: =IF(人物卡!R19-人物卡!J19=0,0,人物卡!R19) -> 0 | R6: =INT(Q6/2) -> 0 | S6: =INT(Q6/5) -> 0 | T6: =IF(W6=0,"",人物卡!AB19) | W6: =IF(人物卡!AN19-人物卡!AF19=0,0,人物卡!AN19) -> 0 | X6: =INT(W6/2) -> 0 | Y6: =INT(W6/5) -> 0 | Z6: 姓名 | AB6: 注释
B7: HP | C7: =人物卡!E10 -> 12 | D7: =人物卡!G10 -> 12 | E7: SAN | F7: =人物卡!N10 -> 75 | G7: =人物卡!P10 -> 99 | H7: MP | I7: =人物卡!W10 -> 15 | J7: =INT(人物卡!AG3/5) -> 15 | K7: Armor | L7: =人物卡!AN10 -> 0 | N7: =IF(Q7=0,0,"技艺：") -> 0 | O7: =IF(N7=0,"",人物卡!H20) | Q7: =IF(人物卡!R20-人物卡!J20=0,0,人物卡!R20) -> 0 | R7: =INT(Q7/2) -> 0 | S7: =INT(Q7/5) -> 0 | T7: =IF(W7=0,"",人物卡!AB20) | W7: =IF(人物卡!AN20-人物卡!AF20=0,0,人物卡!AN20) -> 0 | X7: =INT(W7/2) -> 0 | Y7: =INT(W7/5) -> 0 | Z7: =人物卡!W130 -> 例：丛雨 | AB7: =人物卡!AD130 -> 一起出生入死的医生小姐
N8: =IF(Q8=0,0,"技艺：") -> 0 | O8: =IF(N8=0,"",人物卡!H21) | Q8: =IF(人物卡!R21-人物卡!J21=0,0,人物卡!R21) -> 0 | R8: =INT(Q8/2) -> 0 | S8: =INT(Q8/5) -> 0 | T8: =IF(W8=0,"",人物卡!AB21) | W8: =IF(人物卡!AN21-人物卡!AF21=0,0,人物卡!AN21) -> 0 | X8: =INT(W8/2) -> 0 | Y8: =INT(W8/5) -> 0 | Z8: =人物卡!W131 -> 0 | AB8: =人物卡!AD131 -> 0
B9: DB | C9: =人物卡!AP52 -> +1D4 | E9: Build | F9: =人物卡!AP55 -> 1 | H9: LUCK | I9: =附表!O14 -> 70 | K9: MOV | L9: =人物卡!AF10 -> 8 | N9: =IF(Q9=0,0,"技艺：") -> 0 | O9: =IF(N9=0,"",人物卡!H22) | Q9: =IF(人物卡!R22-人物卡!J22=0,0,人物卡!R22) -> 0 | R9: =INT(Q9/2) -> 0 | S9: =INT(Q9/5) -> 0 | T9: =IF(W9=0,"",人物卡!AB22) -> 博物学 | W9: =IF(人物卡!AN22-人物卡!AF22=0,0,人物卡!AN22) -> 50 | X9: =INT(W9/2) -> 25 | Y9: =INT(W9/5) -> 10 | Z9: =人物卡!W132 -> 0 | AB9: =人物卡!AD132 -> 0
N10: =IF(Q10=0,"",人物卡!F23) -> 取悦 | Q10: =IF(人物卡!R23-人物卡!J23=0,0,人物卡!R23) -> 49 | R10: =INT(Q10/2) -> 24 | S10: =INT(Q10/5) -> 9 | T10: =IF(W10=0,"",人物卡!AB23) | W10: =IF(人物卡!AN23-人物卡!AF23=0,0,人物卡!AN23) -> 0 | X10: =INT(W10/2) -> 0 | Y10: =INT(W10/5) -> 0 | Z10: =人物卡!W133 -> 0 | AB10: =人物卡!AD133 -> 0
B11: 武器表 | N11: =IF(Q11=0,"",人物卡!F24) | Q11: =IF(人物卡!R24-人物卡!J24=0,0,人物卡!R24) -> 0 | R11: =INT(Q11/2) -> 0 | S11: =INT(Q11/5) -> 0 | T11: =IF(W11=0,"",人物卡!AB24) | W11: =IF(人物卡!AN24-人物卡!AF24=0,0,人物卡!AN24) -> 0 | X11: =INT(W11/2) -> 0 | Y11: =INT(W11/5) -> 0 | Z11: =人物卡!W134 -> 0 | AB11: =人物卡!AD134 -> 0
B12: =人物卡!B53 -> 0 | C12: =人物卡!G53 -> 0 | D12: =人物卡!M53 -> 0 | E12: =人物卡!Q53 -> 0 | F12: =人物卡!S53 -> 0 | G12: =人物卡!U53 -> 0 | H12: =人物卡!W53 -> 0 | I12: =人物卡!AA53 -> 0 | J12: =人物卡!AC53 -> 0 | K12: =人物卡!AE53 -> 0 | L12: =人物卡!AG53 -> 0 | M12: =人物卡!AJ53 -> 0 | N12: =IF(Q12=0,"",人物卡!F25) | Q12: =IF(人物卡!R25-人物卡!J25=0,0,人物卡!R25) -> 0 | R12: =INT(Q12/2) -> 0 | S12: =INT(Q12/5) -> 0 | T12: =IF(W12=0,"",人物卡!AB25) | W12: =IF(人物卡!AN25-人物卡!AF25=0,0,人物卡!AN25) -> 0 | X12: =INT(W12/2) -> 0 | Y12: =INT(W12/5) -> 0 | Z12: =人物卡!W135 -> 0 | AB12: =人物卡!AD135 -> 0
B13: =人物卡!B54 -> 0 | C13: =人物卡!G54 -> 0 | D13: =IF(人物卡!M54="请选择类型","",人物卡!M54) -> 0 | E13: =人物卡!Q54 -> 0 | F13: =人物卡!S54 -> 0 | G13: =人物卡!U54 -> 0 | H13: =人物卡!W54 -> 0 | I13: =人物卡!AA54 -> 0 | J13: =人物卡!AC54 -> 0 | K13: =人物卡!AE54 -> 0 | L13: =人物卡!AG54 -> 0 | M13: =人物卡!AJ54 -> 0 | N13: =人物卡!F26 -> 信用评级 | Q13: =人物卡!R26 -> 50 | R13: =IF(Q13=0,32767,INT(Q13/2)) -> 25 | S13: =IF(Q13=0,32767,INT(Q13/5)) -> 10 | T13: =IF(W13=0,"",人物卡!AB26) -> 说服 | W13: =IF(人物卡!AN26-人物卡!AF26=0,0,人物卡!AN26) -> 49 | X13: =INT(W13/2) -> 24 | Y13: =INT(W13/5) -> 9 | Z13: =人物卡!W136 -> 0 | AB13: =人物卡!AD136 -> 0
B14: =人物卡!B55 -> 好用的刀 | C14: =人物卡!G55 -> 小型刀具(弹簧折叠刀等) | D14: =IF(人物卡!M55="请选择类型","",人物卡!M55) -> 斗殴 | E14: =人物卡!Q55 -> 65 | F14: =人物卡!S55 -> 32 | G14: =人物卡!U55 -> 13 | H14: =人物卡!W55 -> 1D4+DB | I14: =人物卡!AA55 -> 接触 | J14: =人物卡!AC55 -> √ | K14: =人物卡!AE55 -> 1 | L14: =人物卡!AG55 -> —— | M14: =人物卡!AJ55 -> —— | N14: =IF(Q14=0,"",人物卡!F27) | Q14: =IF(人物卡!R27-人物卡!J27=0,0,人物卡!R27) -> 0 | R14: =INT(Q14/2) -> 0 | S14: =INT(Q14/5) -> 0 | T14: =IF(W14=0,0,人物卡!AB27) -> 0 | U14: =IF(T14=0,"",人物卡!AD27) | W14: =IF(人物卡!AN27-人物卡!AF27=0,0,人物卡!AN27) -> 0 | X14: =INT(W14/2) -> 0 | Y14: =INT(W14/5) -> 0 | Z14: =人物卡!W137 -> 0 | AB14: =人物卡!AD137 -> 0
B15: =人物卡!B56 -> 好用的枪 | C15: =人物卡!G56 -> .357 马格南左轮 | D15: =IF(人物卡!M56="请选择类型","",人物卡!M56) -> 手枪 | E15: =人物卡!Q56 -> 70 | F15: =人物卡!S56 -> 35 | G15: =人物卡!U56 -> 14 | H15: =人物卡!W56 -> 1D8+1D4 | I15: =人物卡!AA56 -> 15 | J15: =人物卡!AC56 -> √ | K15: =人物卡!AE56 -> 1(3) | L15: =人物卡!AG56 -> 6 | M15: =人物卡!AJ56 -> 100 | N15: =IF(Q15=0,"",人物卡!F28) | Q15: =IF(人物卡!R28-人物卡!J28=0,0,人物卡!R28) -> 0 | R15: =INT(Q15/2) -> 0 | S15: =INT(Q15/5) -> 0 | T15: =IF(W15=0,"",人物卡!AB28) | W15: =IF(人物卡!AN28-人物卡!AF28=0,0,人物卡!AN28) -> 0 | X15: =INT(W15/2) -> 0 | Y15: =INT(W15/5) -> 0 | Z15: =人物卡!W138 -> 0 | AB15: =人物卡!AD138 -> 0
B16: =人物卡!B57 -> 0 | C16: =人物卡!G57 -> 0 | D16: =IF(人物卡!M57="请选择类型","",人物卡!M57) -> 0 | E16: =人物卡!Q57 -> 0 | F16: =人物卡!S57 -> 0 | G16: =人物卡!U57 -> 0 | H16: =人物卡!W57 -> 0 | I16: =人物卡!AA57 -> 0 | J16: =人物卡!AC57 -> 0 | K16: =人物卡!AE57 -> 0 | L16: =人物卡!AG57 -> 0 | M16: =人物卡!AJ57 -> 0 | N16: =人物卡!F29 -> 闪避 | Q16: =人物卡!R29 -> 44 | R16: =IF(Q16=0,32767,INT(Q16/2)) -> 22 | S16: =IF(Q16=0,32767,INT(Q16/5)) -> 8 | T16: =IF(W16=0,"",人物卡!AB29) -> 心理学 | W16: =IF(人物卡!AN29-人物卡!AF29=0,0,人物卡!AN29) -> 49 | X16: =INT(W16/2) -> 24 | Y16: =INT(W16/5) -> 9 | Z16: =人物卡!W139 -> 0 | AB16: =人物卡!AD139 -> 0
B17: 资产 | N17: =IF(Q17=0,"",人物卡!F30) | Q17: =IF(人物卡!R30-人物卡!J30=0,0,人物卡!R30) -> 0 | R17: =INT(Q17/2) -> 0 | S17: =INT(Q17/5) -> 0 | T17: =IF(W17=0,"",人物卡!AB30) | W17: =IF(人物卡!AN30-人物卡!AF30=0,0,人物卡!AN30) -> 0 | X17: =INT(W17/2) -> 0 | Y17: =INT(W17/5) -> 0 | Z17: =人物卡!W140 -> 0 | AB17: =人物卡!AD140 -> 0
B18: 信用评级 | E18: 生活水平 | G18: 消费水平 | I18: 其他资产 | K18: 当前现金($) | M18: 单位 | N18: =IF(Q18=0,"",人物卡!F31) | Q18: =IF(人物卡!R31-人物卡!J31=0,0,人物卡!R31) -> 0 | R18: =INT(Q18/2) -> 0 | S18: =INT(Q18/5) -> 0 | T18: =IF(W18=0,0,"科学：") -> 0 | U18: =IF(T18=0,"",人物卡!AD31) | W18: =IF(人物卡!AN31-人物卡!AF31=0,0,人物卡!AN31) -> 0 | X18: =INT(W18/2) -> 0 | Y18: =INT(W18/5) -> 0
B19: =人物卡!B62 -> 50%/25%/10% | E19: =人物卡!F62 -> 小康 | G19: =人物卡!I62 -> 50 | I19: =人物卡!L62 -> 2.5万 | K19: =人物卡!O62 -> 250 | M19: =人物卡!S62 -> 美元 | N19: =IF(Q19=0,"",人物卡!F32) | Q19: =IF(人物卡!R32-人物卡!J32=0,0,人物卡!R32) -> 0 | R19: =INT(Q19/2) -> 0 | S19: =INT(Q19/5) -> 0 | T19: =IF(W19=0,0,"科学：") -> 0 | U19: =IF(T19=0,"",人物卡!AD32) | W19: =IF(人物卡!AN32-人物卡!AF32=0,0,人物卡!AN32) -> 0 | X19: =INT(W19/2) -> 0 | Y19: =INT(W19/5) -> 0
B20: =人物卡!L63 -> 0 | N20: =IF(Q20=0,"",人物卡!F33) | Q20: =IF(人物卡!R33-人物卡!J33=0,0,人物卡!R33) -> 0 | R20: =INT(Q20/2) -> 0 | S20: =INT(Q20/5) -> 0 | T20: =IF(W20=0,0,"科学：") -> 0 | U20: =IF(T20=0,"",人物卡!AD33) | W20: =IF(人物卡!AN33-人物卡!AF33=0,0,人物卡!AN33) -> 0 | X20: =INT(W20/2) -> 0 | Y20: =INT(W20/5) -> 0
B21: 随身物品 | N21: =IF(Q21=0,0,"格斗：") -> 格斗： | O21: =IF(N21=0,"",人物卡!H34) -> 斗殴 | Q21: =IF(人物卡!R34-人物卡!J34=0,0,人物卡!R34) -> 65 | R21: =INT(Q21/2) -> 32 | S21: =INT(Q21/5) -> 13 | T21: =IF(W21=0,"",人物卡!AB34) | W21: =IF(人物卡!AN34-人物卡!AF34=0,0,人物卡!AN34) -> 0 | X21: =INT(W21/2) -> 0 | Y21: =INT(W21/5) -> 0 | Z21: 神话相关
B22: =人物卡!F79 -> 大衣 | E22: =人物卡!F80 -> 银质项链 | H22: =人物卡!F81 -> 护照、钱包 | K22: =人物卡!F82 -> 公路地图 | N22: =IF(Q22=0,0,"格斗：") -> 0 | O22: =IF(N22=0,"",人物卡!H35) | Q22: =IF(人物卡!R35-人物卡!J35=0,0,人物卡!R35) -> 0 | R22: =INT(Q22/2) -> 0 | S22: =INT(Q22/5) -> 0 | T22: =IF(W22=0,"",人物卡!AB35) -> 侦查 | W22: =IF(人物卡!AN35-人物卡!AF35=0,0,人物卡!AN35) -> 70 | X22: =INT(W22/2) -> 35 | Y22: =INT(W22/5) -> 14 | Z22: 遇到了 | AD22: 累计消耗
B23: =人物卡!F83 -> 打火机 | E23: =人物卡!F84 -> 车钥匙 | H23: =人物卡!F85 -> 烟盒 | K23: =人物卡!F90 -> 手枪 | N23: =IF(Q23=0,0,"格斗：") -> 0 | O23: =IF(N23=0,"",人物卡!H36) | Q23: =IF(人物卡!R36-人物卡!J36=0,0,人物卡!R36) -> 0 | R23: =INT(Q23/2) -> 0 | S23: =INT(Q23/5) -> 0 | T23: =IF(W23=0,"",人物卡!AB36) -> 潜行 | W23: =IF(人物卡!AN36-人物卡!AF36=0,0,人物卡!AN36) -> 60 | X23: =INT(W23/2) -> 30 | Y23: =INT(W23/5) -> 12 | Z23: =人物卡!W98 -> 例：米-戈 | AD23: =人物卡!AR98 -> 6
B24: =人物卡!F91 -> 指南针 | E24: =人物卡!F92 -> 0 | H24: =人物卡!N79 -> 0 | K24: =人物卡!N80 -> 0 | N24: =IF(Q24=0,0,"格斗：") -> 0 | O24: =IF(N24=0,"",人物卡!H37) | Q24: =IF(人物卡!R37-人物卡!J37=0,0,人物卡!R37) -> 0 | R24: =INT(Q24/2) -> 0 | S24: =INT(Q24/5) -> 0 | T24: =IF(W24=0,0,人物卡!AB37) -> 0 | U24: =IF(T24=0,"",人物卡!AD37) | W24: =IF(人物卡!AN37-人物卡!AF37=0,0,人物卡!AN37) -> 0 | X24: =INT(W24/2) -> 0 | Y24: =INT(W24/5) -> 0 | Z24: =人物卡!W99 -> 例：修格斯 | AD24: =人物卡!AR99 -> 5
B25: =人物卡!N81 -> 0 | E25: =人物卡!N82 -> 0 | H25: =人物卡!N83 -> 0 | K25: =人物卡!N84 -> 0 | N25: =IF(Q25=0,0,"射击：") -> 射击： | O25: =IF(N25=0,"",人物卡!H38) -> 手枪 | Q25: =IF(人物卡!R38-人物卡!J38=0,0,人物卡!R38) -> 70 | R25: =INT(Q25/2) -> 35 | S25: =INT(Q25/5) -> 14 | T25: =IF(W25=0,"",人物卡!AB38) | W25: =IF(人物卡!AN38-人物卡!AF38=0,0,人物卡!AN38) -> 0 | X25: =INT(W25/2) -> 0 | Y25: =INT(W25/5) -> 0 | Z25: =人物卡!W100 -> 0 | AD25: =人物卡!AR100 -> 0
B26: =人物卡!N85 -> 0 | E26: =人物卡!N90 -> 0 | H26: =人物卡!N91 -> 0 | K26: =人物卡!N92 -> 0 | N26: =IF(Q26=0,0,"射击：") -> 0 | O26: =IF(N26=0,"",人物卡!H39) | Q26: =IF(人物卡!R39-人物卡!J39=0,0,人物卡!R39) -> 0 | R26: =INT(Q26/2) -> 0 | S26: =INT(Q26/5) -> 0 | T26: =IF(W26=0,"",人物卡!AB39) | W26: =IF(人物卡!AN39-人物卡!AF39=0,0,人物卡!AN39) -> 0 | X26: =INT(W26/2) -> 0 | Y26: =INT(W26/5) -> 0 | Z26: =人物卡!W101 -> 0 | AD26: =人物卡!AR101 -> 0
B27: 背景故事 | N27: =IF(Q27=0,0,"射击：") -> 0 | O27: =IF(N27=0,"",人物卡!H40) | Q27: =IF(人物卡!R40-人物卡!J40=0,0,人物卡!R40) -> 0 | R27: =INT(Q27/2) -> 0 | S27: =INT(Q27/5) -> 0 | T27: =IF(W27=0,"",人物卡!AB40) -> 追踪 | W27: =IF(人物卡!AN40-人物卡!AF40=0,0,人物卡!AN40) -> 50 | X27: =INT(W27/2) -> 25 | Y27: =INT(W27/5) -> 10 | Z27: =人物卡!W102 -> 0 | AD27: =人物卡!AR102 -> 0
B28: 描述 | C28: =人物卡!AA61 -> 肩背宽阔的青年，体格健壮，深棕色头发，灰绿色眼睛，以相貌而言，乍一看，人们会认为他应当是流连于酒场的生意人，碰巧有些运动爱好。然而，他的手积满了厚茧 | G28: 关键 | H28: =人物卡!W77 -> 十四岁那年，艾迪安与朋友在韦科尔山徒步时失足滚下山崖。幸运的是，他最后只摔断了一根肋骨，外加满身擦伤。 获救后，父亲问他当时是不是吓坏了。艾迪安想了一会儿，发现自己并没怎么害怕。坠落时，他甚至还有心思判断该用哪里着地，停下来后的第一件事也是检查自己还能不能动。第二件事——噢，他那时候在想：这里的云真好看。 这让十四岁的艾迪安第一次意识到，自己似乎没什么恐惧心。后来，他开始主动寻找那些别人避之不及的地方：废弃矿洞、地下河、无人山区，以及地图上只有一片空白的角落。 成年后，艾迪安成为了一名探险家。家里对此颇有微词，他则认为这比坐办公室适合自己。 如今，他的探索版图从欧洲一路扩展到了另一块大陆。美国的阿巴拉契亚山脉是个不错的开始。 | N28: =IF(Q28=0,0,"射击：") -> 0 | O28: =IF(N28=0,"",人物卡!H41) | Q28: =IF(人物卡!R41-人物卡!J41=0,0,人物卡!R41) -> 0 | R28: =INT(Q28/2) -> 0 | S28: =INT(Q28/5) -> 0 | T28: =IF(W28=0,"",人物卡!AB41) | W28: =IF(人物卡!AN41-人物卡!AF41=0,0,人物卡!AN41) -> 0 | X28: =INT(W28/2) -> 0 | Y28: =INT(W28/5) -> 0 | Z28: =人物卡!W103 -> 0 | AD28: =人物卡!AR103 -> 0
B29: 信仰 | C29: =人物卡!AA63 -> 未知并不可怖——无知才是。 | G29: =人物卡!AR63 -> ☐ | N29: =IF(Q29=0,"",人物卡!F42) | Q29: =IF(人物卡!R42-人物卡!J42=0,0,人物卡!R42) -> 0 | R29: =INT(Q29/2) -> 0 | S29: =INT(Q29/5) -> 0 | T29: =IF(W29=0,"",人物卡!AB47) | W29: =IF(人物卡!AN42-人物卡!AF42=0,0,人物卡!AN42) -> 0 | X29: =INT(W29/2) -> 0 | Y29: =INT(W29/5) -> 0 | Z29: =人物卡!W104 -> 0 | AD29: =人物卡!AR104 -> 0
B30: 重要人 | C30: =人物卡!AA65 -> 父母。一对体面的中产家庭夫妇，对儿子常年探险这件事既骄傲又头疼。尽管他们支持他的旅行，仍然一直希望他“能找份真正的工作”。 | G30: =人物卡!AR65 -> ☐ | N30: =IF(Q30=0,"",人物卡!F43) | Q30: =IF(人物卡!R43-人物卡!J43=0,0,人物卡!R43) -> 0 | R30: =INT(Q30/2) -> 0 | S30: =INT(Q30/5) -> 0 | T30: =IF(W30=0,"",人物卡!AB43) | W30: =IF(人物卡!AN43-人物卡!AF43=0,0,人物卡!AN43) -> 0 | X30: =INT(W30/2) -> 0 | Y30: =INT(W30/5) -> 0 | Z30: =人物卡!W105 -> 0 | AD30: =人物卡!AR105 -> 0
B31: 重要地 | C31: =人物卡!AA67 -> 韦科尔山地，少年时代第一次独自探险的地方 | G31: =人物卡!AR67 -> ☐ | N31: =IF(Q31=0,"",人物卡!F44) | Q31: =IF(人物卡!R44-人物卡!J44=0,0,人物卡!R44) -> 0 | R31: =INT(Q31/2) -> 0 | S31: =INT(Q31/5) -> 0 | T31: =IF(W31=0,"",人物卡!AB44) | W31: =IF(人物卡!AN44-人物卡!AF44=0,0,人物卡!AN44) -> 0 | X31: =INT(W31/2) -> 0 | Y31: =INT(W31/5) -> 0 | Z31: =人物卡!W106 -> 0 | AD31: =人物卡!AR106 -> 0
B32: 宝物 | C32: =人物卡!AA69 -> 一枚老式机械腕表，父母的礼物，从不跑慢 | G32: =人物卡!AR69 -> ☐ | N32: =IF(Q32=0,"",人物卡!F45) | Q32: =IF(人物卡!R45-人物卡!J45=0,0,人物卡!R45) -> 0 | R32: =INT(Q32/2) -> 0 | S32: =INT(Q32/5) -> 0 | T32: =IF(W32=0,"",人物卡!AB45) | W32: =IF(人物卡!AN45-人物卡!AF45=0,0,人物卡!AN45) -> 0 | X32: =INT(W32/2) -> 0 | Y32: =INT(W32/5) -> 0 | Z32: =人物卡!W107 -> 0 | AD32: =人物卡!AR107 -> 0
B33: 特质 | C33: =人物卡!AA71 -> 好奇心胜过了自保意识 | G33: =人物卡!AR71 -> ☐ | N33: =IF(Q33=0,0,"外语：") -> 0 | O33: =IF(N33=0,"",人物卡!H46) | Q33: =IF(人物卡!R46-人物卡!J46=0,0,人物卡!R46) -> 0 | R33: =INT(Q33/2) -> 0 | S33: =INT(Q33/5) -> 0 | T33: =IF(W33=0,"",人物卡!AB46) | W33: =IF(人物卡!AN46-人物卡!AF46=0,0,人物卡!AN46) -> 0 | X33: =INT(W33/2) -> 0 | Y33: =INT(W33/5) -> 0 | Z33: =人物卡!W108 -> 0 | AD33: =人物卡!AR108 -> 0
B34: 小秘密 | C34: =人物卡!AA73 -> 左侧肋骨附近有一道不规则旧疤，一次攀岩事故留下的 | G34: =人物卡!AR73 -> ☐ | N34: =IF(Q34=0,0,"外语：") -> 0 | O34: =IF(N34=0,"",人物卡!H47) | Q34: =IF(人物卡!R47-人物卡!J47=0,0,人物卡!R47) -> 0 | R34: =INT(Q34/2) -> 0 | S34: =INT(Q34/5) -> 0 | T34: =IF(W34=0,"",#REF!) | W34: =IF(人物卡!AN47-人物卡!AF47=0,0,人物卡!AN47) -> 0 | X34: =INT(W34/2) -> 0 | Y34: =INT(W34/5) -> 0
B35: 伤疤 | C35: =人物卡!AA75 -> 极其不喜欢被困在无法自主离开的地方，却没有发展成幽闭恐惧。他可以进入极狭窄的洞穴，因为他确信自己知道出口在哪里。 | G35: =人物卡!AR75 -> ☐ | N35: =IF(Q35=0,0,"外语：") -> 0 | O35: =IF(N35=0,"",人物卡!H48) | Q35: =IF(人物卡!R48-人物卡!J48=0,0,人物卡!R48) -> 0 | R35: =INT(Q35/2) -> 0 | S35: =INT(Q35/5) -> 0 | T35: =IF(W35=0,"",人物卡!AB48) | W35: =IF(人物卡!AN48-人物卡!AF48=0,0,人物卡!AN48) -> 0 | X35: =INT(W35/2) -> 0 | Y35: =INT(W35/5) -> 0
B36: 恐惧 | C36: =人物卡!AA77 -> 0 | N36: 母语： | O36: =人物卡!H49 -> 0 | Q36: =人物卡!R49 -> 65 | R36: =IF(Q36=0,32767,INT(Q36/2)) -> 32 | S36: =IF(Q36=0,32767,INT(Q36/5)) -> 13 | T36: =IF(W36=0,"",人物卡!AB49) | W36: =IF(人物卡!AN49-人物卡!AF49=0,0,人物卡!AN49) -> 0 | X36: =INT(W36/2) -> 0 | Y36: =INT(W36/5) -> 0 | AF36: 电脑请先将快捷输入复制到下面的框中，再复制框中内容到QQ
B37: 下面就是快捷输入了，手机一般轻点两下就可以复制啦，电脑请先复制到右边的本文框 | P37: 不知道用什么导入看导入框右侧的说明～ | AF37: 电脑本文输入框
B38: 溯洄，shiki（除Exp10)，等大部分骰娘指令快捷输入
B39: 请“复制”下格，就可以导出文本，放进QQ发送给骰子娘啦 | Z39: → | AA39: 大部分骰娘 | AF39: 如果不能使用，请复制到txt文档，然后再复制到QQ
B40: =附表!S24 -> .st 力量90str90敏捷40dex40意志75pow75体质50con50外貌65app65教育65edu65体型70siz70智力80灵感80int80san75san值75理智75理智值75幸运70运气70mp15魔法15hp12体力12会计5人类学1估价5考古学1取悦49魅惑49攀爬20计算机5计算机使用5电脑5信用50信誉50信用评级50克苏鲁0克苏鲁神话0cm0乔装5闪避44汽车20驾驶20汽车驾驶20电气维修10电子学1话术5斗殴65手枪70急救30历史5恐吓15跳跃20母语65法律5图书馆20图书馆使用20聆听49开锁1撬锁1锁匠1机械维修10医学1博物学50自然学50领航10导航10神秘学5重型操作1重型机械1操作重型机械1重型1说服49精神分析1心理学49骑术5妙手10侦查70潜行60生存10游泳20投掷20追踪50驯兽5潜水1爆破1读唇1催眠1炮术1
B44: 塔系骰娘指令快捷输入
B45: 请“复制”下格，就可以导出文本，放进QQ发送给骰子娘啦 | Z45: → | AA45: 这种骰娘，在你输入.bot后，开头会出现以下字样 Dice made in java By SitaNya
B46: =附表!S63 -> .st 艾迪安·多雷-力量90str90敏捷40dex40意志75pow75体质50con50外貌65app65教育65edu65体型70siz70智力80灵感80int80san75san值75理智75理智值75幸运70运气70mp15魔法15hp12体力12会计5人类学1估价5考古学1取悦49魅惑49攀爬20计算机5计算机使用5电脑5信用50信誉50信用评级50克苏鲁0克苏鲁神话0cm0乔装5闪避44汽车20驾驶20汽车驾驶20电气维修10电子学1话术5斗殴65手枪70急救30历史5恐吓15跳跃20母语65法律5图书馆20图书馆使用20聆听49开锁1撬锁1锁匠1机械维修10医学1博物学50自然学50领航10导航10神秘学5重型操作1重型机械1操作重型机械1重型1说服49精神分析1心理学49骑术5妙手10侦查70潜行60生存10游泳20投掷20追踪50驯兽5潜水1爆破1读唇1催眠1炮术1
B50: shiki Exp10骰娘指令快捷输入
B51: 请“复制”下格，就可以导出文本，放进QQ发送给骰子娘啦 | Z51: → | AA51: 这种骰娘，在你输入.bot后，开头会出现以下字样 Dice! by 溯洄 Shiki.Ver 2.3.8Express10(554)
B52: =附表!S46 -> .st 力量90str90敏捷40dex40意志75pow75体质50con50外貌65app65教育65edu65体型70siz70智力80灵感80int80san75san值75理智75理智值75幸运70运气70mp15魔法15hp12体力12会计5人类学1估价5考古学1取悦49魅惑49攀爬20计算机5计算机使用5电脑5信用50信誉50信用评级50克苏鲁0克苏鲁神话0cm0乔装5闪避44汽车20驾驶20汽车驾驶20电气维修10电子学1话术5斗殴65手枪70急救30历史5恐吓15跳跃20母语65法律5图书馆20图书馆使用20聆听49开锁1撬锁1锁匠1机械维修10医学1博物学50自然学50领航10导航10神秘学5重型操作1重型机械1操作重型机械1重型1说服49精神分析1心理学49骑术5妙手10侦查70潜行60生存10游泳20投掷20追踪50驯兽5潜水1爆破1读唇1催眠1炮术1时代:1920s 职业:探险家 年龄31 性别:男 住地:法国 里昂 出身:法国 格勒诺布尔 身体状态:健康 精神状态:清醒 &DB=+1D4 体格:1 护甲:0 &好用的刀=1D4+[DB] &好用的枪=1D8+1D4
AA56: ↑版本号必须是Exp 10或以上
B57: MDice骰娘（惠惠）指令快捷输入
B58: 请“复制”下格，就可以导出文本，放进QQ发送给骰子娘啦 | Z58: → | AA58: 这种骰娘，在你输入.bot后，开头会出现以下字样 MDice x.x.x[xx]ver 修改自溯洄版本dice,斯塔尼亚.shiki等提供了部分代码
B59: =附表!S76 -> .st 艾迪安·多雷？力量90str90敏捷40dex40意志75pow75体质50con50外貌65app65教育65edu65体型70siz70智力80灵感80int80san75san值75理智75理智值75幸运70运气70mp15魔法15hp12体力12会计5人类学1估价5考古学1取悦49魅惑49攀爬20计算机5计算机使用5电脑5信用50信誉50信用评级50克苏鲁0克苏鲁神话0cm0乔装5闪避44汽车20驾驶20汽车驾驶20电气维修10电子学1话术5斗殴65手枪70急救30历史5恐吓15跳跃20母语65法律5图书馆20图书馆使用20聆听49开锁1撬锁1锁匠1机械维修10医学1博物学50自然学50领航10导航10神秘学5重型操作1重型机械1操作重型机械1重型1说服49精神分析1心理学49骑术5妙手10侦查70潜行60生存10游泳20投掷20追踪50驯兽5潜水1爆破1读唇1催眠1炮术1
B64: 技能名的改变
B65: 原技能名称： | D65: 简化 | F65: 别名 | J65: 原技能名称： | L65: 简化 | N65: 别名 | R65: 原技能名称： | T65: 简化 | V65: 别名
B66: 力量 | D66: STR | J66: 体力 | L66: hp | R66: 汽车驾驶 | T66: 汽车 | V66: 驾驶
B67: 敏捷 | D67: DEX | J67: 理智 | L67: san | N67: san值，理智值 | R67: 电子学 Ω | T67: 电子学
B68: 体质 | D68: CON | J68: 魔法 | L68: mp | R68: 步枪/霰弹枪 | T68: 步枪 | V68: 霰弹枪，步霰
B69: 体型 | D69: SIZ | R69: 图书馆使用 | T69: 图书馆
B70: 外貌 | D70: APP | R70: 锁匠 | T70: 开锁
B71: 智力 | D71: INT | F71: 灵感 | R71: 博物学 | V71: 自然学
B72: 意志 | D72: POW | J72: 计算机使用 Ω | L72: 计算机 | N72: 计算机使用，电脑 | R72: 导航 | V72: 领航
B73: 教育 | D73: EDU | J73: 信用评级 | L73: 信用 | N73: 信誉 | R73: 操作重型机械 | T73: 重型操作 | V73: 重型机械，重型，重型机械操作
B74: 幸运 | F74: 运气 | J74: 克苏鲁神话 | L74: 克苏鲁 | N74: cm | R74: 生存： | T74: 生存
B75: 红字代表不能使用该名称roll（没有录入，主要因为其特殊的标点符号）
B77: 可选规则：有故事的调查员
B79: 经历包名称 | E79: SAN值减少 | H79: 技能增长 | J79: 备注
B80: 战场经历包 | E80: 1D10+5 | H80: 70 | J80: 对目击尸体和重伤员造成的理智损失免疫;根据战争的年份和模组发生时的年份调整年龄；背景增加一项：战争相关的伤疤 / 疤痕或恐惧症 / 躁狂症
B82: 警务经历包 | E82: 1D10 | H82: 60 | J82: 对目击尸体造成的理智损失免疫;初始年龄不能低于 25 岁;背景增加一项：警察工作相关的伤疤 / 疤痕或恐惧症 / 躁狂症；
B84: 罪犯经历包 | E84: 1D10 | H84: 60 | J84: 对目击尸体、目击或亲自谋杀、目击对人类的暴力残害造成的理智损失免疫;初始年龄不能低于 20 岁；背景增加一项：犯罪历史相关的伤疤 / 疤痕或恐惧症 / 躁狂症
B86: 医务经历包 | E86: 1D10 | H86: 60 | J86: 对目击尸体和重伤员造成的理智损失免疫;初始年龄不能低于 30 岁；背景增加一项：个人背景相关的伤疤 / 疤痕或恐惧症 / 躁狂症；
B88: 神话经历包 | E88: 如果是"相信者"，减少和克苏鲁神话相同的san值 | H88: 0 | J88: 按 KP 允许的数值增加「克苏鲁神话」技能;背景增加两项：与神话经历相关的伤疤 /疤痕、恐惧症 / 躁狂症、遭遇的怪异存在
B90: =IF(ISBLANK(人物卡!BC26),"",人物卡!BC26) | E90: =IF(ISBLANK(人物卡!BC28),"",人物卡!BC28) | H90: =IF(ISBLANK(人物卡!BG28),"",人物卡!BG28) | J90: =IF(ISBLANK(人物卡!BC30),"",人物卡!BC30)

Sheet 职业列表
A1: 序号 | B1: 职业 | D1: 信用评级 | E1: 职业属性 | F1: 技能点 | G1: 本职技能 | K1: 推荐关系人 | M1: 职业介绍
A2: 0 | B2: 选择职业序号为0，则清除职业模板提示和点数计算器，供强迫症患者使用。 | H2: 右侧下拉框选择自定义职业技能与属性 （excel2007及以下不适用） | I2: 自定义职业本职技能
A3: 1 | B3: =IF(C3="","自定义职业",C3) -> 自定义职业 | E3: =附表!AA9 -> 教育×4 | F3: =SUM(附表!AF10:AF12) -> 260 | G3: =IF(I3<>"",I3&"，"&I4&"，"&I5&"，"&I6&"，"&I7&"，"&I8&"，"&I9&"，"&I10,"不多于8个本职技能。在职业属性中输入第二职业属性的数值（留空则视为EDU）并自行设置起始信誉。使用自定义职业前，请先咨询你的守秘人。") -> 不多于8个本职技能。在职业属性中输入第二职业属性的数值（留空则视为EDU）并自行设置起始信誉。使用自定义职业前，请先咨询你的守秘人。 | K3: 列出一些角色在职业工作中可能接触的个人或组织,它们也可以为调查员的个人背景提供灵感。 | M3: 不多于7个本职技能。 在职业属性中输入第二职业属性的名字（如外貌、意志、教育、敏捷、力量、体质、体型，留空则视为附表!N14）并自行设置起始信誉。使用自定义职业前，请先咨询你的KP
A4: 2 | B4: 会计师 | D4: 30-70 | E4: 教育×4 | F4: =附表!N14*4 -> 260 | G4: 会计，法律，图书馆，聆听，说服，侦查，任意其他两项个人或时代特长。 | K4: 生意伙伴，法律界，金融业界(银行，其他会计师)。 | M4: 会计师可能在企业工作或作为自由会计师，为个体经营者和企业客户担任顾问。 他们是优秀的研究者，既勤奋又关注细节，能够通过仔细分析个人和企业事务历史记录、财务报表和其他记录支持其他调查员。
A5: 3 | B5: 杂技演员 | D5: 9-20 | E5: 教育×2＋敏捷×2 | F5: =附表!N14*2+附表!J14*2 -> 210 | G5: 攀爬，闪避，跳跃，投掷，侦查，游泳，任意两项其他个人或时代特长。 | K5: 业余运动员圈，体育专栏作家，马戏团，嘉年华管理者。 | M5: 杂技演员可能是参加各级比赛(甚至奥运会)的业余运动员，也可能是专业的演员，在马戏团、嘉年华、歌舞团之类的地方作为娱乐业从业者工作。
A6: 4 | B6: 演员-戏剧演员 | D6: 9-40 | E6: 教育×2＋外貌×2 | F6: =附表!N14*2+附表!K14*2 -> 260 | G6: 技艺（表演），乔装，格斗，历史，两项社交技能（取悦、话术、恐吓、说服），心理学，任意一项其他个人或时代特长。 | K6: 戏剧产业，报刊艺术批评家，演员公会。 | M6: 一般指舞台剧演员和电影演员。许多演员有相当深厚的文化素养，认为自己才是“正统”的，倾向于轻视电影业的商业活动。直到20 世纪后期电影业的地位提高，电影演员的薪酬增加，这种情况才发生改变。 电影业和电影明星一直是世界人民关注的焦点。许多明星一夜成名，在媒体的聚光灯下过着光鲜亮丽的生活。 在1920 年代，虽然全国都有大型剧院，美国的戏剧中心仍然是纽约城。英国的情况与之相近，戏剧的中心在伦敦，其他的剧团则在各郡作巡回演出。巡回剧团乘火车旅行，演出内容既包括新编剧目，也包括莎士比亚和其他人的传统剧目。有些剧团也会花时间去国外采风，通常是去加拿大、夏威夷、澳大利亚和欧洲大陆。 20 年代后期出现了有声电影，不少默片时代的明星难以适应有声电影的冲击，挥舞手臂的夸张扮演从此让位给了细致入微的角色特写。这段时间前期的明星包括约翰·加菲尔德和弗兰西斯·布什曼，后期则是贾莱·库珀和琼·克劳馥。
A7: 5 | B7: 演员-电影演员 | D7: 20-90 | E7: 教育×2＋外貌×2 | F7: =附表!N14*2+附表!K14*2 -> 260 | G7: 技艺（表演），乔装，汽车驾驶，两项社交技能（取悦、话术、恐吓、说服），心理学，任意两项其他个人或时代特长（如骑乘或格斗）。 | K7: 电影工作室，媒体评论员，作家。 | M7: 一般指舞台剧演员和电影演员。许多演员有相当深厚的文化素养，认为自己才是“正统”的，倾向于轻视电影业的商业活动。直到20 世纪后期电影业的地位提高，电影演员的薪酬增加，这种情况才发生改变。 电影业和电影明星一直是世界人民关注的焦点。许多明星一夜成名，在媒体的聚光灯下过着光鲜亮丽的生活。 在1920 年代，虽然全国都有大型剧院，美国的戏剧中心仍然是纽约城。英国的情况与之相近，戏剧的中心在伦敦，其他的剧团则在各郡作巡回演出。巡回剧团乘火车旅行，演出内容既包括新编剧目，也包括莎士比亚和其他人的传统剧目。有些剧团也会花时间去国外采风，通常是去加拿大、夏威夷、澳大利亚和欧洲大陆。 20 年代后期出现了有声电影，不少默片时代的明星难以适应有声电影的冲击，挥舞手臂的夸张扮演从此让位给了细致入微的角色特写。这段时间前期的明星包括约翰·加菲尔德和弗兰西斯·布什曼，后期则是贾莱·库珀和琼·克劳馥。
A8: 6 | B8: 事务所侦探、保安 | D8: 20-45 | E8: 教育×2＋力量或敏捷×2 | F8: =附表!N14*2+MAX(附表!G14*2,附表!J14*2) -> 310 | G8: 一项社交技能（取悦、话术、恐吓、说服），格斗（斗殴），射击，法律，图书馆，心理学，潜行，追踪。 | K8: 本地执法机构，客户。 | M8: 世界上有许多著名的侦探机构，其中最著名的是平克顿和伯恩斯调查局(后来合并成一家公司)。这样的公司一般有两类工作人员：安保人员和调查人员。 企业或个人雇用安保人员来保护自己的资产和人员免受盗贼、刺客和绑匪的威胁。这些安保人员角色使用巡警的职业模板。调查人员则是便衣侦探，负责为公司客户解决各种异常事件、阻止谋杀事件、寻找失踪的人员等等。
A9: 7 | B9: 精神病医生（古典） | D9: 10-60 | E9: 教育×4 | F9: =附表!N14*4 -> 260 | G9: 法律，聆听，医学，外语，精神分析，心理学，科学（生物学，化学）。 | K9: 其他精神疾病研究者，医生，有时还有执法机构的侦探。 | M9: 在1920 年代，“精神病医生”这个词专用来称呼治疗精神失常的医生(也就是早期的精神科医生)。精神分析在当时的美国鲜为人知，而且它的基本内容都是性生活和如厕训练之类令大众不齿的东西。精神病学，一种正规的从行为主义发展来的医学理论则要普及得多。精神病医生、精神科医生和神经科医生还经常爆发激烈的论战。
A10: 8 | B10: 动物训练师 | D10: 10-40 | E10: 教育×2＋外貌或意志×2 | F10: =附表!N14*2+MAX(附表!K14*2,附表!M14*2) -> 280 | G10: 跳跃，聆听，自然，心理学，科学（动物学），潜行，追踪，任意一项其他个人或时代特长。 | K10: 动物园，马戏团，赞助人，演员。 | M10: 动物训练师可能在电影工作室、巡回马戏团、马厩工作或自由工作。不管是训练导盲犬、狮子钻火圈，他们工作时基本要独自一人长时间近距离地照看这些动物。动物训练师可以像对人一样对动物使用「心理学」技能。
A11: 9 | B11: 文物学家（原作向） | D11: 30-70 | E11: 教育×4 | F11: =附表!N14*4 -> 260 | G11: 估价，技艺（任一），历史，图书馆，外语，一项社交技能（取悦、话术、恐吓、说服），侦查，任意一项其他个人或时代特长。 | I11: 任意特长数: | K11: 书商，古董收藏者，历史研究学会。 | M11: 文物学家也许是调查员可以从事的最具有洛夫克拉夫特风格的职业：那些历久弥新的的卓越作品、湮没在古代传说中的神奇力量，总能使他们乐在其中。独立的收入使文物学家能够研究古旧晦涩的文物，或者根据自己的兴趣爱好集中探寻特别的种类。他们通常有着欣赏的眼光、敏锐的头脑，和讽刺无知、自大、贪婪者的愚蠢时尖酸刻薄的幽默。
A12: 10 | B12: 古董商 | D12: 30-50 | E12: 教育×4 | F12: =附表!N14*4 -> 260 | G12: 会计，估价，汽车驾驶，两项社交技能（取悦、话术、恐吓、说服），历史，图书馆，导航。 | K12: 本地的历史学家，其他古董商，可能还包括赝造师。 | M12: 古董商通常自己开店，从自己所在的地方转卖物品，或继续扩展业务范围，通过倒卖物品到城市商店赚取利润。
A13: 11 | B13: 考古学家（原作向） | D13: 10-40 | E13: 教育×4 | F13: =附表!N14*4 -> 260 | G13: 估价，考古，历史，外语，图书馆，侦查，机械维修，导航或科学（任一：如化学、物理、地理等）。 | H13: 自定义职业属性 | K13: 赞助人，博物馆，大学。 | M13: 考古学家研究探索历史的痕迹。主要来说，是对人类历史相关的物质数据进行各种鉴识、检查、分析。这项工作包含辛苦细致的研究，更不必提情愿亲自下斗铲土的决心。 在1920 年代，成功的考古学家会被当成著名冒险家与探险家，名利双收。有人运用科学方法考古，不过更多的人对付老祖宗的秘密时喜好暴力破解的办法，甚至祭出炸药，这种碉堡了的办法现代人可是很难看得惯的。
A14: 12 | B14: 建筑师 | D14: 30-70 | E14: 教育×4 | F14: =附表!N14*4 -> 260 | G14: 会计，技艺（技术制图），法律，母语，计算机或图书馆，说服，心理学，科学（数学）。 | H14: 属性名称 | I14: 是否使用 | J14: 使用倍数 | K14: 本地建设和城市规划部门，建筑公司。 | M14: 建筑师掌握设计和营造建筑的知识，不论是个人房屋的改造还是造价数百万美元的地标工程。建筑师与项目经理紧密合作，负责监督施工全程。建筑师必须了解当地的规划法律，健康和安全法规，和基础的公众安全原则。他们既可以在大公司工作，也可以自由工作，这在很大程度上取决于信誉。 在1920 年代，许多人尝试在自家或小办公室单干。不过他们苦心创造的宏伟设计很少能卖得出去。 建筑师也可能专擅某一学科，比如军事建筑或景观工程等。
A15: 13 | B15: 艺术家 | D15: 9-50 | E15: 教育×2＋敏捷或意志×2 | F15: =附表!N14*2+MAX(附表!J14*2,附表!M14*2) -> 280 | G15: 技艺（任一），历史或自然，一项社交技能（取悦、话术、恐吓、说服），外语，心理学，侦查，任意两项其他个人或时代特长。 | H15: 力量 | I15: × | J15: =IF(I15="√",2,0) -> 0 | K15: 美术馆，美术批评家，富有的赞助人，广告业者。 | M15: 艺术家在这里可以是画家，雕塑家等等。他们有时沈浸于自己虚幻的想象当中，有时又沐浴在激发热情和理解的灵感之下。不论是否天资优秀，艺术家的内心必须足够强大，这样才能战胜生涯起步时的障碍和挑剔的眼光，并且在自己小有名气以后继续努力。有些艺术家对物质生活是否丰富并不在乎，而有些则有着强烈的创业倾向。
A16: 14 | B16: 精神病院看护 | D16: 8-20 | E16: 教育×2＋力量或敏捷×2 | F16: =附表!N14*2+MAX(附表!G14*2,附表!J14*2) -> 310 | G16: 闪避，格斗（斗殴），急救，两项社交技能（取悦、话术、恐吓、说服），聆听，心理学，潜行。 | H16: 敏捷 | I16: × | J16: =IF(I16="√",2,0) -> 0 | K16: 医护人员，患者和患者家属。允许接触医疗记录、药品或其他医疗用品。 | M16: 尽管少数富有的人会选择私人疗养院，大多精神病患者最终会被安置到州县设置的定点医院。这些地方除了医生护士以外，还会有一支看护队伍。选聘看护的时候，力量和体格往往比医学知识更被看重。
A17: 15 | B17: 运动员 | D17: 9-70 | E17: 教育×2＋力量或敏捷×2 | F17: =附表!N14*2+MAX(附表!G14*2,附表!J14*2) -> 310 | G17: 攀爬，跳跃，格斗（斗殴），骑乘，一项社交技能（取悦、话术、恐吓、说服），游泳，投掷，任意一项其他个人或时代特长。 | H17: 体质 | I17: × | J17: =IF(I17="√",2,0) -> 0 | K17: 体育界，体育专栏作家，其他明星。 | M17: 运动员可能效力于职业的棒球、足球、板球或者篮球队伍。这支队伍也许是大联盟队伍，有着稳定工资，参加的比赛万人瞩目；或者是众多小联盟队伍之一，尤其是在1920 年代的棒球界。这些队伍往往寄于大联盟队伍篱下，各方面都受其管理，工资更是刚够运动员糊口又不至于让他们跳槽的水平。 成功的运动员在自己的专业领域会拥有相当的声誉——现今尤其如此，在世界各地都能看到体育明星和电影明星并肩站在红地毯上的场景。
A18: 16 | B18: 作家（原作向） | D18: 9-30 | E18: 教育×4 | F18: =附表!N14*4 -> 260 | G18: 技艺（文学），历史，图书馆，自然或神秘学，外语，母语，心理学，任意一项其他个人或时代特长。 | H18: 体型 | I18: × | J18: =IF(I18="√",2,0) -> 0 | K18: 出版社，文学评论家，历史学家等。 | M18: 作家不同于记者，他们用文字定义和探讨人们的社会生活，尤其是人们的情感变化。他们的劳动通常孤立而又自我中心：虽然以前写作是个能稳拿工资的行当，但如今只靠写作发大财的人屈指可数。 作家的工作习惯相差极大。通常作家们会花费数月乃至数年的时间调查取材，为新书的创作做准备；然后闭门谢客，投入紧张的创作。
A19: 17 | B19: 酒保 | D19: 8-25 | E19: 教育×2＋外貌×2 | F19: =附表!N14*2+附表!K14*2 -> 260 | G19: 会计，两项社交技能（取悦、话术、恐吓、说服），格斗（斗殴），聆听，心理学，侦查，任意一项其他个人或时代特长。 | H19: 外貌 | I19: × | J19: =IF(I19="√",2,0) -> 0 | K19: 常客，可能有犯罪组织。 | M19: 酒保虽然不一定是酒吧的掌柜，却一定是所有客人的朋友。对客人们的好声气，一部分来说是出于他们的职业或者业务，而更多的来说则是达到目的的一种手段。 1920 年代，由于禁酒令的存在，酒保变成了非法的职业；但是遍地开花的黑酒吧又不能没有酒保，结果就是酒保仍然不愁找不到活干。
A20: 18 | B20: 猎人 | D20: 20-50 | E20: 教育×2＋力量或敏捷×2 | F20: =附表!N14*2+MAX(附表!G14*2,附表!J14*2) -> 310 | G20: 射击，聆听或侦查，自然，导航，外语或生存（任一），科学（生物学或植物学），潜行，追踪。 | H20: 智力 | I20: × | J20: =IF(I20="√",2,0) -> 0 | K20: 外国政府官员，狩猎监管人员，前客户(大多很有钱)，黑市商人与黑社会，动物园主。 | M20: 猎人是优秀的追踪者和狩猎者，通常靠为富裕的客户捕猎为生。绝大多数猎人会对地球上某一个部分的情况烂熟于心，比如加拿大森林、非洲草原等等。有些人可能从事盗猎活动，例如为私人收藏家捕捉珍稀动物，或者贩卖受保护的动物和违反道德的动物制品，如兽皮、象牙之类——虽然1920 年代大多数国家这些活动都不算违法。 尽管“王牌猎人”是最典型的类型，不过在加拿大育空的深山老林里打驼鹿和熊为生的土著人也可以算是猎人。
A21: 19 | B21: 书商 | D21: 20-40 | E21: 教育×4 | F21: =附表!N14*4 -> 260 | G21: 会计，估价，汽车驾驶，历史，图书馆，母语，外语，一项社交技能（取悦、话术、恐吓、说服）。 | H21: 教育 | I21: √ | J21: =IF(I21="√",IF(SUM(J15:J20,J22:J23)>0,2,4),0) -> 4 | K21: 目录学家、其他书商、图书馆和大学、客户。 | M21: 书商可能拥有自己的店面或者利基(小众)邮购服务，也可能辗转全国甚至海外专门经销书籍。许多人拥有富有的，能提供利润丰厚又稀罕的工作的固定客户。
A22: 20 | B22: 赏金猎人 | D22: 9-30 | E22: 教育×2＋力量或敏捷×2 | F22: =附表!N14*2+MAX(附表!G14*2,附表!J14*2) -> 310 | G22: 汽车驾驶，电子学或电气维修，格斗或射击，一项社交技能（取悦、话术、恐吓、说服），法律，心理学，追踪，潜行。 | H22: 意志 | I22: × | J22: =IF(I22="√",2,0) -> 0 | K22: 保释业者，本地警察，线人。 | M22: 赏金猎人捉拿罪犯并将他们交给正义去审判。最常见的情况是受保释人的委托去缉捕逃狱者。赏金猎人们为了自己的猎物可以不择手段，几乎不会考虑其他人的正当权益之类细枝末节的东西。 非法闯入、威胁、肢体暴力，都是赏金猎人屡试不爽的秘技。现在这些秘技还包括了电话窃听、黑客操作和其他的秘密监控。 (译注：所谓保释业者。向法院交纳保释金，可以在审判之前免受收押；若被保释者按时接受审判，法院会退还保释金。保释金数额较大，故有保释业者以提供保释金收取手续费为业。)
A23: 21 | B23: 拳击手、摔跤手 | D23: 9-60 | E23: 教育×2＋力量×2 | F23: =附表!N14*2+附表!G14*2 -> 310 | G23: 闪避，格斗（斗殴），恐吓，跳跃，心理学，侦查，任意两项其他个人或时代特长。 | H23: 幸运 | I23: × | J23: =IF(I23="√",2,0) -> 0 | K23: 运动会主办者，记者，犯罪组织，专业训练人员。 | M23: 拳击手和摔跤手各分为职业和业余两种。 职业拳击手和职业摔角手的活动由外部利益支持的贸助人安排，并有合同约束。他们还要进行全日制的工作和训练。 业余拳击的竞赛种类非常丰富，同时它也是那些想成为职业拳手的人的训练场。不过也有业余和准职业的选手靠参加黑市拳击赛谋生，举办这些比赛的通常是本地的黑社会或者是从中渔利的庄家。
A24: 22 | B24: 管家、男仆、女仆 | D24: 9-40 | E24: 教育×4 | F24: =附表!N14*4 -> 260 | G24: 会计或估价，技艺（任一：如烹饪、裁缝、理发），急救，聆听，外语，心理学，侦查，任意一项其他个人或时代特长。 | H24: 计算方式
A25: 23 | B25: 神职人员 | D25: 9-60 | E25: 教育×4 | F25: =附表!N14*4 -> 260 | G25: 会计，历史，图书馆，聆听，外语，一项社交技能（取悦、话术、恐吓、说服），心理学，任意一项其他技能。 | H25: 所有属性的点数相加 | K25: 教会高层、地方教会、小区领导。 | M25: 神职人员通常担任一个教区的牧师，或是经过分配外出传教，尤其是去国外(见传教士)。 不同的教会工作的侧重点和组织结构各不相同，如天主教会的牧师可能上升到主教、大主教和红衣主教，而一个卫理公会的牧师则会升职到教区主管和主教。 许多神职人员都接受忏悔(不仅仅是天主教)。虽然不能透露忏悔的内容，但是要怎样利用它们就全凭他们自己了。 有些教职人员在教堂接受医生、律师、学者的专业培训。这样的调查员应该选择最符合自己工作的职业模板。
A26: 24 | B26: 程序员、电子工程师（现代） | D26: 10-70 | E26: 教育×4 | F26: =附表!N14*4 -> 260 | G26: 计算机，电气维修，电子学、图书馆，科学（数学），侦查，任意两项其他个人或时代特长。 | K26: 其他IT 工作者，同事和上司，专业网络小区。 | M26: 计算器程序员通常是设计、编写、测试、调试和维护计算器程序源代码的职业。他们精通从形式逻辑到系统平台(程序运行环境)的各种知识，可能是自由工作者，也可能供职于软件开发部门。 计算器技术人员负责计算器系统和网络的开发和维护工作，经常与其他人员(如项目经理)合作来保证系统的完整稳定和正常提供所需功能。类似的职业还包括数据库管理员、系统管理员、网络管理员、多媒体开发人员、软件工程师、网络管理员等。
A27: 25 | B27: 黑客/骇客（现代） | D27: 10-70 | E27: 教育×4 | F27: =附表!N14*4 -> 260 | G27: 计算机，电气维修，电子学，图书馆，侦查，一项社交技能（取悦、话术、恐吓、说服），任意两项其他技能。 | K27: 其他IT 工作者，专业网络小区，政治团体，犯罪组织。 | M27: 计算器黑客利用计算器和计算器网络为手段，进行干扰或破坏以达成政治目的(有时被称为“政治黑客”)或获取非法利益。达成目标的手段主要是非法入侵计算器和其他用户帐户，目的则可能包括篡改网页、人肉搜索、盗取身份信息、垃圾邮件炸弹、拒绝服务攻击等等。
A28: 26 | B28: 牛仔 | D28: 9-20 | E28: 教育×2＋力量或敏捷×2 | F28: =附表!N14*2+MAX(附表!G14*2,附表!J14*2) -> 310 | G28: 闪避，格斗或射击，急救或自然，跳跃，骑乘，生存（任一），投掷，追踪。 | K28: 本地企业家，州农业部门，牛仔比赛主办者，艺人。 | M28: 牛仔在西部的牧区和牧场工作。有些人拥有自己的牧场，更多的则是在各处打工为生。想赚大钱的牛仔会去冒着丢胳膊少腿乃至送命的危险参加牛仔巡回赛，通过旅行获取名誉。 在1920 年代，一些牛仔能在好莱坞找到西部片替身演员和群众演员的工作，例如怀特·厄普就曾为西部电影担任顾问。在现代，有些牧场也对想要体验一把牛仔生活的游客开放。
A29: 27 | B29: 工匠 | D29: 10-40 | E29: 教育×2＋敏捷×2 | F29: =附表!N14*2+附表!J14*2 -> 210 | G29: 会计，技艺（任二），机械维修，自然，侦查，任意两项其他个人或时代特长。 | K29: 本地商人，其他工匠和艺术家。 | M29: 工匠也可能被人叫做师傅或大师，是擅长对各种材料进行手工加工的人。通常都是才能出众的人，有的凭借自己的艺术作品出名，有的则会服务于自己的小区。 可能的行当包括：家具、珠宝、钟表、陶艺、锻造、纺织、书法、裁缝、木工、书籍装裱、玩具制造、彩色玻璃吹制等等。
A30: 28 | B30: 罪犯-刺客 | D30: 30-60 | E30: 教育×2＋力量或敏捷×2 | F30: =附表!N14*2+MAX(附表!G14*2,附表!J14*2) -> 310 | G30: 乔装，电气维修，格斗，射击，锁匠，机械维修，潜行，心理学。 | K30: 很少，大都是黑社会的人，人们尽量避免和他们交情过深。 | M30: 杀手是地下世界的冷血夺命者。这是一项严谨的活计，他们从外地受雇杀人，接近目标，果断下手，又迅速离开。杀手通常很难融入社会，因为很多杀手行为总是很刻板，其他人很容易以为他们不近人情。但是另一方面，他们也会结婚生子，在其他方面和普通人没有什么不同。
A31: 29 | B31: 罪犯-银行劫匪 | D31: 5-75 | E31: 教育×2＋力量或敏捷×2 | F31: =附表!N14*2+MAX(附表!G14*2,附表!J14*2) -> 310 | G31: 汽车驾驶，电气维修或机械维修，格斗，射击，恐吓，锁匠，操作重型机械，任意一项其他个人或时代特长。 | K31: 同伙(不论是现在还是以前的)，独行罪犯，犯罪组织。 | M31: 罪犯的体格和相貌形形色色，有些是纯粹碰运气伺机行事，比如扒手和暴徒；有些则组成分工明确，会详细调查并制定计划的犯罪组织。后者包括银行劫匪、飞贼、赝造者和诈骗者。 罪犯可能为别人工作，后者通常是“匪帮”或罪犯家族；也可能单打独斗，如果成功的报酬值得去费力冒险，才会和别人搭伙。自由犯罪者则往往被称为抢劫犯、响马贼和江洋大盗。
A32: 30 | B32: 罪犯-打手、暴徒 | D32: 5-30 | E32: 教育×2＋力量×2 | F32: =附表!N14*2+附表!G14*2 -> 310 | G32: 汽车驾驶，格斗，射击，两项社交技能（取悦、话术、恐吓、说服），心理学，潜行，侦查。 | K32: 犯罪组织，本地执法机构，本地企业。 | M32: 打手、暴徒都是犯罪组织的兵卒。他们被犯罪组织豢养，不过团伙上层出事的时候，倒霉的往往是他们这些喽啰。对于他们来说，嘴紧和忠心属于职业道德。
A33: 31 | B33: 罪犯-窃贼 | D33: 5-40 | E33: 教育×2＋敏捷×2 | F33: =附表!N14*2+附表!J14*2 -> 210 | G33: 估价，攀爬，电气维修或机械维修，聆听，锁匠，妙手，潜行，侦查。 | K33: 赃物贩子，其他的盗贼。 | M33: 罪犯的体格和相貌形形色色，有些是纯粹碰运气伺机行事，比如扒手和暴徒；有些则组成分工明确，会详细调查并制定计划的犯罪组织。后者包括银行劫匪、飞贼、赝造者和诈骗者。 罪犯可能为别人工作，后者通常是“匪帮”或罪犯家族；也可能单打独斗，如果成功的报酬值得去费力冒险，才会和别人搭伙。自由犯罪者则往往被称为抢劫犯、响马贼和江洋大盗。
A34: 32 | B34: 罪犯-欺诈师 | D34: 10-65 | E34: 教育×2＋外貌×2 | F34: =附表!N14*2+附表!K14*2 -> 260 | G34: 估价，技艺（表演），法律或外语，聆听，两项社交技能（取悦、话术、恐吓、说服），心理学，妙手。 | K34: 其他的诈骗师，独行罪犯。 | M34: 欺诈师通常都是油嘴滑舌的人物。他们或单独或集体出没在富裕的人家和小区周边，诈取他们来之不易的钱财。许多骗局覆杂精妙，诈骗团伙会倾巢出动乃至租用建筑；有些则不需要这么麻烦，只要一个骗子几分钟就能搞定。
A35: 33 | B35: 罪犯-独行罪犯 | D35: 5-65 | E35: 教育×2＋敏捷或外貌×2 | F35: =附表!N14*2+MAX(附表!J14*2,附表!K14*2) -> 260 | G35: 技艺（表演）或乔装，估价，一项社交技能（取悦、话术、恐吓、说服），格斗或射击，锁匠或机械维修，潜行，心理学，侦查。 | K35: 轻罪罪犯，本地执法机构。 | M35: 罪犯的体格和相貌形形色色，有些是纯粹碰运气伺机行事，比如扒手和暴徒；有些则组成分工明确，会详细调查并制定计划的犯罪组织。后者包括银行劫匪、飞贼、赝造者和诈骗者。 罪犯可能为别人工作，后者通常是“匪帮”或罪犯家族；也可能单打独斗，如果成功的报酬值得去费力冒险，才会和别人搭伙。自由犯罪者则往往被称为抢劫犯、响马贼和江洋大盗。
A36: 34 | B36: 罪犯-女飞贼（古典） | D36: 10-80 | E36: 教育×2＋外貌×2 | F36: =附表!N14*2+附表!K14*2 -> 260 | G36: 技艺（任意），两项社交技能（取悦、话术、恐吓、说服），格斗（斗殴）或射击（手枪），汽车驾驶，聆听，潜行，任意一项其他个人或时代特长。 | K36: 黑帮，执法机构，本地企业 | M36: 女飞贼是名为专业大盗的女人。大部分都是独立行动，也有对自己的男伴言听计从的时候。 不过这也不一定，实际上情况可能完全相反，她完全可以在干了某一票以后就卷走所有现金和皮草溜之大吉。
A37: 35 | B37: 罪犯-赃物贩子 | D37: 20-40 | E37: 教育×2＋外貌×2 | F37: =附表!N14*2+附表!K14*2 -> 260 | G37: 会计，估价，技艺（伪造），历史，一项社交技能（取悦、话术、恐吓、说服），图书馆，侦查，任意一项其他技能。 | K37: 犯罪组织，贸易伙伴，黑市和和守法的买主。 | M37: 赃物贩子，顾名思义是买卖偷抢来的财产，通常是收购赃物并转手卖给其他罪犯或(无意中)守法的顾客。主要来说，他们是小偷和买家的中间人，有时也会从交易中收取提成；不过更常见的还是以极低的价格直接收购赃物。
A38: 36 | B38: 罪犯-赝造者 | D38: 20-60 | E38: 教育×4 | F38: =附表!N14*4 -> 260 | G38: 会计，估价，技艺（伪造），历史，图书馆，侦查，妙手，任意一项其他个人或时代特长（如计算机）。 | K38: 犯罪组织，商人。 | M38: 赝造者是地下世界的艺术家，专门从事伪造官方文件、契约、转让书，并提供伪造的签名。初学者只能做做小贼的假身份证，而顶级的赝造者连印假币的铸模都能做。
A39: 37 | B39: 罪犯-走私者 | D39: 20-60 | E39: 教育×2＋外貌或敏捷×2 | F39: =附表!N14*2+MAX(附表!J14*2,附表!K14*2) -> 260 | G39: 射击，聆听，导航，一项社交技能（取悦、话术、恐吓、说服），汽车驾驶或驾驶（飞行器或船），心理学，妙手，侦查。 | K39: 犯罪组织，海岸卫队，海关官员。 | M39: 走私一直是一个有利可图的高风险行当。走私者往往有一个合法的表面职业，比如船长、飞行员或商人，以掩盖他们非法运输的行为。
A40: 38 | B40: 罪犯-混混 | D40: 3-10 | E40: 教育×2＋力量或敏捷×2 | F40: =附表!N14*2+MAX(附表!G14*2,附表!J14*2) -> 310 | G40: 攀爬，一项社交技能（取悦、话术、恐吓、说服），格斗，射击，跳跃，妙手，潜行，投掷。 | K40: 其他轻罪罪犯，其他混混，本地的赃物贩子，黑帮，当然还有警察。 | M40: 街头混混一般都是些小年轻，弄不好还在寻觅加入真正黑帮的契机。不过他们的本事也就限于偷车，盗窃商店货物，抢钱或者夜盗。
A41: 39 | B41: 教团首领 | D41: 30-60 | E41: 教育×4 | F41: =附表!N14*4 -> 260 | G41: 会计，两项社交技能（取悦、话术、恐吓、说服），神秘学，心理学，侦查，任意其他两项其他个人特长。 | K41: 主要的信徒都是普通人。不过首领的魅力越高，信徒当中有电影明星或者富有的寡妇之类名人的可能性就越大。 | M41: 美国的新兴宗教层出不穷。直到现在，也还有从新英格兰超验主义到“天父的儿女”等等许多种类。教团首领有的创立了严格的教条并且对信徒推行，另一些则仅仅是垂涎于信徒的金钱和权势。 在1920 年代，各种诱惑性的新兴宗教团体纷纷涌现。有些采取基督教的形式，有些则混杂了东方的神秘主义和神秘学的仪式。美国西海岸的人对这些教团屡见不鲜，不过其他形式的教团全国各地都存在。在美国南部的“圣经带”，就有许多巡回帐篷演出圣歌、舞蹈，推行信仰覆兴。其他国家也是一样，只要有需要信仰的人，就会有新兴宗教团体。
A42: 40 | B42: 除魅师（现代） | D42: 20-50 | E42: 教育×4 | F42: =附表!N14*4 -> 260 | G42: 两项社交技能（取悦、话术、恐吓、说服），汽车驾驶，格斗（斗殴）或射击，历史，神秘学，心理学，潜行。※经KP允许 可用催眠替换其中一项。 | K42: 本地和国家的执法机构，罪犯，宗教团体。 | M42: 除魅师的工作是说服(或者强迫)一个人放弃自己的信仰或是对宗教团体、社会团体的忠心。他们一般受雇于深陷教团之类组织的人的亲属，任务就是解救对方(通常靠绑架)，并通过心理学手段使他们割断与原来教团的联系(“控制”)。 也有不那么激烈的除魅师，他们的工作对象则是那些自愿离开教团的人，为他们完全地退出教团进行有效的指导。
A43: 41 | B43: 设计师 | D43: 20-60 | E43: 教育×4 | F43: =附表!N14*4 -> 260 | G43: 会计，技艺（摄影），技艺（任一），计算机或图书馆，机械维修，心理学，侦查，任意一项其他个人特长。 | K43: 广告业，媒体，家具业，建筑业，其他。 | M43: 设计师的工作包括许多方面，从时装到家具或是其他任何东西。他们自由工作，为设计工作室和企业设计产品、流程、法律、游戏、图像等等。 调查员特定的设计方向也会影响他们对专业技能的选择，如果需要的话要进行调整。
A44: 42 | B44: 业余艺术爱好者（原作向） | D44: 50-99 | E44: 教育×2＋外貌×2 | F44: =附表!N14*2+附表!K14*2 -> 260 | G44: 技艺（任一），射击，外语，骑乘，一项社交技能（取悦、话术、恐吓、说服），任意三项其他个人或时代特长。 | K44: 多种多样，但通常是背景和趣味相近的人。同好会组织、波希米亚主义者、上流社会。 | M44: 业余艺术爱好者靠经济自立、遗产继承、信托基金或者其他各种来源保障自己的生活开支，没有必要自己工作。如果经济条件足够好，他们甚至可以雇佣专业的经济顾问来打理自己的产业。他们可能有很高的学历，但不一定是真才实学；优越的经济条件使得他们性情古怪，口无遮拦。 在1920 年代，这些人可能会被时人称为“摩登女郎”或者“公子哥儿”，当然想当一个社交“名流”其实并不要求他有多有钱。换作现代，“时髦”则是恰如其分的形容词。 业余艺术爱好者有着大把的时间考虑如何变得潇洒世故，不过花这些时间去做别的事可是违背他们的天性和兴致。
A45: 43 | B45: 潜水员 | D45: 9-30 | E45: 教育×2＋敏捷×2 | F45: =附表!N14*2+附表!J14*2 -> 210 | G45: 潜水，急救，机械维修，驾驶（船），科学（生物），侦查，游泳，任意一项其他个人或时代特长。 | K45: 海岸警卫队，船长，军队，执法机构，走私者。 | M45: 潜水员可能在军队、执法机构或海绵采集、海上救援、环境保护甚至水下寻宝的民间机构工作。
A46: 44 | B46: 医生（原作向） | D46: 30-80 | E46: 教育×4 | F46: =附表!N14*4 -> 260 | G46: 急救、医学、外语（拉丁文）、心理学、科学（生物学，制药），任两种其他学术或个人特长。 | K46: 其他医生，医护工作者，病人和前病人。 | M46: 医生这里可能是指全科医生、外科医生、其他专科医生或者独立医学研究员。除去个人的目标以外，救死扶伤、获得财富和荣誉、提升公众的理性意识和科学素养也常常是医生的理想。 农村和小城镇的卫生院是全科医生的舞台，而大城市的各大医院则是高手如云，集聚了众多专攻病理学、毒理学、整形外科、脑外科等领域的专家。有些医生也可能担任全职或兼职的法医，进行尸检，并为市、县、州级执法机构出具检验报告。 在美国，行医资格由各州认证，大多要求最少两年的正规医学院校学习经历。不过这个规定还是比较晚近的，在1920 年代很多年长的医生尽管没受过任何正规专业教育，仍然可以获得医师执照。
A47: 45 | B47: 流浪者 | D47: 0-5 | E47: 教育×2＋外貌或敏捷或力量×2 | F47: =附表!N14*2+MAX(附表!J14*2,附表!K14*2,附表!G14*2) -> 310 | G47: 攀爬，跳跃，聆听，导航，一项社交技能（取悦、话术、恐吓、说服），潜行，任意两项其他个人或时代特长。 | K47: 其他流浪者，少数友善的铁路工人，城镇里众多的好心人。 | M47: 相对于那些因贫困而苦恼的人，流浪者选择四处漂泊的生活，可能是出于社会、哲学、经济的原因，或只是渴望摆脱社会的约束。 流浪汉需要工作，有时几天或几个月，但他们应对问题时往往选择流动和孤立，而不是舒适和亲近。在美国，这种情况尤其常见，只要旅行本身没有什么危险，就会有人选择漂泊为生。
A48: 46 | B48: 司机-私人司机 | D48: 10-40 | E48: 教育×2＋敏捷×2 | F48: =附表!N14*2+附表!J14*2 -> 210 | G48: 汽车驾驶，两项社交技能（取悦、话术、恐吓、说服），聆听，机械维修，导航，侦查，任意一项其他个人或时代特长。 | K48: 成功商界人士(包括罪犯)，政要。 | M48: 私人司机是直接受雇于个人或企业，或者是专门提供连人带车的私人司机业务的中介机构。
A49: 47 | B49: 司机-司机 | D49: 9-20 | E49: 教育×2＋力量或敏捷×2 | F49: =附表!N14*2+MAX(附表!G14*2,附表!J14*2) -> 310 | G49: 会计，汽车驾驶，聆听，一项社交技能（取悦、话术、恐吓、说服），机械维修，导航，心理学，任意一项其他个人或时代特长。 | K49: 顾客，企业，执法机构和街头路人。 | M49: 专职司机可能为企业、个人工作，也可能拥有自己的出租车或货车。通常司机还要通过警方的背景调查，获得特殊的驾驶许可证。
A50: 48 | B50: 司机-出租车司机 | D50: 9-30 | E50: 教育×2＋敏捷×2 | F50: =附表!N14*2+附表!J14*2 -> 210 | G50: 会计，汽车驾驶，电气维修，话术，机械维修，导航，侦查，任意一项其他个人或时代特长。 | K50: 街头路人，偶尔有一些有名的顾客。 | M50: 出租车司机可能属于大大小小的出租车公司，也可能靠自己的车和证件运营(在美国，需要出租车牌照)。出租车公司负责为出租车司机登记车辆并分配调度，方便司机自由揽客。出租车上必须统一安装计价器，并由出租车协会进行定期检查。
A51: 49 | B51: 编辑 | D51: 10-30 | E51: 教育×4 | F51: =附表!N14*4 -> 260 | G51: 会计，历史，母语，两项社交技能（取悦、话术、恐吓、说服），心理学，侦查，任意一项其他个人或时代特长。 | K51: 新闻业界，地方政府，专业人士(如时装设计师、运动员、商人)，出版社。 | M51: 编辑的工作包括审核记者的稿件，撰写报刊社论，应对各种突发事件、到了截稿时间要催稿，编辑工作只好偶尔为之啦。大型报社的编辑数量众多，包括比起新闻编辑更多参与业务运营的主编。其他编辑专门负责时尚、体育或者其他板块。许多小报可能就只有一个编辑，他甚至有可能就是报社的业主或者唯一的全职员工。
A52: 50 | B52: 政府官员 | D52: 50-90 | E52: 教育×2＋外貌×2 | F52: =附表!N14*2+附表!K14*2 -> 260 | G52: 取悦，历史，恐吓，话术，聆听，母语，说服，心理学。 | K52: 公务员，政府，新闻媒体，企业，外国政府，可能有犯罪组织。 | M52: 以民选方式选举出来的政府官员享有与他们的职位相符的声望。小城市的市长和城镇的镇长之类，他们的影响力基本出不了城镇的范围，而且这样的职务基本上是兼职的，报酬也很少。大城市的市长，工资就相当可观了，而且还能把自己的城市管理得像小王国一样，影响力和权力比所在州的州长还要大。 州议会的众参两院议员是相当有面子的职位，尤其是在商界和本州岛的其他业界。 州长负责全州的事务，是联系各州和国家的纽带。 联邦政府拥有最高等级的影响力。众议院议员由各州按本州岛人口所占比重选派的共400 余名议员组成，任期为两年。参议院则是不论各州大小，每州选派两名议员到花生屯任职。任期长达六年，人数不超过一百，所以参议员更是权倾一方，许多年长的议员能够享受总统级的待遇。 在英国，下议院议员由选举产生，任期四到五年；上议院议员则不由选举产生，是世袭制或由君主指任。
A53: 51 | B53: 工程师 | D53: 30-60 | E53: 教育×4 | F53: =附表!N14*4 -> 260 | G53: 技艺（技术制图），电气维修，图书馆，机械维修，操作重型机械，科学（工程学，物理），任意一项其他个人或时代特长。 | K53: 生意伙伴或部队同事，地方政府，建筑师。 | M53: 工程师精通机械和电气设备，可能在民间或军工企业工作，也可能是个发明家。他们擅长应用科学、数学知识和丰富的创造思维，解决各种技术问题。
A54: 52 | B54: 艺人 | D54: 9-70 | E54: 教育×2＋外貌×2 | F54: =附表!N14*2+附表!K14*2 -> 260 | G54: 技艺（表演类，如表演、演唱、喜剧等），乔装，两项社交技能（取悦、话术、恐吓、说服），聆听，心理学，任意两项其他个人或时代特长。 | K54: 歌舞杂技团，剧院，电影工作室，娱乐评论家，犯罪组织，电视台(现代)。 | M54: 艺人包括小丑、歌手、舞蹈演员、喜剧演员、杂耍艺人、魔术师，各种以在人前表演谋生的人。他们乐于向更多的人表现自己的能力，并期待观众回报的掌声。 在1920 年代，这一职业并不受人尊重。不过1920 年代好莱坞明星的高薪彻底改变了很多人的想法，现在这个职业背景已经通常被视作是优势了。
A55: 53 | B55: 探险家（古典） | D55: 55-80 | E55: 教育×2＋外貌或敏捷或力量×2 | F55: =附表!N14*2+MAX(附表!J14*2,附表!K14*2,附表!G14*2) -> 310 | G55: 攀爬或游泳，射击，历史，跳跃，自然，导航，外语，生存。 | K55: 大图书馆，大学，博物馆，富有的赞助者，其他探险家，出版社，外国政府官员，本地土著。 | M55: 在20 世纪早期，这世界还有许多地区尚未有人涉足，而探索这些地方正是探险家的工作。这种令人兴奋不已的生活方式，其经济来源则是科学界的赞助、私人的捐赠、博物馆的委托和报纸杂志图书电影的版权等等。 黑非洲的大部分仍然不为人知，同样的地方还包括了南美的马托格罗索高原，澳大利亚的大沙沙漠，撒哈拉和阿拉伯沙漠，和亚洲的茫茫戈壁。尽管南北极点已经被探险家征服了，但周围很大部分的地区仍然是未知的。
A56: 54 | B56: 农民 | D56: 9-30 | E56: 教育×2＋力量或敏捷×2 | F56: =附表!N14*2+MAX(附表!G14*2,附表!J14*2) -> 310 | G56: 技艺（耕作），汽车驾驶（或运货马车），一项社交技能（取悦、话术、恐吓、说服），机械维修，自然，操作重型机械，追踪，任意一项其他个人或时代特长 | K56: 地方银行，地方政治家，各州农业部门。 | M56: 农民可能自己拥有土地，自己从事农牧业，也可能是受雇在农场工作。农业劳动繁重而枯燥，特别适合那些喜欢户外体力劳动的人。 1920 年代是美国城镇人口超过农村人口的首个十年。从这时起一直到现在，自耕农民都在受到规模化农业企业和剧烈波动的农产品市场的双重冲击。
A57: 55 | B57: 联邦探员 | D57: 20-40 | E57: 教育×4 | F57: =附表!N14*4 -> 260 | G57: 汽车驾驶，格斗（斗殴），射击，法律，说服，潜行，侦查，任意一项其他个人或时代特长。 | K57: 联邦司法机构，执法机构，犯罪组织。 | M57: 联邦执法机构和特工种类各异。有些身着制服，比如美国司法部的人员；另外一些则穿便服，工作内容也类似警探，比如联邦调查局的人员。
A58: 56 | B58: 消防员 | D58: 9-30 | E58: 教育×2＋力量或敏捷×2 | F58: =附表!N14*2+MAX(附表!G14*2,附表!J14*2) -> 310 | G58: 攀爬，闪避，汽车驾驶，急救，跳跃，机械维修，操作重型机械，投掷。 | K58: 市政工人，医务人员，执法机构。 | M58: 消防员是公职人员，通常为所管辖的小区服务。他们夜以继日地工作，或者连续几天的倒班工作，吃住包括娱乐活动都要局限在消防局里。消防员的管理结构类似军队，职位包括中尉、上尉和局长等等。
A59: 57 | B59: 驻外记者 | D59: 10-40 | E59: 教育×4 | F59: =附表!N14*4 -> 260 | G59: 历史，外语，母语，聆听，两项社交技能（取悦、话术、恐吓、说服），心理学，任意一项其他个人或时代特长。 | K59: 国内外新闻界，外国政府，军队。 | M59: 驻外记者是新闻界的精英人才。他们拿着固定工资,靠报销单环游全世界。在 1920 年代,驻外记者通常供职于大型报社、广播电台、或者国家级通讯社。当代的驻外记者也可能自由撰稿或 者为电视台、网络通讯社和国际新闻通讯社工作。 这个职业的工作内容五花八门,经常能激动人心。不过博物学灾害、政治动荡和战争也会成为驻外记者报导的主要内容,工作也不总是一帆风 顺。
A60: 58 | B60: 法医 | D60: 40-60 | E60: 教育×4 | F60: =附表!N14*4 -> 260 | G60: 外语（拉丁文），图书馆，医学，说服，科学（生物学，药学，司法科学），侦查。 | K60: 实验室工作人员，执法机构，医护人员。 | M60: 法医是一个高度专门化的职业,大多数法医为市、县或州执法机构工作。工作内容包括尸体解剖,推定死因,并为公诉人提供建议。法医也常常会在刑事审判中出庭提供证言。
A61: 59 | B61: 赌徒 | D61: 8-50 | E61: 教育×2＋外貌或敏捷×2 | F61: =附表!N14*2+MAX(附表!J14*2,附表!K14*2) -> 260 | G61: 会计，技艺（表演），两项社交技能（取悦、话术、恐吓、说服），聆听，心理学，妙手，侦查。 | K61: 其他赌徒，犯罪组织，街头路人。 | M61: 赌徒是罪犯世界里最花哨的一群人。他们衣 着光鲜,不论朴实还是华丽都魅力四射。不论是靠赛马、纸牌游戏还是其他赌博方式,他们总是要凭自己的运气过活。 老练的赌徒会频繁地光顾犯罪组织开设的地 下赌场。少数赌场高手可能经常参加漫长而又一掷千金的豪赌,甚至可能有外部利益集团作为后台。 低级的赌徒则出入于狭窄的小巷,在骰子房 耍弄灌铅的骰子,或者是挤坐在阴暗的台球室里。
A62: 60 | B62: 黑帮-黑帮老大 | D62: 60-95 | E62: 教育×2＋外貌×2 | F62: =附表!N14*2+附表!K14*2 -> 260 | G62: 格斗，射击，法律，聆听，两项社交技能（取悦、话术、恐吓、说服），心理学，侦查。 | K62: 犯罪组织，街头罪犯，警察，地方政府，政治家，法官，工会，律师，同民族的代表。 | M62: 黑帮可能是整个城市、一部分城市的大佬, 也可能只是给这些大佬打工的马仔。马仔们通常 有自己的保护范围,比如监管非法运输和收取保 护费等等。老板总管业务,负责交易,并要就各 种各样的问题给马仔们拿主意。更重要的是,老 板可以各种高人一等,只要能找到马仔或者小弟 去干的事,他基本是不肯污了自己的手去做的。 黑社会在 1920 年代上升为突出的社会问题。本来仅限于在本地收收保护费和管管赌场的外国 裔黑帮,不约而同地发现了贩卖私酒带来的巨大 利润。没过多久,他们就掌控了城市的大片区域, 并在街上和其他黑帮火并。虽然大部分黑帮是按 来源的民族划分——如爱尔兰裔、意大利裔、非 洲裔和犹太裔,黑帮的成员仍然可能是任何民族。 如今,贩毒则取代其他,成为多数黑帮中来 钱最快的犯罪门路。和 1920 年代前辈的工作方法 类似,现在的黑帮老大也需要大量的小弟来负责 保卫、推广、在街道里推行自己的业务。 除去贩私酒和贩毒以外,卖淫、保护、赌博、 腐败等等都是这些犯罪组织的业务范围。
A63: 61 | B63: 黑帮-马仔 | D63: 9-20 | E63: 教育×2＋力量或敏捷×2 | F63: =附表!N14*2+MAX(附表!G14*2,附表!J14*2) -> 310 | G63: 汽车驾驶，格斗，射击，两项社交技能（取悦、话术、恐吓、说服），心理学，任意两项其他个人或时代特长。 | K63: 街头罪犯，警察，企业，同民族的代表。 | M63: 黑帮可能是整个城市、一部分城市的大佬, 也可能只是给这些大佬打工的马仔。马仔们通常 有自己的保护范围,比如监管非法运输和收取保 护费等等。老板总管业务,负责交易,并要就各 种各样的问题给马仔们拿主意。更重要的是,老 板可以各种高人一等,只要能找到马仔或者小弟 去干的事,他基本是不肯污了自己的手去做的。 黑社会在 1920 年代上升为突出的社会问题。本来仅限于在本地收收保护费和管管赌场的外国 裔黑帮,不约而同地发现了贩卖私酒带来的巨大 利润。没过多久,他们就掌控了城市的大片区域, 并在街上和其他黑帮火并。虽然大部分黑帮是按 来源的民族划分——如爱尔兰裔、意大利裔、非 洲裔和犹太裔,黑帮的成员仍然可能是任何民族。 如今,贩毒则取代其他,成为多数黑帮中来 钱最快的犯罪门路。和 1920 年代前辈的工作方法 类似,现在的黑帮老大也需要大量的小弟来负责 保卫、推广、在街道里推行自己的业务。 除去贩私酒和贩毒以外,卖淫、保护、赌博、 腐败等等都是这些犯罪组织的业务范围。
A64: 62 | B64: 绅士、淑女 | D64: 40-90 | E64: 教育×2＋外貌×2 | F64: =附表!N14*2+附表!K14*2 -> 260 | G64: 技艺（任一），两项社交技能（取悦、话术、恐吓、说服），射击（步枪/霰弹枪），历史，外语（任一），导航，骑乘。 | K64: 上流社会和乡绅，政治家，仆人和农民。 | M64: 绅士淑女指的是有良好的教养品行、举止彬彬有礼的人。通常用来称呼上流社会(通过继承 或津贴)拥有相当财富的人。 在上世纪 20 年代,这样的人至少要有一个仆 人(管家、男仆、女仆、私人司机),还要有城 市或乡村的宅第。家庭的富有并不重要,因为家庭的社会地位往往比财产更被上流社会所看重。
A65: 63 | B65: 游民 | D65: 0-5 | E65: 教育×2＋外貌或敏捷×2 | F65: =附表!N14*2+MAX(附表!J14*2,附表!K14*2) -> 260 | G65: 技艺（任一），攀爬，跳跃，聆听，锁匠或妙手，导航，潜行，任意一项其他个人或时代特长。 | K65: 其他游民，少数友好的铁路员工，许多城镇里的好心人。 | M65: 游民只有少数的人愿意去当,虽然失业的人、 醉倒在阴沟里的醉鬼到处都是。和流浪者只会在 必需时才工作不同,游民的工作本身就是流浪。 他们不断地坐火车旅行,从一个城市辗转到 另一个城市,他们是身无分文的诗人、漂泊者, 铁路上的探索者、冒险者和盗贼。但是铁路上的生活一样充满危险。且不说穷困潦倒、无家可归, 还要面对来自警察、周围居民和铁路员工的敌意。另外在深夜中跳车并不是一件容易的事,在跳车的时候被车厢夹断过手脚的人可是不可胜数。
A66: 64 | B66: 勤杂护工 | D66: 6-15 | E66: 教育×2＋力量×2 | F66: =附表!N14*2+附表!G14*2 -> 310 | G66: 电气维修，一项社交技能（取悦、话术、恐吓、说服），格斗（斗殴），急救，聆听，机械维修，心理学，潜行。 | K66: 其他医疗人员，病人。允许接触医疗记录、药品等等。 | M66: 勤杂护工在医院的工作包括倒垃圾、打扫房间、运送病人,还有一些其他乱七八糟的工作。总之对他们的要求不比对看门人多多少。
A67: 65 | B67: 记者(原作向)-调查记者 | D67: 9-30 | E67: 教育×4 | F67: =附表!N14*4 -> 260 | G67: 技艺（艺术或摄影），一项社交技能（取悦、话术、恐吓、说服），历史，图书馆，母语，心理学，任意两项其他个人或时代特长。 | K67: 新闻界，政治家，街头罪犯和执法机构。 | M67: 记者用文字对当天的新闻事件进行报导与评 论,一天之内就要完成一个作家一周的工作量。他们通常为报纸、杂志、广播电台、电视台或者新闻网站撰稿。 优秀的调查记者在报导事件的同时,即使面对丑恶,也能保持自身的清廉正直。恶心的记者则被现实所压倒,最终丧失自己的节操,肆意操纵文字歪曲真相。
A68: 66 | B68: 记者(原作向)-通讯记者 | D68: 9-30 | E68: 教育×4 | F68: =附表!N14*4 -> 260 | G68: 技艺（表演），历史，聆听，母语，一项社交技能（取悦、话术、恐吓、说服），心理学，潜行，侦查。 | K68: 新闻媒体，政治团体与政府，商界，执法机构，街头罪犯，上流社会。 | M68: 通讯记者则是新闻传媒行业大军中的一员, 不管是自由撰稿或是在报社、杂志社、新闻网站、 通讯社工作。大部分记者从事实地工作,包括走 访见证人、查看记录、收集叙述。有些记者被安 排专门追踪警界、体育界或商界的热点新闻,其他人则是负责社会事件乃至园艺俱乐部之类的事情。 通讯记者都会携带记者证,不过记者证除了 各通讯社(主要是报社)用来识别自己的雇员以 外没有太大的作用。实际上记者的工作内容更像 私家侦探,有时为了获得第一手消息也难免使点嘴上花招。
A69: 67 | B69: 法官 | D69: 50-80 | E69: 教育×4 | F69: =附表!N14*4 -> 260 | G69: 历史，恐吓，法律，图书馆，聆听，母语，说服，心理学。 | K69: 法律界，可能有犯罪组织。 | M69: 法官是主持审判全过程的人,可能单独工作或是和同事组成合议庭。一般是推选或任命制, 工作年限也分定期和终身。有的人是初出茅庐就当了法官,而其余的绝大多数,不论是在联邦最高法院还是遥远西部小镇的法官,其实至少都是经过注册的律师。
A70: 68 | B70: 实验室助理 | D70: 10-30 | E70: 教育×4 | F70: =附表!N14*4 -> 260 | G70: 计算机或图书馆，电气维修，外语，科学（化学和任意两项），侦查，任意一项其他个人特长。 | K70: 大学，科学家，图书馆。 | M70: 实验室助理在科研环境中工作,在首席科学家的监督下进行实验和行政工作。 研究内容可能依首席科学家的研究学科而变 化。但基本都包括取样、测试、记录和分析数据、 调整和进行实验、制备标本和样品、管理实验室的日常工作,和保护工作人员的健康与安全。
A71: 69 | B71: 工人-非熟练工人 | D71: 9-30 | E71: 教育×2＋力量或敏捷×2 | F71: =附表!N14*2+MAX(附表!G14*2,附表!J14*2) -> 310 | G71: 汽车驾驶，电气维修，格斗，急救，机械维修，操作重型机械，投掷，任意一项其他个人或时代特长。 | K71: 其他工人和行业主管 | M71: 工人这一大类职业包括工厂工人、纺织工人、 码头工人、养路工人、矿工、建筑工人等等。工人分为两种类型:熟练工和非熟练工。普通的工人虽然技术不熟练,但是仍然长于使用电动工具、 起重机和其他工厂设备。
A72: 70 | B72: 工人-伐木工 | D72: 9-30 | E72: 教育×2＋力量或敏捷×2 | F72: =附表!N14*2+MAX(附表!G14*2,附表!J14*2) -> 310 | G72: 攀爬，闪避，格斗（链锯），急救，跳跃，机械维修，自然或科学（生物学或植物学），投掷。 | K72: 林业工人，野外向导和环境保护者。 | M72: 工人这一大类职业包括工厂工人、纺织工人、 码头工人、养路工人、矿工、建筑工人等等。工人分为两种类型:熟练工和非熟练工。普通的工人虽然技术不熟练,但是仍然长于使用电动工具、 起重机和其他工厂设备。
A73: 71 | B73: 工人-矿工 | D73: 9-30 | E73: 教育×2＋力量或敏捷×2 | F73: =附表!N14*2+MAX(附表!G14*2,附表!J14*2) -> 310 | G73: 攀爬，科学（地质），跳跃，机械维修，操作重型机械，潜行，侦查，任意一项其他个人或时代特长。 | K73: 工会干部，政治团体。 | M73: 工人这一大类职业包括工厂工人、纺织工人、 码头工人、养路工人、矿工、建筑工人等等。工人分为两种类型:熟练工和非熟练工。普通的工人虽然技术不熟练,但是仍然长于使用电动工具、 起重机和其他工厂设备。
A74: 72 | B74: 律师 | D74: 30-80 | E74: 教育×4 | F74: =附表!N14*4 -> 260 | G74: 会计，法律，图书馆，两项社交技能（取悦、话术、恐吓、说服），心理学，两项其他技能。 | K74: 犯罪组织，资本家，检察官和法官。 | M74: 律师或法律顾问精通他们所在地区的法律，擅长把抽象的法学理论知识联系起来，为客户解决法律方面的疑难，担任辩护代理、法律顾问的工作，为客户提供解决办法。可能受托处理个人案件、接受法院指定，也可能专门为某个富裕客户或公司服务。 在美国，“律师”一词一般只指辩护律师。在英国，“律师”一词则包括高级律师、初级律师还有一些执法机构。 假如碰上好客户的话，律师自己也可以一战成名，少数律师还能以自己在政治经济方面的获益吸引媒体的关注。
A75: 73 | B75: 图书馆管理员（原作向） | D75: 9-35 | E75: 教育×4 | F75: =附表!N14*4 -> 260 | G75: 会计，图书馆，外语，母语，任意四项其他个人特长或专业书籍主题。 | K75: 书商，社会团体，专业研究人员。 | M75: 图书馆管理员在公共机构和图书馆工作，负责管理图书目录和书库，并处理图书借阅等。在现代，图书馆管理员还要负责管理视听数据、电子书库。 一些大公司可能聘用图书馆管理员管理书库，偶尔还会有富有的图书藏家招收他们管理自己的私人藏书。
A76: 74 | B76: 技师 | D76: 9-40 | E76: 教育×4 | F76: =附表!N14*4 -> 260 | G76: 技艺（木工、焊接、管道工等），攀爬，汽车驾驶，电气维修，机械维修，操作重型机械，任意两项其他个人或时代或技术特长。 | K76: 工会成员，其他专业技术人员。 | M76: 技师包括所有需要专业训练和作为学徒或实习生工作经验的职业，例如木工、石工、管道工、电气维修、设备安装工人、机修工人等等这些需要技术资质的职业。通常这些工人有自己的工会组织，会和承包人和雇主争取自己的权益。
A77: 75 | B77: 军官 | D77: 20-70 | E77: 教育×2＋力量或敏捷×2 | F77: =附表!N14*2+MAX(附表!G14*2,附表!J14*2) -> 310 | G77: 会计，射击，导航，急救，两项社交技能（取悦、话术、恐吓、说服），心理学，任意一项其他个人或时代特长。 | K77: 部队，联邦政府。 | M77: 军官有严格的等级，许多等级还需要高等教育学历。各国武装部队都建立了人才培养系统，其中包括大学教育。在美国，许多大学开设军校生训练项目，可以让学员同时接受文化教育和军事训练。毕业的学员可以授以陆军或海军少尉军衔，并分派到各驻地。他们通常会为国家服役四年，之后可以退役覆员。许多人有专门的任命，作为医生、律师和工程师工作。 寻求军旅生涯的人会为进入西点军校和美国海军军官学校这样的著名军校而努力，拥有这些名校学历很容易得到其他军官的尊敬。离开学校以后，许多军官也会选择接受飞行训练等特殊训练。 富有经验，特别值得提升的士兵会被破例提拔为一级准尉。虽然在名义上位列最末，获得这一军衔所需要的时间和经验意味着他们远比普通的初中级军官更受尊敬。绝大多数军衔是终身荣誉，退役多年的军官仍然可以自称上尉或者将军。
A78: 76 | B78: 传教士 | D78: 0-30 | E78: 教育×2＋外貌×2 | F78: =附表!N14*2+附表!K14*2 -> 260 | G78: 技艺（任一），急救，机械维修，医学，自然，一项社交技能（取悦、话术、恐吓、说服），任意两项其他个人或时代特长。 | K78: 教会阶层，外国官员。 | M78: 传教士云游到世界的各个角落，传播神的旨意，在文明的地方拯救“不幸的原始人”和“迷途的灵魂”。他们可能属于天主教、新教、伊斯兰教或者其他信仰系统，比如后期圣徒教会(摩门教)在欧美就有专门的传道所。 有的传教士只凭自己的意志独立行动，有的则可能有教会以外的组织支持。 基督教、伊斯兰教的传教者，佛教、印度教的法师，在全世界各个时代都能遇到。
A79: 77 | B79: 登山家 | D79: 30-60 | E79: 教育×2＋力量或敏捷×2 | F79: =附表!N14*2+MAX(附表!G14*2,附表!J14*2) -> 310 | G79: 攀爬，急救，跳跃，聆听，导航，外语，生存（阿尔卑斯或类似），追踪。 | K79: 其他登山者，环境保护者，赞助人，担保人，本地救援队或执法机构，护林员，运动俱乐部。 | M79: 登山家一般都是利用业余时间和假期的运动员，只有少数攀登著名高山的人才会去寻找财力和设备的赞助。 19 世纪登山运动开始兴起，到了1920 年代，所有美洲和阿尔卑斯地区的主要山峰都被一一征服。经过与西藏人的冗长谈判之后，外国登山队终于获准进入喜马拉雅山的高峰地区。作为世界上最后未被征服的高峰，对珠峰的进军经常被电台和报纸报道。不过1921、1922、1924 年的三次远征都没能达到峰顶，还造成了13 人死亡。 到了现代，登山可以是休闲运动或职业选择。如果是后者，则工作内容包括教练、向导、运动员或救生员等。 (译注：1920 年代的登山队都是取道中国境内的北坡，故正是与西藏地方政府进行的商谈。)
A80: 78 | B80: 博物馆管理员 | D80: 10-30 | E80: 教育×4 | F80: =附表!N14*4 -> 260 | G80: 会计，估价，考古，历史，图书馆，神秘学，外语，侦查。 | K80: 本地的大学和学者，出版社，博物馆赞助者。 | M80: 博物馆管理员可能负责大学或其他公共机构的大型设施，也可能负责小一些的博物馆，往往对本地的地质或者其他的内容颇有研究。
A81: 79 | B81: 音乐家 | D81: 9-30 | E81: 教育×2＋意志或敏捷×2 | F81: =附表!N14*2+MAX(附表!M14*2,附表!J14*2) -> 280 | G81: 技艺（乐器），一项社交技能（取悦、话术、恐吓、说服），聆听，心理学，四项其他技能。 | K81: 俱乐部老板，音乐家协会，犯罪组织，街头罪犯。 | M81: 音乐家可能加入乐团、乐队或者独奏，演奏的乐器则可以是任何你能想象的种类。音乐家想出人头地十分困难，签约发布唱片就更难了。所以绝大多数音乐家都贫穷又无人关注，只靠街头卖艺勉强维持生计。少数幸运儿可以找到固定工作，比如在酒吧、宾馆或者市交响乐团弹钢琴。对更少的人来说，在正确的时间出现在正确的地点，再加上一点点天赋，就能获得巨大的成功和可观的财富。 1920 年代是爵士乐的年代，众多的音乐家在美国各地的大中城市、城镇里的爵士乐队和交响乐队工作。少数音乐家住在芝加哥和纽约之类的大城市并在那里打拼，而大部分的人靠巴士、汽车或者火车过着旅行生活。
A82: 80 | B82: 护士 | D82: 9-30 | E82: 教育×4 | F82: =附表!N14*4 -> 260 | G82: 急救，聆听，医学，一项社交技能（取悦、话术、恐吓、说服），心理学，科学（生物学，化学），侦查。 | K82: 护工，医生，小区工作人员。 | M82: 护士是专业的医疗助理，通常在医院和疗养院之类的地方工作，或者和全科医生一起合作。一般来说，护士会协助健康人或病人进行保健或康复活动(或者临终关怀)，虽然其他人若是有足够的力量、意志或者知识，完全不需要护士帮助的康复也是可能的。
A83: 81 | B83: 神秘学家 | D83: 9-65 | E83: 教育×4 | F83: =附表!N14*4 -> 260 | G83: 人类学，历史，图书馆，一项社交技能（取悦、话术、恐吓、说服），神秘学，外语，科学（天文），任意一项其他个人或时代特长 ※经KP允许 可以包含克苏鲁神话 | K83: 图书馆员，神秘学学会或者同好会，其他神秘学家。 | M83: 神秘学家是钻研深奥秘密和神秘魔法的人。他们对超博物学能力深信不疑，并竭尽所能靠他们的能力去了解这些东西。许多人对不同神秘哲学和魔法理论的知识面都相当广泛，有些甚至相信自己专注研究三十年真的成为了魔法师——到底是真是假就交由KP 来决断了。 需要指出的是，神秘学家熟知的基本上是“表面的魔法”——克苏鲁神话魔法的秘密对他们仍然是未知的，或者不过是古书上描述那些诱人的线索而已。
A84: 82 | B84: 旅行家 | D84: 5-20 | E84: 教育×2＋力量或敏捷×2 | F84: =附表!N14*2+MAX(附表!G14*2,附表!J14*2) -> 310 | G84: 射击，急救，聆听，自然，导航，侦查，生存（任一），追踪。 | K84: 本地居民，土著，贸易商。 | M84: 旅行家爱好户外，他们一年中大部分时间都呆在户外，并且一出门就是相当长的时间；通常有相当的捕鱼和狩猎技术，能在最恶劣的环境之中幸存下来。擅长的技术可能包括登山、捕鱼、滑雪、皮划艇、攀登和露营。 旅行家可能在国家公园或素质拓展中心做野外向导和护林员，也可能是有其他经济来源能让他们不用工作就能以这种方式生活，说不定还可能是一个隐士，只有在需要的时候才会回到文明社会。
A85: 83 | B85: 超心理学家 | D85: 9-30 | E85: 教育×4 | F85: =附表!N14*4 -> 260 | G85: 人类学，技艺（摄影），历史，图书馆，神秘学，外语，心理学，任意一项其他个人或时代特长。 | K85: 大学，超心理学刊物。 | M85: 超心理学家从不打算欣赏超常现象。相反，他们试图去观察，记录并研究这些实例。被叫做“捉鬼人”的他们利用技术手段来获取某人或某地点的超博物学活动的证据，当然比起收集到实在的证据，更多的时候他们是在揭穿假冒和误认的超常现象。 一些超心理学家专门研究特定的现象，例如超感官、心灵致动、闹鬼等等。 名牌大学是没有超心理学学位的。这个领域成就的评判标准完全是基于个人声誉，所以一般有相近学科学历比如物理学、心理学和医学的人会比较有说服力。 选择研究这个的人往往对不可视的神秘力量抱有相当的同情态度，并希望其他的科学家也能满意地点头肯定。这就表现出了一种既相信又怀疑的奇异的迭加态——恐怕超心理学家自己也难解决这个问题。一个对观察实验证明不感兴趣的人是个神秘学家而不是个科学家。
A86: 84 | B86: 药剂师 | D86: 35-75 | E86: 教育×4 | F86: =附表!N14*4 -> 260 | G86: 会计，急救，外语（拉丁文），图书馆，一项社交技能（取悦、话术、恐吓、说服），心理学，科学（制药，化学）。 | K86: 本地小区，本地医生，医院和病人。能获得各种药品和化学品。 | M86: 药剂师的管理一直以来都比医生更严格。所有的药剂师都要在各州注册，注册的条件则是高中毕业并至少在药学院学习三年。他们可能在医院或者药房工作，也可能自己开药房。
A87: 85 | B87: 摄影师-摄影师 | D87: 9-30 | E87: 教育×4 | F87: =附表!N14*4 -> 260 | G87: 技艺（摄影），一项社交技能（取悦、话术、恐吓、说服），心理学，科学（化学），潜行，侦查，任意两项其他个人或时代特长。 | K87: 广告业，本地客户(包括政治团体和报纸)。 | M87: 摄影师大部分是自由工作者，可能制作广告电影或者在照相馆做肖像拍摄。其他一些摄像师则在报纸、电视和电影产业工作。 摄影作为一种艺术形式已经产生相当长的时间了，精英的摄影师可以从艺术、新闻报道、野生动物保护等多种角度出发创作他们的作品。不管是哪种立意，他们都能获得名誉和报酬。 摄影记者本质上就是拿照相机，为拍摄的照片写配文的记者。在1920 年代，新闻短片走上历史舞台。笨重的35mm 摄像装备走遍全球各地，搜寻有价值的新闻轶事、体育赛事和泳装选美比赛。新闻片制作人员一般分为三类：一类是画面中的记者，另两个人则负责摄像和灯光等等。新闻中的声音则是在新闻稿完成以后在录音棚中录入完成的。
A88: 86 | B88: 摄影师-摄影记者 | D88: 10-30 | E88: 教育×4 | F88: =附表!N14*4 -> 260 | G88: 技艺（摄影），攀爬，一项社交技能（取悦、话术、恐吓、说服），外语，心理学，科学（化学），任意两项其他个人或时代特长。 | K88: 新闻业，电影工作室(1920 年代)，外国政府和官方。 | M88: 摄影师大部分是自由工作者，可能制作广告电影或者在照相馆做肖像拍摄。其他一些摄像师则在报纸、电视和电影产业工作。 摄影作为一种艺术形式已经产生相当长的时间了，精英的摄影师可以从艺术、新闻报道、野生动物保护等多种角度出发创作他们的作品。不管是哪种立意，他们都能获得名誉和报酬。 摄影记者本质上就是拿照相机，为拍摄的照片写配文的记者。在1920 年代，新闻短片走上历史舞台。笨重的35mm 摄像装备走遍全球各地，搜寻有价值的新闻轶事、体育赛事和泳装选美比赛。新闻片制作人员一般分为三类：一类是画面中的记者，另两个人则负责摄像和灯光等等。新闻中的声音则是在新闻稿完成以后在录音棚中录入完成的。
A89: 87 | B89: 飞行员-飞行员 | D89: 20-70 | E89: 教育×2＋敏捷×2 | F89: =附表!N14*2+附表!J14*2 -> 210 | G89: 电气维修，机械维修，导航，操作重型机械，驾驶（飞行器），科学（天文），任意两项其他个人或时代特长。 | K89: 前部队关系人，乘务员，机械师，机场地勤人员，嘉年华主办者。 | M89: 飞行员可以在美国邮政这样的企业工作，也可以在大大小小的民航公司做飞行人员。 美国1926 年之前没有对飞行员的职业要求，1926 年航空商业法案通过之后才要求有执照。这个时代的多数飞行员从事嘉年华表演、特技飞行表演、乘飞机游玩或是小机场的空中的士等服务。 也有飞行员在部队服现役。许多特技飞行员是在服役期间学会的驾驶飞机，有时仍然会被军队委派任务。
A90: 88 | B90: 飞行员-特技飞行员（古典） | D90: 30-60 | E90: 教育×4 | F90: =附表!N14*4 -> 260 | G90: 会计，电气维修，聆听，机械维修，导航，驾驶（飞行器），侦查，任意一项其他个人或时代特长。 | K90: 前部队关系人，其他飞行员，机场地勤技术人员，商人。 | M90: 特技飞行员在嘉年华工作或者为大胆的消费者进行休闲飞行服务。参加有组织的飞行表演赛，不论是固定路线还是越野赛，往往都可以增加自己的知名度。在1920 年代，好莱坞常常使用特技飞行员，飞机制造商也会录用一些飞行员为新机作测试。许多特技飞行员是在一次大战中掌握的飞行技术，所以许多人仍然在陆海空军或海岸警卫队服役；年轻的飞行员则基本上是在和平时期接受的训练或是自学成才。 参加过一战的王牌飞行员“现在”还活跃在公众视野中的包括：埃迪·里肯巴克，现在在克赖斯勒公司工作；汤米·希区柯克，“现在”是马球赛场的明星；里德·兰迪斯，美国职棒大联盟执行长凯纳索·蒙顿·兰迪斯的儿子。
A91: 89 | B91: 警方(原作向)-警探 | D91: 20-50 | E91: 教育×2＋力量或敏捷×2 | F91: =附表!N14*2+MAX(附表!G14*2,附表!J14*2) -> 310 | G91: 技艺（表演）或乔装，射击，法律，聆听，一项社交技能（取悦、话术、恐吓、说服），心理学，侦查，一项其他技能。 | K91: 执法机构，街头罪犯，尸检部门，司法部门，犯罪组织。 | M91: 便衣警察的工作是检查犯罪现场、收集证据、询问证人以解决凶杀、盗窃等重大案件。他们在现场办案中往往与穿制服的巡警密切合作。 警探可能指挥他的下属进行详尽的调查，但是很难有机会集中精力对付单独一个事件，在美国他们很可能要同时处理数十乃至上百的案件。警探工作最关键的部分是通过梳理证词、重建现场情况，摒弃伪证，从而收集足够逮捕嫌疑人的证据，进而促成成功的刑事审判。警探和检察官的职责是分开的，这样可以保证证据在审判之前被独立地对待。 尽管现在警探通常会参加警察学校课程并获得学位、参加特殊训练或公务员培训，他们最主要的经验还是来源于担任基层警官或者普通巡警时的工作经历。
A92: 90 | B92: 警方(原作向)-巡警 | D92: 9-30 | E92: 教育×2＋力量或敏捷×2 | F92: =附表!N14*2+MAX(附表!G14*2,附表!J14*2) -> 310 | G92: 格斗（斗殴），射击，急救，一项社交技能（取悦、话术、恐吓、说服），法律，心理学，侦查和下面的一种个人特长：汽车驾驶或骑乘。 | K92: 执法机构，本地企业与居民，街头罪犯，犯罪组织。 | M92: 巡警属于市、城镇、县治安部门或州、地区的警察机关。他们工作时可能步行、驾驶巡逻车，或者干脆坐办公室。
A93: 91 | B93: 私家侦探 | D93: 9-30 | E93: 教育×2＋力量或敏捷×2 | F93: =附表!N14*2+MAX(附表!G14*2,附表!J14*2) -> 310 | G93: 技艺（摄影），乔装，法律，图书馆，一项社交技能（取悦、话术、恐吓、说服），心理学，侦查，一项其他个人或时代特长（如计算机、锁匠、格斗、射击）。 | K93: 执法机构，客户。 | M93: 私家侦探通常在警察不出手的地方活跃，包括收集证据为客户准备民事诉讼，追查跑路的配偶或生意伙伴，或者代理刑事案件的私人辩护。他们和任何专业人员一样，私家侦探从不顾及自己的私人情感，只要付钱，不管是有罪还是无罪的一方的委托他们都乐得接受。 私家侦探过去可能在警察队伍里工作，利用以前的业务关系为现在工作谋求优势；然而事实并非总是如此。在许多地方私家侦探必须持证上岗，假如被发现有违法行为，就会撤销执照——侦探生涯也就到此为止。
A94: 92 | B94: 教授（原作向） | D94: 20-70 | E94: 教育×4 | F94: =附表!N14*4 -> 260 | G94: 图书馆，外语，母语，心理学，任意四项其他学术、时代或个人特长。 | K94: 学者，大学，图书馆。 | M94: 教授是受聘于高等院校的学者。大公司也可 能聘请他们以开展学术研究与产品开发。独立的学者也靠开办业余课程作为经济来源。 最重要的一点,这一职业代表了 PhD(博士) 的荣誉称号,意味着可以在世界各地的大学任终身教职。教授的专长是教学和专业研究,往往在自己的专业领域内有着可圈可点的学术成就。
A95: 93 | B95: 淘金客 | D95: 0-10 | E95: 教育×2＋力量或敏捷×2 | F95: =附表!N14*2+MAX(附表!G14*2,附表!J14*2) -> 310 | G95: 攀爬、急救、历史、机械维修、导航、科学（地质），侦查，任意一项其他个人或时代特长。 | K95: 本地企业和居民。 | M95: 淘金客一直是美国西部的特色,即便在加利福尼亚淘金热和内华达康姆斯塔克发现金银矿的日子早已经过去的现在。他们无休止地在山间漫游,寻找能使自己一夜暴富的矿脉。而且现在发现石油和发现金子一样给力。
A96: 94 | B96: 性工作者 | D96: 5-50 | E96: 教育×2＋外貌×2 | F96: =附表!N14*2+附表!K14*2 -> 260 | G96: 技艺（任一），两项社交技能（取悦、话术、恐吓、说服），闪避，心理学，妙手，潜行，任意一项其他个人或时代特长。 | K96: 街头路人，警察，可能有犯罪组织，私人客户。 | M96: 性工作者根据场合、背景和教养,从超级值钱的应召小姐到牛郎再到站街女都有可能。往往入这一行都是权宜之计,许多人梦想有朝一日能够脱身。少数人能够自己接客,不过绝大多数人 基本都是被只认钱不认人的老鸨和皮条客逼迫着 工作。
A97: 95 | B97: 精神病学家 | D97: 30-80 | E97: 教育×4 | F97: =附表!N14*4 -> 260 | G97: 外语，聆听，医学，说服，精神分析，心理学，科学（生物学，化学）。 | K97: 其他精神疾病领域的专家，医生，可能有法律人士。 | M97: 精神病学家是在现代专门从事精神失常诊断和治疗的医生。精神病学家掌握着精神药理学的 治疗方法,使用精神类药物的资质,还能整理脑电图并对其进行计算器分析。 在十九二十世纪之交,精神分析理论刚刚产 生,试图解释一些现在认为实际上是生物学范畴的现象。所以,精神分析学家们努力寻求获得自 己的医疗证书。与此同时,各种不同的精神失常诊断与治疗理论开始起步。到 1930 年代,任何一个医生都可以以精神病学家的身份进入美国医学协会名录中了。
A98: 96 | B98: 心理学家、精神分析学家 | D98: 10-40 | E98: 教育×4 | F98: =附表!N14*4 -> 260 | G98: 会计，图书馆，聆听，说服，精神分析，心理学，任意两项其他学术、个人或时代特长。 | K98: 心理学家团体，病人。 | M98: 心理学家虽然也经常被叫做心理治疗师和心理咨询师,不过这些工作都只是心理学的分支。其他的还有为企业和政府提供顾问的组织管理心 理学家,进行研究并在学校教授心理学的学术型心理学家等等。 临床心理学家可能实际接触病人,并且运用各种可能的心理治疗方法。注意心理学家和专业的精神病学家的区别,后者本质上还是医生。 在1920 年代,对人类行为的研究还是一个新兴的领域,主要的理论还是弗洛伊德心理学。
A99: 97 | B99: 研究员 | D99: 9-30 | E99: 教育×4 | F99: =附表!N14*4 -> 260 | G99: 历史，图书馆，一项社交技能（取悦、话术、恐吓、说服），外语，侦查，任意三项其他学术领域。 | K99: 学者和其他学术界人士，大型企业，外国政府和个人。 | M99: 学术界的研究课题不计其数,尤其是在天文 学、物理学和其他理论领域。私人或企业也雇用 了成千上万的研究员,重点在化学、制药和工程 领域。石油公司则会聘用专业的地质学家,不一 而足。研究员大部分的时间都在室内工作和写作, 不过有的则会经常外出考察。 考察研究员通常经验丰富,思想独立又足智 多谋,可能受雇于私人或者为大学进行学术研究。 石油公司会派出地质学家探索潜在的油田, 人类学家则是调查地球被人遗忘角落的原始部落, 考古学家则竭数年之力挖掘沙漠丛林之中的宝藏, 还要和工人与地方政府打交道。
A100: 98 | B100: 海员-军舰海员 | D100: 9-30 | E100: 教育×4 | F100: =附表!N14*4 -> 260 | G100: 电工或机械维修，格斗，射击，急救，导航，驾驶（船），生存（海上），游泳。 | K100: 军队，退伍军人协会。 | M100: 新入伍的海员像陆军的同行一样,开始时需 要接受基本的训练。这之后他们获得军衔,并被 分配到各镇守府。虽然很多海员担任像水手长副手和司炉工(管理引擎)这样的传统角色,但是也有很多经过专门训练的机械师、无线电操作员、通风管理员之类。海员们最高的军衔是士官长, 达到了这个军衔连高级将领都要礼让三分。在美国,海员通常要服四年的现役和后两年的后备役, 即在国家发布动员令时有应召服役的义务。
...

Sheet 成长表（测试）
B1: 技能成长表
A2: 技能 | B2: 总计成长 | C2: 初始 | D2: 请填入模组名称 | E2: 模组2 | F2: 模组3 | G2: 模组4 | H2: 模组5 | I2: 模组6 | J2: 模组7 | K2: 模组8 | L2: 模组9 | M2: 模组10 | N2: 模组11 | O2: 模组12 | P2: 模组13 | Q2: 模组14 | R2: 模组15 | S2: 模组16 | T2: 模组17 | U2: 模组18 | V2: 模组19 | W2: 模组20 | X2: 模组21 | Y2: 模组22 | Z2: 模组23 | AA2: 模组24 | AB2: 模组25 | AC2: 模组26 | AD2: 模组27 | AE2: 模组28 | AF2: 模组29 | AG2: 模组30 | AH2: 模组31 | AI2: 模组32 | AJ2: 模组33 | AK2: 模组34 | AL2: 模组35 | AM2: 模组36 | AN2: 模组37 | AO2: 模组38 | AP2: 模组39 | AQ2: 模组40 | AR2: 模组41 | AS2: 模组42 | AT2: 模组43 | AU2: 模组44 | AV2: 模组45 | AW2: 模组46 | AX2: 模组47 | AY2: 模组48 | AZ2: 模组49 | BA2: 模组50 | BB2: 模组51 | BC2: 模组52 | BD2: 模组53 | BE2: 模组54 | BF2: 模组55 | BG2: 模组56 | BH2: 模组57 | BI2: 模组58 | BJ2: 模组59 | BK2: 模组60 | BL2: 模组61 | BM2: 模组62 | BN2: 模组63 | BO2: 模组64 | BP2: 模组65 | BQ2: 模组66 | BR2: 模组67 | BS2: 模组68 | BT2: 模组69 | BU2: 模组70 | BV2: 模组71 | BW2: 模组72 | BX2: 模组73 | BY2: 模组74 | BZ2: 模组75 | CA2: 模组76 | CB2: 模组77 | CC2: 模组78 | CD2: 模组79 | CE2: 模组80 | CF2: 模组81 | CG2: 模组82 | CH2: 模组83 | CI2: 模组84 | CJ2: 模组85 | CK2: 模组86 | CL2: 模组87 | CM2: 模组88 | CN2: 模组89 | CO2: 模组90 | CP2: 模组91 | CQ2: 模组92 | CR2: 模组93 | CS2: 模组94 | CT2: 模组95 | CU2: 模组96 | CV2: 模组97 | CW2: 模组98 | CX2: 模组99 | CY2: 模组100
A3: 会计 | B3: =SUM(D3:CY3) -> 0 | C3: 5 | D3: 请填入成长数值
A4: 人类学 | B4: =SUM(D4:CY4) -> 0 | C4: 1 | D4: 后面依次类推哦
A5: 估价 | B5: =SUM(D5:CY5) -> 0 | C5: 5 | D5: 0
A6: 考古学 | B6: =SUM(D6:CY6) -> 1 | C6: 1 | D6: 1
A7: 技艺① | B7: =SUM(D7:CY7) -> 2 | C7: 5 | D7: 2
A8: 技艺② | B8: =SUM(D8:CY8) -> 0 | C8: 5 | D8: 以上这些是示例
A9: 技艺③ | B9: =SUM(D9:CY9) -> 0 | C9: 5
A10: 取悦 | B10: =SUM(D10:CY10) -> 0 | C10: 15
A11: 攀爬 | B11: =SUM(D11:CY11) -> 0 | C11: 20
A12: 计算机使用 Ω | B12: =SUM(D12:CY12) -> 0 | C12: 5
A13: 信用评级 | B13: =SUM(D13:CY13) -> 0 | C13: 0
A14: 克苏鲁神话 | B14: =SUM(D14:CY14) -> 0 | C14: 0
A15: 乔装 | B15: =SUM(D15:CY15) -> 0 | C15: 5
A16: 闪避 | B16: =SUM(D16:CY16) -> 0 | C16: 0
A17: 汽车驾驶 | B17: =SUM(D17:CY17) -> 0 | C17: 20
A18: 电气维修 | B18: =SUM(D18:CY18) -> 0 | C18: 10
A19: 电子学 Ω | B19: =SUM(D19:CY19) -> 0 | C19: 1
A20: 话术 | B20: =SUM(D20:CY20) -> 0 | C20: 5
... A68: 学识： | B68: =SUM(D68:CY68) -> 0 | C68: 1
A69: 自定义技能 | B69: =SUM(D69:CY69) -> 0
A70: 自定义技能 | B70: =SUM(D70:CY70) -> 0
A71: STR | B71: =SUM(D71:CY71) -> 0
A72: CON | B72: =SUM(D72:CY72) -> 0
A73: SIZ | B73: =SUM(D73:CY73) -> 0
A74: DEX | B74: =SUM(D74:CY74) -> 0
A75: APP | B75: =SUM(D75:CY75) -> 0
A76: INT | B76: =SUM(D76:CY76) -> 0
A77: POW | B77: =SUM(D77:CY77) -> 0
A78: EDU | B78: =SUM(D78:CY78) -> 0
A79: 幸运 | B79: =SUM(D79:CY79) -> 0
A80: 理智 | B80: =SUM(D80:CY80) -> 0
B81: =SUM(D81:CY81) -> 0
B82: =SUM(D82:CY82) -> 0
B83: =SUM(D83:CY83) -> 0
B84: =SUM(D84:CY84) -> 0
B85: =SUM(D85:CY85) -> 0
B86: =SUM(D86:CY86) -> 0
B87: =SUM(D87:CY87) -> 0
B88: =SUM(D88:CY88) -> 0
B89: =SUM(D89:CY89) -> 0
B90: =SUM(D90:CY90) -> 0
B91: =SUM(D91:CY91) -> 0
B92: =SUM(D92:CY92) -> 0
... B100: =SUM(D100:CY100) -> 0

Sheet 本职技能
B1: 0 | C1: 1 | D1: 2 | E1: 3 | F1: 4 | G1: 5 | H1: 6 | I1: 7 | J1: 8 | K1: 9 | L1: 10 | M1: 11 | N1: 12 | O1: 13 | P1: 14 | Q1: 15 | R1: 16 | S1: 17 | T1: 18 | U1: 19 | V1: 20 | W1: 21 | X1: 22 | Y1: 23 | Z1: 24 | AA1: 25 | AB1: 26 | AC1: 27 | AD1: 28 | AE1: 29 | AF1: 30 | AG1: 31 | AH1: 32 | AI1: 33 | AJ1: 34 | AK1: 35 | AL1: 36 | AM1: 37 | AN1: 38 | AO1: 39 | AP1: 40 | AQ1: 41 | AR1: 42 | AS1: 43 | AT1: 44 | AU1: 45 | AV1: 46 | AW1: 47 | AX1: 48 | AY1: 49 | AZ1: 50 | BA1: 51 | BB1: 52 | BC1: 53 | BD1: 54 | BE1: 55 | BF1: 56 | BG1: 57 | BH1: 58 | BI1: 59 | BJ1: 60 | BK1: 61 | BL1: 62 | BM1: 63 | BN1: 64 | BO1: 65 | BP1: 66 | BQ1: 67 | BR1: 68 | BS1: 69 | BT1: 70 | BU1: 71 | BV1: 72 | BW1: 73 | BX1: 74 | BY1: 75 | BZ1: 76 | CA1: 77 | CB1: 78 | CC1: 79 | CD1: 80 | CE1: 81 | CF1: 82 | CG1: 83 | CH1: 84 | CI1: 85 | CJ1: 86 | CK1: 87 | CL1: 88 | CM1: 89 | CN1: 90 | CO1: 91 | CP1: 92 | CQ1: 93 | CR1: 94 | CS1: 95 | CT1: 96 | CU1: 97 | CV1: 98 | CW1: 99 | CX1: 100 | CY1: 101 | CZ1: 102 | DA1: 103 | DB1: 104 | DC1: 105 | DD1: 106 | DE1: 107 | DF1: 108 | DG1: 109 | DH1: 110 | DI1: 111 | DJ1: 112 | DK1: 113 | DL1: 114 | DM1: 115 | DN1: 116 | DO1: 117 | DP1: 118 | DQ1: 119 | DR1: 120 | DS1: 121 | DT1: 122 | DU1: 123 | DV1: 124 | DW1: 125 | DX1: 126 | DY1: 127 | DZ1: 128 | EA1: 129 | EB1: 130 | EC1: 131 | ED1: 132 | EE1: 133 | EF1: 134 | EG1: 135 | EH1: 136 | EI1: 137 | EJ1: 138 | EK1: 139 | EL1: 140 | EM1: 141 | EN1: 142 | EO1: 143 | EP1: 144 | EQ1: 145 | ER1: 146 | ES1: 147 | ET1: 148 | EU1: 149 | EV1: 150 | EW1: 151 | EX1: 152 | EY1: 153 | EZ1: 154 | FA1: 155 | FB1: 156 | FC1: 157 | FD1: 158 | FE1: 159 | FF1: 160 | FG1: 161 | FH1: 162 | FI1: 163 | FJ1: 164 | FK1: 165 | FL1: 166 | FM1: 167 | FN1: 168 | FO1: 169 | FP1: 170 | FQ1: 171 | FR1: 172 | FS1: 173 | FT1: 174 | FU1: 175 | FV1: 176 | FW1: 177 | FX1: 178 | FY1: 179 | FZ1: 180 | GA1: 181 | GB1: 182 | GC1: 183 | GD1: 184 | GE1: 185 | GF1: 186 | GG1: 187 | GH1: 188 | GI1: 189 | GJ1: 190 | GK1: 191 | GL1: 192 | GM1: 193 | GN1: 194 | GO1: 195 | GP1: 196 | GQ1: 197 | GR1: 198 | GS1: 199 | GT1: 200 | GU1: 201 | GV1: 202 | GW1: 203 | GX1: 204 | GY1: 205 | GZ1: 206 | HA1: 207 | HB1: 208 | HC1: 209 | HD1: 210 | HE1: 211 | HF1: 212 | HG1: 213 | HH1: 214 | HI1: 215 | HJ1: 216 | HK1: 217 | HL1: 218 | HM1: 219 | HN1: 220 | HO1: 221 | HP1: 222 | HQ1: 223 | HR1: 224 | HS1: 225 | HT1: 226 | HU1: 227 | HV1: 228 | HW1: 229 | HX1: 230
C2: 自定义职业 | D2: 会计师 | E2: 杂技演员 | F2: 演员-戏剧演员 | G2: 演员-电影演员 | H2: 事务所侦探 | I2: 精神病医生（古典） | J2: 动物训练师 | K2: 文物学家（原作向） | L2: 古董商 | M2: 考古学家（原作向） | N2: 建筑师 | O2: 艺术家 | P2: 精神病院看护 | Q2: 运动员 | R2: 作家（原作向） | S2: 酒保 | T2: 猎人 | U2: 书商 | V2: 赏金猎人 | W2: 拳击手、摔跤手 | X2: 管家、男仆、女仆 | Y2: 神职人员 | Z2: 程序员、电子工程师（现代） | AA2: 黑客/骇客（现代） | AB2: 牛仔 | AC2: 工匠 | AD2: 罪犯-刺客 | AE2: 罪犯-银行劫匪 | AF2: 罪犯-打手、暴徒 | AG2: 罪犯-窃贼 | AH2: 罪犯-欺诈师 | AI2: 罪犯-独行罪犯 | AJ2: 罪犯-女飞贼（古典） | AK2: 罪犯-赃物贩子 | AL2: 罪犯-赝造者 | AM2: 罪犯-走私者 | AN2: 罪犯-混混 | AO2: 教团首领 | AP2: 除魅师（现代） | AQ2: 设计师 | AR2: 业余艺术爱好者（原作向） | AS2: 潜水员 | AT2: 医生（原作向） | AU2: 流浪者 | AV2: 司机-私人司机 | AW2: 司机-司机 | AX2: 司机-出租车司机 | AY2: 编辑 | AZ2: 政府官员 | BA2: 工程师 | BB2: 艺人 | BC2: 探险家（古典） | BD2: 农民 | BE2: 联邦探员 | BF2: 消防员 | BG2: 驻外记者 | BH2: 法医 | BI2: 赌徒 | BJ2: 黑帮-黑帮老大 | BK2: 黑帮-马仔 | BL2: 绅士、淑女 | BM2: 游民 | BN2: 勤杂护工 | BO2: 记者(原作向)-调查记者 | BP2: 记者(原作向)-通讯记者 | BQ2: 法官 | BR2: 实验室助理 | BS2: 非熟练工人 | BT2: 工人-伐木工 | BU2: 工人-矿工 | BV2: 律师 | BW2: 图书馆管理员（原作向） | BX2: 技师 | BY2: 军官 | BZ2: 传教士 | CA2: 登山家 | CB2: 博物馆管理员 | CC2: 音乐家 | CD2: 护士 | CE2: 神秘学家 | CF2: 旅行家 | CG2: 超心理学家 | CH2: 药剂师 | CI2: 摄影师-摄影师 | CJ2: 摄影师-摄影记者 | CK2: 飞行员-飞行员 | CL2: 飞行员-特技飞行员（古典） | CM2: 警方(原作向)-警探 | CN2: 警方(原作向)-巡警 | CO2: 私家侦探 | CP2: 教授（原作向） | CQ2: 淘金客 | CR2: 性工作者 | CS2: 精神病学家 | CT2: 心理学家、精神分析学家 | CU2: 研究员 | CV2: 海员-军舰海员 | CW2: 海员-民船海员 | CX2: 推销员 | CY2: 科学家 | CZ2: 秘书 | DA2: 店老板 | DB2: 士兵、海军陆战队士兵 | DC2: 间谍 | DD2: 学生、实习生 | DE2: 替身演员 | DF2: 部落成员 | DG2: 殡葬师 | DH2: 工会活动家 | DI2: 服务生 | DJ2: 白领工人-职员、主管 | DK2: 白领工人-中高层管理人员 | DL2: 狂热者 | DM2: 饲养员 | DN2: 大使 | DO2: 运动员（游泳/潜水） | DP2: 运动员（高尔夫） | DQ2: 运动员（网球） | DR2: 运动员（田径） | DS2: 发言人 | DT2: 保释担保人 | DU2: 神职人员(天主教牧师) | DV2: 神职人员(新教牧师) | DW2: 神职人员(犹太教拉比) | DX2: 专栏作家 | DY2: 社会主义者/激进主义者 | DZ2: 撰稿人 | EA2: 罪犯（赌博庄家） | EB2: 罪犯（放高利贷者） | EC2: 罪犯（扒手） | ED2: 罪犯（地下钱庄） | EE2: 罪犯（黑律师） | EF2: 牙医 | EG2: 外科医生/内科医生 | EH2: 整形医生 | EI2: 司机-公交司机 | EJ2: 实地调研员 | EK2: 电影摄制人员 | EL2: 司法家 | EM2: 运动经理 | EN2: 商船队船员 | EO2: 古典音乐家 | EP2: 赛车手/赛艇手 | EQ2: 电台播音员 | ER2: 推销员（圣经推销员） | ES2: 推销员（旅行推销员） | ET2: 小企业家 | EU2: 舞台工作人员 | EV2: 证券经纪人 | EW2: 勘测员 | EX2: 电话接线员 | EY2: 星探 | EZ2: 医疗技术员 | FA2: 队医 | FB2: 寻宝猎人 | FC2: 西部治安官 | FD2: 暴走族 | FE2: 神职人员(和尚,尼姑) | FF2: 神职人员(神官,巫女) | FG2: 风水师 | FH2: 家传降妖人 | FI2: 高中生(教育60以下) | FJ2: 市子（盲人） | FK2: 言灵师/阴阳师 | FL2: 炼丹师 | FM2: 外语教师 | FN2: 非法移民 | FO2: 相扑力士(SIZ>80,STR>70) | FP2: 渔民 | FQ2: 心理治疗师 | FR2: 女学生 | FS2: 寄居学生 | FT2: 动物辅助治疗师 | FU2: 急诊医生/救援队员 | FV2: 密医 | FW2: 科学搜查研究员 | FX2: 山岳救援队员 | FY2: 舞者 | FZ2: 服装设计师 | GA2: 海上自卫队员 | GB2: 海警 | GC2: 陆上自卫队员 | GD2: 私人军事公司成员 | GE2: 冒险家教授 | GF2: 评论家 | GG2: 偶像 | GH2: 歌手 | GI2: 搞笑艺人 | GJ2: 运动员艺人 | GK2: 播音员 | GL2: 主持人 | GM2: 电视解说员 | GN2: 网络明星 | GO2: 经纪人 | GP2: 捉鬼人 | GQ2: 占卜师、灵媒师 | GR2: 机械师 | GS2: 厨师 | GT2: 网络犯罪者 | GU2: 佣兵 | GV2: 自宅警备员 | GW2: 壮汉保镖 | GX2: 游戏测试员 | GY2: 交际花 | GZ2: 考古学家 | HA2: 贵族 | HB2: 艺术家 | HC2: 作家 | HD2: 马车夫 | HE2: 牧师 | HF2: 咨询侦探 | HG2: 工匠 | HH2: 罪犯 | HI2: 业余艺术爱好者 | HJ2: 艺人 | HK2: 退役军官 | HL2: 探险家 | HM2: 私家侦探 | HN2: 记者 | HO2: 劳工 | HP2: 律师 | HQ2: 医生 | HR2: 警察 | HS2: 教授/学者 | HT2: 科学家 | HU2: 佣人 | HV2: 店主 | HW2: 士兵 | HX2: 密探
A3: ☆ | M3: 1 | N3: 1 | O3: 1 | R3: 1 | T3: 1 | V3: 1 | X3: 1 | AB3: 1 | AE3: 1 | AG3: 1 | AH3: 1 | AI3: 1 | AJ3: 1 | AM3: 1 | AP3: 1 | AQ3: 1 | BC3: 1 | BM3: 1 | BR3: 1 | BT3: 1 | CM3: 1 | CN3: 1 | CV3: 1 | CX3: 1 | CY3: 1 | CZ3: 1 | DB3: 1 | DC3: 1 | DD3: 1 | DE3: 1 | DF3: 1 | DJ3: 1 | EJ3: 1 | EN3: 1 | ER3: 1 | FB3: 1 | FC3: 1 | FE3: 1 | FI3: 1 | FJ3: 1 | FL3: 1 | FZ3: 1 | GC3: 1 | GD3: 1 | GE3: 1 | GF3: 1 | GU3: 1 | GW3: 1 | GY3: 1 | HK3: 1
A4: ⊙ | T4: 1 | V4: 1 | AB4: 1 | AI4: 1 | CZ4: 1
A5: ☯ | F5: 2 | G5: 2 | H5: 1 | K5: 1 | L5: 2 | O5: 1 | P5: 2 | Q5: 1 | S5: 2 | U5: 1 | V5: 1 | Y5: 1 | AA5: 1 | AF5: 2 | AH5: 2 | AI5: 1 | AJ5: 2 | AK5: 1 | AM5: 1 | AN5: 1 | AO5: 2 | AP5: 2 | AR5: 2 | AU5: 1 | AV5: 2 | AW5: 1 | AY5: 2 | BB5: 2 | BD5: 1 | BG5: 2 | BI5: 2 | BJ5: 2 | BK5: 2 | BL5: 2 | BN5: 1 | BO5: 1 | BP5: 1 | BV5: 2 | BY5: 2 | BZ5: 1 | CC5: 1 | CD5: 1 | CE5: 1 | CH5: 1 | CI5: 1 | CJ5: 1 | CM5: 1 | CO5: 1 | CR5: 2 | CU5: 1 | CW5: 1 | CX5: 2 | CY5: 1 | CZ5: 2 | DA5: 2 | DC5: 1 | DG5: 1 | DH5: 2 | DI5: 2 | DJ5: 1 | DK5: 2 | DL5: 2 | DO5: 1 | DP5: 1 | DQ5: 1 | DR5: 1 | DS5: 3 | DT5: 2 | DU5: 1 | DV5: 1 | DW5: 1 | DX5: 1 | DY5: 2 | DZ5: 2 | EA5: 2 | EB5: 2 | EC5: 1 | EE5: 2 | EI5: 1 | EJ5: 1 | EK5: 1 | EM5: 2 | EO5: 1 | ER5: 2 | ES5: 2 | ET5: 2 | EU5: 2 | EV5: 2 | EX5: 2 | EY5: 2 | FA5: 2 | FB5: 1 | FE5: 1 | FF5: 1 | FG5: 1 | FM5: 2 | FQ5: 2 | FR5: 1 | FV5: 1 | FY5: 2 | GB5: 1 | GF5: 1 | GG5: 2 | GH5: 2 | GI5: 2 | GN5: 2 | GO5: 2 | GP5: 1 | GQ5: 2 | GT5: 1 | GW5: 1 | GX5: 1 | GY5: 1 | GZ5: 1 | HC5: 1 | HD5: 1 | HE5: 1 | HG5: 1 | HH5: 1 | HJ5: 2 | HK5: 1 | HM5: 2 | HN5: 2 | HP5: 2 | HR5: 1 | HS5: 1 | HT5: 1 | HV5: 1 | HX5: 1
A6: ※ | AI6: 1 | DB6: 1 | DE6: 1 | GC6: 1 | GD6: 1 | GU6: 1 | HO6: 1 | HU6: 1
A7: 任意特长 | C7: =职业列表!J11 -> 0 | D7: 2 | E7: 2 | F7: 1 | G7: 2 | J7: 1 | K7: 1 | O7: 2 | Q7: 1 | R7: 1 | S7: 1 | W7: 2 | X7: 1 | Y7: 1 | Z7: 2 | AA7: 2 | AC7: 2 | AE7: 1 | AJ7: 1 | AK7: 1 | AL7: 1 | AO7: 2 | AQ7: 1 | AR7: 3 | AS7: 1 | AT7: 2 | AU7: 2 | AV7: 1 | AW7: 1 | AX7: 1 | AY7: 1 | BA7: 1 | BB7: 2 | BD7: 1 | BE7: 1 | BG7: 1 | BK7: 2 | BM7: 1 | BO7: 2 | BR7: 1 | BS7: 1 | BU7: 1 | BV7: 2 | BW7: 4 | BX7: 2 | BY7: 1 | BZ7: 2 | CC7: 4 | CE7: 1 | CG7: 1 | CI7: 2 | CJ7: 2 | CK7: 2 | CL7: 1 | CM7: 1 | CO7: 1 | CP7: 4 | CQ7: 1 | CR7: 1 | CT7: 2 | CU7: 3 | CX7: 1 | CZ7: 1 | DD7: 5 | DI7: 1 | DJ7: 2 | DK7: 2 | DL7: 3 | DO7: 1 | DP7: 1 | DQ7: 1 | DR7: 1 | DS7: 1 | DT7: 2 | DU7: 1 | DV7: 1 | DW7: 1 | DY7: 2 | EA7: 1 | EB7: 2 | EC7: 1 | ED7: 2 | EE7: 2 | EF7: 2 | EG7: 2 | EH7: 2 | EI7: 1 | EJ7: 2 | EK7: 2 | EL7: 1 | EM7: 1 | EN7: 1 | EO7: 3 | EP7: 2 | EQ7: 2 | ER7: 1 | ES7: 1 | ET7: 4 | EU7: 2 | EV7: 2 | EW7: 1 | EX7: 2 | EY7: 2 | FA7: 1 | FD7: 3 | FE7: 1 | FF7: 1 | FG7: 1 | FH7: 2 | FI7: 0 | FJ7: 1 | FK7: 1 | FM7: 2 | FN7: 1 | FO7: 2 | FQ7: 1 | FS7: 2 | FT7: 1 | FV7: 1 | FW7: 1 | FY7: 2 | FZ7: 1 | GG7: 2 | GH7: 2 | GI7: 2 | GJ7: 2 | GK7: 2 | GL7: 2 | GM7: 2 | GO7: 2 | GQ7: 1 | GR7: 2 | GS7: 1 | GT7: 2 | GV7: 3 | GX7: 2 | GY7: 1 | GZ7: 2 | HA7: 3 | HB7: 2 | HC7: 2 | HD7: 1 | HE7: 2 | HF7: 2 | HG7: 1 | HH7: 1 | HI7: 6 | HJ7: 3 | HM7: 1 | HO7: 1 | HP7: 2 | HQ7: 2 | HS7: 6 | HT7: 6 | HU7: 1 | HV7: 1 | HW7: 2
A8: 会计 | C8: =IF(ISTEXT(IFERROR(VLOOKUP(本职技能!A8,职业列表!I3:J10,1,FALSE),0)),"★","") | D8: ★ | L8: ★ | N8: ★ | S8: ★ | U8: ★ | X8: ☆ | Y8: ★ | AC8: ★ | AK8: ★ | AL8: ★ | AO8: ★ | AQ8: ★ | AW8: ★ | AX8: ★ | AY8: ★ | BI8: ★ | BV8: ★ | BW8: ★ | BY8: ★ | CB8: ★ | CH8: ★ | CL8: ★ | CT8: ★ | CX8: ★ | CZ8: ★ | DA8: ★ | DG8: ★ | DH8: ★ | DI8: ★ | DJ8: ★ | DK8: ★ | DM8: ★ | DT8: ★ | DU8: ★ | DV8: ★ | EA8: ★ | EB8: ★ | ED8: ★ | EE8: ★ | EI8: ★ | EJ8: ★ | EM8: ★ | EO8: ★ | ER8: ★ | ES8: ★ | ET8: ★ | EV8: ★ | EW8: ★ | EY8: ★ | FS8: ★ | FV8: ★ | FZ8: ★ | GZ8: ★ | HG8: ★ | HM8: ★ | HP8: ★ | HU8: ※ | HV8: ★
A9: 人类学 | C9: =IF(ISTEXT(IFERROR(VLOOKUP(A9,职业列表!I3:J10,1,FALSE),0)),"★","") | CE9: ★ | CG9: ★ | EN9: ★ | HF9: ★ | HL9: ★
A10: 估价 | C10: =IF(ISTEXT(IFERROR(VLOOKUP(A10,职业列表!I3:J10,1,FALSE),0)),"★","") | K10: ★ | L10: ★ | M10: ★ | U10: ★ | X10: ☆ | AG10: ★ | AH10: ★ | AI10: ★ | AK10: ★ | AL10: ★ | CB10: ★ | EB10: ★ | EV10: ★ | FB10: ★ | GY10: ★ | GZ10: ★ | HB10: ★ | HF10: ★ | HG10: ★ | HH10: ★ | HL10: ★ | HN10: ★ | HO10: ★ | HP10: ★ | HU10: ※ | HV10: ★
A11: 考古学 | C11: =IF(ISTEXT(IFERROR(VLOOKUP(A11,职业列表!I3:J10,1,FALSE),0)),"★","") | M11: ★ | CB11: ★ | HL11: ★
A12: 技艺① | C12: =IF(ISTEXT(IFERROR(VLOOKUP(A12,职业列表!I3:J10,1,FALSE),0)),"★","") | F12: 表演 | G12: 表演 | K12: ★ | N12: 制图 | O12: ★ | R12: 文学 | X12: ★ | AC12: ★ | AH12: 表演 | AI12: 演☆ | AJ12: ★ | AK12: 伪造 | AL12: 伪造 | AQ12: 摄影 | AR12: ★ | BA12: 制图 | BB12: 表 | BD12: 耕作 | BI12: 表演 | BL12: ★ | BM12: ★ | BO12: 摄影☆ | BP12: 表演 | BX12: ★ | BZ12: ★ | CC12: 乐器 | CG12: 摄影 | CI12: 摄影 | CJ12: 摄影 | CM12: 演☆ | CO12: 摄影 | CR12: ★ | DC12: 演☆ | DI12: ★ | DM12: 驯养 | DZ12: 文学 | EK12: ★ | EL12: 摄影 | EO12: 乐器 | EQ12: 表演 | EU12: ★ | EW12: 摄影 | EZ12: 摄影 | FE12: 书法 | FF12: 书法 | FG12: ★ | FJ12: 表演 | FK12: 书法 | FQ12: ★ | FR12: ★ | FS12: 木匠 | FW12: 摄影 | FY12: 表 | FZ12: 摄影 | GG12: 表演 | GH12: 歌唱 | GI12: 表演 | GK12: 表演 | GL12: 表演 | GM12: 表演 | GN12: 表演 | GP12: 摄影 | GQ12: 表演 | GR12: 木匠 | GS12: 厨艺 | GX12: 游戏 | GY12: ★ | GZ12: ★ | HB12: ★ | HC12: 写作 | HG12: ★ | HJ12: ★ | HM12: 摄影 | HN12: 摄影 | HO12: ※ | HT12: ★ | HU12: ★ | HV12: ★
A13: 技艺② | C13: =IF(ISTEXT(IFERROR(VLOOKUP(A13,职业列表!I3:J10,1,FALSE),0)),"★","") | AC13: ★ | AQ13: ★ | BB13: 演 | BO13: 艺☆ | BX13: ★ | CZ13: 字☆ | FF13: ★ | FK13: ★ | FY13: 演 | FZ13: ★ | GG13: 歌唱 | GH13: 舞蹈 | GI13: 喜剧 | GN13: 歌唱 | GR13: 焊接
A14: 技艺③ | C14: =IF(ISTEXT(IFERROR(VLOOKUP(A14,职业列表!I3:J10,1,FALSE),0)),"★","") | BB14: 类 | BX14: ★ | CZ14: 记☆ | FY14: 类 | GG14: 舞蹈 | GH14: 乐器 | GI14: 杂技 | GN14: 喜剧 | GR14: 管道
A15: 取悦 | C15: =IF(ISTEXT(IFERROR(VLOOKUP(A15,职业列表!I3:J10,1,FALSE),0)),"★","") | F15: ☯ | G15: ☯ | H15: ☯ | K15: ☯ | L15: ☯ | O15: ☯ | P15: ☯ | Q15: ☯ | S15: ☯ | U15: ☯ | V15: ☯ | Y15: ☯ | AA15: ☯ | AF15: ☯ | AH15: ☯ | AI15: ☯ | AJ15: ☯ | AK15: ☯ | AM15: ☯ | AN15: ☯ | AO15: ☯ | AP15: ☯ | AR15: ☯ | AU15: ☯ | AV15: ☯ | AW15: ☯ | AY15: ☯ | AZ15: ★ | BB15: ☯ | BD15: ☯ | BG15: ☯ | BI15: ☯ | BJ15: ☯ | BK15: ☯ | BL15: ☯ | BN15: ☯ | BO15: ☯ | BP15: ☯ | BV15: ☯ | BY15: ☯ | BZ15: ☯ | CC15: ☯ | CD15: ☯ | CE15: ☯ | CH15: ☯ | CI15: ☯ | CJ15: ☯ | CM15: ☯ | CN15: ☯ | CO15: ☯ | CR15: ☯ | CU15: ☯ | CW15: ☯ | CX15: ☯ | CY15: ☯ | CZ15: ☯ | DA15: ☯ | DC15: ☯ | DG15: ☯ | DH15: ☯ | DI15: ☯ | DJ15: ☯ | DK15: ☯ | DL15: ☯ | DN15: ★ | DO15: ☯ | DP15: ☯ | DQ15: ☯ | DR15: ☯ | DS15: ☯ | DT15: ☯ | DU15: ☯ | DV15: ☯ | DW15: ☯ | DX15: ☯ | DY15: ☯ | DZ15: ☯ | EA15: ☯ | EB15: ☯ | EC15: ☯ | EE15: ☯ | EI15: ☯ | EJ15: ☯ | EK15: ☯ | EM15: ☯ | EO15: ☯ | EQ15: ★ | ER15: ☯ | ES15: ☯ | ET15: ☯ | EU15: ☯ | EV15: ☯ | EX15: ☯ | EY15: ☯ | FA15: ☯ | FB15: ☯ | FE15: ☯ | FF15: ☯ | FG15: ☯ | FM15: ☯ | FQ15: ☯ | FR15: ☯ | FV15: ☯ | FY15: ☯ | GB15: ☯ | GF15: ☯ | GG15: ☯ | GH15: ☯ | GI15: ☯ | GK15: ★ | GL15: ★ | GM15: ★ | GN15: ☯ | GO15: ☯ | GP15: ☯ | GQ15: ☯ | GT15: ☯ | GW15: ☯ | GX15: ☯ | GY15: ☯ | GZ15: ☯ | HA15: ☯ | HC15: ☯ | HE15: ☯ | HG15: ☯ | HH15: ☯ | HJ15: ☯ | HK15: ☯ | HM15: ☯ | HN15: ☯ | HO15: ☯ | HP15: ☯ | HR15: ☯ | HS15: ☯ | HT15: ☯ | HV15: ☯ | HX15: ☯
A16: 攀爬 | C16: =IF(ISTEXT(IFERROR(VLOOKUP(A16,职业列表!I3:J10,1,FALSE),0)),"★","") | E16: ★ | Q16: ★ | AG16: ★ | AN16: ★ | AU16: ★ | BC16: ☆ | BF16: ★ | BM16: ★ | BT16: ★ | BU16: ★ | BX16: ★ | CA16: ★ | CJ16: ★ | CQ16: ★ | DB16: ☆ | DE16: ★ | DF16: ★ | DO16: ★ | DP16: ★ | DR16: ★ | EJ16: ☆ | EK16: ★ | EN16: ★ | FB16: ★ | FI16: ★ | FU16: ★ | FX16: ★ | GC16: ☆ | GD16: ☆ | GE16: ☆ | GJ16: ★ | GR16: ★ | GU16: ☆ | HK16: ☆ | HL16: ★ | HO16: ※
A17: 计算机使用 Ω | C17: =IF(ISTEXT(IFERROR(VLOOKUP(A17,职业列表!I3:J10,1,FALSE),0)),"★","") | N17: ☆ | Z17: ★ | AA17: ★ | AQ17: ☆ | BR17: ☆ | CY17: ☆ | CZ17: ⊙ | DJ17: ☆ | FZ17: ☆ | GN17: ★ | GT17: ★ | GV17: ★ | GX17: ★
A18: 克苏鲁神话 | C18: =IF(ISTEXT(IFERROR(VLOOKUP(A18,职业列表!I3:J10,1,FALSE),0)),"★","")
A19: 乔装 | C19: =IF(ISTEXT(IFERROR(VLOOKUP(A19,职业列表!I3:J10,1,FALSE),0)),"★","") | F19: ★ | G19: ★ | AD19: ★ | AI19: ☆ | BB19: ★ | CM19: ☆ | CO19: ★ | DC19: ☆ | DS19: ★ | DX19: ★ | EC19: ★ | EU19: ★ | FN19: ★ | FY19: ★ | FZ19: ★ | GF19: ★ | GG19: ★ | GH19: ★ | GI19: ★ | GN19: ★ | GY19: ☆ | HH19: ★ | HJ19: ★ | HX19: ★
A20: 闪避 | C20: =IF(ISTEXT(IFERROR(VLOOKUP(A20,职业列表!I3:J10,1,FALSE),0)),"★","") | E20: ★ | P20: ★ | W20: ★ | AB20: ★ | BF20: ★ | BT20: ★ | CR20: ★ | DB20: ★ | DE20: ★ | DI20: ★ | DM20: ★ | DQ20: ★ | DR20: ★ | DS20: ★ | EM20: ★ | FO20: ★ | GC20: ★ | GD20: ★ | GJ20: ★ | GU20: ★ | HD20: ★ | HJ20: ★ | HN20: ★ | HO20: ★ | HR20: ★ | HU20: ★ | HW20: ★
A21: 汽车驾驶 | C21: =IF(ISTEXT(IFERROR(VLOOKUP(A21,职业列表!I3:J10,1,FALSE),0)),"★","") | G21: ★ | L21: ★ | U21: ★ | V21: ★ | AE21: ★ | AF21: ★ | AJ21: ★ | AM21: ☆ | AP21: ★ | AV21: ★ | AW21: ★ | AX21: ★ | BD21: ★ | BE21: ★ | BF21: ★ | BK21: ★ | BS21: ★ | BX21: ★ | CN21: ☆ | CX21: ★ | DE21: ※ | DG21: ★ | EI21: ★ | EK21: ★ | EP21: ★ | ER21: ★ | ES21: ★ | FB21: ★ | FC21: ★ | FD21: ★ | GO21: ★ | GR21: ★ | GW21: ☆ | HD21: ★ | HO21: ※ | HU21: ※
A22: 电气维修 | C22: =IF(ISTEXT(IFERROR(VLOOKUP(A22,职业列表!I3:J10,1,FALSE),0)),"★","") | V22: ☆ | Z22: ★ | AA22: ★ | AD22: ★ | AE22: ☆ | AG22: ☆ | AX22: ★ | BA22: ★ | BN22: ★ | BR22: ★ | BS22: ★ | BX22: ★ | CK22: ★ | CL22: ★ | CV22: ☆ | DA22: ★ | DE22: ☆ | EI22: ★ | EN22: ☆ | EP22: ★ | EZ22: ★ | FB22: ☆ | FU22: ★ | GA22: ★ | GN22: ★ | GP22: ★ | GR22: ★ | GT22: ★ | GX22: ★
A23: 电子学 Ω | C23: =IF(ISTEXT(IFERROR(VLOOKUP(A23,职业列表!I3:J10,1,FALSE),0)),"★","") | V23: ☆ | Z23: ★ | AA23: ★ | GT23: ★ | GX23: ★
A24: 话术 | C24: =IF(ISTEXT(IFERROR(VLOOKUP(A24,职业列表!I3:J10,1,FALSE),0)),"★","") | F24: ☯ | G24: ☯ | H24: ☯ | K24: ☯ | L24: ☯ | O24: ☯ | P24: ☯ | Q24: ☯ | S24: ☯ | U24: ☯ | V24: ☯ | Y24: ☯ | AA24: ☯ | AF24: ☯ | AH24: ☯ | AI24: ☯ | AJ24: ☯ | AK24: ☯ | AM24: ☯ | AN24: ☯ | AO24: ☯ | AP24: ☯ | AR24: ☯ | AU24: ☯ | AV24: ☯ | AW24: ☯ | AX24: ★ | AY24: ☯ | AZ24: ★ | BB24: ☯ | BD24: ☯ | BG24: ☯ | BI24: ☯ | BJ24: ☯ | BK24: ☯ | BL24: ☯ | BN24: ☯ | BO24: ☯ | BP24: ☯ | BV24: ☯ | BY24: ☯ | BZ24: ☯ | CC24: ☯ | CD24: ☯ | CE24: ☯ | CH24: ☯ | CI24: ☯ | CJ24: ☯ | CM24: ☯ | CN24: ☯ | CO24: ☯ | CR24: ☯ | CU24: ☯ | CW24: ☯ | CX24: ☯ | CY24: ☯ | CZ24: ☯ | DA24: ☯ | DC24: ☯ | DG24: ☯ | DH24: ☯ | DI24: ☯ | DJ24: ☯ | DK24: ☯ | DL24: ☯ | DN24: ★ | DO24: ☯ | DP24: ☯ | DQ24: ☯ | DR24: ☯ | DS24: ☯ | DT24: ☯ | DU24: ☯ | DV24: ☯ | DW24: ☯ | DX24: ☯ | DY24: ☯ | DZ24: ☯ | EA24: ☯ | EB24: ☯ | EC24: ☯ | EE24: ☯ | EI24: ☯ | EJ24: ☯ | EK24: ☯ | EM24: ☯ | EO24: ☯ | EQ24: ★ | ER24: ☯ | ES24: ☯ | ET24: ☯ | EU24: ☯ | EV24: ☯ | EX24: ☯ | EY24: ☯ | FA24: ☯ | FB24: ☯ | FD24: ★ | FE24: ☯ | FF24: ☯ | FG24: ☯ | FJ24: ☆ | FM24: ☯ | FN24: ★ | FQ24: ☯ | FR24: ☯ | FV24: ☯ | FY24: ☯ | GB24: ☯ | GF24: ☯ | GG24: ☯ | GH24: ☯ | GI24: ☯ | GK24: ★ | GL24: ★ | GM24: ★ | GN24: ☯ | GO24: ☯ | GP24: ☯ | GQ24: ☯ | GT24: ☯ | GW24: ☯ | GX24: ☯ | GY24: ☯ | GZ24: ☯ | HA24: ☯ | HC24: ☯ | HE24: ☯ | HG24: ☯ | HH24: ☯ | HJ24: ☯ | HK24: ☯ | HM24: ☯ | HN24: ☯ | HO24: ☯ | HP24: ☯ | HR24: ☯ | HS24: ☯ | HT24: ☯ | HV24: ☯ | HX24: ☯
A25: 格斗： | C25: =IF(ISTEXT(IFERROR(VLOOKUP(A25,职业列表!I3:J10,1,FALSE),0)),"★","") | F25: ★ | H25: ★ | P25: ★ | Q25: ★ | S25: ★ | V25: ⊙ | W25: ★ | AB25: ⊙ | AD25: ★ | AE25: ★ | AF25: ★ | AI25: ⊙ | AJ25: ☆ | AN25: ★ | AP25: ☆ | BE25: ★ | BJ25: ★ | BK25: ★ | BN25: ★ | BS25: ★ | CN25: ★ | CV25: ★ | DB25: ★ | DE25: ★ | DF25: ☆ | DH25: ★ | DO25: ★ | DP25: ★ | DQ25: ★ | DR25: ★ | DY25: ★ | EM25: ★ | FC25: ★ | FD25: ★ | FH25: ★ | FI25: ★ | FO25: ★ | GA25: ★ | GC25: ★ | GD25: ★ | GS25: ★ | GU25: ★ | GW25: ★ | HD25: 鞭 | HL25: ★ | HO25: ※ | HR25: ★ | HX25: ★
A26: 格斗① | C26: =IF(ISTEXT(IFERROR(VLOOKUP(A26,职业列表!I3:J10,1,FALSE),0)),"★","") | F26: ★ | V26: ⊙ | AB26: ⊙ | AD26: ★ | AE26: ★ | AF26: ★ | AI26: ⊙ | AN26: ★ | BJ26: ★ | BK26: ★ | BS26: ★ | BT26: 链锯 | CV26: ★ | DB26: ★ | DE26: ★ | DF26: ☆ | FC26: 鞭 | FR26: 矛 | GA26: ★ | GC26: ★ | GD26: ★ | GU26: ★ | HH26: ★ | HK26: 剑
A27: 格斗② | C27: =IF(ISTEXT(IFERROR(VLOOKUP(A27,职业列表!I3:P12,1,FALSE),0)),"★","") | F27: ★ | V27: ⊙ | AB27: ⊙ | AD27: ★ | AE27: ★ | AF27: ★ | AI27: ⊙ | AN27: ★ | BJ27: ★ | BK27: ★ | BS27: ★ | CV27: ★ | DB27: ★ | DE27: ★ | DF27: ☆ | GA27: ★ | GC27: ★ | GD27: ★ | GU27: ★ | HH27: ★
A28: 格斗③ | C28: =IF(ISTEXT(IFERROR(VLOOKUP(A28,职业列表!I3:J10,1,FALSE),0)),"★","") | F28: ★ | V28: ⊙ | AB28: ⊙ | AD28: ★ | AE28: ★ | AF28: ★ | AI28: ⊙ | AN28: ★ | BJ28: ★ | BK28: ★ | BS28: ★ | CV28: ★ | DB28: ★ | DE28: ★ | DF28: ☆ | GA28: ★ | GC28: ★ | GD28: ★ | GU28: ★ | HH28: ★
A29: 射击： | C29: =IF(ISTEXT(IFERROR(VLOOKUP(A29,职业列表!I3:J10,1,FALSE),0)),"★","") | H29: ★ | T29: ★ | V29: ⊙ | AB29: ⊙ | AD29: ★ | AE29: ★ | AF29: ★ | AI29: ⊙ | AJ29: ☆ | AM29: ★ | AN29: ★ | AP29: ☆ | AR29: ★ | BC29: ★ | BE29: ★ | BJ29: ★ | BK29: ★ | BY29: ★ | CF29: ★ | CM29: ★ | CN29: ★ | CV29: ★ | DB29: ★ | DC29: ★ | DY29: ★ | FC29: ★ | GA29: ★ | GC29: ★ | GD29: ★ | GE29: ★ | GU29: ★ | GW29: ★ | HK29: ★ | HL29: ★ | HR29: ★
A30: 射击① | C30: =IF(ISTEXT(IFERROR(VLOOKUP(A30,职业列表!I3:J10,1,FALSE),0)),"★","") | H30: ★ | T30: ★ | V30: ⊙ | AB30: ⊙ | AD30: ★ | AE30: ★ | AF30: ★ | AI30: ⊙ | AM30: ★ | AN30: ★ | AP30: ☆ | AR30: ★ | BC30: ★ | BE30: ★ | BJ30: ★ | BK30: ★ | BL30: 步/霰 | BY30: ★ | CF30: ★ | CM30: ★ | CN30: ★ | CV30: ★ | DB30: ★ | DC30: ★ | FC30: ★ | FR30: 弓术 | GA30: ★ | GC30: ★ | GD30: ★ | GE30: ★ | GU30: ★ | GW30: ★ | HA30: 霰弹 | HK30: 来复 | HL30: 来复 | HW30: 来复
A31: 射击② | C31: =IF(ISTEXT(IFERROR(VLOOKUP(A31,职业列表!I3:J10,1,FALSE),0)),"★","") | H31: ★ | T31: ★ | V31: ⊙ | AB31: ⊙ | AD31: ★ | AE31: ★ | AF31: ★ | AI31: ⊙ | AM31: ★ | AN31: ★ | AP31: ☆ | AR31: ★ | BC31: ★ | BE31: ★ | BJ31: ★ | BK31: ★ | BY31: ★ | CF31: ★ | CM31: ★ | CN31: ★ | CV31: ★ | DB31: ★ | DC31: ★ | FC31: ★ | GA31: ★ | GC31: ★ | GD31: ★ | GE31: ★ | GU31: ★ | GW31: ★
A32: 射击③ | C32: =IF(ISTEXT(IFERROR(VLOOKUP(A32,职业列表!I3:J10,1,FALSE),0)),"★","") | H32: ★ | T32: ★ | V32: ⊙ | AB32: ⊙ | AD32: ★ | AE32: ★ | AF32: ★ | AI32: ⊙ | AM32: ★ | AN32: ★ | AP32: ☆ | AR32: ★ | BC32: ★ | BE32: ★ | BJ32: ★ | BK32: ★ | BY32: ★ | CF32: ★ | CM32: ★ | CN32: ★ | CV32: ★ | DB32: ★ | DC32: ★ | FC32: ★ | GA32: ★ | GC32: ★ | GD32: ★ | GE32: ★ | GU32: ★ | GW32: ★
A33: 急救 | C33: =IF(ISTEXT(IFERROR(VLOOKUP(A33,职业列表!I3:J10,1,FALSE),0)),"★","") | P33: ★ | X33: ★ | AB33: ☆ | AS33: ★ | AT33: ★ | BF33: ★ | BN33: ★ | BS33: ★ | BT33: ★ | BY33: ★ | BZ33: ★ | CA33: ★ | CD33: ★ | CF33: ★ | CH33: ★ | CN33: ★ | CQ33: ★ | CV33: ★ | CW33: ★ | DB33: ※ | DE33: ★ | DM33: ★ | EF33: ★ | EG33: ★ | EH33: ★ | EJ33: ★ | EM33: ★ | FA33: ★ | FL33: ☆ | FR33: ★ | FS33: ★ | FU33: ★ | FV33: ★ | FX33: ★ | GA33: ★ | GB33: ★ | GC33: ※ | GD33: ※ | GU33: ※ | GW33: ★ | GY33: ★ | HF33: ★ | HK33: ★ | HL33: ★ | HO33: ★ | HQ33: ★ | HR33: ★ | HU33: ※ | HW33: ★
A34: 历史 | C34: =IF(ISTEXT(IFERROR(VLOOKUP(A34,职业列表!I3:J10,1,FALSE),0)),"★","") | F34: ★ | K34: ★ | L34: ★ | M34: ★ | O34: ☆ | R34: ★ | U34: ★ | Y34: ★ | AK34: ★ | AL34: ★ | AP34: ★ | AY34: ★ | AZ34: ★ | BC34: ★ | BG34: ★ | BL34: ★ | BO34: ★ | BP34: ★ | BQ34: ★ | CB34: ★ | CE34: ★ | CG34: ★ | CQ34: ★ | CU34: ★ | DG34: ★ | DL34: ★ | DN34: ★ | DV34: ★ | DW34: ★ | DX34: ★ | DZ34: ★ | FB34: ★ | FE34: ☆ | FI34: ☆ | FJ34: ★ | FK34: ☆ | FM34: ★ | GE34: ★ | GF34: ☆ | GQ34: ★ | GZ34: ★ | HB34: ★ | HC34: ★ | HE34: ★ | HF34: ★ | HP34: ★ | HT34: ★ | HX34: ★
A35: 恐吓 | C35: =IF(ISTEXT(IFERROR(VLOOKUP(A35,职业列表!I3:J10,1,FALSE),0)),"★","") | F35: ☯ | G35: ☯ | H35: ☯ | K35: ☯ | L35: ☯ | O35: ☯ | P35: ☯ | Q35: ☯ | S35: ☯ | U35: ☯ | V35: ☯ | W35: ★ | Y35: ☯ | AA35: ☯ | AE35: ★ | AF35: ☯ | AH35: ☯ | AI35: ☯ | AJ35: ☯ | AK35: ☯ | AM35: ☯ | AN35: ☯ | AO35: ☯ | AP35: ☯ | AR35: ☯ | AU35: ☯ | AV35: ☯ | AW35: ☯ | AY35: ☯ | AZ35: ★ | BB35: ☯ | BD35: ☯ | BG35: ☯ | BI35: ☯ | BJ35: ☯ | BK35: ☯ | BL35: ☯ | BN35: ☯ | BO35: ☯ | BP35: ☯ | BQ35: ★ | BV35: ☯ | BY35: ☯ | BZ35: ☯ | CC35: ☯ | CD35: ☯ | CE35: ☯ | CH35: ☯ | CI35: ☯ | CJ35: ☯ | CM35: ☯ | CN35: ☯ | CO35: ☯ | CR35: ☯ | CU35: ☯ | CW35: ☯ | CX35: ☯ | CY35: ☯ | CZ35: ☯ | DA35: ☯ | DC35: ☯ | DG35: ☯ | DH35: ☯ | DI35: ☯ | DJ35: ☯ | DK35: ☯ | DL35: ☯ | DN35: ★ | DO35: ☯ | DP35: ☯ | DQ35: ☯ | DR35: ☯ | DS35: ☯ | DT35: ☯ | DU35: ☯ | DV35: ☯ | DW35: ☯ | DX35: ☯ | DY35: ☯ | DZ35: ☯ | EA35: ☯ | EB35: ☯ | EC35: ☯ | EE35: ☯ | EI35: ☯ | EJ35: ☯ | EK35: ☯ | EM35: ☯ | EO35: ☯ | ER35: ☯ | ES35: ☯ | ET35: ☯ | EU35: ☯ | EV35: ☯ | EX35: ☯ | EY35: ☯ | FA35: ☯ | FB35: ☯ | FD35: ★ | FE35: ☯ | FF35: ☯ | FG35: ☯ | FM35: ☯ | FO35: ★ | FQ35: ☯ | FR35: ☯ | FV35: ☯ | FY35: ☯ | GB35: ☯ | GF35: ☯ | GG35: ☯ | GH35: ☯ | GI35: ☯ | GN35: ☯ | GO35: ☯ | GP35: ☯ | GQ35: ☯ | GT35: ☯ | GW35: ☯ | GX35: ☯ | GY35: ☯ | GZ35: ☯ | HA35: ☯ | HC35: ☯ | HE35: ☯ | HG35: ☯ | HH35: ☯ | HJ35: ☯ | HK35: ☯ | HM35: ☯ | HN35: ☯ | HO35: ☯ | HP35: ☯ | HR35: ☯ | HS35: ☯ | HT35: ☯ | HV35: ☯ | HX35: ☯
A36: 跳跃 | C36: =IF(ISTEXT(IFERROR(VLOOKUP(A36,职业列表!I3:J10,1,FALSE),0)),"★","") | E36: ★ | J36: ★ | Q36: ★ | W36: ★ | AB36: ★ | AN36: ★ | AU36: ★ | BC36: ★ | BF36: ★ | BM36: ★ | BT36: ★ | BU36: ★ | CA36: ★ | DE36: ★ | DO36: ★ | DP36: ★ | DQ36: ★ | DR36: ★ | EJ36: ☆ | EN36: ★ | FB36: ★ | FI36: ★ | FO36: ★ | FT36: ★ | FU36: ★ | FX36: ★ | GE36: ★ | GJ36: ★ | HD36: ★
A37: 外语① | C37: =IF(ISTEXT(IFERROR(VLOOKUP(A37,职业列表!I3:J10,1,FALSE),0)),"★","") | I37: ★ | K37: ★ | M37: ★ | O37: ★ | R37: ★ | T37: ⊙ | U37: ★ | X37: ★ | Y37: ★ | AH37: ☆ | AR37: ★ | AT37: 拉丁 | BC37: ★ | BG37: ★ | BH37: 拉丁 | BL37: ★ | BR37: ★ | BW37: ★ | CA37: ★ | CB37: ★ | CE37: ★ | CG37: ★ | CH37: 拉丁 | CJ37: ★ | CP37: ★ | CS37: ★ | CU37: ★ | CY37: ★ | DB37: ※ | DC37: ★ | DD37: ☆ | DJ37: ★ | DK37: ★ | DN37: 置换 | DO37: ★ | DR37: ★ | DS37: ★ | DU37: 拉丁 | DW37: 希伯来 | DX37: ★ | DY37: ★ | EF37: 拉丁 | EG37: 拉丁 | EH37: 拉丁 | EJ37: ★ | EN37: ★ | EX37: ★ | FE37: 汉语 | FI37: ★ | FL37: 汉语 | FQ37: ★ | FR37: ★ | FS37: ★ | FV37: ★ | FX37: ★ | GC37: ※ | GD37: ※ | GE37: ★ | GF37: ★ | GS37: ★ | GU37: ※ | GY37: ★ | GZ37: 欧洲 | HA37: 欧洲 | HB37: 欧洲 | HC37: 欧洲 | HE37: 拉丁 | HF37: ★ | HK37: ★ | HL37: ★ | HN37: 欧洲 | HP37: 拉丁 | HQ37: 拉丁 | HS37: 欧洲 | HU37: ※ | HX37: 欧洲
A38: 外语② | C38: =IF(ISTEXT(IFERROR(VLOOKUP(A38,职业列表!I3:J10,1,FALSE),0)),"★","") | I38: ★ | K38: ★ | M38: ★ | O38: ★ | R38: ★ | T38: ⊙ | U38: ★ | X38: ★ | Y38: ★ | AH38: ☆ | AR38: ★ | BC38: ★ | BG38: ★ | BW38: ★ | CA38: ★ | CB38: ★ | CE38: ★ | CG38: ★ | CJ38: ★ | CP38: ★ | CS38: ★ | CU38: ★ | CY38: ★ | DC38: ★ | DD38: ☆ | DJ38: ★ | DK38: ★ | DN38: 置换 | DS38: ★ | DX38: ★ | DY38: ★ | EJ38: ★ | EN38: ★ | EX38: ★ | FE38: 梵语 | FQ38: ★ | FR38: ★ | FV38: ★ | FX38: ★ | GE38: ★ | GF38: ★ | GS38: ★ | HA38: 拉丁
A39: 外语③ | C39: =IF(ISTEXT(IFERROR(VLOOKUP(A39,职业列表!I3:J10,1,FALSE),0)),"★","") | I39: ★ | K39: ★ | M39: ★ | O39: ★ | R39: ★ | T39: ⊙ | U39: ★ | X39: ★ | Y39: ★ | AH39: ☆ | AR39: ★ | BC39: ★ | BG39: ★ | BW39: ★ | CA39: ★ | CB39: ★ | CE39: ★ | CG39: ★ | CJ39: ★ | CP39: ★ | CS39: ★ | CU39: ★ | CY39: ★ | DC39: ★ | DD39: ☆ | DJ39: ★ | DK39: ★ | DS39: ★ | DX39: ★ | DY39: ★ | EJ39: ★ | EN39: ★ | EX39: ★ | FQ39: ★ | FR39: ★ | FV39: ★ | FX39: ★ | GE39: ★ | GF39: ★ | GS39: ★
A40: 母语 | C40: =IF(ISTEXT(IFERROR(VLOOKUP(A40,职业列表!I3:J10,1,FALSE),0)),"★","") | N40: ★ | R40: ★ | U40: ★ | AY40: ★ | AZ40: ★ | BG40: ★ | BO40: ★ | BQ40: ★ | BW40: ★ | CP40: ★ | CY40: ★ | CZ40: ★ | DD40: ☆ | DJ40: ★ | DN40: ★ | DU40: ★ | DW40: ★ | DX40: ★ | DZ40: ★ | EQ40: ★ | EU40: ★ | EV40: ★ | EX40: ★ | FI40: ★ | FM40: ★ | GF40: ★ | GK40: ★ | GL40: ★ | GM40: ★ | GV40: ★ | HC40: ★ | HJ40: ★ | HN40: ★
A41: 法律 | C41: =IF(ISTEXT(IFERROR(VLOOKUP(A41,职业列表!I3:J10,1,FALSE),0)),"★","") | D41: ★ | H41: ★ | I41: ★ | N41: ★ | V41: ★ | AH41: ☆ | BE41: ★ | BJ41: ★ | BQ41: ★ | BV41: ★ | CM41: ★ | CN41: ★ | CO41: ★ | DH41: ★ | DJ41: ★ | DK41: ★ | DT41: ★ | ED41: ★ | EE41: ★ | EL41: ★ | EY41: ★ | FC41: ★ | FQ41: ★ | FV41: ★ | FW41: ★ | GO41: ★ | GW41: ★ | HA41: ★ | HF41: ★ | HM41: ★ | HP41: ★ | HR41: ★
A42: 图书馆使用 | C42: =IF(ISTEXT(IFERROR(VLOOKUP(A42,职业列表!I3:J10,1,FALSE),0)),"★","") | D42: ★ | H42: ★ | K42: ★ | L42: ★ | M42: ★ | N42: ☆ | R42: ★ | U42: ★ | Y42: ★ | Z42: ★ | AA42: ★ | AK42: ★ | AL42: ★ | AQ42: ☆ | BA42: ★ | BH42: ★ | BO42: ★ | BQ42: ★ | BR42: ☆ | BV42: ★ | BW42: ★ | CB42: ★ | CE42: ★ | CG42: ★ | CH42: ★ | CO42: ★ | CP42: ★ | CT42: ★ | CU42: ★ | CY42: ☆ | CZ42: ⊙ | DD42: ★ | DJ42: ☆ | DT42: ★ | DU42: ★ | DV42: ★ | DW42: ★ | DX42: ★ | DZ42: ★ | ED42: ★ | EE42: ★ | EJ42: ★ | EW42: ★ | EZ42: ★ | FE42: ☆ | FF42: ★ | FG42: ★ | FI42: ★ | FK42: ☆ | FL42: ★ | FR42: ★ | FS42: ★ | FZ42: ☆ | GF42: ☆ | GQ42: ★ | GT42: ★ | GV42: ★ | GZ42: ★ | HB42: ★ | HC42: ★ | HE42: ★ | HF42: ★ | HM42: ★ | HN42: ★ | HP42: ★ | HQ42: ★ | HS42: ★ | HT42: ★ | HX42: ★
A43: 聆听 | C43: =IF(ISTEXT(IFERROR(VLOOKUP(A43,职业列表!I3:J10,1,FALSE),0)),"★","") | D43: ★ | I43: ★ | J43: ★ | P43: ★ | S43: ★ | T43: ☆ | X43: ★ | Y43: ★ | AG43: ★ | AH43: ★ | AJ43: ★ | AM43: ★ | AU43: ★ | AV43: ★ | AW43: ★ | AZ43: ★ | BB43: ★ | BG43: ★ | BI43: ★ | BJ43: ★ | BM43: ★ | BN43: ★ | BP43: ★ | BQ43: ★ | CA43: ★ | CC43: ★ | CD43: ★ | CF43: ★ | CL43: ★ | CM43: ★ | CS43: ★ | CT43: ★ | CX43: ★ | DA43: ★ | DC43: ★ | DD43: ★ | DF43: ★ | DH43: ★ | DI43: ★ | DJ43: ★ | DN43: ★ | DV43: ★ | DZ43: ★ | EC43: ★ | ED43: ★ | EO43: ★ | ER43: ★ | ES43: ★ | EX43: ★ | FE43: ★ | FJ43: ★ | FM43: ★ | FN43: ★ | FR43: ★ | FT43: ★ | FX43: ★ | FY43: ★ | GG43: ★ | GH43: ★ | GI43: ★ | GN43: ★ | GO43: ★ | GV43: ★ | GX43: ★ | HD43: ★ | HF43: ★ | HJ43: ★ | HM43: ★ | HN43: ★ | HP43: ★ | HR43: ★ | HU43: ★ | HV43: ★ | HW43: ★ | HX43: ★
A44: 锁匠 | C44: =IF(ISTEXT(IFERROR(VLOOKUP(A44,职业列表!I3:J10,1,FALSE),0)),"★","") | AD44: ★ | AE44: ★ | AG44: ★ | AI44: ※ | BM44: ☆ | FU44: ★ | GY44: ☆ | HH44: ★ | HM44: ★ | HX44: ★
A45: 机械维修 | C45: =IF(ISTEXT(IFERROR(VLOOKUP(A45,职业列表!I3:J10,1,FALSE),0)),"★","") | M45: ★ | AC45: ★ | AE45: ☆ | AG45: ☆ | AI45: ※ | AQ45: ★ | AS45: ★ | AV45: ★ | AW45: ★ | AX45: ★ | BA45: ★ | BD45: ★ | BF45: ★ | BN45: ★ | BS45: ★ | BT45: ★ | BU45: ★ | BX45: ★ | BZ45: ★ | CK45: ★ | CL45: ★ | CQ45: ★ | CV45: ☆ | CW45: ★ | DA45: ★ | DB45: ※ | DE45: ☆ | EI45: ★ | EK45: ★ | EN45: ☆ | EP45: ★ | EZ45: ★ | FB45: ☆ | FD45: ★ | FP45: ★ | FU45: ★ | GA45: ★ | GB45: ★ | GC45: ※ | GD45: ※ | GP45: ★ | GR45: ★ | GU45: ※ | HD45: ★ | HG45: ★ | HO45: ★ | HT45: ★ | HW45: ★
A46: 医学 | C46: =IF(ISTEXT(IFERROR(VLOOKUP(A46,职业列表!I3:J10,1,FALSE),0)),"★","") | I46: ★ | AT46: ★ | BH46: ★ | BZ46: ★ | CD46: ★ | CS46: ★ | DM46: ★ | EF46: ★ | EG46: ★ | EH46: ★ | EL46: ★ | EZ46: ★ | FA46: ★ | FL46: ★ | FU46: ★ | FV46: ★ | FW46: ★ | HQ46: ★
A47: 博物学 | C47: =IF(ISTEXT(IFERROR(VLOOKUP(A47,职业列表!I3:J10,1,FALSE),0)),"★","") | J47: ★ | O47: ☆ | R47: ☆ | T47: ★ | AB47: ☆ | AC47: ★ | BC47: ★ | BD47: ★ | BT47: ☆ | BZ47: ★ | CF47: ★ | CW47: ★ | DF47: ★ | DM47: ★ | EW47: ★ | FH47: ★ | FL47: ★ | FP47: ★ | FT47: ★ | GB47: ★ | GE47: ★ | GS47: ★ | HD47: ★ | HL47: ★
A48: 导航 | C48: =IF(ISTEXT(IFERROR(VLOOKUP(A48,职业列表!I3:J10,1,FALSE),0)),"★","") | L48: ★ | M48: ☆ | T48: ★ | AM48: ★ | AU48: ★ | AV48: ★ | AW48: ★ | AX48: ★ | BC48: ★ | BL48: ★ | BM48: ★ | BY48: ★ | CA48: ★ | CF48: ★ | CK48: ★ | CL48: ★ | CQ48: ★ | CV48: ★ | CW48: ★ | EI48: ★ | ES48: ★ | EW48: ★ | FP48: ★ | FX48: ★ | GA48: ★ | GB48: ★ | GE48: ★ | HD48: ★ | HK48: ★ | HL48: ★ | HX48: ★
A49: 神秘学 | C49: =IF(ISTEXT(IFERROR(VLOOKUP(A49,职业列表!I3:J10,1,FALSE),0)),"★","") | R49: ☆ | AO49: ★ | AP49: ★ | CB49: ★ | CE49: ★ | CG49: ★ | DF49: ★ | DG49: ★ | DU49: ★ | DW49: ★ | FF49: ★ | FG49: ★ | FH49: ★ | FJ49: ★ | FK49: ★ | FL49: ★ | GP49: ★ | GQ49: ★
A50: 操作重型机械 | C50: =IF(ISTEXT(IFERROR(VLOOKUP(A50,职业列表!I3:J10,1,FALSE),0)),"★","") | AE50: ★ | BA50: ★ | BD50: ★ | BF50: ★ | BS50: ★ | BU50: ★ | BX50: ★ | CK50: ★ | DH50: ★ | EN50: ★ | FP50: ★ | GR50: ★ | HO50: ★
A51: 说服 | C51: =IF(ISTEXT(IFERROR(VLOOKUP(A51,职业列表!I3:J10,1,FALSE),0)),"★","") | D51: ★ | F51: ☯ | G51: ☯ | H51: ☯ | K51: ☯ | L51: ☯ | N51: ★ | O51: ☯ | P51: ☯ | Q51: ☯ | S51: ☯ | U51: ☯ | V51: ☯ | Y51: ☯ | AA51: ☯ | AF51: ☯ | AH51: ☯ | AI51: ☯ | AJ51: ☯ | AK51: ☯ | AM51: ☯ | AN51: ☯ | AO51: ☯ | AP51: ☯ | AR51: ☯ | AU51: ☯ | AV51: ☯ | AW51: ☯ | AY51: ☯ | AZ51: ★ | BB51: ☯ | BD51: ☯ | BE51: ★ | BG51: ☯ | BH51: ★ | BI51: ☯ | BJ51: ☯ | BK51: ☯ | BL51: ☯ | BN51: ☯ | BO51: ☯ | BP51: ☯ | BQ51: ★ | BV51: ☯ | BY51: ☯ | BZ51: ☯ | CC51: ☯ | CD51: ☯ | CE51: ☯ | CH51: ☯ | CI51: ☯ | CJ51: ☯ | CM51: ☯ | CN51: ☯ | CO51: ☯ | CR51: ☯ | CS51: ★ | CT51: ★ | CU51: ☯ | CW51: ☯ | CX51: ☯ | CY51: ☯ | CZ51: ☯ | DA51: ☯ | DC51: ☯ | DG51: ☯ | DH51: ☯ | DI51: ☯ | DJ51: ☯ | DK51: ☯ | DL51: ☯ | DN51: ★ | DO51: ☯ | DP51: ☯ | DQ51: ☯ | DR51: ☯ | DS51: ☯ | DT51: ☯ | DU51: ☯ | DV51: ☯ | DW51: ☯ | DX51: ☯ | DY51: ☯ | DZ51: ☯ | EA51: ☯ | EB51: ☯ | EC51: ☯ | ED51: ★ | EE51: ☯ | EI51: ☯ | EJ51: ☯ | EK51: ☯ | EM51: ☯ | EO51: ☯ | EQ51: ★ | ER51: ☯ | ES51: ☯ | ET51: ☯ | EU51: ☯ | EV51: ☯ | EX51: ☯ | EY51: ☯ | FA51: ☯ | FB51: ☯ | FC51: ☆ | FE51: ☯ | FF51: ☯ | FG51: ☯ | FJ51: ☆ | FM51: ☯ | FQ51: ☯ | FR51: ☯ | FS51: ★ | FV51: ☯ | FY51: ☯ | GB51: ☯ | GF51: ☯ | GG51: ☯ | GH51: ☯ | GI51: ☯ | GK51: ★ | GL51: ★ | GM51: ★ | GN51: ☯ | GO51: ☯ | GP51: ☯ | GQ51: ☯ | GT51: ☯ | GW51: ☯ | GX51: ☯ | GY51: ☯ | GZ51: ☯ | HA51: ☯ | HC51: ☯ | HE51: ☯ | HG51: ☯ | HH51: ☯ | HJ51: ☯ | HK51: ☯ | HM51: ☯ | HN51: ☯ | HO51: ☯ | HP51: ☯ | HR51: ☯ | HS51: ☯ | HT51: ☯ | HU51: ※ | HV51: ☯ | HX51: ☯
A52: 驾驶： | C52: =IF(ISTEXT(IFERROR(VLOOKUP(A52,职业列表!I3:J10,1,FALSE),0)),"★","") | AM52: ☆ | AS52: 船 | CK52: 飞行 | CL52: 飞行 | CV52: 船 | CW52: 船 | DE52: ※ | EP52: 船 | FB52: ★ | FP52: 船 | GA52: 船 | GB52: 船 | HL52: 艇船球 | HO52: ※
A53: 精神分析 | C53: =IF(ISTEXT(IFERROR(VLOOKUP(A53,职业列表!I3:J10,1,FALSE),0)),"★","") | I53: ★ | CS53: ★ | CT53: ★ | FL53: ☆ | FQ53: ★ | FT53: ★
A54: 心理学 | C54: =IF(ISTEXT(IFERROR(VLOOKUP(A54,职业列表!I3:J10,1,FALSE),0)),"★","") | F54: ★ | G54: ★ | H54: ★ | I54: ★ | J54: ★ | N54: ★ | O54: ★ | P54: ★ | R54: ★ | S54: ★ | V54: ★ | W54: ★ | X54: ★ | Y54: ★ | AD54: ★ | AF54: ★ | AH54: ★ | AI54: ★ | AM54: ★ | AO54: ★ | AP54: ★ | AQ54: ★ | AT54: ★ | AW54: ★ | AY54: ★ | AZ54: ★ | BB54: ★ | BG54: ★ | BI54: ★ | BJ54: ★ | BK54: ★ | BN54: ★ | BO54: ★ | BP54: ★ | BQ54: ★ | BV54: ★ | BY54: ★ | CC54: ★ | CD54: ★ | CG54: ★ | CH54: ★ | CI54: ★ | CJ54: ★ | CM54: ★ | CN54: ★ | CO54: ★ | CP54: ★ | CR54: ★ | CS54: ★ | CT54: ★ | CX54: ★ | CZ54: ★ | DA54: ★ | DC54: ★ | DG54: ★ | DH54: ★ | DI54: ★ | DK54: ★ | DL54: ★ | DN54: ★ | DQ54: ★ | DS54: ★ | DT54: ★ | DU54: ★ | DV54: ★ | DW54: ★ | DX54: ★ | DY54: ★ | DZ54: ★ | EA54: ★ | EB54: ★ | EC54: ★ | EE54: ★ | EF54: ★ | EG54: ★ | EH54: ★ | EI54: ★ | EM54: ★ | EO54: ★ | EP54: ★ | EQ54: ★ | ER54: ★ | ES54: ★ | ET54: ★ | EU54: ★ | EV54: ★ | EX54: ★ | EY54: ★ | FA54: ★ | FC54: ☆ | FE54: ★ | FF54: ★ | FH54: ★ | FJ54: ★ | FM54: ★ | FN54: ★ | FO54: ★ | FQ54: ★ | FT54: ★ | FY54: ★ | FZ54: ★ | GF54: ★ | GG54: ★ | GH54: ★ | GI54: ★ | GK54: ★ | GL54: ★ | GM54: ★ | GN54: ★ | GQ54: ★ | GW54: ★ | GY54: ★ | GZ54: ★ | HC54: ★ | HD54: ★ | HE54: ★ | HF54: ★ | HJ54: ★ | HK54: ★ | HN54: ★ | HP54: ★ | HQ54: ★ | HR54: ★ | HS54: ★ | HV54: ★ | HX54: ★
A55: 骑术 | C55: =IF(ISTEXT(IFERROR(VLOOKUP(A55,职业列表!I3:J10,1,FALSE),0)),"★","") | Q55: ★ | AB55: ★ | AR55: ★ | BL55: ★ | CN55: ☆ | DE55: ※ | DP55: ★ | FC55: ★ | FR55: ★ | GW55: ☆ | GY55: ★ | HA55: ★ | HK55: ★ | HL55: ★
A56: 科学① | C56: =IF(ISTEXT(IFERROR(VLOOKUP(A56,职业列表!I3:J10,1,FALSE),0)),"★","") | I56: 生物 | J56: 动物 | M56: ☆ | N56: 数学 | T56: 生物 | Z56: 数学 | AS56: 生物 | AT56: 生物 | BA56: 工程 | BH56: 生物 | BR56: 化学 | BT56: 生物☆ | BU56: 地质 | CD56: 生物 | CE56: 天文学 | CH56: 化学 | CI56: 化学 | CJ56: 化学 | CK56: 天文 | CQ56: 地质 | CS56: 生物 | CY56: ★ | DG56: 生物 | DM56: 药学 | EF56: 生物 | EG56: 生物 | EH56: 生物 | EL56: 化学 | EZ56: 生物 | FA56: 药学 | FG56: 天文 | FI56: ☆ | FK56: 天文 | FL56: 化学 | FP56: 天文 | FT56: 动物 | FU56: 化学 | FV56: 药学 | FW56: 化学 | GP56: 物理 | GS56: 生物 | HF56: 化学 | HL56: 生物 | HQ56: 生物
A57: 科学② | C57: =IF(ISTEXT(IFERROR(VLOOKUP(A57,职业列表!I3:J10,1,FALSE),0)),"★","") | I57: 化学 | T57: 植物 | AT57: 药学 | BA57: 物理 | BH57: 司法 | BR57: ★ | BT57: 植☆ | CD57: 化学 | CH57: 制药 | CS57: 化学 | CY57: ★ | DG57: 化学 | DM57: 动物 | EF57: 药学 | EG57: 药学 | EH57: 药学 | EL57: 司法 | EZ57: 化学 | FG57: 地质 | FW57: 司法 | GP57: 化学 | GS57: 化学 | HQ57: 药学
A58: 科学③ | C58: =IF(ISTEXT(IFERROR(VLOOKUP(A58,职业列表!I3:J10,1,FALSE),0)),"★","") | BH58: 药学 | BR58: ★ | CY58: ★ | EL58: 药学 | EZ58: 药学 | FW58: 药学 | GP58: 生物
A59: 妙手 | C59: =IF(ISTEXT(IFERROR(VLOOKUP(A59,职业列表!I3:J10,1,FALSE),0)),"★","") | AG59: ★ | AH59: ★ | AL59: ★ | AM59: ★ | AN59: ★ | BI59: ★ | BM59: ☆ | CR59: ★ | CX59: ☆ | DC59: ★ | EA59: ★ | EC59: ★ | ER59: ☆ | FN59: ★
A60: 侦查 | C60: =IF(ISTEXT(IFERROR(VLOOKUP(A60,职业列表!I3:J10,1,FALSE),0)),"★","") | D60: ★ | E60: ★ | K60: ★ | M60: ★ | O60: ★ | S60: ★ | T60: ☆ | W60: ★ | X60: ★ | Z60: ★ | AA60: ★ | AC60: ★ | AF60: ★ | AG60: ★ | AI60: ★ | AK60: ★ | AL60: ★ | AM60: ★ | AO60: ★ | AQ60: ★ | AS60: ★ | AV60: ★ | AX60: ★ | AY60: ★ | BE60: ★ | BH60: ★ | BI60: ★ | BJ60: ★ | BP60: ★ | BR60: ★ | BU60: ★ | CB60: ★ | CD60: ★ | CF60: ★ | CI60: ★ | CL60: ★ | CM60: ★ | CN60: ★ | CO60: ★ | CQ60: ★ | CU60: ★ | CW60: ★ | CY60: ★ | DA60: ★ | DF60: ★ | DQ60: ★ | EA60: ★ | EB60: ★ | EC60: ★ | ED60: ★ | EL60: ★ | EP60: ★ | EW60: ★ | EY60: ★ | FA60: ★ | FB60: ★ | FN60: ★ | FO60: ★ | FP60: ★ | FW60: ★ | FZ60: ★ | GB60: ★ | GJ60: ★ | GS60: ★ | GT60: ★ | GW60: ★ | GZ60: ★ | HB60: ★ | HF60: ★ | HG60: ★ | HK60: ★ | HL60: ★ | HM60: ★ | HN60: ★ | HR60: ★ | HT60: ★ | HV60: ★ | HW60: ★ | HX60: ★
A61: 潜行 | C61: =IF(ISTEXT(IFERROR(VLOOKUP(A61,职业列表!I3:J10,1,FALSE),0)),"★","") | H61: ★ | J61: ★ | P61: ★ | T61: ★ | V61: ★ | AD61: ★ | AF61: ★ | AG61: ★ | AI61: ★ | AJ61: ★ | AN61: ★ | AP61: ★ | AU61: ★ | BE61: ★ | BM61: ★ | BN61: ★ | BP61: ★ | BU61: ★ | CI61: ★ | CR61: ★ | CX61: ☆ | DB61: ★ | DC61: ★ | DL61: ★ | DX61: ★ | EC61: ★ | ER61: ☆ | FH61: ★ | FI61: ★ | FN61: ★ | GC61: ★ | GD61: ★ | GF61: ★ | GO61: ★ | GU61: ★ | GV61: ★ | GY61: ★ | HH61: ★ | HK61: ★ | HL61: ★ | HR61: ★ | HU61: ★ | HW61: ★ | HX61: ★
A62: 生存： | C62: =IF(ISTEXT(IFERROR(VLOOKUP(A62,职业列表!I3:J10,1,FALSE),0)),"★","") | T62: ⊙ | AB62: ★ | BC62: ★ | CA62: 山 | CF62: ★ | CV62: 海上 | DB62: ★ | DF62: ★ | EN62: 海洋 | EW62: ★ | FX62: 山 | GA62: 海 | GC62: ★ | GD62: ★ | GE62: ★ | GU62: ★
A63: 游泳 | C63: =IF(ISTEXT(IFERROR(VLOOKUP(A63,职业列表!I3:J10,1,FALSE),0)),"★","") | E63: ★ | Q63: ★ | AS63: ★ | BC63: ☆ | CV63: ★ | CW63: ★ | DB63: ☆ | DE63: ★ | DF63: ★ | DO63: ★ | DP63: ★ | FP63: ★ | GA63: ★ | GB63: ★ | GC63: ☆ | GD63: ☆ | GE63: ☆ | GJ63: ★ | GU63: ☆ | HK63: ☆ | HL63: ★
A64: 投掷 | C64: =IF(ISTEXT(IFERROR(VLOOKUP(A64,职业列表!I3:J10,1,FALSE),0)),"★","") | E64: ★ | Q64: ★ | AB64: ★ | AN64: ★ | BF64: ★ | BS64: ★ | BT64: ★ | DF64: ☆ | DO64: ★ | DP64: ★ | DQ64: ★ | DR64: ★ | GJ64: ★
A65: 追踪 | C65: =IF(ISTEXT(IFERROR(VLOOKUP(A65,职业列表!I3:J10,1,FALSE),0)),"★","") | H65: ★ | J65: ★ | T65: ★ | V65: ★ | AB65: ★ | BD65: ★ | CA65: ★ | CF65: ★ | FC65: ★ | FT65: ★ | FX65: ★ | HF65: ★ | HL65: ★
A66: 驯兽 | C66: =IF(ISTEXT(IFERROR(VLOOKUP(A66,职业列表!I3:J10,1,FALSE),0)),"★","") | J66: ★ | DM66: ★
A67: 潜水 | C67: =IF(ISTEXT(IFERROR(VLOOKUP(A67,职业列表!I3:J10,1,FALSE),0)),"★","") | AS67: ★ | DE67: ※
A68: 爆破 | C68: =IF(ISTEXT(IFERROR(VLOOKUP(A68,职业列表!I3:J10,1,FALSE),0)),"★","")
A69: 读唇 | C69: =IF(ISTEXT(IFERROR(VLOOKUP(A69,职业列表!I3:J10,1,FALSE),0)),"★","")
A70: 催眠 | C70: =IF(ISTEXT(IFERROR(VLOOKUP(A70,职业列表!I3:J10,1,FALSE),0)),"★","") | AP70: ★
A71: 炮术 | C71: =IF(ISTEXT(IFERROR(VLOOKUP(A71,职业列表!I3:J10,1,FALSE),0)),"★","")
A72: 学识： | C72: =IF(ISTEXT(IFERROR(VLOOKUP(A72,职业列表!I3:J10,1,FALSE),0)),"★","") | FE72: ★ | FF72: ★ | FG72: ★ | FH72: ★ | FJ72: ★ | FK72: ★ | FL72: ★
A73: =人物卡!AB48 -> 自定义技能 | C73: =IF(ISTEXT(IFERROR(VLOOKUP(A73,职业列表!I3:J10,1,FALSE),0)),"★","")
A74: =人物卡!AB49 -> 0 | C74: =IF(ISTEXT(IFERROR(VLOOKUP(A74,职业列表!I3:J10,1,FALSE),0)),"★","")

Sheet 附表
AJ1: 自定义职业属性
B2: 移动力计算 | S2: 自定义职业
A3: 护甲表减值 是否开启 | B3: 护甲表减值 | C3: 年龄减值 | D3: 力量-体型 | E3: =G14-I14 -> 20 | G3: 技能雷达表 | H3: 值 | I3: 总数 | J3: 百分比 | N3: 伤害加值与体格 | S3: 属性名称 | T3: 使用 | U3: 使用倍数 | V3: 计算
D4: 敏捷-体型 | E4: =J14-I14 -> -30 | G4: 调查 | H4: 交涉 | I4: 战斗 | J4: 特技 | K4: 支援 | L4: 学问 | N4: 力量+体型 | S4: ="力量×"&U4 -> 力量×0 | T4: =职业列表!I15 -> × | U4: =职业列表!J15 -> 0 | V4: =G14*U4 -> 0 | X4: =IF(U4>0,S4,"") | Y4: =IF(AND(U5>0,U4>0),"+","") | Z4: =IF(U5>0,S5,"")
A5: =IF(人物卡!AI12="开",1,IF(人物卡!AI12="关",0)) -> 0 | B5: =IF(人物卡!AN12=0,"0",VLOOKUP(人物卡!AN12,'防具表 载具表'!B2:I101,3,FALSE)) -> 0 | C5: =IF(人物卡!E6<40,0,INT((人物卡!E6/10)-3)) -> 0 | D5: 力量大小 | E5: =IF(E3>0,"1",IF(E3=0,"0",IF(E3<0,"-1"))) -> 1 | G5: =AVERAGE(人物卡!AA7+人物卡!R16+人物卡!R17+人物卡!R18+人物卡!R19+人物卡!R25+人物卡!R27+人物卡!R46+人物卡!R47+人物卡!R48+人物卡!AN17+人物卡!AN18+人物卡!AN22+人物卡!AN24+人物卡!AN28+人物卡!AN29+人物卡!AN35+人物卡!AN40+人物卡!AN44-122) -> 273 | H5: =AVERAGE(人物卡!AA5+人物卡!R17+人物卡!R18+人物卡!R23+人物卡!R26+人物卡!R28+人物卡!R33+人物卡!R44+人物卡!R46+人物卡!R47+人物卡!R48+人物卡!R49+人物卡!AN16+人物卡!AN26+人物卡!AN28+人物卡!AN29+人物卡!AN35+人物卡!AN40+人物卡!AN44-111-人物卡!J49) -> 312 | I5: =AVERAGE((人物卡!U3+人物卡!U7)/2+人物卡!U5+人物卡!AA3+人物卡!R29+人物卡!R34+人物卡!R35+人物卡!R36+人物卡!R38+人物卡!R39+人物卡!R40+人物卡!R44+人物卡!R45+人物卡!AN18+人物卡!AN25+人物卡!AN29+人物卡!AN30+人物卡!AN35+人物卡!AN36+人物卡!AN39+人物卡!AN41+人物卡!AN43+人物卡!AN45+人物卡!AN46-189-人物卡!J29) -> 437 | J5: =AVERAGE(人物卡!AA3+人物卡!R19+人物卡!R20+人物卡!R21+人物卡!R22+人物卡!R24+人物卡!R28+人物卡!R30+人物卡!R31+人物卡!R45+人物卡!AN19+人物卡!AN20+人物卡!AN21+人物卡!AN23+人物卡!AN25+人物卡!AN27+人物卡!AN30+人物卡!AN34+人物卡!AN36+人物卡!AN37+人物卡!AN38+人物卡!AN39+人物卡!AN40+人物卡!AN41+人物卡!AN42+人物卡!AN43+人物卡!AN45+人物卡!AN46-219) -> 120 | K5: =AVERAGE(人物卡!R42+人物卡!AN21+人物卡!AN28+人物卡!R30+人物卡!AN27+人物卡!AN30+人物卡!AN23+人物卡!R26+人物卡!R17+人物卡!AN41+人物卡!AN45+人物卡!AN46-76) -> 50 | L5: =AVERAGE(人物卡!AG5+人物卡!AA7+人物卡!R16+人物卡!R17+人物卡!R25+人物卡!R27+人物卡!R32+人物卡!R43+人物卡!R46+人物卡!R47+人物卡!R48+人物卡!R49-人物卡!J49+人物卡!AN16+人物卡!AN17+人物卡!AN21+人物卡!AN22+人物卡!AN24+人物卡!AN28+人物卡!AN29+人物卡!AN31+人物卡!AN32+人物卡!AN33+人物卡!AN44-76) -> 224 | N5: =G14+I14 -> 160 | S5: ="敏捷×"&U5 -> 敏捷×0 | T5: =职业列表!I16 -> × | U5: =职业列表!J16 -> 0 | V5: =J14*U5 -> 0 | Y5: =IF(AND(U6>0,U5>0),"+","")
B6: 检测是否为数字 | C6: 最终年龄减值 | D6: 敏捷大小 | E6: =IF(E4>0,"1",IF(E4=0,"0",IF(E4<0,"-1"))) -> -1 | J6: =G5+H5+I5+J5+K5+L5 -> 1416 | N6: 非八十整数体格 | O6: 减485后八十的倍数 | P6: 最终体格出目 | R6: × | S6: ="体质×"&U6 -> 体质×0 | T6: =职业列表!I17 -> × | U6: =职业列表!J17 -> 0 | V6: =H14*U6 -> 0 | X6: =IF(U6>0,S6,"") | Y6: =IF(AND(U7>0,U6>0),"+","")
B7: =ISNUMBER(B5) -> TRUE | C7: =IF(ISBLANK(人物卡!E6),0,IF(人物卡!E6>=0,C5,0)) -> 0 | D7: 总值 | E7: =E6+E5 -> 0 | G7: 调查 | H7: 交涉 | I7: 战斗 | J7: 特技 | K7: 支援 | L7: 学问 | N7: =IF(N5<=1,"0",IF(N5<=64,"-2",IF(N5<=84,"-1",IF(N5<=124,"0",IF(N5<=164,"1",IF(N5<=204,"2",IF(N5<=284,"3",IF(N5>284,"4","0")))))))) -> 1 | O7: =INT((N5-285)/80) -> -2 | P7: =IF(O7>=0,O7+N7,N7) -> 1 | R7: √ | S7: ="体型×"&U7 -> 体型×0 | T7: =职业列表!I18 -> × | U7: =职业列表!J18 -> 0 | V7: =I14*U7 -> 0 | X7: =IF(U7>0,S7,"") | Y7: =IF(AND(U8>0,U7>0),"+","")
B8: 护甲表最终减值 | C8: =IF(B7=FALSE,"0",IF(A5=1,B5,0)) -> 0 | D8: 属性最终值 | E8: =IF(E7=2,"1",IF(E7=-2,"-1",0)) -> 0 | G8: =G5/J6 -> 0.19279661 | H8: =H5/J6 -> 0.22033898 | I8: =I5/J6 -> 0.30861582 | J8: =J5/J6 -> 0.084745763 | K8: =K5/J6 -> 0.035310734 | L8: =L5/J6 -> 0.15819209 | N8: 小于1D6的话 | O8: 超过1d6的话 | P8: 最终伤害加值出目 | S8: ="外貌×"&U8 -> 外貌×0 | T8: =职业列表!I19 -> × | U8: =职业列表!J19 -> 0 | V8: =K14*U8 -> 0 | X8: =IF(U8>0,S8,"") | Y8: =IF(AND(U9>0,U8>0),"+","")
B9: 最终补正值 | C9: =E8-C8-C7 -> 0 | N9: =IF(P7="-2","-2",IF(P7="-1","-1",IF(P7="0","0",IF(P7="1","+1D4",IF(P7=2,"+1D6",IF(P7>2,"D6",0)))))) -> +1D4 | O9: =IF(N9="D6",P7-1,"0") -> 0 | P9: =IF(N9="D6",O10,N9) -> +1D4 | S9: ="智力×"&U9 -> 智力×0 | T9: =职业列表!I20 -> × | U9: =职业列表!J20 -> 0 | V9: =L14*U9 -> 0 | X9: =IF(U9>0,S9,"") | Y9: =IF(AND(U10>0,U9>0),"+","") | AA9: =X4&Y4&X5&Y5&X6&Y6&X7&Y7&X8&Y8&X9&Y9&X10&Y10&X11&Y11&X12 -> 教育×4 | AF9: 最终值
B10: 格斗射击基础成功率 | O10: ="+"&O9&"D6" -> +0D6 | S10: ="教育×"&U10 -> 教育×4 | T10: =职业列表!I21 -> √ | U10: =职业列表!J21 -> 4 | V10: =N14*U10 -> 260 | X10: =IF(U10>0,S10,"") -> 教育×4 | Y10: =IF(AND(U11>0,U10>0),"+","") | AA10: =IF(AB10=职业列表!H25,1,0) -> 0 | AB10: 教育+其他属性点数中的最大值（官方） | AF10: =IF(AA10=1,MAX(V4:V9,V11:V12)+V10,0) -> 0
B11: 格斗1 | C11: =IF(人物卡!H35="鞭子","5",IF(人物卡!H35="电锯","10",IF(人物卡!H35="斧","15",IF(人物卡!H35="剑","20",IF(人物卡!H35="绞具","15",IF(人物卡!H35="链枷","10",IF(人物卡!H35="矛","20",IF(人物卡!H35=人物卡!AU28,人物卡!BA28,0)))))))) -> 0 | D11: 射击1 | E11: =IF(人物卡!H39="步枪/霰弹枪","25",IF(人物卡!H39="冲锋枪","15",IF(人物卡!H39="弓术","15",IF(人物卡!H39="喷射器","10",IF(人物卡!H39="机枪","10",IF(人物卡!H39="重武器","10",IF(人物卡!H39=人物卡!AU30,人物卡!BA30,0))))))) -> 0 | S11: ="意志×"&U11 -> 意志×0 | T11: =职业列表!I22 -> × | U11: =职业列表!J22 -> 0 | V11: =M14*U11 -> 0 | X11: =IF(U11>0,S11,"") | Y11: =IF(AND(U12>0,U11>0),"+","") | AA11: =IF(AB11=职业列表!H25,1,0) -> 0 | AB11: 教育+其他属性点数中的所有值 | AF11: =IF(AA11=1,V10+SUM(V4:V9,V11:V12),0) -> 0
B12: 格斗2 | C12: =IF(人物卡!H36="鞭子","5",IF(人物卡!H36="电锯","10",IF(人物卡!H36="斧","15",IF(人物卡!H36="剑","20",IF(人物卡!H36="绞具","15",IF(人物卡!H36="链枷","10",IF(人物卡!H36="矛","20",IF(人物卡!H36=人物卡!AU28,人物卡!BA28,0)))))))) -> 0 | D12: 射击2 | E12: =IF(人物卡!H40="步枪/霰弹枪","25",IF(人物卡!H40="冲锋枪","15",IF(人物卡!H40="弓术","15",IF(人物卡!H40="喷射器","10",IF(人物卡!H40="机枪","10",IF(人物卡!H40="重武器","10",IF(人物卡!H40=人物卡!AU30,人物卡!BA30,0))))))) -> 0 | G12: 属性雷达表 | H12: 基础属性 | I12: 出目 | S12: ="幸运×"&U12 -> 幸运×0 | T12: =职业列表!I23 -> × | U12: =职业列表!J23 -> 0 | V12: =O14*U12 -> 0 | X12: =IF(U12>0,S12,"") | AA12: =IF(AB12=职业列表!H25,1,0) -> 1 | AB12: 所有属性的点数相加 | AF12: =IF(AA12=1,SUM(V4:V12),0) -> 260
B13: 格斗3 | C13: =IF(人物卡!H37="鞭子","5",IF(人物卡!H37="电锯","10",IF(人物卡!H37="斧","15",IF(人物卡!H37="剑","20",IF(人物卡!H37="绞具","15",IF(人物卡!H37="链枷","10",IF(人物卡!H37=人物卡!AU28,人物卡!BA28,0))))))) -> 0 | D13: 射击3 | E13: =IF(人物卡!H41="步枪/霰弹枪","25",IF(人物卡!H41="冲锋枪","15",IF(人物卡!H41="弓术","15",IF(人物卡!H41="喷射器","10",IF(人物卡!H41="机枪","10",IF(人物卡!H41="重武器","10",IF(人物卡!H41=人物卡!AU30,人物卡!BA30,0))))))) -> 0 | G13: 力量 STR | H13: 体质 CON | I13: 体型 SIZ | J13: 敏捷 DEX | K13: 外貌 APP | L13: 智力 灵感 | M13: 意志 POW | N13: 教育 EDU | O13: 幸运 Luck
B14: 熟练下拉 | G14: =人物卡!U3 -> 90 | H14: =人物卡!U5 -> 50 | I14: =人物卡!U7 -> 70 | J14: =人物卡!AA3 -> 40 | K14: =人物卡!AA5 -> 65 | L14: =人物卡!AA7 -> 80 | M14: =人物卡!AG3 -> 75 | N14: =人物卡!AG5 -> 65 | O14: =人物卡!AG7 -> 70 | U14: 自定义技能剩余计算 | Z14: 战斗 | AA14: ←请选择类型 | AB14: 爆破 | AC14: 电气维修 | AD14: 炮术 | AE14: 投掷 | AF14: 格斗1 | AI14: 格斗2 | AL14: 格斗3 | AO14: 射击1 | AP14: 射击2 | AQ14: 射击3 | AR14: 斗殴 | AS14: 手枪 | AT14: 没有数值 | AU14: 最大值 | AV14: 最终出目 | AZ14: 出目 | BA14: =IF(AX27="仅显示1890_2012","",VLOOKUP(AX27,AZ25:BB29,3,FALSE)) -> 广播电台 茶包
B15: ★ | O15: 随身物品下拉表 | U15: 1 | V15: =人物卡!H39 -> 0 | W15: =IF(V15="步枪/霰弹枪",1,0) -> 0 | AA15: =IF(人物卡!M54=AA14,"") -> FALSE | AB15: =IF(人物卡!M54=人物卡!AB43,人物卡!AN43) -> FALSE | AC15: =IF(人物卡!M54=人物卡!F31,人物卡!R31) -> FALSE | AD15: =IF(人物卡!M54=人物卡!AB46,人物卡!AN46) -> FALSE | AE15: =IF(人物卡!M54=人物卡!AB39,人物卡!AN39) -> FALSE | AF15: =IF(人物卡!M54=人物卡!H35,人物卡!R35) -> 0 | AI15: =IF(人物卡!M54=人物卡!H36,人物卡!R36) -> 0 | AL15: =IF(人物卡!M54=人物卡!H37,人物卡!R37) -> 0 | AO15: =IF(人物卡!M54=人物卡!H39,人物卡!R39) -> 0 | AP15: =IF(人物卡!M54=人物卡!H40,人物卡!R40) -> 0 | AQ15: =IF(人物卡!M54=人物卡!H41,人物卡!R41) -> 0 | AR15: =IF(人物卡!M54=人物卡!H34,人物卡!R34) -> FALSE | AS15: =IF(人物卡!M54=人物卡!H38,人物卡!R38) -> FALSE | AT15: =IF(AU15=0,IF(人物卡!M54=附表!U220,附表!V220,IF(人物卡!M54=附表!U221,附表!V221,IF(人物卡!M54=附表!U219,附表!V219,IF(人物卡!M54=附表!U224,附表!V224,IF(人物卡!M54=附表!U225,附表!V225,IF(人物卡!M54=附表!U223,附表!V223,IF(人物卡!M54=附表!U222,附表!V222,IF(人物卡!M54=附表!U226,#REF!,IF(人物卡!M54=附表!Q220,附表!R220,IF(人物卡!M54=附表!Q221,附表!R221,IF(人物卡!M54=附表!Q222,附表!R222,IF(人物卡!M54=附表!Q223,附表!R223,IF(人物卡!M54=附表!Q224,附表!R224,IF(人物卡!M54=附表!Q219,附表!R219,IF(人物卡!M54=附表!Q225,附表!R225,"")))))))))))))))) | AU15: =MAX(AA15:AS15) -> 0 | AV15: =IF(AU15=0,AT15,AU15)
L16: san值计算 | O16: 颅———— | U16: 2 | V16: =人物卡!H40 -> 0 | W16: =IF(V16="步枪/霰弹枪",1,0) -> 0 | AA16: =IF(人物卡!M55=AA14,"") -> FALSE | AB16: =IF(人物卡!M55=AB14,人物卡!AN43) -> FALSE | AC16: =IF(人物卡!M55=AC14,人物卡!R31) -> FALSE | AD16: =IF(人物卡!M55=AD14,人物卡!AN46) -> FALSE | AE16: =IF(人物卡!M55=AE14,人物卡!AN39) -> FALSE | AF16: =IF(ISBLANK(人物卡!H35),FALSE,IF(人物卡!M55=人物卡!H35,人物卡!R35)) -> FALSE | AI16: =IF(ISBLANK(人物卡!H36),FALSE,IF(人物卡!M55=人物卡!H36,人物卡!R36)) -> FALSE | AL16: =IF(ISBLANK(人物卡!H37),FALSE,IF(人物卡!M55=人物卡!H37,人物卡!R37)) -> FALSE | AO16: =IF(ISBLANK(人物卡!H39),FALSE,IF(人物卡!M55=人物卡!H39,人物卡!R39)) -> FALSE | AP16: =IF(ISBLANK(人物卡!H40),FALSE,IF(人物卡!M55=人物卡!H40,人物卡!R40)) -> FALSE | AQ16: =IF(ISBLANK(人物卡!H41),FALSE,IF(人物卡!M55=人物卡!H41,人物卡!R41)) -> FALSE | AR16: =IF(人物卡!M55=AR14,人物卡!R34) -> 65 | AS16: =IF(人物卡!M55=AS14,人物卡!R38) -> FALSE | AT16: =IF(AU16=0,IF(人物卡!M55=附表!U220,附表!V220,IF(人物卡!M55=附表!U221,附表!V221,IF(人物卡!M55=附表!U219,附表!V219,IF(人物卡!M55=附表!U224,附表!V224,IF(人物卡!M55=附表!U225,附表!V225,IF(人物卡!M55=附表!U223,附表!V223,IF(人物卡!M55=附表!U222,附表!V222,IF(人物卡!M55=附表!U226,#REF!,IF(人物卡!M55=附表!Q220,附表!R220,IF(人物卡!M55=附表!Q221,附表!R221,IF(人物卡!M55=附表!Q222,附表!R222,IF(人物卡!M55=附表!Q223,附表!R223,IF(人物卡!M55=附表!Q224,附表!R224,IF(人物卡!M55=附表!Q219,附表!R219,IF(人物卡!M55=附表!Q225,附表!R225,"")))))))))))))))) -> FALSE | AU16: =MAX(AA16:AS16) -> 65 | AV16: =IF(AU16=0,AT16,AU16) -> 65
L17: 意志 | M17: 最大值 | O17: 头部 | R17: 健康 | S17: 清醒 | U17: 3 | V17: =人物卡!H41 -> 0 | W17: =IF(V17="步枪/霰弹枪",1,0) -> 0 | AA17: =IF(人物卡!M56=AA14,"") -> FALSE | AB17: =IF(人物卡!M56=AB14,人物卡!AN43) -> FALSE | AC17: =IF(人物卡!M56=AC14,人物卡!R31) -> FALSE | AD17: =IF(人物卡!M56=AD14,人物卡!AN46) -> FALSE | AE17: =IF(人物卡!M56=AE14,人物卡!AN39) -> FALSE | AF17: =IF(ISBLANK(人物卡!H35),FALSE,IF(人物卡!M56=人物卡!H35,人物卡!R35)) -> FALSE | AI17: =IF(ISBLANK(人物卡!H36),FALSE,IF(人物卡!M56=人物卡!H36,人物卡!R36)) -> FALSE | AL17: =IF(ISBLANK(人物卡!H37),FALSE,IF(人物卡!M56=人物卡!H37,人物卡!R37)) -> FALSE | AO17: =IF(ISBLANK(人物卡!H39),FALSE,IF(人物卡!M56=人物卡!H39,人物卡!R39)) -> FALSE | AP17: =IF(ISBLANK(人物卡!H40),FALSE,IF(人物卡!M56=人物卡!H40,人物卡!R40)) -> FALSE | AQ17: =IF(ISBLANK(人物卡!H41),FALSE,IF(人物卡!M56=人物卡!H41,人物卡!R41)) -> FALSE | AR17: =IF(人物卡!M56=AR14,人物卡!R34) -> FALSE | AS17: =IF(人物卡!M56=AS14,人物卡!R38) -> 70 | AT17: =IF(AU17=0,IF(人物卡!M56=附表!U220,附表!V220,IF(人物卡!M56=附表!U221,附表!V221,IF(人物卡!M56=附表!U219,附表!V219,IF(人物卡!M56=附表!U224,附表!V224,IF(人物卡!M56=附表!U225,附表!V225,IF(人物卡!M56=附表!U223,附表!V223,IF(人物卡!M56=附表!U222,附表!V222,IF(人物卡!M56=附表!U226,#REF!,IF(人物卡!M56=附表!Q220,附表!R220,IF(人物卡!M56=附表!Q221,附表!R221,IF(人物卡!M56=附表!Q222,附表!R222,IF(人物卡!M56=附表!Q223,附表!R223,IF(人物卡!M56=附表!Q224,附表!R224,IF(人物卡!M56=附表!Q219,附表!R219,IF(人物卡!M56=附表!Q225,附表!R225,"")))))))))))))))) -> FALSE | AU17: =MAX(AA17:AS17) -> 70 | AV17: =IF(AU17=0,AT17,AU17) -> 70
B18: 可选规则：有故事的调查员 | L18: =M14 -> 75 | M18: =人物卡!P10 -> 99 | O18: 头发 | R18: 昏迷 | S18: 临时疯狂 | U18: 自定义 | V18: =人物卡!AB48 -> 自定义技能 | W18: =IF(V18="自定义技能",1,0) -> 1
B19: 名称 | C19: san | D19: 技能 | E19: 备注 | L19: 最终值 | O19: 耳朵 | R19: 重伤 | S19: 不定性疯狂
B20: 战场经历包 | C20: 1d10+5 | D20: 70 | E20: 对目击尸体和重伤员造成的理智损失免疫;根据战争的年份和模组发生时的年份调整年龄；背景增加一项：战争相关的伤疤 / 疤痕或恐惧症 / 躁狂症 | L20: =IF(L18>M18,M18,L18) -> 75 | O20: 面部 | R20: 死亡 | S20: 永久疯狂 | AA20: 任意 | AR20: 特定时间
B21: 警务经历包 | C21: 1d10 | D21: 60 | E21: 对目击尸体造成的理智损失免疫;初始年龄不能低于 25 岁;背景增加一项：警察工作相关的伤疤 / 疤痕或恐惧症 / 躁狂症； | O21: 颈部 | R21: =IF(ISBLANK(人物卡!BK26),"",人物卡!BK26) | S21: =IF(ISBLANK(人物卡!BO26),"",人物卡!BO26) | AA21: =IF(ISBLANK(人物卡!BA18),0,1) -> 0 | AB21: =IF(ISBLANK(人物卡!BJ18),0,1) -> 0 | AD21: 总数 | AE21: 最终值 | AR21: =人物卡!BL129 -> 1920 | AS21: =IF(AR21="仅显示1890_2020","",VLOOKUP(AR21,AE33:AS163,15,FALSE)) -> 广播电台 茶包
B22: 罪犯经历包 | C22: 1d10 | D22: 60 | E22: 对目击尸体、目击或亲自谋杀、目击对人类的暴力残害造成的理智损失免疫;初始年龄不能低于 20 岁；背景增加一项：犯罪历史相关的伤疤 / 疤痕或恐惧症 / 躁狂症 | O22: 其他(头) | AA22: =IF(ISBLANK(人物卡!BA19),0,1) -> 0 | AB22: =IF(ISBLANK(人物卡!BJ19),0,1) -> 0 | AD22: =AA21+AA23+AA22+AA25+AA24+AB21+AB22+AB24+AB23+AB25 -> 0 | AE22: =IF(AD32=1,"仅显示1890_2020",AE28) -> 1980 | AF22: =IF(AE22="仅显示1890_2020","",VLOOKUP(AE22,AE33:AS163,2,FALSE)) -> 莫斯科奥运会 | AG22: =IF(AE22="仅显示1890～2020","",VLOOKUP(AE22,AE33:AS163,3,FALSE)) -> 0 | AH22: =IF(AE22="仅显示1890～2020","",VLOOKUP(AE22,AE33:AS163,4,FALSE)) -> 0 | AI22: =IF(AE22="仅显示1890_2020","",VLOOKUP(AE22,AE33:AS163,5,FALSE)) -> —— | AJ22: =IF(AE22="仅显示1890_2020","",VLOOKUP(AE22,AE33:AS163,6,FALSE)) -> 0 | AK22: =IF(AE22="仅显示1890_2020","",VLOOKUP(AE22,AE33:AS163,7,FALSE)) -> 0 | AL22: =IF(AE22="仅显示1890_2020","",VLOOKUP(AE22,AE33:AS163,8,FALSE)) -> 二十世纪 八十年代 | AM22: =IF(AE22="仅显示1890_2820","",VLOOKUP(AE22,AE33:AS163,9,FALSE)) -> 庚申猴年 | AN22: =IF(AE22="仅显示1890_2020","",VLOOKUP(AE22,AE33:AS163,10,FALSE)) -> 中华人民共和国31周年 | AO22: =IF(AE22="仅显示1890_2020","",VLOOKUP(AE22,AE33:AS163,11,FALSE)) -> 美国每盎司黄金达到802 美元 美国通胀率33 年来最高 银行业放松管制 圣海伦火山喷发死亡超过50 人 伊朗人质解救失败 波兰团结公会成立 亚马逊淘金热 杜比C型降噪器 美国公债9080 亿美元 美国人口2.265 亿 | AP22: =IF(AE22="仅显示1890_2020","",VLOOKUP(AE22,AE33:AS163,12,FALSE)) -> 总统： 吉米·卡特（民主党） | AQ22: =IF(AE22="仅显示1890_2020","",VLOOKUP(AE22,AE33:AS163,13,FALSE)) -> 艾滋病毒 强效可卡因 温室效应 CD 暗物质 暗能量 太阳能飞行器 甲型H1N1 流感 希格斯玻色子 引力波 | AR22: =IF(AE22="仅显示1890_2020","",VLOOKUP(AE22,AE33:AS163,14,FALSE)) -> 电气地铁 圣代冰淇淋 实用水电站 手电 电影摄影机 收音机 霍乱疫苗 啤酒瓶盖 柴油发动机 双向电报 实用的胶卷 块麦片 电报 可口可乐 X射线 卷烟机发明 电影放映机 排球 印名片机 福特车 潜望镜 油印蜡纸发明 阴极射线管 商品阿司匹林 凯洛格牌玉米片 手电筒 钋 镭 摇控器 α粒子 β粒子 打字机 柯达布朗尼相机 齐柏林飞艇 人类血型 跨大西洋电报 汽轮机游船 现代柏油路 铝罐奶粉 爆米花 泰迪熊 卡鲁索电唱机 便宜的肥皂和烹饪用油 飞机 荧光灯 邮戳机 摩托车发动机 热水瓶 农业轨道机械 木棉安全带 电动汽车喇叭 化学泡沫灭火器 狭义相对论 自动点唱机 量产舰艇舷外发动机 动画 电动洗衣机 家用洗洁精 立式吸尘器 饮用纸杯 双层公交车 无线电测向仪 电煎锅 质子和电子 玻璃纸 战壕风衣 汽车自动起动器 麦片 氯气毒气 防毒面具 拉链 机械雨刮器 广义相对论 芥子气 量产拖拉机 电子钟 黄油枪 降落伞 广播电台播音 茶包 罗夏墨迹测验 机器人 胰岛素 实用邮戳机 滑水 百日咳疫苗 纸制鸡蛋托 面巾纸 商用飞机农药喷撒 液体燃料火箭 劳力士防水表 遥控电唱机 面包机 防水玻璃纸 电传打字机 盖革计数器 纯维生素C 彩色电影胶片 透明胶带 音乐汽车喇叭 闪光灯 速冻食品 球形潜水舱 回旋加速器 折叠式雨伞 电动剃须刀 车载收音机 玛氏巧克力棒 变焦镜头 大富翁桌游 商业洗衣店 畅销平装书 里氏震级 磁带录音机 大众汽车 超市推车 带温控器的电熨斗 速溶咖啡 尼龙 圆珠笔 黄热病疫苗 雷达 汽车自动变速箱 充气救生衣 人工授精 青霉素 军用吉普车 原子裂变 火箭筒 凝固汽油弹 水肺 麦角酸二乙酰胺 神经毒气 原子弹 特百惠 计算机 静电复印法 比基尼泳衣 浓缩咖啡机 宝丽来相机 拼字盘 实心电吉他 尼龙扣 晶体管 黑胶唱片 有线电视 电视显像管 汽车自动点火装置 信用卡 复印机 宽荧幕电影 动力转向器 三色停车灯 人行红绿灯 晶体管助听器 氢弹 录像带 DNA双螺旋结构 麻疹疫苗 按动圆珠笔 硅晶体管 核导弹 空对空导弹 迪士尼乐园 特氟龙 卡丁车 地对空核导弹 沙宾疫苗 通讯卫星 呼啦圈 安全带 人工肾脏 避孕药 气象卫星 便携晶体管收音机 安定 砷化镓半导体激光器 三维全息技术 合成器 香烟健康警示 凯夫拉纤维 子午胎 IBM文字处理机 杜比A型降噪器 滑雪板 喇叭裤 绕月载人火箭 人工心脏移植 波音747喷气式客机 互联网 条形码 软盘 帆板 热裤 液晶显示 便携电子计算器 电视游戏 DNA重组技术 电子游戏机 超级计算机 光纤 试管婴儿 魔方 索尼Walkman 杜比C型降噪器 | AS22: =IF(AE22="仅显示1890_2020","",VLOOKUP(AE22,AE33:AS163,15,FALSE)) -> 杜比C型降噪器
B23: 医务经历包 | C23: 1d10 | D23: 60 | E23: 对目击尸体和重伤员造成的理智损失免疫;初始年龄不能低于 30 岁；背景增加一项：个人背景相关的伤疤 / 疤痕或恐惧症 / 躁狂症； | O23: 躯———— | Q23: 显露 | AA23: =IF(ISBLANK(人物卡!BA20),0,1) -> 0 | AB23: =IF(ISBLANK(人物卡!BJ20),0,1) -> 0 | AD23: 数 | AE23: 目前值
B24: 神话经历包 | C24: 如果是"相信者"，减少和克苏鲁神话相同的san值 | D24: 0 | E24: 按 KP 允许的数值增加「克苏鲁神话」技能;背景增加两项：与神话经历相关的伤疤 /疤痕、恐惧症 / 躁狂症、遭遇的怪异存在 | O24: 肩 | Q24: 隐藏 | S24: =".st "&"力量"&G14&"str"&G14&"敏捷"&J14&"dex"&J14&"意志"&M14&"pow"&M14&"体质"&H14&"con"&H14&"外貌"&K14&"app"&K14&"教育"&N14&"edu"&N14&"体型"&I14&"siz"&I14&"智力"&L14&"灵感"&L14&"int"&L14&"san"&人物卡!N10&"san值"&人物卡!N10&"理智"&人物卡!N10&"理智值"&人物卡!N10&"幸运"&O14&"运气"&O14&"mp"&人物卡!W10&"魔法"&人物卡!W10&"hp"&人物卡!E10&"体力"&人物卡!E10&人物卡!F16&人物卡!R16&人物卡!F17&人物卡!R17&人物卡!F18&人物卡!R18&人物卡!F19&人物卡!R19&IF(人物卡!H20="","",人物卡!H20&人物卡!R20)&IF(人物卡!H21="","",人物卡!H21&人物卡!R21)&IF(人物卡!H22="","",人物卡!H22&人物卡!R22)&人物卡!F23&人物卡!R23&"魅惑"&人物卡!R23&人物卡!F24&人物卡!R24&"计算机"&人物卡!R25&"计算机使用"&人物卡!R25&"电脑"&人物卡!R25&"信用"&人物卡!R26&"信誉"&人物卡!R26&"信用评级"&人物卡!R26&"克苏鲁"&人物卡!R27&"克苏鲁神话"&人物卡!R27&"cm"&人物卡!R27&人物卡!F28&人物卡!R28&人物卡!F29&人物卡!R29&"汽车"&人物卡!R30&"驾驶"&人物卡!R30&"汽车驾驶"&人物卡!R30&人物卡!F31&人物卡!R31&"电子学"&人物卡!R32&人物卡!F33&人物卡!R33&人物卡!H34&人物卡!R34&IF(人物卡!H35="","",人物卡!H35&人物卡!R35)&IF(人物卡!H36="","",人物卡!H36&人物卡!R36)&IF(人物卡!H37="","",人物卡!H36&人物卡!R37)&人物卡!H38&人物卡!R38&IF(W15=1,人物卡!AB39&人物卡!R39&"步枪"&人物卡!R39&"霰弹枪"&人物卡!R39&"步霰"&人物卡!R39,IF(人物卡!H39="","",人物卡!H39&人物卡!R39))&IF(W16=1,人物卡!AB40&人物卡!R40&"步枪"&人物卡!R40&"霰弹枪"&人物卡!R40&"步霰"&人物卡!R40,IF(人物卡!H40="","",人物卡!H40&人物卡!R40))&IF(W17=1,人物卡!AB41&人物卡!R41&"步枪"&人物卡!R41&"霰弹枪"&人物卡!R41&"步霰"&人物卡!R41,IF(人物卡!H41="","",人物卡!H41&人物卡!R41))&人物卡!F42&人物卡!R42&人物卡!F43&人物卡!R43&人物卡!F44&人物卡!R44&人物卡!F45&人物卡!R45&IF(人物卡!H46="","",人物卡!H46&人物卡!R46)&IF(人物卡!H47="","",人物卡!H47&人物卡!R47)&IF(人物卡!H48="","",人物卡!H48&人物卡!R48)&人物卡!F49&人物卡!R49&人物卡!AB16&人物卡!AN16&"图书馆"&人物卡!AN17&"图书馆使用"&人物卡!AN17&人物卡!AB18&人物卡!AN18&"开锁"&人物卡!AN19&"撬锁"&人物卡!AN19&"锁匠"&人物卡!AN19&人物卡!AB20&人物卡!AN20&人物卡!AB21&人物卡!AN21&"博物学"&人物卡!AN22&"自然学"&人物卡!AN22&"领航"&人物卡!AN23&"导航"&人物卡!AN23&人物卡!AB24&人物卡!AN24&"重型操作"&人物卡!AN25&"重型机械"&人物卡!AN25&"操作重型机械"&人物卡!AN25&"重型"&人物卡!AN25&人物卡!AB26&人物卡!AN26&IF(人物卡!AD27="","",人物卡!AD27&人物卡!AN27)&人物卡!AB28&人物卡!AN28&人物卡!AB29&人物卡!AN29&人物卡!AB30&人物卡!AN30&IF(人物卡!AD31="","",人物卡!AD31&人物卡!AN31)&IF(人物卡!AD32="","",人物卡!AD32&人物卡!AN32)&IF(人物卡!AD33="","",人物卡!AD33&人物卡!AN33)&人物卡!AB34&人物卡!AN34&人物卡!AB35&人物卡!AN35&人物卡!AB36&人物卡!AN36&"生存"&人物卡!AN37&人物卡!AB38&人物卡!AN38&人物卡!AB39&人物卡!AN39&人物卡!AB40&人物卡!AN40&人物卡!AB41&人物卡!AN41&人物卡!AB42&人物卡!AN42&人物卡!AB43&人物卡!AN43&人物卡!AB44&人物卡!AN44&人物卡!AB45&人物卡!AN45&人物卡!AB46&人物卡!AN46&IF(人物卡!AD47="","",人物卡!AD47&人物卡!AN47)&IF(W18=1,"",人物卡!AB48&人物卡!AN48)&IF(人物卡!AB49="","",人物卡!AB49&人物卡!AN49) -> .st 力量90str90敏捷40dex40意志75pow75体质50con50外貌65app65教育65edu65体型70siz70智力80灵感80int80san75san值75理智75理智值75幸运70运气70mp15魔法15hp12体力12会计5人类学1估价5考古学1取悦49魅惑49攀爬20计算机5计算机使用5电脑5信用50信誉50信用评级50克苏鲁0克苏鲁神话0cm0乔装5闪避44汽车20驾驶20汽车驾驶20电气维修10电子学1话术5斗殴65手枪70急救30历史5恐吓15跳跃20母语65法律5图书馆20图书馆使用20聆听49开锁1撬锁1锁匠1机械维修10医学1博物学50自然学50领航10导航10神秘学5重型操作1重型机械1操作重型机械1重型1说服49精神分析1心理学49骑术5妙手10侦查70潜行60生存10游泳20投掷20追踪50驯兽5潜水1爆破1读唇1催眠1炮术1 | AA24: =IF(ISBLANK(人物卡!BA21),0,1) -> 0 | AB24: =IF(ISBLANK(人物卡!BJ21),0,1) -> 0 | AD24: =人物卡!F9-AD22 -> 0 | AE24: =人物卡!G8 -> 1980 | AX24: 总值 | AZ24: 分类
B25: =IF(ISBLANK(人物卡!BC26),"自定义经历包",人物卡!BC26) -> 自定义经历包 | C25: ='简化卡 骰娘导入'!E90 | D25: ='简化卡 骰娘导入'!H90 | E25: ='简化卡 骰娘导入'!J90 | O25: 胸前 | X25: 会计 | AA25: =IF(ISBLANK(人物卡!BA22),0,1) -> 0 | AB25: =IF(ISBLANK(人物卡!BJ22),0,1) -> 0 | AC25: 最终 | AD25: =IF(AD24=0,"无",IF(AD24<0,"过多！",AD24)) -> 无 | AE25: 公元调整 | AT25: 未出现的 | AV25: =IF(AT25=人物卡!AZ129,1,0) -> 0 | AZ25: 1 | BA25: 未出现的发明 | BB25: =AQ22 -> 艾滋病毒 强效可卡因 温室效应 CD 暗物质 暗能量 太阳能飞行器 甲型H1N1 流感 希格斯玻色子 引力波
B26: 无 | O26: 背后 | X26: 人类学 | AE26: =IF(人物卡!E8="公元前",人物卡!G8*2,0) -> 0 | AT26: 已出现的 | AV26: =IF(AT26=人物卡!AZ129,2,0) -> 0 | AZ26: 2 | BA26: 已出现的发明 | BB26: =AR22 -> 电气地铁 圣代冰淇淋 实用水电站 手电 电影摄影机 收音机 霍乱疫苗 啤酒瓶盖 柴油发动机 双向电报 实用的胶卷 块麦片 电报 可口可乐 X射线 卷烟机发明 电影放映机 排球 印名片机 福特车 潜望镜 油印蜡纸发明 阴极射线管 商品阿司匹林 凯洛格牌玉米片 手电筒 钋 镭 摇控器 α粒子 β粒子 打字机 柯达布朗尼相机 齐柏林飞艇 人类血型 跨大西洋电报 汽轮机游船 现代柏油路 铝罐奶粉 爆米花 泰迪熊 卡鲁索电唱机 便宜的肥皂和烹饪用油 飞机 荧光灯 邮戳机 摩托车发动机 热水瓶 农业轨道机械 木棉安全带 电动汽车喇叭 化学泡沫灭火器 狭义相对论 自动点唱机 量产舰艇舷外发动机 动画 电动洗衣机 家用洗洁精 立式吸尘器 饮用纸杯 双层公交车 无线电测向仪 电煎锅 质子和电子 玻璃纸 战壕风衣 汽车自动起动器 麦片 氯气毒气 防毒面具 拉链 机械雨刮器 广义相对论 芥子气 量产拖拉机 电子钟 黄油枪 降落伞 广播电台播音 茶包 罗夏墨迹测验 机器人 胰岛素 实用邮戳机 滑水 百日咳疫苗 纸制鸡蛋托 面巾纸 商用飞机农药喷撒 液体燃料火箭 劳力士防水表 遥控电唱机 面包机 防水玻璃纸 电传打字机 盖革计数器 纯维生素C 彩色电影胶片 透明胶带 音乐汽车喇叭 闪光灯 速冻食品 球形潜水舱 回旋加速器 折叠式雨伞 电动剃须刀 车载收音机 玛氏巧克力棒 变焦镜头 大富翁桌游 商业洗衣店 畅销平装书 里氏震级 磁带录音机 大众汽车 超市推车 带温控器的电熨斗 速溶咖啡 尼龙 圆珠笔 黄热病疫苗 雷达 汽车自动变速箱 充气救生衣 人工授精 青霉素 军用吉普车 原子裂变 火箭筒 凝固汽油弹 水肺 麦角酸二乙酰胺 神经毒气 原子弹 特百惠 计算机 静电复印法 比基尼泳衣 浓缩咖啡机 宝丽来相机 拼字盘 实心电吉他 尼龙扣 晶体管 黑胶唱片 有线电视 电视显像管 汽车自动点火装置 信用卡 复印机 宽荧幕电影 动力转向器 三色停车灯 人行红绿灯 晶体管助听器 氢弹 录像带 DNA双螺旋结构 麻疹疫苗 按动圆珠笔 硅晶体管 核导弹 空对空导弹 迪士尼乐园 特氟龙 卡丁车 地对空核导弹 沙宾疫苗 通讯卫星 呼啦圈 安全带 人工肾脏 避孕药 气象卫星 便携晶体管收音机 安定 砷化镓半导体激光器 三维全息技术 合成器 香烟健康警示 凯夫拉纤维 子午胎 IBM文字处理机 杜比A型降噪器 滑雪板 喇叭裤 绕月载人火箭 人工心脏移植 波音747喷气式客机 互联网 条形码 软盘 帆板 热裤 液晶显示 便携电子计算器 电视游戏 DNA重组技术 电子游戏机 超级计算机 光纤 试管婴儿 魔方 索尼Walkman 杜比C型降噪器
C27: =IF(人物卡!F113=B20,C20,0) -> 0 | D27: =IF(人物卡!F113=B20,D20,0) -> 0 | E27: =IF(人物卡!F113=B20,E20,0) -> 0 | O27: 肋 | X27: 估价 | AB27: 经历包剩余点 | AC27: =D34-SUM(人物卡!L16:L49,人物卡!AH16:AH49) -> 0 | AD27: 最终值 | AE27: 调整出目 | AX27: =AV25+AV26+AV28+AV29+AV30 -> 4 | AZ27: 3 | BA27: 本年的发明 | BB27: =AS22 -> 杜比C型降噪器
C28: =IF(人物卡!F113=B21,C21,0) -> 0 | D28: =IF(人物卡!F113=B21,D21,0) -> 0 | E28: =IF(人物卡!F113=B21,E21,0) -> 0 | O28: 裆 | X28: 考古学 | AB28: 检测是否为数字 | AC28: =ISNUMBER(AC27) -> TRUE | AD28: =IF(AC28=FALSE,"0",AC27) -> 0 | AE28: =AE24-AE26 -> 1980 | AT28: 本年的发明 | AV28: =IF(AT28=人物卡!AZ129,3,0) -> 0 | AZ28: 4 | BA28: 查找年份发明 | BB28: =AS21 -> 广播电台 茶包
C29: =IF(人物卡!F113=B22,C22,0) -> 0 | D29: =IF(人物卡!F113=B22,D22,0) -> 0 | E29: =IF(人物卡!F113=B22,E22,0) -> 0 | O29: 腰 | X29: 技艺① | AB29: 职业点数 | AC29: =IF(人物卡!M5=0," ",LOOKUP(人物卡!M5,职业列表!A2:C232,职业列表!F2:F232)) -> 310 | AD29: 检测大小 | AT29: 查找年份发明 | AV29: =IF(AT29=人物卡!AZ129,4,0) -> 4 | AZ29: 5 | BA29: 查找发明的时间 | BB29: ?
C30: =IF(人物卡!F113=B23,C23,0) -> 0 | D30: =IF(人物卡!F113=B23,D23,0) -> 0 | E30: =IF(人物卡!F113=B23,E23,0) -> 0 | O30: 胯 | X30: 技艺② | AD30: =IF(AE30="大",1,0) -> 0 | AE30: =IF(AE28>2020,"大") -> FALSE | AT30: 研发中... | AU30: 查找发明的时间 | AV30: =IF(AU30=人物卡!AZ129,5,0) -> 0
C31: =IF(人物卡!F113=B24,C24,0) -> 0 | D31: =IF(人物卡!F113=B24,D24,0) -> 0 | E31: =IF(人物卡!F113=B24,E24,0) -> 0 | O31: 其他(躯) | X31: 技艺③ | AD31: =IF(AE31="小",1,0) -> 0 | AE31: =IF(AE28<1890,"小") -> FALSE
C32: =IF(人物卡!F113=B25,C25,0) -> 0 | D32: =IF(人物卡!F113=B25,D25,0) -> 0 | E32: =IF(人物卡!F113=B25,E25,0) -> 0 | O32: 服———— | X32: 取悦 | AD32: =AD30+AD31 -> 0 | AE32: 年份 | AF32: 国际重大时代标志 | AG32: 2 | AH32: 3 | AI32: 中国重大时代标志 | AL32: 年代 | AO32: 重大事件 | AP32: 名人 | AQ32: 未出现的发明 | AR32: 已出现的发明 | AS32: 本年发明
O33: 衣兜 | X33: 攀爬 | AE33: 1890 | AF33: 梵高饮弹自尽 | AG33: 发现火星“人工运河” | AI33: —— | AL33: 十九世纪 九十年代 | AM33: 庚寅虎年 | AN33: 清光绪16年 | AO33: 芝加哥建设世界首座全钢结构建筑 伦敦首条电气地铁 英国鱼雷巡洋舰蛇号在西班牙海岸失事，死亡 167 人 坐牛在印第安人起义中被杀 首个圣代冰淇淋 美国总人口达到 629 万 | AP33: 总统： 本杰明·哈里森（共和党） | AQ33: 实用水电站 手电 电影摄影机 收音机 霍乱疫苗 啤酒瓶盖 柴油发动机 双向电报 实用的胶卷 块麦片 电报 可口可乐 X射线 卷烟机发明 电影放映机 排球 印名片机福特车 潜望镜 油印蜡纸发明 阴极射线管 商品阿司匹林 凯洛格牌玉米片 手电筒 钋 镭 摇控器 α粒子 β粒子 打字机 柯达布朗尼相机 齐柏林飞艇 人类血型 跨大西洋电报 汽轮机游船 现代柏油路 铝罐奶粉 爆米花 泰迪熊 卡鲁索电唱机 便宜的肥皂和烹饪用油 飞机 荧光灯 邮戳机 摩托车发动机 热水瓶 农业轨道机械 木棉安全带 电动汽车喇叭 化学泡沫灭火器 狭义相对论 自动点唱机 量产舰艇舷外发动机 动画 电动洗衣机 家用洗洁精 立式吸尘器 饮用纸杯 双层公交车 无线电测向仪 电煎锅 质子和电子 玻璃纸 战壕风衣 汽车自动起动器 麦片 氯气毒气 防毒面具 拉链 机械雨刮器 广义相对论 芥子气 量产拖拉机 电子钟 黄油枪 降落伞 广播电台播音 茶包 罗夏墨迹测验 机器人 胰岛素 实用邮戳机 滑水 百日咳疫苗 纸制鸡蛋托 面巾纸 商用飞机农药喷撒 液体燃料火箭 劳力士防水表 遥控电唱机 面包机 防水玻璃纸 电传打字机 盖革计数器 纯维生素C 彩色电影胶片 透明胶带 音乐汽车喇叭 闪光灯 速冻食品 球形潜水舱 回旋加速器 折叠式雨伞 电动剃须刀 车载收音机 玛氏巧克力棒 变焦镜头 大富翁桌游 商业洗衣店 畅销平装书 里氏震级 磁带录音机 大众汽车 超市推车 带温控器的电熨斗 速溶咖啡 尼龙 圆珠笔 黄热病疫苗 雷达 汽车自动变速箱 充气救生衣 人工授精 青霉素 军用吉普车 原子裂变 火箭筒 凝固汽油弹 水肺 麦角酸二乙酰胺 神经毒气 原子弹 特百惠 计算机 静电复印法 比基尼泳衣 浓缩咖啡机 宝丽来相机 拼字盘 实心电吉他 尼龙扣 晶体管 黑胶唱片 有线电视 电视显像管 汽车自动点火装置 信用卡 复印机 宽荧幕电影 动力转向器 三色停车灯 人行红绿灯 晶体管助听器 氢弹 录像带 DNA双螺旋结构 麻疹疫苗 按动圆珠笔 硅晶体管 核导弹 空对空导弹 迪士尼乐园 特氟龙 卡丁车 地对空核导弹 沙宾疫苗 通讯卫星 呼啦圈 安全带 人工肾脏 避孕药 气象卫星 便携晶体管收音机 安定 砷化镓半导体激光器 三维全息技术 合成器 香烟健康警示 凯夫拉纤维 子午胎 IBM文字处理机 杜比A型降噪器 滑雪板 喇叭裤 绕月载人火箭 人工心脏移植 波音747喷气式客机 互联网 条形码 软盘 帆板 热裤 液晶显示 便携电子计算器 电视游戏 DNA重组技术 电子游戏机 超级计算机 光纤 试管婴儿 魔方 索尼Walkman 杜比C型降噪器 艾滋病毒 强效可卡因 温室效应 CD 暗物质 暗能量 太阳能飞行器 甲型H1N1 流感 希格斯玻色子 引力波 | AR33: 电气地铁 圣代冰淇淋 | AS33: 电气地铁 圣代冰淇淋 | AT33: 1890
C34: =IF(C27=0,IF(C28=0,IF(C29=0,IF(C30=0,IF(C31=0,IF(C32=0,"",C32),C31),C30),C29),C28),C27) | D34: =IF(D27=0,IF(D28=0,IF(D29=0,IF(D30=0,IF(D31=0,IF(D32=0,0,D32),D31),D30),D29),D28),D27) -> 0 | E34: =IF(E27=0,IF(E28=0,IF(E29=0,IF(E30=0,IF(E31=0,IF(E32=0,"",E32),E31),E30),E29),E28),E27) | O34: 内衬 | X34: 计算机使用 Ω | AE34: 1891 | AF34: 马德里协定 | AI34: —— | AL34: 十九世纪 九十年代 | AM34: 辛卯兔年 | AN34: 清光绪17年 | AO34: 日本浓尾大地震，毁坏 2 万房屋，死亡 2.5万人 首个实用水电站 英国普及手电 爱迪生申请到电影摄影机的专利权 爱迪生拿到收音机的专利 | AP34: 总统： 本杰明·哈里森（共和党） | AQ34: 霍乱疫苗 啤酒瓶盖 柴油发动机 双向电报 实用的胶卷 块麦片 电报 可口可乐 X射线 卷烟机发明 电影放映机 排球 印名片机福特车 潜望镜 油印蜡纸发明 阴极射线管 商品阿司匹林 凯洛格牌玉米片 手电筒 钋 镭 摇控器 α粒子 β粒子 打字机 柯达布朗尼相机 齐柏林飞艇 人类血型 跨大西洋电报 汽轮机游船 现代柏油路 铝罐奶粉 爆米花 泰迪熊 卡鲁索电唱机 便宜的肥皂和烹饪用油 飞机 荧光灯 邮戳机 摩托车发动机 热水瓶 农业轨道机械 木棉安全带 电动汽车喇叭 化学泡沫灭火器 狭义相对论 自动点唱机 量产舰艇舷外发动机 动画 电动洗衣机 家用洗洁精 立式吸尘器 饮用纸杯 双层公交车 无线电测向仪 电煎锅 质子和电子 玻璃纸 战壕风衣 汽车自动起动器 麦片 氯气毒气 防毒面具 拉链 机械雨刮器 广义相对论 芥子气 量产拖拉机 电子钟 黄油枪 降落伞 广播电台播音 茶包 罗夏墨迹测验 机器人 胰岛素 实用邮戳机 滑水 百日咳疫苗 纸制鸡蛋托 面巾纸 商用飞机农药喷撒 液体燃料火箭 劳力士防水表 遥控电唱机 面包机 防水玻璃纸 电传打字机 盖革计数器 纯维生素C 彩色电影胶片 透明胶带 音乐汽车喇叭 闪光灯 速冻食品 球形潜水舱 回旋加速器 折叠式雨伞 电动剃须刀 车载收音机 玛氏巧克力棒 变焦镜头 大富翁桌游 商业洗衣店 畅销平装书 里氏震级 磁带录音机 大众汽车 超市推车 带温控器的电熨斗 速溶咖啡 尼龙 圆珠笔 黄热病疫苗 雷达 汽车自动变速箱 充气救生衣 人工授精 青霉素 军用吉普车 原子裂变 火箭筒 凝固汽油弹 水肺 麦角酸二乙酰胺 神经毒气 原子弹 特百惠 计算机 静电复印法 比基尼泳衣 浓缩咖啡机 宝丽来相机 拼字盘 实心电吉他 尼龙扣 晶体管 黑胶唱片 有线电视 电视显像管 汽车自动点火装置 信用卡 复印机 宽荧幕电影 动力转向器 三色停车灯 人行红绿灯 晶体管助听器 氢弹 录像带 DNA双螺旋结构 麻疹疫苗 按动圆珠笔 硅晶体管 核导弹 空对空导弹 迪士尼乐园 特氟龙 卡丁车 地对空核导弹 沙宾疫苗 通讯卫星 呼啦圈 安全带 人工肾脏 避孕药 气象卫星 便携晶体管收音机 安定 砷化镓半导体激光器 三维全息技术 合成器 香烟健康警示 凯夫拉纤维 子午胎 IBM文字处理机 杜比A型降噪器 滑雪板 喇叭裤 绕月载人火箭 人工心脏移植 波音747喷气式客机 互联网 条形码 软盘 帆板 热裤 液晶显示 便携电子计算器 电视游戏 DNA重组技术 电子游戏机 超级计算机 光纤 试管婴儿 魔方 索尼Walkman 杜比C型降噪器 艾滋病毒 强效可卡因 温室效应 CD 暗物质 暗能量 太阳能飞行器 甲型H1N1 流感 希格斯玻色子 引力波 | AR34: 电气地铁 圣代冰淇淋 实用水电站 手电 电影摄影机 收音机 | AS34: 实用水电站 手电 电影摄影机 收音机 | AT34: 1891
O35: 衣服内 | X35: 信用评级 | AE35: 1892 | AF35: —— | AI35: —— | AL35: 十九世纪 九十年代 | AM35: 壬辰龙年 | AN35: 清光绪18年 | AO35: 宾夕法尼亚州石油城暴发洪水，死亡130 人 霍乱疫苗 开普敦 - 约翰内斯堡铁路竣工 啤酒瓶盖发明 柴油发动机取得专利 爱迪生获得双向电报的专利权 | AP35: 书籍： 阿瑟·柯南·道尔出版《福尔摩斯办案记》（The Adventures of Sherlock Holmes） 总统： 本杰明·哈里森（共和党） | AQ35: 实用的胶卷 块麦片 电报 可口可乐 X射线 卷烟机发明 电影放映机 排球 印名片机福特车 潜望镜 油印蜡纸发明 阴极射线管 商品阿司匹林 凯洛格牌玉米片 手电筒 钋 镭 摇控器 α粒子 β粒子 打字机 柯达布朗尼相机 齐柏林飞艇 人类血型 跨大西洋电报 汽轮机游船 现代柏油路 铝罐奶粉 爆米花 泰迪熊 卡鲁索电唱机 便宜的肥皂和烹饪用油 飞机 荧光灯 邮戳机 摩托车发动机 热水瓶 农业轨道机械 木棉安全带 电动汽车喇叭 化学泡沫灭火器 狭义相对论 自动点唱机 量产舰艇舷外发动机 动画 电动洗衣机 家用洗洁精 立式吸尘器 饮用纸杯 双层公交车 无线电测向仪 电煎锅 质子和电子 玻璃纸 战壕风衣 汽车自动起动器 麦片 氯气毒气 防毒面具 拉链 机械雨刮器 广义相对论 芥子气 量产拖拉机 电子钟 黄油枪 降落伞 广播电台播音 茶包 罗夏墨迹测验 机器人 胰岛素 实用邮戳机 滑水 百日咳疫苗 纸制鸡蛋托 面巾纸 商用飞机农药喷撒 液体燃料火箭 劳力士防水表 遥控电唱机 面包机 防水玻璃纸 电传打字机 盖革计数器 纯维生素C 彩色电影胶片 透明胶带 音乐汽车喇叭 闪光灯 速冻食品 球形潜水舱 回旋加速器 折叠式雨伞 电动剃须刀 车载收音机 玛氏巧克力棒 变焦镜头 大富翁桌游 商业洗衣店 畅销平装书 里氏震级 磁带录音机 大众汽车 超市推车 带温控器的电熨斗 速溶咖啡 尼龙 圆珠笔 黄热病疫苗 雷达 汽车自动变速箱 充气救生衣 人工授精 青霉素 军用吉普车 原子裂变 火箭筒 凝固汽油弹 水肺 麦角酸二乙酰胺 神经毒气 原子弹 特百惠 计算机 静电复印法 比基尼泳衣 浓缩咖啡机 宝丽来相机 拼字盘 实心电吉他 尼龙扣 晶体管 黑胶唱片 有线电视 电视显像管 汽车自动点火装置 信用卡 复印机 宽荧幕电影 动力转向器 三色停车灯 人行红绿灯 晶体管助听器 氢弹 录像带 DNA双螺旋结构 麻疹疫苗 按动圆珠笔 硅晶体管 核导弹 空对空导弹 迪士尼乐园 特氟龙 卡丁车 地对空核导弹 沙宾疫苗 通讯卫星 呼啦圈 安全带 人工肾脏 避孕药 气象卫星 便携晶体管收音机 安定 砷化镓半导体激光器 三维全息技术 合成器 香烟健康警示 凯夫拉纤维 子午胎 IBM文字处理机 杜比A型降噪器 滑雪板 喇叭裤 绕月载人火箭 人工心脏移植 波音747喷气式客机 互联网 条形码 软盘 帆板 热裤 液晶显示 便携电子计算器 电视游戏 DNA重组技术 电子游戏机 超级计算机 光纤 试管婴儿 魔方 索尼Walkman 杜比C型降噪器 艾滋病毒 强效可卡因 温室效应 CD 暗物质 暗能量 太阳能飞行器 甲型H1N1 流感 希格斯玻色子 引力波 | AR35: 电气地铁 圣代冰淇淋 实用水电站 手电 电影摄影机 收音机 霍乱疫苗 啤酒瓶盖 柴油发动机 双向电报 | AS35: 霍乱疫苗 啤酒瓶盖 柴油发动机 双向电报 | AT35: 1892
C36: 年龄 | D36: 最终值 | I36: 毒剂示例 | O36: 裤兜 | X36: 克苏鲁神话 | AE36: 1893 | AF36: 新西兰给予女性投票权 | AG36: 第一次里夫战争 | AI36: —— | AL36: 十九世纪 九十年代 | AM36: 癸巳蛇年 | AN36: 清光绪19年 | AO36: 飓风造成的洪水袭击美国南部西海岸 ,死亡 2000 人 首个实用的胶卷 块麦片 芝加哥万国博览会 | AP36: 总统： 本杰明·哈里森（共和党） 格罗佛·克利夫兰（民主党） | AQ36: 电报 可口可乐 X射线 卷烟机发明 电影放映机 排球 印名片机福特车 潜望镜 油印蜡纸发明 阴极射线管 商品阿司匹林 凯洛格牌玉米片 手电筒 钋 镭 摇控器 α粒子 β粒子 打字机 柯达布朗尼相机 齐柏林飞艇 人类血型 跨大西洋电报 汽轮机游船 现代柏油路 铝罐奶粉 爆米花 泰迪熊 卡鲁索电唱机 便宜的肥皂和烹饪用油 飞机 荧光灯 邮戳机 摩托车发动机 热水瓶 农业轨道机械 木棉安全带 电动汽车喇叭 化学泡沫灭火器 狭义相对论 自动点唱机 量产舰艇舷外发动机 动画 电动洗衣机 家用洗洁精 立式吸尘器 饮用纸杯 双层公交车 无线电测向仪 电煎锅 质子和电子 玻璃纸 战壕风衣 汽车自动起动器 麦片 氯气毒气 防毒面具 拉链 机械雨刮器 广义相对论 芥子气 量产拖拉机 电子钟 黄油枪 降落伞 广播电台播音 茶包 罗夏墨迹测验 机器人 胰岛素 实用邮戳机 滑水 百日咳疫苗 纸制鸡蛋托 面巾纸 商用飞机农药喷撒 液体燃料火箭 劳力士防水表 遥控电唱机 面包机 防水玻璃纸 电传打字机 盖革计数器 纯维生素C 彩色电影胶片 透明胶带 音乐汽车喇叭 闪光灯 速冻食品 球形潜水舱 回旋加速器 折叠式雨伞 电动剃须刀 车载收音机 玛氏巧克力棒 变焦镜头 大富翁桌游 商业洗衣店 畅销平装书 里氏震级 磁带录音机 大众汽车 超市推车 带温控器的电熨斗 速溶咖啡 尼龙 圆珠笔 黄热病疫苗 雷达 汽车自动变速箱 充气救生衣 人工授精 青霉素 军用吉普车 原子裂变 火箭筒 凝固汽油弹 水肺 麦角酸二乙酰胺 神经毒气 原子弹 特百惠 计算机 静电复印法 比基尼泳衣 浓缩咖啡机 宝丽来相机 拼字盘 实心电吉他 尼龙扣 晶体管 黑胶唱片 有线电视 电视显像管 汽车自动点火装置 信用卡 复印机 宽荧幕电影 动力转向器 三色停车灯 人行红绿灯 晶体管助听器 氢弹 录像带 DNA双螺旋结构 麻疹疫苗 按动圆珠笔 硅晶体管 核导弹 空对空导弹 迪士尼乐园 特氟龙 卡丁车 地对空核导弹 沙宾疫苗 通讯卫星 呼啦圈 安全带 人工肾脏 避孕药 气象卫星 便携晶体管收音机 安定 砷化镓半导体激光器 三维全息技术 合成器 香烟健康警示 凯夫拉纤维 子午胎 IBM文字处理机 杜比A型降噪器 滑雪板 喇叭裤 绕月载人火箭 人工心脏移植 波音747喷气式客机 互联网 条形码 软盘 帆板 热裤 液晶显示 便携电子计算器 电视游戏 DNA重组技术 电子游戏机 超级计算机 光纤 试管婴儿 魔方 索尼Walkman 杜比C型降噪器 艾滋病毒 强效可卡因 温室效应 CD 暗物质 暗能量 太阳能飞行器 甲型H1N1 流感 希格斯玻色子 引力波 | AR36: 电气地铁 圣代冰淇淋 实用水电站 手电 电影摄影机 收音机 霍乱疫苗 啤酒瓶盖 柴油发动机 双向电报 实用的胶卷 块麦片 | AS36: 实用的胶卷 块麦片 | AT36: 1893 | AV36: 电报 可口可乐
C37: =ABS(人物卡!E6) -> 31 | D37: =IF(ISBLANK(人物卡!AU37),IF(AND(C37>=15,C37<=19),D39,IF(AND(C37>=20,C37<=39),D40,IF(AND(C37>=40,C37<=49),D41,IF(AND(C37>=50,C37<=59),D42,IF(AND(C37>=60,C37<=69),D43,IF(AND(C37>=70,C37<=79),D44,IF(AND(C37>=80,C37<=89),D45,IF(ABS(C37)>=90,D48,"请和kp商议")))))))),人物卡!AU37) -> 教育进步*1 | I37: 毒剂名称 | J37: 生效时间 | K37: 症状 | L37: 伤害 | M37: 备注 | O37: 其他(服) | S37: =IF(人物卡!M4="","","时代:"&人物卡!M4&CHAR(9))&IF(人物卡!E5="","","职业:"&人物卡!E5&CHAR(9))&IF(人物卡!E6="","","年龄"&人物卡!E6&" ")&IF(人物卡!M6="","","性别:"&人物卡!M6&CHAR(9))&IF(人物卡!E7="","","住地:"&人物卡!E7&CHAR(9))&IF(人物卡!M7="","","出身:"&人物卡!M7&CHAR(9)) -> 时代:1920s 职业:探险家 年龄31 性别:男 住地:法国 里昂 出身:法国 格勒诺布尔 | X37: 乔装 | AE37: 1894 | AF37: 朝鲜东学党起义 | AG37: 奥林匹克委员会成立 | AI37: 中日甲午战争 | AJ37: 孙中山建立兴中会 | AL37: 十九世纪 九十年代 | AM37: 甲午马年 | AN37: 清光绪20年 | AO37: 明尼苏达森林大火，死亡 480 人 德雷福斯事件，其被流放魔鬼岛 首份电报 瓶装可口可乐 | AP37: 总统： 格罗佛·克利夫兰（民主党） | AQ37: X射线 卷烟机发明 电影放映机 排球 印名片机福特车 潜望镜 油印蜡纸发明 阴极射线管 商品阿司匹林 凯洛格牌玉米片 手电筒 钋 镭 摇控器 α粒子 β粒子 打字机 柯达布朗尼相机 齐柏林飞艇 人类血型 跨大西洋电报 汽轮机游船 现代柏油路 铝罐奶粉 爆米花 泰迪熊 卡鲁索电唱机 便宜的肥皂和烹饪用油 飞机 荧光灯 邮戳机 摩托车发动机 热水瓶 农业轨道机械 木棉安全带 电动汽车喇叭 化学泡沫灭火器 狭义相对论 自动点唱机 量产舰艇舷外发动机 动画 电动洗衣机 家用洗洁精 立式吸尘器 饮用纸杯 双层公交车 无线电测向仪 电煎锅 质子和电子 玻璃纸 战壕风衣 汽车自动起动器 麦片 氯气毒气 防毒面具 拉链 机械雨刮器 广义相对论 芥子气 量产拖拉机 电子钟 黄油枪 降落伞 广播电台播音 茶包 罗夏墨迹测验 机器人 胰岛素 实用邮戳机 滑水 百日咳疫苗 纸制鸡蛋托 面巾纸 商用飞机农药喷撒 液体燃料火箭 劳力士防水表 遥控电唱机 面包机 防水玻璃纸 电传打字机 盖革计数器 纯维生素C 彩色电影胶片 透明胶带 音乐汽车喇叭 闪光灯 速冻食品 球形潜水舱 回旋加速器 折叠式雨伞 电动剃须刀 车载收音机 玛氏巧克力棒 变焦镜头 大富翁桌游 商业洗衣店 畅销平装书 里氏震级 磁带录音机 大众汽车 超市推车 带温控器的电熨斗 速溶咖啡 尼龙 圆珠笔 黄热病疫苗 雷达 汽车自动变速箱 充气救生衣 人工授精 青霉素 军用吉普车 原子裂变 火箭筒 凝固汽油弹 水肺 麦角酸二乙酰胺 神经毒气 原子弹 特百惠 计算机 静电复印法 比基尼泳衣 浓缩咖啡机 宝丽来相机 拼字盘 实心电吉他 尼龙扣 晶体管 黑胶唱片 有线电视 电视显像管 汽车自动点火装置 信用卡 复印机 宽荧幕电影 动力转向器 三色停车灯 人行红绿灯 晶体管助听器 氢弹 录像带 DNA双螺旋结构 麻疹疫苗 按动圆珠笔 硅晶体管 核导弹 空对空导弹 迪士尼乐园 特氟龙 卡丁车 地对空核导弹 沙宾疫苗 通讯卫星 呼啦圈 安全带 人工肾脏 避孕药 气象卫星 便携晶体管收音机 安定 砷化镓半导体激光器 三维全息技术 合成器 香烟健康警示 凯夫拉纤维 子午胎 IBM文字处理机 杜比A型降噪器 滑雪板 喇叭裤 绕月载人火箭 人工心脏移植 波音747喷气式客机 互联网 条形码 软盘 帆板 热裤 液晶显示 便携电子计算器 电视游戏 DNA重组技术 电子游戏机 超级计算机 光纤 试管婴儿 魔方 索尼Walkman 杜比C型降噪器 艾滋病毒 强效可卡因 温室效应 CD 暗物质 暗能量 太阳能飞行器 甲型H1N1 流感 希格斯玻色子 引力波 | AR37: 电气地铁 圣代冰淇淋 实用水电站 手电 电影摄影机 收音机 霍乱疫苗 啤酒瓶盖 柴油发动机 双向电报 实用的胶卷 块麦片 电报 可口可乐 | AS37: 电报 可口可乐 | AT37: 1894
C38: 年龄年龄补正 | I38: 鹅膏菌（毒蘑菇） | J38: 6～24小时 | K38: 剧烈腹痛、呕吐、黄疸 | L38: 1D10 | M38: 造成了95%的毒蘑菇致死事件，鬼笔鹅膏是最常见的一种蘑菇毒素。 | O38: 上肢———— | X38: 闪避 | AE38: 1895 | AF38: 台湾民主国成立 | AG38: 台湾民主国被日军占领 | AI38: 《马关条约》 | AJ38: 公车上书 | AL38: 十九世纪 九十年代 | AM38: 乙未羊年 | AN38: 清光绪21年 | AO38: 伦琴发现 X 射线 卷烟机发明 卢米埃兄弟制成电影放映机并在巴黎首次放映电影 卡尔斯滕·埃格贝尔格·博克格尔文克成为第一名在南极洲大陆登陆的人 韦廉姆·G·摩根在美国发明排球 | AP38: 总统： 格罗佛·克利夫兰（民主党） | AQ38: 印名片机 福特车 潜望镜 油印蜡纸发明 阴极射线管 商品阿司匹林 凯洛格牌玉米片 手电筒 钋 镭 摇控器 α粒子 β粒子 打字机 柯达布朗尼相机 齐柏林飞艇 人类血型 跨大西洋电报 汽轮机游船 现代柏油路 铝罐奶粉 爆米花 泰迪熊 卡鲁索电唱机 便宜的肥皂和烹饪用油 飞机 荧光灯 邮戳机 摩托车发动机 热水瓶 农业轨道机械 木棉安全带 电动汽车喇叭 化学泡沫灭火器 狭义相对论 自动点唱机 量产舰艇舷外发动机 动画 电动洗衣机 家用洗洁精 立式吸尘器 饮用纸杯 双层公交车 无线电测向仪 电煎锅 质子和电子 玻璃纸 战壕风衣 汽车自动起动器 麦片 氯气毒气 防毒面具 拉链 机械雨刮器 广义相对论 芥子气 量产拖拉机 电子钟 黄油枪 降落伞 广播电台播音 茶包 罗夏墨迹测验 机器人 胰岛素 实用邮戳机 滑水 百日咳疫苗 纸制鸡蛋托 面巾纸 商用飞机农药喷撒 液体燃料火箭 劳力士防水表 遥控电唱机 面包机 防水玻璃纸 电传打字机 盖革计数器 纯维生素C 彩色电影胶片 透明胶带 音乐汽车喇叭 闪光灯 速冻食品 球形潜水舱 回旋加速器 折叠式雨伞 电动剃须刀 车载收音机 玛氏巧克力棒 变焦镜头 大富翁桌游 商业洗衣店 畅销平装书 里氏震级 磁带录音机 大众汽车 超市推车 带温控器的电熨斗 速溶咖啡 尼龙 圆珠笔 黄热病疫苗 雷达 汽车自动变速箱 充气救生衣 人工授精 青霉素 军用吉普车 原子裂变 火箭筒 凝固汽油弹 水肺 麦角酸二乙酰胺 神经毒气 原子弹 特百惠 计算机 静电复印法 比基尼泳衣 浓缩咖啡机 宝丽来相机 拼字盘 实心电吉他 尼龙扣 晶体管 黑胶唱片 有线电视 电视显像管 汽车自动点火装置 信用卡 复印机 宽荧幕电影 动力转向器 三色停车灯 人行红绿灯 晶体管助听器 氢弹 录像带 DNA双螺旋结构 麻疹疫苗 按动圆珠笔 硅晶体管 核导弹 空对空导弹 迪士尼乐园 特氟龙 卡丁车 地对空核导弹 沙宾疫苗 通讯卫星 呼啦圈 安全带 人工肾脏 避孕药 气象卫星 便携晶体管收音机 安定 砷化镓半导体激光器 三维全息技术 合成器 香烟健康警示 凯夫拉纤维 子午胎 IBM文字处理机 杜比A型降噪器 滑雪板 喇叭裤 绕月载人火箭 人工心脏移植 波音747喷气式客机 互联网 条形码 软盘 帆板 热裤 液晶显示 便携电子计算器 电视游戏 DNA重组技术 电子游戏机 超级计算机 光纤 试管婴儿 魔方 索尼Walkman 杜比C型降噪器 艾滋病毒 强效可卡因 温室效应 CD 暗物质 暗能量 太阳能飞行器 甲型H1N1 流感 希格斯玻色子 引力波 | AR38: 电气地铁 圣代冰淇淋 实用水电站 手电 电影摄影机 收音机 霍乱疫苗 啤酒瓶盖 柴油发动机 双向电报 实用的胶卷 块麦片 电报 可口可乐 X射线 卷烟机 电影放映机 排球 | AS38: X 射线 卷烟机 电影放映机 排球 | AT38: 1895 | AV38: =IF(AV36="仅显示1890_2012","",VLOOKUP(AV36,AS33:AT155,2,FALSE)) -> 1894
B39: 15 | C39: 19 | D39: 力量体型共-5 E-5 L*2 | I39: 砷化物 | J39: 30分钟～24小时 | K39: 灼痛、呕吐、剧烈腹泻 | L39: 4D10 | M39: 砷中毒难以确认（这使得它作为毒杀工具大受欢迎），直到1836年马氏试砷法发明为止。 | O39: 左手 | S39: =IF(人物卡!I11="",""," 身体状态:"&人物卡!I11&CHAR(9))&IF(人物卡!R11="",""," 精神状态:"&人物卡!R11&CHAR(9)) -> 身体状态:健康 精神状态:清醒 | X39: 汽车驾驶 | AE39: 1896 | AF39: 雅典奥运会 | AI39: 《中俄密约》 | AL39: 十九世纪 九十年代 | AM39: 丙申猴年 | AN39: 清光绪22年 | AO39: 克朗代克淘金热 印名片机取得专利 首辆福特车 潜望镜 雅典举办首届奥运会 | AP39: 总统： 格罗佛·克利夫兰（民主党） | AQ39: 油印蜡纸发明 阴极射线管 商品阿司匹林 凯洛格牌玉米片 手电筒 钋 镭 摇控器 α粒子 β粒子 打字机 柯达布朗尼相机 齐柏林飞艇 人类血型 跨大西洋电报 汽轮机游船 现代柏油路 铝罐奶粉 爆米花 泰迪熊 卡鲁索电唱机 便宜的肥皂和烹饪用油 飞机 荧光灯 邮戳机 摩托车发动机 热水瓶 农业轨道机械 木棉安全带 电动汽车喇叭 化学泡沫灭火器 狭义相对论 自动点唱机 量产舰艇舷外发动机 动画 电动洗衣机 家用洗洁精 立式吸尘器 饮用纸杯 双层公交车 无线电测向仪 电煎锅 质子和电子 玻璃纸 战壕风衣 汽车自动起动器 麦片 氯气毒气 防毒面具 拉链 机械雨刮器 广义相对论 芥子气 量产拖拉机 电子钟 黄油枪 降落伞 广播电台播音 茶包 罗夏墨迹测验 机器人 胰岛素 实用邮戳机 滑水 百日咳疫苗 纸制鸡蛋托 面巾纸 商用飞机农药喷撒 液体燃料火箭 劳力士防水表 遥控电唱机 面包机 防水玻璃纸 电传打字机 盖革计数器 纯维生素C 彩色电影胶片 透明胶带 音乐汽车喇叭 闪光灯 速冻食品 球形潜水舱 回旋加速器 折叠式雨伞 电动剃须刀 车载收音机 玛氏巧克力棒 变焦镜头 大富翁桌游 商业洗衣店 畅销平装书 里氏震级 磁带录音机 大众汽车 超市推车 带温控器的电熨斗 速溶咖啡 尼龙 圆珠笔 黄热病疫苗 雷达 汽车自动变速箱 充气救生衣 人工授精 青霉素 军用吉普车 原子裂变 火箭筒 凝固汽油弹 水肺 麦角酸二乙酰胺 神经毒气 原子弹 特百惠 计算机 静电复印法 比基尼泳衣 浓缩咖啡机 宝丽来相机 拼字盘 实心电吉他 尼龙扣 晶体管 黑胶唱片 有线电视 电视显像管 汽车自动点火装置 信用卡 复印机 宽荧幕电影 动力转向器 三色停车灯 人行红绿灯 晶体管助听器 氢弹 录像带 DNA双螺旋结构 麻疹疫苗 按动圆珠笔 硅晶体管 核导弹 空对空导弹 迪士尼乐园 特氟龙 卡丁车 地对空核导弹 沙宾疫苗 通讯卫星 呼啦圈 安全带 人工肾脏 避孕药 气象卫星 便携晶体管收音机 安定 砷化镓半导体激光器 三维全息技术 合成器 香烟健康警示 凯夫拉纤维 子午胎 IBM文字处理机 杜比A型降噪器 滑雪板 喇叭裤 绕月载人火箭 人工心脏移植 波音747喷气式客机 互联网 条形码 软盘 帆板 热裤 液晶显示 便携电子计算器 电视游戏 DNA重组技术 电子游戏机 超级计算机 光纤 试管婴儿 魔方 索尼Walkman 杜比C型降噪器 艾滋病毒 强效可卡因 温室效应 CD 暗物质 暗能量 太阳能飞行器 甲型H1N1 流感 希格斯玻色子 引力波 | AR39: 电气地铁 圣代冰淇淋 实用水电站 手电 电影摄影机 收音机 霍乱疫苗 啤酒瓶盖 柴油发动机 双向电报 实用的胶卷 块麦片 电报 可口可乐 X射线 卷烟机发明 电影放映机 排球 印名片机 福特车 潜望镜 | AS39: 印名片机 福特车 潜望镜 | AT39: 1896
B40: 20 | C40: 39 | D40: 教育进步*1 | I40: 颠茄 | J40: 2小时～2天 | K40: 心率加快、视力受损、惊厥 | L40: 4D10 | M40: 世界上毒性最大的植物之一，成人食用10～20颗就可能死亡。 | O40: 右手 | S40: =IF(人物卡!AP52="","","&DB="&人物卡!AP52&" 体格:"&人物卡!AP55)&IF(OR(人物卡!AP57="",,人物卡!R29<>人物卡!J29),""," 闪避:"&人物卡!AP57)&IF(人物卡!AN10="",""," 护甲:"&人物卡!AN10) -> &DB=+1D4 体格:1 护甲:0 | X40: 电气维修 | AE40: 1897 | AF40: —— | AI40: —— | AL40: 十九世纪 九十年代 | AM40: 丁酉鸡年 | AN40: 清光绪23年 | AO40: 油印蜡纸发明 首个阴极射线管 | AP40: 总统： 格罗佛·克利夫兰（民主党） 威廉·麦金利（共和党） | AQ40: 商品阿司匹林 凯洛格牌玉米片 手电筒 钋 镭 摇控器 α粒子 β粒子 打字机 柯达布朗尼相机 齐柏林飞艇 人类血型 跨大西洋电报 汽轮机游船 现代柏油路 铝罐奶粉 爆米花 泰迪熊 卡鲁索电唱机 便宜的肥皂和烹饪用油 飞机 荧光灯 邮戳机 摩托车发动机 热水瓶 农业轨道机械 木棉安全带 电动汽车喇叭 化学泡沫灭火器 狭义相对论 自动点唱机 量产舰艇舷外发动机 动画 电动洗衣机 家用洗洁精 立式吸尘器 饮用纸杯 双层公交车 无线电测向仪 电煎锅 质子和电子 玻璃纸 战壕风衣 汽车自动起动器 麦片 氯气毒气 防毒面具 拉链 机械雨刮器 广义相对论 芥子气 量产拖拉机 电子钟 黄油枪 降落伞 广播电台播音 茶包 罗夏墨迹测验 机器人 胰岛素 实用邮戳机 滑水 百日咳疫苗 纸制鸡蛋托 面巾纸 商用飞机农药喷撒 液体燃料火箭 劳力士防水表 遥控电唱机 面包机 防水玻璃纸 电传打字机 盖革计数器 纯维生素C 彩色电影胶片 透明胶带 音乐汽车喇叭 闪光灯 速冻食品 球形潜水舱 回旋加速器 折叠式雨伞 电动剃须刀 车载收音机 玛氏巧克力棒 变焦镜头 大富翁桌游 商业洗衣店 畅销平装书 里氏震级 磁带录音机 大众汽车 超市推车 带温控器的电熨斗 速溶咖啡 尼龙 圆珠笔 黄热病疫苗 雷达 汽车自动变速箱 充气救生衣 人工授精 青霉素 军用吉普车 原子裂变 火箭筒 凝固汽油弹 水肺 麦角酸二乙酰胺 神经毒气 原子弹 特百惠 计算机 静电复印法 比基尼泳衣 浓缩咖啡机 宝丽来相机 拼字盘 实心电吉他 尼龙扣 晶体管 黑胶唱片 有线电视 电视显像管 汽车自动点火装置 信用卡 复印机 宽荧幕电影 动力转向器 三色停车灯 人行红绿灯 晶体管助听器 氢弹 录像带 DNA双螺旋结构 麻疹疫苗 按动圆珠笔 硅晶体管 核导弹 空对空导弹 迪士尼乐园 特氟龙 卡丁车 地对空核导弹 沙宾疫苗 通讯卫星 呼啦圈 安全带 人工肾脏 避孕药 气象卫星 便携晶体管收音机 安定 砷化镓半导体激光器 三维全息技术 合成器 香烟健康警示 凯夫拉纤维 子午胎 IBM文字处理机 杜比A型降噪器 滑雪板 喇叭裤 绕月载人火箭 人工心脏移植 波音747喷气式客机 互联网 条形码 软盘 帆板 热裤 液晶显示 便携电子计算器 电视游戏 DNA重组技术 电子游戏机 超级计算机 光纤 试管婴儿 魔方 索尼Walkman 杜比C型降噪器 艾滋病毒 强效可卡因 温室效应 CD 暗物质 暗能量 太阳能飞行器 甲型H1N1 流感 希格斯玻色子 引力波 | AR40: 电气地铁 圣代冰淇淋 实用水电站 手电 电影摄影机 收音机 霍乱疫苗 啤酒瓶盖 柴油发动机 双向电报 实用的胶卷 块麦片 电报 可口可乐 X射线 卷烟机发明 电影放映机 排球 印名片机 福特车 潜望镜 油印蜡纸发明 阴极射线管 | AS40: 油印蜡纸发明 阴极射线管 | AT40: 1897
B41: 40 | C41: 49 | D41: 进步*2,SCD共-5 A-5 | I41: 黑寡妇蜘蛛毒 | J41: 2～8小时 | K41: 寒战、出汗、恶心 | L41: 1D10 | M41: 如果及时进行医治，基本不会死亡。 | O41: 双手 | S41: =IF(人物卡!G54="",IF(人物卡!B54="",""," &"&人物卡!B54&"="&人物卡!W54)," &"&人物卡!B54&"="&VLOOKUP(人物卡!G54,'武器列表 战斗'!B2:T105,19,FALSE)) | X41: 电子学 Ω | AE41: 1898 | AF41: 美西战争 | AG41: 美国兼并夏威夷共和国 | AI41: 戊戌变法/百日维新 | AL41: 十九世纪 九十年代 | AM41: 戊戌狗年 | AN41: 清光绪24年 | AO41: 飓风袭击美国南部数百人死亡 美西战争，死亡 2446 美军 唱片普及 商品阿司匹林出现 凯洛格牌玉米片 手电筒 居里夫妇宣布发现新的放射性元素钋 居里夫妇发现了化学元素镭 尼古拉·特斯拉开发第一个摇控器 | AP41: 总统： 威廉·麦金利（共和党） | AQ41: α粒子 β粒子 打字机 柯达布朗尼相机 齐柏林飞艇 人类血型 跨大西洋电报 汽轮机游船 现代柏油路 铝罐奶粉 爆米花 泰迪熊 卡鲁索电唱机 便宜的肥皂和烹饪用油 飞机 荧光灯 邮戳机 摩托车发动机 热水瓶 农业轨道机械 木棉安全带 电动汽车喇叭 化学泡沫灭火器 狭义相对论 自动点唱机 量产舰艇舷外发动机 动画 电动洗衣机 家用洗洁精 立式吸尘器 饮用纸杯 双层公交车 无线电测向仪 电煎锅 质子和电子 玻璃纸 战壕风衣 汽车自动起动器 麦片 氯气毒气 防毒面具 拉链 机械雨刮器 广义相对论 芥子气 量产拖拉机 电子钟 黄油枪 降落伞 广播电台播音 茶包 罗夏墨迹测验 机器人 胰岛素 实用邮戳机 滑水 百日咳疫苗 纸制鸡蛋托 面巾纸 商用飞机农药喷撒 液体燃料火箭 劳力士防水表 遥控电唱机 面包机 防水玻璃纸 电传打字机 盖革计数器 纯维生素C 彩色电影胶片 透明胶带 音乐汽车喇叭 闪光灯 速冻食品 球形潜水舱 回旋加速器 折叠式雨伞 电动剃须刀 车载收音机 玛氏巧克力棒 变焦镜头 大富翁桌游 商业洗衣店 畅销平装书 里氏震级 磁带录音机 大众汽车 超市推车 带温控器的电熨斗 速溶咖啡 尼龙 圆珠笔 黄热病疫苗 雷达 汽车自动变速箱 充气救生衣 人工授精 青霉素 军用吉普车 原子裂变 火箭筒 凝固汽油弹 水肺 麦角酸二乙酰胺 神经毒气 原子弹 特百惠 计算机 静电复印法 比基尼泳衣 浓缩咖啡机 宝丽来相机 拼字盘 实心电吉他 尼龙扣 晶体管 黑胶唱片 有线电视 电视显像管 汽车自动点火装置 信用卡 复印机 宽荧幕电影 动力转向器 三色停车灯 人行红绿灯 晶体管助听器 氢弹 录像带 DNA双螺旋结构 麻疹疫苗 按动圆珠笔 硅晶体管 核导弹 空对空导弹 迪士尼乐园 特氟龙 卡丁车 地对空核导弹 沙宾疫苗 通讯卫星 呼啦圈 安全带 人工肾脏 避孕药 气象卫星 便携晶体管收音机 安定 砷化镓半导体激光器 三维全息技术 合成器 香烟健康警示 凯夫拉纤维 子午胎 IBM文字处理机 杜比A型降噪器 滑雪板 喇叭裤 绕月载人火箭 人工心脏移植 波音747喷气式客机 互联网 条形码 软盘 帆板 热裤 液晶显示 便携电子计算器 电视游戏 DNA重组技术 电子游戏机 超级计算机 光纤 试管婴儿 魔方 索尼Walkman 杜比C型降噪器 艾滋病毒 强效可卡因 温室效应 CD 暗物质 暗能量 太阳能飞行器 甲型H1N1 流感 希格斯玻色子 引力波 | AR41: 电气地铁 圣代冰淇淋 实用水电站 手电 电影摄影机 收音机 霍乱疫苗 啤酒瓶盖 柴油发动机 双向电报 实用的胶卷 块麦片 电报 可口可乐 X射线 卷烟机发明 电影放映机 排球 印名片机 福特车 潜望镜 油印蜡纸发明 阴极射线管 商品阿司匹林 凯洛格牌玉米片 手电筒 钋 镭 摇控器 | AS41: 商品阿司匹林 凯洛格牌玉米片 手电筒 钋 镭 摇控器 | AT41: 1898
B42: 50 | C42: 59 | D42: 进步*3,SCD共-10 A-10 | I42: 三氯甲烷（氯仿） | J42: 1轮 | K42: 昏迷1小时 | L42: 无伤害 | M42: 在1800~1900s是常见的麻醉剂，不过高的摄入量也会致死。 | O42: 左臂 | S42: =IF(人物卡!G55="",IF(人物卡!B55="",""," &"&人物卡!B55&"="&人物卡!W55)," &"&人物卡!B55&"="&VLOOKUP(人物卡!G55,'武器列表 战斗'!B2:T105,19,FALSE)) -> &好用的刀=1D4+[DB] | X42: 话术 | AE42: 1899 | AF42: 第二次布尔战争 | AI42: —— | AL42: 十九世纪 九十年代 | AM42: 己亥猪年 | AN42: 清光绪25年 | AO42: 纽约温莎酒店大火，数百万人受灾，死亡 14 人 卢瑟福发现 α 粒子和 β 粒子 打字机开始普及 | AP42: 总统： 威廉·麦金利（共和党） | AQ42: 柯达布朗尼相机 齐柏林飞艇 人类血型 跨大西洋电报 汽轮机游船 现代柏油路 铝罐奶粉 爆米花 泰迪熊 卡鲁索电唱机 便宜的肥皂和烹饪用油 飞机 荧光灯 邮戳机 摩托车发动机 热水瓶 农业轨道机械 木棉安全带 电动汽车喇叭 化学泡沫灭火器 狭义相对论 自动点唱机 量产舰艇舷外发动机 动画 电动洗衣机 家用洗洁精 立式吸尘器 饮用纸杯 双层公交车 无线电测向仪 电煎锅 质子和电子 玻璃纸 战壕风衣 汽车自动起动器 麦片 氯气毒气 防毒面具 拉链 机械雨刮器 广义相对论 芥子气 量产拖拉机 电子钟 黄油枪 降落伞 广播电台播音 茶包 罗夏墨迹测验 机器人 胰岛素 实用邮戳机 滑水 百日咳疫苗 纸制鸡蛋托 面巾纸 商用飞机农药喷撒 液体燃料火箭 劳力士防水表 遥控电唱机 面包机 防水玻璃纸 电传打字机 盖革计数器 纯维生素C 彩色电影胶片 透明胶带 音乐汽车喇叭 闪光灯 速冻食品 球形潜水舱 回旋加速器 折叠式雨伞 电动剃须刀 车载收音机 玛氏巧克力棒 变焦镜头 大富翁桌游 商业洗衣店 畅销平装书 里氏震级 磁带录音机 大众汽车 超市推车 带温控器的电熨斗 速溶咖啡 尼龙 圆珠笔 黄热病疫苗 雷达 汽车自动变速箱 充气救生衣 人工授精 青霉素 军用吉普车 原子裂变 火箭筒 凝固汽油弹 水肺 麦角酸二乙酰胺 神经毒气 原子弹 特百惠 计算机 静电复印法 比基尼泳衣 浓缩咖啡机 宝丽来相机 拼字盘 实心电吉他 尼龙扣 晶体管 黑胶唱片 有线电视 电视显像管 汽车自动点火装置 信用卡 复印机 宽荧幕电影 动力转向器 三色停车灯 人行红绿灯 晶体管助听器 氢弹 录像带 DNA双螺旋结构 麻疹疫苗 按动圆珠笔 硅晶体管 核导弹 空对空导弹 迪士尼乐园 特氟龙 卡丁车 地对空核导弹 沙宾疫苗 通讯卫星 呼啦圈 安全带 人工肾脏 避孕药 气象卫星 便携晶体管收音机 安定 砷化镓半导体激光器 三维全息技术 合成器 香烟健康警示 凯夫拉纤维 子午胎 IBM文字处理机 杜比A型降噪器 滑雪板 喇叭裤 绕月载人火箭 人工心脏移植 波音747喷气式客机 互联网 条形码 软盘 帆板 热裤 液晶显示 便携电子计算器 电视游戏 DNA重组技术 电子游戏机 超级计算机 光纤 试管婴儿 魔方 索尼Walkman 杜比C型降噪器 艾滋病毒 强效可卡因 温室效应 CD 暗物质 暗能量 太阳能飞行器 甲型H1N1 流感 希格斯玻色子 引力波 | AR42: 电气地铁 圣代冰淇淋 实用水电站 手电 电影摄影机 收音机 霍乱疫苗 啤酒瓶盖 柴油发动机 双向电报 实用的胶卷 块麦片 电报 可口可乐 X射线 卷烟机发明 电影放映机 排球 印名片机 福特车 潜望镜 油印蜡纸发明 阴极射线管 商品阿司匹林 凯洛格牌玉米片 手电筒 钋 镭 摇控器 α粒子 β粒子 打字机 | AS42: α 粒子和 β 粒子 打字机 | AT42: 1899
B43: 60 | C43: 69 | D43: 进步*4,SCD共-20 A-15 | I43: 眼镜蛇毒 | J43: 15～60分钟 | K43: 惊厥、呼吸衰竭 | L43: 4D10 | M43: 接触眼睛会产生直接的刺激，未经处理会失明。如果有血清，可以避免受重伤和死亡。 | O43: 右臂 | S43: =IF(人物卡!G56="",IF(人物卡!B56="",""," &"&人物卡!B56&"="&人物卡!W56)," &"&人物卡!B56&"="&VLOOKUP(人物卡!G56,'武器列表 战斗'!B2:T105,19,FALSE)) -> &好用的枪=1D8+1D4 | X43: 格斗： | AE43: 1900 | AF43: 巴黎奥运会 | AG43: 诺贝尔奖基金会 | AI43: 八国联军侵华战争 | AJ43: 庚子国变 | AL43: 二十世纪初 | AM43: 庚子鼠年 | AN43: 清光绪26年 | AO43: 码头失火，蒸汽艇里约热内卢号在旧金山港沉没，死亡 128 人 大飓风加尔维斯顿，死亡 6000 人 庚子国变 柯达布朗尼相机 齐柏林伯爵起飞 420 英尺飞艇 美国公债12.63 亿美元 美国人口 760 万。 | AP43: 总统： 威廉·麦金利（共和党） | AQ43: 人类血型 跨大西洋电报 汽轮机游船 现代柏油路 铝罐奶粉 爆米花 泰迪熊 卡鲁索电唱机 便宜的肥皂和烹饪用油 飞机 荧光灯 邮戳机 摩托车发动机 热水瓶 农业轨道机械 木棉安全带 电动汽车喇叭 化学泡沫灭火器 狭义相对论 自动点唱机 量产舰艇舷外发动机 动画 电动洗衣机 家用洗洁精 立式吸尘器 饮用纸杯 双层公交车 无线电测向仪 电煎锅 质子和电子 玻璃纸 战壕风衣 汽车自动起动器 麦片 氯气毒气 防毒面具 拉链 机械雨刮器 广义相对论 芥子气 量产拖拉机 电子钟 黄油枪 降落伞 广播电台播音 茶包 罗夏墨迹测验 机器人 胰岛素 实用邮戳机 滑水 百日咳疫苗 纸制鸡蛋托 面巾纸 商用飞机农药喷撒 液体燃料火箭 劳力士防水表 遥控电唱机 面包机 防水玻璃纸 电传打字机 盖革计数器 纯维生素C 彩色电影胶片 透明胶带 音乐汽车喇叭 闪光灯 速冻食品 球形潜水舱 回旋加速器 折叠式雨伞 电动剃须刀 车载收音机 玛氏巧克力棒 变焦镜头 大富翁桌游 商业洗衣店 畅销平装书 里氏震级 磁带录音机 大众汽车 超市推车 带温控器的电熨斗 速溶咖啡 尼龙 圆珠笔 黄热病疫苗 雷达 汽车自动变速箱 充气救生衣 人工授精 青霉素 军用吉普车 原子裂变 火箭筒 凝固汽油弹 水肺 麦角酸二乙酰胺 神经毒气 原子弹 特百惠 计算机 静电复印法 比基尼泳衣 浓缩咖啡机 宝丽来相机 拼字盘 实心电吉他 尼龙扣 晶体管 黑胶唱片 有线电视 电视显像管 汽车自动点火装置 信用卡 复印机 宽荧幕电影 动力转向器 三色停车灯 人行红绿灯 晶体管助听器 氢弹 录像带 DNA双螺旋结构 麻疹疫苗 按动圆珠笔 硅晶体管 核导弹 空对空导弹 迪士尼乐园 特氟龙 卡丁车 地对空核导弹 沙宾疫苗 通讯卫星 呼啦圈 安全带 人工肾脏 避孕药 气象卫星 便携晶体管收音机 安定 砷化镓半导体激光器 三维全息技术 合成器 香烟健康警示 凯夫拉纤维 子午胎 IBM文字处理机 杜比A型降噪器 滑雪板 喇叭裤 绕月载人火箭 人工心脏移植 波音747喷气式客机 互联网 条形码 软盘 帆板 热裤 液晶显示 便携电子计算器 电视游戏 DNA重组技术 电子游戏机 超级计算机 光纤 试管婴儿 魔方 索尼Walkman 杜比C型降噪器 艾滋病毒 强效可卡因 温室效应 CD 暗物质 暗能量 太阳能飞行器 甲型H1N1 流感 希格斯玻色子 引力波 | AR43: 电气地铁 圣代冰淇淋 实用水电站 手电 电影摄影机 收音机 霍乱疫苗 啤酒瓶盖 柴油发动机 双向电报 实用的胶卷 块麦片 电报 可口可乐 X射线 卷烟机发明 电影放映机 排球 印名片机 福特车 潜望镜 油印蜡纸发明 阴极射线管 商品阿司匹林 凯洛格牌玉米片 手电筒 钋 镭 摇控器 α粒子 β粒子 打字机 柯达布朗尼相机 齐柏林飞艇 | AS43: 柯达布朗尼相机 齐柏林飞艇 | AT43: 1900
B44: 70 | C44: 79 | D44: 进步*4,SCD共-40 A-20 | I44: 箭毒碱 | J44: 1轮 | K44: 肌肉麻痹、呼吸衰竭。 | L44: 4D10 | M44: 南美洲人涂在箭上毒剂的通称。口服无害，只有通过皮肤伤口直接侵入才会导致瘫痪。 | O44: 双臂 | S44: =S41&S42&S43 -> &好用的刀=1D4+[DB] &好用的枪=1D8+1D4 | X44: 格斗① | AE44: 1901 | AF44: 维多利亚时代结束（英国） | AI44: 《辛丑条约》 | AL44: 二十世纪初 | AM44: 辛丑牛年 | AN44: 清光绪27年 | AO44: 麦金莱总统遇刺 美国两次爆发伤寒 维多利亚女王逝世 人类血型发现 首份跨越大西洋电报 | AP44: 总统： 威廉·麦金利（共和党） 西奥多·罗斯福（共和党） | AQ44: 汽轮机游船 现代柏油路 铝罐奶粉 爆米花 泰迪熊 卡鲁索电唱机 便宜的肥皂和烹饪用油 飞机 荧光灯 邮戳机 摩托车发动机 热水瓶 农业轨道机械 木棉安全带 电动汽车喇叭 化学泡沫灭火器 狭义相对论 自动点唱机 量产舰艇舷外发动机 动画 电动洗衣机 家用洗洁精 立式吸尘器 饮用纸杯 双层公交车 无线电测向仪 电煎锅 质子和电子 玻璃纸 战壕风衣 汽车自动起动器 麦片 氯气毒气 防毒面具 拉链 机械雨刮器 广义相对论 芥子气 量产拖拉机 电子钟 黄油枪 降落伞 广播电台播音 茶包 罗夏墨迹测验 机器人 胰岛素 实用邮戳机 滑水 百日咳疫苗 纸制鸡蛋托 面巾纸 商用飞机农药喷撒 液体燃料火箭 劳力士防水表 遥控电唱机 面包机 防水玻璃纸 电传打字机 盖革计数器 纯维生素C 彩色电影胶片 透明胶带 音乐汽车喇叭 闪光灯 速冻食品 球形潜水舱 回旋加速器 折叠式雨伞 电动剃须刀 车载收音机 玛氏巧克力棒 变焦镜头 大富翁桌游 商业洗衣店 畅销平装书 里氏震级 磁带录音机 大众汽车 超市推车 带温控器的电熨斗 速溶咖啡 尼龙 圆珠笔 黄热病疫苗 雷达 汽车自动变速箱 充气救生衣 人工授精 青霉素 军用吉普车 原子裂变 火箭筒 凝固汽油弹 水肺 麦角酸二乙酰胺 神经毒气 原子弹 特百惠 计算机 静电复印法 比基尼泳衣 浓缩咖啡机 宝丽来相机 拼字盘 实心电吉他 尼龙扣 晶体管 黑胶唱片 有线电视 电视显像管 汽车自动点火装置 信用卡 复印机 宽荧幕电影 动力转向器 三色停车灯 人行红绿灯 晶体管助听器 氢弹 录像带 DNA双螺旋结构 麻疹疫苗 按动圆珠笔 硅晶体管 核导弹 空对空导弹 迪士尼乐园 特氟龙 卡丁车 地对空核导弹 沙宾疫苗 通讯卫星 呼啦圈 安全带 人工肾脏 避孕药 气象卫星 便携晶体管收音机 安定 砷化镓半导体激光器 三维全息技术 合成器 香烟健康警示 凯夫拉纤维 子午胎 IBM文字处理机 杜比A型降噪器 滑雪板 喇叭裤 绕月载人火箭 人工心脏移植 波音747喷气式客机 互联网 条形码 软盘 帆板 热裤 液晶显示 便携电子计算器 电视游戏 DNA重组技术 电子游戏机 超级计算机 光纤 试管婴儿 魔方 索尼Walkman 杜比C型降噪器 艾滋病毒 强效可卡因 温室效应 CD 暗物质 暗能量 太阳能飞行器 甲型H1N1 流感 希格斯玻色子 引力波 | AR44: 电气地铁 圣代冰淇淋 实用水电站 手电 电影摄影机 收音机 霍乱疫苗 啤酒瓶盖 柴油发动机 双向电报 实用的胶卷 块麦片 电报 可口可乐 X射线 卷烟机发明 电影放映机 排球 印名片机 福特车 潜望镜 油印蜡纸发明 阴极射线管 商品阿司匹林 凯洛格牌玉米片 手电筒 钋 镭 摇控器 α粒子 β粒子 打字机 柯达布朗尼相机 齐柏林飞艇 人类血型 跨大西洋电报 | AS44: 人类血型 跨大西洋电报 | AT44: 1901
B45: 80 | C45: 89 | D45: 进步*4,SCD共-80 A-25 | I45: 氰化物 | J45: 1～15分钟 | K45: 眩晕、惊厥、晕厥、死亡。 | L45: 4D10 | M45: 剧毒——摄入了氰化物盐或者通过气体吸入都会致死。 | O45: 肘部 | X45: 格斗② | AE45: 1902 | AF45: 第二次布尔战争结束 | AI45: —— | AL45: 二十世纪初 | AM45: 壬寅虎年 | AN45: 清光绪28年 | AO45: 布尔战争 马提尼克（中美洲岛屿 ) 培雷火山爆发，死亡 4 万人 首个汽轮机游船 现代柏油路产生 首个铝罐奶粉 爆米花 首个泰迪熊 首个卡鲁索电唱机 商用氢化油脂使得制皂和烹饪用油来源增加 | AP45: 总统： 西奥多·罗斯福（共和党） | AQ45: 飞机 荧光灯 邮戳机 摩托车发动机 热水瓶 农业轨道机械 木棉安全带 电动汽车喇叭 化学泡沫灭火器 狭义相对论 自动点唱机 量产舰艇舷外发动机 动画 电动洗衣机 家用洗洁精 立式吸尘器 饮用纸杯 双层公交车 无线电测向仪 电煎锅 质子和电子 玻璃纸 战壕风衣 汽车自动起动器 麦片 氯气毒气 防毒面具 拉链 机械雨刮器 广义相对论 芥子气 量产拖拉机 电子钟 黄油枪 降落伞 广播电台播音 茶包 罗夏墨迹测验 机器人 胰岛素 实用邮戳机 滑水 百日咳疫苗 纸制鸡蛋托 面巾纸 商用飞机农药喷撒 液体燃料火箭 劳力士防水表 遥控电唱机 面包机 防水玻璃纸 电传打字机 盖革计数器 纯维生素C 彩色电影胶片 透明胶带 音乐汽车喇叭 闪光灯 速冻食品 球形潜水舱 回旋加速器 折叠式雨伞 电动剃须刀 车载收音机 玛氏巧克力棒 变焦镜头 大富翁桌游 商业洗衣店 畅销平装书 里氏震级 磁带录音机 大众汽车 超市推车 带温控器的电熨斗 速溶咖啡 尼龙 圆珠笔 黄热病疫苗 雷达 汽车自动变速箱 充气救生衣 人工授精 青霉素 军用吉普车 原子裂变 火箭筒 凝固汽油弹 水肺 麦角酸二乙酰胺 神经毒气 原子弹 特百惠 计算机 静电复印法 比基尼泳衣 浓缩咖啡机 宝丽来相机 拼字盘 实心电吉他 尼龙扣 晶体管 黑胶唱片 有线电视 电视显像管 汽车自动点火装置 信用卡 复印机 宽荧幕电影 动力转向器 三色停车灯 人行红绿灯 晶体管助听器 氢弹 录像带 DNA双螺旋结构 麻疹疫苗 按动圆珠笔 硅晶体管 核导弹 空对空导弹 迪士尼乐园 特氟龙 卡丁车 地对空核导弹 沙宾疫苗 通讯卫星 呼啦圈 安全带 人工肾脏 避孕药 气象卫星 便携晶体管收音机 安定 砷化镓半导体激光器 三维全息技术 合成器 香烟健康警示 凯夫拉纤维 子午胎 IBM文字处理机 杜比A型降噪器 滑雪板 喇叭裤 绕月载人火箭 人工心脏移植 波音747喷气式客机 互联网 条形码 软盘 帆板 热裤 液晶显示 便携电子计算器 电视游戏 DNA重组技术 电子游戏机 超级计算机 光纤 试管婴儿 魔方 索尼Walkman 杜比C型降噪器 艾滋病毒 强效可卡因 温室效应 CD 暗物质 暗能量 太阳能飞行器 甲型H1N1 流感 希格斯玻色子 引力波 | AR45: 电气地铁 圣代冰淇淋 实用水电站 手电 电影摄影机 收音机 霍乱疫苗 啤酒瓶盖 柴油发动机 双向电报 实用的胶卷 块麦片 电报 可口可乐 X射线 卷烟机发明 电影放映机 排球 印名片机 福特车 潜望镜 油印蜡纸发明 阴极射线管 商品阿司匹林 凯洛格牌玉米片 手电筒 钋 镭 摇控器 α粒子 β粒子 打字机 柯达布朗尼相机 齐柏林飞艇 人类血型 跨大西洋电报 汽轮机游船 现代柏油路 铝罐奶粉 爆米花 泰迪熊 卡鲁索电唱机 便宜的肥皂和烹饪用油 | AS45: 汽轮机游船 现代柏油路 铝罐奶粉 爆米花 泰迪熊 卡鲁索电唱机 便宜的肥皂和烹饪用油 | AT45: 1902
C46: 年龄倍数 | D46: scd | E46: a | I46: 响尾蛇毒 | J46: 15～60分钟 | K46: 呕吐、剧烈抽搐、黄视。 | L46: 2D10 | M46: 毒液会破坏组织、引发坏死，不过很少致命（特别是一两个小时内就获得解药的话）。 | O46: 其他(上肢) | S46: =S24&S37&S39&S40&S44 -> .st 力量90str90敏捷40dex40意志75pow75体质50con50外貌65app65教育65edu65体型70siz70智力80灵感80int80san75san值75理智75理智值75幸运70运气70mp15魔法15hp12体力12会计5人类学1估价5考古学1取悦49魅惑49攀爬20计算机5计算机使用5电脑5信用50信誉50信用评级50克苏鲁0克苏鲁神话0cm0乔装5闪避44汽车20驾驶20汽车驾驶20电气维修10电子学1话术5斗殴65手枪70急救30历史5恐吓15跳跃20母语65法律5图书馆20图书馆使用20聆听49开锁1撬锁1锁匠1机械维修10医学1博物学50自然学50领航10导航10神秘学5重型操作1重型机械1操作重型机械1重型1说服49精神分析1心理学49骑术5妙手10侦查70潜行60生存10游泳20投掷20追踪50驯兽5潜水1爆破1读唇1催眠1炮术1时代:1920s 职业:探险家 年龄31 性别:男 住地:法国 里昂 出身:法国 格勒诺布尔 身体状态:健康 精神状态:清醒 &DB=+1D4 体格:1 护甲:0 &好用的刀=1D4+[DB] &好用的枪=1D8+1D4 | X46: 格斗③ | AE46: 1903 | AF46: —— | AI46: —— | AL46: 二十世纪初 | AM46: 癸卯兔年 | AN46: 清光绪29年 | AO46: 芝加哥易洛魁剧院大火，死亡 602 人，是美国历史上最严重的火灾 莱特兄弟试飞飞机 首个荧光灯 邮戳机产生 车架中心摩托车发动机 | AP46: 总统： 西奥多·罗斯福（共和党） | AQ46: 热水瓶 农业轨道机械 木棉安全带 电动汽车喇叭 化学泡沫灭火器 狭义相对论 自动点唱机 量产舰艇舷外发动机 动画 电动洗衣机 家用洗洁精 立式吸尘器 饮用纸杯 双层公交车 无线电测向仪 电煎锅 质子和电子 玻璃纸 战壕风衣 汽车自动起动器 麦片 氯气毒气 防毒面具 拉链 机械雨刮器 广义相对论 芥子气 量产拖拉机 电子钟 黄油枪 降落伞 广播电台播音 茶包 罗夏墨迹测验 机器人 胰岛素 实用邮戳机 滑水 百日咳疫苗 纸制鸡蛋托 面巾纸 商用飞机农药喷撒 液体燃料火箭 劳力士防水表 遥控电唱机 面包机 防水玻璃纸 电传打字机 盖革计数器 纯维生素C 彩色电影胶片 透明胶带 音乐汽车喇叭 闪光灯 速冻食品 球形潜水舱 回旋加速器 折叠式雨伞 电动剃须刀 车载收音机 玛氏巧克力棒 变焦镜头 大富翁桌游 商业洗衣店 畅销平装书 里氏震级 磁带录音机 大众汽车 超市推车 带温控器的电熨斗 速溶咖啡 尼龙 圆珠笔 黄热病疫苗 雷达 汽车自动变速箱 充气救生衣 人工授精 青霉素 军用吉普车 原子裂变 火箭筒 凝固汽油弹 水肺 麦角酸二乙酰胺 神经毒气 原子弹 特百惠 计算机 静电复印法 比基尼泳衣 浓缩咖啡机 宝丽来相机 拼字盘 实心电吉他 尼龙扣 晶体管 黑胶唱片 有线电视 电视显像管 汽车自动点火装置 信用卡 复印机 宽荧幕电影 动力转向器 三色停车灯 人行红绿灯 晶体管助听器 氢弹 录像带 DNA双螺旋结构 麻疹疫苗 按动圆珠笔 硅晶体管 核导弹 空对空导弹 迪士尼乐园 特氟龙 卡丁车 地对空核导弹 沙宾疫苗 通讯卫星 呼啦圈 安全带 人工肾脏 避孕药 气象卫星 便携晶体管收音机 安定 砷化镓半导体激光器 三维全息技术 合成器 香烟健康警示 凯夫拉纤维 子午胎 IBM文字处理机 杜比A型降噪器 滑雪板 喇叭裤 绕月载人火箭 人工心脏移植 波音747喷气式客机 互联网 条形码 软盘 帆板 热裤 液晶显示 便携电子计算器 电视游戏 DNA重组技术 电子游戏机 超级计算机 光纤 试管婴儿 魔方 索尼Walkman 杜比C型降噪器 艾滋病毒 强效可卡因 温室效应 CD 暗物质 暗能量 太阳能飞行器 甲型H1N1 流感 希格斯玻色子 引力波 | AR46: 电气地铁 圣代冰淇淋 实用水电站 手电 电影摄影机 收音机 霍乱疫苗 啤酒瓶盖 柴油发动机 双向电报 实用的胶卷 块麦片 电报 可口可乐 X射线 卷烟机发明 电影放映机 排球 印名片机 福特车 潜望镜 油印蜡纸发明 阴极射线管 商品阿司匹林 凯洛格牌玉米片 手电筒 钋 镭 摇控器 α粒子 β粒子 打字机 柯达布朗尼相机 齐柏林飞艇 人类血型 跨大西洋电报 汽轮机游船 现代柏油路 铝罐奶粉 爆米花 泰迪熊 卡鲁索电唱机 便宜的肥皂和烹饪用油 飞机 荧光灯 邮戳机 摩托车发动机 | AS46: 飞机 荧光灯 邮戳机 摩托车发动机 | AT46: 1903
C47: =INT((C37-B45)/10) -> -5 | D47: =80+80*C47 -> -320 | E47: 25 | I47: 氟硝西泮 | J47: 15～30分钟 | K47: 昏迷4～8小时，可能会失忆。 | L47: 无伤害 | M47: 无色无味，只在现代背景中出现。 | O47: 下肢———— | X47: 射击： | AE47: 1904 | AF47: 日俄战争 | AG47: 圣路易斯奥运会 | AI47: —— | AL47: 二十世纪初 | AM47: 甲辰龙年 | AN47: 清光绪30年 | AO47: 伊甸火车在洪水中出轨，死亡 96 人 百老汇地铁在纽约城开通 热水瓶获得专利 轨道机械（相对于轮式 ) 出现在农业机械当中 木棉安全带 日俄战争 | AP47: 总统： 西奥多·罗斯福（共和党） | AQ47: 电动汽车喇叭 化学泡沫灭火器 狭义相对论 自动点唱机 量产舰艇舷外发动机 动画 电动洗衣机 家用洗洁精 立式吸尘器 饮用纸杯 双层公交车 无线电测向仪 电煎锅 质子和电子 玻璃纸 战壕风衣 汽车自动起动器 麦片 氯气毒气 防毒面具 拉链 机械雨刮器 广义相对论 芥子气 量产拖拉机 电子钟 黄油枪 降落伞 广播电台播音 茶包 罗夏墨迹测验 机器人 胰岛素 实用邮戳机 滑水 百日咳疫苗 纸制鸡蛋托 面巾纸 商用飞机农药喷撒 液体燃料火箭 劳力士防水表 遥控电唱机 面包机 防水玻璃纸 电传打字机 盖革计数器 纯维生素C 彩色电影胶片 透明胶带 音乐汽车喇叭 闪光灯 速冻食品 球形潜水舱 回旋加速器 折叠式雨伞 电动剃须刀 车载收音机 玛氏巧克力棒 变焦镜头 大富翁桌游 商业洗衣店 畅销平装书 里氏震级 磁带录音机 大众汽车 超市推车 带温控器的电熨斗 速溶咖啡 尼龙 圆珠笔 黄热病疫苗 雷达 汽车自动变速箱 充气救生衣 人工授精 青霉素 军用吉普车 原子裂变 火箭筒 凝固汽油弹 水肺 麦角酸二乙酰胺 神经毒气 原子弹 特百惠 计算机 静电复印法 比基尼泳衣 浓缩咖啡机 宝丽来相机 拼字盘 实心电吉他 尼龙扣 晶体管 黑胶唱片 有线电视 电视显像管 汽车自动点火装置 信用卡 复印机 宽荧幕电影 动力转向器 三色停车灯 人行红绿灯 晶体管助听器 氢弹 录像带 DNA双螺旋结构 麻疹疫苗 按动圆珠笔 硅晶体管 核导弹 空对空导弹 迪士尼乐园 特氟龙 卡丁车 地对空核导弹 沙宾疫苗 通讯卫星 呼啦圈 安全带 人工肾脏 避孕药 气象卫星 便携晶体管收音机 安定 砷化镓半导体激光器 三维全息技术 合成器 香烟健康警示 凯夫拉纤维 子午胎 IBM文字处理机 杜比A型降噪器 滑雪板 喇叭裤 绕月载人火箭 人工心脏移植 波音747喷气式客机 互联网 条形码 软盘 帆板 热裤 液晶显示 便携电子计算器 电视游戏 DNA重组技术 电子游戏机 超级计算机 光纤 试管婴儿 魔方 索尼Walkman 杜比C型降噪器 艾滋病毒 强效可卡因 温室效应 CD 暗物质 暗能量 太阳能飞行器 甲型H1N1 流感 希格斯玻色子 引力波 | AR47: 电气地铁 圣代冰淇淋 实用水电站 手电 电影摄影机 收音机 霍乱疫苗 啤酒瓶盖 柴油发动机 双向电报 实用的胶卷 块麦片 电报 可口可乐 X射线 卷烟机发明 电影放映机 排球 印名片机 福特车 潜望镜 油印蜡纸发明 阴极射线管 商品阿司匹林 凯洛格牌玉米片 手电筒 钋 镭 摇控器 α粒子 β粒子 打字机 柯达布朗尼相机 齐柏林飞艇 人类血型 跨大西洋电报 汽轮机游船 现代柏油路 铝罐奶粉 爆米花 泰迪熊 卡鲁索电唱机 便宜的肥皂和烹饪用油 飞机 荧光灯 邮戳机 摩托车发动机 热水瓶 农业轨道机械 木棉安全带 | AS47: 热水瓶 农业轨道机械 木棉安全带 | AT47: 1904
C48: =C37 -> 31 | D48: ="进步*4,SCD共-"&D47&" A-"&E47 -> 进步*4,SCD共--320 A-25 | I48: 番木鳖碱（马钱子碱、士的宁） | J48: 10～20分钟 | K48: 剧烈的肌肉痉挛、窒息、死亡。 | L48: 4D10 | M48: 如果不及时医治，几小时内就会死亡。 | O48: 左脚 | X48: 射击① | AE48: 1905 | AF48: 俄国革命 | AI48: —— | AL48: 二十世纪初 | AM48: 乙巳蛇年 | AN48: 清光绪31年 | AO48: 库利南钻石（3000 克拉 )，当时世界最大的钻石 英国海军标准配备蒸汽轮机 1905 年俄国革命 电动汽车喇叭 化学泡沫灭火器 狭义相对论 | AP48: 总统： 西奥多·罗斯福（共和党） | AQ48: 自动点唱机 量产舰艇舷外发动机 动画 电动洗衣机 家用洗洁精 立式吸尘器 饮用纸杯 双层公交车 无线电测向仪 电煎锅 质子和电子 玻璃纸 战壕风衣 汽车自动起动器 麦片 氯气毒气 防毒面具 拉链 机械雨刮器 广义相对论 芥子气 量产拖拉机 电子钟 黄油枪 降落伞 广播电台播音 茶包 罗夏墨迹测验 机器人 胰岛素 实用邮戳机 滑水 百日咳疫苗 纸制鸡蛋托 面巾纸 商用飞机农药喷撒 液体燃料火箭 劳力士防水表 遥控电唱机 面包机 防水玻璃纸 电传打字机 盖革计数器 纯维生素C 彩色电影胶片 透明胶带 音乐汽车喇叭 闪光灯 速冻食品 球形潜水舱 回旋加速器 折叠式雨伞 电动剃须刀 车载收音机 玛氏巧克力棒 变焦镜头 大富翁桌游 商业洗衣店 畅销平装书 里氏震级 磁带录音机 大众汽车 超市推车 带温控器的电熨斗 速溶咖啡 尼龙 圆珠笔 黄热病疫苗 雷达 汽车自动变速箱 充气救生衣 人工授精 青霉素 军用吉普车 原子裂变 火箭筒 凝固汽油弹 水肺 麦角酸二乙酰胺 神经毒气 原子弹 特百惠 计算机 静电复印法 比基尼泳衣 浓缩咖啡机 宝丽来相机 拼字盘 实心电吉他 尼龙扣 晶体管 黑胶唱片 有线电视 电视显像管 汽车自动点火装置 信用卡 复印机 宽荧幕电影 动力转向器 三色停车灯 人行红绿灯 晶体管助听器 氢弹 录像带 DNA双螺旋结构 麻疹疫苗 按动圆珠笔 硅晶体管 核导弹 空对空导弹 迪士尼乐园 特氟龙 卡丁车 地对空核导弹 沙宾疫苗 通讯卫星 呼啦圈 安全带 人工肾脏 避孕药 气象卫星 便携晶体管收音机 安定 砷化镓半导体激光器 三维全息技术 合成器 香烟健康警示 凯夫拉纤维 子午胎 IBM文字处理机 杜比A型降噪器 滑雪板 喇叭裤 绕月载人火箭 人工心脏移植 波音747喷气式客机 互联网 条形码 软盘 帆板 热裤 液晶显示 便携电子计算器 电视游戏 DNA重组技术 电子游戏机 超级计算机 光纤 试管婴儿 魔方 索尼Walkman 杜比C型降噪器 艾滋病毒 强效可卡因 温室效应 CD 暗物质 暗能量 太阳能飞行器 甲型H1N1 流感 希格斯玻色子 引力波 | AR48: 电气地铁 圣代冰淇淋 实用水电站 手电 电影摄影机 收音机 霍乱疫苗 啤酒瓶盖 柴油发动机 双向电报 实用的胶卷 块麦片 电报 可口可乐 X射线 卷烟机发明 电影放映机 排球 印名片机 福特车 潜望镜 油印蜡纸发明 阴极射线管 商品阿司匹林 凯洛格牌玉米片 手电筒 钋 镭 摇控器 α粒子 β粒子 打字机 柯达布朗尼相机 齐柏林飞艇 人类血型 跨大西洋电报 汽轮机游船 现代柏油路 铝罐奶粉 爆米花 泰迪熊 卡鲁索电唱机 便宜的肥皂和烹饪用油 飞机 荧光灯 邮戳机 摩托车发动机 热水瓶 农业轨道机械 木棉安全带 电动汽车喇叭 化学泡沫灭火器 狭义相对论 | AS48: 电动汽车喇叭 化学泡沫灭火器 狭义相对论 | AT48: 1905
I49: 请打开下拉栏选择 | O49: 右脚 | X49: 射击② | AE49: 1906 | AF49: 美军占领古巴 | AG49: 印度民族解放运动 | AI49: —— | AL49: 二十世纪初 | AM49: 丙午马年 | AN49: 清光绪32年 | AO49: 1906 年旧金山大地震引发大火，死亡700 人，28818 间房屋损毁 美军占领古巴到 1909年 卢西塔尼亚和毛里塔尼亚号下水 自动点唱机 舰艇舷外发动机量产 | AP49: 总统： 西奥多·罗斯福（共和党） | AQ49: 动画 电动洗衣机 家用洗洁精 立式吸尘器 饮用纸杯 双层公交车 无线电测向仪 电煎锅 质子和电子 玻璃纸 战壕风衣 汽车自动起动器 麦片 氯气毒气 防毒面具 拉链 机械雨刮器 广义相对论 芥子气 量产拖拉机 电子钟 黄油枪 降落伞 广播电台播音 茶包 罗夏墨迹测验 机器人 胰岛素 实用邮戳机 滑水 百日咳疫苗 纸制鸡蛋托 面巾纸 商用飞机农药喷撒 液体燃料火箭 劳力士防水表 遥控电唱机 面包机 防水玻璃纸 电传打字机 盖革计数器 纯维生素C 彩色电影胶片 透明胶带 音乐汽车喇叭 闪光灯 速冻食品 球形潜水舱 回旋加速器 折叠式雨伞 电动剃须刀 车载收音机 玛氏巧克力棒 变焦镜头 大富翁桌游 商业洗衣店 畅销平装书 里氏震级 磁带录音机 大众汽车 超市推车 带温控器的电熨斗 速溶咖啡 尼龙 圆珠笔 黄热病疫苗 雷达 汽车自动变速箱 充气救生衣 人工授精 青霉素 军用吉普车 原子裂变 火箭筒 凝固汽油弹 水肺 麦角酸二乙酰胺 神经毒气 原子弹 特百惠 计算机 静电复印法 比基尼泳衣 浓缩咖啡机 宝丽来相机 拼字盘 实心电吉他 尼龙扣 晶体管 黑胶唱片 有线电视 电视显像管 汽车自动点火装置 信用卡 复印机 宽荧幕电影 动力转向器 三色停车灯 人行红绿灯 晶体管助听器 氢弹 录像带 DNA双螺旋结构 麻疹疫苗 按动圆珠笔 硅晶体管 核导弹 空对空导弹 迪士尼乐园 特氟龙 卡丁车 地对空核导弹 沙宾疫苗 通讯卫星 呼啦圈 安全带 人工肾脏 避孕药 气象卫星 便携晶体管收音机 安定 砷化镓半导体激光器 三维全息技术 合成器 香烟健康警示 凯夫拉纤维 子午胎 IBM文字处理机 杜比A型降噪器 滑雪板 喇叭裤 绕月载人火箭 人工心脏移植 波音747喷气式客机 互联网 条形码 软盘 帆板 热裤 液晶显示 便携电子计算器 电视游戏 DNA重组技术 电子游戏机 超级计算机 光纤 试管婴儿 魔方 索尼Walkman 杜比C型降噪器 艾滋病毒 强效可卡因 温室效应 CD 暗物质 暗能量 太阳能飞行器 甲型H1N1 流感 希格斯玻色子 引力波 | AR49: 电气地铁 圣代冰淇淋 实用水电站 手电 电影摄影机 收音机 霍乱疫苗 啤酒瓶盖 柴油发动机 双向电报 实用的胶卷 块麦片 电报 可口可乐 X射线 卷烟机发明 电影放映机 排球 印名片机 福特车 潜望镜 油印蜡纸发明 阴极射线管 商品阿司匹林 凯洛格牌玉米片 手电筒 钋 镭 摇控器 α粒子 β粒子 打字机 柯达布朗尼相机 齐柏林飞艇 人类血型 跨大西洋电报 汽轮机游船 现代柏油路 铝罐奶粉 爆米花 泰迪熊 卡鲁索电唱机 便宜的肥皂和烹饪用油 飞机 荧光灯 邮戳机 摩托车发动机 热水瓶 农业轨道机械 木棉安全带 电动汽车喇叭 化学泡沫灭火器 狭义相对论 自动点唱机 量产舰艇舷外发动机 | AS49: 自动点唱机 量产舰艇舷外发动机 | AT49: 1906
O50: 双脚 | X50: 射击③ | AE50: 1907 | AF50: —— | AI50: —— | AL50: 二十世纪初 | AM50: 丁未羊年 | AN50: 清光绪33年 | AO50: 西弗吉尼亚州煤矿矿难死亡361 人 拉斯普京在沙俄飞扬跋扈 动画 电动洗衣机 家用洗洁精 立式吸尘器 | AP50: 总统： 西奥多·罗斯福（共和党） | AQ50: 饮用纸杯 双层公交车 无线电测向仪 电煎锅 质子和电子 玻璃纸 战壕风衣 汽车自动起动器 麦片 氯气毒气 防毒面具 拉链 机械雨刮器 广义相对论 芥子气 量产拖拉机 电子钟 黄油枪 降落伞 广播电台播音 茶包 罗夏墨迹测验 机器人 胰岛素 实用邮戳机 滑水 百日咳疫苗 纸制鸡蛋托 面巾纸 商用飞机农药喷撒 液体燃料火箭 劳力士防水表 遥控电唱机 面包机 防水玻璃纸 电传打字机 盖革计数器 纯维生素C 彩色电影胶片 透明胶带 音乐汽车喇叭 闪光灯 速冻食品 球形潜水舱 回旋加速器 折叠式雨伞 电动剃须刀 车载收音机 玛氏巧克力棒 变焦镜头 大富翁桌游 商业洗衣店 畅销平装书 里氏震级 磁带录音机 大众汽车 超市推车 带温控器的电熨斗 速溶咖啡 尼龙 圆珠笔 黄热病疫苗 雷达 汽车自动变速箱 充气救生衣 人工授精 青霉素 军用吉普车 原子裂变 火箭筒 凝固汽油弹 水肺 麦角酸二乙酰胺 神经毒气 原子弹 特百惠 计算机 静电复印法 比基尼泳衣 浓缩咖啡机 宝丽来相机 拼字盘 实心电吉他 尼龙扣 晶体管 黑胶唱片 有线电视 电视显像管 汽车自动点火装置 信用卡 复印机 宽荧幕电影 动力转向器 三色停车灯 人行红绿灯 晶体管助听器 氢弹 录像带 DNA双螺旋结构 麻疹疫苗 按动圆珠笔 硅晶体管 核导弹 空对空导弹 迪士尼乐园 特氟龙 卡丁车 地对空核导弹 沙宾疫苗 通讯卫星 呼啦圈 安全带 人工肾脏 避孕药 气象卫星 便携晶体管收音机 安定 砷化镓半导体激光器 三维全息技术 合成器 香烟健康警示 凯夫拉纤维 子午胎 IBM文字处理机 杜比A型降噪器 滑雪板 喇叭裤 绕月载人火箭 人工心脏移植 波音747喷气式客机 互联网 条形码 软盘 帆板 热裤 液晶显示 便携电子计算器 电视游戏 DNA重组技术 电子游戏机 超级计算机 光纤 试管婴儿 魔方 索尼Walkman 杜比C型降噪器 艾滋病毒 强效可卡因 温室效应 CD 暗物质 暗能量 太阳能飞行器 甲型H1N1 流感 希格斯玻色子 引力波 | AR50: 电气地铁 圣代冰淇淋 实用水电站 手电 电影摄影机 收音机 霍乱疫苗 啤酒瓶盖 柴油发动机 双向电报 实用的胶卷 块麦片 电报 可口可乐 X射线 卷烟机发明 电影放映机 排球 印名片机 福特车 潜望镜 油印蜡纸发明 阴极射线管 商品阿司匹林 凯洛格牌玉米片 手电筒 钋 镭 摇控器 α粒子 β粒子 打字机 柯达布朗尼相机 齐柏林飞艇 人类血型 跨大西洋电报 汽轮机游船 现代柏油路 铝罐奶粉 爆米花 泰迪熊 卡鲁索电唱机 便宜的肥皂和烹饪用油 飞机 荧光灯 邮戳机 摩托车发动机 热水瓶 农业轨道机械 木棉安全带 电动汽车喇叭 化学泡沫灭火器 狭义相对论 自动点唱机 量产舰艇舷外发动机 动画 电动洗衣机 家用洗洁精 立式吸尘器 | AS50: 动画 电动洗衣机 家用洗洁精 立式吸尘器 | AT50: 1907
O51: 左腿 | X51: 急救 | AE51: 1908 | AF51: 伦敦奥运会 | AI51: —— | AL51: 二十世纪初 | AM51: 戊申猴年 | AN51: 清光绪34年 | AO51: 敏可夫斯基阐述他的四维几何 饮用纸杯 | AP51: 总统： 西奥多·罗斯福（共和党） | AQ51: 双层公交车 无线电测向仪 电煎锅 质子和电子 玻璃纸 战壕风衣 汽车自动起动器 麦片 氯气毒气 防毒面具 拉链 机械雨刮器 广义相对论 芥子气 量产拖拉机 电子钟 黄油枪 降落伞 广播电台播音 茶包 罗夏墨迹测验 机器人 胰岛素 实用邮戳机 滑水 百日咳疫苗 纸制鸡蛋托 面巾纸 商用飞机农药喷撒 液体燃料火箭 劳力士防水表 遥控电唱机 面包机 防水玻璃纸 电传打字机 盖革计数器 纯维生素C 彩色电影胶片 透明胶带 音乐汽车喇叭 闪光灯 速冻食品 球形潜水舱 回旋加速器 折叠式雨伞 电动剃须刀 车载收音机 玛氏巧克力棒 变焦镜头 大富翁桌游 商业洗衣店 畅销平装书 里氏震级 磁带录音机 大众汽车 超市推车 带温控器的电熨斗 速溶咖啡 尼龙 圆珠笔 黄热病疫苗 雷达 汽车自动变速箱 充气救生衣 人工授精 青霉素 军用吉普车 原子裂变 火箭筒 凝固汽油弹 水肺 麦角酸二乙酰胺 神经毒气 原子弹 特百惠 计算机 静电复印法 比基尼泳衣 浓缩咖啡机 宝丽来相机 拼字盘 实心电吉他 尼龙扣 晶体管 黑胶唱片 有线电视 电视显像管 汽车自动点火装置 信用卡 复印机 宽荧幕电影 动力转向器 三色停车灯 人行红绿灯 晶体管助听器 氢弹 录像带 DNA双螺旋结构 麻疹疫苗 按动圆珠笔 硅晶体管 核导弹 空对空导弹 迪士尼乐园 特氟龙 卡丁车 地对空核导弹 沙宾疫苗 通讯卫星 呼啦圈 安全带 人工肾脏 避孕药 气象卫星 便携晶体管收音机 安定 砷化镓半导体激光器 三维全息技术 合成器 香烟健康警示 凯夫拉纤维 子午胎 IBM文字处理机 杜比A型降噪器 滑雪板 喇叭裤 绕月载人火箭 人工心脏移植 波音747喷气式客机 互联网 条形码 软盘 帆板 热裤 液晶显示 便携电子计算器 电视游戏 DNA重组技术 电子游戏机 超级计算机 光纤 试管婴儿 魔方 索尼Walkman 杜比C型降噪器 艾滋病毒 强效可卡因 温室效应 CD 暗物质 暗能量 太阳能飞行器 甲型H1N1 流感 希格斯玻色子 引力波 | AR51: 电气地铁 圣代冰淇淋 实用水电站 手电 电影摄影机 收音机 霍乱疫苗 啤酒瓶盖 柴油发动机 双向电报 实用的胶卷 块麦片 电报 可口可乐 X射线 卷烟机发明 电影放映机 排球 印名片机 福特车 潜望镜 油印蜡纸发明 阴极射线管 商品阿司匹林 凯洛格牌玉米片 手电筒 钋 镭 摇控器 α粒子 β粒子 打字机 柯达布朗尼相机 齐柏林飞艇 人类血型 跨大西洋电报 汽轮机游船 现代柏油路 铝罐奶粉 爆米花 泰迪熊 卡鲁索电唱机 便宜的肥皂和烹饪用油 飞机 荧光灯 邮戳机 摩托车发动机 热水瓶 农业轨道机械 木棉安全带 电动汽车喇叭 化学泡沫灭火器 狭义相对论 自动点唱机 量产舰艇舷外发动机 动画 电动洗衣机 家用洗洁精 立式吸尘器 饮用纸杯 | AS51: 饮用纸杯 | AT51: 1908
E52: =IF(人物卡!M5=0," ","["&LOOKUP(人物卡!M5,职业列表!A2:A232,职业列表!B2:B232)&"]") -> [探险家] | H52: ←这个职业 要这样获得技能点→ | J52: =IF(人物卡!M5=0," ","["&LOOKUP(人物卡!M5,职业列表!A2:C232,职业列表!E2:E232)&"]") -> [教育×2＋外貌或敏捷或力量×2] | O52: 右腿 | X52: 历史 | AE52: 1909 | AF52: —— | AI52: —— | AL52: 二十世纪初 清·宣统元年 | AM52: 己酉鸡年 | AN52: 清宣统元年 | AO52: 罗伯特·E·皮尔里抵达北极点 路易斯安那和密西西比州飓风，死亡350 人 首次穿越英吉利海峡的飞行 英国双层公交车 | AP52: 总统： 西奥多·罗斯福（共和党） 威廉·霍华德·塔夫脱（共和党） | AQ52: 无线电测向仪 电煎锅 质子和电子 玻璃纸 战壕风衣 汽车自动起动器 麦片 氯气毒气 防毒面具 拉链 机械雨刮器 广义相对论 芥子气 量产拖拉机 电子钟 黄油枪 降落伞 广播电台播音 茶包 罗夏墨迹测验 机器人 胰岛素 实用邮戳机 滑水 百日咳疫苗 纸制鸡蛋托 面巾纸 商用飞机农药喷撒 液体燃料火箭 劳力士防水表 遥控电唱机 面包机 防水玻璃纸 电传打字机 盖革计数器 纯维生素C 彩色电影胶片 透明胶带 音乐汽车喇叭 闪光灯 速冻食品 球形潜水舱 回旋加速器 折叠式雨伞 电动剃须刀 车载收音机 玛氏巧克力棒 变焦镜头 大富翁桌游 商业洗衣店 畅销平装书 里氏震级 磁带录音机 大众汽车 超市推车 带温控器的电熨斗 速溶咖啡 尼龙 圆珠笔 黄热病疫苗 雷达 汽车自动变速箱 充气救生衣 人工授精 青霉素 军用吉普车 原子裂变 火箭筒 凝固汽油弹 水肺 麦角酸二乙酰胺 神经毒气 原子弹 特百惠 计算机 静电复印法 比基尼泳衣 浓缩咖啡机 宝丽来相机 拼字盘 实心电吉他 尼龙扣 晶体管 黑胶唱片 有线电视 电视显像管 汽车自动点火装置 信用卡 复印机 宽荧幕电影 动力转向器 三色停车灯 人行红绿灯 晶体管助听器 氢弹 录像带 DNA双螺旋结构 麻疹疫苗 按动圆珠笔 硅晶体管 核导弹 空对空导弹 迪士尼乐园 特氟龙 卡丁车 地对空核导弹 沙宾疫苗 通讯卫星 呼啦圈 安全带 人工肾脏 避孕药 气象卫星 便携晶体管收音机 安定 砷化镓半导体激光器 三维全息技术 合成器 香烟健康警示 凯夫拉纤维 子午胎 IBM文字处理机 杜比A型降噪器 滑雪板 喇叭裤 绕月载人火箭 人工心脏移植 波音747喷气式客机 互联网 条形码 软盘 帆板 热裤 液晶显示 便携电子计算器 电视游戏 DNA重组技术 电子游戏机 超级计算机 光纤 试管婴儿 魔方 索尼Walkman 杜比C型降噪器 艾滋病毒 强效可卡因 温室效应 CD 暗物质 暗能量 太阳能飞行器 甲型H1N1 流感 希格斯玻色子 引力波 | AR52: 电气地铁 圣代冰淇淋 实用水电站 手电 电影摄影机 收音机 霍乱疫苗 啤酒瓶盖 柴油发动机 双向电报 实用的胶卷 块麦片 电报 可口可乐 X射线 卷烟机发明 电影放映机 排球 印名片机 福特车 潜望镜 油印蜡纸发明 阴极射线管 商品阿司匹林 凯洛格牌玉米片 手电筒 钋 镭 摇控器 α粒子 β粒子 打字机 柯达布朗尼相机 齐柏林飞艇 人类血型 跨大西洋电报 汽轮机游船 现代柏油路 铝罐奶粉 爆米花 泰迪熊 卡鲁索电唱机 便宜的肥皂和烹饪用油 飞机 荧光灯 邮戳机 摩托车发动机 热水瓶 农业轨道机械 木棉安全带 电动汽车喇叭 化学泡沫灭火器 狭义相对论 自动点唱机 量产舰艇舷外发动机 动画 电动洗衣机 家用洗洁精 立式吸尘器 饮用纸杯 双层公交车 | AS52: 双层公交车 | AT52: 1909
E53: =IF(人物卡!M5=0," ","["&LOOKUP(人物卡!M5,职业列表!A2:A232,职业列表!B2:B232)&"]的本职技能："&LOOKUP(人物卡!M5,职业列表!A2:A232,职业列表!G2:G232)) -> [探险家]的本职技能：人类学，考古学，估价，科学（生物学），攀爬，急救，射击（手枪、来复枪），格斗（斗殴），博物学，导航，其他语言（任意），驾驶（小艇，船，热气球），骑术，潜行，侦查，游泳，追踪 | J53: =IF(人物卡!M5=0," ",LOOKUP(人物卡!M5,职业列表!A2:C232,职业列表!F2:F232)) -> 310 | O53: 双腿 | X53: 恐吓 | AE53: 1910 | AF53: —— | AI53: —— | AL53: 二十世纪 十年代 清·宣统二年 | AM53: 庚戌狗年 | AN53: 清宣统2年 | AO53: 明尼苏达州弗吉尼亚，滑坡掩埋诺曼露天煤矿工人 华盛顿州惠灵顿火车被雪崩掩埋，死亡96 人 约翰·默里和约翰·休特进行首次深海探险 无线电测向仪 美国童子军成立 美国人口920 万人 | AP53: 总统： 威廉·霍华德·塔夫脱（共和党） | AQ53: 电煎锅 质子和电子 玻璃纸 战壕风衣 汽车自动起动器 麦片 氯气毒气 防毒面具 拉链 机械雨刮器 广义相对论 芥子气 量产拖拉机 电子钟 黄油枪 降落伞 广播电台播音 茶包 罗夏墨迹测验 机器人 胰岛素 实用邮戳机 滑水 百日咳疫苗 纸制鸡蛋托 面巾纸 商用飞机农药喷撒 液体燃料火箭 劳力士防水表 遥控电唱机 面包机 防水玻璃纸 电传打字机 盖革计数器 纯维生素C 彩色电影胶片 透明胶带 音乐汽车喇叭 闪光灯 速冻食品 球形潜水舱 回旋加速器 折叠式雨伞 电动剃须刀 车载收音机 玛氏巧克力棒 变焦镜头 大富翁桌游 商业洗衣店 畅销平装书 里氏震级 磁带录音机 大众汽车 超市推车 带温控器的电熨斗 速溶咖啡 尼龙 圆珠笔 黄热病疫苗 雷达 汽车自动变速箱 充气救生衣 人工授精 青霉素 军用吉普车 原子裂变 火箭筒 凝固汽油弹 水肺 麦角酸二乙酰胺 神经毒气 原子弹 特百惠 计算机 静电复印法 比基尼泳衣 浓缩咖啡机 宝丽来相机 拼字盘 实心电吉他 尼龙扣 晶体管 黑胶唱片 有线电视 电视显像管 汽车自动点火装置 信用卡 复印机 宽荧幕电影 动力转向器 三色停车灯 人行红绿灯 晶体管助听器 氢弹 录像带 DNA双螺旋结构 麻疹疫苗 按动圆珠笔 硅晶体管 核导弹 空对空导弹 迪士尼乐园 特氟龙 卡丁车 地对空核导弹 沙宾疫苗 通讯卫星 呼啦圈 安全带 人工肾脏 避孕药 气象卫星 便携晶体管收音机 安定 砷化镓半导体激光器 三维全息技术 合成器 香烟健康警示 凯夫拉纤维 子午胎 IBM文字处理机 杜比A型降噪器 滑雪板 喇叭裤 绕月载人火箭 人工心脏移植 波音747喷气式客机 互联网 条形码 软盘 帆板 热裤 液晶显示 便携电子计算器 电视游戏 DNA重组技术 电子游戏机 超级计算机 光纤 试管婴儿 魔方 索尼Walkman 杜比C型降噪器 艾滋病毒 强效可卡因 温室效应 CD 暗物质 暗能量 太阳能飞行器 甲型H1N1 流感 希格斯玻色子 引力波 | AR53: 电气地铁 圣代冰淇淋 实用水电站 手电 电影摄影机 收音机 霍乱疫苗 啤酒瓶盖 柴油发动机 双向电报 实用的胶卷 块麦片 电报 可口可乐 X射线 卷烟机发明 电影放映机 排球 印名片机 福特车 潜望镜 油印蜡纸发明 阴极射线管 商品阿司匹林 凯洛格牌玉米片 手电筒 钋 镭 摇控器 α粒子 β粒子 打字机 柯达布朗尼相机 齐柏林飞艇 人类血型 跨大西洋电报 汽轮机游船 现代柏油路 铝罐奶粉 爆米花 泰迪熊 卡鲁索电唱机 便宜的肥皂和烹饪用油 飞机 荧光灯 邮戳机 摩托车发动机 热水瓶 农业轨道机械 木棉安全带 电动汽车喇叭 化学泡沫灭火器 狭义相对论 自动点唱机 量产舰艇舷外发动机 动画 电动洗衣机 家用洗洁精 立式吸尘器 饮用纸杯 双层公交车 无线电测向仪 | AS53: 无线电测向仪 | AT53: 1910
O54: 膝部 | X54: 跳跃 | AE54: 1911 | AF54: —— | AI54: 辛亥革命 | AL54: 二十世纪 十年代 清·宣统三年 | AM54: 辛亥猪年 | AN54: 清宣统3年 | AO54: 泽西市火车站40 吨炸药爆炸，死亡30 人 纽约三角女衬衫厂火灾，死亡145 人 埃米利亚诺·萨帕塔兵临墨西哥城 辛亥革命 电煎锅 挪威探险家罗阿尔德·阿蒙森抵达南极 | AP54: 歌剧： 巴托克·贝拉《蓝胡子公爵的城堡》 总统： 威廉·霍华德·塔夫脱（共和党） | AQ54: 质子和电子 玻璃纸 战壕风衣 汽车自动起动器 麦片 氯气毒气 防毒面具 拉链 机械雨刮器 广义相对论 芥子气 量产拖拉机 电子钟 黄油枪 降落伞 广播电台播音 茶包 罗夏墨迹测验 机器人 胰岛素 实用邮戳机 滑水 百日咳疫苗 纸制鸡蛋托 面巾纸 商用飞机农药喷撒 液体燃料火箭 劳力士防水表 遥控电唱机 面包机 防水玻璃纸 电传打字机 盖革计数器 纯维生素C 彩色电影胶片 透明胶带 音乐汽车喇叭 闪光灯 速冻食品 球形潜水舱 回旋加速器 折叠式雨伞 电动剃须刀 车载收音机 玛氏巧克力棒 变焦镜头 大富翁桌游 商业洗衣店 畅销平装书 里氏震级 磁带录音机 大众汽车 超市推车 带温控器的电熨斗 速溶咖啡 尼龙 圆珠笔 黄热病疫苗 雷达 汽车自动变速箱 充气救生衣 人工授精 青霉素 军用吉普车 原子裂变 火箭筒 凝固汽油弹 水肺 麦角酸二乙酰胺 神经毒气 原子弹 特百惠 计算机 静电复印法 比基尼泳衣 浓缩咖啡机 宝丽来相机 拼字盘 实心电吉他 尼龙扣 晶体管 黑胶唱片 有线电视 电视显像管 汽车自动点火装置 信用卡 复印机 宽荧幕电影 动力转向器 三色停车灯 人行红绿灯 晶体管助听器 氢弹 录像带 DNA双螺旋结构 麻疹疫苗 按动圆珠笔 硅晶体管 核导弹 空对空导弹 迪士尼乐园 特氟龙 卡丁车 地对空核导弹 沙宾疫苗 通讯卫星 呼啦圈 安全带 人工肾脏 避孕药 气象卫星 便携晶体管收音机 安定 砷化镓半导体激光器 三维全息技术 合成器 香烟健康警示 凯夫拉纤维 子午胎 IBM文字处理机 杜比A型降噪器 滑雪板 喇叭裤 绕月载人火箭 人工心脏移植 波音747喷气式客机 互联网 条形码 软盘 帆板 热裤 液晶显示 便携电子计算器 电视游戏 DNA重组技术 电子游戏机 超级计算机 光纤 试管婴儿 魔方 索尼Walkman 杜比C型降噪器 艾滋病毒 强效可卡因 温室效应 CD 暗物质 暗能量 太阳能飞行器 甲型H1N1 流感 希格斯玻色子 引力波 | AR54: 电气地铁 圣代冰淇淋 实用水电站 手电 电影摄影机 收音机 霍乱疫苗 啤酒瓶盖 柴油发动机 双向电报 实用的胶卷 块麦片 电报 可口可乐 X射线 卷烟机发明 电影放映机 排球 印名片机 福特车 潜望镜 油印蜡纸发明 阴极射线管 商品阿司匹林 凯洛格牌玉米片 手电筒 钋 镭 摇控器 α粒子 β粒子 打字机 柯达布朗尼相机 齐柏林飞艇 人类血型 跨大西洋电报 汽轮机游船 现代柏油路 铝罐奶粉 爆米花 泰迪熊 卡鲁索电唱机 便宜的肥皂和烹饪用油 飞机 荧光灯 邮戳机 摩托车发动机 热水瓶 农业轨道机械 木棉安全带 电动汽车喇叭 化学泡沫灭火器 狭义相对论 自动点唱机 量产舰艇舷外发动机 动画 电动洗衣机 家用洗洁精 立式吸尘器 饮用纸杯 双层公交车 无线电测向仪 电煎锅 | AS54: 电煎锅 | AT54: 1911
O55: 其他(下肢) | X55: 外语① | AE55: 1912 | AF55: 日本改元大正 | AG55: 斯德哥尔摩奥运会 | AI55: 中华民国成立 | AJ55: 清帝退位 | AL55: 二十世纪 十年代 民国元年 | AM55: 壬子鼠年 | AN55: 民国元年 | AO55: 泰坦尼克号撞上冰山，1517 名船员和乘客死亡 由威尔逊云室发现质子和电子 赛璐玢（玻璃纸) 获得专利 伦敦裁缝街发明战壕风衣 凯迪拉克展示首个汽车自动起动器 加利福尼亚州两个自助杂货店开业 | AP55: 总统： 威廉·霍华德·塔夫脱（共和党） | AQ55: 麦片 氯气毒气 防毒面具 拉链 机械雨刮器 广义相对论 芥子气 量产拖拉机 电子钟 黄油枪 降落伞 广播电台播音 茶包 罗夏墨迹测验 机器人 胰岛素 实用邮戳机 滑水 百日咳疫苗 纸制鸡蛋托 面巾纸 商用飞机农药喷撒 液体燃料火箭 劳力士防水表 遥控电唱机 面包机 防水玻璃纸 电传打字机 盖革计数器 纯维生素C 彩色电影胶片 透明胶带 音乐汽车喇叭 闪光灯 速冻食品 球形潜水舱 回旋加速器 折叠式雨伞 电动剃须刀 车载收音机 玛氏巧克力棒 变焦镜头 大富翁桌游 商业洗衣店 畅销平装书 里氏震级 磁带录音机 大众汽车 超市推车 带温控器的电熨斗 速溶咖啡 尼龙 圆珠笔 黄热病疫苗 雷达 汽车自动变速箱 充气救生衣 人工授精 青霉素 军用吉普车 原子裂变 火箭筒 凝固汽油弹 水肺 麦角酸二乙酰胺 神经毒气 原子弹 特百惠 计算机 静电复印法 比基尼泳衣 浓缩咖啡机 宝丽来相机 拼字盘 实心电吉他 尼龙扣 晶体管 黑胶唱片 有线电视 电视显像管 汽车自动点火装置 信用卡 复印机 宽荧幕电影 动力转向器 三色停车灯 人行红绿灯 晶体管助听器 氢弹 录像带 DNA双螺旋结构 麻疹疫苗 按动圆珠笔 硅晶体管 核导弹 空对空导弹 迪士尼乐园 特氟龙 卡丁车 地对空核导弹 沙宾疫苗 通讯卫星 呼啦圈 安全带 人工肾脏 避孕药 气象卫星 便携晶体管收音机 安定 砷化镓半导体激光器 三维全息技术 合成器 香烟健康警示 凯夫拉纤维 子午胎 IBM文字处理机 杜比A型降噪器 滑雪板 喇叭裤 绕月载人火箭 人工心脏移植 波音747喷气式客机 互联网 条形码 软盘 帆板 热裤 液晶显示 便携电子计算器 电视游戏 DNA重组技术 电子游戏机 超级计算机 光纤 试管婴儿 魔方 索尼Walkman 杜比C型降噪器 艾滋病毒 强效可卡因 温室效应 CD 暗物质 暗能量 太阳能飞行器 甲型H1N1 流感 希格斯玻色子 引力波 | AR55: 电气地铁 圣代冰淇淋 实用水电站 手电 电影摄影机 收音机 霍乱疫苗 啤酒瓶盖 柴油发动机 双向电报 实用的胶卷 块麦片 电报 可口可乐 X射线 卷烟机发明 电影放映机 排球 印名片机 福特车 潜望镜 油印蜡纸发明 阴极射线管 商品阿司匹林 凯洛格牌玉米片 手电筒 钋 镭 摇控器 α粒子 β粒子 打字机 柯达布朗尼相机 齐柏林飞艇 人类血型 跨大西洋电报 汽轮机游船 现代柏油路 铝罐奶粉 爆米花 泰迪熊 卡鲁索电唱机 便宜的肥皂和烹饪用油 飞机 荧光灯 邮戳机 摩托车发动机 热水瓶 农业轨道机械 木棉安全带 电动汽车喇叭 化学泡沫灭火器 狭义相对论 自动点唱机 量产舰艇舷外发动机 动画 电动洗衣机 家用洗洁精 立式吸尘器 饮用纸杯 双层公交车 无线电测向仪 电煎锅 质子和电子 玻璃纸 战壕风衣 汽车自动起动器 | AS55: 质子和电子 玻璃纸 战壕风衣 汽车自动起动器 | AT55: 1912
O56: 其他———— | X56: 外语② | AE56: 1913 | AF56: 巴尔干战争 | AI56: —— | AL56: 二十世纪 十年代 | AM56: 癸丑牛年 | AN56: 民国2年 | AO56: 两次巴尔干战争 英国轮船卡尔瓦达斯号在马尔马拉海的暴风雨中失踪，200 人失踪 伍德罗·威尔逊就任美国总统 汽车自动起动器应用 美国宪法第十六号（所得税)、第十七号修正案（参议员直选) | AP56: 总统： 威廉·霍华德·塔夫脱（共和党） 伍德罗·威尔逊（民主党） | AQ56: 麦片 氯气毒气 防毒面具 拉链 机械雨刮器 广义相对论 芥子气 量产拖拉机 电子钟 黄油枪 降落伞 广播电台播音 茶包 罗夏墨迹测验 机器人 胰岛素 实用邮戳机 滑水 百日咳疫苗 纸制鸡蛋托 面巾纸 商用飞机农药喷撒 液体燃料火箭 劳力士防水表 遥控电唱机 面包机 防水玻璃纸 电传打字机 盖革计数器 纯维生素C 彩色电影胶片 透明胶带 音乐汽车喇叭 闪光灯 速冻食品 球形潜水舱 回旋加速器 折叠式雨伞 电动剃须刀 车载收音机 玛氏巧克力棒 变焦镜头 大富翁桌游 商业洗衣店 畅销平装书 里氏震级 磁带录音机 大众汽车 超市推车 带温控器的电熨斗 速溶咖啡 尼龙 圆珠笔 黄热病疫苗 雷达 汽车自动变速箱 充气救生衣 人工授精 青霉素 军用吉普车 原子裂变 火箭筒 凝固汽油弹 水肺 麦角酸二乙酰胺 神经毒气 原子弹 特百惠 计算机 静电复印法 比基尼泳衣 浓缩咖啡机 宝丽来相机 拼字盘 实心电吉他 尼龙扣 晶体管 黑胶唱片 有线电视 电视显像管 汽车自动点火装置 信用卡 复印机 宽荧幕电影 动力转向器 三色停车灯 人行红绿灯 晶体管助听器 氢弹 录像带 DNA双螺旋结构 麻疹疫苗 按动圆珠笔 硅晶体管 核导弹 空对空导弹 迪士尼乐园 特氟龙 卡丁车 地对空核导弹 沙宾疫苗 通讯卫星 呼啦圈 安全带 人工肾脏 避孕药 气象卫星 便携晶体管收音机 安定 砷化镓半导体激光器 三维全息技术 合成器 香烟健康警示 凯夫拉纤维 子午胎 IBM文字处理机 杜比A型降噪器 滑雪板 喇叭裤 绕月载人火箭 人工心脏移植 波音747喷气式客机 互联网 条形码 软盘 帆板 热裤 液晶显示 便携电子计算器 电视游戏 DNA重组技术 电子游戏机 超级计算机 光纤 试管婴儿 魔方 索尼Walkman 杜比C型降噪器 艾滋病毒 强效可卡因 温室效应 CD 暗物质 暗能量 太阳能飞行器 甲型H1N1 流感 希格斯玻色子 引力波 | AR56: 电气地铁 圣代冰淇淋 实用水电站 手电 电影摄影机 收音机 霍乱疫苗 啤酒瓶盖 柴油发动机 双向电报 实用的胶卷 块麦片 电报 可口可乐 X射线 卷烟机发明 电影放映机 排球 印名片机 福特车 潜望镜 油印蜡纸发明 阴极射线管 商品阿司匹林 凯洛格牌玉米片 手电筒 钋 镭 摇控器 α粒子 β粒子 打字机 柯达布朗尼相机 齐柏林飞艇 人类血型 跨大西洋电报 汽轮机游船 现代柏油路 铝罐奶粉 爆米花 泰迪熊 卡鲁索电唱机 便宜的肥皂和烹饪用油 飞机 荧光灯 邮戳机 摩托车发动机 热水瓶 农业轨道机械 木棉安全带 电动汽车喇叭 化学泡沫灭火器 狭义相对论 自动点唱机 量产舰艇舷外发动机 动画 电动洗衣机 家用洗洁精 立式吸尘器 饮用纸杯 双层公交车 无线电测向仪 电煎锅 质子和电子 玻璃纸 战壕风衣 汽车自动起动器 麦片 氯气毒气 防毒面具 拉链 | AT56: 1913
O57: 其他 | X57: 外语③ | AE57: 1914 | AF57: 第一次世界大战 | AI57: —— | AL57: 二十世纪 十年代 | AM57: 甲寅虎年 | AN57: 民国3年 | AO57: 第一次世界大战爆发 首次空袭 巴拿马运河运行 加利福尼亚州太平洋轮船印度女皇号在圣劳伦斯河上与斯托斯塔德号[6]相撞，死亡1024 人 圣诞停火 | AP57: 总统： 伍德罗·威尔逊（民主党） | AQ57: 麦片 氯气毒气 防毒面具 拉链 机械雨刮器 广义相对论 芥子气 量产拖拉机 电子钟 黄油枪 降落伞 广播电台播音 茶包 罗夏墨迹测验 机器人 胰岛素 实用邮戳机 滑水 百日咳疫苗 纸制鸡蛋托 面巾纸 商用飞机农药喷撒 液体燃料火箭 劳力士防水表 遥控电唱机 面包机 防水玻璃纸 电传打字机 盖革计数器 纯维生素C 彩色电影胶片 透明胶带 音乐汽车喇叭 闪光灯 速冻食品 球形潜水舱 回旋加速器 折叠式雨伞 电动剃须刀 车载收音机 玛氏巧克力棒 变焦镜头 大富翁桌游 商业洗衣店 畅销平装书 里氏震级 磁带录音机 大众汽车 超市推车 带温控器的电熨斗 速溶咖啡 尼龙 圆珠笔 黄热病疫苗 雷达 汽车自动变速箱 充气救生衣 人工授精 青霉素 军用吉普车 原子裂变 火箭筒 凝固汽油弹 水肺 麦角酸二乙酰胺 神经毒气 原子弹 特百惠 计算机 静电复印法 比基尼泳衣 浓缩咖啡机 宝丽来相机 拼字盘 实心电吉他 尼龙扣 晶体管 黑胶唱片 有线电视 电视显像管 汽车自动点火装置 信用卡 复印机 宽荧幕电影 动力转向器 三色停车灯 人行红绿灯 晶体管助听器 氢弹 录像带 DNA双螺旋结构 麻疹疫苗 按动圆珠笔 硅晶体管 核导弹 空对空导弹 迪士尼乐园 特氟龙 卡丁车 地对空核导弹 沙宾疫苗 通讯卫星 呼啦圈 安全带 人工肾脏 避孕药 气象卫星 便携晶体管收音机 安定 砷化镓半导体激光器 三维全息技术 合成器 香烟健康警示 凯夫拉纤维 子午胎 IBM文字处理机 杜比A型降噪器 滑雪板 喇叭裤 绕月载人火箭 人工心脏移植 波音747喷气式客机 互联网 条形码 软盘 帆板 热裤 液晶显示 便携电子计算器 电视游戏 DNA重组技术 电子游戏机 超级计算机 光纤 试管婴儿 魔方 索尼Walkman 杜比C型降噪器 艾滋病毒 强效可卡因 温室效应 CD 暗物质 暗能量 太阳能飞行器 甲型H1N1 流感 希格斯玻色子 引力波 | AR57: 电气地铁 圣代冰淇淋 实用水电站 手电 电影摄影机 收音机 霍乱疫苗 啤酒瓶盖 柴油发动机 双向电报 实用的胶卷 块麦片 电报 可口可乐 X射线 卷烟机发明 电影放映机 排球 印名片机 福特车 潜望镜 油印蜡纸发明 阴极射线管 商品阿司匹林 凯洛格牌玉米片 手电筒 钋 镭 摇控器 α粒子 β粒子 打字机 柯达布朗尼相机 齐柏林飞艇 人类血型 跨大西洋电报 汽轮机游船 现代柏油路 铝罐奶粉 爆米花 泰迪熊 卡鲁索电唱机 便宜的肥皂和烹饪用油 飞机 荧光灯 邮戳机 摩托车发动机 热水瓶 农业轨道机械 木棉安全带 电动汽车喇叭 化学泡沫灭火器 狭义相对论 自动点唱机 量产舰艇舷外发动机 动画 电动洗衣机 家用洗洁精 立式吸尘器 饮用纸杯 双层公交车 无线电测向仪 电煎锅 质子和电子 玻璃纸 战壕风衣 汽车自动起动器 麦片 氯气毒气 防毒面具 拉链 | AT57: 1914
X58: 母语 | AE58: 1915 | AF58: 第一次世界大战 | AI58: 新文化运动 | AL58: 二十世纪 十年代 | AM58: 乙卯兔年 | AN58: 民国4年 | AO58: 卢西塔尼亚号被德国潜艇轰沉，死亡1199 人，美国表示惊愕与愤怒 第一次世界大战造成史无前例的重大伤亡 麦片上市 氯气用作毒气 防毒面具 拉链获得专利 | AP58: 总统： 伍德罗·威尔逊（民主党） | AQ58: 机械雨刮器 广义相对论 芥子气 量产拖拉机 电子钟 黄油枪 降落伞 广播电台播音 茶包 罗夏墨迹测验 机器人 胰岛素 实用邮戳机 滑水 百日咳疫苗 纸制鸡蛋托 面巾纸 商用飞机农药喷撒 液体燃料火箭 劳力士防水表 遥控电唱机 面包机 防水玻璃纸 电传打字机 盖革计数器 纯维生素C 彩色电影胶片 透明胶带 音乐汽车喇叭 闪光灯 速冻食品 球形潜水舱 回旋加速器 折叠式雨伞 电动剃须刀 车载收音机 玛氏巧克力棒 变焦镜头 大富翁桌游 商业洗衣店 畅销平装书 里氏震级 磁带录音机 大众汽车 超市推车 带温控器的电熨斗 速溶咖啡 尼龙 圆珠笔 黄热病疫苗 雷达 汽车自动变速箱 充气救生衣 人工授精 青霉素 军用吉普车 原子裂变 火箭筒 凝固汽油弹 水肺 麦角酸二乙酰胺 神经毒气 原子弹 特百惠 计算机 静电复印法 比基尼泳衣 浓缩咖啡机 宝丽来相机 拼字盘 实心电吉他 尼龙扣 晶体管 黑胶唱片 有线电视 电视显像管 汽车自动点火装置 信用卡 复印机 宽荧幕电影 动力转向器 三色停车灯 人行红绿灯 晶体管助听器 氢弹 录像带 DNA双螺旋结构 麻疹疫苗 按动圆珠笔 硅晶体管 核导弹 空对空导弹 迪士尼乐园 特氟龙 卡丁车 地对空核导弹 沙宾疫苗 通讯卫星 呼啦圈 安全带 人工肾脏 避孕药 气象卫星 便携晶体管收音机 安定 砷化镓半导体激光器 三维全息技术 合成器 香烟健康警示 凯夫拉纤维 子午胎 IBM文字处理机 杜比A型降噪器 滑雪板 喇叭裤 绕月载人火箭 人工心脏移植 波音747喷气式客机 互联网 条形码 软盘 帆板 热裤 液晶显示 便携电子计算器 电视游戏 DNA重组技术 电子游戏机 超级计算机 光纤 试管婴儿 魔方 索尼Walkman 杜比C型降噪器 艾滋病毒 强效可卡因 温室效应 CD 暗物质 暗能量 太阳能飞行器 甲型H1N1 流感 希格斯玻色子 引力波 | AR58: 电气地铁 圣代冰淇淋 实用水电站 手电 电影摄影机 收音机 霍乱疫苗 啤酒瓶盖 柴油发动机 双向电报 实用的胶卷 块麦片 电报 可口可乐 X射线 卷烟机发明 电影放映机 排球 印名片机 福特车 潜望镜 油印蜡纸发明 阴极射线管 商品阿司匹林 凯洛格牌玉米片 手电筒 钋 镭 摇控器 α粒子 β粒子 打字机 柯达布朗尼相机 齐柏林飞艇 人类血型 跨大西洋电报 汽轮机游船 现代柏油路 铝罐奶粉 爆米花 泰迪熊 卡鲁索电唱机 便宜的肥皂和烹饪用油 飞机 荧光灯 邮戳机 摩托车发动机 热水瓶 农业轨道机械 木棉安全带 电动汽车喇叭 化学泡沫灭火器 狭义相对论 自动点唱机 量产舰艇舷外发动机 动画 电动洗衣机 家用洗洁精 立式吸尘器 饮用纸杯 双层公交车 无线电测向仪 电煎锅 质子和电子 玻璃纸 战壕风衣 汽车自动起动器 麦片 氯气毒气 防毒面具 拉链 | AS58: 麦片 氯气毒气 防毒面具 拉链 | AT58: 1915
E59: =IF(人物卡!M5=0," ",LOOKUP(人物卡!M5,职业列表!A2:C232,职业列表!E2:E232)) -> 教育×2＋外貌或敏捷或力量×2 | X59: 法律 | AE59: 1916 | AF59: 第一次世界大战 | AG59: 奥运停办 | AI59: 袁世凯恢复帝制失败 | AL59: 二十世纪 十年代 | AM59: 丙辰龙年 | AN59: 民国5年 | AO59: 凡尔登战役，死亡70 万人 索姆河战役，死亡100 万人 美国脊髓灰质炎流行，死亡7000 人并致2.7 万青少年残疾 加利波利战役 爱尔兰复活节起义 日德兰海战 机械雨刮器 广义相对论 潘兴入侵墨西哥镇压起义军 | AP59: 总统： 伍德罗·威尔逊（民主党） | AQ59: 芥子气 量产拖拉机 电子钟 黄油枪 降落伞 广播电台播音 茶包 罗夏墨迹测验 机器人 胰岛素 实用邮戳机 滑水 百日咳疫苗 纸制鸡蛋托 面巾纸 商用飞机农药喷撒 液体燃料火箭 劳力士防水表 遥控电唱机 面包机 防水玻璃纸 电传打字机 盖革计数器 纯维生素C 彩色电影胶片 透明胶带 音乐汽车喇叭 闪光灯 速冻食品 球形潜水舱 回旋加速器 折叠式雨伞 电动剃须刀 车载收音机 玛氏巧克力棒 变焦镜头 大富翁桌游 商业洗衣店 畅销平装书 里氏震级 磁带录音机 大众汽车 超市推车 带温控器的电熨斗 速溶咖啡 尼龙 圆珠笔 黄热病疫苗 雷达 汽车自动变速箱 充气救生衣 人工授精 青霉素 军用吉普车 原子裂变 火箭筒 凝固汽油弹 水肺 麦角酸二乙酰胺 神经毒气 原子弹 特百惠 计算机 静电复印法 比基尼泳衣 浓缩咖啡机 宝丽来相机 拼字盘 实心电吉他 尼龙扣 晶体管 黑胶唱片 有线电视 电视显像管 汽车自动点火装置 信用卡 复印机 宽荧幕电影 动力转向器 三色停车灯 人行红绿灯 晶体管助听器 氢弹 录像带 DNA双螺旋结构 麻疹疫苗 按动圆珠笔 硅晶体管 核导弹 空对空导弹 迪士尼乐园 特氟龙 卡丁车 地对空核导弹 沙宾疫苗 通讯卫星 呼啦圈 安全带 人工肾脏 避孕药 气象卫星 便携晶体管收音机 安定 砷化镓半导体激光器 三维全息技术 合成器 香烟健康警示 凯夫拉纤维 子午胎 IBM文字处理机 杜比A型降噪器 滑雪板 喇叭裤 绕月载人火箭 人工心脏移植 波音747喷气式客机 互联网 条形码 软盘 帆板 热裤 液晶显示 便携电子计算器 电视游戏 DNA重组技术 电子游戏机 超级计算机 光纤 试管婴儿 魔方 索尼Walkman 杜比C型降噪器 艾滋病毒 强效可卡因 温室效应 CD 暗物质 暗能量 太阳能飞行器 甲型H1N1 流感 希格斯玻色子 引力波 | AR59: 电气地铁 圣代冰淇淋 实用水电站 手电 电影摄影机 收音机 霍乱疫苗 啤酒瓶盖 柴油发动机 双向电报 实用的胶卷 块麦片 电报 可口可乐 X射线 卷烟机发明 电影放映机 排球 印名片机 福特车 潜望镜 油印蜡纸发明 阴极射线管 商品阿司匹林 凯洛格牌玉米片 手电筒 钋 镭 摇控器 α粒子 β粒子 打字机 柯达布朗尼相机 齐柏林飞艇 人类血型 跨大西洋电报 汽轮机游船 现代柏油路 铝罐奶粉 爆米花 泰迪熊 卡鲁索电唱机 便宜的肥皂和烹饪用油 飞机 荧光灯 邮戳机 摩托车发动机 热水瓶 农业轨道机械 木棉安全带 电动汽车喇叭 化学泡沫灭火器 狭义相对论 自动点唱机 量产舰艇舷外发动机 动画 电动洗衣机 家用洗洁精 立式吸尘器 饮用纸杯 双层公交车 无线电测向仪 电煎锅 质子和电子 玻璃纸 战壕风衣 汽车自动起动器 麦片 氯气毒气 防毒面具 拉链 机械雨刮器 广义相对论 | AS59: 机械雨刮器 广义相对论 | AT59: 1916
X60: 图书馆使用 | AB60: 这是个啥？ | AE60: 1917 | AF60: 第一次世界大战 | AG60: 十月革命 | AI60: 张勋复辟失败 | AJ60: 护法运动 | AL60: 二十世纪 十年代 | AM60: 丁巳蛇年 | AN60: 民国6年 | AO60: 美国参加协约国 二月革命和十月革命 芥子气 福特量产拖拉机 轮船卡斯塔利亚号在苏必利尔湖沉没，死亡22 人 宾夕法尼亚州军火库爆炸，死亡133 人 新斯科舍省哈利法克斯船舶爆炸沉没，1600 人死亡 | AP60: 总统： 伍德罗·威尔逊（民主党） | AQ60: 电子钟 黄油枪 降落伞 广播电台播音 茶包 罗夏墨迹测验 机器人 胰岛素 实用邮戳机 滑水 百日咳疫苗 纸制鸡蛋托 面巾纸 商用飞机农药喷撒 液体燃料火箭 劳力士防水表 遥控电唱机 面包机 防水玻璃纸 电传打字机 盖革计数器 纯维生素C 彩色电影胶片 透明胶带 音乐汽车喇叭 闪光灯 速冻食品 球形潜水舱 回旋加速器 折叠式雨伞 电动剃须刀 车载收音机 玛氏巧克力棒 变焦镜头 大富翁桌游 商业洗衣店 畅销平装书 里氏震级 磁带录音机 大众汽车 超市推车 带温控器的电熨斗 速溶咖啡 尼龙 圆珠笔 黄热病疫苗 雷达 汽车自动变速箱 充气救生衣 人工授精 青霉素 军用吉普车 原子裂变 火箭筒 凝固汽油弹 水肺 麦角酸二乙酰胺 神经毒气 原子弹 特百惠 计算机 静电复印法 比基尼泳衣 浓缩咖啡机 宝丽来相机 拼字盘 实心电吉他 尼龙扣 晶体管 黑胶唱片 有线电视 电视显像管 汽车自动点火装置 信用卡 复印机 宽荧幕电影 动力转向器 三色停车灯 人行红绿灯 晶体管助听器 氢弹 录像带 DNA双螺旋结构 麻疹疫苗 按动圆珠笔 硅晶体管 核导弹 空对空导弹 迪士尼乐园 特氟龙 卡丁车 地对空核导弹 沙宾疫苗 通讯卫星 呼啦圈 安全带 人工肾脏 避孕药 气象卫星 便携晶体管收音机 安定 砷化镓半导体激光器 三维全息技术 合成器 香烟健康警示 凯夫拉纤维 子午胎 IBM文字处理机 杜比A型降噪器 滑雪板 喇叭裤 绕月载人火箭 人工心脏移植 波音747喷气式客机 互联网 条形码 软盘 帆板 热裤 液晶显示 便携电子计算器 电视游戏 DNA重组技术 电子游戏机 超级计算机 光纤 试管婴儿 魔方 索尼Walkman 杜比C型降噪器 艾滋病毒 强效可卡因 温室效应 CD 暗物质 暗能量 太阳能飞行器 甲型H1N1 流感 希格斯玻色子 引力波 | AR60: 电气地铁 圣代冰淇淋 实用水电站 手电 电影摄影机 收音机 霍乱疫苗 啤酒瓶盖 柴油发动机 双向电报 实用的胶卷 块麦片 电报 可口可乐 X射线 卷烟机发明 电影放映机 排球 印名片机 福特车 潜望镜 油印蜡纸发明 阴极射线管 商品阿司匹林 凯洛格牌玉米片 手电筒 钋 镭 摇控器 α粒子 β粒子 打字机 柯达布朗尼相机 齐柏林飞艇 人类血型 跨大西洋电报 汽轮机游船 现代柏油路 铝罐奶粉 爆米花 泰迪熊 卡鲁索电唱机 便宜的肥皂和烹饪用油 飞机 荧光灯 邮戳机 摩托车发动机 热水瓶 农业轨道机械 木棉安全带 电动汽车喇叭 化学泡沫灭火器 狭义相对论 自动点唱机 量产舰艇舷外发动机 动画 电动洗衣机 家用洗洁精 立式吸尘器 饮用纸杯 双层公交车 无线电测向仪 电煎锅 质子和电子 玻璃纸 战壕风衣 汽车自动起动器 麦片 氯气毒气 防毒面具 拉链 机械雨刮器 广义相对论 芥子气 量产拖拉机 | AS60: 芥子气 量产拖拉机 | AT60: 1917
X61: 聆听 | AA61: 这是个啥？ | AB61: =IF(ISBLANK(#REF!),"",#REF!) -> #REF! | AC61: 这是个啥？ | AE61: 1918 | AF61: 第一次世界大战 | AI61: —— | AL61: 二十世纪 十年代 | AM61: 戊午马年 | AN61: 民国7年 | AO61: 第一次世界大战结束 苏俄内战 固定美国航空邮件服务 西班牙大流感，死亡2160 万人 美国独眼巨人号离开巴巴多斯后失踪 飞机时速达到150 迈，飞行高度达3万英尺 电子钟 | AP61: 总统： 伍德罗·威尔逊（民主党） | AQ61: 黄油枪 降落伞 广播电台播音 茶包 罗夏墨迹测验 机器人 胰岛素 实用邮戳机 滑水 百日咳疫苗 纸制鸡蛋托 面巾纸 商用飞机农药喷撒 液体燃料火箭 劳力士防水表 遥控电唱机 面包机 防水玻璃纸 电传打字机 盖革计数器 纯维生素C 彩色电影胶片 透明胶带 音乐汽车喇叭 闪光灯 速冻食品 球形潜水舱 回旋加速器 折叠式雨伞 电动剃须刀 车载收音机 玛氏巧克力棒 变焦镜头 大富翁桌游 商业洗衣店 畅销平装书 里氏震级 磁带录音机 大众汽车 超市推车 带温控器的电熨斗 速溶咖啡 尼龙 圆珠笔 黄热病疫苗 雷达 汽车自动变速箱 充气救生衣 人工授精 青霉素 军用吉普车 原子裂变 火箭筒 凝固汽油弹 水肺 麦角酸二乙酰胺 神经毒气 原子弹 特百惠 计算机 静电复印法 比基尼泳衣 浓缩咖啡机 宝丽来相机 拼字盘 实心电吉他 尼龙扣 晶体管 黑胶唱片 有线电视 电视显像管 汽车自动点火装置 信用卡 复印机 宽荧幕电影 动力转向器 三色停车灯 人行红绿灯 晶体管助听器 氢弹 录像带 DNA双螺旋结构 麻疹疫苗 按动圆珠笔 硅晶体管 核导弹 空对空导弹 迪士尼乐园 特氟龙 卡丁车 地对空核导弹 沙宾疫苗 通讯卫星 呼啦圈 安全带 人工肾脏 避孕药 气象卫星 便携晶体管收音机 安定 砷化镓半导体激光器 三维全息技术 合成器 香烟健康警示 凯夫拉纤维 子午胎 IBM文字处理机 杜比A型降噪器 滑雪板 喇叭裤 绕月载人火箭 人工心脏移植 波音747喷气式客机 互联网 条形码 软盘 帆板 热裤 液晶显示 便携电子计算器 电视游戏 DNA重组技术 电子游戏机 超级计算机 光纤 试管婴儿 魔方 索尼Walkman 杜比C型降噪器 艾滋病毒 强效可卡因 温室效应 CD 暗物质 暗能量 太阳能飞行器 甲型H1N1 流感 希格斯玻色子 引力波 | AR61: 电气地铁 圣代冰淇淋 实用水电站 手电 电影摄影机 收音机 霍乱疫苗 啤酒瓶盖 柴油发动机 双向电报 实用的胶卷 块麦片 电报 可口可乐 X射线 卷烟机发明 电影放映机 排球 印名片机 福特车 潜望镜 油印蜡纸发明 阴极射线管 商品阿司匹林 凯洛格牌玉米片 手电筒 钋 镭 摇控器 α粒子 β粒子 打字机 柯达布朗尼相机 齐柏林飞艇 人类血型 跨大西洋电报 汽轮机游船 现代柏油路 铝罐奶粉 爆米花 泰迪熊 卡鲁索电唱机 便宜的肥皂和烹饪用油 飞机 荧光灯 邮戳机 摩托车发动机 热水瓶 农业轨道机械 木棉安全带 电动汽车喇叭 化学泡沫灭火器 狭义相对论 自动点唱机 量产舰艇舷外发动机 动画 电动洗衣机 家用洗洁精 立式吸尘器 饮用纸杯 双层公交车 无线电测向仪 电煎锅 质子和电子 玻璃纸 战壕风衣 汽车自动起动器 麦片 氯气毒气 防毒面具 拉链 机械雨刮器 广义相对论 芥子气 量产拖拉机 电子钟 | AS61: 电子钟 | AT61: 1918
X62: 锁匠 | AB62: 这是个啥？ | AE62: 1919 | AF62: 巴黎和会 | AI62: 五四爱国运动 | AL62: 二十世纪 十年代 | AM62: 己未羊年 | AN62: 民国8年 | AO62: 美国宪法第十八号修正案（禁酒令) 首次跨大西洋飞行（1880 英里，16 小时12 分钟) 黄油枪 降落伞 | AP62: 书籍： 威尔 · 罗杰斯《禁酒时代的牛仔哲学家》 影视： “妖妇”蒂达·巴拉主演《莎乐美》 D·W·格里菲斯导演《残花泪》 朗 · 钱尼《奇人》 总统： 伍德罗·威尔逊（民主党） | AQ62: 广播电台播音 茶包 罗夏墨迹测验 机器人 胰岛素 实用邮戳机 滑水 百日咳疫苗 纸制鸡蛋托 面巾纸 商用飞机农药喷撒 液体燃料火箭 劳力士防水表 遥控电唱机 面包机 防水玻璃纸 电传打字机 盖革计数器 纯维生素C 彩色电影胶片 透明胶带 音乐汽车喇叭 闪光灯 速冻食品 球形潜水舱 回旋加速器 折叠式雨伞 电动剃须刀 车载收音机 玛氏巧克力棒 变焦镜头 大富翁桌游 商业洗衣店 畅销平装书 里氏震级 磁带录音机 大众汽车 超市推车 带温控器的电熨斗 速溶咖啡 尼龙 圆珠笔 黄热病疫苗 雷达 汽车自动变速箱 充气救生衣 人工授精 青霉素 军用吉普车 原子裂变 火箭筒 凝固汽油弹 水肺 麦角酸二乙酰胺 神经毒气 原子弹 特百惠 计算机 静电复印法 比基尼泳衣 浓缩咖啡机 宝丽来相机 拼字盘 实心电吉他 尼龙扣 晶体管 黑胶唱片 有线电视 电视显像管 汽车自动点火装置 信用卡 复印机 宽荧幕电影 动力转向器 三色停车灯 人行红绿灯 晶体管助听器 氢弹 录像带 DNA双螺旋结构 麻疹疫苗 按动圆珠笔 硅晶体管 核导弹 空对空导弹 迪士尼乐园 特氟龙 卡丁车 地对空核导弹 沙宾疫苗 通讯卫星 呼啦圈 安全带 人工肾脏 避孕药 气象卫星 便携晶体管收音机 安定 砷化镓半导体激光器 三维全息技术 合成器 香烟健康警示 凯夫拉纤维 子午胎 IBM文字处理机 杜比A型降噪器 滑雪板 喇叭裤 绕月载人火箭 人工心脏移植 波音747喷气式客机 互联网 条形码 软盘 帆板 热裤 液晶显示 便携电子计算器 电视游戏 DNA重组技术 电子游戏机 超级计算机 光纤 试管婴儿 魔方 索尼Walkman 杜比C型降噪器 艾滋病毒 强效可卡因 温室效应 CD 暗物质 暗能量 太阳能飞行器 甲型H1N1 流感 希格斯玻色子 引力波 | AR62: 电气地铁 圣代冰淇淋 实用水电站 手电 电影摄影机 收音机 霍乱疫苗 啤酒瓶盖 柴油发动机 双向电报 实用的胶卷 块麦片 电报 可口可乐 X射线 卷烟机发明 电影放映机 排球 印名片机 福特车 潜望镜 油印蜡纸发明 阴极射线管 商品阿司匹林 凯洛格牌玉米片 手电筒 钋 镭 摇控器 α粒子 β粒子 打字机 柯达布朗尼相机 齐柏林飞艇 人类血型 跨大西洋电报 汽轮机游船 现代柏油路 铝罐奶粉 爆米花 泰迪熊 卡鲁索电唱机 便宜的肥皂和烹饪用油 飞机 荧光灯 邮戳机 摩托车发动机 热水瓶 农业轨道机械 木棉安全带 电动汽车喇叭 化学泡沫灭火器 狭义相对论 自动点唱机 量产舰艇舷外发动机 动画 电动洗衣机 家用洗洁精 立式吸尘器 饮用纸杯 双层公交车 无线电测向仪 电煎锅 质子和电子 玻璃纸 战壕风衣 汽车自动起动器 麦片 氯气毒气 防毒面具 拉链 机械雨刮器 广义相对论 芥子气 量产拖拉机 电子钟 黄油枪 降落伞 | AS62: 黄油枪 降落伞 | AT62: 1919
S63: =".st "&人物卡!E3&"-"&"力量"&G14&"str"&G14&"敏捷"&J14&"dex"&J14&"意志"&M14&"pow"&M14&"体质"&H14&"con"&H14&"外貌"&K14&"app"&K14&"教育"&N14&"edu"&N14&"体型"&I14&"siz"&I14&"智力"&L14&"灵感"&L14&"int"&L14&"san"&人物卡!N10&"san值"&人物卡!N10&"理智"&人物卡!N10&"理智值"&人物卡!N10&"幸运"&O14&"运气"&O14&"mp"&人物卡!W10&"魔法"&人物卡!W10&"hp"&人物卡!E10&"体力"&人物卡!E10&人物卡!F16&人物卡!R16&人物卡!F17&人物卡!R17&人物卡!F18&人物卡!R18&人物卡!F19&人物卡!R19&IF(人物卡!H20="","",人物卡!H20&人物卡!R20)&IF(人物卡!H21="","",人物卡!H21&人物卡!R21)&IF(人物卡!H22="","",人物卡!H22&人物卡!R22)&人物卡!F23&人物卡!R23&"魅惑"&人物卡!R23&人物卡!F24&人物卡!R24&"计算机"&人物卡!R25&"计算机使用"&人物卡!R25&"电脑"&人物卡!R25&"信用"&人物卡!R26&"信誉"&人物卡!R26&"信用评级"&人物卡!R26&"克苏鲁"&人物卡!R27&"克苏鲁神话"&人物卡!R27&"cm"&人物卡!R27&人物卡!F28&人物卡!R28&人物卡!F29&人物卡!R29&"汽车"&人物卡!R30&"驾驶"&人物卡!R30&"汽车驾驶"&人物卡!R30&人物卡!F31&人物卡!R31&"电子学"&人物卡!R32&人物卡!F33&人物卡!R33&人物卡!H34&人物卡!R34&IF(人物卡!H35="","",人物卡!H35&人物卡!R35)&IF(人物卡!H36="","",人物卡!H36&人物卡!R36)&IF(人物卡!H37="","",人物卡!H36&人物卡!R37)&人物卡!H38&人物卡!R38&IF(W15=1,人物卡!AB39&人物卡!R39&"步枪"&人物卡!R39&"霰弹枪"&人物卡!R39&"步霰"&人物卡!R39,IF(人物卡!H39="","",人物卡!H39&人物卡!R39))&IF(W16=1,人物卡!AB40&人物卡!R40&"步枪"&人物卡!R40&"霰弹枪"&人物卡!R40&"步霰"&人物卡!R40,IF(人物卡!H40="","",人物卡!H40&人物卡!R40))&IF(W17=1,人物卡!AB41&人物卡!R41&"步枪"&人物卡!R41&"霰弹枪"&人物卡!R41&"步霰"&人物卡!R41,IF(人物卡!H41="","",人物卡!H41&人物卡!R41))&人物卡!F42&人物卡!R42&人物卡!F43&人物卡!R43&人物卡!F44&人物卡!R44&人物卡!F45&人物卡!R45&IF(人物卡!H46="","",人物卡!H46&人物卡!R46)&IF(人物卡!H47="","",人物卡!H47&人物卡!R47)&IF(人物卡!H48="","",人物卡!H48&人物卡!R48)&人物卡!F49&人物卡!R49&人物卡!AB16&人物卡!AN16&"图书馆"&人物卡!AN17&"图书馆使用"&人物卡!AN17&人物卡!AB18&人物卡!AN18&"开锁"&人物卡!AN19&"撬锁"&人物卡!AN19&"锁匠"&人物卡!AN19&人物卡!AB20&人物卡!AN20&人物卡!AB21&人物卡!AN21&"博物学"&人物卡!AN22&"自然学"&人物卡!AN22&"领航"&人物卡!AN23&"导航"&人物卡!AN23&人物卡!AB24&人物卡!AN24&"重型操作"&人物卡!AN25&"重型机械"&人物卡!AN25&"操作重型机械"&人物卡!AN25&"重型"&人物卡!AN25&人物卡!AB26&人物卡!AN26&IF(人物卡!AD27="","",人物卡!AD27&人物卡!AN27)&人物卡!AB28&人物卡!AN28&人物卡!AB29&人物卡!AN29&人物卡!AB30&人物卡!AN30&IF(人物卡!AD31="","",人物卡!AD31&人物卡!AN31)&IF(人物卡!AD32="","",人物卡!AD32&人物卡!AN32)&IF(人物卡!AD33="","",人物卡!AD33&人物卡!AN33)&人物卡!AB34&人物卡!AN34&人物卡!AB35&人物卡!AN35&人物卡!AB36&人物卡!AN36&"生存"&人物卡!AN37&人物卡!AB38&人物卡!AN38&人物卡!AB39&人物卡!AN39&人物卡!AB40&人物卡!AN40&人物卡!AB41&人物卡!AN41&人物卡!AB42&人物卡!AN42&人物卡!AB43&人物卡!AN43&人物卡!AB44&人物卡!AN44&人物卡!AB45&人物卡!AN45&人物卡!AB46&人物卡!AN46&IF(人物卡!AD47="","",人物卡!AD47&人物卡!AN47)&IF(W18=1,"",人物卡!AB48&人物卡!AN48)&IF(人物卡!AB49="","",人物卡!AB49&人物卡!AN49) -> .st 艾迪安·多雷-力量90str90敏捷40dex40意志75pow75体质50con50外貌65app65教育65edu65体型70siz70智力80灵感80int80san75san值75理智75理智值75幸运70运气70mp15魔法15hp12体力12会计5人类学1估价5考古学1取悦49魅惑49攀爬20计算机5计算机使用5电脑5信用50信誉50信用评级50克苏鲁0克苏鲁神话0cm0乔装5闪避44汽车20驾驶20汽车驾驶20电气维修10电子学1话术5斗殴65手枪70急救30历史5恐吓15跳跃20母语65法律5图书馆20图书馆使用20聆听49开锁1撬锁1锁匠1机械维修10医学1博物学50自然学50领航10导航10神秘学5重型操作1重型机械1操作重型机械1重型1说服49精神分析1心理学49骑术5妙手10侦查70潜行60生存10游泳20投掷20追踪50驯兽5潜水1爆破1读唇1催眠1炮术1 | X63: 机械维修 | AE63: 1920 | AF63: 咆哮的二十年代（美国） | AG63: 安特卫普奥运会 | AI63: 海原大地震 | AL63: 二十世纪 二十年代 | AM63: 庚申猴年 | AN63: 民国9年 | AO63: 禁酒令生效 布尔什维克赢得苏俄内战 中国海原大地震，死亡 20 万人 首次广播电台播音 茶包 美国公债 243 亿美元 美国人口 1.057 亿 | AP63: 书籍： 赞恩·格雷：《林中人》 弗·斯科特·菲茨杰拉德：《人间天堂》 影视： 朗·钱尼：主演《惩罚》 丽莲·吉许：主演《暴风雨中的孤儿》 约翰·巴里摩尔：出演《化身博士》 玛丽·毕克馥：出演《波丽安娜》 老道格拉斯·范朋克：出演《佐罗的面具》 查理·卓别林、玛丽·毕克馥、道格拉斯·范朋克和传奇制片人兼导演 D·W·格里菲斯成立联美电影公司。 流行歌曲： 《I'll be With You at Apple Blossom Time》 杰 洛 姆· 科 恩《Look for the Silver Lining》 《When My Baby Smiles at Me》 百老汇舞台： 齐格菲尔德歌舞团女星范妮·布莱斯出演《华盛顿广场的玫瑰》 总统： 威廉·塔夫脱（共和党） | AQ63: 罗夏墨迹测验 机器人 胰岛素 实用邮戳机 滑水 百日咳疫苗 纸制鸡蛋托 面巾纸 商用飞机农药喷撒 液体燃料火箭 劳力士防水表 遥控电唱机 面包机 防水玻璃纸 电传打字机 盖革计数器 纯维生素C 彩色电影胶片 透明胶带 音乐汽车喇叭 闪光灯 速冻食品 球形潜水舱 回旋加速器 折叠式雨伞 电动剃须刀 车载收音机 玛氏巧克力棒 变焦镜头 大富翁桌游 商业洗衣店 畅销平装书 里氏震级 磁带录音机 大众汽车 超市推车 带温控器的电熨斗 速溶咖啡 尼龙 圆珠笔 黄热病疫苗 雷达 汽车自动变速箱 充气救生衣 人工授精 青霉素 军用吉普车 原子裂变 火箭筒 凝固汽油弹 水肺 麦角酸二乙酰胺 神经毒气 原子弹 特百惠 计算机 静电复印法 比基尼泳衣 浓缩咖啡机 宝丽来相机 拼字盘 实心电吉他 尼龙扣 晶体管 黑胶唱片 有线电视 电视显像管 汽车自动点火装置 信用卡 复印机 宽荧幕电影 动力转向器 三色停车灯 人行红绿灯 晶体管助听器 氢弹 录像带 DNA双螺旋结构 麻疹疫苗 按动圆珠笔 硅晶体管 核导弹 空对空导弹 迪士尼乐园 特氟龙 卡丁车 地对空核导弹 沙宾疫苗 通讯卫星 呼啦圈 安全带 人工肾脏 避孕药 气象卫星 便携晶体管收音机 安定 砷化镓半导体激光器 三维全息技术 合成器 香烟健康警示 凯夫拉纤维 子午胎 IBM文字处理机 杜比A型降噪器 滑雪板 喇叭裤 绕月载人火箭 人工心脏移植 波音747喷气式客机 互联网 条形码 软盘 帆板 热裤 液晶显示 便携电子计算器 电视游戏 DNA重组技术 电子游戏机 超级计算机 光纤 试管婴儿 魔方 索尼Walkman 杜比C型降噪器 艾滋病毒 强效可卡因 温室效应 CD 暗物质 暗能量 太阳能飞行器 甲型H1N1 流感 希格斯玻色子 引力波 | AR63: 电气地铁 圣代冰淇淋 实用水电站 手电 电影摄影机 收音机 霍乱疫苗 啤酒瓶盖 柴油发动机 双向电报 实用的胶卷 块麦片 电报 可口可乐 X射线 卷烟机发明 电影放映机 排球 印名片机 福特车 潜望镜 油印蜡纸发明 阴极射线管 商品阿司匹林 凯洛格牌玉米片 手电筒 钋 镭 摇控器 α粒子 β粒子 打字机 柯达布朗尼相机 齐柏林飞艇 人类血型 跨大西洋电报 汽轮机游船 现代柏油路 铝罐奶粉 爆米花 泰迪熊 卡鲁索电唱机 便宜的肥皂和烹饪用油 飞机 荧光灯 邮戳机 摩托车发动机 热水瓶 农业轨道机械 木棉安全带 电动汽车喇叭 化学泡沫灭火器 狭义相对论 自动点唱机 量产舰艇舷外发动机 动画 电动洗衣机 家用洗洁精 立式吸尘器 饮用纸杯 双层公交车 无线电测向仪 电煎锅 质子和电子 玻璃纸 战壕风衣 汽车自动起动器 麦片 氯气毒气 防毒面具 拉链 机械雨刮器 广义相对论 芥子气 量产拖拉机 电子钟 黄油枪 降落伞 广播电台播音 茶包 | AS63: 广播电台 茶包 | AT63: 1920
X64: 医学 | AE64: 1921 | AF64: 咆哮的二十年代（美国） | AI64: 中国共产党成立 | AL64: 二十世纪 二十年代 | AM64: 辛酉鸡年 | AN64: 民国10年 | AO64: 罗夏墨迹测验获得专利 德国恶性通胀开始 KDKA 电台转播体育赛事 恰佩克提出“机器人”一词 | AP64: 书籍： 赫伯特·乔治·威尔斯《世界史纲》 赞恩·格雷《神秘骑手》 伊迪斯·华顿《纯真年代》 伊迪斯·霍尔《酋长》 影视： 鲁道夫·瓦伦蒂诺凭借《启示录四骑士》和《沙漠情酋》一夜成名 马克·森内特制作《小城偶像》 卓别林主演《寻子遇仙记》 道格拉斯·范朋克出演《三个火枪手》 流行歌曲： 《Sheik of Araby》 《I'm Just Wild About Harry》 《Ain't We Got Fun》 百老汇舞台： 萨蒂斯餐厅在曼哈顿剧院区开张 范妮·布莱斯出演《二手玫瑰》保持去年的热度 总统： 伍德罗·威尔逊（民主党） 沃伦·甘梅利尔·哈定（共和党） | AQ64: 胰岛素 实用邮戳机 滑水 百日咳疫苗 纸制鸡蛋托 面巾纸 商用飞机农药喷撒 液体燃料火箭 劳力士防水表 遥控电唱机 面包机 防水玻璃纸 电传打字机 盖革计数器 纯维生素C 彩色电影胶片 透明胶带 音乐汽车喇叭 闪光灯 速冻食品 球形潜水舱 回旋加速器 折叠式雨伞 电动剃须刀 车载收音机 玛氏巧克力棒 变焦镜头 大富翁桌游 商业洗衣店 畅销平装书 里氏震级 磁带录音机 大众汽车 超市推车 带温控器的电熨斗 速溶咖啡 尼龙 圆珠笔 黄热病疫苗 雷达 汽车自动变速箱 充气救生衣 人工授精 青霉素 军用吉普车 原子裂变 火箭筒 凝固汽油弹 水肺 麦角酸二乙酰胺 神经毒气 原子弹 特百惠 计算机 静电复印法 比基尼泳衣 浓缩咖啡机 宝丽来相机 拼字盘 实心电吉他 尼龙扣 晶体管 黑胶唱片 有线电视 电视显像管 汽车自动点火装置 信用卡 复印机 宽荧幕电影 动力转向器 三色停车灯 人行红绿灯 晶体管助听器 氢弹 录像带 DNA双螺旋结构 麻疹疫苗 按动圆珠笔 硅晶体管 核导弹 空对空导弹 迪士尼乐园 特氟龙 卡丁车 地对空核导弹 沙宾疫苗 通讯卫星 呼啦圈 安全带 人工肾脏 避孕药 气象卫星 便携晶体管收音机 安定 砷化镓半导体激光器 三维全息技术 合成器 香烟健康警示 凯夫拉纤维 子午胎 IBM文字处理机 杜比A型降噪器 滑雪板 喇叭裤 绕月载人火箭 人工心脏移植 波音747喷气式客机 互联网 条形码 软盘 帆板 热裤 液晶显示 便携电子计算器 电视游戏 DNA重组技术 电子游戏机 超级计算机 光纤 试管婴儿 魔方 索尼Walkman 杜比C型降噪器 艾滋病毒 强效可卡因 温室效应 CD 暗物质 暗能量 太阳能飞行器 甲型H1N1 流感 希格斯玻色子 引力波 | AR64: 电气地铁 圣代冰淇淋 实用水电站 手电 电影摄影机 收音机 霍乱疫苗 啤酒瓶盖 柴油发动机 双向电报 实用的胶卷 块麦片 电报 可口可乐 X射线 卷烟机发明 电影放映机 排球 印名片机 福特车 潜望镜 油印蜡纸发明 阴极射线管 商品阿司匹林 凯洛格牌玉米片 手电筒 钋 镭 摇控器 α粒子 β粒子 打字机 柯达布朗尼相机 齐柏林飞艇 人类血型 跨大西洋电报 汽轮机游船 现代柏油路 铝罐奶粉 爆米花 泰迪熊 卡鲁索电唱机 便宜的肥皂和烹饪用油 飞机 荧光灯 邮戳机 摩托车发动机 热水瓶 农业轨道机械 木棉安全带 电动汽车喇叭 化学泡沫灭火器 狭义相对论 自动点唱机 量产舰艇舷外发动机 动画 电动洗衣机 家用洗洁精 立式吸尘器 饮用纸杯 双层公交车 无线电测向仪 电煎锅 质子和电子 玻璃纸 战壕风衣 汽车自动起动器 麦片 氯气毒气 防毒面具 拉链 机械雨刮器 广义相对论 芥子气 量产拖拉机 电子钟 黄油枪 降落伞 广播电台播音 茶包 罗夏墨迹测验 机器人 | AS64: 罗夏墨迹测验 “机器人” | AT64: 1921
