Workbook
Name APP: 人物卡!$AA$5
Name CON: 人物卡!$U$5
Name DEX: 人物卡!$AA$3
Name EDU: 人物卡!$AG$5
Name INT: 人物卡!$AA$7
Name Luck: 人物卡!$AG$7
Name MP: 人物卡!$W$10
Name POW: 人物卡!$AG$3
Name SIZ: 人物卡!$U$7
Name STR: 人物卡!$U$3

Sheet 人物卡
B1: 彩色-黑红色 欢迎使用！建议用wps打开 可能会有小bug 如果发现了欢迎来群里联系作者（657573844）
B2: 调查员信息 | S2: 年龄补正： | V2: =附表!D37 -> 教育进步*1 | AA2: 属性 | AC2: 总点数(不含运): | AG2: =IF(AC2="总点数(含运):",U3+U5+U7+AA3+AA5+AA7+AG3+AG5+AG7,U3+U5+U7+AA7+AA5+AA3+AG3+AG5) -> 480 | AU2: 调查员可能
B3: 姓名 | E3: 尤金 | J3: 玩家 | M3: 文月 | S3: 力量 STR | U3: 30 | W3: =INT(U3/2) -> 15 | Y3: 敏捷 DEX | AA3: 70 | AC3: =INT(AA3/2) -> 35 | AE3: 意志 POW | AG3: 60 | AI3: =INT(AG3/2) -> 30 | AU3: =IF(U3=0,"",IF(U3<=15,"虚弱，孱弱",IF(U3<=40,"力量弱小",IF(U3<=60,"有正常人的力量",IF(U3<=80,"超乎常人的力量",IF(U3<100,"超乎超乎常人的力量")))))) -> 力量弱小 | BC3: =IF(AA3=0,"",IF(AA3<=20,"很不灵活",IF(AA3<=40,"不是很灵活",IF(AA3<=60,"普通人水平",IF(AA3<=80,"是一位运动健将",IF(AA3<100,"高速而灵活,可以达成超凡的技艺")))))) -> 是一位运动健将 | BK3: =IF(AG3=0,"",IF(AG3<=20,"尔不过玩物",IF(AG3<=40,"痴愚盲目",IF(AG3<=60,"如常人一般会有一定自制力",IF(AG3<=80,"我心如铁，心坚石穿",IF(AG3<100,"泰山崩于面而色不变",IF(AG3<140,"钢铁之心，还能看见鬼","你怕是个假人吧"))))))) -> 如常人一般会有一定自制力
B4: 年龄 | E4: 29 | J4: 时代 | M4: 1920s | W4: =INT(U3/5) -> 6 | AC4: =INT(AA3/5) -> 14 | AI4: =INT(AG3/5) -> 12
B5: 职业 | E5: 私家侦探 | J5: 职业序号 | M5: 219 | S5: 体质 CON | U5: 50 | W5: =INT(U5/2) -> 25 | Y5: 外貌 APP | AA5: 80 | AC5: =INT(AA5/2) -> 40 | AE5: 教育 EDU | AG5: 55 | AI5: =INT(AG5/2) -> 27 | AU5: =IF(U5=0,"",IF(U5<=20,"常年患病在身",IF(U5<=40,"体弱多病",IF(U5<=60,"不会生什么大毛病",IF(U5<=80,"健硕，浑身湿透也不会感冒",IF(U5<100,"身体素质极好，精神抖擞")))))) -> 不会生什么大毛病 | BC5: =IF(AA5=0,"",IF(AA5<=20,"用脸就能恐惧敌人。。或队友",IF(AA5<=40,"有些难看",IF(AA5<=60,"人群之中谁也不会看你一眼之后就忘不掉你容颜",IF(AA5<=80,"五官端正，仪表堂堂",IF(AA5<100,"沉鱼落雁，闭月羞花")))))) -> 五官端正，仪表堂堂 | BK5: =IF(AG5=0,"",IF(AG5<=20,"目不识丁",IF(AG5<=40,"小学毕业",IF(AG5<=60,"高中毕业",IF(AG5<=80,"是重点大学的学生，或是普通大学的研究生",IF(AG5<100,"饱读诗书，满腹经纶")))))) -> 高中毕业
B6: 性别 | E6: 男 | J6: 国籍 | M6: 美国 | W6: =INT(U5/5) -> 10 | AC6: =INT(AA5/5) -> 16 | AI6: =INT(AG5/5) -> 11
B7: 住地 | E7: 布鲁克林区 | J7: 故乡 | M7: 纽约 | S7: 体型 SIZ | U7: 55 | W7: =INT(U7/2) -> 27 | Y7: 智力 灵感 | AA7: 80 | AC7: =INT(AA7/2) -> 40 | AE7: 幸运 Luck | AG7: 50 | AI7: =INT(AG7/2) -> 25 | AU7: =IF(U7=0,"",IF(U7<=20,"孩童，身短体瘦",IF(U7<=40,"乙女身材",IF(U7<=60,"普遍身高155-175",IF(U7<=80,"不是高就是胖",IF(U7<=100,"大号的人",IF(U7<150,"听说你正在申请身高世界记录？",IF(U7<180,"你可能是一头牛",IF(U7<200,"你已经是历史上最重的人类了","过分了喂！"))))))))) -> 普遍身高155-175 | BC7: =IF(INT=0,"",IF(INT<=20,"脑子是个好东西，可惜。。。",IF(INT<=40,"理解知识要耗费比普通人更多的时间",IF(INT<=60,"有着普通人的灵光一现",IF(INT<=80,"可以自主进行发明创造",IF(INT<100,"天才级水准")))))) -> 可以自主进行发明创造 | BK7: =IF(Luck=0,"",IF(Luck<=20,"克夫克妻",IF(Luck<=40,"霉运连连",IF(Luck<=60,"命格平庸",IF(Luck<=80,"在马路边捡到100块",IF(Luck<100,"被幸运女神所眷顾")))))) -> 命格平庸
B8: 现时间 | E8: 公元 | G8: 2023 | J8: 1月 | L8: 1日 | N8: 0：00 | W8: =INT(U7/5) -> 11 | AC8: =INT(AA7/5) -> 16 | AI8: =INT(AG7/5) -> 10
B9: =IF(F9=0,"","任意特长数：") -> 任意特长数： | F9: =INDEX(本职技能!$A$2:$IE$68,MATCH("任意特长",本职技能!$A$2:$A$74,0),MATCH(附表!B58,本职技能!$A$1:$IE$1,0)) -> 1 | K9: =INDEX(本职技能!$A$2:$IE$68,MATCH("☆",本职技能!$A$2:$A$74,0),MATCH(附表!B58,本职技能!$A$1:$IE$1,0)) -> 0 | T9: =INDEX(本职技能!$A$2:$IE$68,MATCH("⊙",本职技能!$A$2:$A$74,0),MATCH(附表!B58,本职技能!$A$1:$IE$1,0)) -> 0 | AC9: =INDEX(本职技能!$A$2:$IE$68,MATCH("☯",本职技能!$A$2:$A$74,0),MATCH(附表!B58,本职技能!$A$1:$IE$1,0)) -> 2 | AL9: =INDEX(本职技能!$A$2:$IE$68,MATCH("※",本职技能!$A$2:$A$74,0),MATCH(附表!B58,本职技能!$A$1:$IE$1,0)) -> 0
B10: 体力 Hit Points | E10: =G10 -> 10 | G10: =INT((U5+U7)/10) -> 10 | I10: 状态: | K10: 理智 Sanity | N10: =IF(AG3>P10,P10,AG3) -> 60 | P10: =99-R28 -> 99 | R10: 状态: | T10: 魔法 Magic Points | W10: =Y10 -> 12 | Y10: =INT(AG3/5) -> 12 | AA10: 每h恢复 | AC10: 移动力 MOV | AF10: =AI11+8 -> 8 | AI10: 调整值 | AK10: 护甲 Armor | AN10: =IF($AN12=0,"0",VLOOKUP($AN12,'防具表 载具表'!B2:I101,2,FALSE)) | AR10: 覆盖部位
I11: 健康 | R11: 清醒 | AA11: =IF(AG3="","",INT(AG3/100+1)) -> 1 | AI11: =附表!C9 -> 0 | AR11: =IF($AN12=0,"",VLOOKUP($AN12,'防具表 载具表'!B2:I101,4,FALSE))
B12: 重伤值: | D12: =CEILING(G10/2,1) -> 5 | F12: 临时体力值： | I12: 0 | K12: 今日损失 : | N12: 0 | P12: 剩余： | R12: =N10-N12 -> 60 | T12: 使用过的魔法 : | AC12: 移动方式 | AE12: 步式 | AG12: 护甲减值 | AI12: 关 | AK12: 护甲类型 : | AN12: 请看【防具表】
B13: [0]经历包可选技能： | I13: =附表!B17 -> 会计，两项社交技能（取悦、话术、恐吓、说服），法律，图书馆，聆听，锁匠，艺术及手艺（摄影），侦查，任意一项其他个人或时代特长
B15: 技能表
B16: 成功标 | D16: =附表!G15 -> 经历包 | F16: 技能名称 | J16: 初始 | L16: 成长/经历 | N16: 职业 | P16: 兴趣 | R16: 成功率 普通/困难/极限 | X16: 成功标 | Z16: =附表!G15 -> 经历包 | AB16: 技能名称 | AF16: 初始 | AH16: 成长/经历 | AJ16: 职业 | AL16: 兴趣 | AN16: 成功率 普通/困难/极限
B17: ☐ | D17: =IF(ISTEXT(IFERROR(VLOOKUP(人物卡!F17,人物卡!BJ19:BR23,1,FALSE),IFERROR(VLOOKUP(人物卡!F17,BB19:BB23,1,FALSE),0))),"★",INDEX(本职技能!$A$2:$IE$75,MATCH(人物卡!F17,本职技能!$A$2:$A$74,0),MATCH(附表!B58,本职技能!$A$1:$IE$1,0))) -> ★ | F17: 会计 | J17: 5 | R17: =SUM(J17:P17) -> 5 | T17: =INT(R17/2) -> 2 | V17: =INT(R17/5) -> 1 | X17: ☐ | Z17: =IF(ISTEXT(IFERROR(VLOOKUP(人物卡!AB17,人物卡!BJ19:BR23,1,FALSE),IFERROR(VLOOKUP(人物卡!AB17,人物卡!BB19:BC23,1,FALSE),0))),"★",INDEX(本职技能!$A$2:$IE$75,MATCH(人物卡!AB17,本职技能!$A$2:$A$74,0),MATCH(附表!B58,本职技能!$A$1:$IE$1,0))) -> ★ | AB17: 法律 | AF17: 5 | AN17: =SUM(AF17:AL17) -> 5 | AP17: =INT(AN17/2) -> 2 | AR17: =INT(AN17/5) -> 1
B18: ☐ | D18: =IF(ISTEXT(IFERROR(VLOOKUP(人物卡!F18,BJ19:BJ23,1,FALSE),IFERROR(VLOOKUP(人物卡!F18,BB19:BB23,1,FALSE),0))),"★",INDEX(本职技能!$A$2:$IE$75,MATCH(人物卡!F18,本职技能!$A$2:$A$74,0),MATCH(附表!B58,本职技能!$A$1:$IE$1,0))) -> 0 | F18: 人类学 | J18: 1 | R18: =SUM(J18:P18) -> 1 | T18: =INT(R18/2) -> 0 | V18: =INT(R18/5) -> 0 | X18: ☐ | Z18: =IF(ISTEXT(IFERROR(VLOOKUP(人物卡!AB18,人物卡!BJ19:BR23,1,FALSE),IFERROR(VLOOKUP(人物卡!AB18,人物卡!BB19:BC23,1,FALSE),0))),"★",INDEX(本职技能!$A$2:$IE$75,MATCH(人物卡!AB18,本职技能!$A$2:$A$74,0),MATCH(附表!B58,本职技能!$A$1:$IE$1,0))) -> ★ | AB18: 图书馆使用 | AF18: 20 | AN18: =SUM(AF18:AL18) -> 20 | AP18: =INT(AN18/2) -> 10 | AR18: =INT(AN18/5) -> 4 | AU18: 你现在有这么多 | BB18: 那么你分配到了哪里?
B19: ☐ | D19: =IF(ISTEXT(IFERROR(VLOOKUP(人物卡!F19,人物卡!BJ19:BR23,1,FALSE),IFERROR(VLOOKUP(人物卡!F19,人物卡!BB19:BC23,1,FALSE),0))),"★",INDEX(本职技能!$A$2:$IE$75,MATCH(人物卡!F19,本职技能!$A$2:$A$74,0),MATCH(附表!B58,本职技能!$A$1:$IE$1,0))) -> 0 | F19: 估价 | J19: 5 | R19: =SUM(J19:P19) -> 5 | T19: =INT(R19/2) -> 2 | V19: =INT(R19/5) -> 1 | X19: ☐ | Z19: =IF(ISTEXT(IFERROR(VLOOKUP(人物卡!AB19,BJ19:BJ23,1,FALSE),IFERROR(VLOOKUP(人物卡!AB19,BB19:BB23,1,FALSE),0))),"★",INDEX(本职技能!$A$2:$IE$75,MATCH(人物卡!AB19,本职技能!$A$2:$A$74,0),MATCH(附表!B58,本职技能!$A$1:$IE$1,0))) -> ★ | AB19: 聆听 | AF19: 20 | AJ19: 45 | AL19: 5 | AN19: =SUM(AF19:AL19) -> 70 | AP19: =INT(AN19/2) -> 35 | AR19: =INT(AN19/5) -> 14 | AU19: 任意特长
B20: ☐ | D20: =IF(ISTEXT(IFERROR(VLOOKUP(人物卡!F20,人物卡!BJ19:BR23,1,FALSE),IFERROR(VLOOKUP(人物卡!F20,人物卡!BB19:BC23,1,FALSE),0))),"★",INDEX(本职技能!$A$2:$IE$75,MATCH(人物卡!F20,本职技能!$A$2:$A$74,0),MATCH(附表!B58,本职技能!$A$1:$IE$1,0))) -> 0 | F20: 考古学 | J20: 1 | R20: =SUM(J20:P20) -> 1 | T20: =INT(R20/2) -> 0 | V20: =INT(R20/5) -> 0 | X20: ☐ | Z20: =IF(ISTEXT(IFERROR(VLOOKUP(人物卡!AB20,人物卡!BJ19:BR23,1,FALSE),IFERROR(VLOOKUP(人物卡!AB20,人物卡!BB19:BC23,1,FALSE),0))),"★",INDEX(本职技能!$A$2:$IE$75,MATCH(人物卡!AB20,本职技能!$A$2:$A$74,0),MATCH(附表!B58,本职技能!$A$1:$IE$1,0))) -> ★ | AB20: 锁匠 | AF20: 1 | AJ20: 70 | AN20: =SUM(AF20:AL20) -> 71 | AP20: =INT(AN20/2) -> 35 | AR20: =INT(AN20/5) -> 14 | AU20: =附表!AD25 -> 1
B21: ☐ | D21: =IF(ISTEXT(IFERROR(VLOOKUP(人物卡!F21,人物卡!BJ19:BR23,1,FALSE),IFERROR(VLOOKUP(人物卡!F21,人物卡!BB19:BC23,1,FALSE),0))),"★",INDEX(本职技能!$A$2:$IE$75,MATCH(人物卡!F21,本职技能!$A$2:$A$74,0),MATCH(附表!B58,本职技能!$A$1:$IE$1,0))) -> 摄影★ | F21: 技艺① | J21: =IF(ISBLANK(AU27),5,IF(H21=AU27,BA27,5)) -> 5 | R21: =J21+L21+N21+P21 -> 5 | T21: =INT(R21/2) -> 2 | V21: =INT(R21/5) -> 1 | X21: ☐ | Z21: =IF(ISTEXT(IFERROR(VLOOKUP(人物卡!AB21,人物卡!BJ19:BR23,1,FALSE),IFERROR(VLOOKUP(人物卡!AB21,人物卡!BB19:BC23,1,FALSE),0))),"★",INDEX(本职技能!$A$2:$IE$75,MATCH(人物卡!AB21,本职技能!$A$2:$A$74,0),MATCH(附表!B58,本职技能!$A$1:$IE$1,0))) -> 0 | AB21: 机械维修 | AF21: 10 | AN21: =SUM(AF21:AL21) -> 10 | AP21: =INT(AN21/2) -> 5 | AR21: =INT(AN21/5) -> 2
B22: ☐ | D22: =IF(ISTEXT(IFERROR(VLOOKUP(人物卡!F22,人物卡!BJ19:BR23,1,FALSE),IFERROR(VLOOKUP(人物卡!F22,人物卡!BB19:BC23,1,FALSE),0))),"★",INDEX(本职技能!$A$2:$IE$75,MATCH(人物卡!F22,本职技能!$A$2:$A$74,0),MATCH(附表!B58,本职技能!$A$1:$IE$1,0))) -> 0 | F22: 技艺② | J22: =IF(ISBLANK(AU27),5,IF(H22=AU27,BA27,5)) -> 5 | R22: =P22+N22+L22+J22 -> 5 | T22: =INT(R22/2) -> 2 | V22: =INT(R22/5) -> 1 | X22: ☐ | Z22: =IF(ISTEXT(IFERROR(VLOOKUP(人物卡!AB22,人物卡!BJ19:BR23,1,FALSE),IFERROR(VLOOKUP(人物卡!AB22,人物卡!BB19:BC23,1,FALSE),0))),"★",INDEX(本职技能!$A$2:$IE$75,MATCH(人物卡!AB22,本职技能!$A$2:$A$74,0),MATCH(附表!B58,本职技能!$A$1:$IE$1,0))) -> 0 | AB22: 医学 | AF22: 1 | AN22: =SUM(AF22:AL22) -> 1 | AP22: =INT(AN22/2) -> 0 | AR22: =INT(AN22/5) -> 0
B23: ☐ | D23: =IF(ISTEXT(IFERROR(VLOOKUP(人物卡!F23,人物卡!BJ19:BR23,1,FALSE),IFERROR(VLOOKUP(人物卡!F23,人物卡!BB19:BC23,1,FALSE),0))),"★",INDEX(本职技能!$A$2:$IE$75,MATCH(人物卡!F23,本职技能!$A$2:$A$74,0),MATCH(附表!B58,本职技能!$A$1:$IE$1,0))) -> 0 | F23: 技艺③ | J23: =IF(ISBLANK(AU27),5,IF(H23=AU27,BA27,5)) -> 5 | R23: =P23+N23+L23+J23 -> 5 | T23: =INT(R23/2) -> 2 | V23: =INT(R23/5) -> 1 | X23: ☐ | Z23: =IF(ISTEXT(IFERROR(VLOOKUP(人物卡!AB23,人物卡!BJ19:BR23,1,FALSE),IFERROR(VLOOKUP(人物卡!AB23,人物卡!BB19:BC23,1,FALSE),0))),"★",INDEX(本职技能!$A$2:$IE$75,MATCH(人物卡!AB23,本职技能!$A$2:$A$74,0),MATCH(附表!B58,本职技能!$A$1:$IE$1,0))) -> 0 | AB23: 博物学 | AF23: 10 | AN23: =SUM(AF23:AL23) -> 10 | AP23: =INT(AN23/2) -> 5 | AR23: =INT(AN23/5) -> 2 | AU23: 提示当前职业
B24: ☐ | D24: =IF(ISTEXT(IFERROR(VLOOKUP(人物卡!F24,人物卡!BJ19:BR23,1,FALSE),IFERROR(VLOOKUP(人物卡!F24,人物卡!BB19:BC23,1,FALSE),0))),"★",INDEX(本职技能!$A$2:$IE$75,MATCH(人物卡!F24,本职技能!$A$2:$A$74,0),MATCH(附表!B58,本职技能!$A$1:$IE$1,0))) -> ☯ | F24: 取悦 | J24: 15 | N24: 15 | P24: 40 | R24: =SUM(J24:P24) -> 70 | T24: =INT(R24/2) -> 35 | V24: =INT(R24/5) -> 14 | X24: ☐ | Z24: =IF(ISTEXT(IFERROR(VLOOKUP(人物卡!AB24,人物卡!BJ19:BR23,1,FALSE),IFERROR(VLOOKUP(人物卡!AB24,人物卡!BB19:BC23,1,FALSE),0))),"★",INDEX(本职技能!$A$2:$IE$75,MATCH(人物卡!AB24,本职技能!$A$2:$A$74,0),MATCH(附表!B58,本职技能!$A$1:$IE$1,0))) -> 0 | AB24: 导航 | AF24: 10 | AN24: =SUM(AF24:AL24) -> 10 | AP24: =INT(AN24/2) -> 5 | AR24: =INT(AN24/5) -> 2 | AU24: 请将你选择的任意特长写在上方栏内，这样既方便你写卡又方便KP审卡
B25: ☐ | D25: =IF(ISTEXT(IFERROR(VLOOKUP(人物卡!F25,人物卡!BJ19:BR23,1,FALSE),IFERROR(VLOOKUP(人物卡!F25,人物卡!BB19:BC23,1,FALSE),0))),"★",INDEX(本职技能!$A$2:$IE$75,MATCH(人物卡!F25,本职技能!$A$2:$A$74,0),MATCH(附表!B58,本职技能!$A$1:$IE$1,0))) -> 0 | F25: 攀爬 | J25: 20 | R25: =SUM(J25:P25) -> 20 | T25: =INT(R25/2) -> 10 | V25: =INT(R25/5) -> 4 | X25: ☐ | Z25: =IF(ISTEXT(IFERROR(VLOOKUP(人物卡!AB25,人物卡!BJ19:BR23,1,FALSE),IFERROR(VLOOKUP(人物卡!AB25,人物卡!BB19:BC23,1,FALSE),0))),"★",INDEX(本职技能!$A$2:$IE$75,MATCH(人物卡!AB25,本职技能!$A$2:$A$74,0),MATCH(附表!B58,本职技能!$A$1:$IE$1,0))) -> 0 | AB25: 神秘学 | AF25: 5 | AN25: =SUM(AF25:AL25) -> 5 | AP25: =INT(AN25/2) -> 2 | AR25: =INT(AN25/5) -> 1 | AU25: 自定义子技能 | BC25: 自定义经历包 | BK25: 自定义状态
B26: ☐ | D26: =IF(ISTEXT(IFERROR(VLOOKUP(人物卡!F26,人物卡!BJ19:BR23,1,FALSE),IFERROR(VLOOKUP(人物卡!F26,人物卡!BB19:BC23,1,FALSE),0))),"★",INDEX(本职技能!$A$2:$IE$75,MATCH(人物卡!F26,本职技能!$A$2:$A$74,0),MATCH(附表!B58,本职技能!$A$1:$IE$1,0))) -> 0 | F26: 计算机使用 Ω | J26: 5 | R26: =SUM(J26:P26) -> 5 | T26: =INT(R26/2) -> 2 | V26: =INT(R26/5) -> 1 | X26: ☐ | Z26: =IF(ISTEXT(IFERROR(VLOOKUP(人物卡!AB26,人物卡!BJ19:BR23,1,FALSE),IFERROR(VLOOKUP(人物卡!AB26,人物卡!BB19:BC23,1,FALSE),0))),"★",INDEX(本职技能!$A$2:$IE$75,MATCH(人物卡!AB26,本职技能!$A$2:$A$74,0),MATCH(附表!B58,本职技能!$A$1:$IE$1,0))) -> 0 | AB26: 操作重型机械 | AF26: 1 | AN26: =SUM(AF26:AL26) -> 1 | AP26: =INT(AN26/2) -> 0 | AR26: =INT(AN26/5) -> 0 | AU26: 技能名称 | BA26: 基础值 | BC26: 经历包名称 | BK26: 状态名称(例:生病、精神分裂)
B27: —— | D27: ★ | F27: 信用评级 | J27: 0 | N27: 20 | R27: =SUM(J27:P27) -> 20 | T27: =INT(R27/2) -> 10 | V27: =INT(R27/5) -> 4 | X27: ☐ | Z27: =IF(ISTEXT(IFERROR(VLOOKUP(人物卡!AB27,人物卡!BJ19:BR23,1,FALSE),IFERROR(VLOOKUP(人物卡!AB27,人物卡!BB19:BC23,1,FALSE),0))),"★",INDEX(本职技能!$A$2:$IE$75,MATCH(人物卡!AB27,本职技能!$A$2:$A$74,0),MATCH(附表!B58,本职技能!$A$1:$IE$1,0))) -> ☯ | AB27: 说服 | AF27: 10 | AN27: =SUM(AF27:AL27) -> 10 | AP27: =INT(AN27/2) -> 5 | AR27: =INT(AN27/5) -> 2
B28: —— | D28: =IF(ISTEXT(IFERROR(VLOOKUP(F28,人物卡!BJ19:BR23,1,FALSE),IFERROR(VLOOKUP(F28,人物卡!BB19:BC23,1,FALSE),0))),"★",INDEX(本职技能!$A$2:$IE$75,MATCH(F28,本职技能!$A$2:$A$74,0),MATCH(附表!B58,本职技能!$A$1:$IE$1,0))) -> 0 | F28: 克苏鲁神话 | J28: 0 | N28: —— | P28: —— | R28: =SUM(J28:P28) -> 0 | T28: =INT(R28/2) -> 0 | V28: =INT(R28/5) -> 0 | X28: ☐ | Z28: =IF(ISTEXT(IFERROR(VLOOKUP(人物卡!AB28,人物卡!BJ19:BR23,1,FALSE),IFERROR(VLOOKUP(人物卡!AB28,人物卡!BB19:BC23,1,FALSE),0))),"★",INDEX(本职技能!$A$2:$IE$75,MATCH(人物卡!AB28,本职技能!$A$2:$A$74,0),MATCH(附表!B58,本职技能!$A$1:$IE$1,0))) -> 0 | AB28: 驾驶： | AF28: =IF(ISBLANK(AU27),1,IF(AD28=AU27,BA27,1)) -> 1 | AN28: =SUM(AF28:AL28) -> 1 | AP28: =INT(AN28/2) -> 0 | AR28: =INT(AN28/5) -> 0 | AU28: 用法/备注 | BC28: san值减少 | BG28: 技能增长 | BK28: 身体状态 | BO28: 精神状态
B29: ☐ | D29: =IF(ISTEXT(IFERROR(VLOOKUP(人物卡!F29,人物卡!BJ19:BR23,1,FALSE),IFERROR(VLOOKUP(人物卡!F29,人物卡!BB19:BC23,1,FALSE),0))),"★",INDEX(本职技能!$A$2:$IE$75,MATCH(人物卡!F29,本职技能!$A$2:$A$74,0),MATCH(附表!B58,本职技能!$A$1:$IE$1,0))) -> 0 | F29: 乔装 | J29: 5 | R29: =SUM(J29:P29) -> 5 | T29: =INT(R29/2) -> 2 | V29: =INT(R29/5) -> 1 | X29: ☐ | Z29: =IF(ISTEXT(IFERROR(VLOOKUP(人物卡!AB29,人物卡!BJ19:BR23,1,FALSE),IFERROR(VLOOKUP(人物卡!AB29,人物卡!BB19:BC23,1,FALSE),0))),"★",INDEX(本职技能!$A$2:$IE$75,MATCH(人物卡!AB29,本职技能!$A$2:$A$74,0),MATCH(附表!B58,本职技能!$A$1:$IE$1,0))) -> 0 | AB29: 精神分析 | AF29: 1 | AN29: =SUM(AF29:AL29) -> 1 | AP29: =INT(AN29/2) -> 0 | AR29: =INT(AN29/5) -> 0
B30: ☐ | D30: =IF(ISTEXT(IFERROR(VLOOKUP(人物卡!F30,人物卡!BJ19:BR23,1,FALSE),IFERROR(VLOOKUP(人物卡!F30,人物卡!BB19:BC23,1,FALSE),0))),"★",INDEX(本职技能!$A$2:$IE$75,MATCH(人物卡!F30,本职技能!$A$2:$A$74,0),MATCH(附表!B58,本职技能!$A$1:$IE$1,0))) -> 0 | F30: 闪避 | J30: =INT(DEX/2) -> 35 | P30: 25 | R30: =SUM(J30:P30) -> 60 | T30: =INT(R30/2) -> 30 | V30: =INT(R30/5) -> 12 | X30: ☐ | Z30: =IF(ISTEXT(IFERROR(VLOOKUP(人物卡!AB30,人物卡!BJ19:BR23,1,FALSE),IFERROR(VLOOKUP(人物卡!AB30,人物卡!BB19:BC23,1,FALSE),0))),"★",INDEX(本职技能!$A$2:$IE$75,MATCH(人物卡!AB30,本职技能!$A$2:$A$74,0),MATCH(附表!B58,本职技能!$A$1:$IE$1,0))) -> 0 | AB30: 心理学 | AF30: 10 | AL30: 50 | AN30: =SUM(AF30:AL30) -> 60 | AP30: =INT(AN30/2) -> 30 | AR30: =INT(AN30/5) -> 12 | BC30: 可选技能
B31: ☐ | D31: =IF(ISTEXT(IFERROR(VLOOKUP(人物卡!F31,人物卡!BJ19:BR23,1,FALSE),IFERROR(VLOOKUP(人物卡!F31,人物卡!BB19:BC23,1,FALSE),0))),"★",INDEX(本职技能!$A$2:$IE$75,MATCH(人物卡!F31,本职技能!$A$2:$A$74,0),MATCH(附表!B58,本职技能!$A$1:$IE$1,0))) -> 0 | F31: 汽车驾驶 | J31: 20 | R31: =SUM(J31:P31) -> 20 | T31: =INT(R31/2) -> 10 | V31: =INT(R31/5) -> 4 | X31: ☐ | Z31: =IF(ISTEXT(IFERROR(VLOOKUP(人物卡!AB31,人物卡!BJ19:BR23,1,FALSE),IFERROR(VLOOKUP(人物卡!AB31,人物卡!BB19:BC23,1,FALSE),0))),"★",INDEX(本职技能!$A$2:$IE$75,MATCH(人物卡!AB31,本职技能!$A$2:$A$74,0),MATCH(附表!B58,本职技能!$A$1:$IE$1,0))) -> 0 | AB31: 骑术 | AF31: 5 | AN31: =SUM(AF31:AL31) -> 5 | AP31: =INT(AN31/2) -> 2 | AR31: =INT(AN31/5) -> 1
B32: ☐ | D32: =IF(ISTEXT(IFERROR(VLOOKUP(人物卡!F32,人物卡!BJ19:BR23,1,FALSE),IFERROR(VLOOKUP(人物卡!F32,人物卡!BB19:BC23,1,FALSE),0))),"★",INDEX(本职技能!$A$2:$IE$75,MATCH(人物卡!F32,本职技能!$A$2:$A$74,0),MATCH(附表!B58,本职技能!$A$1:$IE$1,0))) -> 0 | F32: 电气维修 | J32: 10 | R32: =SUM(J32:P32) -> 10 | T32: =INT(R32/2) -> 5 | V32: =INT(R32/5) -> 2 | X32: ☐ | Z32: =IF(ISTEXT(IFERROR(VLOOKUP(人物卡!AB32,人物卡!BJ19:BR23,1,FALSE),IFERROR(VLOOKUP(人物卡!AB32,人物卡!BB19:BC23,1,FALSE),0))),"★",INDEX(本职技能!$A$2:$IE$75,MATCH(人物卡!AB32,本职技能!$A$2:$A$74,0),MATCH(附表!B58,本职技能!$A$1:$IE$1,0))) -> 0 | AB32: 科学① | AF32: =IF(ISBLANK(AU27),IF(AD32="数学",10,1),IF(AD32=AU27,BA27,1)) -> 1 | AN32: =AF32+AH32+AL32+AJ32 -> 1 | AP32: =INT(AN32/2) -> 0 | AR32: =INT(AN32/5) -> 0
B33: ☐ | D33: =IF(ISTEXT(IFERROR(VLOOKUP(人物卡!F33,人物卡!BJ19:BR23,1,FALSE),IFERROR(VLOOKUP(人物卡!F33,人物卡!BB19:BC23,1,FALSE),0))),"★",INDEX(本职技能!$A$2:$IE$75,MATCH(人物卡!F33,本职技能!$A$2:$A$74,0),MATCH(附表!B58,本职技能!$A$1:$IE$1,0))) -> 0 | F33: 电子学 Ω | J33: 1 | R33: =SUM(J33:P33) -> 1 | T33: =INT(R33/2) -> 0 | V33: =INT(R33/5) -> 0 | X33: ☐ | Z33: =IF(ISTEXT(IFERROR(VLOOKUP(人物卡!AB33,人物卡!BJ19:BR23,1,FALSE),IFERROR(VLOOKUP(人物卡!AB33,人物卡!BB19:BC23,1,FALSE),0))),"★",INDEX(本职技能!$A$2:$IE$75,MATCH(人物卡!AB33,本职技能!$A$2:$A$74,0),MATCH(附表!B58,本职技能!$A$1:$IE$1,0))) -> 0 | AB33: 科学② | AF33: =IF(ISBLANK(AU27),IF(AD33="数学",10,1),IF(AD33=AU27,BA27,1)) -> 1 | AN33: =AL33+AJ33+AF33+AH33 -> 1 | AP33: =INT(AN33/2) -> 0 | AR33: =INT(AN33/5) -> 0
B34: ☐ | D34: =IF(ISTEXT(IFERROR(VLOOKUP(人物卡!F34,人物卡!BJ19:BR23,1,FALSE),IFERROR(VLOOKUP(人物卡!F34,人物卡!BB19:BC23,1,FALSE),0))),"★",INDEX(本职技能!$A$2:$IE$75,MATCH(人物卡!F34,本职技能!$A$2:$A$74,0),MATCH(附表!B58,本职技能!$A$1:$IE$1,0))) -> ☯ | F34: 话术 | J34: 5 | N34: 65 | R34: =SUM(J34:P34) -> 70 | T34: =INT(R34/2) -> 35 | V34: =INT(R34/5) -> 14 | X34: ☐ | Z34: =IF(ISTEXT(IFERROR(VLOOKUP(人物卡!AB34,人物卡!BJ19:BR23,1,FALSE),IFERROR(VLOOKUP(人物卡!AB34,人物卡!BB19:BC23,1,FALSE),0))),"★",INDEX(本职技能!$A$2:$IE$75,MATCH(人物卡!AB34,本职技能!$A$2:$A$74,0),MATCH(附表!B58,本职技能!$A$1:$IE$1,0))) -> 0 | AB34: 科学③ | AF34: =IF(ISBLANK(AU27),IF(AD34="数学",10,1),IF(AD34=AU27,BA27,1)) -> 1 | AN34: =AF34+AH34+AJ34+AL34 -> 1 | AP34: =INT(AN34/2) -> 0 | AR34: =INT(AN34/5) -> 0 | BC34: 备注
B35: ☐ | D35: =IF(ISTEXT(IFERROR(VLOOKUP(人物卡!F35,人物卡!BJ19:BR23,1,FALSE),IFERROR(VLOOKUP(人物卡!F35,人物卡!BB19:BC23,1,FALSE),0))),"★",INDEX(本职技能!$A$2:$IE$75,MATCH(人物卡!F35,本职技能!$A$2:$A$74,0),MATCH(附表!B58,本职技能!$A$1:$IE$1,0))) -> 0 | F35: 格斗： | H35: 斗殴 | J35: 25 | R35: =SUM(J35:P35) -> 25 | T35: =INT(R35/2) -> 12 | V35: =INT(R35/5) -> 5 | X35: ☐ | Z35: =IF(ISTEXT(IFERROR(VLOOKUP(人物卡!AB35,人物卡!BJ19:BR23,1,FALSE),IFERROR(VLOOKUP(人物卡!AB35,人物卡!BB19:BC23,1,FALSE),0))),"★",INDEX(本职技能!$A$2:$IE$75,MATCH(人物卡!AB35,本职技能!$A$2:$A$74,0),MATCH(附表!B58,本职技能!$A$1:$IE$1,0))) -> 0 | AB35: 妙手 | AF35: 10 | AN35: =SUM(AF35:AL35) -> 10 | AP35: =INT(AN35/2) -> 5 | AR35: =INT(AN35/5) -> 2
B36: ☐ | D36: =IF(ISTEXT(IFERROR(VLOOKUP(人物卡!F36,人物卡!BJ19:BR23,1,FALSE),IFERROR(VLOOKUP(人物卡!F36,人物卡!BB19:BC23,1,FALSE),0))),"★",INDEX(本职技能!$A$2:$IE$75,MATCH(人物卡!F36,本职技能!$A$2:$A$74,0),MATCH(附表!B58,本职技能!$A$1:$IE$1,0))) -> 0 | F36: 格斗① | J36: =附表!C11 -> 0 | R36: =J36+L36+N36+P36 -> 0 | T36: =INT(R36/2) -> 0 | V36: =INT(R36/5) -> 0 | X36: ☐ | Z36: =IF(ISTEXT(IFERROR(VLOOKUP(人物卡!AB36,人物卡!BJ19:BR23,1,FALSE),IFERROR(VLOOKUP(人物卡!AB36,人物卡!BB19:BC23,1,FALSE),0))),"★",INDEX(本职技能!$A$2:$IE$75,MATCH(人物卡!AB36,本职技能!$A$2:$A$74,0),MATCH(附表!B58,本职技能!$A$1:$IE$1,0))) -> ★ | AB36: 侦查 | AF36: 25 | AJ36: 55 | AN36: =SUM(AF36:AL36) -> 80 | AP36: =INT(AN36/2) -> 40 | AR36: =INT(AN36/5) -> 16 | AU36: 自定义年龄补正 | BK36: 自定义货币
B37: ☐ | D37: =IF(ISTEXT(IFERROR(VLOOKUP(F37,人物卡!BJ19:BR23,1,FALSE),IFERROR(VLOOKUP(F37,人物卡!BB19:BC23,1,FALSE),0))),"★",INDEX(本职技能!$A$2:$IE$75,MATCH(F37,本职技能!$A$2:$A$74,0),MATCH(附表!B58,本职技能!$A$1:$IE$1,0))) -> 0 | F37: 格斗② | J37: =附表!C12 -> 0 | R37: =J37+L37+P37+N37 -> 0 | T37: =INT(R37/2) -> 0 | V37: =INT(R37/5) -> 0 | X37: ☐ | Z37: =IF(ISTEXT(IFERROR(VLOOKUP(人物卡!AB37,人物卡!BJ19:BR23,1,FALSE),IFERROR(VLOOKUP(人物卡!AB37,人物卡!BB19:BC23,1,FALSE),0))),"★",INDEX(本职技能!$A$2:$IE$75,MATCH(人物卡!AB37,本职技能!$A$2:$A$74,0),MATCH(附表!B58,本职技能!$A$1:$IE$1,0))) -> 0 | AB37: 潜行 | AF37: 20 | AL37: 40 | AN37: =SUM(AF37:AL37) -> 60 | AP37: =INT(AN37/2) -> 30 | AR37: =INT(AN37/5) -> 12 | AU37: 年龄补正 | BK37: 货币名称 | BO37: 与美元的汇率
B38: ☐ | D38: =IF(ISTEXT(IFERROR(VLOOKUP(F38,人物卡!BJ19:BR23,1,FALSE),IFERROR(VLOOKUP(F38,人物卡!BB19:BC23,1,FALSE),0))),"★",INDEX(本职技能!$A$2:$IE$75,MATCH(F38,本职技能!$A$2:$A$74,0),MATCH(附表!B58,本职技能!$A$1:$IE$1,0))) -> 0 | F38: 格斗③ | J38: =附表!C13 -> 0 | R38: =P38+N38+L38+J38 -> 0 | T38: =INT(R38/2) -> 0 | V38: =INT(R38/5) -> 0 | X38: ☐ | Z38: =IF(ISTEXT(IFERROR(VLOOKUP(人物卡!AB38,人物卡!BJ19:BR23,1,FALSE),IFERROR(VLOOKUP(人物卡!AB38,人物卡!BB19:BC23,1,FALSE),0))),"★",INDEX(本职技能!$A$2:$IE$75,MATCH(人物卡!AB38,本职技能!$A$2:$A$74,0),MATCH(附表!B58,本职技能!$A$1:$IE$1,0))) -> 0 | AB38: 生存： | AF38: 10 | AN38: =SUM(AF38:AL38) -> 10 | AP38: =INT(AN38/2) -> 5 | AR38: =INT(AN38/5) -> 2
B39: ☐ | D39: =IF(ISTEXT(IFERROR(VLOOKUP(人物卡!F39,人物卡!BJ19:BR23,1,FALSE),IFERROR(VLOOKUP(人物卡!F39,人物卡!BB19:BC23,1,FALSE),0))),"★",INDEX(本职技能!$A$2:$IE$75,MATCH(人物卡!F39,本职技能!$A$2:$A$74,0),MATCH(附表!B58,本职技能!$A$1:$IE$1,0))) -> 0 | F39: 射击： | H39: 手枪 | J39: 20 | R39: =SUM(J39:P39) -> 20 | T39: =INT(R39/2) -> 10 | V39: =INT(R39/5) -> 4 | X39: ☐ | Z39: =IF(ISTEXT(IFERROR(VLOOKUP(人物卡!AB39,人物卡!BJ19:BR23,1,FALSE),IFERROR(VLOOKUP(人物卡!AB39,人物卡!BB19:BC23,1,FALSE),0))),"★",INDEX(本职技能!$A$2:$IE$75,MATCH(人物卡!AB39,本职技能!$A$2:$A$74,0),MATCH(附表!B58,本职技能!$A$1:$IE$1,0))) -> 0 | AB39: 游泳 | AF39: 20 | AN39: =SUM(AF39:AL39) -> 20 | AP39: =INT(AN39/2) -> 10 | AR39: =INT(AN39/5) -> 4 | AU39: 推 荐 关 系 人 | AV39: =IF(M5=0," ",""&LOOKUP(M5,职业列表!A2:A232,职业列表!L2:L232))
B40: ☐ | D40: =IF(ISTEXT(IFERROR(VLOOKUP(人物卡!F40,人物卡!BJ19:BR23,1,FALSE),IFERROR(VLOOKUP(人物卡!F40,人物卡!BB19:BC23,1,FALSE),0))),"★",INDEX(本职技能!$A$2:$IE$75,MATCH(人物卡!F40,本职技能!$A$2:$A$74,0),MATCH(附表!B58,本职技能!$A$1:$IE$1,0))) -> 0 | F40: 射击① | J40: =附表!E11 -> 0 | R40: =P40+N40+L40+J40 -> 0 | T40: =INT(R40/2) -> 0 | V40: =INT(R40/5) -> 0 | X40: ☐ | Z40: =IF(ISTEXT(IFERROR(VLOOKUP(人物卡!AB40,人物卡!BJ19:BR23,1,FALSE),IFERROR(VLOOKUP(人物卡!AB40,人物卡!BB19:BC23,1,FALSE),0))),"★",INDEX(本职技能!$A$2:$IE$75,MATCH(人物卡!AB40,本职技能!$A$2:$A$74,0),MATCH(附表!B58,本职技能!$A$1:$IE$1,0))) -> 0 | AB40: 投掷 | AF40: 20 | AN40: =SUM(AF40:AL40) -> 20 | AP40: =INT(AN40/2) -> 10 | AR40: =INT(AN40/5) -> 4
B41: ☐ | D41: =IF(ISTEXT(IFERROR(VLOOKUP(F41,人物卡!BJ19:BR23,1,FALSE),IFERROR(VLOOKUP(F41,人物卡!BB19:BC23,1,FALSE),0))),"★",INDEX(本职技能!$A$2:$IE$75,MATCH(F41,本职技能!$A$2:$A$74,0),MATCH(附表!B58,本职技能!$A$1:$IE$1,0))) -> 0 | F41: 射击② | J41: =附表!E12 -> 0 | R41: =P41+N41+L41+J41 -> 0 | T41: =INT(R41/2) -> 0 | V41: =INT(R41/5) -> 0 | X41: ☐ | Z41: =IF(ISTEXT(IFERROR(VLOOKUP(人物卡!AB41,人物卡!BJ19:BR23,1,FALSE),IFERROR(VLOOKUP(人物卡!AB41,人物卡!BB19:BC23,1,FALSE),0))),"★",INDEX(本职技能!$A$2:$IE$75,MATCH(人物卡!AB41,本职技能!$A$2:$A$74,0),MATCH(附表!B58,本职技能!$A$1:$IE$1,0))) -> 0 | AB41: 追踪 | AF41: 10 | AN41: =SUM(AF41:AL41) -> 10 | AP41: =INT(AN41/2) -> 5 | AR41: =INT(AN41/5) -> 2
B42: ☐ | D42: =IF(ISTEXT(IFERROR(VLOOKUP(F42,人物卡!BJ19:BR23,1,FALSE),IFERROR(VLOOKUP(F42,人物卡!BB19:BC23,1,FALSE),0))),"★",INDEX(本职技能!$A$2:$IE$75,MATCH(F42,本职技能!$A$2:$A$74,0),MATCH(附表!B58,本职技能!$A$1:$IE$1,0))) -> 0 | F42: 射击③ | J42: =附表!E13 -> 0 | R42: =P42+N42+L42+J42 -> 0 | T42: =INT(R42/2) -> 0 | V42: =INT(R42/5) -> 0 | X42: ☐ | Z42: =IF(ISTEXT(IFERROR(VLOOKUP(人物卡!AB42,人物卡!BJ19:BR23,1,FALSE),IFERROR(VLOOKUP(人物卡!AB42,人物卡!BB19:BC23,1,FALSE),0))),"★",INDEX(本职技能!$A$2:$IE$75,MATCH(人物卡!AB42,本职技能!$A$2:$A$74,0),MATCH(附表!B58,本职技能!$A$1:$IE$1,0))) -> 0 | AB42: 驯兽 | AF42: 5 | AN42: =SUM(AF42:AL42) -> 5 | AP42: =INT(AN42/2) -> 2 | AR42: =INT(AN42/5) -> 1
B43: ☐ | D43: =IF(ISTEXT(IFERROR(VLOOKUP(人物卡!F43,人物卡!BJ19:BR23,1,FALSE),IFERROR(VLOOKUP(人物卡!F43,人物卡!BB19:BC23,1,FALSE),0))),"★",INDEX(本职技能!$A$2:$IE$75,MATCH(人物卡!F43,本职技能!$A$2:$A$74,0),MATCH(附表!B58,本职技能!$A$1:$IE$1,0))) -> 0 | F43: 急救 | J43: 30 | R43: =SUM(J43:P43) -> 30 | T43: =INT(R43/2) -> 15 | V43: =INT(R43/5) -> 6 | X43: ☐ | Z43: =IF(ISTEXT(IFERROR(VLOOKUP(人物卡!AB43,人物卡!BJ19:BR23,1,FALSE),IFERROR(VLOOKUP(人物卡!AB43,人物卡!BB19:BC23,1,FALSE),0))),"★",INDEX(本职技能!$A$2:$IE$75,MATCH(人物卡!AB43,本职技能!$A$2:$A$74,0),MATCH(附表!B58,本职技能!$A$1:$IE$1,0))) -> 0 | AB43: 潜水 | AF43: 1 | AN43: =SUM(AF43:AL43) -> 1 | AP43: =INT(AN43/2) -> 0 | AR43: =INT(AN43/5) -> 0
B44: ☐ | D44: =IF(ISTEXT(IFERROR(VLOOKUP(人物卡!F44,人物卡!BJ19:BR23,1,FALSE),IFERROR(VLOOKUP(人物卡!F44,人物卡!BB19:BC23,1,FALSE),0))),"★",INDEX(本职技能!$A$2:$IE$75,MATCH(人物卡!F44,本职技能!$A$2:$A$74,0),MATCH(附表!B58,本职技能!$A$1:$IE$1,0))) -> 0 | F44: 历史 | J44: 5 | R44: =SUM(J44:P44) -> 5 | T44: =INT(R44/2) -> 2 | V44: =INT(R44/5) -> 1 | X44: ☐ | Z44: =IF(ISTEXT(IFERROR(VLOOKUP(人物卡!AB44,人物卡!BJ19:BR23,1,FALSE),IFERROR(VLOOKUP(人物卡!AB44,人物卡!BB19:BC23,1,FALSE),0))),"★",INDEX(本职技能!$A$2:$IE$75,MATCH(人物卡!AB44,本职技能!$A$2:$A$74,0),MATCH(附表!B58,本职技能!$A$1:$IE$1,0))) -> 0 | AB44: 爆破 | AF44: 1 | AN44: =SUM(AF44:AL44) -> 1 | AP44: =INT(AN44/2) -> 0 | AR44: =INT(AN44/5) -> 0 | AU44: 职业介绍
B45: ☐ | D45: =IF(ISTEXT(IFERROR(VLOOKUP(人物卡!F45,人物卡!BJ19:BR23,1,FALSE),IFERROR(VLOOKUP(人物卡!F45,人物卡!BB19:BC23,1,FALSE),0))),"★",INDEX(本职技能!$A$2:$IE$75,MATCH(人物卡!F45,本职技能!$A$2:$A$74,0),MATCH(附表!B58,本职技能!$A$1:$IE$1,0))) -> ☯ | F45: 恐吓 | J45: 15 | R45: =SUM(J45:P45) -> 15 | T45: =INT(R45/2) -> 7 | V45: =INT(R45/5) -> 3 | X45: ☐ | Z45: =IF(ISTEXT(IFERROR(VLOOKUP(人物卡!AB45,人物卡!BJ19:BR23,1,FALSE),IFERROR(VLOOKUP(人物卡!AB45,人物卡!BB19:BC23,1,FALSE),0))),"★",INDEX(本职技能!$A$2:$IE$75,MATCH(人物卡!AB45,本职技能!$A$2:$A$74,0),MATCH(附表!B58,本职技能!$A$1:$IE$1,0))) -> 0 | AB45: 读唇 | AF45: 1 | AN45: =SUM(AF45:AL45) -> 1 | AP45: =INT(AN45/2) -> 0 | AR45: =INT(AN45/5) -> 0 | AU45: =IF(M5=0," ",""&LOOKUP(M5,职业列表!A2:A232,职业列表!N2:N232)) -> 《克苏鲁煤气灯》1980s职业，使用前请征得KP同意。
B46: ☐ | D46: =IF(ISTEXT(IFERROR(VLOOKUP(人物卡!F46,人物卡!BJ19:BR23,1,FALSE),IFERROR(VLOOKUP(人物卡!F46,人物卡!BB19:BC23,1,FALSE),0))),"★",INDEX(本职技能!$A$2:$IE$75,MATCH(人物卡!F46,本职技能!$A$2:$A$74,0),MATCH(附表!B58,本职技能!$A$1:$IE$1,0))) -> 0 | F46: 跳跃 | J46: 20 | R46: =SUM(J46:P46) -> 20 | T46: =INT(R46/2) -> 10 | V46: =INT(R46/5) -> 4 | X46: ☐ | Z46: =IF(ISTEXT(IFERROR(VLOOKUP(人物卡!AB46,人物卡!BJ19:BR23,1,FALSE),IFERROR(VLOOKUP(人物卡!AB46,人物卡!BB19:BC23,1,FALSE),0))),"★",INDEX(本职技能!$A$2:$IE$75,MATCH(人物卡!AB46,本职技能!$A$2:$A$74,0),MATCH(附表!B58,本职技能!$A$1:$IE$1,0))) -> 0 | AB46: 催眠 | AF46: 1 | AN46: =SUM(AF46:AL46) -> 1 | AP46: =INT(AN46/2) -> 0 | AR46: =INT(AN46/5) -> 0
B47: ☐ | D47: =IF(ISTEXT(IFERROR(VLOOKUP(人物卡!F47,人物卡!BJ19:BR23,1,FALSE),IFERROR(VLOOKUP(人物卡!F47,人物卡!BB19:BC23,1,FALSE),0))),"★",INDEX(本职技能!$A$2:$IE$75,MATCH(人物卡!F47,本职技能!$A$2:$A$74,0),MATCH(附表!B58,本职技能!$A$1:$IE$1,0))) -> 0 | F47: 外语① | J47: 1 | R47: =SUM(J47:P47) -> 1 | T47: =INT(R47/2) -> 0 | V47: =INT(R47/5) -> 0 | X47: ☐ | Z47: =IF(ISTEXT(IFERROR(VLOOKUP(人物卡!AB47,人物卡!BJ19:BR23,1,FALSE),IFERROR(VLOOKUP(人物卡!AB47,人物卡!BB19:BC23,1,FALSE),0))),"★",INDEX(本职技能!$A$2:$IE$75,MATCH(人物卡!AB47,本职技能!$A$2:$A$74,0),MATCH(附表!B58,本职技能!$A$1:$IE$1,0))) -> 0 | AB47: 炮术 | AF47: 1 | AN47: =SUM(AF47:AL47) -> 1 | AP47: =INT(AN47/2) -> 0 | AR47: =INT(AN47/5) -> 0
B48: ☐ | D48: =IF(ISTEXT(IFERROR(VLOOKUP(人物卡!F48,人物卡!BJ19:BR23,1,FALSE),IFERROR(VLOOKUP(人物卡!F48,人物卡!BB19:BC23,1,FALSE),0))),"★",INDEX(本职技能!$A$2:$IE$75,MATCH(人物卡!F48,本职技能!$A$2:$A$74,0),MATCH(附表!B58,本职技能!$A$1:$IE$1,0))) -> 0 | F48: 外语② | J48: 1 | R48: =SUM(J48:P48) -> 1 | T48: =INT(R48/2) -> 0 | V48: =INT(R48/5) -> 0 | X48: ☐ | Z48: =IF(ISTEXT(IFERROR(VLOOKUP(人物卡!AB48,人物卡!BJ19:BR23,1,FALSE),IFERROR(VLOOKUP(人物卡!AB48,人物卡!BB19:BC23,1,FALSE),0))),"★",INDEX(本职技能!$A$2:$IE$75,MATCH(人物卡!AB48,本职技能!$A$2:$A$74,0),MATCH(附表!B58,本职技能!$A$1:$IE$1,0))) -> 0 | AB48: 学问： | AF48: 1 | AN48: =SUM(AF48:AL48) -> 1 | AP48: =INT(AN48/2) -> 0 | AR48: =INT(AN48/5) -> 0
B49: ☐ | D49: =IF(ISTEXT(IFERROR(VLOOKUP(F49,人物卡!BJ19:BR23,1,FALSE),IFERROR(VLOOKUP(F49,人物卡!BB19:BC23,1,FALSE),0))),"★",INDEX(本职技能!$A$2:$IE$75,MATCH(F49,本职技能!$A$2:$A$74,0),MATCH(附表!B58,本职技能!$A$1:$IE$1,0))) -> 0 | F49: 外语③ | J49: 1 | R49: =SUM(J49:P49) -> 1 | T49: =INT(R49/2) -> 0 | V49: =INT(R49/5) -> 0 | X49: ☐ | Z49: =IF(ISTEXT(IFERROR(VLOOKUP(AB49,人物卡!BJ19:BR23,1,FALSE),IFERROR(VLOOKUP(AB49,人物卡!BB19:BC23,1,FALSE),0))),"★",INDEX(本职技能!$A$2:$IE$75,MATCH(AB49,本职技能!$A$2:$A$74,0),MATCH(附表!B58,本职技能!$A$1:$IE$1,0))) -> 0 | AB49: 自定义技能 | AN49: =SUM(AF49:AL49) -> 0 | AP49: =INT(AN49/2) -> 0 | AR49: =INT(AN49/5) -> 0
B50: ☐ | D50: =IF(ISTEXT(IFERROR(VLOOKUP(人物卡!F50,人物卡!BJ19:BR23,1,FALSE),IFERROR(VLOOKUP(人物卡!F50,人物卡!BB19:BC23,1,FALSE),0))),"★",INDEX(本职技能!$A$2:$IE$75,MATCH(人物卡!F50,本职技能!$A$2:$A$74,0),MATCH(附表!B58,本职技能!$A$1:$IE$1,0))) -> 0 | F50: 母语 | J50: =AG5 -> 55 | R50: =SUM(J50:P50) -> 55 | T50: =INT(R50/2) -> 27 | V50: =INT(R50/5) -> 11 | X50: ☐ | Z50: =IF(ISTEXT(IFERROR(VLOOKUP(AB50,人物卡!BJ19:BR23,1,FALSE),IFERROR(VLOOKUP(AB50,人物卡!BB19:BC23,1,FALSE),0))),"★",INDEX(本职技能!$A$2:$IE$75,MATCH(AB50,本职技能!$A$2:$A$74,0),MATCH(附表!B58,本职技能!$A$1:$IE$1,0))) -> 0 | AN50: =SUM(AF50:AL50) -> 0 | AP50: =INT(AN50/2) -> 0 | AR50: =INT(AN50/5) -> 0
B51: =IF(M5=0,"","职业信誉范围："&LOOKUP(M5,职业列表!A2:A232,职业列表!D2:D232)&"-"&LOOKUP(M5,职业列表!A2:A232,职业列表!E2:E232)) -> 职业信誉范围：9-40 | H51: =IF(M5=0,"","本职属性："&附表!J52&" ")&IF(M5=0,"",IF(AND(附表!J53-SUM(N17:O50,AJ17:AK50)=0,附表!L53-SUM(P17:Q50,AL17:AM50)=0,附表!L55+AL51-SUM(L17:M50,AH17:AI50)=0),"",("剩余职业点="&附表!J53-SUM(N17:O50,AJ17:AK50))&" 剩余兴趣点="&附表!L53-SUM(P17:Q50,AL17:AM50)&IF(E115=附表!B26,""," 剩余经历包点="&IF(ISNUMBER(附表!D34),附表!D34-SUM(L17:M50,AH17:AI50),附表!D34)))) -> 本职属性：[教育×2＋外貌或敏捷×2]
B52: 武器表 | AM52: 格斗
B53: 武器名称 | G53: 类型 | M53: 使用技能 | Q53: 成功率 | W53: 伤害 | AA53: 射程 | AC53: 穿刺 | AE53: 次数 | AG53: 装弹量 | AJ53: 故障值 | AM53: 伤害加值 Damage Bonus | AP53: =附表!P9 -> 0
B54: 无 | G54: 肉搏 | M54: 斗殴 | Q54: =R35 -> 25 | S54: =INT(Q54/2) -> 12 | U54: =INT(Q54/5) -> 5 | W54: 1D3+DB | AA54: —— | AC54: × | AE54: 1 | AG54: —— | AJ54: ——
B55: 钢笔刀 | G55: 小型刀具(弹簧折叠刀等) | M55: =IF($G55=0,"←请选择类型",VLOOKUP($G55,武器列表!$B$2:$I$105,2,FALSE)) -> 斗殴 | Q55: =附表!AV15 -> 25 | S55: =IF(Q55="","",INT(Q55/2)) -> 12 | U55: =IF(Q55="","",INT(Q55/5)) -> 5 | W55: =IF($G55=0,"",VLOOKUP($G55,武器列表!$B$2:$I$105,3,FALSE)) -> 1D4+DB | AA55: =IF($G55=0,"",VLOOKUP($G55,武器列表!$B$2:$I$105,4,FALSE)) -> 接触 | AC55: =IF($G55=0,"",VLOOKUP($G55,武器列表!$B$2:$I$105,5,FALSE)) -> √ | AE55: =IF($G55=0,"",VLOOKUP($G55,武器列表!$B$2:$I$105,6,FALSE)) -> 1 | AG55: =IF($G55=0,"",VLOOKUP($G55,武器列表!$B$2:$I$105,7,FALSE)) -> —— | AJ55: =IF($G55=0,"",VLOOKUP($G55,武器列表!$B$2:$I$105,8,FALSE)) -> ——
M56: =IF($G56=0,IF(M55="←请选择类型","","←请选择类型"),VLOOKUP($G56,武器列表!$B$2:$I$105,2,FALSE)) -> ←请选择类型 | Q56: =附表!AV16 | S56: =IF(Q56="","",INT(Q56/2)) | U56: =IF(Q56="","",INT(Q56/5)) | W56: =IF($G56=0,"",VLOOKUP($G56,武器列表!$B$2:$I$105,3,FALSE)) | AA56: =IF($G56=0,"",VLOOKUP($G56,武器列表!$B$2:$I$105,4,FALSE)) | AC56: =IF($G56=0,"",VLOOKUP($G56,武器列表!$B$2:$I$105,5,FALSE)) | AE56: =IF($G56=0,"",VLOOKUP($G56,武器列表!$B$2:$I$105,6,FALSE)) | AG56: =IF($G56=0,"",VLOOKUP($G56,武器列表!$B$2:$I$105,7,FALSE)) | AJ56: =IF($G56=0,"",VLOOKUP($G56,武器列表!$B$2:$I$105,8,FALSE)) | AM56: 体格 Build | AP56: =附表!P7 -> 0
M57: =IF($G57=0,IF(OR(M55="←请选择类型",M56="←请选择类型"),"","←请选择类型"),VLOOKUP($G57,武器列表!$B$2:$I$105,2,FALSE)) | Q57: =附表!AV17 | S57: =IF(Q57="","",INT(Q57/2)) | U57: =IF(Q57="","",INT(Q57/5)) | W57: =IF($G57=0,"",VLOOKUP($G57,武器列表!$B$2:$I$105,3,FALSE)) | AA57: =IF($G57=0,"",VLOOKUP($G57,武器列表!$B$2:$I$105,4,FALSE)) | AC57: =IF($G57=0,"",VLOOKUP($G57,武器列表!$B$2:$I$105,5,FALSE)) | AE57: =IF($G57=0,"",VLOOKUP($G57,武器列表!$B$2:$I$105,6,FALSE)) | AG57: =IF($G57=0,"",VLOOKUP($G57,武器列表!$B$2:$I$105,7,FALSE)) | AJ57: =IF($G57=0,"",VLOOKUP($G57,武器列表!$B$2:$I$105,8,FALSE))
AM58: 闪避 Dodge | AP58: =R30 -> 60 | AR58: =T30 -> 30
AR59: =V30 -> 12
B61: 资产 | W61: 背景故事
B62: 信用评级 | F62: 生活水平 | I62: 消费水平 | L62: 其他资产 | O62: 当前现金($) | S62: 单位 | W62: 个人描述 角色外貌 | AA62: 高瘦，黑发蓝眼，英俊 | AR62: 关键 连接
B63: =附表!Z223 -> 20%/10%/4% | F63: =附表!Z225 -> 标准 | I63: =附表!AE240 -> 10 | L63: =附表!AG240 -> 没有 | O63: =附表!AF240 -> 10 | S63: 美元 | AU63: =IF(附表!AE22="仅显示1890~2012","时代介绍仅显示1890~2012这段时间","时代介绍") -> 时代介绍
B64: =IF(R27<=0,"连贫穷都够不上的人才能够叫做身无分文。住所：大概只有睡大街。旅行：步行，扒车或逃票上火车轮船。",IF(R27<=9,"刚好买得起最廉价的屋顶，每天能够吃到一餐廉价食物住所：最最最廉价的出租屋或睡袋旅馆。旅行：最便宜的公众运输方式。反正只要赶便宜就对了，与之相伴的是不可靠。",IF(R27<=49,"舒适的生活水平，一日三餐，偶尔下馆子。住所：普通的家或公寓，并关租赁还是自购。外出住普通的旅馆。旅行：会使用普通的旅行方式，不会用最高级。在现代来看，大概会有一辆自己的小车。",IF(R27<=89,"小康级别已经可以享受奢侈品的舒适了。住所：真材实料的住地，也许会有一些仆人（管家，主妇，清洁工，园丁，等等）。乡下估计还有小别墅。会住昂贵的宾馆。旅行：头等舱。会买高档车或同等的交通工具。",IF(R27<=98,"富裕级别就是享受超级奢侈品的时候了。住所：豪华住所和有着大量仆人的庭院。乡下和别处有着别墅是定番。住总统套房。旅行：头等舱。现代社会估摸还会有很多豪车。",IF(R27>=99,"与富裕差不多，但钱已经只是一个代号了。你将是世纪界上最富有的人。","请正确分配您的技能点！")))))) -> 舒适的生活水平，一日三餐，偶尔下馆子。住所：普通的家或公寓，并关租赁还是自购。外出住普通的旅馆。旅行：会使用普通的旅行方式，不会用最高级。在现代来看，大概会有一辆自己的小车。 | L64: 请在这里详述你的资产 | W64: 思想与信念 | AA64: 他没有什么追求，但或许他能为像凯瑟琳一样的人做些什么 | AR64: ☐ | AU64: 年代 | AZ64: 国际重大历史进程 | BF64: 中国重大历史进程 | BL64: 年代
AU65: =IF(E8="公元","A.C."&G8,"B.C."&G8) -> A.C.2023 | AZ65: =附表!AF22 -> —— | BF65: =附表!AI22 -> —— | BL65: =附表!AL22 -> 二十一世纪 二十年代
W66: 重要之人 | AA66: 母亲凯瑟琳 | AR66: ☐ | AZ66: =附表!AG22 -> 0 | BF66: =附表!AJ22 -> 0 | BL66: =附表!AM22 -> 癸卯兔年
AZ67: =附表!AH22 -> 0 | BF67: =附表!AK22 -> 0 | BL67: =附表!AN22 -> 中华人民共和国74周年
W68: 意义非凡之地 | AA68: 纽约港口 | AR68: ☐ | AU68: 新闻
B69: 其他资产表 | AU69: =附表!AO22 -> 0
B70: 交通工具 | F70: 住所 | J70: 奢侈品 | N70: 股票/证券等 | R70: 其他 | W70: 宝贵之物 | AA70: 凯瑟琳的银项链 | AR70: ☐
J71: 精致烟盒和打火机、一对昂贵的宝石耳环
W72: 难言之隐 | AA72: 厌恶酒精和不忠诚的男人 | AR72: ☐
W74: 特质 | AA74: 散漫，看着不那么靠谱，女人缘极好 | AR74: ☐
B76: 0 | F76: 0 | J76: 0 | N76: 0 | R76: 0 | W76: 伤口和疤痕 | AA76: 无 | AR76: ☐
B77: ="资产总和："&SUM(B76:U76) -> 资产总和：0 | N77: ="剩余资产值："&IF(附表!AG230="没有",0-SUM(B76:U76),附表!AG230-SUM(B76:U76)) -> 剩余资产值：0
B78: 随身物品（使用右侧栏位需要背包） | W78: 恐惧症和狂躁症
B79: 状态 | D79: 位置 | F79: 物品名称 | N79: 背包格↓
B80: 显露 | D80: 衣兜 | F80: 炭黑色大衣 | N80: 小型黄铜望远镜 | W80: 纽约港口漂浮着油污与垃圾的臭味，母亲凯瑟琳沉海自杀后，西奥多觉得又多了一丝血腥味。 她所有的不幸都源自西奥多酗酒、出轨、家暴的父亲，于是某一个冬日，喝醉的父亲“意外”从结冰的消防梯跌落而亡，警方以醉鬼失足草草结案。 凯瑟琳曾说他是最聪明的孩子，明年春天要送他去上学，到头来，却由社会这所最残酷的学校教会他察言观色、谎言求生，谁也不知道他的真实想法，而西奥多天生的智慧让他摸索到适合自己的道路，他成为了一名私家侦探。 区别于不满足现状的许多同行，西奥多无意成为福尔摩斯，反而沉迷捉奸事业，很乐意为女士们服务，偶尔不收钱，甚至倒贴。至于男委托人，请付双倍报酬。 因为职业与过分英俊的外表，他有时也会卷入一些麻烦。 但没关系，凯瑟琳的银项链一直在他的心口处。 上帝不会保佑他，凯瑟琳会。
D81: 衣兜 | F81: 炭黑色大衣 | N81: 便签本、钢笔刀
D82: 衣兜 | F82: 炭黑色大衣 | N82: 绣字手帕
D83: 衣兜 | F83: 炭黑色大衣 | N83: 钱包
D84: 裤兜 | F84: 中灰色西装裤 | N84: 精致烟盒和打火机
B85: 隐藏 | D85: 衣服内 | F85: 西装马甲内侧 | N85: 一对昂贵的宝石耳环
D86: 内衬 | F86: 衬衫内帖胸口处 | N86: 凯瑟琳的银项链
D87: 其他(服) | F87: 银质领带夹 | N87: 开锁探针
B96: 调查员经历 | W96: 神话相关
B97: 经历模组 | J97: 人物变化描述 | W97: 第三类接触（古籍、咒文、神话知识等）
B98: 例：【毒汤】 | J98: SAN-6,HP-2,侦查+2 | W98: 遇到了 | AA98: 获得的结果 | AK98: 备注 | AR98: 累计
W99: 例：米-戈 | AA99: 克苏鲁+3，克苏鲁(疯)+5，SAN-6，SAN(信)-8 | AK99: 第一次神话疯狂，相信者规则激活 | AR99: 6
W100: 例：修格斯 | AA100: 克苏鲁+7，克苏鲁(疯)+1，SAN-5 | AK100: 第二次神话疯狂 | AR100: 5
AU105: 流行（1919-1930年美国）
AU106: =附表!AP22 -> 总统： 约瑟夫·拜登（民主党）
W113: 法术一览
B114: 经历包 (玩家手册): | E114: 经历包名称： | J114: =IF(E115="无","","SAN值减少"&附表!C34&" 备注："&附表!E34&"可选技能见【简化卡】下方") | W114: 编号 | Y114: 法术名称 | AC114: 使用代价 | AH114: 作用
E115: 无 | W115: 例：1 | Y115: 灰色束缚 | AC115: 8mp 1d6san 1h | AH115: 可以控制死去的人，直到腐烂为止
E116: 经历包职业：
B119: 快速参考规则
B120: 技能和属性检定 成功等级 | F120: 大失败 | L120: 失败 | N120: 成功 | P120: 困难 | R120: 极难 | T120: 大成功
F121: 技能成功率≥50为100 否则为96-100 | L121: >技能 | N121: ≤技能 | P121: 1/2值 | R121: 1/5值 | T121: 1
B123: 孤注一骰：使用孤注一骰来重投上一次检定结果，需要合理的解释重掷原因，战斗和理智检定不能执行孤注一骰。
B125: [急救]回复1点体力 | L125: [医学]回复1D3点体力
B126: 重伤 | D126: 一次受到最大生命值一半的伤害
...

Sheet 简化卡
B2: =人物卡!E3&"，"&人物卡!E6&"，"&人物卡!E4&"岁"&"，"&人物卡!E5&"，"&人物卡!M4&"，"&"现居："&人物卡!E7&"，"&人物卡!M6&"，"&人物卡!M7&"人" -> 尤金，男，29岁，私家侦探，1920s，现居：布鲁克林区，美国，纽约人 | N2: 技能 | Z2: 当前时间
B3: STR | C3: =STR -> 30 | D3: =INT(C3/2) -> 15 | E3: DEX | F3: =DEX -> 70 | G3: =INT(F3/2) -> 35 | H3: POW | I3: =POW -> 60 | J3: =INT(I3/2) -> 30 | K3: INT | L3: =INT -> 80 | M3: =INT(L3/2) -> 40 | N3: =IF(Q3=0,"",人物卡!F17) | Q3: =IF(人物卡!R17-人物卡!J17=0,0,人物卡!R17) -> 0 | R3: =INT(Q3/2) -> 0 | S3: =INT(Q3/5) -> 0 | T3: =IF(W3=0,"",人物卡!AB17) | W3: =IF(人物卡!AN17-人物卡!AF17=0,0,人物卡!AN17) -> 0 | X3: =INT(W3/2) -> 0 | Y3: =INT(W3/5) -> 0 | Z3: =人物卡!E8 -> 公元 | AA3: =人物卡!G8 -> 2023 | AC3: =人物卡!J8 -> 1月 | AD3: =人物卡!N8 -> 0：00
D4: =INT(C3/5) -> 6 | G4: =INT(F3/5) -> 14 | J4: =INT(I3/5) -> 12 | M4: =INT(L3/5) -> 16 | N4: =IF(Q4=0,"",人物卡!F18) | Q4: =IF(人物卡!R18-人物卡!J18=0,0,人物卡!R18) -> 0 | R4: =INT(Q4/2) -> 0 | S4: =INT(Q4/5) -> 0 | T4: =IF(W4=0,"",人物卡!AB18) | W4: =IF(人物卡!AN18-人物卡!AF18=0,0,人物卡!AN18) -> 0 | X4: =INT(W4/2) -> 0 | Y4: =INT(W4/5) -> 0 | AC4: =人物卡!L8 -> 1日
B5: CON | C5: =CON -> 50 | D5: =INT(C5/2) -> 25 | E5: APP | F5: =APP -> 80 | G5: =INT(F5/2) -> 40 | H5: EDU | I5: =EDU -> 55 | J5: =INT(I5/2) -> 27 | K5: SIZ | L5: =SIZ -> 55 | M5: =INT(L5/2) -> 27 | N5: =IF(Q5=0,"",人物卡!F19) | Q5: =IF(人物卡!R19-人物卡!J19=0,0,人物卡!R19) -> 0 | R5: =INT(Q5/2) -> 0 | S5: =INT(Q5/5) -> 0 | T5: =IF(W5=0,"",人物卡!AB19) -> 聆听 | W5: =IF(人物卡!AN19-人物卡!AF19=0,0,人物卡!AN19) -> 70 | X5: =INT(W5/2) -> 35 | Y5: =INT(W5/5) -> 14 | Z5: 调查员伙伴
D6: =INT(C5/5) -> 10 | G6: =INT(F5/5) -> 16 | J6: =INT(I5/5) -> 11 | M6: =INT(L5/5) -> 11 | N6: =IF(Q6=0,"",人物卡!F20) | Q6: =IF(人物卡!R20-人物卡!J20=0,0,人物卡!R20) -> 0 | R6: =INT(Q6/2) -> 0 | S6: =INT(Q6/5) -> 0 | T6: =IF(W6=0,"",人物卡!AB20) -> 锁匠 | W6: =IF(人物卡!AN20-人物卡!AF20=0,0,人物卡!AN20) -> 71 | X6: =INT(W6/2) -> 35 | Y6: =INT(W6/5) -> 14 | Z6: 姓名 | AB6: 注释
B7: HP | C7: =人物卡!E10 -> 10 | D7: =人物卡!G10 -> 10 | E7: SAN | F7: =人物卡!N10 -> 60 | G7: =人物卡!P10 -> 99 | H7: MP | I7: =人物卡!W10 -> 12 | J7: =MP -> 12 | K7: Armor | L7: =人物卡!AN10 | N7: =IF(Q7=0,0,"技艺：") -> 0 | O7: =IF(N7=0,"",人物卡!H21) | Q7: =IF(人物卡!R21-人物卡!J21=0,0,人物卡!R21) -> 0 | R7: =INT(Q7/2) -> 0 | S7: =INT(Q7/5) -> 0 | T7: =IF(W7=0,"",人物卡!AB21) | W7: =IF(人物卡!AN21-人物卡!AF21=0,0,人物卡!AN21) -> 0 | X7: =INT(W7/2) -> 0 | Y7: =INT(W7/5) -> 0 | Z7: =人物卡!W131 -> 0 | AB7: =人物卡!AD131 -> 那次团的二五仔，团灭了全体
N8: =IF(Q8=0,0,"技艺：") -> 0 | O8: =IF(N8=0,"",人物卡!H22) | Q8: =IF(人物卡!R22-人物卡!J22=0,0,人物卡!R22) -> 0 | R8: =INT(Q8/2) -> 0 | S8: =INT(Q8/5) -> 0 | T8: =IF(W8=0,"",人物卡!AB22) | W8: =IF(人物卡!AN22-人物卡!AF22=0,0,人物卡!AN22) -> 0 | X8: =INT(W8/2) -> 0 | Y8: =INT(W8/5) -> 0 | Z8: =人物卡!W132 -> 0 | AB8: =人物卡!AD132 -> 0
B9: DB | C9: =人物卡!AP53 -> 0 | E9: Build | F9: =人物卡!AP56 -> 0 | H9: LUCK | I9: =Luck -> 50 | K9: MOV | L9: =人物卡!AF10 -> 8 | N9: =IF(Q9=0,0,"技艺：") -> 0 | O9: =IF(N9=0,"",人物卡!H23) | Q9: =IF(人物卡!R23-人物卡!J23=0,0,人物卡!R23) -> 0 | R9: =INT(Q9/2) -> 0 | S9: =INT(Q9/5) -> 0 | T9: =IF(W9=0,"",人物卡!AB23) | W9: =IF(人物卡!AN23-人物卡!AF23=0,0,人物卡!AN23) -> 0 | X9: =INT(W9/2) -> 0 | Y9: =INT(W9/5) -> 0 | Z9: =人物卡!W133 -> 0 | AB9: =人物卡!AD133 -> 0
N10: =IF(Q10=0,"",人物卡!F24) -> 取悦 | Q10: =IF(人物卡!R24-人物卡!J24=0,0,人物卡!R24) -> 70 | R10: =INT(Q10/2) -> 35 | S10: =INT(Q10/5) -> 14 | T10: =IF(W10=0,"",人物卡!AB24) | W10: =IF(人物卡!AN24-人物卡!AF24=0,0,人物卡!AN24) -> 0 | X10: =INT(W10/2) -> 0 | Y10: =INT(W10/5) -> 0 | Z10: =人物卡!W134 -> 0 | AB10: =人物卡!AD134 -> 0
B11: 武器表 | N11: =IF(Q11=0,"",人物卡!F25) | Q11: =IF(人物卡!R25-人物卡!J25=0,0,人物卡!R25) -> 0 | R11: =INT(Q11/2) -> 0 | S11: =INT(Q11/5) -> 0 | T11: =IF(W11=0,"",人物卡!AB25) | W11: =IF(人物卡!AN25-人物卡!AF25=0,0,人物卡!AN25) -> 0 | X11: =INT(W11/2) -> 0 | Y11: =INT(W11/5) -> 0 | Z11: =人物卡!W135 -> 0 | AB11: =人物卡!AD135 -> 0
B12: =人物卡!B54 -> 无 | C12: =人物卡!G54 -> 肉搏 | D12: =人物卡!M54 -> 斗殴 | E12: =人物卡!Q54 -> 25 | F12: =人物卡!S54 -> 12 | G12: =人物卡!U54 -> 5 | H12: =人物卡!W54 -> 1D3+DB | I12: =人物卡!AA54 -> —— | J12: =人物卡!AC54 -> × | K12: =人物卡!AE54 -> 1 | L12: =人物卡!AG54 -> —— | M12: =人物卡!AJ54 -> —— | N12: =IF(Q12=0,"",人物卡!F26) | Q12: =IF(人物卡!R26-人物卡!J26=0,0,人物卡!R26) -> 0 | R12: =INT(Q12/2) -> 0 | S12: =INT(Q12/5) -> 0 | T12: =IF(W12=0,"",人物卡!AB26) | W12: =IF(人物卡!AN26-人物卡!AF26=0,0,人物卡!AN26) -> 0 | X12: =INT(W12/2) -> 0 | Y12: =INT(W12/5) -> 0 | Z12: =人物卡!W136 -> 0 | AB12: =人物卡!AD136 -> 0
B13: =人物卡!B55 -> 钢笔刀 | C13: =人物卡!G55 -> 小型刀具(弹簧折叠刀等) | D13: =IF(人物卡!M55="请选择类型","",人物卡!M55) -> 斗殴 | E13: =人物卡!Q55 -> 25 | F13: =人物卡!S55 -> 12 | G13: =人物卡!U55 -> 5 | H13: =人物卡!W55 -> 1D4+DB | I13: =人物卡!AA55 -> 接触 | J13: =人物卡!AC55 -> √ | K13: =人物卡!AE55 -> 1 | L13: =人物卡!AG55 -> —— | M13: =人物卡!AJ55 -> —— | N13: =人物卡!F27 -> 信用评级 | Q13: =人物卡!R27 -> 20 | R13: =IF(Q13=0,32767,INT(Q13/2)) -> 10 | S13: =IF(Q13=0,32767,INT(Q13/5)) -> 4 | T13: =IF(W13=0,"",人物卡!AB27) | W13: =IF(人物卡!AN27-人物卡!AF27=0,0,人物卡!AN27) -> 0 | X13: =INT(W13/2) -> 0 | Y13: =INT(W13/5) -> 0 | Z13: =人物卡!W137 -> 0 | AB13: =人物卡!AD137 -> 0
B14: =人物卡!B56 -> 0 | C14: =人物卡!G56 -> 0 | D14: =IF(人物卡!M56="请选择类型","",人物卡!M56) -> ←请选择类型 | E14: =人物卡!Q56 | F14: =人物卡!S56 | G14: =人物卡!U56 | H14: =人物卡!W56 | I14: =人物卡!AA56 | J14: =人物卡!AC56 | K14: =人物卡!AE56 | L14: =人物卡!AG56 | M14: =人物卡!AJ56 | N14: =IF(Q14=0,"",人物卡!F28) | Q14: =IF(人物卡!R28-人物卡!J28=0,0,人物卡!R28) -> 0 | R14: =INT(Q14/2) -> 0 | S14: =INT(Q14/5) -> 0 | T14: =IF(W14=0,0,人物卡!AB28) -> 0 | U14: =IF(T14=0,"",人物卡!AD28) | W14: =IF(人物卡!AN28-人物卡!AF28=0,0,人物卡!AN28) -> 0 | X14: =INT(W14/2) -> 0 | Y14: =INT(W14/5) -> 0 | Z14: =人物卡!W138 -> 0 | AB14: =人物卡!AD138 -> 0
B15: =人物卡!B57 -> 0 | C15: =人物卡!G57 -> 0 | D15: =IF(人物卡!M57="请选择类型","",人物卡!M57) | E15: =人物卡!Q57 | F15: =人物卡!S57 | G15: =人物卡!U57 | H15: =人物卡!W57 | I15: =人物卡!AA57 | J15: =人物卡!AC57 | K15: =人物卡!AE57 | L15: =人物卡!AG57 | M15: =人物卡!AJ57 | N15: =IF(Q15=0,"",人物卡!F29) | Q15: =IF(人物卡!R29-人物卡!J29=0,0,人物卡!R29) -> 0 | R15: =INT(Q15/2) -> 0 | S15: =INT(Q15/5) -> 0 | T15: =IF(W15=0,"",人物卡!AB29) | W15: =IF(人物卡!AN29-人物卡!AF29=0,0,人物卡!AN29) -> 0 | X15: =INT(W15/2) -> 0 | Y15: =INT(W15/5) -> 0 | Z15: =人物卡!W139 -> 0 | AB15: =人物卡!AD139 -> 0
B16: =人物卡!B58 -> 0 | C16: =人物卡!G58 -> 0 | D16: =IF(人物卡!M58="请选择类型","",人物卡!M58) -> 0 | E16: =人物卡!Q58 -> 0 | F16: =人物卡!S58 -> 0 | G16: =人物卡!U58 -> 0 | H16: =人物卡!W58 -> 0 | I16: =人物卡!AA58 -> 0 | J16: =人物卡!AC58 -> 0 | K16: =人物卡!AE58 -> 0 | L16: =人物卡!AG58 -> 0 | M16: =人物卡!AJ58 -> 0 | N16: =人物卡!F30 -> 闪避 | Q16: =人物卡!R30 -> 60 | R16: =IF(Q16=0,32767,INT(Q16/2)) -> 30 | S16: =IF(Q16=0,32767,INT(Q16/5)) -> 12 | T16: =IF(W16=0,"",人物卡!AB30) -> 心理学 | W16: =IF(人物卡!AN30-人物卡!AF30=0,0,人物卡!AN30) -> 60 | X16: =INT(W16/2) -> 30 | Y16: =INT(W16/5) -> 12 | Z16: =人物卡!W140 -> 0 | AB16: =人物卡!AD140 -> 0
B17: 资产 | N17: =IF(Q17=0,"",人物卡!F31) | Q17: =IF(人物卡!R31-人物卡!J31=0,0,人物卡!R31) -> 0 | R17: =INT(Q17/2) -> 0 | S17: =INT(Q17/5) -> 0 | T17: =IF(W17=0,"",人物卡!AB31) | W17: =IF(人物卡!AN31-人物卡!AF31=0,0,人物卡!AN31) -> 0 | X17: =INT(W17/2) -> 0 | Y17: =INT(W17/5) -> 0 | Z17: =人物卡!W141 -> 0 | AB17: =人物卡!AD141 -> 0
B18: 信用评级 | E18: 生活水平 | G18: 消费水平 | I18: 其他资产 | K18: 当前现金($) | M18: 单位 | N18: =IF(Q18=0,"",人物卡!F32) | Q18: =IF(人物卡!R32-人物卡!J32=0,0,人物卡!R32) -> 0 | R18: =INT(Q18/2) -> 0 | S18: =INT(Q18/5) -> 0 | T18: =IF(W18=0,0,"科学：") -> 0 | U18: =IF(T18=0,"",人物卡!AD32) | W18: =IF(人物卡!AN32-人物卡!AF32=0,0,人物卡!AN32) -> 0 | X18: =INT(W18/2) -> 0 | Y18: =INT(W18/5) -> 0
B19: =人物卡!B63 -> 20%/10%/4% | E19: =人物卡!F63 -> 标准 | G19: =人物卡!I63 -> 10 | I19: =人物卡!L63 -> 没有 | K19: =人物卡!O63 -> 10 | M19: =人物卡!S63 -> 美元 | N19: =IF(Q19=0,"",人物卡!F33) | Q19: =IF(人物卡!R33-人物卡!J33=0,0,人物卡!R33) -> 0 | R19: =INT(Q19/2) -> 0 | S19: =INT(Q19/5) -> 0 | T19: =IF(W19=0,0,"科学：") -> 0 | U19: =IF(T19=0,"",人物卡!AD33) | W19: =IF(人物卡!AN33-人物卡!AF33=0,0,人物卡!AN33) -> 0 | X19: =INT(W19/2) -> 0 | Y19: =INT(W19/5) -> 0
B20: =人物卡!L64 -> 请在这里详述你的资产 | N20: =IF(Q20=0,"",人物卡!F34) -> 话术 | Q20: =IF(人物卡!R34-人物卡!J34=0,0,人物卡!R34) -> 70 | R20: =INT(Q20/2) -> 35 | S20: =INT(Q20/5) -> 14 | T20: =IF(W20=0,0,"科学：") -> 0 | U20: =IF(T20=0,"",人物卡!AD34) | W20: =IF(人物卡!AN34-人物卡!AF34=0,0,人物卡!AN34) -> 0 | X20: =INT(W20/2) -> 0 | Y20: =INT(W20/5) -> 0
N21: =IF(Q21=0,0,"格斗：") -> 0 | O21: =IF(N21=0,"",人物卡!H35) | Q21: =IF(人物卡!R35-人物卡!J35=0,0,人物卡!R35) -> 0 | R21: =INT(Q21/2) -> 0 | S21: =INT(Q21/5) -> 0 | T21: =IF(W21=0,"",人物卡!AB35) | W21: =IF(人物卡!AN35-人物卡!AF35=0,0,人物卡!AN35) -> 0 | X21: =INT(W21/2) -> 0 | Y21: =INT(W21/5) -> 0 | Z21: 神话相关
B22: 随身物品 | N22: =IF(Q22=0,0,"格斗：") -> 0 | O22: =IF(N22=0,"",人物卡!H36) | Q22: =IF(人物卡!R36-人物卡!J36=0,0,人物卡!R36) -> 0 | R22: =INT(Q22/2) -> 0 | S22: =INT(Q22/5) -> 0 | T22: =IF(W22=0,"",人物卡!AB36) -> 侦查 | W22: =IF(人物卡!AN36-人物卡!AF36=0,0,人物卡!AN36) -> 80 | X22: =INT(W22/2) -> 40 | Y22: =INT(W22/5) -> 16 | Z22: 遇到了 | AD22: 累计消耗
B23: =人物卡!F80 -> 炭黑色大衣 | E23: =人物卡!F81 -> 炭黑色大衣 | H23: =人物卡!F82 -> 炭黑色大衣 | K23: =人物卡!F83 -> 炭黑色大衣 | N23: =IF(Q23=0,0,"格斗：") -> 0 | O23: =IF(N23=0,"",人物卡!H37) | Q23: =IF(人物卡!R37-人物卡!J37=0,0,人物卡!R37) -> 0 | R23: =INT(Q23/2) -> 0 | S23: =INT(Q23/5) -> 0 | T23: =IF(W23=0,"",人物卡!AB37) -> 潜行 | W23: =IF(人物卡!AN37-人物卡!AF37=0,0,人物卡!AN37) -> 60 | X23: =INT(W23/2) -> 30 | Y23: =INT(W23/5) -> 12 | Z23: =人物卡!W99 -> 例：米-戈 | AD23: =人物卡!AR99 -> 6
B24: =人物卡!F84 -> 中灰色西装裤 | E24: =人物卡!F85 -> 西装马甲内侧 | H24: =人物卡!F86 -> 衬衫内帖胸口处 | K24: =人物卡!F91 -> 0 | N24: =IF(Q24=0,0,"格斗：") -> 0 | O24: =IF(N24=0,"",人物卡!H38) | Q24: =IF(人物卡!R38-人物卡!J38=0,0,人物卡!R38) -> 0 | R24: =INT(Q24/2) -> 0 | S24: =INT(Q24/5) -> 0 | T24: =IF(W24=0,0,人物卡!AB38) -> 0 | U24: =IF(T24=0,"",人物卡!AD38) | W24: =IF(人物卡!AN38-人物卡!AF38=0,0,人物卡!AN38) -> 0 | X24: =INT(W24/2) -> 0 | Y24: =INT(W24/5) -> 0 | Z24: =人物卡!W100 -> 例：修格斯 | AD24: =人物卡!AR100 -> 5
B25: =人物卡!F92 -> 0 | E25: =人物卡!F93 -> 0 | H25: =人物卡!N80 -> 小型黄铜望远镜 | K25: =人物卡!N81 -> 便签本、钢笔刀 | N25: =IF(Q25=0,0,"射击：") -> 0 | O25: =IF(N25=0,"",人物卡!H39) | Q25: =IF(人物卡!R39-人物卡!J39=0,0,人物卡!R39) -> 0 | R25: =INT(Q25/2) -> 0 | S25: =INT(Q25/5) -> 0 | T25: =IF(W25=0,"",人物卡!AB39) | W25: =IF(人物卡!AN39-人物卡!AF39=0,0,人物卡!AN39) -> 0 | X25: =INT(W25/2) -> 0 | Y25: =INT(W25/5) -> 0 | Z25: =人物卡!W101 -> 0 | AD25: =人物卡!AR101 -> 0
B26: =人物卡!N82 -> 绣字手帕 | E26: =人物卡!N83 -> 钱包 | H26: =人物卡!N84 -> 精致烟盒和打火机 | K26: =人物卡!N85 -> 一对昂贵的宝石耳环 | N26: =IF(Q26=0,0,"射击：") -> 0 | O26: =IF(N26=0,"",人物卡!H40) | Q26: =IF(人物卡!R40-人物卡!J40=0,0,人物卡!R40) -> 0 | R26: =INT(Q26/2) -> 0 | S26: =INT(Q26/5) -> 0 | T26: =IF(W26=0,"",人物卡!AB40) | W26: =IF(人物卡!AN40-人物卡!AF40=0,0,人物卡!AN40) -> 0 | X26: =INT(W26/2) -> 0 | Y26: =INT(W26/5) -> 0 | Z26: =人物卡!W102 -> 0 | AD26: =人物卡!AR102 -> 0
B27: =人物卡!N86 -> 凯瑟琳的银项链 | E27: =人物卡!N91 -> 0 | H27: =人物卡!N92 -> 0 | K27: =人物卡!N93 -> 0 | N27: =IF(Q27=0,0,"射击：") -> 0 | O27: =IF(N27=0,"",人物卡!H41) | Q27: =IF(人物卡!R41-人物卡!J41=0,0,人物卡!R41) -> 0 | R27: =INT(Q27/2) -> 0 | S27: =INT(Q27/5) -> 0 | T27: =IF(W27=0,"",人物卡!AB41) | W27: =IF(人物卡!AN41-人物卡!AF41=0,0,人物卡!AN41) -> 0 | X27: =INT(W27/2) -> 0 | Y27: =INT(W27/5) -> 0 | Z27: =人物卡!W103 -> 0 | AD27: =人物卡!AR103 -> 0
B28: 背景故事 | N28: =IF(Q28=0,0,"射击：") -> 0 | O28: =IF(N28=0,"",人物卡!H42) | Q28: =IF(人物卡!R42-人物卡!J42=0,0,人物卡!R42) -> 0 | R28: =INT(Q28/2) -> 0 | S28: =INT(Q28/5) -> 0 | T28: =IF(W28=0,"",人物卡!AB42) | W28: =IF(人物卡!AN42-人物卡!AF42=0,0,人物卡!AN42) -> 0 | X28: =INT(W28/2) -> 0 | Y28: =INT(W28/5) -> 0 | Z28: =人物卡!W104 -> 0 | AD28: =人物卡!AR104 -> 0
B29: 描述 | C29: =人物卡!AA62 -> 高瘦，黑发蓝眼，英俊 | G29: 关键 | H29: =人物卡!W80 -> 纽约港口漂浮着油污与垃圾的臭味，母亲凯瑟琳沉海自杀后，西奥多觉得又多了一丝血腥味。 她所有的不幸都源自西奥多酗酒、出轨、家暴的父亲，于是某一个冬日，喝醉的父亲“意外”从结冰的消防梯跌落而亡，警方以醉鬼失足草草结案。 凯瑟琳曾说他是最聪明的孩子，明年春天要送他去上学，到头来，却由社会这所最残酷的学校教会他察言观色、谎言求生，谁也不知道他的真实想法，而西奥多天生的智慧让他摸索到适合自己的道路，他成为了一名私家侦探。 区别于不满足现状的许多同行，西奥多无意成为福尔摩斯，反而沉迷捉奸事业，很乐意为女士们服务，偶尔不收钱，甚至倒贴。至于男委托人，请付双倍报酬。 因为职业与过分英俊的外表，他有时也会卷入一些麻烦。 但没关系，凯瑟琳的银项链一直在他的心口处。 上帝不会保佑他，凯瑟琳会。 | N29: =IF(Q29=0,"",人物卡!F43) | Q29: =IF(人物卡!R43-人物卡!J43=0,0,人物卡!R43) -> 0 | R29: =INT(Q29/2) -> 0 | S29: =INT(Q29/5) -> 0 | T29: =IF(W29=0,"",人物卡!AB48) | W29: =IF(人物卡!AN43-人物卡!AF43=0,0,人物卡!AN43) -> 0 | X29: =INT(W29/2) -> 0 | Y29: =INT(W29/5) -> 0 | Z29: =人物卡!W105 -> 0 | AD29: =人物卡!AR105 -> 0
B30: 信仰 | C30: =人物卡!AA64 -> 他没有什么追求，但或许他能为像凯瑟琳一样的人做些什么 | G30: =人物卡!AR64 -> ☐ | N30: =IF(Q30=0,"",人物卡!F44) | Q30: =IF(人物卡!R44-人物卡!J44=0,0,人物卡!R44) -> 0 | R30: =INT(Q30/2) -> 0 | S30: =INT(Q30/5) -> 0 | T30: =IF(W30=0,"",人物卡!AB44) | W30: =IF(人物卡!AN44-人物卡!AF44=0,0,人物卡!AN44) -> 0 | X30: =INT(W30/2) -> 0 | Y30: =INT(W30/5) -> 0 | Z30: =人物卡!W106 -> 0 | AD30: =人物卡!AR106 -> 0
B31: 重要人 | C31: =人物卡!AA66 -> 母亲凯瑟琳 | G31: =人物卡!AR66 -> ☐ | N31: =IF(Q31=0,"",人物卡!F45) | Q31: =IF(人物卡!R45-人物卡!J45=0,0,人物卡!R45) -> 0 | R31: =INT(Q31/2) -> 0 | S31: =INT(Q31/5) -> 0 | T31: =IF(W31=0,"",人物卡!AB45) | W31: =IF(人物卡!AN45-人物卡!AF45=0,0,人物卡!AN45) -> 0 | X31: =INT(W31/2) -> 0 | Y31: =INT(W31/5) -> 0 | Z31: =人物卡!W107 -> 0 | AD31: =人物卡!AR107 -> 0
B32: 重要地 | C32: =人物卡!AA68 -> 纽约港口 | G32: =人物卡!AR68 -> ☐ | N32: =IF(Q32=0,"",人物卡!F46) | Q32: =IF(人物卡!R46-人物卡!J46=0,0,人物卡!R46) -> 0 | R32: =INT(Q32/2) -> 0 | S32: =INT(Q32/5) -> 0 | T32: =IF(W32=0,"",人物卡!AB46) | W32: =IF(人物卡!AN46-人物卡!AF46=0,0,人物卡!AN46) -> 0 | X32: =INT(W32/2) -> 0 | Y32: =INT(W32/5) -> 0 | Z32: =人物卡!W108 -> 0 | AD32: =人物卡!AR108 -> 0
B33: 宝物 | C33: =人物卡!AA70 -> 凯瑟琳的银项链 | G33: =人物卡!AR70 -> ☐ | N33: =IF(Q33=0,0,"外语：") -> 0 | O33: =IF(N33=0,"",人物卡!H47) | Q33: =IF(人物卡!R47-人物卡!J47=0,0,人物卡!R47) -> 0 | R33: =INT(Q33/2) -> 0 | S33: =INT(Q33/5) -> 0 | T33: =IF(W33=0,"",人物卡!AB47) | W33: =IF(人物卡!AN47-人物卡!AF47=0,0,人物卡!AN47) -> 0 | X33: =INT(W33/2) -> 0 | Y33: =INT(W33/5) -> 0 | Z33: =人物卡!W109 -> 0 | AD33: =人物卡!AR109 -> 0
B34: 特质 | C34: =人物卡!AA74 -> 散漫，看着不那么靠谱，女人缘极好 | G34: =人物卡!AR74 -> ☐ | N34: =IF(Q34=0,0,"外语：") -> 0 | O34: =IF(N34=0,"",人物卡!H48) | Q34: =IF(人物卡!R48-人物卡!J48=0,0,人物卡!R48) -> 0 | R34: =INT(Q34/2) -> 0 | S34: =INT(Q34/5) -> 0 | T34: =IF(W34=0,"",人物卡!#REF!) | W34: =IF(人物卡!AN48-人物卡!AF48=0,0,人物卡!AN48) -> 0 | X34: =INT(W34/2) -> 0 | Y34: =INT(W34/5) -> 0
B35: 伤疤 | C35: =人物卡!AA76 -> 无 | G35: =人物卡!AR76 -> ☐ | N35: =IF(Q35=0,0,"外语：") -> 0 | O35: =IF(N35=0,"",人物卡!H49) | Q35: =IF(人物卡!R49-人物卡!J49=0,0,人物卡!R49) -> 0 | R35: =INT(Q35/2) -> 0 | S35: =INT(Q35/5) -> 0 | T35: =IF(W35=0,"",人物卡!AB49) | W35: =IF(人物卡!AN49-人物卡!AF49=0,0,人物卡!AN49) -> 0 | X35: =INT(W35/2) -> 0 | Y35: =INT(W35/5) -> 0
B36: 恐惧 | C36: =人物卡!AA78 -> 0 | N36: 母语： | O36: =人物卡!H50 -> 0 | Q36: =人物卡!R50 -> 55 | R36: =IF(Q36=0,32767,INT(Q36/2)) -> 27 | S36: =IF(Q36=0,32767,INT(Q36/5)) -> 11 | T36: =IF(W36=0,"",人物卡!AB50) | W36: =IF(人物卡!AN50-人物卡!AF50=0,0,人物卡!AN50) -> 0 | X36: =INT(W36/2) -> 0 | Y36: =INT(W36/5) -> 0
B38: .st指令快捷输入 | Z38: TXT框→
B39: 请右键下格，点击“复制”，并且在右方的TXT栏“粘贴”就可以导出文本，放进QQ发送给骰子娘啦
B40: =附表!S23 -> .st 力量30str30敏捷70dex70意志60pow60体质50con50外貌80app80教育55知识55edu55体型55siz55智力80灵感80int80san60san值60理智60理智值60幸运50运气50mp12魔法12hp10体力10会计5人类学1估价5考古学1取悦70攀爬20计算机5计算机使用5电脑5信用20信誉20信用评级20克苏鲁0克苏鲁神话0cm0乔装5闪避60汽车20驾驶20汽车驾驶20电气维修10电子学1话术70斗殴25手枪20急救30历史5恐吓15跳跃20母语55法律5图书馆20图书馆使用20聆听70开锁71撬锁71锁匠71机械维修10医学1博物学10自然学10领航10导航10神秘学5重型操作1重型机械1操作重型机械1重型1说服10精神分析1心理学60骑术5妙手10侦查80潜行60生存10游泳20投掷20追踪10驯兽5潜水1爆破1读唇1催眠1炮术1
B41: 技能名的改变
B42: 原技能名称： | D42: 简化 | F42: 别名 | J42: 原技能名称： | L42: 简化 | N42: 别名 | R42: 原技能名称： | T42: 简化 | V42: 别名
B43: 力量 | D43: STR | J43: 体力 | L43: hp | R43: 汽车驾驶 | T43: 汽车 | V43: 驾驶
B44: 敏捷 | D44: DEX | J44: 理智 | L44: san | N44: san值，理智值 | R44: 电子学 Ω | T44: 电子学
B45: 体质 | D45: CON | J45: 魔法 | L45: mp | R45: 步枪/霰弹枪 | T45: 步枪 | V45: 霰弹枪，步霰
B46: 体型 | D46: SIZ | R46: 图书馆使用 | T46: 图书馆
B47: 外貌 | D47: APP | R47: 锁匠 | T47: 开锁
B48: 智力 | D48: INT | F48: 灵感 | R48: 博物学 | V48: 自然学
B49: 意志 | D49: POW | J49: 计算机使用 Ω | L49: 计算机 | N49: 计算机使用，电脑 | R49: 导航 | V49: 领航
B50: 教育 | D50: EDU | F50: 知识 | J50: 信用评级 | L50: 信用 | N50: 信誉 | R50: 操作重型机械 | T50: 重型操作 | V50: 重型机械，重型，重型机械操作
B51: 幸运 | F51: 运气 | J51: 克苏鲁神话 | L51: 克苏鲁 | N51: cm | R51: 生存： | T51: 生存
B52: 红字代表不能使用该名称roll（没有录入，主要因为其特殊的标点符号）
B54: 简化.st指令快捷输入 | Z54: TXT框→
B55: 请右键下格，点击“复制”，并且在右方的TXT栏“粘贴”就可以导出文本，放进QQ发送给骰子娘啦
B56: =附表!U40 -> .st 力量30str30敏捷70dex70意志60pow60体质50con50外貌80app80教育55edu55体型55siz55智力80灵感80int80san60san值60理智60理智值60幸运50运气50mp12魔法12hp10体力10取悦70信用评级20闪避60话术70聆听70锁匠71心理学60潜行60侦查80
B57: 注释
B58: 这个栏位是为了一些不能输入很长~~~一段的.st骰子姬设计的， 就是除了基础属性（九维属性和体力理智魔法）外全部简化为原技能名称+技能值，并且忽略掉没有在技能基础值增加或减少的技能 | M58: 而那些有特殊符号的将会删除特殊符号 例："计算机使用 Ω"改为了"计算机使用" 拥有子技能的会优先使用子技能名称，没有子技能名称将会使用母技能去符号 例：“技艺① 打字”成功率为10 就会显示为“打字10” “技艺①（子技能没填）”成功率为10 就会显示为“技艺10”
B66: 可选规则：有故事的调查员
B68: 经历包名称 | E68: SAN值减少 | H68: 技能增长 | J68: 可选技能： | T68: 备注：
B69: 战场经历包 | E69: 1D10+5 | H69: 70 | J69: 普通士兵：攀爬，格斗(斗殴)，射击(步霰)，急救，恐吓，聆听，潜行，投掷，妙手，侦查，生存 | O69: 军官：攀爬，格斗(斗殴)，射击(手枪)，急救，聆听，（导航、取悦，说服，恐吓)中选一项，潜行，投掷，侦查 | T69: 对目击尸体和重伤员造成的理智损失免疫; 根据战争的年份和模组发生时的年份调整年龄； 背景增加一项：战争相关的伤疤 / 疤痕或恐惧症 / 躁狂症
B72: 警务经历包 | E72: 1D10 | H72: 60 | J72: 攀爬，汽车驾驶，格斗（斗殴），射击（手枪或步霰），急救，法律，聆听，外语，两项社交技能（魅惑、话术、说服、恐吓），追踪 | T72: 对目击尸体造成的理智损失免疫; 初始年龄不能低于 25 岁; 背景增加一项：警察工作相关的伤疤 / 疤痕或恐惧症 / 躁狂症
B75: 罪犯经历包 | E75: 1D10 | H75: 60 | J75: 攀爬，汽车驾驶，格斗（任一），射击（任一），一项社交技能（魅惑、话术、说服、恐吓），法律，聆听，锁匠，心理学，追踪 | T75: 对目击尸体、目击或亲自谋杀、目击对人类的暴力残害造成的理智损失免疫; 初始年龄不能低于 20 岁； 背景增加一项：犯罪历史相关的伤疤 / 疤痕或恐惧症 / 躁狂症
B78: 医务经历包 | E78: 1D10 | H78: 60 | J78: 急救，法律，聆听，医学，心理学，侦查，科学（任二） | T78: 对目击尸体和重伤员造成的理智损失免疫; 初始年龄不能低于 30 岁； 背景增加一项：个人背景相关的伤疤 / 疤痕或恐惧症 / 躁狂症
B81: 神话经历包 | E81: 如果是"相信者" 减少和克苏鲁神话相同的san值 | H81: 0 | J81: 无 | T81: 按 KP 允许的数值增加「克苏鲁神话」技能; 背景增加两项：与神话经历相关的伤疤 /疤痕、恐惧症 / 躁狂症、遭遇的怪异存在
B84: =IF(ISBLANK(人物卡!BC27),"",人物卡!BC27) | E84: =IF(ISBLANK(人物卡!BC29),"",人物卡!BC29) | H84: =IF(ISBLANK(人物卡!BG29),"",人物卡!BG29) | J84: =IF(ISBLANK(人物卡!BC31),"",人物卡!BC31) | T84: =IF(ISBLANK(人物卡!BC35),"",人物卡!BC35)

Sheet 职业列表
A1: 序号 | B1: 职业 | D1: 最小 信誉 | E1: 最大 信誉 | F1: 职业属性 | G1: 技能点 | H1: 本职技能（请往右翻→） | L1: 推荐关系人 | N1: 职业介绍 | R1: =人物卡!M4 -> 1920s
A2: 0 | B2: 选择职业序号为0，则清除职业模板提示和点数计算器，供强迫症患者使用。 | I2: 右侧下拉框选择自定义职业技能与属性 | J2: 自定义职业本职技能
A3: 1 | B3: =IF(C3="","自定义职业",C3) -> 自定义职业 | D3: 0 | E3: 50 | F3: =附表!AB5 -> 教育×2+力量×2或体质×2 | G3: =附表!AF5 -> 210 | H3: =IF(附表!P60=1,附表!Q61&附表!Q62&附表!Q63&附表!Q64&附表!Q65&附表!Q66&附表!Q67&附表!Q68&附表!Q72&附表!Q69&附表!Q70&附表!Q71,"不多于8个本职技能。在职业属性中输入第二职业属性的数值（留空则视为EDU）并自行设置起始信誉。使用自定义职业前，请先咨询你的守秘人。") -> 不多于8个本职技能。在职业属性中输入第二职业属性的数值（留空则视为EDU）并自行设置起始信誉。使用自定义职业前，请先咨询你的守秘人。 | L3: 列出一些角色在职业工作中可能接触的个人或组织,它们也可以为调查员的个人背景提供灵感。 | N3: 不多于7个本职技能。 在职业属性中输入第二职业属性的名字（如外貌、意志、教育、敏捷、力量、体质、体型，留空则视为EDU）并自行设置起始信誉。使用自定义职业前，请先咨询你的KP
A4: 2 | B4: 会计师 | D4: 30 | E4: 70 | F4: 教育×4 | G4: =EDU*4 -> 220 | H4: 会计，法律，图书馆，聆听，说服，侦查，任意其他两项个人或时代特长。 | L4: 生意伙伴，法律界，金融业界(银行，其他会计师)。 | N4: 会计师可能在企业工作或作为自由会计师，为个体经营者和企业客户担任顾问。 他们是优秀的研究者，既勤奋又关注细节，能够通过仔细分析个人和企业事务历史记录、财务报表和其他记录支持其他调查员。
A5: 3 | B5: 杂技演员 | D5: 9 | E5: 20 | F5: 教育×2＋敏捷×2 | G5: =EDU*2+DEX*2 -> 250 | H5: 攀爬，闪避，跳跃，投掷，侦查，游泳，任意两项其他个人或时代特长。 | L5: 业余运动员圈，体育专栏作家，马戏团，嘉年华管理者。 | N5: 杂技演员可能是参加各级比赛(甚至奥运会)的业余运动员，也可能是专业的演员，在马戏团、嘉年华、歌舞团之类的地方作为娱乐业从业者工作。
A6: 4 | B6: 演员-戏剧演员 | D6: 9 | E6: 40 | F6: 教育×2＋外貌×2 | G6: =EDU*2+APP*2 -> 270 | H6: 技艺（表演），乔装，格斗，历史，两项社交技能（取悦、话术、恐吓、说服），心理学，任意一项其他个人或时代特长。 | L6: 戏剧产业，报刊艺术批评家，演员公会。 | N6: 一般指舞台剧演员和电影演员。许多演员有相当深厚的文化素养，认为自己才是“正统”的，倾向于轻视电影业的商业活动。直到20 世纪后期电影业的地位提高，电影演员的薪酬增加，这种情况才发生改变。 电影业和电影明星一直是世界人民关注的焦点。许多明星一夜成名，在媒体的聚光灯下过着光鲜亮丽的生活。 在1920 年代，虽然全国都有大型剧院，美国的戏剧中心仍然是纽约城。英国的情况与之相近，戏剧的中心在伦敦，其他的剧团则在各郡作巡回演出。巡回剧团乘火车旅行，演出内容既包括新编剧目，也包括莎士比亚和其他人的传统剧目。有些剧团也会花时间去国外采风，通常是去加拿大、夏威夷、澳大利亚和欧洲大陆。 20 年代后期出现了有声电影，不少默片时代的明星难以适应有声电影的冲击，挥舞手臂的夸张扮演从此让位给了细致入微的角色特写。这段时间前期的明星包括约翰·加菲尔德和弗兰西斯·布什曼，后期则是贾莱·库珀和琼·克劳馥。
A7: 5 | B7: 演员-电影演员 | D7: 20 | E7: 90 | F7: 教育×2＋外貌×2 | G7: =EDU*2+APP*2 -> 270 | H7: 技艺（表演），乔装，汽车驾驶，两项社交技能（取悦、话术、恐吓、说服），心理学，任意两项其他个人或时代特长（如骑乘或格斗）。 | L7: 电影工作室，媒体评论员，作家。 | N7: 一般指舞台剧演员和电影演员。许多演员有相当深厚的文化素养，认为自己才是“正统”的，倾向于轻视电影业的商业活动。直到20 世纪后期电影业的地位提高，电影演员的薪酬增加，这种情况才发生改变。 电影业和电影明星一直是世界人民关注的焦点。许多明星一夜成名，在媒体的聚光灯下过着光鲜亮丽的生活。 在1920 年代，虽然全国都有大型剧院，美国的戏剧中心仍然是纽约城。英国的情况与之相近，戏剧的中心在伦敦，其他的剧团则在各郡作巡回演出。巡回剧团乘火车旅行，演出内容既包括新编剧目，也包括莎士比亚和其他人的传统剧目。有些剧团也会花时间去国外采风，通常是去加拿大、夏威夷、澳大利亚和欧洲大陆。 20 年代后期出现了有声电影，不少默片时代的明星难以适应有声电影的冲击，挥舞手臂的夸张扮演从此让位给了细致入微的角色特写。这段时间前期的明星包括约翰·加菲尔德和弗兰西斯·布什曼，后期则是贾莱·库珀和琼·克劳馥。
A8: 6 | B8: 事务所侦探/保安 | D8: 20 | E8: 45 | F8: 教育×2＋力量或敏捷×2 | G8: =EDU*2+MAX(STR*2,DEX*2) -> 250 | H8: 一项社交技能（取悦、话术、恐吓、说服），格斗（斗殴），射击，法律，图书馆，心理学，潜行，追踪。 | L8: 本地执法机构，客户。 | N8: 世界上有许多著名的侦探机构，其中最著名的是平克顿和伯恩斯调查局(后来合并成一家公司)。这样的公司一般有两类工作人员：安保人员和调查人员。 企业或个人雇用安保人员来保护自己的资产和人员免受盗贼、刺客和绑匪的威胁。这些安保人员角色使用巡警的职业模板。调查人员则是便衣侦探，负责为公司客户解决各种异常事件、阻止谋杀事件、寻找失踪的人员等等。
A9: 7 | B9: 精神病医生（古典） | D9: 10 | E9: 60 | F9: 教育×4 | G9: =EDU*4 -> 220 | H9: 法律，聆听，医学，外语，精神分析，心理学，科学（生物学，化学）。 | L9: 其他精神疾病研究者，医生，有时还有执法机构的侦探。 | N9: 在1920 年代，“精神病医生”这个词专用来称呼治疗精神失常的医生(也就是早期的精神科医生)。精神分析在当时的美国鲜为人知，而且它的基本内容都是性生活和如厕训练之类令大众不齿的东西。精神病学，一种正规的从行为主义发展来的医学理论则要普及得多。精神病医生、精神科医生和神经科医生还经常爆发激烈的论战。
A10: 8 | B10: 动物训练师 | D10: 10 | E10: 40 | F10: 教育×2＋外貌或意志×2 | G10: =EDU*2+MAX(APP*2,POW*2) -> 270 | H10: 跳跃，聆听，自然，心理学，科学（动物学），潜行，追踪，任意一项其他个人或时代特长。 | L10: 动物园，马戏团，赞助人，演员。 | N10: 动物训练师可能在电影工作室、巡回马戏团、马厩工作或自由工作。不管是训练导盲犬、狮子钻火圈，他们工作时基本要独自一人长时间近距离地照看这些动物。动物训练师可以像对人一样对动物使用「心理学」技能。
A11: 9 | B11: 文物学家（原作向） | D11: 30 | E11: 70 | F11: 教育×4 | G11: =EDU*4 -> 220 | H11: 估价，技艺（任一），历史，图书馆，外语，一项社交技能（取悦、话术、恐吓、说服），侦查，任意一项其他个人或时代特长。 | J11: 任意特长数: | L11: 书商，古董收藏者，历史研究学会。 | N11: 文物学家也许是调查员可以从事的最具有洛夫克拉夫特风格的职业：那些历久弥新的的卓越作品、湮没在古代传说中的神奇力量，总能使他们乐在其中。独立的收入使文物学家能够研究古旧晦涩的文物，或者根据自己的兴趣爱好集中探寻特别的种类。他们通常有着欣赏的眼光、敏锐的头脑，和讽刺无知、自大、贪婪者的愚蠢时尖酸刻薄的幽默。
A12: 10 | B12: 古董商 | D12: 30 | E12: 50 | F12: 教育×4 | G12: =EDU*4 -> 220 | H12: 会计，估价，汽车驾驶，两项社交技能（取悦、话术、恐吓、说服），历史，图书馆，导航。 | L12: 本地的历史学家，其他古董商，可能还包括赝造师。 | N12: 古董商通常自己开店，从自己所在的地方转卖物品，或继续扩展业务范围，通过倒卖物品到城市商店赚取利润。
A13: 11 | B13: 考古学家（原作向） | D13: 10 | E13: 40 | F13: 教育×4 | G13: =EDU*4 -> 220 | H13: 估价，考古，历史，外语，图书馆，侦查，机械维修，导航或科学（任一：如化学、物理、地理等）。 | I13: 自定义职业属性 | L13: 赞助人，博物馆，大学。 | N13: 考古学家研究探索历史的痕迹。主要来说，是对人类历史相关的物质数据进行各种鉴识、检查、分析。这项工作包含辛苦细致的研究，更不必提情愿亲自下斗铲土的决心。 在1920 年代，成功的考古学家会被当成著名冒险家与探险家，名利双收。有人运用科学方法考古，不过更多的人对付老祖宗的秘密时喜好暴力破解的办法，甚至祭出炸药，这种碉堡了的办法现代人可是很难看得惯的。
A14: 12 | B14: 建筑师 | D14: 30 | E14: 70 | F14: 教育×4 | G14: =EDU*4 -> 220 | H14: 会计，技艺（技术制图），法律，母语，计算机或图书馆，说服，心理学，科学（数学）。 | I14: 属性名称 | J14: 是否使用 | K14: 使用倍数 | L14: 本地建设和城市规划部门，建筑公司。 | N14: 建筑师掌握设计和营造建筑的知识，不论是个人房屋的改造还是造价数百万美元的地标工程。建筑师与项目经理紧密合作，负责监督施工全程。建筑师必须了解当地的规划法律，健康和安全法规，和基础的公众安全原则。他们既可以在大公司工作，也可以自由工作，这在很大程度上取决于信誉。 在1920 年代，许多人尝试在自家或小办公室单干。不过他们苦心创造的宏伟设计很少能卖得出去。 建筑师也可能专擅某一学科，比如军事建筑或景观工程等。
A15: 13 | B15: 艺术家 | D15: 9 | E15: 50 | F15: 教育×2＋敏捷或意志×2 | G15: =EDU*2+MAX(DEX*2,POW*2) -> 250 | H15: 技艺（任一），历史或自然，一项社交技能（取悦、话术、恐吓、说服），外语，心理学，侦查，任意两项其他个人或时代特长。 | I15: 力量 | J15: √ | K15: =IF(J15="√",2,0) -> 2 | L15: 美术馆，美术批评家，富有的赞助人，广告业者。 | N15: 艺术家在这里可以是画家，雕塑家等等。他们有时沈浸于自己虚幻的想象当中，有时又沐浴在激发热情和理解的灵感之下。不论是否天资优秀，艺术家的内心必须足够强大，这样才能战胜生涯起步时的障碍和挑剔的眼光，并且在自己小有名气以后继续努力。有些艺术家对物质生活是否丰富并不在乎，而有些则有着强烈的创业倾向。
A16: 14 | B16: 精神病院看护 | D16: 8 | E16: 20 | F16: 教育×2＋力量或敏捷×2 | G16: =EDU*2+MAX(STR*2,DEX*2) -> 250 | H16: 闪避，格斗（斗殴），急救，两项社交技能（取悦、话术、恐吓、说服），聆听，心理学，潜行。 | I16: 敏捷 | J16: × | K16: =IF(J16="√",2,0) -> 0 | L16: 医护人员，患者和患者家属。允许接触医疗记录、药品或其他医疗用品。 | N16: 尽管少数富有的人会选择私人疗养院，大多精神病患者最终会被安置到州县设置的定点医院。这些地方除了医生护士以外，还会有一支看护队伍。选聘看护的时候，力量和体格往往比医学知识更被看重。
A17: 15 | B17: 运动员 | D17: 9 | E17: 70 | F17: 教育×2＋力量或敏捷×2 | G17: =EDU*2+MAX(STR*2,DEX*2) -> 250 | H17: 攀爬，跳跃，格斗（斗殴），骑乘，一项社交技能（取悦、话术、恐吓、说服），游泳，投掷，任意一项其他个人或时代特长。 | I17: 体质 | J17: √ | K17: =IF(J17="√",2,0) -> 2 | L17: 体育界，体育专栏作家，其他明星。 | N17: 运动员可能效力于职业的棒球、足球、板球或者篮球队伍。这支队伍也许是大联盟队伍，有着稳定工资，参加的比赛万人瞩目；或者是众多小联盟队伍之一，尤其是在1920 年代的棒球界。这些队伍往往寄于大联盟队伍篱下，各方面都受其管理，工资更是刚够运动员糊口又不至于让他们跳槽的水平。 成功的运动员在自己的专业领域会拥有相当的声誉——现今尤其如此，在世界各地都能看到体育明星和电影明星并肩站在红地毯上的场景。
A18: 16 | B18: 作家（原作向） | D18: 9 | E18: 30 | F18: 教育×4 | G18: =EDU*4 -> 220 | H18: 技艺（文学），历史，图书馆，自然或神秘学，外语，母语，心理学，任意一项其他个人或时代特长。 | I18: 体型 | J18: × | K18: =IF(J18="√",2,0) -> 0 | L18: 出版社，文学评论家，历史学家等。 | N18: 作家不同于记者，他们用文字定义和探讨人们的社会生活，尤其是人们的情感变化。他们的劳动通常孤立而又自我中心：虽然以前写作是个能稳拿工资的行当，但如今只靠写作发大财的人屈指可数。 作家的工作习惯相差极大。通常作家们会花费数月乃至数年的时间调查取材，为新书的创作做准备；然后闭门谢客，投入紧张的创作。 | V18: =IF(K39="是",I40,0) -> 0
A19: 17 | B19: 酒保 | D19: 8 | E19: 25 | F19: 教育×2＋外貌×2 | G19: =EDU*2+APP*2 -> 270 | H19: 会计，两项社交技能（取悦、话术、恐吓、说服），格斗（斗殴），聆听，心理学，侦查，任意一项其他个人或时代特长。 | I19: 外貌 | J19: × | K19: =IF(J19="√",2,0) -> 0 | L19: 常客，可能有犯罪组织。 | N19: 酒保虽然不一定是酒吧的掌柜，却一定是所有客人的朋友。对客人们的好声气，一部分来说是出于他们的职业或者业务，而更多的来说则是达到目的的一种手段。 1920 年代，由于禁酒令的存在，酒保变成了非法的职业；但是遍地开花的黑酒吧又不能没有酒保，结果就是酒保仍然不愁找不到活干。 | V19: =IF(K51="是",I52,0) -> 0
A20: 18 | B20: 猎人 | D20: 20 | E20: 50 | F20: 教育×2＋力量或敏捷×2 | G20: =EDU*2+MAX(STR*2,DEX*2) -> 250 | H20: 射击，聆听或侦查，自然，导航，外语或生存（任一），科学（生物学或植物学），潜行，追踪。 | I20: 智力 | J20: × | K20: =IF(J20="√",2,0) -> 0 | L20: 外国政府官员，狩猎监管人员，前客户(大多很有钱)，黑市商人与黑社会，动物园主。 | N20: 猎人是优秀的追踪者和狩猎者，通常靠为富裕的客户捕猎为生。绝大多数猎人会对地球上某一个部分的情况烂熟于心，比如加拿大森林、非洲草原等等。有些人可能从事盗猎活动，例如为私人收藏家捕捉珍稀动物，或者贩卖受保护的动物和违反道德的动物制品，如兽皮、象牙之类——虽然1920 年代大多数国家这些活动都不算违法。 尽管“王牌猎人”是最典型的类型，不过在加拿大育空的深山老林里打驼鹿和熊为生的土著人也可以算是猎人。 | V20: =IF(K63="是",I64,0) -> 0
A21: 19 | B21: 书商 | D21: 20 | E21: 40 | F21: 教育×4 | G21: =EDU*4 -> 220 | H21: 会计，估价，汽车驾驶，历史，图书馆，母语，外语，一项社交技能（取悦、话术、恐吓、说服）。 | I21: 教育 | J21: √ | K21: =IF(J21="√",IF(SUM(K15:K20,K22:K23)>0,2,4),0) -> 2 | L21: 目录学家、其他书商、图书馆和大学、客户。 | N21: 书商可能拥有自己的店面或者利基(小众)邮购服务，也可能辗转全国甚至海外专门经销书籍。许多人拥有富有的，能提供利润丰厚又稀罕的工作的固定客户。
A22: 20 | B22: 赏金猎人 | D22: 9 | E22: 30 | F22: 教育×2＋力量或敏捷×2 | G22: =EDU*2+MAX(STR*2,DEX*2) -> 250 | H22: 汽车驾驶，电子学或电气维修，格斗或射击，一项社交技能（取悦、话术、恐吓、说服），法律，心理学，追踪，潜行。 | I22: 意志 | J22: × | K22: =IF(J22="√",2,0) -> 0 | L22: 保释业者，本地警察，线人。 | N22: 赏金猎人捉拿罪犯并将他们交给正义去审判。最常见的情况是受保释人的委托去缉捕逃狱者。赏金猎人们为了自己的猎物可以不择手段，几乎不会考虑其他人的正当权益之类细枝末节的东西。 非法闯入、威胁、肢体暴力，都是赏金猎人屡试不爽的秘技。现在这些秘技还包括了电话窃听、黑客操作和其他的秘密监控。 (译注：所谓保释业者。向法院交纳保释金，可以在审判之前免受收押；若被保释者按时接受审判，法院会退还保释金。保释金数额较大，故有保释业者以提供保释金收取手续费为业。)
A23: 21 | B23: 拳击手/摔跤手 | D23: 9 | E23: 60 | F23: 教育×2＋力量×2 | G23: =EDU*2+STR*2 -> 170 | H23: 闪避，格斗（斗殴），恐吓，跳跃，心理学，侦查，任意两项其他个人或时代特长。 | I23: 幸运 | J23: × | K23: =IF(J23="√",2,0) -> 0 | L23: 运动会主办者，记者，犯罪组织，专业训练人员。 | N23: 拳击手和摔跤手各分为职业和业余两种。 职业拳击手和职业摔角手的活动由外部利益支持的贸助人安排，并有合同约束。他们还要进行全日制的工作和训练。 业余拳击的竞赛种类非常丰富，同时它也是那些想成为职业拳手的人的训练场。不过也有业余和准职业的选手靠参加黑市拳击赛谋生，举办这些比赛的通常是本地的黑社会或者是从中渔利的庄家。
A24: 22 | B24: 管家/男仆/女仆 | D24: 9 | E24: 40 | F24: 教育×4 | G24: =EDU*4 -> 220 | H24: 会计或估价，技艺（任一：如烹饪、裁缝、理发），急救，聆听，外语，心理学，侦查，任意一项其他个人或时代特长。 | I24: 计算方式 | V24: 检查有没有被使用
A25: 23 | B25: 神职人员 | D25: 9 | E25: 60 | F25: 教育×4 | G25: =EDU*4 -> 220 | H25: 会计，历史，图书馆，聆听，外语，一项社交技能（取悦、话术、恐吓、说服），心理学，任意一项其他技能。 | I25: 教育+其他属性点数中的最大值(官方) | L25: 教会高层、地方教会、小区领导。 | N25: 神职人员通常担任一个教区的牧师，或是经过分配外出传教，尤其是去国外(见传教士)。 不同的教会工作的侧重点和组织结构各不相同，如天主教会的牧师可能上升到主教、大主教和红衣主教，而一个卫理公会的牧师则会升职到教区主管和主教。 许多神职人员都接受忏悔(不仅仅是天主教)。虽然不能透露忏悔的内容，但是要怎样利用它们就全凭他们自己了。 有些教职人员在教堂接受医生、律师、学者的专业培训。这样的调查员应该选择最符合自己工作的职业模板。 | V25: =IF(K39="是",IF(职业列表!$I$31="社交技能","☯","☆"),"")
A26: 24 | B26: 程序员/电子工程师（现代） | D26: 10 | E26: 70 | F26: 教育×4 | G26: =EDU*4 -> 220 | H26: 计算机，电气维修，电子学、图书馆，科学（数学），侦查，任意两项其他个人或时代特长。 | I26: =F3 -> 教育×2+力量×2或体质×2 | L26: 其他IT 工作者，同事和上司，专业网络小区。 | N26: 计算器程序员通常是设计、编写、测试、调试和维护计算器程序源代码的职业。他们精通从形式逻辑到系统平台(程序运行环境)的各种知识，可能是自由工作者，也可能供职于软件开发部门。 计算器技术人员负责计算器系统和网络的开发和维护工作，经常与其他人员(如项目经理)合作来保证系统的完整稳定和正常提供所需功能。类似的职业还包括数据库管理员、系统管理员、网络管理员、多媒体开发人员、软件工程师、网络管理员等。 | V26: =IF(K51="是",IF(职业列表!$I$43="社交技能","☯","⊙"),"") | W26: 检查有没有
A27: 25 | B27: 黑客/骇客（现代） | D27: 10 | E27: 70 | F27: 教育×4 | G27: =EDU*4 -> 220 | H27: 计算机，电气维修，电子学，图书馆，侦查，一项社交技能（取悦、话术、恐吓、说服），任意两项其他技能。 | L27: 其他IT 工作者，专业网络小区，政治团体，犯罪组织。 | N27: 计算器黑客利用计算器和计算器网络为手段，进行干扰或破坏以达成政治目的(有时被称为“政治黑客”)或获取非法利益。达成目标的手段主要是非法入侵计算器和其他用户帐户，目的则可能包括篡改网页、人肉搜索、盗取身份信息、垃圾邮件炸弹、拒绝服务攻击等等。 | V27: =IF(K63="是",IF(职业列表!$I$55="社交技能","☯","※"),"") | W27: =IF(ISNUMBER(职业列表!$J$3+职业列表!$J$4+职业列表!$J$5+职业列表!$J$6+职业列表!$J$7+职业列表!$J$8+职业列表!$J$9+职业列表!$J$10),0,1) -> 0
A28: 26 | B28: 牛仔 | D28: 9 | E28: 20 | F28: 教育×2＋力量或敏捷×2 | G28: =EDU*2+MAX(STR*2,DEX*2) -> 250 | H28: 闪避，格斗或射击，急救或自然，跳跃，骑乘，生存（任一），投掷，追踪。 | L28: 本地企业家，州农业部门，牛仔比赛主办者，艺人。 | N28: 牛仔在西部的牧区和牧场工作。有些人拥有自己的牧场，更多的则是在各处打工为生。想赚大钱的牛仔会去冒着丢胳膊少腿乃至送命的危险参加牛仔巡回赛，通过旅行获取名誉。 在1920 年代，一些牛仔能在好莱坞找到西部片替身演员和群众演员的工作，例如怀特·厄普就曾为西部电影担任顾问。在现代，有些牧场也对想要体验一把牛仔生活的游客开放。
A29: 27 | B29: 工匠 | D29: 10 | E29: 40 | F29: 教育×2＋敏捷×2 | G29: =EDU*2+DEX*2 -> 250 | H29: 会计，技艺（任二），机械维修，自然，侦查，任意两项其他个人或时代特长。 | I29: =V25&"自定义 X 选 X 技能"&V25 -> 自定义 X 选 X 技能
A30: 28 | B30: 罪犯-刺客 | D30: 30 | E30: 60 | F30: 教育×2＋力量或敏捷×2 | G30: =EDU*2+MAX(STR*2,DEX*2) -> 250 | H30: 乔装，电气维修，格斗，射击，锁匠，机械维修，潜行，心理学。 | I30: 备注 | J30: 技能列表 | K30: 选择几项
A31: 29 | B31: 罪犯-银行劫匪 | D31: 5 | E31: 75 | F31: 教育×2＋力量或敏捷×2 | G31: =EDU*2+MAX(STR*2,DEX*2) -> 250 | H31: 汽车驾驶，电气维修或机械维修，格斗，射击，恐吓，锁匠，操作重型机械，任意一项其他个人或时代特长。 | I31: 社交技能 | J31: 恐吓 | K31: 1
A32: 30 | B32: 罪犯-打手/暴徒 | D32: 5 | E32: 30 | F32: 教育×2＋力量×2 | G32: =EDU*2+STR*2 -> 170 | H32: 汽车驾驶，格斗，射击，两项社交技能（取悦、话术、恐吓、说服），心理学，潜行，侦查。 | I32: 如果名称为 “社交技能” 则符号变为☯ | J32: 说服 | U32: =IF(IFERROR(VLOOKUP("驯兽",$J$3:$K$10,1,FALSE),"%^&@%##@^")="驯兽",1,0) -> 0 | W32: 驯兽 | X32: ☆
A33: 31 | B33: 罪犯-窃贼 | D33: 5 | E33: 40 | F33: 教育×2＋敏捷×2 | G33: =EDU*2+DEX*2 -> 250 | H33: 估价，攀爬，电气维修或机械维修，聆听，锁匠，妙手，潜行，侦查。 | J33: 话术 | U33: =IF(IFERROR(VLOOKUP("驯兽",$J$31:$J$39,1,FALSE),"%^&@%##@^")="驯兽",1,0) -> 0 | V33: =IF(IF(IFERROR(VLOOKUP("驯兽",$J$3:$K$10,1,FALSE),"%^&@%##@^")="驯兽",1,0)+IF(IFERROR(VLOOKUP("驯兽",$J$31:$J$39,1,FALSE),"%^&@%##@^")="驯兽",1,0)+IF(IFERROR(VLOOKUP("驯兽",$J$43:$J$51,1,FALSE),"%^&@%##@^")="驯兽",1,0)+IF(IFERROR(VLOOKUP("驯兽",$J$55:$J$63,1,FALSE),"%^&@%##@^")="驯兽",1,0)=0,0,0) -> 0 | W33: =_xlfn.IFS(IF(IFERROR(VLOOKUP("驯兽",职业列表!$J$3:$K$10,1,FALSE),"%^&@%##@^")="驯兽",1,0)=1,"★",IF(IFERROR(VLOOKUP("驯兽",职业列表!$J$31:$J$39,1,FALSE),"%^&@%##@^")="驯兽",1,0)=1,IF($I$31="社交技能","☯","☆"),IF(IFERROR(VLOOKUP("驯兽",职业列表!$J$43:$J$51,1,FALSE),"%^&@%##@^")="驯兽",1,0)=1,IF($I$43="社交技能","☯","⊙"),IF(IFERROR(VLOOKUP("驯兽",职业列表!$J$55:$J$63,1,FALSE),"%^&@%##@^")="驯兽",1,0)=1,IF($I$55="社交技能","☯","※"),IF(IFERROR(VLOOKUP("驯兽",职业列表!$J$3:$K$10,1,FALSE),"%^&@%##@^")="驯兽",1,0)+IF(IFERROR(VLOOKUP("驯兽",职业列表!$J$31:$J$39,1,FALSE),"%^&@%##@^")="驯兽",1,0)+IF(IFERROR(VLOOKUP("驯兽",职业列表!$J$43:$J$51,1,FALSE),"%^&@%##@^")="驯兽",1,0)+IF(IFERROR(VLOOKUP("驯兽",职业列表!$J$55:$J$63,1,FALSE),"%^&@%##@^")="驯兽",1,0)=0,0) -> 0 | X33: ※
A34: 32 | B34: 罪犯-欺诈师 | D34: 10 | E34: 65 | F34: 教育×2＋外貌×2 | G34: =EDU*2+APP*2 -> 270 | H34: 估价，技艺（表演），法律或外语，聆听，两项社交技能（取悦、话术、恐吓、说服），心理学，妙手。 | J34: 取悦 | U34: =IF(IFERROR(VLOOKUP("驯兽",$J$43:$J$51,1,FALSE),"%^&@%##@^")="驯兽",1,0) -> 0 | X34: ☯
A35: 33 | B35: 罪犯-独行罪犯 | D35: 5 | E35: 65 | F35: 教育×2＋敏捷或外貌×2 | G35: =EDU*2+MAX(DEX*2,APP*2) -> 270 | H35: 技艺（表演）或乔装，估价，一项社交技能（取悦、话术、恐吓、说服），格斗或射击，锁匠或机械维修，潜行，心理学，侦查。 | U35: =IF(IFERROR(VLOOKUP("驯兽",$J$55:$J$63,1,FALSE),"%^&@%##@^")="驯兽",1,0) -> 0 | X35: ⊙
A36: 34 | B36: 罪犯-女飞贼（古典） | D36: 10 | E36: 80 | F36: 教育×2＋外貌×2 | G36: =EDU*2+APP*2 -> 270 | H36: 技艺（任意），两项社交技能（取悦、话术、恐吓、说服），格斗（斗殴）或射击（手枪），汽车驾驶，聆听，潜行，任意一项其他个人或时代特长。
A37: 35 | B37: 罪犯-赃物贩子 | D37: 20 | E37: 40 | F37: 教育×2＋外貌×2 | G37: =EDU*2+APP*2 -> 270 | H37: 会计，估价，技艺（伪造），历史，一项社交技能（取悦、话术、恐吓、说服），图书馆，侦查，任意一项其他技能。
A38: 36 | B38: 罪犯-赝造者 | D38: 20 | E38: 60 | F38: 教育×4 | G38: =EDU*4 -> 220 | H38: 会计，估价，技艺（伪造），历史，图书馆，侦查，妙手，任意一项其他个人或时代特长（如计算机）。 | K38: 是否选用?
A39: 37 | B39: 罪犯-走私者 | D39: 20 | E39: 60 | F39: 教育×2＋外貌或敏捷×2 | G39: =EDU*2+MAX(DEX*2,APP*2) -> 270 | H39: 射击，聆听，导航，一项社交技能（取悦、话术、恐吓、说服），汽车驾驶或驾驶（飞行器或船），心理学，妙手，侦查。 | K39: 否
A40: 38 | B40: 罪犯-混混 | D40: 3 | E40: 10 | F40: 教育×2＋力量或敏捷×2 | G40: =EDU*2+MAX(STR*2,DEX*2) -> 250 | H40: 攀爬，一项社交技能（取悦、话术、恐吓、说服），格斗，射击，跳跃，妙手，潜行，投掷。 | I40: =_xlfn.IFS(附表!P74=0,"",附表!P74=1,附表!O75&附表!Q85,附表!P74=2,附表!O76&附表!Q85,附表!P74=3,附表!O74&附表!Q85) -> 一项社交技能:(恐吓、说服、话术、取悦)
A41: 39 | B41: 教团首领 | D41: 30 | E41: 30 | F41: 教育×4 | G41: =EDU*4 -> 220 | H41: 会计，两项社交技能（取悦、话术、恐吓、说服），神秘学，心理学，侦查，任意其他两项其他个人特长。 | I41: =V26&"自定义 X 选 X 技能"&V26 -> 自定义 X 选 X 技能
A42: 40 | B42: 除魅师（现代） | D42: 20 | E42: 60 | F42: 教育×4 | G42: =EDU*4 -> 220 | H42: 两项社交技能（取悦、话术、恐吓、说服），汽车驾驶，格斗（斗殴）或射击，历史，神秘学，心理学，潜行。※经KP允许 可用催眠替换其中一项。 | I42: 备注 | J42: 技能列表 | K42: 选择几项
A43: 41 | B43: 设计师 | D43: 20 | E43: 60 | F43: 教育×4 | G43: =EDU*4 -> 220 | H43: 会计，技艺（摄影），技艺（任一），计算机或图书馆，机械维修，心理学，侦查，任意一项其他个人特长。
A44: 42 | B44: 业余艺术爱好者（原作向） | D44: 50 | E44: 99 | F44: 教育×2＋外貌×2 | G44: =EDU*2+APP*2 -> 270 | H44: 技艺（任一），射击，外语，骑乘，一项社交技能（取悦、话术、恐吓、说服），任意三项其他个人或时代特长。
A45: 43 | B45: 潜水员 | D45: 9 | E45: 30 | F45: 教育×2＋敏捷×2 | G45: =EDU*2+DEX*2 -> 250 | H45: 潜水，急救，机械维修，驾驶（船），科学（生物），侦查，游泳，任意一项其他个人或时代特长。
A46: 44 | B46: 医生（原作向） | D46: 30 | E46: 80 | F46: 教育×4 | G46: =EDU*4 -> 220 | H46: 急救、医学、外语（拉丁文）、心理学、科学（生物学，制药），任两种其他学术或个人特长。
A47: 45 | B47: 流浪者 | D47: 0 | E47: 5 | F47: 教育×2＋外貌或敏捷或力量×2 | G47: =EDU*2+MAX(DEX*2,APP*2,STR*2) -> 270 | H47: 攀爬，跳跃，聆听，导航，一项社交技能（取悦、话术、恐吓、说服），潜行，任意两项其他个人或时代特长。
A48: 46 | B48: 司机-私人司机 | D48: 10 | E48: 40 | F48: 教育×2＋敏捷×2 | G48: =EDU*2+DEX*2 -> 250 | H48: 汽车驾驶，两项社交技能（取悦、话术、恐吓、说服），聆听，机械维修，导航，侦查，任意一项其他个人或时代特长。
A49: 47 | B49: 司机-司机 | D49: 9 | E49: 20 | F49: 教育×2＋力量或敏捷×2 | G49: =EDU*2+MAX(STR*2,DEX*2) -> 250 | H49: 会计，汽车驾驶，聆听，一项社交技能（取悦、话术、恐吓、说服），机械维修，导航，心理学，任意一项其他个人或时代特长。
A50: 48 | B50: 司机-出租车司机 | D50: 9 | E50: 30 | F50: 教育×2＋敏捷×2 | G50: =EDU*2+DEX*2 -> 250 | H50: 会计，汽车驾驶，电气维修，话术，机械维修，导航，侦查，任意一项其他个人或时代特长。 | K50: 是否选用?
A51: 49 | B51: 编辑 | D51: 10 | E51: 30 | F51: 教育×4 | G51: =EDU*4 -> 220 | H51: 会计，历史，母语，两项社交技能（取悦、话术、恐吓、说服），心理学，侦查，任意一项其他个人或时代特长。 | K51: 否
A52: 50 | B52: 政府官员 | D52: 50 | E52: 90 | F52: 教育×2＋外貌×2 | G52: =EDU*2+APP*2 -> 270 | H52: 取悦，历史，恐吓，话术，聆听，母语，说服，心理学。 | I52: =_xlfn.IFS(附表!P86=0,"",附表!P86=1,附表!O87&附表!Q97,附表!P86=2,附表!O88&附表!Q97,附表!P86=3,附表!O86&附表!Q97)
A53: 51 | B53: 工程师 | D53: 30 | E53: 60 | F53: 教育×4 | G53: =EDU*4 -> 220 | H53: 技艺（技术制图），电气维修，图书馆，机械维修，操作重型机械，科学（工程学，物理），任意一项其他个人或时代特长。 | I53: =V27&"自定义 X 选 X 技能"&V27 -> 自定义 X 选 X 技能
A54: 52 | B54: 艺人 | D54: 9 | E54: 70 | F54: 教育×2＋外貌×2 | G54: =EDU*2+APP*2 -> 270 | H54: 技艺（表演类，如表演、演唱、喜剧等），乔装，两项社交技能（取悦、话术、恐吓、说服），聆听，心理学，任意两项其他个人或时代特长。 | I54: 备注 | J54: 技能列表 | K54: 选择几项
A55: 53 | B55: 探险家（古典） | D55: 55 | E55: 80 | F55: 教育×2＋外貌或敏捷或力量×2 | G55: =EDU*2+MAX(DEX*2,APP*2,STR*2) -> 270 | H55: 攀爬或游泳，射击，历史，跳跃，自然，导航，外语，生存。
A56: 54 | B56: 农民 | D56: 9 | E56: 30 | F56: 教育×2＋力量或敏捷×2 | G56: =EDU*2+MAX(STR*2,DEX*2) -> 250 | H56: 技艺（耕作），汽车驾驶（或运货马车），一项社交技能（取悦、话术、恐吓、说服），机械维修，自然，操作重型机械，追踪，任意一项其他个人或时代特长
A57: 55 | B57: 联邦探员 | D57: 20 | E57: 40 | F57: 教育×4 | G57: =EDU*4 -> 220 | H57: 汽车驾驶，格斗（斗殴），射击，法律，说服，潜行，侦查，任意一项其他个人或时代特长。
A58: 56 | B58: 消防员 | D58: 9 | E58: 30 | F58: 教育×2＋力量或敏捷×2 | G58: =EDU*2+MAX(STR*2,DEX*2) -> 250 | H58: 攀爬，闪避，汽车驾驶，急救，跳跃，机械维修，操作重型机械，投掷。
A59: 57 | B59: 驻外记者 | D59: 10 | E59: 40 | F59: 教育×4 | G59: =EDU*4 -> 220 | H59: 历史，外语，母语，聆听，两项社交技能（取悦、话术、恐吓、说服），心理学，任意一项其他个人或时代特长。
A60: 58 | B60: 法医 | D60: 40 | E60: 60 | F60: 教育×4 | G60: =EDU*4 -> 220 | H60: 外语（拉丁文），图书馆，医学，说服，科学（生物学，鉴证，制药），侦查。
A61: 59 | B61: 赌徒 | D61: 8 | E61: 50 | F61: 教育×2＋外貌或敏捷×2 | G61: =EDU*2+MAX(DEX*2,APP*2) -> 270 | H61: 会计，技艺（表演），两项社交技能（取悦、话术、恐吓、说服），聆听，心理学，妙手，侦查。
A62: 60 | B62: 黑帮-黑帮老大 | D62: 60 | E62: 95 | F62: 教育×2＋外貌×2 | G62: =EDU*2+APP*2 -> 270 | H62: 格斗，射击，法律，聆听，两项社交技能（取悦、话术、恐吓、说服），心理学，侦查。 | K62: 是否选用?
A63: 61 | B63: 黑帮-马仔 | D63: 9 | E63: 20 | F63: 教育×2＋力量或敏捷×2 | G63: =EDU*2+MAX(STR*2,DEX*2) -> 250 | H63: 汽车驾驶，格斗，射击，两项社交技能（取悦、话术、恐吓、说服），心理学，任意两项其他个人或时代特长。 | K63: 否
A64: 62 | B64: 绅士/淑女 | D64: 40 | E64: 90 | F64: 教育×2＋外貌×2 | G64: =EDU*2+APP*2 -> 270 | H64: 技艺（任一），两项社交技能（取悦、话术、恐吓、说服），射击（步枪/霰弹枪），历史，外语（任一），导航，骑乘。 | I64: =_xlfn.IFS(附表!P98=0,"",附表!P98=1,附表!O99&附表!Q109,附表!P98=2,附表!O100&附表!Q109,附表!P98=3,附表!O98&附表!Q109)
A65: 63 | B65: 游民 | D65: 0 | E65: 5 | F65: 教育×2＋外貌或敏捷×2 | G65: =EDU*2+MAX(DEX*2,APP*2) -> 270 | H65: 技艺（任一），攀爬，跳跃，聆听，锁匠或妙手，导航，潜行，任意一项其他个人或时代特长。 | L65: 其他游民，少数友好的铁路员工，许多城镇里的好心人。 | N65: 游民只有少数的人愿意去当,虽然失业的人、 醉倒在阴沟里的醉鬼到处都是。和流浪者只会在 必需时才工作不同,游民的工作本身就是流浪。 他们不断地坐火车旅行,从一个城市辗转到 另一个城市,他们是身无分文的诗人、漂泊者, 铁路上的探索者、冒险者和盗贼。但是铁路上的生活一样充满危险。且不说穷困潦倒、无家可归, 还要面对来自警察、周围居民和铁路员工的敌意。另外在深夜中跳车并不是一件容易的事,在跳车的时候被车厢夹断过手脚的人可是不可胜数。
A66: 64 | B66: 勤杂护工 | D66: 6 | E66: 15 | F66: 教育×2＋力量×2 | G66: =EDU*2+STR*2 -> 170 | H66: 电气维修，一项社交技能（取悦、话术、恐吓、说服），格斗（斗殴），急救，聆听，机械维修，心理学，潜行。 | L66: 其他医疗人员，病人。允许接触医疗记录、药品等等。 | N66: 勤杂护工在医院的工作包括倒垃圾、打扫房间、运送病人,还有一些其他乱七八糟的工作。总之对他们的要求不比对看门人多多少。
A67: 65 | B67: 记者(原作向)-调查记者 | D67: 9 | E67: 30 | F67: 教育×4 | G67: =EDU*4 -> 220 | H67: 技艺（艺术或摄影），一项社交技能（取悦、话术、恐吓、说服），历史，图书馆，母语，心理学，任意两项其他个人或时代特长。 | L67: 新闻界，政治家，街头罪犯和执法机构。 | N67: 记者用文字对当天的新闻事件进行报导与评 论,一天之内就要完成一个作家一周的工作量。他们通常为报纸、杂志、广播电台、电视台或者新闻网站撰稿。 优秀的调查记者在报导事件的同时,即使面对丑恶,也能保持自身的清廉正直。恶心的记者则被现实所压倒,最终丧失自己的节操,肆意操纵文字歪曲真相。
A68: 66 | B68: 记者(原作向)-通讯记者 | D68: 9 | E68: 30 | F68: 教育×4 | G68: =EDU*4 -> 220 | H68: 技艺（表演），历史，聆听，母语，一项社交技能（取悦、话术、恐吓、说服），心理学，潜行，侦查。 | L68: 新闻媒体，政治团体与政府，商界，执法机构，街头罪犯，上流社会。 | N68: 通讯记者则是新闻传媒行业大军中的一员, 不管是自由撰稿或是在报社、杂志社、新闻网站、 通讯社工作。大部分记者从事实地工作,包括走 访见证人、查看记录、收集叙述。有些记者被安 排专门追踪警界、体育界或商界的热点新闻,其他人则是负责社会事件乃至园艺俱乐部之类的事情。 通讯记者都会携带记者证,不过记者证除了 各通讯社(主要是报社)用来识别自己的雇员以 外没有太大的作用。实际上记者的工作内容更像 私家侦探,有时为了获得第一手消息也难免使点嘴上花招。
A69: 67 | B69: 法官 | D69: 50 | E69: 80 | F69: 教育×4 | G69: =EDU*4 -> 220 | H69: 历史，恐吓，法律，图书馆，聆听，母语，说服，心理学。 | L69: 法律界，可能有犯罪组织。 | N69: 法官是主持审判全过程的人,可能单独工作或是和同事组成合议庭。一般是推选或任命制, 工作年限也分定期和终身。有的人是初出茅庐就当了法官,而其余的绝大多数,不论是在联邦最高法院还是遥远西部小镇的法官,其实至少都是经过注册的律师。
A70: 68 | B70: 实验室助理 | D70: 10 | E70: 30 | F70: 教育×4 | G70: =EDU*4 -> 220 | H70: 计算机或图书馆，电气维修，外语，科学（化学和任意两项），侦查，任意一项其他个人特长。 | L70: 大学，科学家，图书馆。 | N70: 实验室助理在科研环境中工作,在首席科学家的监督下进行实验和行政工作。 研究内容可能依首席科学家的研究学科而变 化。但基本都包括取样、测试、记录和分析数据、 调整和进行实验、制备标本和样品、管理实验室的日常工作,和保护工作人员的健康与安全。
A71: 69 | B71: 工人-非熟练工人 | D71: 9 | E71: 30 | F71: 教育×2＋力量或敏捷×2 | G71: =EDU*2+MAX(STR*2,DEX*2) -> 250 | H71: 汽车驾驶，电气维修，格斗，急救，机械维修，操作重型机械，投掷，任意一项其他个人或时代特长。 | L71: 其他工人和行业主管 | N71: 工人这一大类职业包括工厂工人、纺织工人、 码头工人、养路工人、矿工、建筑工人等等。工人分为两种类型:熟练工和非熟练工。普通的工人虽然技术不熟练,但是仍然长于使用电动工具、 起重机和其他工厂设备。
A72: 70 | B72: 工人-伐木工 | D72: 9 | E72: 30 | F72: 教育×2＋力量或敏捷×2 | G72: =EDU*2+MAX(STR*2,DEX*2) -> 250 | H72: 攀爬，闪避，格斗（电锯），急救，跳跃，机械维修，自然或科学（生物学或植物学），投掷。 | L72: 林业工人，野外向导和环境保护者。 | N72: 工人这一大类职业包括工厂工人、纺织工人、 码头工人、养路工人、矿工、建筑工人等等。工人分为两种类型:熟练工和非熟练工。普通的工人虽然技术不熟练,但是仍然长于使用电动工具、 起重机和其他工厂设备。
A73: 71 | B73: 工人-矿工 | D73: 9 | E73: 30 | F73: 教育×2＋力量或敏捷×2 | G73: =EDU*2+MAX(STR*2,DEX*2) -> 250 | H73: 攀爬，科学（地质），跳跃，机械维修，操作重型机械，潜行，侦查，任意一项其他个人或时代特长。 | L73: 工会干部，政治团体。 | N73: 工人这一大类职业包括工厂工人、纺织工人、 码头工人、养路工人、矿工、建筑工人等等。工人分为两种类型:熟练工和非熟练工。普通的工人虽然技术不熟练,但是仍然长于使用电动工具、 起重机和其他工厂设备。
A74: 72 | B74: 律师 | D74: 30 | E74: 80 | F74: 教育×4 | G74: =EDU*4 -> 220 | H74: 会计，法律，图书馆，两项社交技能（取悦、话术、恐吓、说服），心理学，两项其他技能。 | L74: 犯罪组织，资本家，检察官和法官。 | N74: 律师或法律顾问精通他们所在地区的法律，擅长把抽象的法学理论知识联系起来，为客户解决法律方面的疑难，担任辩护代理、法律顾问的工作，为客户提供解决办法。可能受托处理个人案件、接受法院指定，也可能专门为某个富裕客户或公司服务。 在美国，“律师”一词一般只指辩护律师。在英国，“律师”一词则包括高级律师、初级律师还有一些执法机构。 假如碰上好客户的话，律师自己也可以一战成名，少数律师还能以自己在政治经济方面的获益吸引媒体的关注。
A75: 73 | B75: 图书馆管理员（原作向） | D75: 9 | E75: 35 | F75: 教育×4 | G75: =EDU*4 -> 220 | H75: 会计，图书馆，外语，母语，任意四项其他个人特长或专业书籍主题。 | L75: 书商，社会团体，专业研究人员。 | N75: 图书馆管理员在公共机构和图书馆工作，负责管理图书目录和书库，并处理图书借阅等。在现代，图书馆管理员还要负责管理视听数据、电子书库。 一些大公司可能聘用图书馆管理员管理书库，偶尔还会有富有的图书藏家招收他们管理自己的私人藏书。
A76: 74 | B76: 技师 | D76: 9 | E76: 40 | F76: 教育×4 | G76: =EDU*4 -> 220 | H76: 技艺（木工、焊接、管道工等），攀爬，汽车驾驶，电气维修，机械维修，操作重型机械，任意两项其他个人或时代或技术特长。 | L76: 工会成员，其他专业技术人员。 | N76: 技师包括所有需要专业训练和作为学徒或实习生工作经验的职业，例如木工、石工、管道工、电气维修、设备安装工人、机修工人等等这些需要技术资质的职业。通常这些工人有自己的工会组织，会和承包人和雇主争取自己的权益。
A77: 75 | B77: 军官 | D77: 20 | E77: 70 | F77: 教育×2＋力量或敏捷×2 | G77: =EDU*2+MAX(STR*2,DEX*2) -> 250 | H77: 会计，射击，导航，急救，两项社交技能（取悦、话术、恐吓、说服），心理学，任意一项其他个人或时代特长。 | L77: 部队，联邦政府。 | N77: 军官有严格的等级，许多等级还需要高等教育学历。各国武装部队都建立了人才培养系统，其中包括大学教育。在美国，许多大学开设军校生训练项目，可以让学员同时接受文化教育和军事训练。毕业的学员可以授以陆军或海军少尉军衔，并分派到各驻地。他们通常会为国家服役四年，之后可以退役覆员。许多人有专门的任命，作为医生、律师和工程师工作。 寻求军旅生涯的人会为进入西点军校和美国海军军官学校这样的著名军校而努力，拥有这些名校学历很容易得到其他军官的尊敬。离开学校以后，许多军官也会选择接受飞行训练等特殊训练。 富有经验，特别值得提升的士兵会被破例提拔为一级准尉。虽然在名义上位列最末，获得这一军衔所需要的时间和经验意味着他们远比普通的初中级军官更受尊敬。绝大多数军衔是终身荣誉，退役多年的军官仍然可以自称上尉或者将军。
A78: 76 | B78: 传教士 | D78: 0 | E78: 30 | F78: 教育×2＋外貌×2 | G78: =EDU*2+APP*2 -> 270 | H78: 技艺（任一），急救，机械维修，医学，自然，一项社交技能（取悦、话术、恐吓、说服），任意两项其他个人或时代特长。 | L78: 教会阶层，外国官员。 | N78: 传教士云游到世界的各个角落，传播神的旨意，在文明的地方拯救“不幸的原始人”和“迷途的灵魂”。他们可能属于天主教、新教、伊斯兰教或者其他信仰系统，比如后期圣徒教会(摩门教)在欧美就有专门的传道所。 有的传教士只凭自己的意志独立行动，有的则可能有教会以外的组织支持。 基督教、伊斯兰教的传教者，佛教、印度教的法师，在全世界各个时代都能遇到。
A79: 77 | B79: 登山家 | D79: 30 | E79: 60 | F79: 教育×2＋力量或敏捷×2 | G79: =EDU*2+MAX(STR*2,DEX*2) -> 250 | H79: 攀爬，急救，跳跃，聆听，导航，外语，生存（阿尔卑斯或类似），追踪。 | L79: 其他登山者，环境保护者，赞助人，担保人，本地救援队或执法机构，护林员，运动俱乐部。 | N79: 登山家一般都是利用业余时间和假期的运动员，只有少数攀登著名高山的人才会去寻找财力和设备的赞助。 19 世纪登山运动开始兴起，到了1920 年代，所有美洲和阿尔卑斯地区的主要山峰都被一一征服。经过与西藏人的冗长谈判之后，外国登山队终于获准进入喜马拉雅山的高峰地区。作为世界上最后未被征服的高峰，对珠峰的进军经常被电台和报纸报道。不过1921、1922、1924 年的三次远征都没能达到峰顶，还造成了13 人死亡。 到了现代，登山可以是休闲运动或职业选择。如果是后者，则工作内容包括教练、向导、运动员或救生员等。 (译注：1920 年代的登山队都是取道中国境内的北坡，故正是与西藏地方政府进行的商谈。)
A80: 78 | B80: 博物馆管理员 | D80: 10 | E80: 30 | F80: 教育×4 | G80: =EDU*4 -> 220 | H80: 会计，估价，考古，历史，图书馆，神秘学，外语，侦查。 | L80: 本地的大学和学者，出版社，博物馆赞助者。 | N80: 博物馆管理员可能负责大学或其他公共机构的大型设施，也可能负责小一些的博物馆，往往对本地的地质或者其他的内容颇有研究。
A81: 79 | B81: 音乐家 | D81: 9 | E81: 30 | F81: 教育×2＋意志或敏捷×2 | G81: =EDU*2+MAX(POW*2,DEX*2) -> 250 | H81: 技艺（乐器），一项社交技能（取悦、话术、恐吓、说服），聆听，心理学，四项其他技能。 | L81: 俱乐部老板，音乐家协会，犯罪组织，街头罪犯。 | N81: 音乐家可能加入乐团、乐队或者独奏，演奏的乐器则可以是任何你能想象的种类。音乐家想出人头地十分困难，签约发布唱片就更难了。所以绝大多数音乐家都贫穷又无人关注，只靠街头卖艺勉强维持生计。少数幸运儿可以找到固定工作，比如在酒吧、宾馆或者市交响乐团弹钢琴。对更少的人来说，在正确的时间出现在正确的地点，再加上一点点天赋，就能获得巨大的成功和可观的财富。 1920 年代是爵士乐的年代，众多的音乐家在美国各地的大中城市、城镇里的爵士乐队和交响乐队工作。少数音乐家住在芝加哥和纽约之类的大城市并在那里打拼，而大部分的人靠巴士、汽车或者火车过着旅行生活。
A82: 80 | B82: 护士 | D82: 9 | E82: 30 | F82: 教育×4 | G82: =EDU*4 -> 220 | H82: 急救，聆听，医学，一项社交技能（取悦、话术、恐吓、说服），心理学，科学（生物学，化学），侦查。 | L82: 护工，医生，小区工作人员。 | N82: 护士是专业的医疗助理，通常在医院和疗养院之类的地方工作，或者和全科医生一起合作。一般来说，护士会协助健康人或病人进行保健或康复活动(或者临终关怀)，虽然其他人若是有足够的力量、意志或者知识，完全不需要护士帮助的康复也是可能的。
A83: 81 | B83: 神秘学家 | D83: 9 | E83: 65 | F83: 教育×4 | G83: =EDU*4 -> 220 | H83: 人类学，历史，图书馆，一项社交技能（取悦、话术、恐吓、说服），神秘学，外语，科学（天文），任意一项其他个人或时代特长 ※经KP允许 可以包含克苏鲁神话 | L83: 图书馆员，神秘学学会或者同好会，其他神秘学家。 | N83: 神秘学家是钻研深奥秘密和神秘魔法的人。他们对超博物学能力深信不疑，并竭尽所能靠他们的能力去了解这些东西。许多人对不同神秘哲学和魔法理论的知识面都相当广泛，有些甚至相信自己专注研究三十年真的成为了魔法师——到底是真是假就交由KP 来决断了。 需要指出的是，神秘学家熟知的基本上是“表面的魔法”——克苏鲁神话魔法的秘密对他们仍然是未知的，或者不过是古书上描述那些诱人的线索而已。
A84: 82 | B84: 旅行家 | D84: 5 | E84: 20 | F84: 教育×2＋力量或敏捷×2 | G84: =EDU*2+MAX(STR*2,DEX*2) -> 250 | H84: 射击，急救，聆听，自然，导航，侦查，生存（任一），追踪。 | L84: 本地居民，土著，贸易商。 | N84: 旅行家爱好户外，他们一年中大部分时间都呆在户外，并且一出门就是相当长的时间；通常有相当的捕鱼和狩猎技术，能在最恶劣的环境之中幸存下来。擅长的技术可能包括登山、捕鱼、滑雪、皮划艇、攀登和露营。 旅行家可能在国家公园或素质拓展中心做野外向导和护林员，也可能是有其他经济来源能让他们不用工作就能以这种方式生活，说不定还可能是一个隐士，只有在需要的时候才会回到文明社会。
A85: 83 | B85: 超心理学家 | D85: 9 | E85: 30 | F85: 教育×4 | G85: =EDU*4 -> 220 | H85: 人类学，技艺（摄影），历史，图书馆，神秘学，外语，心理学，任意一项其他个人或时代特长。 | L85: 大学，超心理学刊物。 | N85: 超心理学家从不打算欣赏超常现象。相反，他们试图去观察，记录并研究这些实例。被叫做“捉鬼人”的他们利用技术手段来获取某人或某地点的超博物学活动的证据，当然比起收集到实在的证据，更多的时候他们是在揭穿假冒和误认的超常现象。 一些超心理学家专门研究特定的现象，例如超感官、心灵致动、闹鬼等等。 名牌大学是没有超心理学学位的。这个领域成就的评判标准完全是基于个人声誉，所以一般有相近学科学历比如物理学、心理学和医学的人会比较有说服力。 选择研究这个的人往往对不可视的神秘力量抱有相当的同情态度，并希望其他的科学家也能满意地点头肯定。这就表现出了一种既相信又怀疑的奇异的迭加态——恐怕超心理学家自己也难解决这个问题。一个对观察实验证明不感兴趣的人是个神秘学家而不是个科学家。
A86: 84 | B86: 药剂师 | D86: 35 | E86: 75 | F86: 教育×4 | G86: =EDU*4 -> 220 | H86: 会计，急救，外语（拉丁文），图书馆，一项社交技能（取悦、话术、恐吓、说服），心理学，科学（制药，化学）。 | L86: 本地小区，本地医生，医院和病人。能获得各种药品和化学品。 | N86: 药剂师的管理一直以来都比医生更严格。所有的药剂师都要在各州注册，注册的条件则是高中毕业并至少在药学院学习三年。他们可能在医院或者药房工作，也可能自己开药房。
A87: 85 | B87: 摄影师-摄影师 | D87: 9 | E87: 30 | F87: 教育×4 | G87: =EDU*4 -> 220 | H87: 技艺（摄影），一项社交技能（取悦、话术、恐吓、说服），心理学，科学（化学），潜行，侦查，任意两项其他个人或时代特长。 | L87: 广告业，本地客户(包括政治团体和报纸)。 | N87: 摄影师大部分是自由工作者，可能制作广告电影或者在照相馆做肖像拍摄。其他一些摄像师则在报纸、电视和电影产业工作。 摄影作为一种艺术形式已经产生相当长的时间了，精英的摄影师可以从艺术、新闻报道、野生动物保护等多种角度出发创作他们的作品。不管是哪种立意，他们都能获得名誉和报酬。 摄影记者本质上就是拿照相机，为拍摄的照片写配文的记者。在1920 年代，新闻短片走上历史舞台。笨重的35mm 摄像装备走遍全球各地，搜寻有价值的新闻轶事、体育赛事和泳装选美比赛。新闻片制作人员一般分为三类：一类是画面中的记者，另两个人则负责摄像和灯光等等。新闻中的声音则是在新闻稿完成以后在录音棚中录入完成的。
A88: 86 | B88: 摄影师-摄影记者 | D88: 10 | E88: 30 | F88: 教育×4 | G88: =EDU*4 -> 220 | H88: 技艺（摄影），攀爬，一项社交技能（取悦、话术、恐吓、说服），外语，心理学，科学（化学），任意两项其他个人或时代特长。 | L88: 新闻业，电影工作室(1920 年代)，外国政府和官方。 | N88: 摄影师大部分是自由工作者，可能制作广告电影或者在照相馆做肖像拍摄。其他一些摄像师则在报纸、电视和电影产业工作。 摄影作为一种艺术形式已经产生相当长的时间了，精英的摄影师可以从艺术、新闻报道、野生动物保护等多种角度出发创作他们的作品。不管是哪种立意，他们都能获得名誉和报酬。 摄影记者本质上就是拿照相机，为拍摄的照片写配文的记者。在1920 年代，新闻短片走上历史舞台。笨重的35mm 摄像装备走遍全球各地，搜寻有价值的新闻轶事、体育赛事和泳装选美比赛。新闻片制作人员一般分为三类：一类是画面中的记者，另两个人则负责摄像和灯光等等。新闻中的声音则是在新闻稿完成以后在录音棚中录入完成的。
A89: 87 | B89: 飞行员-飞行员 | D89: 20 | E89: 70 | F89: 教育×2＋敏捷×2 | G89: =EDU*2+DEX*2 -> 250 | H89: 电气维修，机械维修，导航，操作重型机械，驾驶（飞行器），科学（天文），任意两项其他个人或时代特长。 | L89: 前部队关系人，乘务员，机械师，机场地勤人员，嘉年华主办者。 | N89: 飞行员可以在美国邮政这样的企业工作，也可以在大大小小的民航公司做飞行人员。 美国1926 年之前没有对飞行员的职业要求，1926 年航空商业法案通过之后才要求有执照。这个时代的多数飞行员从事嘉年华表演、特技飞行表演、乘飞机游玩或是小机场的空中的士等服务。 也有飞行员在部队服现役。许多特技飞行员是在服役期间学会的驾驶飞机，有时仍然会被军队委派任务。
A90: 88 | B90: 飞行员-特技飞行员（古典） | D90: 30 | E90: 60 | F90: 教育×4 | G90: =EDU*4 -> 220 | H90: 会计，电气维修，聆听，机械维修，导航，驾驶（飞行器），侦查，任意一项其他个人或时代特长。 | L90: 前部队关系人，其他飞行员，机场地勤技术人员，商人。 | N90: 特技飞行员在嘉年华工作或者为大胆的消费者进行休闲飞行服务。参加有组织的飞行表演赛，不论是固定路线还是越野赛，往往都可以增加自己的知名度。在1920 年代，好莱坞常常使用特技飞行员，飞机制造商也会录用一些飞行员为新机作测试。许多特技飞行员是在一次大战中掌握的飞行技术，所以许多人仍然在陆海空军或海岸警卫队服役；年轻的飞行员则基本上是在和平时期接受的训练或是自学成才。 参加过一战的王牌飞行员“现在”还活跃在公众视野中的包括：埃迪·里肯巴克，现在在克赖斯勒公司工作；汤米·希区柯克，“现在”是马球赛场的明星；里德·兰迪斯，美国职棒大联盟执行长凯纳索·蒙顿·兰迪斯的儿子。
A91: 89 | B91: 警方(原作向)-警探 | D91: 20 | E91: 50 | F91: 教育×2＋力量或敏捷×2 | G91: =EDU*2+MAX(STR*2,DEX*2) -> 250 | H91: 技艺（表演）或乔装，射击，法律，聆听，一项社交技能（取悦、话术、恐吓、说服），心理学，侦查，一项其他技能。 | L91: 执法机构，街头罪犯，尸检部门，司法部门，犯罪组织。 | N91: 便衣警察的工作是检查犯罪现场、收集证据、询问证人以解决凶杀、盗窃等重大案件。他们在现场办案中往往与穿制服的巡警密切合作。 警探可能指挥他的下属进行详尽的调查，但是很难有机会集中精力对付单独一个事件，在美国他们很可能要同时处理数十乃至上百的案件。警探工作最关键的部分是通过梳理证词、重建现场情况，摒弃伪证，从而收集足够逮捕嫌疑人的证据，进而促成成功的刑事审判。警探和检察官的职责是分开的，这样可以保证证据在审判之前被独立地对待。 尽管现在警探通常会参加警察学校课程并获得学位、参加特殊训练或公务员培训，他们最主要的经验还是来源于担任基层警官或者普通巡警时的工作经历。
A92: 90 | B92: 警方(原作向)-巡警 | D92: 9 | E92: 30 | F92: 教育×2＋力量或敏捷×2 | G92: =EDU*2+MAX(STR*2,DEX*2) -> 250 | H92: 格斗（斗殴），射击，急救，一项社交技能（取悦、话术、恐吓、说服），法律，心理学，侦查和下面的一种个人特长：汽车驾驶或骑乘。 | L92: 执法机构，本地企业与居民，街头罪犯，犯罪组织。 | N92: 巡警属于市、城镇、县治安部门或州、地区的警察机关。他们工作时可能步行、驾驶巡逻车，或者干脆坐办公室。
A93: 91 | B93: 私家侦探 | D93: 9 | E93: 30 | F93: 教育×2＋力量或敏捷×2 | G93: =EDU*2+MAX(STR*2,DEX*2) -> 250 | H93: 技艺（摄影），乔装，法律，图书馆，一项社交技能（取悦、话术、恐吓、说服），心理学，侦查，一项其他个人或时代特长（如计算机、锁匠、格斗、射击）。 | L93: 执法机构，客户。 | N93: 私家侦探通常在警察不出手的地方活跃，包括收集证据为客户准备民事诉讼，追查跑路的配偶或生意伙伴，或者代理刑事案件的私人辩护。他们和任何专业人员一样，私家侦探从不顾及自己的私人情感，只要付钱，不管是有罪还是无罪的一方的委托他们都乐得接受。 私家侦探过去可能在警察队伍里工作，利用以前的业务关系为现在工作谋求优势；然而事实并非总是如此。在许多地方私家侦探必须持证上岗，假如被发现有违法行为，就会撤销执照——侦探生涯也就到此为止。
A94: 92 | B94: 教授（原作向） | D94: 20 | E94: 70 | F94: 教育×4 | G94: =EDU*4 -> 220 | H94: 图书馆，外语，母语，心理学，任意四项其他学术、时代或个人特长。 | L94: 学者，大学，图书馆。 | N94: 教授是受聘于高等院校的学者。大公司也可 能聘请他们以开展学术研究与产品开发。独立的学者也靠开办业余课程作为经济来源。 最重要的一点,这一职业代表了 PhD(博士) 的荣誉称号,意味着可以在世界各地的大学任终身教职。教授的专长是教学和专业研究,往往在自己的专业领域内有着可圈可点的学术成就。
A95: 93 | B95: 淘金客 | D95: 0 | E95: 10 | F95: 教育×2＋力量或敏捷×2 | G95: =EDU*2+MAX(STR*2,DEX*2) -> 250 | H95: 攀爬、急救、历史、机械维修、导航、科学（地质），侦查，任意一项其他个人或时代特长。 | L95: 本地企业和居民。 | N95: 淘金客一直是美国西部的特色,即便在加利福尼亚淘金热和内华达康姆斯塔克发现金银矿的日子早已经过去的现在。他们无休止地在山间漫游,寻找能使自己一夜暴富的矿脉。而且现在发现石油和发现金子一样给力。
A96: 94 | B96: 性工作者 | D96: 5 | E96: 50 | F96: 教育×2＋外貌×2 | G96: =EDU*2+APP*2 -> 270 | H96: 技艺（任一），两项社交技能（取悦、话术、恐吓、说服），闪避，心理学，妙手，潜行，任意一项其他个人或时代特长。 | L96: 街头路人，警察，可能有犯罪组织，私人客户。 | N96: 性工作者根据场合、背景和教养,从超级值钱的应召小姐到牛郎再到站街女都有可能。往往入这一行都是权宜之计,许多人梦想有朝一日能够脱身。少数人能够自己接客,不过绝大多数人 基本都是被只认钱不认人的老鸨和皮条客逼迫着 工作。
A97: 95 | B97: 精神病学家 | D97: 30 | E97: 80 | F97: 教育×4 | G97: =EDU*4 -> 220 | H97: 外语，聆听，医学，说服，精神分析，心理学，科学（生物学，化学）。 | L97: 其他精神疾病领域的专家，医生，可能有法律人士。 | N97: 精神病学家是在现代专门从事精神失常诊断和治疗的医生。精神病学家掌握着精神药理学的 治疗方法,使用精神类药物的资质,还能整理脑电图并对其进行计算器分析。 在十九二十世纪之交,精神分析理论刚刚产 生,试图解释一些现在认为实际上是生物学范畴的现象。所以,精神分析学家们努力寻求获得自 己的医疗证书。与此同时,各种不同的精神失常诊断与治疗理论开始起步。到 1930 年代,任何一个医生都可以以精神病学家的身份进入美国医学协会名录中了。
A98: 96 | B98: 心理学家/精神分析学家 | D98: 10 | E98: 40 | F98: 教育×4 | G98: =EDU*4 -> 220 | H98: 会计，图书馆，聆听，说服，精神分析，心理学，任意两项其他学术、个人或时代特长。 | L98: 心理学家团体，病人。 | N98: 心理学家虽然也经常被叫做心理治疗师和心理咨询师,不过这些工作都只是心理学的分支。其他的还有为企业和政府提供顾问的组织管理心 理学家,进行研究并在学校教授心理学的学术型心理学家等等。 临床心理学家可能实际接触病人,并且运用各种可能的心理治疗方法。注意心理学家和专业的精神病学家的区别,后者本质上还是医生。 在1920 年代,对人类行为的研究还是一个新兴的领域,主要的理论还是弗洛伊德心理学。
A99: 97 | B99: 研究员 | D99: 9 | E99: 30 | F99: 教育×4 | G99: =EDU*4 -> 220 | H99: 历史，图书馆，一项社交技能（取悦、话术、恐吓、说服），外语，侦查，任意三项其他学术领域。 | L99: 学者和其他学术界人士，大型企业，外国政府和个人。 | N99: 学术界的研究课题不计其数,尤其是在天文 学、物理学和其他理论领域。私人或企业也雇用 了成千上万的研究员,重点在化学、制药和工程 领域。石油公司则会聘用专业的地质学家,不一 而足。研究员大部分的时间都在室内工作和写作, 不过有的则会经常外出考察。 考察研究员通常经验丰富,思想独立又足智 多谋,可能受雇于私人或者为大学进行学术研究。 石油公司会派出地质学家探索潜在的油田, 人类学家则是调查地球被人遗忘角落的原始部落, 考古学家则竭数年之力挖掘沙漠丛林之中的宝藏, 还要和工人与地方政府打交道。
A100: 98 | B100: 海员-军舰海员 | D100: 9 | E100: 30 | F100: 教育×4 | G100: =EDU*4 -> 220 | H100: 电工或机械维修，格斗，射击，急救，导航，驾驶（船），生存（海上），游泳。 | L100: 军队，退伍军人协会。 | N100: 新入伍的海员像陆军的同行一样,开始时需 要接受基本的训练。这之后他们获得军衔,并被 分配到各镇守府。虽然很多海员担任像水手长副手和司炉工(管理引擎)这样的传统角色,但是也有很多经过专门训练的机械师、无线电操作员、通风管理员之类。海员们最高的军衔是士官长, 达到了这个军衔连高级将领都要礼让三分。在美国,海员通常要服四年的现役和后两年的后备役, 即在国家发布动员令时有应召服役的义务。
...

Sheet 技能注释
A2: 需要注意的是：艺术与手艺是试做部分，这些技能的注释仅供参考。 玩家也可以添加更多手艺，比如：游戏，木工，油漆工，铁匠之类的。 具体作用和KP交流好左边是自定义表,在下面写好改技能的备注(用法) | B2: 技能查询 | N2: 技能成功等级与注释
B3: 技能名称 | E3: 基础成功率 | G3: 特殊适用 | I3: 成功难度等级取决于 | N3: 成功率 | O3: 解释
B4: 会计 | E4: =IF($B4=附表!B213,"【←下拉框】",VLOOKUP($B4,附表!B95:K212,2,FALSE)) -> 5% | G4: =IF($B4=附表!B213,"",VLOOKUP($B4,附表!B95:K212,3,FALSE)) -> —— | I4: =IF($B4=附表!B213,"",VLOOKUP($B4,附表!B95:K212,4,FALSE)) -> 如果有人想要隐瞒什么，那么难度等级将会取决于进行隐藏的人的会计技能。 | N4: 0 | O4: 并不知晓有这种学问或技能的存在。
N6: 1-5 | O6: 完完全全的门外汉，仅仅是知道有这种技能而已
N8: 5-10 | O8: 经过了最基础的了解，可以说出一两个专业名词，但是实际操作几乎不可能。
B10: 孤注一掷示例 | I10: 普通难度 | K10: 困难难度 | N10: 11-19 | O10: 自行摸索的自学或经过一段不认真的教育（指学习与教课双方）之后获取的知识。
B11: =IF($B4=附表!B213,"",VLOOKUP($B4,附表!B95:K212,8,FALSE)) -> · 花费更多的时间来阅览文档 · 拜访银行或者企业来确认自己的发现 · 复核里面的账目和数据 | I11: =IF($B4=附表!B213,"",VLOOKUP($B4,附表!B95:K212,6,FALSE)) -> 详尽以及良好整理的会计账簿。 | K11: =IF($B4=附表!B213,"",VLOOKUP($B4,附表!B95:K212,7,FALSE)) -> 无序或者残缺的会计账簿。
N12: 20-25 | O12: 非常有天赋或非常努力的人可以在短时间内达到这种程度，再或者一些知识渊博的人也能得到这个级别的知识。
N14: 26-39 | O14: 一定时间内经过了系统式的教育或名师指导。对这方面拥有了一个初步的了解，专业性上比普通人都要强， 但是实际操作依旧有些困难。
N17: 40-49 | O17: 对这方面拥有很高的热情，但基础知识或学习时间依旧没有达到标准。 这阶段很可能是一个瓶颈期
N20: 50 | O20: 已经可以以此为生但依旧不是非常熟练 如果以该技能为职业至少要达到50
N23: 51-70 | O23: 不断精进的技术，虽然放到同行里一抓一大把，但是基本上已经可以独当一面了。
B24: 孤注一掷失败的范例结果 | H24: 疯狂调查员孤注一掷失败的范例结果
B25: =IF($B4=附表!B213,"",VLOOKUP($B4,附表!B95:K212,9,FALSE)) -> · 调查员与其他人之间的讨论让敌对势力对调查员的意图起了警觉 · 账簿最重要的一部分被摧毁或者丢失了（可能调查员因为疲劳将咖啡洒出在了上面）。 | H25: =IF($B4=附表!B213,"",VLOOKUP($B4,附表!B95:K212,10,FALSE)) -> 他可能会被发现他把部分的账簿吃下了肚。 | N25: 71-80 | O25: 在一定范围内你具有了比较高的知名度，虽然不至于成为权威但是已经是一个很好的咨询对象了。 对于这个技能你无论怎么操作都非常得心应手（除了更加精进的钻研自己 的技术或说服流氓同行）
N28: 81-90 | O28: 该专业的权威，即使你仅靠这方面的技能也能得到很多人的重视与保护。
N30: 91-99 | O30: 伟人级别，如果你有时间有精力，绝对可以创造一个不可磨灭的瑰宝留给后世纪子孙。
N32: 100 | O32: 在当代，和这方面有关的事情你已经无所不知了，如果出现了一种你不认识的东西，这种东西就会被称为：新大陆
N34: 101-110 | O34: 对于这方面拥有全新的解释或发现，并且已经初步了解了这些新知识。
N36: 111-140 | O36: 超越本时代几乎所有人，能和你平起平坐的应该不会超过十个人。拥有着大量的发明创造， 甚至在之后很长一段时间内都会不分国界的被世纪人记住
B39: 技能解释 | N39: 150 | O39: 进入了超时代的知识领域，即使穿越也可以成为该领域的专家 从这个阶段开始和其相关的领域知识也会一并提高，并且可能是超时代的
B40: =IF($B4=附表!B213,"",VLOOKUP($B4,附表!B95:K212,5,FALSE)) -> · 使你理解会计工作的流程以及一个企业或者个人的金融职务。 · 通过检查账簿，你可以发现做假账的员工，对资金的偷偷挪用，对行贿或者敲诈的款项支付，以及经济状况是否比表面陈述的更好或者更差。 · 通过仔细检查旧账户，你可以了解过去的资金的得与失（谷物，奴隶贸易，威士忌酒的运营等）以及这些资金是付给了谁以及为了什么款项而支付。
N43: 500 | O43: 在这方面上几乎所有知识的获取，已经没有任何成长的必要了，再获取的知识也不过是一些鸡毛蒜皮的小事
O45: 如果你发现了难以理解的翻译、不完整的显示、或是其他各种问题请联系作者（在更新说明页有联系方式）
B64: 技能可选规则
B68: 专业技能：可以转移的技能优势
B70: 艺术和手艺 | O70: 语言
B72: 当一名角色的某些类似的技能与学问的成功率 提升到50%以上的时候： | H72: 当一名角色的某些类似的技能与学问的成功率 提升到90%以上的时候： | O72: 当一名角色将一种非母语语言的成功率 提升到了50%以上的时候： | U72: 当一名角色将一种非母语语言的成功率 提升到了90%以上的时候：
B75: 其他所有类似技能都会提升10% 但是不能超过50% | H75: 其他所有类似技能又会提升10% 但是不能超过90% | O75: 其他所有同语系的语言都会提升10% 但是不能超过50% | U75: 其他所有同语系的语言都会提升10% 但是不能超过90%
B77: 例如：作画成功率上升到50%的时候 书法、伪造、技术制图之类的的成功率都会提升10% 但假如技术制图的成功率是70%，那么它将则不会成长 | O77: 例如：德语成功率上升到50%的时候 在印欧语系内的英语、法语、意大利语、西班牙等的成功率都会提升10% 但假如英语的成功率是70%，那么英语则不会成长
B81: 格斗、生存、驾驶、社交类、治疗类、维修类、科学、神话等 只要是KP认为有关联的技能都可以运用此规则
N82: 这是一张展示世纪界语系的地图（来自维基百科2018）
B84: 当然这属于一个可选规则，kp也可以不选择此规则（看看我们的KP是善良还是邪恶呢~）
B85: 另外，上述的10%是直接在现有值里增长10点，不是现有的成功率乘以0.1
B94: 可选规则：给技能等级安个保险
B96: 如果你担心原版规则的职业技能最高可以达到90%这点会影响游戏的话。 你可以要求PL在车卡的时候不能将技能的成功率点到XX%以上。 当然兴趣技能也可以运用此规则。
B102: 例如：KP在跑团之前放公告或提醒大家“这次跑团的技能上限是70/60” 这里的70/60，就是职业技能成功率最高70% 兴趣技能成功率最高可以达到60%
B113: 游戏系统少见规则
B117: 幕间成长：90%或更多的技能值 | G117: 对抗检定平手 | L117: 超越人体极限：多调查员协作检定 | U117: 调查员幕间成长（超越100）
B119: 于幕间成长中： 若一位调查员有技能达到了 90%或更高，为他的当前SAN值增加 2D6 。 这一奖励表示经过磨练从精通一项技能中获得的自信。 | G119: 若在同属性或同技能的对抗中双方的成功等级相同： 技能（或属性）更高的一方获胜 若仍然相同则双方重新再骰一次 对抗不能孤注一掷 | L119: 调查员们只是人类，所以物理上存在能力的极限。 当对手拥有90或更高的属性时难度等级将为极难。 超过100+的技能和属性对于调查员来说是无法对抗的。比如一个人类不可能在力量方面上对抗一个力量220的黑山羊幼崽。 | U119: 除了意志和体型，人类的属性最大值都被定为了99，但是技能和属性不一样。 技能不仅能够更加精进更加熟练，而且用的越多越容易更熟练，而且还可以超越时代的熟练。 当你获得了99点的技能，不要担心ta会就此止步。 在幕间成长投出大于95的数字就可以为技能增加1D10的成功率，哪怕这个技能的成功率已经10000了也可以成长
L124: 但是人类之所以是人类就是因为他们能做到不可能的事情
L125: 将很多调查员的力量揉到一起，他们就能做到一个人类做不到的事情，在游戏中为以下表现。
L127: 这是一只黑山羊幼崽 （STR 220） | P127: 左上人类 （STR 50） | R127: 右上人类 （STR 70）
P129: 肥宅人类 （STR 20） | R129: 大熊人类 （STR 90）
L131: 公式：强大的存在-（人类①+人类②+人类③......）=x<100
L132: 例1： | M132: 左上人类（STR50）面对着一个黑山羊幼崽，他想要和他掰手腕，但是很明显这会把自己掰了。于是他叫来了右上人类（STR70），他们两个人（STR50+70=120）用尽力气和黑山羊幼崽对抗。 220-（50+70）=100 这样就不是不可能了，虽然是极难难度但是已经从不可能变成可能了。于是右下人类骰出了骰子 D100=70（普通成功）
L140: 例2： | M140: 这两个人类很简单的就被掰傻了 但是他们不甘心，依然希望赢过黑山羊幼崽 正好一个STR20的肥宅人类路过。 于是他们就把肥宅人类当成朋友（消耗道具）用了。 220-（50+70+20）=80 这里力量最大的还是右上人类（STR 70） 80不在他的成功范围内但是已经低于90了于是就是困难难度 D100=100（大失败）
L149: 例3： | M149: 很可惜。。我们刚刚失去了肥宅 但是幸运的是天降大熊，有了他的帮助我们一定能成功的 220-（50+70+90）=10 终于，常规难度出现了，大熊人类是这里力量最大的 也就是说他骰出小于等于90的任何数字都可以成功！ D100=100（大失败）
T156: 唉

Sheet 附表
AJ1: 自定义职业属性
B2: 移动力计算 | S2: 自定义职业
A3: 护甲表减值 是否开启 | B3: 护甲表减值 | C3: 年龄减值 | D3: 力量-体型 | E3: =G14-I14 -> -25 | G3: 技能雷达表 | H3: 值 | I3: 总数 | J3: 百分比 | N3: 伤害加值与体格 | S3: 属性名称 | T3: shiyong | U3: 使用倍数 | W3: 显示 | X3: 查看之后 | Y3: 是否为空 | Z3: 计算 | AA3: 出
D4: 敏捷-体型 | E4: =J14-I14 -> 15 | G4: 调查 | H4: 交涉 | I4: 战斗 | J4: 特技 | K4: 支援 | L4: 学问 | N4: 力量+体型 | S4: ="力量×"&U4 -> 力量×2 | T4: =职业列表!J15 -> √ | U4: =职业列表!K15 -> 2 | W4: =IF(U10>0,S10,"") -> 教育×2 | Y4: =IF(W4="",1,0) -> 0 | Z4: =G14*U4 -> 60 | AA4: =IF(Y5+Y6+Y7+Y8+Y9+Y10+Y11+Y12=8,"",IF(U10=0,"","+")) -> + | AH4: =IF(U4=0,"",G14*U4) -> 60 | AJ4: =IF(U4=0,"",G14*U4) -> 60
A5: =IF(人物卡!AI12="开",1,IF(人物卡!AI12="关",0)) -> 0 | B5: =IF(人物卡!AN12=0,"0",VLOOKUP(人物卡!AN12,'防具表 载具表'!B2:I101,3,FALSE)) | C5: =IF(人物卡!E4<40,0,INT((人物卡!E4/10)-3)) -> 0 | D5: 力量大小 | E5: =IF(E3>0,"1",IF(E3=0,"0",IF(E3<0,"-1"))) -> -1 | G5: =AVERAGE(人物卡!AA7+人物卡!R17+人物卡!R18+人物卡!R19+人物卡!R20+人物卡!R26+人物卡!R28+人物卡!R47+人物卡!R48+人物卡!R49+人物卡!AN18+人物卡!AN19+人物卡!AN23+人物卡!AN25+人物卡!AN29+人物卡!AN30+人物卡!AN36+人物卡!AN41+人物卡!AN45-122) -> 235 | H5: =AVERAGE(人物卡!AA5+人物卡!R18+人物卡!R19+人物卡!R24+人物卡!R27+人物卡!R29+人物卡!R34+人物卡!R45+人物卡!R47+人物卡!R48+人物卡!R49+人物卡!R50+人物卡!AN17+人物卡!AN27+人物卡!AN29+人物卡!AN30+人物卡!AN36+人物卡!AN41+人物卡!AN45-111-人物卡!J50) -> 325 | I5: =AVERAGE((人物卡!U3+人物卡!U7)/2+人物卡!U5+人物卡!AA3+人物卡!R30+人物卡!R35+人物卡!R36+人物卡!R37+人物卡!R39+人物卡!R40+人物卡!R41+人物卡!R45+人物卡!R46+人物卡!AN19+人物卡!AN26+人物卡!AN30+人物卡!AN31+人物卡!AN36+人物卡!AN37+人物卡!AN40+人物卡!AN42+人物卡!AN44+人物卡!AN46+人物卡!AN47-189-人物卡!J30) -> 382.5 | J5: =AVERAGE(人物卡!AA3+人物卡!R20+人物卡!R21+人物卡!R22+人物卡!R23+人物卡!R25+人物卡!R29+人物卡!R31+人物卡!R32+人物卡!R46+人物卡!AN20+人物卡!AN21+人物卡!AN22+人物卡!AN24+人物卡!AN26+人物卡!AN28+人物卡!AN31+人物卡!AN35+人物卡!AN37+人物卡!AN38+人物卡!AN39+人物卡!AN40+人物卡!AN41+人物卡!AN42+人物卡!AN43+人物卡!AN44+人物卡!AN46+人物卡!AN47-219) -> 180 | K5: =AVERAGE(人物卡!R43+人物卡!AN22+人物卡!AN29+人物卡!R31+人物卡!AN28+人物卡!AN31+人物卡!AN24+人物卡!R27+人物卡!R18+人物卡!AN42+人物卡!AN46+人物卡!AN47-76) -> 20 | L5: =AVERAGE(人物卡!AG5+人物卡!AA7+人物卡!R17+人物卡!R18+人物卡!R26+人物卡!R28+人物卡!R33+人物卡!R44+人物卡!R47+人物卡!R48+人物卡!R49+人物卡!R50-人物卡!J50+人物卡!AN17+人物卡!AN18+人物卡!AN22+人物卡!AN23+人物卡!AN25+人物卡!AN29+人物卡!AN30+人物卡!AN32+人物卡!AN33+人物卡!AN34+人物卡!AN45-76) -> 185 | N5: =G14+I14 -> 85 | S5: ="敏捷×"&U5 -> 敏捷×0 | T5: =职业列表!J16 -> × | U5: =职业列表!K16 -> 0 | W5: =IF(U4>0,S4,"") -> 力量×2 | X5: =IF(Y5=0,IF(AB6=1,"或",IF(AB7+AB8=1,"+","")),"") -> 或 | Y5: =IF(W5="",1,0) -> 0 | Z5: =J14*U5 -> 0 | AA5: =IF(Y6+Y7+Y8+Y9+Y10+Y11+Y12=7,"",X5) -> 或 | AB5: =W4&AA4&W5&AA5&W6&AA6&W7&AA7&W8&AA8&W9&AA9&W10&AA10&W11&AA11&W12 -> 教育×2+力量×2或体质×2 | AF5: =SUM(AF6:AF10) -> 210 | AH5: =IF(U5=0,"",J14*U5) | AJ5: =IF(U5=0,"",J14*U5)
B6: 检测是否为数字 | C6: 最终年龄减值 | D6: 敏捷大小 | E6: =IF(E4>0,"1",IF(E4=0,"0",IF(E4<0,"-1"))) -> 1 | J6: =G5+H5+I5+J5+K5+L5 -> 1327.5 | N6: 非八十整数体格 | O6: 减485后八十的倍数 | P6: 最终体格出目 | S6: ="体质×"&U6 -> 体质×2 | T6: =职业列表!J17 -> √ | U6: =职业列表!K17 -> 2 | W6: =IF(U5>0,S5,"") | X6: =IF(Y6=0,IF(AB6=1,"或",IF(AB7+AB8=1,"+","")),"") | Y6: =IF(W6="",1,0) -> 1 | Z6: =H14*U6 -> 100 | AA6: =IF(Y7+Y8+Y9+Y10+Y11+Y12=6,"",X6) | AB6: =IF(AC6=职业列表!I25,1,0) -> 1 | AC6: 教育+其他属性点数中的最大值(官方) | AF6: =IF(AB6=1,AI10+MAX(AH4:AH12),0) -> 210 | AH6: =IF(U6=0,"",H14*U6) -> 100 | AJ6: =IF(U6=0,"",H14*U6) -> 100
B7: =ISNUMBER(B5) -> FALSE | C7: =IF(ISBLANK(人物卡!E4),0,IF(人物卡!E4>=0,C5,0)) -> 0 | D7: 总值 | E7: =E6+E5 -> 0 | G7: 调查 | H7: 交涉 | I7: 战斗 | J7: 特技 | K7: 支援 | L7: 学问 | N7: =IF(N5<=1,"0",IF(N5<=64,"-2",IF(N5<=84,"-1",IF(N5<=124,"0",IF(N5<=164,"1",IF(N5<=204,"2",IF(N5<=284,"3",IF(N5>284,"4","0")))))))) -> 0 | O7: =INT((N5-285)/80) -> -3 | P7: =IF(O7>=0,O7+N7,N7) -> 0 | S7: ="体型×"&U7 -> 体型×0 | T7: =职业列表!J18 -> × | U7: =职业列表!K18 -> 0 | W7: =IF(U6>0,S6,"") -> 体质×2 | X7: =IF(Y7=0,IF(AB6=1,"或",IF(AB7+AB8=1,"+","")),"") -> 或 | Y7: =IF(W7="",1,0) -> 0 | Z7: =I14*U7 -> 0 | AA7: =IF(Y8+Y9+Y10+Y11+Y12=5,"",X7) | AB7: =IF(AC7=职业列表!I25,1,0) -> 0 | AC7: 教育+其他属性点数中的最小值 | AF7: =IF(AB7=1,AI10+MIN(AH4:AH12),0) -> 0 | AH7: =IF(U7=0,"",I14*U7) | AJ7: =IF(U7=0,"",I14*U7)
B8: 护甲表最终减值 | C8: =IF(B7=FALSE,"0",IF(A5=1,B5,0)) -> 0 | D8: 属性最终值 | E8: =IF(E7=2,"1",IF(E7=-2,"-1",0)) -> 0 | G8: =G5/J6 -> 0.17702448 | H8: =H5/J6 -> 0.24482109 | I8: =I5/J6 -> 0.28813559 | J8: =J5/J6 -> 0.13559322 | K8: =K5/J6 -> 0.015065913 | L8: =L5/J6 -> 0.1393597 | N8: 小于1D6的话 | O8: 超过1d6的话 | P8: 最终伤害加值出目 | S8: ="外貌×"&U8 -> 外貌×0 | T8: =职业列表!J19 -> × | U8: =职业列表!K19 -> 0 | W8: =IF(U7>0,S7,"") | X8: =IF(Y8=0,IF(AB6=1,"或",IF(AB7+AB8=1,"+","")),"") | Y8: =IF(W8="",1,0) -> 1 | Z8: =K14*U8 -> 0 | AA8: =IF(Y9+Y10+Y11+Y12=4,"",X8) | AB8: =IF(AC8=职业列表!I25,1,0) -> 0 | AC8: 最高的属性点+其他属性的最大值 | AF8: =IF(AB8=1,MAX(AJ4:AJ12)+LARGE(AJ4:AJ12,2),0) -> 0 | AH8: =IF(U8=0,"",K14*U8) | AJ8: =IF(U8=0,"",K14*U8)
B9: 最终补正值 | C9: =E8-C8-C7 -> 0 | N9: =IF(P7="-2","-2",IF(P7="-1","-1",IF(P7="0","0",IF(P7="1","+1D4",IF(P7=2,"+1D6",IF(P7>2,"D6",0)))))) -> 0 | O9: =IF(N9="D6",P7-1,"0") -> 0 | P9: =IF(N9="D6",O10,N9) -> 0 | S9: ="智力×"&U9 -> 智力×0 | T9: =职业列表!J20 -> × | U9: =职业列表!K20 -> 0 | W9: =IF(U8>0,S8,"") | X9: =IF(Y9=0,IF(AB6=1,"或",IF(AB7+AB8=1,"+","")),"") | Y9: =IF(W9="",1,0) -> 1 | Z9: =L14*U9 -> 0 | AA9: =IF(Y10+Y11+Y12=3,"",X9) | AB9: =IF(AC9=职业列表!I25,1,0) -> 0 | AC9: 最高的属性点+其他属性的最小值 | AF9: =IF(AB9=1,MAX(AJ4:AJ12)+MIN(AJ4:AJ12),0) -> 0 | AH9: =IF(U9=0,"",L14*U9) | AJ9: =IF(U9=0,"",L14*U9)
B10: 格斗射击基础成功率 | O10: ="+"&O9&"D6" -> +0D6 | S10: ="教育×"&U10 -> 教育×2 | T10: =职业列表!J21 -> √ | U10: =职业列表!K21 -> 2 | W10: =IF(U9>0,S9,"") | X10: =IF(Y10=0,IF(AB6=1,"或",IF(AB7+AB8=1,"+","")),"") | Y10: =IF(W10="",1,0) -> 1 | Z10: =N14*U10 -> 110 | AA10: =IF(Y11+Y12=2,"",X10) | AB10: =IF(AC10=职业列表!I25,1,0) -> 0 | AC10: 选择属性点数中的所有值相加 | AF10: =IF(AB10=1,SUM(AJ4:AJ12),0) -> 0 | AH10: ="" | AI10: =IF(U10=0,0,N14*U10) -> 110 | AJ10: =IF(U10=0,"",N14*U10) -> 110
B11: 格斗1 | C11: =IF(人物卡!H36="鞭子","5",IF(人物卡!H36="电锯","10",IF(人物卡!H36="斧","15",IF(人物卡!H36="剑","20",IF(人物卡!H36="绞具","15",IF(人物卡!H36="链枷","10",IF(人物卡!H36="矛","20",IF(人物卡!H36=人物卡!AU27,人物卡!BA27,0)))))))) -> 0 | D11: 射击1 | E11: =IF(人物卡!H40="步枪/霰弹枪","25",IF(人物卡!H40="冲锋枪","15",IF(人物卡!H40="弓","15",IF(人物卡!H40="喷射器","10",IF(人物卡!H40="机枪","10",IF(人物卡!H40="重武器","10",IF(人物卡!H40=人物卡!AU27,人物卡!BA27,0))))))) -> 0 | S11: ="意志×"&U11 -> 意志×0 | T11: =职业列表!J22 -> × | U11: =职业列表!K22 -> 0 | W11: =IF(U11>0,S11,"") | X11: =IF(Y11=0,IF(AB6=1,"或",IF(AB7+AB8=1,"+","")),"") | Y11: =IF(W11="",1,0) -> 1 | Z11: =M14*U11 -> 0 | AA11: =IF(Y12=1,"",X11) | AH11: =IF(U11=0,"",M14*U11) | AJ11: =IF(U11=0,"",M14*U11)
B12: 格斗2 | C12: =IF(人物卡!H37="鞭子","5",IF(人物卡!H37="电锯","10",IF(人物卡!H37="斧","15",IF(人物卡!H37="剑","20",IF(人物卡!H37="绞具","15",IF(人物卡!H37="链枷","10",IF(人物卡!H37="矛","20",IF(人物卡!H37=人物卡!AU27,人物卡!BA27,0)))))))) -> 0 | D12: 射击2 | E12: =IF(人物卡!H41="步枪/霰弹枪","25",IF(人物卡!H41="冲锋枪","15",IF(人物卡!H41="弓","15",IF(人物卡!H41="喷射器","10",IF(人物卡!H41="机枪","10",IF(人物卡!H41="重武器","10",IF(人物卡!H41=人物卡!AU27,人物卡!BA27,0))))))) -> 0 | G12: 属性雷达表 | H12: 基础属性 | I12: 出目 | S12: ="幸运×"&U12 -> 幸运×0 | T12: =职业列表!J23 -> × | U12: =职业列表!K23 -> 0 | W12: =IF(U12>0,S12,"") | X12: =IF(Y12=0,IF(AB6=1,"或",IF(AB7+AB8=1,"+","")),"") | Y12: =IF(W12="",1,0) -> 1 | Z12: =O14*U12 -> 0 | AH12: =IF(U12=0,"",O14*U12) | AJ12: =IF(U12=0,"",O14*U12)
B13: 格斗3 | C13: =IF(人物卡!H38="鞭子","5",IF(人物卡!H38="电锯","10",IF(人物卡!H38="斧","15",IF(人物卡!H38="剑","20",IF(人物卡!H38="绞具","15",IF(人物卡!H38="链枷","10",IF(人物卡!H38=人物卡!AU27,人物卡!BA27,0))))))) -> 0 | D13: 射击3 | E13: =IF(人物卡!H42="步枪/霰弹枪","25",IF(人物卡!H42="冲锋枪","15",IF(人物卡!H42="弓","15",IF(人物卡!H42="喷射器","10",IF(人物卡!H42="机枪","10",IF(人物卡!H42="重武器","10",IF(人物卡!H42=人物卡!AU27,人物卡!BA27,0))))))) -> 0 | G13: 力量 STR | H13: 体质 CON | I13: 体型 SIZ | J13: 敏捷 DEX | K13: 外貌 APP | L13: 智力 灵感 | M13: 意志 POW | N13: 教育 EDU | O13: 幸运 Luck
B14: 熟练下拉 | G14: =STR -> 30 | H14: =CON -> 50 | I14: =SIZ -> 55 | J14: =DEX -> 70 | K14: =APP -> 80 | L14: =INT -> 80 | M14: =POW -> 60 | N14: =EDU -> 55 | O14: =Luck -> 50 | U14: 自定义技能剩余计算 | Z14: 战斗 | AA14: ←请选择类型 | AB14: 爆破 | AC14: 电气维修 | AD14: 炮术 | AE14: 投掷 | AF14: 格斗1 | AI14: 格斗2 | AL14: 格斗3 | AO14: 射击1 | AP14: 射击2 | AQ14: 射击3 | AR14: 斗殴 | AS14: 手枪 | AT14: 没有数值 | AU14: 最大值 | AV14: 最终出目 | AZ14: 出目 | BA14: =IF(AX27="仅显示1890~2012","",VLOOKUP(AX27,AZ25:BB29,3,FALSE)) -> 0
B15: ★ | C15: =IF(人物卡!M5=0," ",LOOKUP(人物卡!M5,职业列表!A2:A232,职业列表!H2:H232)) -> 会计，两项社交技能（取悦、话术、恐吓、说服），法律，图书馆，聆听，锁匠，艺术及手艺（摄影），侦查，任意一项其他个人或时代特长 | E15: =IF(人物卡!M5=0,"","["&LOOKUP(人物卡!M5,职业列表!A2:A232,职业列表!B2:B232)&"]的本职技能：") -> [私家侦探]的本职技能： | G15: =IF(F16=1,J16,J15) -> 经历包 | J15: 本职 | O15: 随身物品下拉表 | U15: 1 | V15: =人物卡!H40 -> 0 | W15: =IF(V15="步枪/霰弹枪",1,0) -> 0 | AA15: =IF(人物卡!M55=AA14,"") -> FALSE | AB15: =IF(人物卡!M55=人物卡!AB44,人物卡!AN44) -> FALSE | AC15: =IF(人物卡!M55=人物卡!F32,人物卡!R32) -> FALSE | AD15: =IF(人物卡!M55=人物卡!AB47,人物卡!AN47) -> FALSE | AE15: =IF(人物卡!M55=人物卡!AB40,人物卡!AN40) -> FALSE | AF15: =IF(人物卡!M55=人物卡!H36,人物卡!R36) -> FALSE | AI15: =IF(人物卡!M55=人物卡!H37,人物卡!R37) -> FALSE | AL15: =IF(人物卡!M55=人物卡!H38,人物卡!R38) -> FALSE | AO15: =IF(人物卡!M55=人物卡!H40,人物卡!R40) -> FALSE | AP15: =IF(人物卡!M55=人物卡!H41,人物卡!R41) -> FALSE | AQ15: =IF(人物卡!M55=人物卡!H42,人物卡!R42) -> FALSE | AR15: =IF(人物卡!M55=人物卡!H35,人物卡!R35) -> 25 | AS15: =IF(人物卡!M55=人物卡!H39,人物卡!R39) -> FALSE | AT15: =IF(AU15=0,IF(人物卡!M55=附表!U220,附表!V220,IF(人物卡!M55=附表!U221,附表!V221,IF(人物卡!M55=附表!U219,附表!V219,IF(人物卡!M55=附表!U224,附表!V224,IF(人物卡!M55=附表!U225,附表!V225,IF(人物卡!M55=附表!U223,附表!V223,IF(人物卡!M55=附表!U222,附表!V222,IF(人物卡!M55=附表!U226,技能注释!#REF!,IF(人物卡!M55=附表!Q220,附表!R220,IF(人物卡!M55=附表!Q221,附表!R221,IF(人物卡!M55=附表!Q222,附表!R222,IF(人物卡!M55=附表!Q223,附表!R223,IF(人物卡!M55=附表!Q224,附表!R224,IF(人物卡!M55=附表!Q219,附表!R219,IF(人物卡!M55=附表!Q225,附表!R225,"")))))))))))))))) -> FALSE | AU15: =MAX(AA15:AS15) -> 25 | AV15: =IF(AU15=0,AT15,AU15) -> 25
C16: =IF(D16=A30,G20,L34) -> 攀爬，格斗(斗殴)，射击(手枪)，急救，聆听，导航，(取悦，说服，恐吓)中选一项，潜行，投掷，侦查 | D16: =人物卡!E117 -> 0 | E16: =IF(B30=0,"","["&D16&"]经历包可选技能：") -> [0]经历包可选技能： | F16: =IF(人物卡!B13=E16,1,0) -> 1 | J16: 经历包 | L16: san值计算 | O16: 颅———— | U16: 2 | V16: =人物卡!H41 -> 0 | W16: =IF(V16="步枪/霰弹枪",1,0) -> 0 | AA16: =IF(人物卡!M56=AA14,"") | AB16: =IF(人物卡!M56=AB14,人物卡!AN44) -> FALSE | AC16: =IF(人物卡!M56=AC14,人物卡!R32) -> FALSE | AD16: =IF(人物卡!M56=AD14,人物卡!AN47) -> FALSE | AE16: =IF(人物卡!M56=AE14,人物卡!AN40) -> FALSE | AF16: =IF(ISBLANK(人物卡!H36),FALSE,IF(人物卡!M56=人物卡!H36,人物卡!R36)) -> FALSE | AI16: =IF(ISBLANK(人物卡!H37),FALSE,IF(人物卡!M56=人物卡!H37,人物卡!R37)) -> FALSE | AL16: =IF(ISBLANK(人物卡!H38),FALSE,IF(人物卡!M56=人物卡!H38,人物卡!R38)) -> FALSE | AO16: =IF(ISBLANK(人物卡!H40),FALSE,IF(人物卡!M56=人物卡!H40,人物卡!R40)) -> FALSE | AP16: =IF(ISBLANK(人物卡!H41),FALSE,IF(人物卡!M56=人物卡!H41,人物卡!R41)) -> FALSE | AQ16: =IF(ISBLANK(人物卡!H42),FALSE,IF(人物卡!M56=人物卡!H42,人物卡!R42)) -> FALSE | AR16: =IF(人物卡!M56=AR14,人物卡!R35) -> FALSE | AS16: =IF(人物卡!M56=AS14,人物卡!R39) -> FALSE | AT16: =IF(AU16=0,IF(人物卡!M56=附表!U220,附表!V220,IF(人物卡!M56=附表!U221,附表!V221,IF(人物卡!M56=附表!U219,附表!V219,IF(人物卡!M56=附表!U224,附表!V224,IF(人物卡!M56=附表!U225,附表!V225,IF(人物卡!M56=附表!U223,附表!V223,IF(人物卡!M56=附表!U222,附表!V222,IF(人物卡!M56=附表!U226,技能注释!#REF!,IF(人物卡!M56=附表!Q220,附表!R220,IF(人物卡!M56=附表!Q221,附表!R221,IF(人物卡!M56=附表!Q222,附表!R222,IF(人物卡!M56=附表!Q223,附表!R223,IF(人物卡!M56=附表!Q224,附表!R224,IF(人物卡!M56=附表!Q219,附表!R219,IF(人物卡!M56=附表!Q225,附表!R225,"")))))))))))))))) | AU16: =MAX(AA16:AS16) -> 0 | AV16: =IF(AU16=0,AT16,AU16)
B17: =IF(AND(F16=1,A32=1),C16,C15) -> 会计，两项社交技能（取悦、话术、恐吓、说服），法律，图书馆，聆听，锁匠，艺术及手艺（摄影），侦查，任意一项其他个人或时代特长 | L17: 意志 | M17: 最大值 | O17: 头部 | R17: 健康 | S17: 清醒 | U17: 3 | V17: =人物卡!H42 -> 0 | W17: =IF(V17="步枪/霰弹枪",1,0) -> 0 | AA17: =IF(人物卡!M57=AA14,"") -> FALSE | AB17: =IF(人物卡!M57=AB14,人物卡!AN44) -> FALSE | AC17: =IF(人物卡!M57=AC14,人物卡!R32) -> FALSE | AD17: =IF(人物卡!M57=AD14,人物卡!AN47) -> FALSE | AE17: =IF(人物卡!M57=AE14,人物卡!AN40) -> FALSE | AF17: =IF(ISBLANK(人物卡!H36),FALSE,IF(人物卡!M57=人物卡!H36,人物卡!R36)) -> FALSE | AI17: =IF(ISBLANK(人物卡!H37),FALSE,IF(人物卡!M57=人物卡!H37,人物卡!R37)) -> FALSE | AL17: =IF(ISBLANK(人物卡!H38),FALSE,IF(人物卡!M57=人物卡!H38,人物卡!R38)) -> FALSE | AO17: =IF(ISBLANK(人物卡!H40),FALSE,IF(人物卡!M57=人物卡!H40,人物卡!R40)) -> FALSE | AP17: =IF(ISBLANK(人物卡!H41),FALSE,IF(人物卡!M57=人物卡!H41,人物卡!R41)) -> FALSE | AQ17: =IF(ISBLANK(人物卡!H42),FALSE,IF(人物卡!M57=人物卡!H42,人物卡!R42)) -> FALSE | AR17: =IF(人物卡!M57=AR14,人物卡!R35) -> FALSE | AS17: =IF(人物卡!M57=AS14,人物卡!R39) -> FALSE | AT17: =IF(AU17=0,IF(人物卡!M57=附表!U220,附表!V220,IF(人物卡!M57=附表!U221,附表!V221,IF(人物卡!M57=附表!U219,附表!V219,IF(人物卡!M57=附表!U224,附表!V224,IF(人物卡!M57=附表!U225,附表!V225,IF(人物卡!M57=附表!U223,附表!V223,IF(人物卡!M57=附表!U222,附表!V222,IF(人物卡!M57=附表!U226,技能注释!#REF!,IF(人物卡!M57=附表!Q220,附表!R220,IF(人物卡!M57=附表!Q221,附表!R221,IF(人物卡!M57=附表!Q222,附表!R222,IF(人物卡!M57=附表!Q223,附表!R223,IF(人物卡!M57=附表!Q224,附表!R224,IF(人物卡!M57=附表!Q219,附表!R219,IF(人物卡!M57=附表!Q225,附表!R225,"")))))))))))))))) | AU17: =MAX(AA17:AS17) -> 0 | AV17: =IF(AU17=0,AT17,AU17)
B18: 可选规则：有故事的调查员 | L18: =M14 -> 60 | M18: =人物卡!P10 -> 99 | O18: 头发 | R18: 昏迷 | S18: 临时疯狂 | U18: 自定义 | V18: =人物卡!AB49 -> 自定义技能 | W18: =IF(V18="自定义技能",1,0) -> 1
B19: 名称 | C19: san | D19: 技能 | E19: 备注 | F19: jineng | L19: 最终值 | O19: 耳朵 | R19: 重伤 | S19: 不定性疯狂
B20: 战场经历包 | C20: 1d10+5 | D20: 70 | E20: 对目击尸体和重伤员造成的理智损失免疫； 根据战争的年份和模组发生时的年份调整年龄； 背景增加一项：战争相关的伤疤 / 疤痕或恐惧症 / 躁狂症 | F20: 攀爬，格斗(斗殴)，射击(步霰)，急救，恐吓，聆听，潜行，投掷，妙手，侦查，生存； | G20: 攀爬，格斗(斗殴)，射击(手枪)，急救，聆听，导航，(取悦，说服，恐吓)中选一项，潜行，投掷，侦查 | L20: =IF(L18>M18,M18,L18) -> 60 | O20: 面部 | R20: 死亡 | S20: 永久疯狂 | AA20: 任意 | AR20: 特定时间
B21: 警务经历包 | C21: 1d10 | D21: 60 | E21: 对目击尸体造成的理智损失免疫； 初始年龄不能低于 25 岁； 背景增加一项：警察工作相关的伤疤 / 疤痕或恐惧症 / 躁狂症 | F21: 攀爬，汽车驾驶，格斗（斗殴），射击（手枪或步霰），急救，法律，聆听，外语，两项社交技能（魅惑、话术、说服、恐吓），追踪 | O21: 颈部 | R21: =IF(ISBLANK(人物卡!BK27),"",人物卡!BK27) | S21: =IF(ISBLANK(人物卡!BO27),"",人物卡!BO27) | AA21: =IF(ISBLANK(人物卡!BB19),0,1) -> 0 | AB21: =IF(ISBLANK(人物卡!BJ19),0,1) -> 0 | AC21: 总数 | AD21: 是否停用 | AE21: 最终值 | AR21: =人物卡!BL130 -> 1920 | AS21: =IF(AR21="仅显示1890~2012","",VLOOKUP(AR21,AE33:AS155,15,FALSE)) -> 广播电台 茶包
B22: 罪犯经历包 | C22: 1d10 | D22: 60 | E22: 对目击尸体、目击或亲自谋杀、目击对人类的暴力残害造成的理智损失免疫； 初始年龄不能低于 20 岁； 背景增加一项：犯罪历史相关的伤疤 / 疤痕或恐惧症 / 躁狂症 | F22: 攀爬，汽车驾驶，格斗（任一），射击（任一），一项社交技能（魅惑、话术、说服、恐吓），法律，聆听，锁匠，心理学，追踪 | O22: 其他(头) | AA22: =IF(ISBLANK(人物卡!BB20),0,1) -> 0 | AB22: =IF(ISBLANK(人物卡!BJ20),0,1) -> 0 | AC22: =AA21+AA23+AA22+AA25+AA24+AB21+AB22+AB23+AB24+AB25 -> 0 | AD22: =IF(人物卡!AU23="提示当前职业",0,1) -> 0 | AE22: =IF(AD32=1,"仅显示1890~2023",AE28) -> 2023 | AF22: =IF(AE22="仅显示1890~2023","",VLOOKUP(AE22,AE33:AS186,2,FALSE)) -> —— | AG22: =IF(AE22="仅显示1890~2023","",VLOOKUP(AE22,AE33:AS186,3,FALSE)) -> 0 | AH22: =IF(AE22="仅显示1890~2023","",VLOOKUP(AE22,AE33:AS186,4,FALSE)) -> 0 | AI22: =IF(AE22="仅显示1890~2023","",VLOOKUP(AE22,AE33:AS186,5,FALSE)) -> —— | AJ22: =IF(AE22="仅显示1890~2023","",VLOOKUP(AE22,AE33:AS186,6,FALSE)) -> 0 | AK22: =IF(AE22="仅显示1890~2023","",VLOOKUP(AE22,AE33:AS186,7,FALSE)) -> 0 | AL22: =IF(AE22="仅显示1890~2023","",VLOOKUP(AE22,AE33:AS186,8,FALSE)) -> 二十一世纪 二十年代 | AM22: =IF(AE22="仅显示1890~2023","",VLOOKUP(AE22,AE33:AS186,9,FALSE)) -> 癸卯兔年 | AN22: =IF(AE22="仅显示1890~2023","",VLOOKUP(AE22,AE33:AS186,10,FALSE)) -> 中华人民共和国74周年 | AO22: =IF(AE22="仅显示1890~2023","",VLOOKUP(AE22,AE33:AS186,11,FALSE)) -> 0 | AP22: =IF(AE22="仅显示1890~2023","",VLOOKUP(AE22,AE33:AS186,12,FALSE)) -> 总统： 约瑟夫·拜登（民主党） | AQ22: =IF(AE22="仅显示1890~2023","",VLOOKUP(AE22,AE33:AS186,13,FALSE)) -> 0 | AR22: =IF(AE22="仅显示1890~2023","",VLOOKUP(AE22,AE33:AS186,14,FALSE)) -> 电气地铁 圣代冰淇淋 实用水电站 手电 电影摄影机 收音机 霍乱疫苗 啤酒瓶盖 柴油发动机 双向电报 实用的胶卷 块麦片 电报 可口可乐 X射线 卷烟机发明 电影放映机 排球 印名片机 福特车 潜望镜 油印蜡纸发明 阴极射线管 商品阿司匹林 凯洛格牌玉米片 手电筒 钋 镭 摇控器 α粒子 β粒子 打字机 柯达布朗尼相机 齐柏林飞艇 人类血型 跨大西洋电报 汽轮机游船 现代柏油路 铝罐奶粉 爆米花 泰迪熊 卡鲁索电唱机 便宜的肥皂和烹饪用油 飞机 荧光灯 邮戳机 摩托车发动机 热水瓶 农业轨道机械 木棉安全带 电动汽车喇叭 化学泡沫灭火器 狭义相对论 自动点唱机 量产舰艇舷外发动机 动画 电动洗衣机 家用洗洁精 立式吸尘器 饮用纸杯 双层公交车 无线电测向仪 电煎锅 质子和电子 玻璃纸 战壕风衣 汽车自动起动器 麦片 氯气毒气 防毒面具 拉链 机械雨刮器 广义相对论 芥子气 量产拖拉机 电子钟 黄油枪 降落伞 广播电台播音 茶包 罗夏墨迹测验 机器人 胰岛素 实用邮戳机 滑水 百日咳疫苗 纸制鸡蛋托 面巾纸 商用飞机农药喷撒 液体燃料火箭 劳力士防水表 遥控电唱机 面包机 防水玻璃纸 电传打字机 盖革计数器 纯维生素C 彩色电影胶片 透明胶带 音乐汽车喇叭 闪光灯 速冻食品 球形潜水舱 回旋加速器 折叠式雨伞 电动剃须刀 车载收音机 玛氏巧克力棒 变焦镜头 大富翁桌游 商业洗衣店 畅销平装书 里氏震级 磁带录音机 大众汽车 超市推车 带温控器的电熨斗 速溶咖啡 尼龙 圆珠笔 黄热病疫苗 雷达 汽车自动变速箱 充气救生衣 人工授精 青霉素 军用吉普车 原子裂变 火箭筒 凝固汽油弹 水肺 麦角酸二乙酰胺 神经毒气 原子弹 特百惠 计算机 静电复印法 比基尼泳衣 浓缩咖啡机 宝丽来相机 拼字盘 实心电吉他 尼龙扣 晶体管 黑胶唱片 有线电视 电视显像管 汽车自动点火装置 信用卡 复印机 宽荧幕电影 动力转向器 三色停车灯 人行红绿灯 晶体管助听器 氢弹 录像带 DNA双螺旋结构 麻疹疫苗 按动圆珠笔 硅晶体管 核导弹 空对空导弹 迪士尼乐园 特氟龙 卡丁车 地对空核导弹 沙宾疫苗 通讯卫星 呼啦圈 安全带 人工肾脏 避孕药 气象卫星 便携晶体管收音机 安定 砷化镓半导体激光器 三维全息技术 合成器 香烟健康警示 凯夫拉纤维 子午胎 IBM文字处理机 杜比A型降噪器 滑雪板 喇叭裤 绕月载人火箭 人工心脏移植 波音747喷气式客机 互联网 条形码 软盘 帆板 热裤 液晶显示 便携电子计算器 电视游戏 DNA重组技术 电子游戏机 超级计算机 光纤 试管婴儿 魔方 索尼Walkman 杜比C型降噪器 艾滋病毒 强效可卡因 温室效应 CD 暗物质 暗能量 太阳能飞行器 甲型H1N6 流感 希格斯玻色子 引力波 | AS22: =IF(AE22="仅显示1890~2023","",VLOOKUP(AE22,AE33:AS186,15,FALSE)) -> 0
B23: 医务经历包 | C23: 1d10 | D23: 60 | E23: 对目击尸体和重伤员造成的理智损失免疫； 初始年龄不能低于 30 岁； 背景增加一项：个人背景相关的伤疤 / 疤痕或恐惧症 / 躁狂症； | F23: 急救，法律，聆听，医学，心理学，侦查，科学（任二） | O23: 躯———— | Q23: 显露 | S23: =".st "&"力量"&G14&"str"&G14&"敏捷"&J14&"dex"&J14&"意志"&M14&"pow"&M14&"体质"&H14&"con"&H14&"外貌"&K14&"app"&K14&"教育"&N14&"知识"&N14&"edu"&N14&"体型"&I14&"siz"&I14&"智力"&L14&"灵感"&L14&"int"&L14&"san"&人物卡!N10&"san值"&人物卡!N10&"理智"&人物卡!N10&"理智值"&人物卡!N10&"幸运"&O14&"运气"&O14&"mp"&人物卡!W10&"魔法"&人物卡!W10&"hp"&人物卡!E10&"体力"&人物卡!E10&人物卡!F17&人物卡!R17&人物卡!F18&人物卡!R18&人物卡!F19&人物卡!R19&人物卡!F20&人物卡!R20&IF(人物卡!H21="","",人物卡!H21&人物卡!R21)&IF(人物卡!H22="","",人物卡!H22&人物卡!R22)&IF(人物卡!H23="","",人物卡!H23&人物卡!R23)&人物卡!F24&人物卡!R24&人物卡!F25&人物卡!R25&"计算机"&人物卡!R26&"计算机使用"&人物卡!R26&"电脑"&人物卡!R26&"信用"&人物卡!R27&"信誉"&人物卡!R27&"信用评级"&人物卡!R27&"克苏鲁"&人物卡!R28&"克苏鲁神话"&人物卡!R28&"cm"&人物卡!R28&人物卡!F29&人物卡!R29&人物卡!F30&人物卡!R30&"汽车"&人物卡!R31&"驾驶"&人物卡!R31&"汽车驾驶"&人物卡!R31&人物卡!F32&人物卡!R32&"电子学"&人物卡!R33&人物卡!F34&人物卡!R34&人物卡!H35&人物卡!R35&IF(人物卡!H36="","",人物卡!H36&人物卡!R36)&IF(人物卡!H37="","",人物卡!H37&人物卡!R37)&IF(人物卡!H38="","",人物卡!H37&人物卡!R38)&人物卡!H39&人物卡!R39&IF(W15=1,人物卡!AB40&人物卡!R40&"步枪"&人物卡!R40&"霰弹枪"&人物卡!R40&"步霰"&人物卡!R40,IF(人物卡!H40="","",人物卡!H40&人物卡!R40))&IF(W16=1,人物卡!AB41&人物卡!R41&"步枪"&人物卡!R41&"霰弹枪"&人物卡!R41&"步霰"&人物卡!R41,IF(人物卡!H41="","",人物卡!H41&人物卡!R41))&IF(W17=1,人物卡!AB42&人物卡!R42&"步枪"&人物卡!R42&"霰弹枪"&人物卡!R42&"步霰"&人物卡!R42,IF(人物卡!H42="","",人物卡!H42&人物卡!R42))&人物卡!F43&人物卡!R43&人物卡!F44&人物卡!R44&人物卡!F45&人物卡!R45&人物卡!F46&人物卡!R46&IF(人物卡!H47="","",人物卡!H47&人物卡!R47)&IF(人物卡!H48="","",人物卡!H48&人物卡!R48)&IF(人物卡!H49="","",人物卡!H49&人物卡!R49)&人物卡!F50&人物卡!R50&人物卡!AB17&人物卡!AN17&"图书馆"&人物卡!AN18&"图书馆使用"&人物卡!AN18&人物卡!AB19&人物卡!AN19&"开锁"&人物卡!AN20&"撬锁"&人物卡!AN20&"锁匠"&人物卡!AN20&人物卡!AB21&人物卡!AN21&人物卡!AB22&人物卡!AN22&"博物学"&人物卡!AN23&"自然学"&人物卡!AN23&"领航"&人物卡!AN24&"导航"&人物卡!AN24&人物卡!AB25&人物卡!AN25&"重型操作"&人物卡!AN26&"重型机械"&人物卡!AN26&"操作重型机械"&人物卡!AN26&"重型"&人物卡!AN26&人物卡!AB27&人物卡!AN27&IF(人物卡!AD28="","",人物卡!AD28&人物卡!AN28)&人物卡!AB29&人物卡!AN29&人物卡!AB30&人物卡!AN30&人物卡!AB31&人物卡!AN31&IF(人物卡!AD32="","",人物卡!AD32&人物卡!AN32)&IF(人物卡!AD33="","",人物卡!AD33&人物卡!AN33)&IF(人物卡!AD34="","",人物卡!AD34&人物卡!AN34)&人物卡!AB35&人物卡!AN35&人物卡!AB36&人物卡!AN36&人物卡!AB37&人物卡!AN37&"生存"&人物卡!AN38&人物卡!AB39&人物卡!AN39&人物卡!AB40&人物卡!AN40&人物卡!AB41&人物卡!AN41&人物卡!AB42&人物卡!AN42&人物卡!AB43&人物卡!AN43&人物卡!AB44&人物卡!AN44&人物卡!AB45&人物卡!AN45&人物卡!AB46&人物卡!AN46&人物卡!AB47&人物卡!AN47&IF(人物卡!AD48="","",人物卡!AD48&人物卡!AN48)&IF(W18=1,"",人物卡!AB49&人物卡!AN49)&IF(人物卡!AB50="","",人物卡!AB50&人物卡!AN50) -> .st 力量30str30敏捷70dex70意志60pow60体质50con50外貌80app80教育55知识55edu55体型55siz55智力80灵感80int80san60san值60理智60理智值60幸运50运气50mp12魔法12hp10体力10会计5人类学1估价5考古学1取悦70攀爬20计算机5计算机使用5电脑5信用20信誉20信用评级20克苏鲁0克苏鲁神话0cm0乔装5闪避60汽车20驾驶20汽车驾驶20电气维修10电子学1话术70斗殴25手枪20急救30历史5恐吓15跳跃20母语55法律5图书馆20图书馆使用20聆听70开锁71撬锁71锁匠71机械维修10医学1博物学10自然学10领航10导航10神秘学5重型操作1重型机械1操作重型机械1重型1说服10精神分析1心理学60骑术5妙手10侦查80潜行60生存10游泳20投掷20追踪10驯兽5潜水1爆破1读唇1催眠1炮术1 | AA23: =IF(ISBLANK(人物卡!BB21),0,1) -> 0 | AB23: =IF(ISBLANK(人物卡!BJ21),0,1) -> 0 | AC23: 数 | AE23: 目前值
B24: 神话经历包 | C24: 如果是"相信者"，减少和克苏鲁神话相同的san值 | D24: 0 | E24: 按 KP 允许的数值增加「克苏鲁神话」技能； 背景增加两项：与神话经历相关的伤疤 /疤痕、恐惧症 / 躁狂症、遭遇的怪异存在 | F24: 无 | O24: 肩 | Q24: 隐藏 | X24: 任意 | AA24: =IF(ISBLANK(人物卡!BB22),0,1) -> 0 | AB24: =IF(ISBLANK(人物卡!BJ22),0,1) -> 0 | AC24: =人物卡!F9-AC22 -> 1 | AE24: =人物卡!G8 -> 2023 | AX24: 总值 | AZ24: 分类
B25: =IF(ISBLANK(人物卡!BC27),"自定义经历包",人物卡!BC27) -> 自定义经历包 | C25: =简化卡!E84 | D25: =简化卡!H84 | E25: =简化卡!J84 | H25: =人物卡!BC31 -> 0 | O25: 胸前 | X25: 会计 | AA25: =IF(ISBLANK(人物卡!BB23),0,1) -> 0 | AB25: =IF(ISBLANK(人物卡!BJ23),0,1) -> 0 | AC25: 最终 | AD25: =IF(AD22=1," ",IF(AC24=0,"无",IF(AC24<0,"过多！",AC24))) -> 1 | AE25: 公元调整 | AT25: 未出现的 | AV25: =IF(AT25=人物卡!AZ130,1,0) -> 1 | AZ25: 1 | BA25: 未出现的发明 | BB25: =AQ22 -> 0
B26: 无 | O26: 背后 | X26: 人类学 | AE26: =IF(人物卡!E8="公元前",人物卡!G8*2,0) -> 0 | AT26: 已出现的 | AV26: =IF(AT26=人物卡!AZ130,2,0) -> 0 | AZ26: 2 | BA26: 已出现的发明 | BB26: =AR22 -> 电气地铁 圣代冰淇淋 实用水电站 手电 电影摄影机 收音机 霍乱疫苗 啤酒瓶盖 柴油发动机 双向电报 实用的胶卷 块麦片 电报 可口可乐 X射线 卷烟机发明 电影放映机 排球 印名片机 福特车 潜望镜 油印蜡纸发明 阴极射线管 商品阿司匹林 凯洛格牌玉米片 手电筒 钋 镭 摇控器 α粒子 β粒子 打字机 柯达布朗尼相机 齐柏林飞艇 人类血型 跨大西洋电报 汽轮机游船 现代柏油路 铝罐奶粉 爆米花 泰迪熊 卡鲁索电唱机 便宜的肥皂和烹饪用油 飞机 荧光灯 邮戳机 摩托车发动机 热水瓶 农业轨道机械 木棉安全带 电动汽车喇叭 化学泡沫灭火器 狭义相对论 自动点唱机 量产舰艇舷外发动机 动画 电动洗衣机 家用洗洁精 立式吸尘器 饮用纸杯 双层公交车 无线电测向仪 电煎锅 质子和电子 玻璃纸 战壕风衣 汽车自动起动器 麦片 氯气毒气 防毒面具 拉链 机械雨刮器 广义相对论 芥子气 量产拖拉机 电子钟 黄油枪 降落伞 广播电台播音 茶包 罗夏墨迹测验 机器人 胰岛素 实用邮戳机 滑水 百日咳疫苗 纸制鸡蛋托 面巾纸 商用飞机农药喷撒 液体燃料火箭 劳力士防水表 遥控电唱机 面包机 防水玻璃纸 电传打字机 盖革计数器 纯维生素C 彩色电影胶片 透明胶带 音乐汽车喇叭 闪光灯 速冻食品 球形潜水舱 回旋加速器 折叠式雨伞 电动剃须刀 车载收音机 玛氏巧克力棒 变焦镜头 大富翁桌游 商业洗衣店 畅销平装书 里氏震级 磁带录音机 大众汽车 超市推车 带温控器的电熨斗 速溶咖啡 尼龙 圆珠笔 黄热病疫苗 雷达 汽车自动变速箱 充气救生衣 人工授精 青霉素 军用吉普车 原子裂变 火箭筒 凝固汽油弹 水肺 麦角酸二乙酰胺 神经毒气 原子弹 特百惠 计算机 静电复印法 比基尼泳衣 浓缩咖啡机 宝丽来相机 拼字盘 实心电吉他 尼龙扣 晶体管 黑胶唱片 有线电视 电视显像管 汽车自动点火装置 信用卡 复印机 宽荧幕电影 动力转向器 三色停车灯 人行红绿灯 晶体管助听器 氢弹 录像带 DNA双螺旋结构 麻疹疫苗 按动圆珠笔 硅晶体管 核导弹 空对空导弹 迪士尼乐园 特氟龙 卡丁车 地对空核导弹 沙宾疫苗 通讯卫星 呼啦圈 安全带 人工肾脏 避孕药 气象卫星 便携晶体管收音机 安定 砷化镓半导体激光器 三维全息技术 合成器 香烟健康警示 凯夫拉纤维 子午胎 IBM文字处理机 杜比A型降噪器 滑雪板 喇叭裤 绕月载人火箭 人工心脏移植 波音747喷气式客机 互联网 条形码 软盘 帆板 热裤 液晶显示 便携电子计算器 电视游戏 DNA重组技术 电子游戏机 超级计算机 光纤 试管婴儿 魔方 索尼Walkman 杜比C型降噪器 艾滋病毒 强效可卡因 温室效应 CD 暗物质 暗能量 太阳能飞行器 甲型H1N6 流感 希格斯玻色子 引力波
C27: =IF(人物卡!E115=B20,C20,0) -> 0 | D27: =IF(人物卡!E115=B20,D20,0) -> 0 | E27: =IF(人物卡!E115=B20,E20,0) -> 0 | L27: =IF(人物卡!E115=B20,IF(D16=B30,F20,G20),0) -> 0 | O27: 肋 | X27: 估价 | AB27: 经历包剩余点 | AC27: =D34-SUM(人物卡!L17:L50,人物卡!AH17:AH50) -> 0 | AD27: 最终值 | AE27: 调整出目 | AX27: =AV25+AV26+AV28+AV29+AV30 -> 1 | AZ27: 3 | BA27: 本年的发明 | BB27: =AS22 -> 0
C28: =IF(人物卡!E115=B21,C21,0) -> 0 | D28: =IF(人物卡!E115=B21,D21,0) -> 0 | E28: =IF(人物卡!E115=B21,E21,0) -> 0 | L28: =IF(人物卡!E115=B21,F21,0) -> 0 | O28: 裆 | X28: 考古学 | AB28: 检测是否为数字 | AC28: =ISNUMBER(AC27) -> TRUE | AD28: =IF(AC28=FALSE,"0",AC27) -> 0 | AE28: =AE24-AE26 -> 2023 | AT28: 本年的发明 | AV28: =IF(AT28=人物卡!AZ130,3,0) -> 0 | AZ28: 4 | BA28: 查找年份发明 | BB28: =AS21 -> 广播电台 茶包
C29: =IF(人物卡!E115=B22,C22,0) -> 0 | D29: =IF(人物卡!E115=B22,D22,0) -> 0 | E29: =IF(人物卡!E115=B22,E22,0) -> 0 | L29: =IF(人物卡!E115=B22,F22,0) -> 0 | O29: 腰 | X29: 技艺① | AD29: 检测大小 | AT29: 查找年份发明 | AV29: =IF(AT29=人物卡!AZ130,4,0) -> 0 | AZ29: 5 | BA29: 查找发明的时间 | BB29: ?
B30: =IF(C27=0,IF(C28=0,IF(C29=0,IF(C30=0,IF(C31=0,IF(C32=0,"",IF(人物卡!E5=0,"请先填写调查员信息",人物卡!E5)),IF(人物卡!E5=0,"请先填写调查员信息",人物卡!E5)),"医务人员"),"罪犯"),"警务人员"),"军官") | C30: =IF(人物卡!E115=B23,C23,0) -> 0 | D30: =IF(人物卡!E115=B23,D23,0) -> 0 | E30: =IF(人物卡!E115=B23,E23,0) -> 0 | L30: =IF(人物卡!E115=B23,F23,0) -> 0 | O30: 胯 | X30: 技艺② | AD30: =IF(AE30="大",1,0) -> 0 | AE30: =IF(AE28>2023,"大") -> FALSE | AT30: 研发中... | AU30: 查找发明的时间 | AV30: =IF(AU30=人物卡!AZ130,5,0) -> 0
A31: 检查是否一致 | B31: =IF(C27=0,"","普通士兵") | C31: =IF(人物卡!E115=B24,C24,0) -> 0 | D31: =IF(人物卡!E115=B24,D24,0) -> 0 | E31: =IF(人物卡!E115=B24,E24,0) -> 0 | L31: =IF(人物卡!E115=B24,F24,0) -> 0 | O31: 其他(躯) | X31: 技艺③ | Z31: 0 | AA31: 零 | AD31: =IF(AE31="小",1,0) -> 0 | AE31: =IF(AE28<1890,"小") -> FALSE
A32: =IF(OR(B30=D16,B31=D16),1,0) -> 0 | C32: =IF(人物卡!E115=B25,C25,0) -> 0 | D32: =IF(人物卡!E115=B25,D25,0) -> 0 | E32: =IF(人物卡!E115=B25,E25,0) -> 0 | L32: =IF(人物卡!E115=B25,F25,0) -> 0 | O32: 服———— | X32: 取悦 | Z32: 1 | AA32: 一 | AD32: =AD30+AD31 -> 0 | AE32: 年份 | AF32: 国际重大时代标志 | AG32: 2 | AH32: 3 | AI32: 中国重大时代标志 | AL32: 年代 | AO32: 重大事件 | AP32: 名人 | AQ32: 未出现的发明 | AR32: 已出现的发明 | AS32: 本年发明
O33: 衣兜 | X33: 攀爬 | Z33: 2 | AA33: 二 | AE33: 1890 | AF33: 梵高饮弹自尽 | AG33: 发现火星“人工运河” | AI33: —— | AL33: 十九世纪纪 九十年代 | AM33: 庚寅虎年 | AN33: 清光绪16年 | AO33: 芝加哥建设世纪界首座全钢结构建筑 伦敦首条电气地铁 英国鱼雷巡洋舰蛇号在西班牙海岸失事，死亡 167 人 坐牛在印第安人起义中被杀 首个圣代冰淇淋 美国总人口达到 629 万 | AP33: 总统： 本杰明·哈里森（共和党） | AQ33: 实用水电站 手电 电影摄影机 收音机 霍乱疫苗 啤酒瓶盖 柴油发动机 双向电报 实用的胶卷 块麦片 电报 可口可乐 X射线 卷烟机发明 电影放映机 排球 印名片机福特车 潜望镜 油印蜡纸发明 阴极射线管 商品阿司匹林 凯洛格牌玉米片 手电筒 钋 镭 摇控器 α粒子 β粒子 打字机 柯达布朗尼相机 齐柏林飞艇 人类血型 跨大西洋电报 汽轮机游船 现代柏油路 铝罐奶粉 爆米花 泰迪熊 卡鲁索电唱机 便宜的肥皂和烹饪用油 飞机 荧光灯 邮戳机 摩托车发动机 热水瓶 农业轨道机械 木棉安全带 电动汽车喇叭 化学泡沫灭火器 狭义相对论 自动点唱机 量产舰艇舷外发动机 动画 电动洗衣机 家用洗洁精 立式吸尘器 饮用纸杯 双层公交车 无线电测向仪 电煎锅 质子和电子 玻璃纸 战壕风衣 汽车自动起动器 麦片 氯气毒气 防毒面具 拉链 机械雨刮器 广义相对论 芥子气 量产拖拉机 电子钟 黄油枪 降落伞 广播电台播音 茶包 罗夏墨迹测验 机器人 胰岛素 实用邮戳机 滑水 百日咳疫苗 纸制鸡蛋托 面巾纸 商用飞机农药喷撒 液体燃料火箭 劳力士防水表 遥控电唱机 面包机 防水玻璃纸 电传打字机 盖革计数器 纯维生素C 彩色电影胶片 透明胶带 音乐汽车喇叭 闪光灯 速冻食品 球形潜水舱 回旋加速器 折叠式雨伞 电动剃须刀 车载收音机 玛氏巧克力棒 变焦镜头 大富翁桌游 商业洗衣店 畅销平装书 里氏震级 磁带录音机 大众汽车 超市推车 带温控器的电熨斗 速溶咖啡 尼龙 圆珠笔 黄热病疫苗 雷达 汽车自动变速箱 充气救生衣 人工授精 青霉素 军用吉普车 原子裂变 火箭筒 凝固汽油弹 水肺 麦角酸二乙酰胺 神经毒气 原子弹 特百惠 计算机 静电复印法 比基尼泳衣 浓缩咖啡机 宝丽来相机 拼字盘 实心电吉他 尼龙扣 晶体管 黑胶唱片 有线电视 电视显像管 汽车自动点火装置 信用卡 复印机 宽荧幕电影 动力转向器 三色停车灯 人行红绿灯 晶体管助听器 氢弹 录像带 DNA双螺旋结构 麻疹疫苗 按动圆珠笔 硅晶体管 核导弹 空对空导弹 迪士尼乐园 特氟龙 卡丁车 地对空核导弹 沙宾疫苗 通讯卫星 呼啦圈 安全带 人工肾脏 避孕药 气象卫星 便携晶体管收音机 安定 砷化镓半导体激光器 三维全息技术 合成器 香烟健康警示 凯夫拉纤维 子午胎 IBM文字处理机 杜比A型降噪器 滑雪板 喇叭裤 绕月载人火箭 人工心脏移植 波音747喷气式客机 互联网 条形码 软盘 帆板 热裤 液晶显示 便携电子计算器 电视游戏 DNA重组技术 电子游戏机 超级计算机 光纤 试管婴儿 魔方 索尼Walkman 杜比C型降噪器 艾滋病毒 强效可卡因 温室效应 CD 暗物质 暗能量 太阳能飞行器 甲型H1N1 流感 希格斯玻色子 引力波 | AR33: 电气地铁 圣代冰淇淋 | AS33: 电气地铁 圣代冰淇淋 | AT33: 1890
C34: =IF(C27=0,IF(C28=0,IF(C29=0,IF(C30=0,IF(C31=0,IF(C32=0,"",C32),C31),C30),C29),C28),C27) | D34: =IF(D27=0,IF(D28=0,IF(D29=0,IF(D30=0,IF(D31=0,IF(D32=0,0,D32),D31),D30),D29),D28),D27) -> 0 | E34: =IF(E27=0,IF(E28=0,IF(E29=0,IF(E30=0,IF(E31=0,IF(E32=0,"",E32),E31),E30),E29),E28),E27) | L34: =IF(L27=0,IF(L28=0,IF(L29=0,IF(L30=0,IF(L31=0,IF(L32=0,"",L32),L31),L30),L29),L28),L27) | O34: 内衬 | X34: 计算机使用 Ω | Z34: 3 | AA34: 三 | AE34: 1891 | AF34: 马德里协定 | AI34: —— | AL34: 十九世纪纪 九十年代 | AM34: 辛卯兔年 | AN34: 清光绪17年 | AO34: 日本浓尾大地震，毁坏 2 万房屋，死亡 2.5万人 首个实用水电站 英国普及手电 爱迪生申请到电影摄影机的专利权 爱迪生拿到收音机的专利 | AP34: 总统： 本杰明·哈里森（共和党） | AQ34: 霍乱疫苗 啤酒瓶盖 柴油发动机 双向电报 实用的胶卷 块麦片 电报 可口可乐 X射线 卷烟机发明 电影放映机 排球 印名片机福特车 潜望镜 油印蜡纸发明 阴极射线管 商品阿司匹林 凯洛格牌玉米片 手电筒 钋 镭 摇控器 α粒子 β粒子 打字机 柯达布朗尼相机 齐柏林飞艇 人类血型 跨大西洋电报 汽轮机游船 现代柏油路 铝罐奶粉 爆米花 泰迪熊 卡鲁索电唱机 便宜的肥皂和烹饪用油 飞机 荧光灯 邮戳机 摩托车发动机 热水瓶 农业轨道机械 木棉安全带 电动汽车喇叭 化学泡沫灭火器 狭义相对论 自动点唱机 量产舰艇舷外发动机 动画 电动洗衣机 家用洗洁精 立式吸尘器 饮用纸杯 双层公交车 无线电测向仪 电煎锅 质子和电子 玻璃纸 战壕风衣 汽车自动起动器 麦片 氯气毒气 防毒面具 拉链 机械雨刮器 广义相对论 芥子气 量产拖拉机 电子钟 黄油枪 降落伞 广播电台播音 茶包 罗夏墨迹测验 机器人 胰岛素 实用邮戳机 滑水 百日咳疫苗 纸制鸡蛋托 面巾纸 商用飞机农药喷撒 液体燃料火箭 劳力士防水表 遥控电唱机 面包机 防水玻璃纸 电传打字机 盖革计数器 纯维生素C 彩色电影胶片 透明胶带 音乐汽车喇叭 闪光灯 速冻食品 球形潜水舱 回旋加速器 折叠式雨伞 电动剃须刀 车载收音机 玛氏巧克力棒 变焦镜头 大富翁桌游 商业洗衣店 畅销平装书 里氏震级 磁带录音机 大众汽车 超市推车 带温控器的电熨斗 速溶咖啡 尼龙 圆珠笔 黄热病疫苗 雷达 汽车自动变速箱 充气救生衣 人工授精 青霉素 军用吉普车 原子裂变 火箭筒 凝固汽油弹 水肺 麦角酸二乙酰胺 神经毒气 原子弹 特百惠 计算机 静电复印法 比基尼泳衣 浓缩咖啡机 宝丽来相机 拼字盘 实心电吉他 尼龙扣 晶体管 黑胶唱片 有线电视 电视显像管 汽车自动点火装置 信用卡 复印机 宽荧幕电影 动力转向器 三色停车灯 人行红绿灯 晶体管助听器 氢弹 录像带 DNA双螺旋结构 麻疹疫苗 按动圆珠笔 硅晶体管 核导弹 空对空导弹 迪士尼乐园 特氟龙 卡丁车 地对空核导弹 沙宾疫苗 通讯卫星 呼啦圈 安全带 人工肾脏 避孕药 气象卫星 便携晶体管收音机 安定 砷化镓半导体激光器 三维全息技术 合成器 香烟健康警示 凯夫拉纤维 子午胎 IBM文字处理机 杜比A型降噪器 滑雪板 喇叭裤 绕月载人火箭 人工心脏移植 波音747喷气式客机 互联网 条形码 软盘 帆板 热裤 液晶显示 便携电子计算器 电视游戏 DNA重组技术 电子游戏机 超级计算机 光纤 试管婴儿 魔方 索尼Walkman 杜比C型降噪器 艾滋病毒 强效可卡因 温室效应 CD 暗物质 暗能量 太阳能飞行器 甲型H1N1 流感 希格斯玻色子 引力波 | AR34: 电气地铁 圣代冰淇淋 实用水电站 手电 电影摄影机 收音机 | AS34: 实用水电站 手电 电影摄影机 收音机 | AT34: 1891
O35: 衣服内 | X35: 信用评级 | Z35: 4 | AA35: 四 | AE35: 1892 | AF35: —— | AI35: —— | AL35: 十九世纪纪 九十年代 | AM35: 壬辰龙年 | AN35: 清光绪18年 | AO35: 宾夕法尼亚州石油城暴发洪水，死亡130 人 霍乱疫苗 开普敦 - 约翰内斯堡铁路竣工 啤酒瓶盖发明 柴油发动机取得专利 爱迪生获得双向电报的专利权 | AP35: 书籍： 阿瑟·柯南·道尔出版《福尔摩斯办案记》（The Adventures of Sherlock Holmes） 总统： 本杰明·哈里森（共和党） | AQ35: 实用的胶卷 块麦片 电报 可口可乐 X射线 卷烟机发明 电影放映机 排球 印名片机福特车 潜望镜 油印蜡纸发明 阴极射线管 商品阿司匹林 凯洛格牌玉米片 手电筒 钋 镭 摇控器 α粒子 β粒子 打字机 柯达布朗尼相机 齐柏林飞艇 人类血型 跨大西洋电报 汽轮机游船 现代柏油路 铝罐奶粉 爆米花 泰迪熊 卡鲁索电唱机 便宜的肥皂和烹饪用油 飞机 荧光灯 邮戳机 摩托车发动机 热水瓶 农业轨道机械 木棉安全带 电动汽车喇叭 化学泡沫灭火器 狭义相对论 自动点唱机 量产舰艇舷外发动机 动画 电动洗衣机 家用洗洁精 立式吸尘器 饮用纸杯 双层公交车 无线电测向仪 电煎锅 质子和电子 玻璃纸 战壕风衣 汽车自动起动器 麦片 氯气毒气 防毒面具 拉链 机械雨刮器 广义相对论 芥子气 量产拖拉机 电子钟 黄油枪 降落伞 广播电台播音 茶包 罗夏墨迹测验 机器人 胰岛素 实用邮戳机 滑水 百日咳疫苗 纸制鸡蛋托 面巾纸 商用飞机农药喷撒 液体燃料火箭 劳力士防水表 遥控电唱机 面包机 防水玻璃纸 电传打字机 盖革计数器 纯维生素C 彩色电影胶片 透明胶带 音乐汽车喇叭 闪光灯 速冻食品 球形潜水舱 回旋加速器 折叠式雨伞 电动剃须刀 车载收音机 玛氏巧克力棒 变焦镜头 大富翁桌游 商业洗衣店 畅销平装书 里氏震级 磁带录音机 大众汽车 超市推车 带温控器的电熨斗 速溶咖啡 尼龙 圆珠笔 黄热病疫苗 雷达 汽车自动变速箱 充气救生衣 人工授精 青霉素 军用吉普车 原子裂变 火箭筒 凝固汽油弹 水肺 麦角酸二乙酰胺 神经毒气 原子弹 特百惠 计算机 静电复印法 比基尼泳衣 浓缩咖啡机 宝丽来相机 拼字盘 实心电吉他 尼龙扣 晶体管 黑胶唱片 有线电视 电视显像管 汽车自动点火装置 信用卡 复印机 宽荧幕电影 动力转向器 三色停车灯 人行红绿灯 晶体管助听器 氢弹 录像带 DNA双螺旋结构 麻疹疫苗 按动圆珠笔 硅晶体管 核导弹 空对空导弹 迪士尼乐园 特氟龙 卡丁车 地对空核导弹 沙宾疫苗 通讯卫星 呼啦圈 安全带 人工肾脏 避孕药 气象卫星 便携晶体管收音机 安定 砷化镓半导体激光器 三维全息技术 合成器 香烟健康警示 凯夫拉纤维 子午胎 IBM文字处理机 杜比A型降噪器 滑雪板 喇叭裤 绕月载人火箭 人工心脏移植 波音747喷气式客机 互联网 条形码 软盘 帆板 热裤 液晶显示 便携电子计算器 电视游戏 DNA重组技术 电子游戏机 超级计算机 光纤 试管婴儿 魔方 索尼Walkman 杜比C型降噪器 艾滋病毒 强效可卡因 温室效应 CD 暗物质 暗能量 太阳能飞行器 甲型H1N1 流感 希格斯玻色子 引力波 | AR35: 电气地铁 圣代冰淇淋 实用水电站 手电 电影摄影机 收音机 霍乱疫苗 啤酒瓶盖 柴油发动机 双向电报 | AS35: 霍乱疫苗 啤酒瓶盖 柴油发动机 双向电报 | AT35: 1892
C36: 年龄 | D36: 最终值 | I36: 毒剂示例 | O36: 裤兜 | X36: 克苏鲁神话 | Z36: 5 | AA36: 五 | AE36: 1893 | AF36: 新西兰给予女性投票权 | AG36: 第一次里夫战争 | AI36: —— | AL36: 十九世纪纪 九十年代 | AM36: 癸巳蛇年 | AN36: 清光绪19年 | AO36: 飓风造成的洪水袭击美国南部西海岸 ,死亡 2000 人 首个实用的胶卷 块麦片 芝加哥万国博览会 | AP36: 总统： 本杰明·哈里森（共和党） 格罗佛·克利夫兰（民主党） | AQ36: 电报 可口可乐 X射线 卷烟机发明 电影放映机 排球 印名片机福特车 潜望镜 油印蜡纸发明 阴极射线管 商品阿司匹林 凯洛格牌玉米片 手电筒 钋 镭 摇控器 α粒子 β粒子 打字机 柯达布朗尼相机 齐柏林飞艇 人类血型 跨大西洋电报 汽轮机游船 现代柏油路 铝罐奶粉 爆米花 泰迪熊 卡鲁索电唱机 便宜的肥皂和烹饪用油 飞机 荧光灯 邮戳机 摩托车发动机 热水瓶 农业轨道机械 木棉安全带 电动汽车喇叭 化学泡沫灭火器 狭义相对论 自动点唱机 量产舰艇舷外发动机 动画 电动洗衣机 家用洗洁精 立式吸尘器 饮用纸杯 双层公交车 无线电测向仪 电煎锅 质子和电子 玻璃纸 战壕风衣 汽车自动起动器 麦片 氯气毒气 防毒面具 拉链 机械雨刮器 广义相对论 芥子气 量产拖拉机 电子钟 黄油枪 降落伞 广播电台播音 茶包 罗夏墨迹测验 机器人 胰岛素 实用邮戳机 滑水 百日咳疫苗 纸制鸡蛋托 面巾纸 商用飞机农药喷撒 液体燃料火箭 劳力士防水表 遥控电唱机 面包机 防水玻璃纸 电传打字机 盖革计数器 纯维生素C 彩色电影胶片 透明胶带 音乐汽车喇叭 闪光灯 速冻食品 球形潜水舱 回旋加速器 折叠式雨伞 电动剃须刀 车载收音机 玛氏巧克力棒 变焦镜头 大富翁桌游 商业洗衣店 畅销平装书 里氏震级 磁带录音机 大众汽车 超市推车 带温控器的电熨斗 速溶咖啡 尼龙 圆珠笔 黄热病疫苗 雷达 汽车自动变速箱 充气救生衣 人工授精 青霉素 军用吉普车 原子裂变 火箭筒 凝固汽油弹 水肺 麦角酸二乙酰胺 神经毒气 原子弹 特百惠 计算机 静电复印法 比基尼泳衣 浓缩咖啡机 宝丽来相机 拼字盘 实心电吉他 尼龙扣 晶体管 黑胶唱片 有线电视 电视显像管 汽车自动点火装置 信用卡 复印机 宽荧幕电影 动力转向器 三色停车灯 人行红绿灯 晶体管助听器 氢弹 录像带 DNA双螺旋结构 麻疹疫苗 按动圆珠笔 硅晶体管 核导弹 空对空导弹 迪士尼乐园 特氟龙 卡丁车 地对空核导弹 沙宾疫苗 通讯卫星 呼啦圈 安全带 人工肾脏 避孕药 气象卫星 便携晶体管收音机 安定 砷化镓半导体激光器 三维全息技术 合成器 香烟健康警示 凯夫拉纤维 子午胎 IBM文字处理机 杜比A型降噪器 滑雪板 喇叭裤 绕月载人火箭 人工心脏移植 波音747喷气式客机 互联网 条形码 软盘 帆板 热裤 液晶显示 便携电子计算器 电视游戏 DNA重组技术 电子游戏机 超级计算机 光纤 试管婴儿 魔方 索尼Walkman 杜比C型降噪器 艾滋病毒 强效可卡因 温室效应 CD 暗物质 暗能量 太阳能飞行器 甲型H1N1 流感 希格斯玻色子 引力波 | AR36: 电气地铁 圣代冰淇淋 实用水电站 手电 电影摄影机 收音机 霍乱疫苗 啤酒瓶盖 柴油发动机 双向电报 实用的胶卷 块麦片 | AS36: 实用的胶卷 块麦片 | AT36: 1893 | AV36: 电报 可口可乐
C37: =ABS(人物卡!E4) -> 29 | D37: =IF(ISBLANK(人物卡!AU38),IF(AND(C37>=15,C37<=19),D39,IF(AND(C37>=20,C37<=39),D40,IF(AND(C37>=40,C37<=49),D41,IF(AND(C37>=50,C37<=59),D42,IF(AND(C37>=60,C37<=69),D43,IF(AND(C37>=70,C37<=79),D44,IF(AND(C37>=80,C37<=89),D45,IF(ABS(C37)>=90,D48,"请和kp商议")))))))),人物卡!AU38) -> 教育进步*1 | I37: 毒剂名称 | J37: 生效时间 | K37: 症状 | L37: 伤害 | M37: 备注 | O37: 其他(服) | X37: 乔装 | Z37: 6 | AA37: 六 | AE37: 1894 | AF37: 朝鲜东学党起义 | AG37: 奥林匹克委员会成立 | AI37: 中日甲午战争 | AJ37: 孙中山建立兴中会 | AL37: 十九世纪纪 九十年代 | AM37: 甲午马年 | AN37: 清光绪20年 | AO37: 明尼苏达森林大火，死亡 480 人 德雷福斯事件，其被流放魔鬼岛 首份电报 瓶装可口可乐 | AP37: 总统： 格罗佛·克利夫兰（民主党） | AQ37: X射线 卷烟机发明 电影放映机 排球 印名片机福特车 潜望镜 油印蜡纸发明 阴极射线管 商品阿司匹林 凯洛格牌玉米片 手电筒 钋 镭 摇控器 α粒子 β粒子 打字机 柯达布朗尼相机 齐柏林飞艇 人类血型 跨大西洋电报 汽轮机游船 现代柏油路 铝罐奶粉 爆米花 泰迪熊 卡鲁索电唱机 便宜的肥皂和烹饪用油 飞机 荧光灯 邮戳机 摩托车发动机 热水瓶 农业轨道机械 木棉安全带 电动汽车喇叭 化学泡沫灭火器 狭义相对论 自动点唱机 量产舰艇舷外发动机 动画 电动洗衣机 家用洗洁精 立式吸尘器 饮用纸杯 双层公交车 无线电测向仪 电煎锅 质子和电子 玻璃纸 战壕风衣 汽车自动起动器 麦片 氯气毒气 防毒面具 拉链 机械雨刮器 广义相对论 芥子气 量产拖拉机 电子钟 黄油枪 降落伞 广播电台播音 茶包 罗夏墨迹测验 机器人 胰岛素 实用邮戳机 滑水 百日咳疫苗 纸制鸡蛋托 面巾纸 商用飞机农药喷撒 液体燃料火箭 劳力士防水表 遥控电唱机 面包机 防水玻璃纸 电传打字机 盖革计数器 纯维生素C 彩色电影胶片 透明胶带 音乐汽车喇叭 闪光灯 速冻食品 球形潜水舱 回旋加速器 折叠式雨伞 电动剃须刀 车载收音机 玛氏巧克力棒 变焦镜头 大富翁桌游 商业洗衣店 畅销平装书 里氏震级 磁带录音机 大众汽车 超市推车 带温控器的电熨斗 速溶咖啡 尼龙 圆珠笔 黄热病疫苗 雷达 汽车自动变速箱 充气救生衣 人工授精 青霉素 军用吉普车 原子裂变 火箭筒 凝固汽油弹 水肺 麦角酸二乙酰胺 神经毒气 原子弹 特百惠 计算机 静电复印法 比基尼泳衣 浓缩咖啡机 宝丽来相机 拼字盘 实心电吉他 尼龙扣 晶体管 黑胶唱片 有线电视 电视显像管 汽车自动点火装置 信用卡 复印机 宽荧幕电影 动力转向器 三色停车灯 人行红绿灯 晶体管助听器 氢弹 录像带 DNA双螺旋结构 麻疹疫苗 按动圆珠笔 硅晶体管 核导弹 空对空导弹 迪士尼乐园 特氟龙 卡丁车 地对空核导弹 沙宾疫苗 通讯卫星 呼啦圈 安全带 人工肾脏 避孕药 气象卫星 便携晶体管收音机 安定 砷化镓半导体激光器 三维全息技术 合成器 香烟健康警示 凯夫拉纤维 子午胎 IBM文字处理机 杜比A型降噪器 滑雪板 喇叭裤 绕月载人火箭 人工心脏移植 波音747喷气式客机 互联网 条形码 软盘 帆板 热裤 液晶显示 便携电子计算器 电视游戏 DNA重组技术 电子游戏机 超级计算机 光纤 试管婴儿 魔方 索尼Walkman 杜比C型降噪器 艾滋病毒 强效可卡因 温室效应 CD 暗物质 暗能量 太阳能飞行器 甲型H1N1 流感 希格斯玻色子 引力波 | AR37: 电气地铁 圣代冰淇淋 实用水电站 手电 电影摄影机 收音机 霍乱疫苗 啤酒瓶盖 柴油发动机 双向电报 实用的胶卷 块麦片 电报 可口可乐 | AS37: 电报 可口可乐 | AT37: 1894
C38: 年龄年龄补正 | I38: 鹅膏菌（毒蘑菇） | J38: 6～24小时 | K38: 剧烈腹痛、呕吐、黄疸 | L38: 1D10 | M38: 造成了95%的毒蘑菇致死事件，鬼笔鹅膏是最常见的一种蘑菇毒素。 | O38: 上肢———— | X38: 闪避 | Z38: 7 | AA38: 七 | AC38: 任意 | AE38: 1895 | AF38: 台湾民主国成立 | AG38: 台湾民主国被日军占领 | AI38: 《马关条约》 | AJ38: 公车上书 | AL38: 十九世纪纪 九十年代 | AM38: 乙未羊年 | AN38: 清光绪21年 | AO38: 伦琴发现 X 射线 卷烟机发明 卢米埃兄弟制成电影放映机并在巴黎首次放映电影 卡尔斯滕·埃格贝尔格·博克格尔文克成为第一名在南极洲大陆登陆的人 韦廉姆·G·摩根在美国发明排球 | AP38: 总统： 格罗佛·克利夫兰（民主党） | AQ38: 印名片机 福特车 潜望镜 油印蜡纸发明 阴极射线管 商品阿司匹林 凯洛格牌玉米片 手电筒 钋 镭 摇控器 α粒子 β粒子 打字机 柯达布朗尼相机 齐柏林飞艇 人类血型 跨大西洋电报 汽轮机游船 现代柏油路 铝罐奶粉 爆米花 泰迪熊 卡鲁索电唱机 便宜的肥皂和烹饪用油 飞机 荧光灯 邮戳机 摩托车发动机 热水瓶 农业轨道机械 木棉安全带 电动汽车喇叭 化学泡沫灭火器 狭义相对论 自动点唱机 量产舰艇舷外发动机 动画 电动洗衣机 家用洗洁精 立式吸尘器 饮用纸杯 双层公交车 无线电测向仪 电煎锅 质子和电子 玻璃纸 战壕风衣 汽车自动起动器 麦片 氯气毒气 防毒面具 拉链 机械雨刮器 广义相对论 芥子气 量产拖拉机 电子钟 黄油枪 降落伞 广播电台播音 茶包 罗夏墨迹测验 机器人 胰岛素 实用邮戳机 滑水 百日咳疫苗 纸制鸡蛋托 面巾纸 商用飞机农药喷撒 液体燃料火箭 劳力士防水表 遥控电唱机 面包机 防水玻璃纸 电传打字机 盖革计数器 纯维生素C 彩色电影胶片 透明胶带 音乐汽车喇叭 闪光灯 速冻食品 球形潜水舱 回旋加速器 折叠式雨伞 电动剃须刀 车载收音机 玛氏巧克力棒 变焦镜头 大富翁桌游 商业洗衣店 畅销平装书 里氏震级 磁带录音机 大众汽车 超市推车 带温控器的电熨斗 速溶咖啡 尼龙 圆珠笔 黄热病疫苗 雷达 汽车自动变速箱 充气救生衣 人工授精 青霉素 军用吉普车 原子裂变 火箭筒 凝固汽油弹 水肺 麦角酸二乙酰胺 神经毒气 原子弹 特百惠 计算机 静电复印法 比基尼泳衣 浓缩咖啡机 宝丽来相机 拼字盘 实心电吉他 尼龙扣 晶体管 黑胶唱片 有线电视 电视显像管 汽车自动点火装置 信用卡 复印机 宽荧幕电影 动力转向器 三色停车灯 人行红绿灯 晶体管助听器 氢弹 录像带 DNA双螺旋结构 麻疹疫苗 按动圆珠笔 硅晶体管 核导弹 空对空导弹 迪士尼乐园 特氟龙 卡丁车 地对空核导弹 沙宾疫苗 通讯卫星 呼啦圈 安全带 人工肾脏 避孕药 气象卫星 便携晶体管收音机 安定 砷化镓半导体激光器 三维全息技术 合成器 香烟健康警示 凯夫拉纤维 子午胎 IBM文字处理机 杜比A型降噪器 滑雪板 喇叭裤 绕月载人火箭 人工心脏移植 波音747喷气式客机 互联网 条形码 软盘 帆板 热裤 液晶显示 便携电子计算器 电视游戏 DNA重组技术 电子游戏机 超级计算机 光纤 试管婴儿 魔方 索尼Walkman 杜比C型降噪器 艾滋病毒 强效可卡因 温室效应 CD 暗物质 暗能量 太阳能飞行器 甲型H1N1 流感 希格斯玻色子 引力波 | AR38: 电气地铁 圣代冰淇淋 实用水电站 手电 电影摄影机 收音机 霍乱疫苗 啤酒瓶盖 柴油发动机 双向电报 实用的胶卷 块麦片 电报 可口可乐 X射线 卷烟机 电影放映机 排球 | AS38: X 射线 卷烟机 电影放映机 排球 | AT38: 1895 | AV38: =IF(AV36="仅显示1890~2012","",VLOOKUP(AV36,AS33:AT155,2,FALSE)) -> 1894
B39: 15 | C39: 19 | D39: 力量体型共-5 E-5 L*2 | I39: 砷化物 | J39: 30分钟～24小时 | K39: 灼痛、呕吐、剧烈腹泻 | L39: 4D10 | M39: 砷中毒难以确认（这使得它作为毒杀工具大受欢迎），直到1836年马氏试砷法发明为止。 | O39: 左手 | X39: 汽车驾驶 | Z39: 8 | AA39: 八 | AC39: 会计 | AE39: 1896 | AF39: 雅典奥运会 | AI39: 《中俄密约》 | AL39: 十九世纪纪 九十年代 | AM39: 丙申猴年 | AN39: 清光绪22年 | AO39: 克朗代克淘金热 印名片机取得专利 首辆福特车 潜望镜 雅典举办首届奥运会 | AP39: 总统： 格罗佛·克利夫兰（民主党） | AQ39: 油印蜡纸发明 阴极射线管 商品阿司匹林 凯洛格牌玉米片 手电筒 钋 镭 摇控器 α粒子 β粒子 打字机 柯达布朗尼相机 齐柏林飞艇 人类血型 跨大西洋电报 汽轮机游船 现代柏油路 铝罐奶粉 爆米花 泰迪熊 卡鲁索电唱机 便宜的肥皂和烹饪用油 飞机 荧光灯 邮戳机 摩托车发动机 热水瓶 农业轨道机械 木棉安全带 电动汽车喇叭 化学泡沫灭火器 狭义相对论 自动点唱机 量产舰艇舷外发动机 动画 电动洗衣机 家用洗洁精 立式吸尘器 饮用纸杯 双层公交车 无线电测向仪 电煎锅 质子和电子 玻璃纸 战壕风衣 汽车自动起动器 麦片 氯气毒气 防毒面具 拉链 机械雨刮器 广义相对论 芥子气 量产拖拉机 电子钟 黄油枪 降落伞 广播电台播音 茶包 罗夏墨迹测验 机器人 胰岛素 实用邮戳机 滑水 百日咳疫苗 纸制鸡蛋托 面巾纸 商用飞机农药喷撒 液体燃料火箭 劳力士防水表 遥控电唱机 面包机 防水玻璃纸 电传打字机 盖革计数器 纯维生素C 彩色电影胶片 透明胶带 音乐汽车喇叭 闪光灯 速冻食品 球形潜水舱 回旋加速器 折叠式雨伞 电动剃须刀 车载收音机 玛氏巧克力棒 变焦镜头 大富翁桌游 商业洗衣店 畅销平装书 里氏震级 磁带录音机 大众汽车 超市推车 带温控器的电熨斗 速溶咖啡 尼龙 圆珠笔 黄热病疫苗 雷达 汽车自动变速箱 充气救生衣 人工授精 青霉素 军用吉普车 原子裂变 火箭筒 凝固汽油弹 水肺 麦角酸二乙酰胺 神经毒气 原子弹 特百惠 计算机 静电复印法 比基尼泳衣 浓缩咖啡机 宝丽来相机 拼字盘 实心电吉他 尼龙扣 晶体管 黑胶唱片 有线电视 电视显像管 汽车自动点火装置 信用卡 复印机 宽荧幕电影 动力转向器 三色停车灯 人行红绿灯 晶体管助听器 氢弹 录像带 DNA双螺旋结构 麻疹疫苗 按动圆珠笔 硅晶体管 核导弹 空对空导弹 迪士尼乐园 特氟龙 卡丁车 地对空核导弹 沙宾疫苗 通讯卫星 呼啦圈 安全带 人工肾脏 避孕药 气象卫星 便携晶体管收音机 安定 砷化镓半导体激光器 三维全息技术 合成器 香烟健康警示 凯夫拉纤维 子午胎 IBM文字处理机 杜比A型降噪器 滑雪板 喇叭裤 绕月载人火箭 人工心脏移植 波音747喷气式客机 互联网 条形码 软盘 帆板 热裤 液晶显示 便携电子计算器 电视游戏 DNA重组技术 电子游戏机 超级计算机 光纤 试管婴儿 魔方 索尼Walkman 杜比C型降噪器 艾滋病毒 强效可卡因 温室效应 CD 暗物质 暗能量 太阳能飞行器 甲型H1N1 流感 希格斯玻色子 引力波 | AR39: 电气地铁 圣代冰淇淋 实用水电站 手电 电影摄影机 收音机 霍乱疫苗 啤酒瓶盖 柴油发动机 双向电报 实用的胶卷 块麦片 电报 可口可乐 X射线 卷烟机发明 电影放映机 排球 印名片机 福特车 潜望镜 | AS39: 印名片机 福特车 潜望镜 | AT39: 1896
B40: 20 | C40: 39 | D40: 教育进步*1 | I40: 颠茄 | J40: 2小时～2天 | K40: 心率加快、视力受损、惊厥 | L40: 4D10 | M40: 世纪界上毒性最大的植物之一，成人食用10～20颗就可能死亡。 | O40: 右手 | S40: =IF(人物卡!J17=人物卡!R17,"",人物卡!F17&人物卡!R17) | T40: =IF(人物卡!AF17=人物卡!AN17,"",人物卡!AB17&人物卡!AN17) | U40: =".st "&"力量"&G14&"str"&G14&"敏捷"&J14&"dex"&J14&"意志"&M14&"pow"&M14&"体质"&H14&"con"&H14&"外貌"&K14&"app"&K14&"教育"&N14&"edu"&N14&"体型"&I14&"siz"&I14&"智力"&L14&"灵感"&L14&"int"&L14&"san"&人物卡!N10&"san值"&人物卡!N10&"理智"&人物卡!N10&"理智值"&人物卡!N10&"幸运"&O14&"运气"&O14&"mp"&人物卡!W10&"魔法"&人物卡!W10&"hp"&人物卡!E10&"体力"&人物卡!E10&S40&S41&S42&S43&S44&S45&S46&S47&S48&S49&S50&S51&S52&S53&S54&S55&S57&S56&S58&S59&S60&S61&S62&S63&S64&S65&S66&S67&S68&S69&S70&S71&S72&S73&T72&T71&T73&T70&T69&T68&T40&T41&T42&T43&T44&T45&T47&T46&T48&T50&T49&T51&T53&T54&T56&T60&T64&T66&T67&T65&T55&T52&T57&T58&T59&T61&T62&T63 -> .st 力量30str30敏捷70dex70意志60pow60体质50con50外貌80app80教育55edu55体型55siz55智力80灵感80int80san60san值60理智60理智值60幸运50运气50mp12魔法12hp10体力10取悦70信用评级20闪避60话术70聆听70锁匠71心理学60潜行60侦查80 | X40: 电气维修 | Z40: 9 | AA40: 九 | AC40: 人类学 | AE40: 1897 | AF40: —— | AI40: —— | AL40: 十九世纪纪 九十年代 | AM40: 丁酉鸡年 | AN40: 清光绪23年 | AO40: 油印蜡纸发明 首个阴极射线管 | AP40: 总统： 格罗佛·克利夫兰（民主党） 威廉·麦金利（共和党） | AQ40: 商品阿司匹林 凯洛格牌玉米片 手电筒 钋 镭 摇控器 α粒子 β粒子 打字机 柯达布朗尼相机 齐柏林飞艇 人类血型 跨大西洋电报 汽轮机游船 现代柏油路 铝罐奶粉 爆米花 泰迪熊 卡鲁索电唱机 便宜的肥皂和烹饪用油 飞机 荧光灯 邮戳机 摩托车发动机 热水瓶 农业轨道机械 木棉安全带 电动汽车喇叭 化学泡沫灭火器 狭义相对论 自动点唱机 量产舰艇舷外发动机 动画 电动洗衣机 家用洗洁精 立式吸尘器 饮用纸杯 双层公交车 无线电测向仪 电煎锅 质子和电子 玻璃纸 战壕风衣 汽车自动起动器 麦片 氯气毒气 防毒面具 拉链 机械雨刮器 广义相对论 芥子气 量产拖拉机 电子钟 黄油枪 降落伞 广播电台播音 茶包 罗夏墨迹测验 机器人 胰岛素 实用邮戳机 滑水 百日咳疫苗 纸制鸡蛋托 面巾纸 商用飞机农药喷撒 液体燃料火箭 劳力士防水表 遥控电唱机 面包机 防水玻璃纸 电传打字机 盖革计数器 纯维生素C 彩色电影胶片 透明胶带 音乐汽车喇叭 闪光灯 速冻食品 球形潜水舱 回旋加速器 折叠式雨伞 电动剃须刀 车载收音机 玛氏巧克力棒 变焦镜头 大富翁桌游 商业洗衣店 畅销平装书 里氏震级 磁带录音机 大众汽车 超市推车 带温控器的电熨斗 速溶咖啡 尼龙 圆珠笔 黄热病疫苗 雷达 汽车自动变速箱 充气救生衣 人工授精 青霉素 军用吉普车 原子裂变 火箭筒 凝固汽油弹 水肺 麦角酸二乙酰胺 神经毒气 原子弹 特百惠 计算机 静电复印法 比基尼泳衣 浓缩咖啡机 宝丽来相机 拼字盘 实心电吉他 尼龙扣 晶体管 黑胶唱片 有线电视 电视显像管 汽车自动点火装置 信用卡 复印机 宽荧幕电影 动力转向器 三色停车灯 人行红绿灯 晶体管助听器 氢弹 录像带 DNA双螺旋结构 麻疹疫苗 按动圆珠笔 硅晶体管 核导弹 空对空导弹 迪士尼乐园 特氟龙 卡丁车 地对空核导弹 沙宾疫苗 通讯卫星 呼啦圈 安全带 人工肾脏 避孕药 气象卫星 便携晶体管收音机 安定 砷化镓半导体激光器 三维全息技术 合成器 香烟健康警示 凯夫拉纤维 子午胎 IBM文字处理机 杜比A型降噪器 滑雪板 喇叭裤 绕月载人火箭 人工心脏移植 波音747喷气式客机 互联网 条形码 软盘 帆板 热裤 液晶显示 便携电子计算器 电视游戏 DNA重组技术 电子游戏机 超级计算机 光纤 试管婴儿 魔方 索尼Walkman 杜比C型降噪器 艾滋病毒 强效可卡因 温室效应 CD 暗物质 暗能量 太阳能飞行器 甲型H1N1 流感 希格斯玻色子 引力波 | AR40: 电气地铁 圣代冰淇淋 实用水电站 手电 电影摄影机 收音机 霍乱疫苗 啤酒瓶盖 柴油发动机 双向电报 实用的胶卷 块麦片 电报 可口可乐 X射线 卷烟机发明 电影放映机 排球 印名片机 福特车 潜望镜 油印蜡纸发明 阴极射线管 | AS40: 油印蜡纸发明 阴极射线管 | AT40: 1897
B41: 40 | C41: 49 | D41: 进步*2,SCD共-5 A-5 | I41: 黑寡妇蜘蛛毒 | J41: 2～8小时 | K41: 寒战、出汗、恶心 | L41: 1D10 | M41: 如果及时进行医治，基本不会死亡。 | O41: 双手 | S41: =IF(人物卡!J18=人物卡!R18,"",人物卡!F18&人物卡!R18) | T41: =IF(人物卡!AF18=人物卡!AN18,"",人物卡!AB18&人物卡!AN18) | X41: 电子学 Ω | AC41: 估价 | AE41: 1898 | AF41: 美西战争 | AG41: 美国兼并夏威夷共和国 | AI41: 戊戌变法/百日维新 | AL41: 十九世纪纪 九十年代 | AM41: 戊戌狗年 | AN41: 清光绪24年 | AO41: 飓风袭击美国南部数百人死亡 美西战争，死亡 2446 美军 唱片普及 商品阿司匹林出现 凯洛格牌玉米片 手电筒 居里夫妇宣布发现新的放射性元素钋 居里夫妇发现了化学元素镭 尼古拉·特斯拉开发第一个摇控器 | AP41: 总统： 威廉·麦金利（共和党） | AQ41: α粒子 β粒子 打字机 柯达布朗尼相机 齐柏林飞艇 人类血型 跨大西洋电报 汽轮机游船 现代柏油路 铝罐奶粉 爆米花 泰迪熊 卡鲁索电唱机 便宜的肥皂和烹饪用油 飞机 荧光灯 邮戳机 摩托车发动机 热水瓶 农业轨道机械 木棉安全带 电动汽车喇叭 化学泡沫灭火器 狭义相对论 自动点唱机 量产舰艇舷外发动机 动画 电动洗衣机 家用洗洁精 立式吸尘器 饮用纸杯 双层公交车 无线电测向仪 电煎锅 质子和电子 玻璃纸 战壕风衣 汽车自动起动器 麦片 氯气毒气 防毒面具 拉链 机械雨刮器 广义相对论 芥子气 量产拖拉机 电子钟 黄油枪 降落伞 广播电台播音 茶包 罗夏墨迹测验 机器人 胰岛素 实用邮戳机 滑水 百日咳疫苗 纸制鸡蛋托 面巾纸 商用飞机农药喷撒 液体燃料火箭 劳力士防水表 遥控电唱机 面包机 防水玻璃纸 电传打字机 盖革计数器 纯维生素C 彩色电影胶片 透明胶带 音乐汽车喇叭 闪光灯 速冻食品 球形潜水舱 回旋加速器 折叠式雨伞 电动剃须刀 车载收音机 玛氏巧克力棒 变焦镜头 大富翁桌游 商业洗衣店 畅销平装书 里氏震级 磁带录音机 大众汽车 超市推车 带温控器的电熨斗 速溶咖啡 尼龙 圆珠笔 黄热病疫苗 雷达 汽车自动变速箱 充气救生衣 人工授精 青霉素 军用吉普车 原子裂变 火箭筒 凝固汽油弹 水肺 麦角酸二乙酰胺 神经毒气 原子弹 特百惠 计算机 静电复印法 比基尼泳衣 浓缩咖啡机 宝丽来相机 拼字盘 实心电吉他 尼龙扣 晶体管 黑胶唱片 有线电视 电视显像管 汽车自动点火装置 信用卡 复印机 宽荧幕电影 动力转向器 三色停车灯 人行红绿灯 晶体管助听器 氢弹 录像带 DNA双螺旋结构 麻疹疫苗 按动圆珠笔 硅晶体管 核导弹 空对空导弹 迪士尼乐园 特氟龙 卡丁车 地对空核导弹 沙宾疫苗 通讯卫星 呼啦圈 安全带 人工肾脏 避孕药 气象卫星 便携晶体管收音机 安定 砷化镓半导体激光器 三维全息技术 合成器 香烟健康警示 凯夫拉纤维 子午胎 IBM文字处理机 杜比A型降噪器 滑雪板 喇叭裤 绕月载人火箭 人工心脏移植 波音747喷气式客机 互联网 条形码 软盘 帆板 热裤 液晶显示 便携电子计算器 电视游戏 DNA重组技术 电子游戏机 超级计算机 光纤 试管婴儿 魔方 索尼Walkman 杜比C型降噪器 艾滋病毒 强效可卡因 温室效应 CD 暗物质 暗能量 太阳能飞行器 甲型H1N1 流感 希格斯玻色子 引力波 | AR41: 电气地铁 圣代冰淇淋 实用水电站 手电 电影摄影机 收音机 霍乱疫苗 啤酒瓶盖 柴油发动机 双向电报 实用的胶卷 块麦片 电报 可口可乐 X射线 卷烟机发明 电影放映机 排球 印名片机 福特车 潜望镜 油印蜡纸发明 阴极射线管 商品阿司匹林 凯洛格牌玉米片 手电筒 钋 镭 摇控器 | AS41: 商品阿司匹林 凯洛格牌玉米片 手电筒 钋 镭 摇控器 | AT41: 1898
B42: 50 | C42: 59 | D42: 进步*3,SCD共-10 A-10 | I42: 三氯甲烷（氯仿） | J42: 1轮 | K42: 昏迷1小时 | L42: 无伤害 | M42: 在1800~1900s是常见的麻醉剂，不过高的摄入量也会致死。 | O42: 左臂 | S42: =IF(人物卡!J19=人物卡!R19,"",人物卡!F19&人物卡!R19) | T42: =IF(人物卡!AF19=人物卡!AN19,"",人物卡!AB19&人物卡!AN19) -> 聆听70 | X42: 话术 | AC42: 考古学 | AE42: 1899 | AF42: 第二次布尔战争 | AI42: —— | AL42: 十九世纪纪 九十年代 | AM42: 己亥猪年 | AN42: 清光绪25年 | AO42: 纽约温莎酒店大火，数百万人受灾，死亡 14 人 卢瑟福发现 α 粒子和 β 粒子 打字机开始普及 | AP42: 总统： 威廉·麦金利（共和党） | AQ42: 柯达布朗尼相机 齐柏林飞艇 人类血型 跨大西洋电报 汽轮机游船 现代柏油路 铝罐奶粉 爆米花 泰迪熊 卡鲁索电唱机 便宜的肥皂和烹饪用油 飞机 荧光灯 邮戳机 摩托车发动机 热水瓶 农业轨道机械 木棉安全带 电动汽车喇叭 化学泡沫灭火器 狭义相对论 自动点唱机 量产舰艇舷外发动机 动画 电动洗衣机 家用洗洁精 立式吸尘器 饮用纸杯 双层公交车 无线电测向仪 电煎锅 质子和电子 玻璃纸 战壕风衣 汽车自动起动器 麦片 氯气毒气 防毒面具 拉链 机械雨刮器 广义相对论 芥子气 量产拖拉机 电子钟 黄油枪 降落伞 广播电台播音 茶包 罗夏墨迹测验 机器人 胰岛素 实用邮戳机 滑水 百日咳疫苗 纸制鸡蛋托 面巾纸 商用飞机农药喷撒 液体燃料火箭 劳力士防水表 遥控电唱机 面包机 防水玻璃纸 电传打字机 盖革计数器 纯维生素C 彩色电影胶片 透明胶带 音乐汽车喇叭 闪光灯 速冻食品 球形潜水舱 回旋加速器 折叠式雨伞 电动剃须刀 车载收音机 玛氏巧克力棒 变焦镜头 大富翁桌游 商业洗衣店 畅销平装书 里氏震级 磁带录音机 大众汽车 超市推车 带温控器的电熨斗 速溶咖啡 尼龙 圆珠笔 黄热病疫苗 雷达 汽车自动变速箱 充气救生衣 人工授精 青霉素 军用吉普车 原子裂变 火箭筒 凝固汽油弹 水肺 麦角酸二乙酰胺 神经毒气 原子弹 特百惠 计算机 静电复印法 比基尼泳衣 浓缩咖啡机 宝丽来相机 拼字盘 实心电吉他 尼龙扣 晶体管 黑胶唱片 有线电视 电视显像管 汽车自动点火装置 信用卡 复印机 宽荧幕电影 动力转向器 三色停车灯 人行红绿灯 晶体管助听器 氢弹 录像带 DNA双螺旋结构 麻疹疫苗 按动圆珠笔 硅晶体管 核导弹 空对空导弹 迪士尼乐园 特氟龙 卡丁车 地对空核导弹 沙宾疫苗 通讯卫星 呼啦圈 安全带 人工肾脏 避孕药 气象卫星 便携晶体管收音机 安定 砷化镓半导体激光器 三维全息技术 合成器 香烟健康警示 凯夫拉纤维 子午胎 IBM文字处理机 杜比A型降噪器 滑雪板 喇叭裤 绕月载人火箭 人工心脏移植 波音747喷气式客机 互联网 条形码 软盘 帆板 热裤 液晶显示 便携电子计算器 电视游戏 DNA重组技术 电子游戏机 超级计算机 光纤 试管婴儿 魔方 索尼Walkman 杜比C型降噪器 艾滋病毒 强效可卡因 温室效应 CD 暗物质 暗能量 太阳能飞行器 甲型H1N1 流感 希格斯玻色子 引力波 | AR42: 电气地铁 圣代冰淇淋 实用水电站 手电 电影摄影机 收音机 霍乱疫苗 啤酒瓶盖 柴油发动机 双向电报 实用的胶卷 块麦片 电报 可口可乐 X射线 卷烟机发明 电影放映机 排球 印名片机 福特车 潜望镜 油印蜡纸发明 阴极射线管 商品阿司匹林 凯洛格牌玉米片 手电筒 钋 镭 摇控器 α粒子 β粒子 打字机 | AS42: α 粒子和 β 粒子 打字机 | AT42: 1899
B43: 60 | C43: 69 | D43: 进步*4,SCD共-20 A-15 | I43: 眼镜蛇毒 | J43: 15～60分钟 | K43: 惊厥、呼吸衰竭 | L43: 4D10 | M43: 接触眼睛会产生直接的刺激，未经处理会失明。如果有血清，可以避免受重伤和死亡。 | O43: 右臂 | S43: =IF(人物卡!J20=人物卡!R20,"",人物卡!F20&人物卡!R20) | T43: =IF(人物卡!AF20=人物卡!AN20,"",人物卡!AB20&人物卡!AN20) -> 锁匠71 | X43: 格斗： | AC43: 技艺 | AE43: 1900 | AF43: 巴黎奥运会 | AG43: 诺贝尔奖基金会 | AI43: 八国联军侵华战争 | AJ43: 庚子国变 | AL43: 二十世纪纪初 | AM43: 庚子鼠年 | AN43: 清光绪26年 | AO43: 码头失火，蒸汽艇里约热内卢号在旧金山港沉没，死亡 128 人 大飓风加尔维斯顿，死亡 6000 人 庚子国变 柯达布朗尼相机 齐柏林伯爵起飞 420 英尺飞艇 美国公债12.63 亿美元 美国人口 760 万。 | AP43: 总统： 威廉·麦金利（共和党） | AQ43: 人类血型 跨大西洋电报 汽轮机游船 现代柏油路 铝罐奶粉 爆米花 泰迪熊 卡鲁索电唱机 便宜的肥皂和烹饪用油 飞机 荧光灯 邮戳机 摩托车发动机 热水瓶 农业轨道机械 木棉安全带 电动汽车喇叭 化学泡沫灭火器 狭义相对论 自动点唱机 量产舰艇舷外发动机 动画 电动洗衣机 家用洗洁精 立式吸尘器 饮用纸杯 双层公交车 无线电测向仪 电煎锅 质子和电子 玻璃纸 战壕风衣 汽车自动起动器 麦片 氯气毒气 防毒面具 拉链 机械雨刮器 广义相对论 芥子气 量产拖拉机 电子钟 黄油枪 降落伞 广播电台播音 茶包 罗夏墨迹测验 机器人 胰岛素 实用邮戳机 滑水 百日咳疫苗 纸制鸡蛋托 面巾纸 商用飞机农药喷撒 液体燃料火箭 劳力士防水表 遥控电唱机 面包机 防水玻璃纸 电传打字机 盖革计数器 纯维生素C 彩色电影胶片 透明胶带 音乐汽车喇叭 闪光灯 速冻食品 球形潜水舱 回旋加速器 折叠式雨伞 电动剃须刀 车载收音机 玛氏巧克力棒 变焦镜头 大富翁桌游 商业洗衣店 畅销平装书 里氏震级 磁带录音机 大众汽车 超市推车 带温控器的电熨斗 速溶咖啡 尼龙 圆珠笔 黄热病疫苗 雷达 汽车自动变速箱 充气救生衣 人工授精 青霉素 军用吉普车 原子裂变 火箭筒 凝固汽油弹 水肺 麦角酸二乙酰胺 神经毒气 原子弹 特百惠 计算机 静电复印法 比基尼泳衣 浓缩咖啡机 宝丽来相机 拼字盘 实心电吉他 尼龙扣 晶体管 黑胶唱片 有线电视 电视显像管 汽车自动点火装置 信用卡 复印机 宽荧幕电影 动力转向器 三色停车灯 人行红绿灯 晶体管助听器 氢弹 录像带 DNA双螺旋结构 麻疹疫苗 按动圆珠笔 硅晶体管 核导弹 空对空导弹 迪士尼乐园 特氟龙 卡丁车 地对空核导弹 沙宾疫苗 通讯卫星 呼啦圈 安全带 人工肾脏 避孕药 气象卫星 便携晶体管收音机 安定 砷化镓半导体激光器 三维全息技术 合成器 香烟健康警示 凯夫拉纤维 子午胎 IBM文字处理机 杜比A型降噪器 滑雪板 喇叭裤 绕月载人火箭 人工心脏移植 波音747喷气式客机 互联网 条形码 软盘 帆板 热裤 液晶显示 便携电子计算器 电视游戏 DNA重组技术 电子游戏机 超级计算机 光纤 试管婴儿 魔方 索尼Walkman 杜比C型降噪器 艾滋病毒 强效可卡因 温室效应 CD 暗物质 暗能量 太阳能飞行器 甲型H1N1 流感 希格斯玻色子 引力波 | AR43: 电气地铁 圣代冰淇淋 实用水电站 手电 电影摄影机 收音机 霍乱疫苗 啤酒瓶盖 柴油发动机 双向电报 实用的胶卷 块麦片 电报 可口可乐 X射线 卷烟机发明 电影放映机 排球 印名片机 福特车 潜望镜 油印蜡纸发明 阴极射线管 商品阿司匹林 凯洛格牌玉米片 手电筒 钋 镭 摇控器 α粒子 β粒子 打字机 柯达布朗尼相机 齐柏林飞艇 | AS43: 柯达布朗尼相机 齐柏林飞艇 | AT43: 1900
B44: 70 | C44: 79 | D44: 进步*4,SCD共-40 A-20 | I44: 箭毒碱 | J44: 1轮 | K44: 肌肉麻痹、呼吸衰竭。 | L44: 4D10 | M44: 南美洲人涂在箭上毒剂的通称。口服无害，只有通过皮肤伤口直接侵入才会导致瘫痪。 | O44: 双臂 | S44: =IF(人物卡!J21=人物卡!R21,"",IF(ISBLANK(人物卡!H21),"技艺"&人物卡!R21,人物卡!H21&人物卡!R21)) | T44: =IF(人物卡!AF21=人物卡!AN21,"",人物卡!AB21&人物卡!AN21) | X44: 格斗① | AC44: 取悦 | AE44: 1901 | AF44: 维多利亚时代结束（英国） | AI44: 《辛丑条约》 | AL44: 二十世纪纪初 | AM44: 辛丑牛年 | AN44: 清光绪27年 | AO44: 麦金莱总统遇刺 美国两次爆发伤寒 维多利亚女王逝世纪 人类血型发现 首份跨越大西洋电报 | AP44: 总统： 威廉·麦金利（共和党） 西奥多·罗斯福（共和党） | AQ44: 汽轮机游船 现代柏油路 铝罐奶粉 爆米花 泰迪熊 卡鲁索电唱机 便宜的肥皂和烹饪用油 飞机 荧光灯 邮戳机 摩托车发动机 热水瓶 农业轨道机械 木棉安全带 电动汽车喇叭 化学泡沫灭火器 狭义相对论 自动点唱机 量产舰艇舷外发动机 动画 电动洗衣机 家用洗洁精 立式吸尘器 饮用纸杯 双层公交车 无线电测向仪 电煎锅 质子和电子 玻璃纸 战壕风衣 汽车自动起动器 麦片 氯气毒气 防毒面具 拉链 机械雨刮器 广义相对论 芥子气 量产拖拉机 电子钟 黄油枪 降落伞 广播电台播音 茶包 罗夏墨迹测验 机器人 胰岛素 实用邮戳机 滑水 百日咳疫苗 纸制鸡蛋托 面巾纸 商用飞机农药喷撒 液体燃料火箭 劳力士防水表 遥控电唱机 面包机 防水玻璃纸 电传打字机 盖革计数器 纯维生素C 彩色电影胶片 透明胶带 音乐汽车喇叭 闪光灯 速冻食品 球形潜水舱 回旋加速器 折叠式雨伞 电动剃须刀 车载收音机 玛氏巧克力棒 变焦镜头 大富翁桌游 商业洗衣店 畅销平装书 里氏震级 磁带录音机 大众汽车 超市推车 带温控器的电熨斗 速溶咖啡 尼龙 圆珠笔 黄热病疫苗 雷达 汽车自动变速箱 充气救生衣 人工授精 青霉素 军用吉普车 原子裂变 火箭筒 凝固汽油弹 水肺 麦角酸二乙酰胺 神经毒气 原子弹 特百惠 计算机 静电复印法 比基尼泳衣 浓缩咖啡机 宝丽来相机 拼字盘 实心电吉他 尼龙扣 晶体管 黑胶唱片 有线电视 电视显像管 汽车自动点火装置 信用卡 复印机 宽荧幕电影 动力转向器 三色停车灯 人行红绿灯 晶体管助听器 氢弹 录像带 DNA双螺旋结构 麻疹疫苗 按动圆珠笔 硅晶体管 核导弹 空对空导弹 迪士尼乐园 特氟龙 卡丁车 地对空核导弹 沙宾疫苗 通讯卫星 呼啦圈 安全带 人工肾脏 避孕药 气象卫星 便携晶体管收音机 安定 砷化镓半导体激光器 三维全息技术 合成器 香烟健康警示 凯夫拉纤维 子午胎 IBM文字处理机 杜比A型降噪器 滑雪板 喇叭裤 绕月载人火箭 人工心脏移植 波音747喷气式客机 互联网 条形码 软盘 帆板 热裤 液晶显示 便携电子计算器 电视游戏 DNA重组技术 电子游戏机 超级计算机 光纤 试管婴儿 魔方 索尼Walkman 杜比C型降噪器 艾滋病毒 强效可卡因 温室效应 CD 暗物质 暗能量 太阳能飞行器 甲型H1N1 流感 希格斯玻色子 引力波 | AR44: 电气地铁 圣代冰淇淋 实用水电站 手电 电影摄影机 收音机 霍乱疫苗 啤酒瓶盖 柴油发动机 双向电报 实用的胶卷 块麦片 电报 可口可乐 X射线 卷烟机发明 电影放映机 排球 印名片机 福特车 潜望镜 油印蜡纸发明 阴极射线管 商品阿司匹林 凯洛格牌玉米片 手电筒 钋 镭 摇控器 α粒子 β粒子 打字机 柯达布朗尼相机 齐柏林飞艇 人类血型 跨大西洋电报 | AS44: 人类血型 跨大西洋电报 | AT44: 1901
B45: 80 | C45: 89 | D45: 进步*4,SCD共-80 A-25 | I45: 氰化物 | J45: 1～15分钟 | K45: 眩晕、惊厥、晕厥、死亡。 | L45: 4D10 | M45: 剧毒——摄入了氰化物盐或者通过气体吸入都会致死。 | O45: 肘部 | S45: =IF(人物卡!J22=人物卡!R22,"",IF(ISBLANK(人物卡!H22),"技艺"&人物卡!R22,人物卡!H22&人物卡!R22)) | T45: =IF(人物卡!AF22=人物卡!AN22,"",人物卡!AB22&人物卡!AN22) | X45: 格斗② | AC45: 攀爬 | AE45: 1902 | AF45: 第二次布尔战争结束 | AI45: —— | AL45: 二十世纪纪初 | AM45: 壬寅虎年 | AN45: 清光绪28年 | AO45: 布尔战争 马提尼克（中美洲岛屿 ) 培雷火山爆发，死亡 4 万人 首个汽轮机游船 现代柏油路产生 首个铝罐奶粉 爆米花 首个泰迪熊 首个卡鲁索电唱机 商用氢化油脂使得制皂和烹饪用油来源增加 | AP45: 总统： 西奥多·罗斯福（共和党） | AQ45: 飞机 荧光灯 邮戳机 摩托车发动机 热水瓶 农业轨道机械 木棉安全带 电动汽车喇叭 化学泡沫灭火器 狭义相对论 自动点唱机 量产舰艇舷外发动机 动画 电动洗衣机 家用洗洁精 立式吸尘器 饮用纸杯 双层公交车 无线电测向仪 电煎锅 质子和电子 玻璃纸 战壕风衣 汽车自动起动器 麦片 氯气毒气 防毒面具 拉链 机械雨刮器 广义相对论 芥子气 量产拖拉机 电子钟 黄油枪 降落伞 广播电台播音 茶包 罗夏墨迹测验 机器人 胰岛素 实用邮戳机 滑水 百日咳疫苗 纸制鸡蛋托 面巾纸 商用飞机农药喷撒 液体燃料火箭 劳力士防水表 遥控电唱机 面包机 防水玻璃纸 电传打字机 盖革计数器 纯维生素C 彩色电影胶片 透明胶带 音乐汽车喇叭 闪光灯 速冻食品 球形潜水舱 回旋加速器 折叠式雨伞 电动剃须刀 车载收音机 玛氏巧克力棒 变焦镜头 大富翁桌游 商业洗衣店 畅销平装书 里氏震级 磁带录音机 大众汽车 超市推车 带温控器的电熨斗 速溶咖啡 尼龙 圆珠笔 黄热病疫苗 雷达 汽车自动变速箱 充气救生衣 人工授精 青霉素 军用吉普车 原子裂变 火箭筒 凝固汽油弹 水肺 麦角酸二乙酰胺 神经毒气 原子弹 特百惠 计算机 静电复印法 比基尼泳衣 浓缩咖啡机 宝丽来相机 拼字盘 实心电吉他 尼龙扣 晶体管 黑胶唱片 有线电视 电视显像管 汽车自动点火装置 信用卡 复印机 宽荧幕电影 动力转向器 三色停车灯 人行红绿灯 晶体管助听器 氢弹 录像带 DNA双螺旋结构 麻疹疫苗 按动圆珠笔 硅晶体管 核导弹 空对空导弹 迪士尼乐园 特氟龙 卡丁车 地对空核导弹 沙宾疫苗 通讯卫星 呼啦圈 安全带 人工肾脏 避孕药 气象卫星 便携晶体管收音机 安定 砷化镓半导体激光器 三维全息技术 合成器 香烟健康警示 凯夫拉纤维 子午胎 IBM文字处理机 杜比A型降噪器 滑雪板 喇叭裤 绕月载人火箭 人工心脏移植 波音747喷气式客机 互联网 条形码 软盘 帆板 热裤 液晶显示 便携电子计算器 电视游戏 DNA重组技术 电子游戏机 超级计算机 光纤 试管婴儿 魔方 索尼Walkman 杜比C型降噪器 艾滋病毒 强效可卡因 温室效应 CD 暗物质 暗能量 太阳能飞行器 甲型H1N1 流感 希格斯玻色子 引力波 | AR45: 电气地铁 圣代冰淇淋 实用水电站 手电 电影摄影机 收音机 霍乱疫苗 啤酒瓶盖 柴油发动机 双向电报 实用的胶卷 块麦片 电报 可口可乐 X射线 卷烟机发明 电影放映机 排球 印名片机 福特车 潜望镜 油印蜡纸发明 阴极射线管 商品阿司匹林 凯洛格牌玉米片 手电筒 钋 镭 摇控器 α粒子 β粒子 打字机 柯达布朗尼相机 齐柏林飞艇 人类血型 跨大西洋电报 汽轮机游船 现代柏油路 铝罐奶粉 爆米花 泰迪熊 卡鲁索电唱机 便宜的肥皂和烹饪用油 | AS45: 汽轮机游船 现代柏油路 铝罐奶粉 爆米花 泰迪熊 卡鲁索电唱机 便宜的肥皂和烹饪用油 | AT45: 1902
C46: 年龄倍数 | D46: scd | E46: a | I46: 响尾蛇毒 | J46: 15～60分钟 | K46: 呕吐、剧烈抽搐、黄视。 | L46: 2D10 | M46: 毒液会破坏组织、引发坏死，不过很少致命（特别是一两个小时内就获得解药的话）。 | O46: 其他(上肢) | S46: =IF(人物卡!J23=人物卡!R23,"",IF(ISBLANK(人物卡!H23),"技艺"&人物卡!R23,人物卡!H23&人物卡!R23)) | T46: =IF(人物卡!AF23=人物卡!AN23,"",人物卡!AB23&人物卡!AN23) | X46: 格斗③ | AC46: 计算机 | AE46: 1903 | AF46: —— | AI46: —— | AL46: 二十世纪纪初 | AM46: 癸卯兔年 | AN46: 清光绪29年 | AO46: 芝加哥易洛魁剧院大火，死亡 602 人，是美国历史上最严重的火灾 莱特兄弟试飞飞机 首个荧光灯 邮戳机产生 车架中心摩托车发动机 | AP46: 总统： 西奥多·罗斯福（共和党） | AQ46: 热水瓶 农业轨道机械 木棉安全带 电动汽车喇叭 化学泡沫灭火器 狭义相对论 自动点唱机 量产舰艇舷外发动机 动画 电动洗衣机 家用洗洁精 立式吸尘器 饮用纸杯 双层公交车 无线电测向仪 电煎锅 质子和电子 玻璃纸 战壕风衣 汽车自动起动器 麦片 氯气毒气 防毒面具 拉链 机械雨刮器 广义相对论 芥子气 量产拖拉机 电子钟 黄油枪 降落伞 广播电台播音 茶包 罗夏墨迹测验 机器人 胰岛素 实用邮戳机 滑水 百日咳疫苗 纸制鸡蛋托 面巾纸 商用飞机农药喷撒 液体燃料火箭 劳力士防水表 遥控电唱机 面包机 防水玻璃纸 电传打字机 盖革计数器 纯维生素C 彩色电影胶片 透明胶带 音乐汽车喇叭 闪光灯 速冻食品 球形潜水舱 回旋加速器 折叠式雨伞 电动剃须刀 车载收音机 玛氏巧克力棒 变焦镜头 大富翁桌游 商业洗衣店 畅销平装书 里氏震级 磁带录音机 大众汽车 超市推车 带温控器的电熨斗 速溶咖啡 尼龙 圆珠笔 黄热病疫苗 雷达 汽车自动变速箱 充气救生衣 人工授精 青霉素 军用吉普车 原子裂变 火箭筒 凝固汽油弹 水肺 麦角酸二乙酰胺 神经毒气 原子弹 特百惠 计算机 静电复印法 比基尼泳衣 浓缩咖啡机 宝丽来相机 拼字盘 实心电吉他 尼龙扣 晶体管 黑胶唱片 有线电视 电视显像管 汽车自动点火装置 信用卡 复印机 宽荧幕电影 动力转向器 三色停车灯 人行红绿灯 晶体管助听器 氢弹 录像带 DNA双螺旋结构 麻疹疫苗 按动圆珠笔 硅晶体管 核导弹 空对空导弹 迪士尼乐园 特氟龙 卡丁车 地对空核导弹 沙宾疫苗 通讯卫星 呼啦圈 安全带 人工肾脏 避孕药 气象卫星 便携晶体管收音机 安定 砷化镓半导体激光器 三维全息技术 合成器 香烟健康警示 凯夫拉纤维 子午胎 IBM文字处理机 杜比A型降噪器 滑雪板 喇叭裤 绕月载人火箭 人工心脏移植 波音747喷气式客机 互联网 条形码 软盘 帆板 热裤 液晶显示 便携电子计算器 电视游戏 DNA重组技术 电子游戏机 超级计算机 光纤 试管婴儿 魔方 索尼Walkman 杜比C型降噪器 艾滋病毒 强效可卡因 温室效应 CD 暗物质 暗能量 太阳能飞行器 甲型H1N1 流感 希格斯玻色子 引力波 | AR46: 电气地铁 圣代冰淇淋 实用水电站 手电 电影摄影机 收音机 霍乱疫苗 啤酒瓶盖 柴油发动机 双向电报 实用的胶卷 块麦片 电报 可口可乐 X射线 卷烟机发明 电影放映机 排球 印名片机 福特车 潜望镜 油印蜡纸发明 阴极射线管 商品阿司匹林 凯洛格牌玉米片 手电筒 钋 镭 摇控器 α粒子 β粒子 打字机 柯达布朗尼相机 齐柏林飞艇 人类血型 跨大西洋电报 汽轮机游船 现代柏油路 铝罐奶粉 爆米花 泰迪熊 卡鲁索电唱机 便宜的肥皂和烹饪用油 飞机 荧光灯 邮戳机 摩托车发动机 | AS46: 飞机 荧光灯 邮戳机 摩托车发动机 | AT46: 1903
C47: =INT((C37-B45)/10) -> -6 | D47: =80+80*C47 -> -400 | E47: 25 | I47: 氟硝西泮 | J47: 15～30分钟 | K47: 昏迷4～8小时，可能会失忆。 | L47: 无伤害 | M47: 无色无味，只在现代背景中出现。 | O47: 下肢———— | S47: =IF(人物卡!J24=人物卡!R24,"",人物卡!F24&人物卡!R24) -> 取悦70 | T47: =IF(人物卡!AF24=人物卡!AN24,"",人物卡!AB24&人物卡!AN24) | X47: 射击： | AC47: 信用评级 | AE47: 1904 | AF47: 日俄战争 | AG47: 圣路易斯奥运会 | AI47: —— | AL47: 二十世纪纪初 | AM47: 甲辰龙年 | AN47: 清光绪30年 | AO47: 伊甸火车在洪水中出轨，死亡 96 人 百老汇地铁在纽约城开通 热水瓶获得专利 轨道机械（相对于轮式 ) 出现在农业机械当中 木棉安全带 日俄战争 | AP47: 总统： 西奥多·罗斯福（共和党） | AQ47: 电动汽车喇叭 化学泡沫灭火器 狭义相对论 自动点唱机 量产舰艇舷外发动机 动画 电动洗衣机 家用洗洁精 立式吸尘器 饮用纸杯 双层公交车 无线电测向仪 电煎锅 质子和电子 玻璃纸 战壕风衣 汽车自动起动器 麦片 氯气毒气 防毒面具 拉链 机械雨刮器 广义相对论 芥子气 量产拖拉机 电子钟 黄油枪 降落伞 广播电台播音 茶包 罗夏墨迹测验 机器人 胰岛素 实用邮戳机 滑水 百日咳疫苗 纸制鸡蛋托 面巾纸 商用飞机农药喷撒 液体燃料火箭 劳力士防水表 遥控电唱机 面包机 防水玻璃纸 电传打字机 盖革计数器 纯维生素C 彩色电影胶片 透明胶带 音乐汽车喇叭 闪光灯 速冻食品 球形潜水舱 回旋加速器 折叠式雨伞 电动剃须刀 车载收音机 玛氏巧克力棒 变焦镜头 大富翁桌游 商业洗衣店 畅销平装书 里氏震级 磁带录音机 大众汽车 超市推车 带温控器的电熨斗 速溶咖啡 尼龙 圆珠笔 黄热病疫苗 雷达 汽车自动变速箱 充气救生衣 人工授精 青霉素 军用吉普车 原子裂变 火箭筒 凝固汽油弹 水肺 麦角酸二乙酰胺 神经毒气 原子弹 特百惠 计算机 静电复印法 比基尼泳衣 浓缩咖啡机 宝丽来相机 拼字盘 实心电吉他 尼龙扣 晶体管 黑胶唱片 有线电视 电视显像管 汽车自动点火装置 信用卡 复印机 宽荧幕电影 动力转向器 三色停车灯 人行红绿灯 晶体管助听器 氢弹 录像带 DNA双螺旋结构 麻疹疫苗 按动圆珠笔 硅晶体管 核导弹 空对空导弹 迪士尼乐园 特氟龙 卡丁车 地对空核导弹 沙宾疫苗 通讯卫星 呼啦圈 安全带 人工肾脏 避孕药 气象卫星 便携晶体管收音机 安定 砷化镓半导体激光器 三维全息技术 合成器 香烟健康警示 凯夫拉纤维 子午胎 IBM文字处理机 杜比A型降噪器 滑雪板 喇叭裤 绕月载人火箭 人工心脏移植 波音747喷气式客机 互联网 条形码 软盘 帆板 热裤 液晶显示 便携电子计算器 电视游戏 DNA重组技术 电子游戏机 超级计算机 光纤 试管婴儿 魔方 索尼Walkman 杜比C型降噪器 艾滋病毒 强效可卡因 温室效应 CD 暗物质 暗能量 太阳能飞行器 甲型H1N1 流感 希格斯玻色子 引力波 | AR47: 电气地铁 圣代冰淇淋 实用水电站 手电 电影摄影机 收音机 霍乱疫苗 啤酒瓶盖 柴油发动机 双向电报 实用的胶卷 块麦片 电报 可口可乐 X射线 卷烟机发明 电影放映机 排球 印名片机 福特车 潜望镜 油印蜡纸发明 阴极射线管 商品阿司匹林 凯洛格牌玉米片 手电筒 钋 镭 摇控器 α粒子 β粒子 打字机 柯达布朗尼相机 齐柏林飞艇 人类血型 跨大西洋电报 汽轮机游船 现代柏油路 铝罐奶粉 爆米花 泰迪熊 卡鲁索电唱机 便宜的肥皂和烹饪用油 飞机 荧光灯 邮戳机 摩托车发动机 热水瓶 农业轨道机械 木棉安全带 | AS47: 热水瓶 农业轨道机械 木棉安全带 | AT47: 1904
C48: =C37 -> 29 | D48: ="进步*4,SCD共-"&D47&" A-"&E47 -> 进步*4,SCD共--400 A-25 | I48: 番木鳖碱（马钱子碱、士的宁） | J48: 10～20分钟 | K48: 剧烈的肌肉痉挛、窒息、死亡。 | L48: 4D10 | M48: 如果不及时医治，几小时内就会死亡。 | O48: 左脚 | S48: =IF(人物卡!J25=人物卡!R25,"",人物卡!F25&人物卡!R25) | T48: =IF(人物卡!AF25=人物卡!AN25,"",人物卡!AB25&人物卡!AN25) | X48: 射击① | AC48: 克苏鲁神话 | AE48: 1905 | AF48: 俄国革命 | AI48: —— | AL48: 二十世纪纪初 | AM48: 乙巳蛇年 | AN48: 清光绪31年 | AO48: 库利南钻石（3000 克拉 )，当时世纪界最大的钻石 英国海军标准配备蒸汽轮机 1905 年俄国革命 电动汽车喇叭 化学泡沫灭火器 狭义相对论 | AP48: 总统： 西奥多·罗斯福（共和党） | AQ48: 自动点唱机 量产舰艇舷外发动机 动画 电动洗衣机 家用洗洁精 立式吸尘器 饮用纸杯 双层公交车 无线电测向仪 电煎锅 质子和电子 玻璃纸 战壕风衣 汽车自动起动器 麦片 氯气毒气 防毒面具 拉链 机械雨刮器 广义相对论 芥子气 量产拖拉机 电子钟 黄油枪 降落伞 广播电台播音 茶包 罗夏墨迹测验 机器人 胰岛素 实用邮戳机 滑水 百日咳疫苗 纸制鸡蛋托 面巾纸 商用飞机农药喷撒 液体燃料火箭 劳力士防水表 遥控电唱机 面包机 防水玻璃纸 电传打字机 盖革计数器 纯维生素C 彩色电影胶片 透明胶带 音乐汽车喇叭 闪光灯 速冻食品 球形潜水舱 回旋加速器 折叠式雨伞 电动剃须刀 车载收音机 玛氏巧克力棒 变焦镜头 大富翁桌游 商业洗衣店 畅销平装书 里氏震级 磁带录音机 大众汽车 超市推车 带温控器的电熨斗 速溶咖啡 尼龙 圆珠笔 黄热病疫苗 雷达 汽车自动变速箱 充气救生衣 人工授精 青霉素 军用吉普车 原子裂变 火箭筒 凝固汽油弹 水肺 麦角酸二乙酰胺 神经毒气 原子弹 特百惠 计算机 静电复印法 比基尼泳衣 浓缩咖啡机 宝丽来相机 拼字盘 实心电吉他 尼龙扣 晶体管 黑胶唱片 有线电视 电视显像管 汽车自动点火装置 信用卡 复印机 宽荧幕电影 动力转向器 三色停车灯 人行红绿灯 晶体管助听器 氢弹 录像带 DNA双螺旋结构 麻疹疫苗 按动圆珠笔 硅晶体管 核导弹 空对空导弹 迪士尼乐园 特氟龙 卡丁车 地对空核导弹 沙宾疫苗 通讯卫星 呼啦圈 安全带 人工肾脏 避孕药 气象卫星 便携晶体管收音机 安定 砷化镓半导体激光器 三维全息技术 合成器 香烟健康警示 凯夫拉纤维 子午胎 IBM文字处理机 杜比A型降噪器 滑雪板 喇叭裤 绕月载人火箭 人工心脏移植 波音747喷气式客机 互联网 条形码 软盘 帆板 热裤 液晶显示 便携电子计算器 电视游戏 DNA重组技术 电子游戏机 超级计算机 光纤 试管婴儿 魔方 索尼Walkman 杜比C型降噪器 艾滋病毒 强效可卡因 温室效应 CD 暗物质 暗能量 太阳能飞行器 甲型H1N1 流感 希格斯玻色子 引力波 | AR48: 电气地铁 圣代冰淇淋 实用水电站 手电 电影摄影机 收音机 霍乱疫苗 啤酒瓶盖 柴油发动机 双向电报 实用的胶卷 块麦片 电报 可口可乐 X射线 卷烟机发明 电影放映机 排球 印名片机 福特车 潜望镜 油印蜡纸发明 阴极射线管 商品阿司匹林 凯洛格牌玉米片 手电筒 钋 镭 摇控器 α粒子 β粒子 打字机 柯达布朗尼相机 齐柏林飞艇 人类血型 跨大西洋电报 汽轮机游船 现代柏油路 铝罐奶粉 爆米花 泰迪熊 卡鲁索电唱机 便宜的肥皂和烹饪用油 飞机 荧光灯 邮戳机 摩托车发动机 热水瓶 农业轨道机械 木棉安全带 电动汽车喇叭 化学泡沫灭火器 狭义相对论 | AS48: 电动汽车喇叭 化学泡沫灭火器 狭义相对论 | AT48: 1905
I49: 请打开下拉栏选择 | O49: 右脚 | S49: =IF(人物卡!J26=人物卡!R26,"","计算机使用"&人物卡!R26) | T49: =IF(人物卡!AF26=人物卡!AN26,"",人物卡!AB26&人物卡!AN26) | X49: 射击② | AC49: 乔装 | AE49: 1906 | AF49: 美军占领古巴 | AG49: 印度民族解放运动 | AI49: —— | AL49: 二十世纪纪初 | AM49: 丙午马年 | AN49: 清光绪32年 | AO49: 1906 年旧金山大地震引发大火，死亡700 人，28818 间房屋损毁 美军占领古巴到 1909年 卢西塔尼亚和毛里塔尼亚号下水 自动点唱机 舰艇舷外发动机量产 | AP49: 总统： 西奥多·罗斯福（共和党） | AQ49: 动画 电动洗衣机 家用洗洁精 立式吸尘器 饮用纸杯 双层公交车 无线电测向仪 电煎锅 质子和电子 玻璃纸 战壕风衣 汽车自动起动器 麦片 氯气毒气 防毒面具 拉链 机械雨刮器 广义相对论 芥子气 量产拖拉机 电子钟 黄油枪 降落伞 广播电台播音 茶包 罗夏墨迹测验 机器人 胰岛素 实用邮戳机 滑水 百日咳疫苗 纸制鸡蛋托 面巾纸 商用飞机农药喷撒 液体燃料火箭 劳力士防水表 遥控电唱机 面包机 防水玻璃纸 电传打字机 盖革计数器 纯维生素C 彩色电影胶片 透明胶带 音乐汽车喇叭 闪光灯 速冻食品 球形潜水舱 回旋加速器 折叠式雨伞 电动剃须刀 车载收音机 玛氏巧克力棒 变焦镜头 大富翁桌游 商业洗衣店 畅销平装书 里氏震级 磁带录音机 大众汽车 超市推车 带温控器的电熨斗 速溶咖啡 尼龙 圆珠笔 黄热病疫苗 雷达 汽车自动变速箱 充气救生衣 人工授精 青霉素 军用吉普车 原子裂变 火箭筒 凝固汽油弹 水肺 麦角酸二乙酰胺 神经毒气 原子弹 特百惠 计算机 静电复印法 比基尼泳衣 浓缩咖啡机 宝丽来相机 拼字盘 实心电吉他 尼龙扣 晶体管 黑胶唱片 有线电视 电视显像管 汽车自动点火装置 信用卡 复印机 宽荧幕电影 动力转向器 三色停车灯 人行红绿灯 晶体管助听器 氢弹 录像带 DNA双螺旋结构 麻疹疫苗 按动圆珠笔 硅晶体管 核导弹 空对空导弹 迪士尼乐园 特氟龙 卡丁车 地对空核导弹 沙宾疫苗 通讯卫星 呼啦圈 安全带 人工肾脏 避孕药 气象卫星 便携晶体管收音机 安定 砷化镓半导体激光器 三维全息技术 合成器 香烟健康警示 凯夫拉纤维 子午胎 IBM文字处理机 杜比A型降噪器 滑雪板 喇叭裤 绕月载人火箭 人工心脏移植 波音747喷气式客机 互联网 条形码 软盘 帆板 热裤 液晶显示 便携电子计算器 电视游戏 DNA重组技术 电子游戏机 超级计算机 光纤 试管婴儿 魔方 索尼Walkman 杜比C型降噪器 艾滋病毒 强效可卡因 温室效应 CD 暗物质 暗能量 太阳能飞行器 甲型H1N1 流感 希格斯玻色子 引力波 | AR49: 电气地铁 圣代冰淇淋 实用水电站 手电 电影摄影机 收音机 霍乱疫苗 啤酒瓶盖 柴油发动机 双向电报 实用的胶卷 块麦片 电报 可口可乐 X射线 卷烟机发明 电影放映机 排球 印名片机 福特车 潜望镜 油印蜡纸发明 阴极射线管 商品阿司匹林 凯洛格牌玉米片 手电筒 钋 镭 摇控器 α粒子 β粒子 打字机 柯达布朗尼相机 齐柏林飞艇 人类血型 跨大西洋电报 汽轮机游船 现代柏油路 铝罐奶粉 爆米花 泰迪熊 卡鲁索电唱机 便宜的肥皂和烹饪用油 飞机 荧光灯 邮戳机 摩托车发动机 热水瓶 农业轨道机械 木棉安全带 电动汽车喇叭 化学泡沫灭火器 狭义相对论 自动点唱机 量产舰艇舷外发动机 | AS49: 自动点唱机 量产舰艇舷外发动机 | AT49: 1906
O50: 双脚 | S50: =IF(人物卡!J27=人物卡!R27,"",人物卡!F27&人物卡!R27) -> 信用评级20 | T50: =IF(人物卡!AF27=人物卡!AN27,"",人物卡!AB27&人物卡!AN27) | X50: 射击③ | AC50: 闪避 | AE50: 1907 | AF50: —— | AI50: —— | AL50: 二十世纪纪初 | AM50: 丁未羊年 | AN50: 清光绪33年 | AO50: 西弗吉尼亚州煤矿矿难死亡361 人 拉斯普京在沙俄飞扬跋扈 动画 电动洗衣机 家用洗洁精 立式吸尘器 | AP50: 总统： 西奥多·罗斯福（共和党） | AQ50: 饮用纸杯 双层公交车 无线电测向仪 电煎锅 质子和电子 玻璃纸 战壕风衣 汽车自动起动器 麦片 氯气毒气 防毒面具 拉链 机械雨刮器 广义相对论 芥子气 量产拖拉机 电子钟 黄油枪 降落伞 广播电台播音 茶包 罗夏墨迹测验 机器人 胰岛素 实用邮戳机 滑水 百日咳疫苗 纸制鸡蛋托 面巾纸 商用飞机农药喷撒 液体燃料火箭 劳力士防水表 遥控电唱机 面包机 防水玻璃纸 电传打字机 盖革计数器 纯维生素C 彩色电影胶片 透明胶带 音乐汽车喇叭 闪光灯 速冻食品 球形潜水舱 回旋加速器 折叠式雨伞 电动剃须刀 车载收音机 玛氏巧克力棒 变焦镜头 大富翁桌游 商业洗衣店 畅销平装书 里氏震级 磁带录音机 大众汽车 超市推车 带温控器的电熨斗 速溶咖啡 尼龙 圆珠笔 黄热病疫苗 雷达 汽车自动变速箱 充气救生衣 人工授精 青霉素 军用吉普车 原子裂变 火箭筒 凝固汽油弹 水肺 麦角酸二乙酰胺 神经毒气 原子弹 特百惠 计算机 静电复印法 比基尼泳衣 浓缩咖啡机 宝丽来相机 拼字盘 实心电吉他 尼龙扣 晶体管 黑胶唱片 有线电视 电视显像管 汽车自动点火装置 信用卡 复印机 宽荧幕电影 动力转向器 三色停车灯 人行红绿灯 晶体管助听器 氢弹 录像带 DNA双螺旋结构 麻疹疫苗 按动圆珠笔 硅晶体管 核导弹 空对空导弹 迪士尼乐园 特氟龙 卡丁车 地对空核导弹 沙宾疫苗 通讯卫星 呼啦圈 安全带 人工肾脏 避孕药 气象卫星 便携晶体管收音机 安定 砷化镓半导体激光器 三维全息技术 合成器 香烟健康警示 凯夫拉纤维 子午胎 IBM文字处理机 杜比A型降噪器 滑雪板 喇叭裤 绕月载人火箭 人工心脏移植 波音747喷气式客机 互联网 条形码 软盘 帆板 热裤 液晶显示 便携电子计算器 电视游戏 DNA重组技术 电子游戏机 超级计算机 光纤 试管婴儿 魔方 索尼Walkman 杜比C型降噪器 艾滋病毒 强效可卡因 温室效应 CD 暗物质 暗能量 太阳能飞行器 甲型H1N1 流感 希格斯玻色子 引力波 | AR50: 电气地铁 圣代冰淇淋 实用水电站 手电 电影摄影机 收音机 霍乱疫苗 啤酒瓶盖 柴油发动机 双向电报 实用的胶卷 块麦片 电报 可口可乐 X射线 卷烟机发明 电影放映机 排球 印名片机 福特车 潜望镜 油印蜡纸发明 阴极射线管 商品阿司匹林 凯洛格牌玉米片 手电筒 钋 镭 摇控器 α粒子 β粒子 打字机 柯达布朗尼相机 齐柏林飞艇 人类血型 跨大西洋电报 汽轮机游船 现代柏油路 铝罐奶粉 爆米花 泰迪熊 卡鲁索电唱机 便宜的肥皂和烹饪用油 飞机 荧光灯 邮戳机 摩托车发动机 热水瓶 农业轨道机械 木棉安全带 电动汽车喇叭 化学泡沫灭火器 狭义相对论 自动点唱机 量产舰艇舷外发动机 动画 电动洗衣机 家用洗洁精 立式吸尘器 | AS50: 动画 电动洗衣机 家用洗洁精 立式吸尘器 | AT50: 1907
O51: 左腿 | S51: =IF(人物卡!J28=人物卡!R28,"",人物卡!F28&人物卡!R28) | T51: =IF(人物卡!AF28=人物卡!AN28,"",IF(ISBLANK(人物卡!AD28),"驾驶"&人物卡!AN28,人物卡!AD28&人物卡!AN28)) | X51: 急救 | AC51: 汽车驾驶 | AE51: 1908 | AF51: 伦敦奥运会 | AI51: —— | AL51: 二十世纪纪初 | AM51: 戊申猴年 | AN51: 清光绪34年 | AO51: 敏可夫斯基阐述他的四维几何 饮用纸杯 | AP51: 总统： 西奥多·罗斯福（共和党） | AQ51: 双层公交车 无线电测向仪 电煎锅 质子和电子 玻璃纸 战壕风衣 汽车自动起动器 麦片 氯气毒气 防毒面具 拉链 机械雨刮器 广义相对论 芥子气 量产拖拉机 电子钟 黄油枪 降落伞 广播电台播音 茶包 罗夏墨迹测验 机器人 胰岛素 实用邮戳机 滑水 百日咳疫苗 纸制鸡蛋托 面巾纸 商用飞机农药喷撒 液体燃料火箭 劳力士防水表 遥控电唱机 面包机 防水玻璃纸 电传打字机 盖革计数器 纯维生素C 彩色电影胶片 透明胶带 音乐汽车喇叭 闪光灯 速冻食品 球形潜水舱 回旋加速器 折叠式雨伞 电动剃须刀 车载收音机 玛氏巧克力棒 变焦镜头 大富翁桌游 商业洗衣店 畅销平装书 里氏震级 磁带录音机 大众汽车 超市推车 带温控器的电熨斗 速溶咖啡 尼龙 圆珠笔 黄热病疫苗 雷达 汽车自动变速箱 充气救生衣 人工授精 青霉素 军用吉普车 原子裂变 火箭筒 凝固汽油弹 水肺 麦角酸二乙酰胺 神经毒气 原子弹 特百惠 计算机 静电复印法 比基尼泳衣 浓缩咖啡机 宝丽来相机 拼字盘 实心电吉他 尼龙扣 晶体管 黑胶唱片 有线电视 电视显像管 汽车自动点火装置 信用卡 复印机 宽荧幕电影 动力转向器 三色停车灯 人行红绿灯 晶体管助听器 氢弹 录像带 DNA双螺旋结构 麻疹疫苗 按动圆珠笔 硅晶体管 核导弹 空对空导弹 迪士尼乐园 特氟龙 卡丁车 地对空核导弹 沙宾疫苗 通讯卫星 呼啦圈 安全带 人工肾脏 避孕药 气象卫星 便携晶体管收音机 安定 砷化镓半导体激光器 三维全息技术 合成器 香烟健康警示 凯夫拉纤维 子午胎 IBM文字处理机 杜比A型降噪器 滑雪板 喇叭裤 绕月载人火箭 人工心脏移植 波音747喷气式客机 互联网 条形码 软盘 帆板 热裤 液晶显示 便携电子计算器 电视游戏 DNA重组技术 电子游戏机 超级计算机 光纤 试管婴儿 魔方 索尼Walkman 杜比C型降噪器 艾滋病毒 强效可卡因 温室效应 CD 暗物质 暗能量 太阳能飞行器 甲型H1N1 流感 希格斯玻色子 引力波 | AR51: 电气地铁 圣代冰淇淋 实用水电站 手电 电影摄影机 收音机 霍乱疫苗 啤酒瓶盖 柴油发动机 双向电报 实用的胶卷 块麦片 电报 可口可乐 X射线 卷烟机发明 电影放映机 排球 印名片机 福特车 潜望镜 油印蜡纸发明 阴极射线管 商品阿司匹林 凯洛格牌玉米片 手电筒 钋 镭 摇控器 α粒子 β粒子 打字机 柯达布朗尼相机 齐柏林飞艇 人类血型 跨大西洋电报 汽轮机游船 现代柏油路 铝罐奶粉 爆米花 泰迪熊 卡鲁索电唱机 便宜的肥皂和烹饪用油 飞机 荧光灯 邮戳机 摩托车发动机 热水瓶 农业轨道机械 木棉安全带 电动汽车喇叭 化学泡沫灭火器 狭义相对论 自动点唱机 量产舰艇舷外发动机 动画 电动洗衣机 家用洗洁精 立式吸尘器 饮用纸杯 | AS51: 饮用纸杯 | AT51: 1908
J52: =IF(人物卡!M5=0," ","["&E59&"]") -> [教育×2＋外貌或敏捷×2] | L52: 兴趣点 | O52: 右腿 | S52: =IF(人物卡!J29=人物卡!R29,"",人物卡!F29&人物卡!R29) | T52: =IF(人物卡!AF29=人物卡!AN29,"",人物卡!AB29&人物卡!AN29) | X52: 历史 | AC52: 电气维修 | AE52: 1909 | AF52: —— | AI52: —— | AL52: 二十世纪纪初 清·宣统元年 | AM52: 己酉鸡年 | AN52: 清宣统元年 | AO52: 罗伯特·E·皮尔里抵达北极点 路易斯安那和密西西比州飓风，死亡350 人 首次穿越英吉利海峡的飞行 英国双层公交车 | AP52: 总统： 西奥多·罗斯福（共和党） 威廉·霍华德·塔夫脱（共和党） | AQ52: 无线电测向仪 电煎锅 质子和电子 玻璃纸 战壕风衣 汽车自动起动器 麦片 氯气毒气 防毒面具 拉链 机械雨刮器 广义相对论 芥子气 量产拖拉机 电子钟 黄油枪 降落伞 广播电台播音 茶包 罗夏墨迹测验 机器人 胰岛素 实用邮戳机 滑水 百日咳疫苗 纸制鸡蛋托 面巾纸 商用飞机农药喷撒 液体燃料火箭 劳力士防水表 遥控电唱机 面包机 防水玻璃纸 电传打字机 盖革计数器 纯维生素C 彩色电影胶片 透明胶带 音乐汽车喇叭 闪光灯 速冻食品 球形潜水舱 回旋加速器 折叠式雨伞 电动剃须刀 车载收音机 玛氏巧克力棒 变焦镜头 大富翁桌游 商业洗衣店 畅销平装书 里氏震级 磁带录音机 大众汽车 超市推车 带温控器的电熨斗 速溶咖啡 尼龙 圆珠笔 黄热病疫苗 雷达 汽车自动变速箱 充气救生衣 人工授精 青霉素 军用吉普车 原子裂变 火箭筒 凝固汽油弹 水肺 麦角酸二乙酰胺 神经毒气 原子弹 特百惠 计算机 静电复印法 比基尼泳衣 浓缩咖啡机 宝丽来相机 拼字盘 实心电吉他 尼龙扣 晶体管 黑胶唱片 有线电视 电视显像管 汽车自动点火装置 信用卡 复印机 宽荧幕电影 动力转向器 三色停车灯 人行红绿灯 晶体管助听器 氢弹 录像带 DNA双螺旋结构 麻疹疫苗 按动圆珠笔 硅晶体管 核导弹 空对空导弹 迪士尼乐园 特氟龙 卡丁车 地对空核导弹 沙宾疫苗 通讯卫星 呼啦圈 安全带 人工肾脏 避孕药 气象卫星 便携晶体管收音机 安定 砷化镓半导体激光器 三维全息技术 合成器 香烟健康警示 凯夫拉纤维 子午胎 IBM文字处理机 杜比A型降噪器 滑雪板 喇叭裤 绕月载人火箭 人工心脏移植 波音747喷气式客机 互联网 条形码 软盘 帆板 热裤 液晶显示 便携电子计算器 电视游戏 DNA重组技术 电子游戏机 超级计算机 光纤 试管婴儿 魔方 索尼Walkman 杜比C型降噪器 艾滋病毒 强效可卡因 温室效应 CD 暗物质 暗能量 太阳能飞行器 甲型H1N1 流感 希格斯玻色子 引力波 | AR52: 电气地铁 圣代冰淇淋 实用水电站 手电 电影摄影机 收音机 霍乱疫苗 啤酒瓶盖 柴油发动机 双向电报 实用的胶卷 块麦片 电报 可口可乐 X射线 卷烟机发明 电影放映机 排球 印名片机 福特车 潜望镜 油印蜡纸发明 阴极射线管 商品阿司匹林 凯洛格牌玉米片 手电筒 钋 镭 摇控器 α粒子 β粒子 打字机 柯达布朗尼相机 齐柏林飞艇 人类血型 跨大西洋电报 汽轮机游船 现代柏油路 铝罐奶粉 爆米花 泰迪熊 卡鲁索电唱机 便宜的肥皂和烹饪用油 飞机 荧光灯 邮戳机 摩托车发动机 热水瓶 农业轨道机械 木棉安全带 电动汽车喇叭 化学泡沫灭火器 狭义相对论 自动点唱机 量产舰艇舷外发动机 动画 电动洗衣机 家用洗洁精 立式吸尘器 饮用纸杯 双层公交车 | AS52: 双层公交车 | AT52: 1909
B53: 职业序号 | E53: =IF(人物卡!M5=0," ",LOOKUP(人物卡!M5,职业列表!A2:A232,职业列表!H2:H232)) -> 会计，两项社交技能（取悦、话术、恐吓、说服），法律，图书馆，聆听，锁匠，艺术及手艺（摄影），侦查，任意一项其他个人或时代特长 | J53: =IF(人物卡!M5=0," ",VLOOKUP(人物卡!M5,职业列表!A2:H232,7,FALSE)) -> 270 | L53: =人物卡!AA7+人物卡!AA7 -> 160 | O53: 双腿 | S53: =IF(人物卡!J30=人物卡!R30,"",人物卡!F30&人物卡!R30) -> 闪避60 | T53: =IF(人物卡!AF30=人物卡!AN30,"",人物卡!AB30&人物卡!AN30) -> 心理学60 | X53: 恐吓 | AC53: 电子学 | AE53: 1910 | AF53: —— | AI53: —— | AL53: 二十世纪纪 十年代 清·宣统二年 | AM53: 庚戌狗年 | AN53: 清宣统2年 | AO53: 明尼苏达州弗吉尼亚，滑坡掩埋诺曼露天煤矿工人 华盛顿州惠灵顿火车被雪崩掩埋，死亡96 人 约翰·默里和约翰·休特进行首次深海探险 无线电测向仪 美国童子军成立 美国人口920 万人 | AP53: 总统： 威廉·霍华德·塔夫脱（共和党） | AQ53: 电煎锅 质子和电子 玻璃纸 战壕风衣 汽车自动起动器 麦片 氯气毒气 防毒面具 拉链 机械雨刮器 广义相对论 芥子气 量产拖拉机 电子钟 黄油枪 降落伞 广播电台播音 茶包 罗夏墨迹测验 机器人 胰岛素 实用邮戳机 滑水 百日咳疫苗 纸制鸡蛋托 面巾纸 商用飞机农药喷撒 液体燃料火箭 劳力士防水表 遥控电唱机 面包机 防水玻璃纸 电传打字机 盖革计数器 纯维生素C 彩色电影胶片 透明胶带 音乐汽车喇叭 闪光灯 速冻食品 球形潜水舱 回旋加速器 折叠式雨伞 电动剃须刀 车载收音机 玛氏巧克力棒 变焦镜头 大富翁桌游 商业洗衣店 畅销平装书 里氏震级 磁带录音机 大众汽车 超市推车 带温控器的电熨斗 速溶咖啡 尼龙 圆珠笔 黄热病疫苗 雷达 汽车自动变速箱 充气救生衣 人工授精 青霉素 军用吉普车 原子裂变 火箭筒 凝固汽油弹 水肺 麦角酸二乙酰胺 神经毒气 原子弹 特百惠 计算机 静电复印法 比基尼泳衣 浓缩咖啡机 宝丽来相机 拼字盘 实心电吉他 尼龙扣 晶体管 黑胶唱片 有线电视 电视显像管 汽车自动点火装置 信用卡 复印机 宽荧幕电影 动力转向器 三色停车灯 人行红绿灯 晶体管助听器 氢弹 录像带 DNA双螺旋结构 麻疹疫苗 按动圆珠笔 硅晶体管 核导弹 空对空导弹 迪士尼乐园 特氟龙 卡丁车 地对空核导弹 沙宾疫苗 通讯卫星 呼啦圈 安全带 人工肾脏 避孕药 气象卫星 便携晶体管收音机 安定 砷化镓半导体激光器 三维全息技术 合成器 香烟健康警示 凯夫拉纤维 子午胎 IBM文字处理机 杜比A型降噪器 滑雪板 喇叭裤 绕月载人火箭 人工心脏移植 波音747喷气式客机 互联网 条形码 软盘 帆板 热裤 液晶显示 便携电子计算器 电视游戏 DNA重组技术 电子游戏机 超级计算机 光纤 试管婴儿 魔方 索尼Walkman 杜比C型降噪器 艾滋病毒 强效可卡因 温室效应 CD 暗物质 暗能量 太阳能飞行器 甲型H1N1 流感 希格斯玻色子 引力波 | AR53: 电气地铁 圣代冰淇淋 实用水电站 手电 电影摄影机 收音机 霍乱疫苗 啤酒瓶盖 柴油发动机 双向电报 实用的胶卷 块麦片 电报 可口可乐 X射线 卷烟机发明 电影放映机 排球 印名片机 福特车 潜望镜 油印蜡纸发明 阴极射线管 商品阿司匹林 凯洛格牌玉米片 手电筒 钋 镭 摇控器 α粒子 β粒子 打字机 柯达布朗尼相机 齐柏林飞艇 人类血型 跨大西洋电报 汽轮机游船 现代柏油路 铝罐奶粉 爆米花 泰迪熊 卡鲁索电唱机 便宜的肥皂和烹饪用油 飞机 荧光灯 邮戳机 摩托车发动机 热水瓶 农业轨道机械 木棉安全带 电动汽车喇叭 化学泡沫灭火器 狭义相对论 自动点唱机 量产舰艇舷外发动机 动画 电动洗衣机 家用洗洁精 立式吸尘器 饮用纸杯 双层公交车 无线电测向仪 | AS53: 无线电测向仪 | AT53: 1910
B54: =人物卡!M5 -> 219 | L54: 经历点 | O54: 膝部 | S54: =IF(人物卡!J31=人物卡!R31,"",人物卡!F31&人物卡!R31) | T54: =IF(人物卡!AF31=人物卡!AN31,"",人物卡!AB31&人物卡!AN31) | X54: 跳跃 | AC54: 话术 | AE54: 1911 | AF54: —— | AI54: 辛亥革命 | AL54: 二十世纪纪 十年代 清·宣统三年 | AM54: 辛亥猪年 | AN54: 清宣统3年 | AO54: 泽西市火车站40 吨炸药爆炸，死亡30 人 纽约三角女衬衫厂火灾，死亡145 人 埃米利亚诺·萨帕塔兵临墨西哥城 辛亥革命 电煎锅 挪威探险家罗阿尔德·阿蒙森抵达南极 | AP54: 歌剧： 巴托克·贝拉《蓝胡子公爵的城堡》 总统： 威廉·霍华德·塔夫脱（共和党） | AQ54: 质子和电子 玻璃纸 战壕风衣 汽车自动起动器 麦片 氯气毒气 防毒面具 拉链 机械雨刮器 广义相对论 芥子气 量产拖拉机 电子钟 黄油枪 降落伞 广播电台播音 茶包 罗夏墨迹测验 机器人 胰岛素 实用邮戳机 滑水 百日咳疫苗 纸制鸡蛋托 面巾纸 商用飞机农药喷撒 液体燃料火箭 劳力士防水表 遥控电唱机 面包机 防水玻璃纸 电传打字机 盖革计数器 纯维生素C 彩色电影胶片 透明胶带 音乐汽车喇叭 闪光灯 速冻食品 球形潜水舱 回旋加速器 折叠式雨伞 电动剃须刀 车载收音机 玛氏巧克力棒 变焦镜头 大富翁桌游 商业洗衣店 畅销平装书 里氏震级 磁带录音机 大众汽车 超市推车 带温控器的电熨斗 速溶咖啡 尼龙 圆珠笔 黄热病疫苗 雷达 汽车自动变速箱 充气救生衣 人工授精 青霉素 军用吉普车 原子裂变 火箭筒 凝固汽油弹 水肺 麦角酸二乙酰胺 神经毒气 原子弹 特百惠 计算机 静电复印法 比基尼泳衣 浓缩咖啡机 宝丽来相机 拼字盘 实心电吉他 尼龙扣 晶体管 黑胶唱片 有线电视 电视显像管 汽车自动点火装置 信用卡 复印机 宽荧幕电影 动力转向器 三色停车灯 人行红绿灯 晶体管助听器 氢弹 录像带 DNA双螺旋结构 麻疹疫苗 按动圆珠笔 硅晶体管 核导弹 空对空导弹 迪士尼乐园 特氟龙 卡丁车 地对空核导弹 沙宾疫苗 通讯卫星 呼啦圈 安全带 人工肾脏 避孕药 气象卫星 便携晶体管收音机 安定 砷化镓半导体激光器 三维全息技术 合成器 香烟健康警示 凯夫拉纤维 子午胎 IBM文字处理机 杜比A型降噪器 滑雪板 喇叭裤 绕月载人火箭 人工心脏移植 波音747喷气式客机 互联网 条形码 软盘 帆板 热裤 液晶显示 便携电子计算器 电视游戏 DNA重组技术 电子游戏机 超级计算机 光纤 试管婴儿 魔方 索尼Walkman 杜比C型降噪器 艾滋病毒 强效可卡因 温室效应 CD 暗物质 暗能量 太阳能飞行器 甲型H1N1 流感 希格斯玻色子 引力波 | AR54: 电气地铁 圣代冰淇淋 实用水电站 手电 电影摄影机 收音机 霍乱疫苗 啤酒瓶盖 柴油发动机 双向电报 实用的胶卷 块麦片 电报 可口可乐 X射线 卷烟机发明 电影放映机 排球 印名片机 福特车 潜望镜 油印蜡纸发明 阴极射线管 商品阿司匹林 凯洛格牌玉米片 手电筒 钋 镭 摇控器 α粒子 β粒子 打字机 柯达布朗尼相机 齐柏林飞艇 人类血型 跨大西洋电报 汽轮机游船 现代柏油路 铝罐奶粉 爆米花 泰迪熊 卡鲁索电唱机 便宜的肥皂和烹饪用油 飞机 荧光灯 邮戳机 摩托车发动机 热水瓶 农业轨道机械 木棉安全带 电动汽车喇叭 化学泡沫灭火器 狭义相对论 自动点唱机 量产舰艇舷外发动机 动画 电动洗衣机 家用洗洁精 立式吸尘器 饮用纸杯 双层公交车 无线电测向仪 电煎锅 | AS54: 电煎锅 | AT54: 1911
B55: 经历包序号 | L55: =D34 -> 0 | O55: 其他(下肢) | S55: =IF(人物卡!J32=人物卡!R32,"",人物卡!F32&人物卡!R32) | T55: =IF(人物卡!AF32=人物卡!AN32,"",IF(ISBLANK(人物卡!AD32),"科学"&人物卡!AN32,人物卡!AD32&人物卡!AN32)) | X55: 外语① | AC55: 格斗 | AE55: 1912 | AF55: 斯德哥尔摩奥运会 | AI55: 中华民国成立 | AJ55: 清帝退位 | AL55: 二十世纪纪 十年代 民国元年 | AM55: 壬子鼠年 | AN55: 民国元年 | AO55: 泰坦尼克号撞上冰山，1517 名船员和乘客死亡 由威尔逊云室发现质子和电子 赛璐玢（玻璃纸) 获得专利 伦敦裁缝街发明战壕风衣 凯迪拉克展示首个汽车自动起动器 加利福尼亚州两个自助杂货店开业 | AP55: 总统： 威廉·霍华德·塔夫脱（共和党） | AQ55: 麦片 氯气毒气 防毒面具 拉链 机械雨刮器 广义相对论 芥子气 量产拖拉机 电子钟 黄油枪 降落伞 广播电台播音 茶包 罗夏墨迹测验 机器人 胰岛素 实用邮戳机 滑水 百日咳疫苗 纸制鸡蛋托 面巾纸 商用飞机农药喷撒 液体燃料火箭 劳力士防水表 遥控电唱机 面包机 防水玻璃纸 电传打字机 盖革计数器 纯维生素C 彩色电影胶片 透明胶带 音乐汽车喇叭 闪光灯 速冻食品 球形潜水舱 回旋加速器 折叠式雨伞 电动剃须刀 车载收音机 玛氏巧克力棒 变焦镜头 大富翁桌游 商业洗衣店 畅销平装书 里氏震级 磁带录音机 大众汽车 超市推车 带温控器的电熨斗 速溶咖啡 尼龙 圆珠笔 黄热病疫苗 雷达 汽车自动变速箱 充气救生衣 人工授精 青霉素 军用吉普车 原子裂变 火箭筒 凝固汽油弹 水肺 麦角酸二乙酰胺 神经毒气 原子弹 特百惠 计算机 静电复印法 比基尼泳衣 浓缩咖啡机 宝丽来相机 拼字盘 实心电吉他 尼龙扣 晶体管 黑胶唱片 有线电视 电视显像管 汽车自动点火装置 信用卡 复印机 宽荧幕电影 动力转向器 三色停车灯 人行红绿灯 晶体管助听器 氢弹 录像带 DNA双螺旋结构 麻疹疫苗 按动圆珠笔 硅晶体管 核导弹 空对空导弹 迪士尼乐园 特氟龙 卡丁车 地对空核导弹 沙宾疫苗 通讯卫星 呼啦圈 安全带 人工肾脏 避孕药 气象卫星 便携晶体管收音机 安定 砷化镓半导体激光器 三维全息技术 合成器 香烟健康警示 凯夫拉纤维 子午胎 IBM文字处理机 杜比A型降噪器 滑雪板 喇叭裤 绕月载人火箭 人工心脏移植 波音747喷气式客机 互联网 条形码 软盘 帆板 热裤 液晶显示 便携电子计算器 电视游戏 DNA重组技术 电子游戏机 超级计算机 光纤 试管婴儿 魔方 索尼Walkman 杜比C型降噪器 艾滋病毒 强效可卡因 温室效应 CD 暗物质 暗能量 太阳能飞行器 甲型H1N1 流感 希格斯玻色子 引力波 | AR55: 电气地铁 圣代冰淇淋 实用水电站 手电 电影摄影机 收音机 霍乱疫苗 啤酒瓶盖 柴油发动机 双向电报 实用的胶卷 块麦片 电报 可口可乐 X射线 卷烟机发明 电影放映机 排球 印名片机 福特车 潜望镜 油印蜡纸发明 阴极射线管 商品阿司匹林 凯洛格牌玉米片 手电筒 钋 镭 摇控器 α粒子 β粒子 打字机 柯达布朗尼相机 齐柏林飞艇 人类血型 跨大西洋电报 汽轮机游船 现代柏油路 铝罐奶粉 爆米花 泰迪熊 卡鲁索电唱机 便宜的肥皂和烹饪用油 飞机 荧光灯 邮戳机 摩托车发动机 热水瓶 农业轨道机械 木棉安全带 电动汽车喇叭 化学泡沫灭火器 狭义相对论 自动点唱机 量产舰艇舷外发动机 动画 电动洗衣机 家用洗洁精 立式吸尘器 饮用纸杯 双层公交车 无线电测向仪 电煎锅 质子和电子 玻璃纸 战壕风衣 汽车自动起动器 | AS55: 质子和电子 玻璃纸 战壕风衣 汽车自动起动器 | AT55: 1912
B56: =E62+F62+G62+H62+I62+J62+K62 -> 994 | O56: 其他———— | S56: =IF(人物卡!J33=人物卡!R33,"","电子学"&人物卡!R33) | T56: =IF(人物卡!AF33=人物卡!AN33,"",IF(ISBLANK(人物卡!AD33),"科学"&人物卡!AN33,人物卡!AD33&人物卡!AN33)) | X56: 外语② | AC56: 射击 | AE56: 1913 | AF56: 巴尔干战争 | AI56: —— | AL56: 二十世纪纪 十年代 | AM56: 癸丑牛年 | AN56: 民国2年 | AO56: 两次巴尔干战争 英国轮船卡尔瓦达斯号在马尔马拉海的暴风雨中失踪，200 人失踪 伍德罗·威尔逊就任美国总统 汽车自动起动器应用 美国宪法第十六号（所得税)、第十七号修正案（参议员直选) | AP56: 总统： 威廉·霍华德·塔夫脱（共和党） 伍德罗·威尔逊（民主党） | AQ56: 麦片 氯气毒气 防毒面具 拉链 机械雨刮器 广义相对论 芥子气 量产拖拉机 电子钟 黄油枪 降落伞 广播电台播音 茶包 罗夏墨迹测验 机器人 胰岛素 实用邮戳机 滑水 百日咳疫苗 纸制鸡蛋托 面巾纸 商用飞机农药喷撒 液体燃料火箭 劳力士防水表 遥控电唱机 面包机 防水玻璃纸 电传打字机 盖革计数器 纯维生素C 彩色电影胶片 透明胶带 音乐汽车喇叭 闪光灯 速冻食品 球形潜水舱 回旋加速器 折叠式雨伞 电动剃须刀 车载收音机 玛氏巧克力棒 变焦镜头 大富翁桌游 商业洗衣店 畅销平装书 里氏震级 磁带录音机 大众汽车 超市推车 带温控器的电熨斗 速溶咖啡 尼龙 圆珠笔 黄热病疫苗 雷达 汽车自动变速箱 充气救生衣 人工授精 青霉素 军用吉普车 原子裂变 火箭筒 凝固汽油弹 水肺 麦角酸二乙酰胺 神经毒气 原子弹 特百惠 计算机 静电复印法 比基尼泳衣 浓缩咖啡机 宝丽来相机 拼字盘 实心电吉他 尼龙扣 晶体管 黑胶唱片 有线电视 电视显像管 汽车自动点火装置 信用卡 复印机 宽荧幕电影 动力转向器 三色停车灯 人行红绿灯 晶体管助听器 氢弹 录像带 DNA双螺旋结构 麻疹疫苗 按动圆珠笔 硅晶体管 核导弹 空对空导弹 迪士尼乐园 特氟龙 卡丁车 地对空核导弹 沙宾疫苗 通讯卫星 呼啦圈 安全带 人工肾脏 避孕药 气象卫星 便携晶体管收音机 安定 砷化镓半导体激光器 三维全息技术 合成器 香烟健康警示 凯夫拉纤维 子午胎 IBM文字处理机 杜比A型降噪器 滑雪板 喇叭裤 绕月载人火箭 人工心脏移植 波音747喷气式客机 互联网 条形码 软盘 帆板 热裤 液晶显示 便携电子计算器 电视游戏 DNA重组技术 电子游戏机 超级计算机 光纤 试管婴儿 魔方 索尼Walkman 杜比C型降噪器 艾滋病毒 强效可卡因 温室效应 CD 暗物质 暗能量 太阳能飞行器 甲型H1N1 流感 希格斯玻色子 引力波 | AR56: 电气地铁 圣代冰淇淋 实用水电站 手电 电影摄影机 收音机 霍乱疫苗 啤酒瓶盖 柴油发动机 双向电报 实用的胶卷 块麦片 电报 可口可乐 X射线 卷烟机发明 电影放映机 排球 印名片机 福特车 潜望镜 油印蜡纸发明 阴极射线管 商品阿司匹林 凯洛格牌玉米片 手电筒 钋 镭 摇控器 α粒子 β粒子 打字机 柯达布朗尼相机 齐柏林飞艇 人类血型 跨大西洋电报 汽轮机游船 现代柏油路 铝罐奶粉 爆米花 泰迪熊 卡鲁索电唱机 便宜的肥皂和烹饪用油 飞机 荧光灯 邮戳机 摩托车发动机 热水瓶 农业轨道机械 木棉安全带 电动汽车喇叭 化学泡沫灭火器 狭义相对论 自动点唱机 量产舰艇舷外发动机 动画 电动洗衣机 家用洗洁精 立式吸尘器 饮用纸杯 双层公交车 无线电测向仪 电煎锅 质子和电子 玻璃纸 战壕风衣 汽车自动起动器 麦片 氯气毒气 防毒面具 拉链 | AT56: 1913
B57: 最后显示序号 | O57: 其他 | S57: =IF(人物卡!J34=人物卡!R34,"",人物卡!F34&人物卡!R34) -> 话术70 | T57: =IF(人物卡!AF34=人物卡!AN34,"",IF(ISBLANK(人物卡!AD34),"科学"&人物卡!AN34,人物卡!AD34&人物卡!AN34)) | X57: 外语③ | AC57: 急救 | AE57: 1914 | AF57: 第一次世界大战 | AI57: —— | AL57: 二十世纪纪 十年代 | AM57: 甲寅虎年 | AN57: 民国3年 | AO57: 第一次世纪界大战爆发 首次空袭 巴拿马运河运行 加利福尼亚州太平洋轮船印度女皇号在圣劳伦斯河上与斯托斯塔德号[6]相撞，死亡1024 人 圣诞停火 | AP57: 总统： 伍德罗·威尔逊（民主党） | AQ57: 麦片 氯气毒气 防毒面具 拉链 机械雨刮器 广义相对论 芥子气 量产拖拉机 电子钟 黄油枪 降落伞 广播电台播音 茶包 罗夏墨迹测验 机器人 胰岛素 实用邮戳机 滑水 百日咳疫苗 纸制鸡蛋托 面巾纸 商用飞机农药喷撒 液体燃料火箭 劳力士防水表 遥控电唱机 面包机 防水玻璃纸 电传打字机 盖革计数器 纯维生素C 彩色电影胶片 透明胶带 音乐汽车喇叭 闪光灯 速冻食品 球形潜水舱 回旋加速器 折叠式雨伞 电动剃须刀 车载收音机 玛氏巧克力棒 变焦镜头 大富翁桌游 商业洗衣店 畅销平装书 里氏震级 磁带录音机 大众汽车 超市推车 带温控器的电熨斗 速溶咖啡 尼龙 圆珠笔 黄热病疫苗 雷达 汽车自动变速箱 充气救生衣 人工授精 青霉素 军用吉普车 原子裂变 火箭筒 凝固汽油弹 水肺 麦角酸二乙酰胺 神经毒气 原子弹 特百惠 计算机 静电复印法 比基尼泳衣 浓缩咖啡机 宝丽来相机 拼字盘 实心电吉他 尼龙扣 晶体管 黑胶唱片 有线电视 电视显像管 汽车自动点火装置 信用卡 复印机 宽荧幕电影 动力转向器 三色停车灯 人行红绿灯 晶体管助听器 氢弹 录像带 DNA双螺旋结构 麻疹疫苗 按动圆珠笔 硅晶体管 核导弹 空对空导弹 迪士尼乐园 特氟龙 卡丁车 地对空核导弹 沙宾疫苗 通讯卫星 呼啦圈 安全带 人工肾脏 避孕药 气象卫星 便携晶体管收音机 安定 砷化镓半导体激光器 三维全息技术 合成器 香烟健康警示 凯夫拉纤维 子午胎 IBM文字处理机 杜比A型降噪器 滑雪板 喇叭裤 绕月载人火箭 人工心脏移植 波音747喷气式客机 互联网 条形码 软盘 帆板 热裤 液晶显示 便携电子计算器 电视游戏 DNA重组技术 电子游戏机 超级计算机 光纤 试管婴儿 魔方 索尼Walkman 杜比C型降噪器 艾滋病毒 强效可卡因 温室效应 CD 暗物质 暗能量 太阳能飞行器 甲型H1N1 流感 希格斯玻色子 引力波 | AR57: 电气地铁 圣代冰淇淋 实用水电站 手电 电影摄影机 收音机 霍乱疫苗 啤酒瓶盖 柴油发动机 双向电报 实用的胶卷 块麦片 电报 可口可乐 X射线 卷烟机发明 电影放映机 排球 印名片机 福特车 潜望镜 油印蜡纸发明 阴极射线管 商品阿司匹林 凯洛格牌玉米片 手电筒 钋 镭 摇控器 α粒子 β粒子 打字机 柯达布朗尼相机 齐柏林飞艇 人类血型 跨大西洋电报 汽轮机游船 现代柏油路 铝罐奶粉 爆米花 泰迪熊 卡鲁索电唱机 便宜的肥皂和烹饪用油 飞机 荧光灯 邮戳机 摩托车发动机 热水瓶 农业轨道机械 木棉安全带 电动汽车喇叭 化学泡沫灭火器 狭义相对论 自动点唱机 量产舰艇舷外发动机 动画 电动洗衣机 家用洗洁精 立式吸尘器 饮用纸杯 双层公交车 无线电测向仪 电煎锅 质子和电子 玻璃纸 战壕风衣 汽车自动起动器 麦片 氯气毒气 防毒面具 拉链 | AT57: 1914
B58: =IF(人物卡!I13=E53,B54,IF(AND(L34=C16,A32=1,F16=1),B56,0)) -> 219 | S58: =IF(人物卡!J35=人物卡!R35,"",人物卡!H35&人物卡!R35) | T58: =IF(人物卡!AF35=人物卡!AN35,"",人物卡!AB35&人物卡!AN35) | X58: 母语 | AC58: 历史 | AE58: 1915 | AF58: 第一次世界大战 | AI58: 新文化运动 | AL58: 二十世纪纪 十年代 | AM58: 乙卯兔年 | AN58: 民国4年 | AO58: 卢西塔尼亚号被德国潜艇轰沉，死亡1199 人，美国表示惊愕与愤怒 第一次世纪界大战造成史无前例的重大伤亡 麦片上市 氯气用作毒气 防毒面具 拉链获得专利 | AP58: 总统： 伍德罗·威尔逊（民主党） | AQ58: 机械雨刮器 广义相对论 芥子气 量产拖拉机 电子钟 黄油枪 降落伞 广播电台播音 茶包 罗夏墨迹测验 机器人 胰岛素 实用邮戳机 滑水 百日咳疫苗 纸制鸡蛋托 面巾纸 商用飞机农药喷撒 液体燃料火箭 劳力士防水表 遥控电唱机 面包机 防水玻璃纸 电传打字机 盖革计数器 纯维生素C 彩色电影胶片 透明胶带 音乐汽车喇叭 闪光灯 速冻食品 球形潜水舱 回旋加速器 折叠式雨伞 电动剃须刀 车载收音机 玛氏巧克力棒 变焦镜头 大富翁桌游 商业洗衣店 畅销平装书 里氏震级 磁带录音机 大众汽车 超市推车 带温控器的电熨斗 速溶咖啡 尼龙 圆珠笔 黄热病疫苗 雷达 汽车自动变速箱 充气救生衣 人工授精 青霉素 军用吉普车 原子裂变 火箭筒 凝固汽油弹 水肺 麦角酸二乙酰胺 神经毒气 原子弹 特百惠 计算机 静电复印法 比基尼泳衣 浓缩咖啡机 宝丽来相机 拼字盘 实心电吉他 尼龙扣 晶体管 黑胶唱片 有线电视 电视显像管 汽车自动点火装置 信用卡 复印机 宽荧幕电影 动力转向器 三色停车灯 人行红绿灯 晶体管助听器 氢弹 录像带 DNA双螺旋结构 麻疹疫苗 按动圆珠笔 硅晶体管 核导弹 空对空导弹 迪士尼乐园 特氟龙 卡丁车 地对空核导弹 沙宾疫苗 通讯卫星 呼啦圈 安全带 人工肾脏 避孕药 气象卫星 便携晶体管收音机 安定 砷化镓半导体激光器 三维全息技术 合成器 香烟健康警示 凯夫拉纤维 子午胎 IBM文字处理机 杜比A型降噪器 滑雪板 喇叭裤 绕月载人火箭 人工心脏移植 波音747喷气式客机 互联网 条形码 软盘 帆板 热裤 液晶显示 便携电子计算器 电视游戏 DNA重组技术 电子游戏机 超级计算机 光纤 试管婴儿 魔方 索尼Walkman 杜比C型降噪器 艾滋病毒 强效可卡因 温室效应 CD 暗物质 暗能量 太阳能飞行器 甲型H1N1 流感 希格斯玻色子 引力波 | AR58: 电气地铁 圣代冰淇淋 实用水电站 手电 电影摄影机 收音机 霍乱疫苗 啤酒瓶盖 柴油发动机 双向电报 实用的胶卷 块麦片 电报 可口可乐 X射线 卷烟机发明 电影放映机 排球 印名片机 福特车 潜望镜 油印蜡纸发明 阴极射线管 商品阿司匹林 凯洛格牌玉米片 手电筒 钋 镭 摇控器 α粒子 β粒子 打字机 柯达布朗尼相机 齐柏林飞艇 人类血型 跨大西洋电报 汽轮机游船 现代柏油路 铝罐奶粉 爆米花 泰迪熊 卡鲁索电唱机 便宜的肥皂和烹饪用油 飞机 荧光灯 邮戳机 摩托车发动机 热水瓶 农业轨道机械 木棉安全带 电动汽车喇叭 化学泡沫灭火器 狭义相对论 自动点唱机 量产舰艇舷外发动机 动画 电动洗衣机 家用洗洁精 立式吸尘器 饮用纸杯 双层公交车 无线电测向仪 电煎锅 质子和电子 玻璃纸 战壕风衣 汽车自动起动器 麦片 氯气毒气 防毒面具 拉链 | AS58: 麦片 氯气毒气 防毒面具 拉链 | AT58: 1915
E59: =IF(人物卡!M5=0,"",VLOOKUP(人物卡!M5,职业列表!A2:H232,6,FALSE)) -> 教育×2＋外貌或敏捷×2 | G59: 是否一致 | S59: =IF(人物卡!J36=人物卡!R36,"",IF(ISBLANK(人物卡!H36),"格斗"&人物卡!R36,人物卡!H36&人物卡!R36)) | T59: =IF(人物卡!AF36=人物卡!AN36,"",人物卡!AB36&人物卡!AN36) -> 侦查80 | X59: 法律 | AC59: 恐吓 | AE59: 1916 | AF59: 第一次世界大战 | AG59: 奥运停办 | AI59: 袁世凯恢复帝制失败 | AL59: 二十世纪纪 十年代 | AM59: 丙辰龙年 | AN59: 民国5年 | AO59: 凡尔登战役，死亡70 万人 索姆河战役，死亡100 万人 美国脊髓灰质炎流行，死亡7000 人并致2.7 万青少年残疾 加利波利战役 爱尔兰复活节起义 日德兰海战 机械雨刮器 广义相对论 潘兴入侵墨西哥镇压起义军 | AP59: 总统： 伍德罗·威尔逊（民主党） | AQ59: 芥子气 量产拖拉机 电子钟 黄油枪 降落伞 广播电台播音 茶包 罗夏墨迹测验 机器人 胰岛素 实用邮戳机 滑水 百日咳疫苗 纸制鸡蛋托 面巾纸 商用飞机农药喷撒 液体燃料火箭 劳力士防水表 遥控电唱机 面包机 防水玻璃纸 电传打字机 盖革计数器 纯维生素C 彩色电影胶片 透明胶带 音乐汽车喇叭 闪光灯 速冻食品 球形潜水舱 回旋加速器 折叠式雨伞 电动剃须刀 车载收音机 玛氏巧克力棒 变焦镜头 大富翁桌游 商业洗衣店 畅销平装书 里氏震级 磁带录音机 大众汽车 超市推车 带温控器的电熨斗 速溶咖啡 尼龙 圆珠笔 黄热病疫苗 雷达 汽车自动变速箱 充气救生衣 人工授精 青霉素 军用吉普车 原子裂变 火箭筒 凝固汽油弹 水肺 麦角酸二乙酰胺 神经毒气 原子弹 特百惠 计算机 静电复印法 比基尼泳衣 浓缩咖啡机 宝丽来相机 拼字盘 实心电吉他 尼龙扣 晶体管 黑胶唱片 有线电视 电视显像管 汽车自动点火装置 信用卡 复印机 宽荧幕电影 动力转向器 三色停车灯 人行红绿灯 晶体管助听器 氢弹 录像带 DNA双螺旋结构 麻疹疫苗 按动圆珠笔 硅晶体管 核导弹 空对空导弹 迪士尼乐园 特氟龙 卡丁车 地对空核导弹 沙宾疫苗 通讯卫星 呼啦圈 安全带 人工肾脏 避孕药 气象卫星 便携晶体管收音机 安定 砷化镓半导体激光器 三维全息技术 合成器 香烟健康警示 凯夫拉纤维 子午胎 IBM文字处理机 杜比A型降噪器 滑雪板 喇叭裤 绕月载人火箭 人工心脏移植 波音747喷气式客机 互联网 条形码 软盘 帆板 热裤 液晶显示 便携电子计算器 电视游戏 DNA重组技术 电子游戏机 超级计算机 光纤 试管婴儿 魔方 索尼Walkman 杜比C型降噪器 艾滋病毒 强效可卡因 温室效应 CD 暗物质 暗能量 太阳能飞行器 甲型H1N1 流感 希格斯玻色子 引力波 | AR59: 电气地铁 圣代冰淇淋 实用水电站 手电 电影摄影机 收音机 霍乱疫苗 啤酒瓶盖 柴油发动机 双向电报 实用的胶卷 块麦片 电报 可口可乐 X射线 卷烟机发明 电影放映机 排球 印名片机 福特车 潜望镜 油印蜡纸发明 阴极射线管 商品阿司匹林 凯洛格牌玉米片 手电筒 钋 镭 摇控器 α粒子 β粒子 打字机 柯达布朗尼相机 齐柏林飞艇 人类血型 跨大西洋电报 汽轮机游船 现代柏油路 铝罐奶粉 爆米花 泰迪熊 卡鲁索电唱机 便宜的肥皂和烹饪用油 飞机 荧光灯 邮戳机 摩托车发动机 热水瓶 农业轨道机械 木棉安全带 电动汽车喇叭 化学泡沫灭火器 狭义相对论 自动点唱机 量产舰艇舷外发动机 动画 电动洗衣机 家用洗洁精 立式吸尘器 饮用纸杯 双层公交车 无线电测向仪 电煎锅 质子和电子 玻璃纸 战壕风衣 汽车自动起动器 麦片 氯气毒气 防毒面具 拉链 机械雨刮器 广义相对论 | AS59: 机械雨刮器 广义相对论 | AT59: 1916
G60: =IF(人物卡!I13=E53,1,0) -> 1 | P60: =IF(ISNUMBER(P61+P62+P63+P64+P65+P66+O67+P68+P69+P70+P71),0,1) -> 0 | S60: =IF(人物卡!J37=人物卡!R37,"",IF(ISBLANK(人物卡!H37),"格斗"&人物卡!R37,人物卡!H37&人物卡!R37)) | T60: =IF(人物卡!AF37=人物卡!AN37,"",人物卡!AB37&人物卡!AN37) -> 潜行60 | X60: 图书馆使用 | AC60: 跳跃 | AE60: 1917 | AF60: 第一次世界大战 | AG60: 十月革命 | AI60: 张勋复辟失败 | AJ60: 护法运动 | AL60: 二十世纪纪 十年代 | AM60: 丁巳蛇年 | AN60: 民国6年 | AO60: 美国参加协约国 二月革命和十月革命 芥子气 福特量产拖拉机 轮船卡斯塔利亚号在苏必利尔湖沉没，死亡22 人 宾夕法尼亚州军火库爆炸，死亡133 人 新斯科舍省哈利法克斯船舶爆炸沉没，1600 人死亡 | AP60: 总统： 伍德罗·威尔逊（民主党） | AQ60: 电子钟 黄油枪 降落伞 广播电台播音 茶包 罗夏墨迹测验 机器人 胰岛素 实用邮戳机 滑水 百日咳疫苗 纸制鸡蛋托 面巾纸 商用飞机农药喷撒 液体燃料火箭 劳力士防水表 遥控电唱机 面包机 防水玻璃纸 电传打字机 盖革计数器 纯维生素C 彩色电影胶片 透明胶带 音乐汽车喇叭 闪光灯 速冻食品 球形潜水舱 回旋加速器 折叠式雨伞 电动剃须刀 车载收音机 玛氏巧克力棒 变焦镜头 大富翁桌游 商业洗衣店 畅销平装书 里氏震级 磁带录音机 大众汽车 超市推车 带温控器的电熨斗 速溶咖啡 尼龙 圆珠笔 黄热病疫苗 雷达 汽车自动变速箱 充气救生衣 人工授精 青霉素 军用吉普车 原子裂变 火箭筒 凝固汽油弹 水肺 麦角酸二乙酰胺 神经毒气 原子弹 特百惠 计算机 静电复印法 比基尼泳衣 浓缩咖啡机 宝丽来相机 拼字盘 实心电吉他 尼龙扣 晶体管 黑胶唱片 有线电视 电视显像管 汽车自动点火装置 信用卡 复印机 宽荧幕电影 动力转向器 三色停车灯 人行红绿灯 晶体管助听器 氢弹 录像带 DNA双螺旋结构 麻疹疫苗 按动圆珠笔 硅晶体管 核导弹 空对空导弹 迪士尼乐园 特氟龙 卡丁车 地对空核导弹 沙宾疫苗 通讯卫星 呼啦圈 安全带 人工肾脏 避孕药 气象卫星 便携晶体管收音机 安定 砷化镓半导体激光器 三维全息技术 合成器 香烟健康警示 凯夫拉纤维 子午胎 IBM文字处理机 杜比A型降噪器 滑雪板 喇叭裤 绕月载人火箭 人工心脏移植 波音747喷气式客机 互联网 条形码 软盘 帆板 热裤 液晶显示 便携电子计算器 电视游戏 DNA重组技术 电子游戏机 超级计算机 光纤 试管婴儿 魔方 索尼Walkman 杜比C型降噪器 艾滋病毒 强效可卡因 温室效应 CD 暗物质 暗能量 太阳能飞行器 甲型H1N1 流感 希格斯玻色子 引力波 | AR60: 电气地铁 圣代冰淇淋 实用水电站 手电 电影摄影机 收音机 霍乱疫苗 啤酒瓶盖 柴油发动机 双向电报 实用的胶卷 块麦片 电报 可口可乐 X射线 卷烟机发明 电影放映机 排球 印名片机 福特车 潜望镜 油印蜡纸发明 阴极射线管 商品阿司匹林 凯洛格牌玉米片 手电筒 钋 镭 摇控器 α粒子 β粒子 打字机 柯达布朗尼相机 齐柏林飞艇 人类血型 跨大西洋电报 汽轮机游船 现代柏油路 铝罐奶粉 爆米花 泰迪熊 卡鲁索电唱机 便宜的肥皂和烹饪用油 飞机 荧光灯 邮戳机 摩托车发动机 热水瓶 农业轨道机械 木棉安全带 电动汽车喇叭 化学泡沫灭火器 狭义相对论 自动点唱机 量产舰艇舷外发动机 动画 电动洗衣机 家用洗洁精 立式吸尘器 饮用纸杯 双层公交车 无线电测向仪 电煎锅 质子和电子 玻璃纸 战壕风衣 汽车自动起动器 麦片 氯气毒气 防毒面具 拉链 机械雨刮器 广义相对论 芥子气 量产拖拉机 | AS60: 芥子气 量产拖拉机 | AT60: 1917
E61: 军 | F61: 兵 | G61: 警 | H61: 罪 | I61: 医 | J61: 神 | K61: 自定义 | P61: =IF(ISBLANK(职业列表!J3),职业列表!J3,IF(ISNUMBER(P62+P63+P64+P65+P66+P67+P68+P69+P70+P71+P72),职业列表!J3,职业列表!J3&"，")) -> 0 | Q61: =IF(ISNUMBER(P61),"",P61) | S61: =IF(人物卡!J38=人物卡!R38,"",IF(ISBLANK(人物卡!H38),"格斗"&人物卡!R38,人物卡!H38&人物卡!R38)) | T61: =IF(人物卡!AF38=人物卡!AN38,"",IF(ISBLANK(人物卡!AD38),"生存"&人物卡!AN38,人物卡!AD38&人物卡!AN38)) | X61: 聆听 | AC61: 外语 | AE61: 1918 | AF61: 第一次世界大战 | AI61: —— | AL61: 二十世纪纪 十年代 | AM61: 戊午马年 | AN61: 民国7年 | AO61: 第一次世纪界大战结束 苏俄内战 固定美国航空邮件服务 西班牙大流感，死亡2160 万人 美国独眼巨人号离开巴巴多斯后失踪 飞机时速达到150 迈，飞行高度达3万英尺 电子钟 | AP61: 总统： 伍德罗·威尔逊（民主党） | AQ61: 黄油枪 降落伞 广播电台播音 茶包 罗夏墨迹测验 机器人 胰岛素 实用邮戳机 滑水 百日咳疫苗 纸制鸡蛋托 面巾纸 商用飞机农药喷撒 液体燃料火箭 劳力士防水表 遥控电唱机 面包机 防水玻璃纸 电传打字机 盖革计数器 纯维生素C 彩色电影胶片 透明胶带 音乐汽车喇叭 闪光灯 速冻食品 球形潜水舱 回旋加速器 折叠式雨伞 电动剃须刀 车载收音机 玛氏巧克力棒 变焦镜头 大富翁桌游 商业洗衣店 畅销平装书 里氏震级 磁带录音机 大众汽车 超市推车 带温控器的电熨斗 速溶咖啡 尼龙 圆珠笔 黄热病疫苗 雷达 汽车自动变速箱 充气救生衣 人工授精 青霉素 军用吉普车 原子裂变 火箭筒 凝固汽油弹 水肺 麦角酸二乙酰胺 神经毒气 原子弹 特百惠 计算机 静电复印法 比基尼泳衣 浓缩咖啡机 宝丽来相机 拼字盘 实心电吉他 尼龙扣 晶体管 黑胶唱片 有线电视 电视显像管 汽车自动点火装置 信用卡 复印机 宽荧幕电影 动力转向器 三色停车灯 人行红绿灯 晶体管助听器 氢弹 录像带 DNA双螺旋结构 麻疹疫苗 按动圆珠笔 硅晶体管 核导弹 空对空导弹 迪士尼乐园 特氟龙 卡丁车 地对空核导弹 沙宾疫苗 通讯卫星 呼啦圈 安全带 人工肾脏 避孕药 气象卫星 便携晶体管收音机 安定 砷化镓半导体激光器 三维全息技术 合成器 香烟健康警示 凯夫拉纤维 子午胎 IBM文字处理机 杜比A型降噪器 滑雪板 喇叭裤 绕月载人火箭 人工心脏移植 波音747喷气式客机 互联网 条形码 软盘 帆板 热裤 液晶显示 便携电子计算器 电视游戏 DNA重组技术 电子游戏机 超级计算机 光纤 试管婴儿 魔方 索尼Walkman 杜比C型降噪器 艾滋病毒 强效可卡因 温室效应 CD 暗物质 暗能量 太阳能飞行器 甲型H1N1 流感 希格斯玻色子 引力波 | AR61: 电气地铁 圣代冰淇淋 实用水电站 手电 电影摄影机 收音机 霍乱疫苗 啤酒瓶盖 柴油发动机 双向电报 实用的胶卷 块麦片 电报 可口可乐 X射线 卷烟机发明 电影放映机 排球 印名片机 福特车 潜望镜 油印蜡纸发明 阴极射线管 商品阿司匹林 凯洛格牌玉米片 手电筒 钋 镭 摇控器 α粒子 β粒子 打字机 柯达布朗尼相机 齐柏林飞艇 人类血型 跨大西洋电报 汽轮机游船 现代柏油路 铝罐奶粉 爆米花 泰迪熊 卡鲁索电唱机 便宜的肥皂和烹饪用油 飞机 荧光灯 邮戳机 摩托车发动机 热水瓶 农业轨道机械 木棉安全带 电动汽车喇叭 化学泡沫灭火器 狭义相对论 自动点唱机 量产舰艇舷外发动机 动画 电动洗衣机 家用洗洁精 立式吸尘器 饮用纸杯 双层公交车 无线电测向仪 电煎锅 质子和电子 玻璃纸 战壕风衣 汽车自动起动器 麦片 氯气毒气 防毒面具 拉链 机械雨刮器 广义相对论 芥子气 量产拖拉机 电子钟 | AS61: 电子钟 | AT61: 1918
E62: =IF(C16=F20,993,0) -> 0 | F62: =IF(C16=G20,994,0) -> 994 | G62: =IF(C16=F21,995,0) -> 0 | H62: =IF(C16=F22,996,0) -> 0 | I62: =IF(C16=F23,997,0) -> 0 | J62: =IF(C16=F24,998,0) -> 0 | K62: =IF(C16=F25,999,0) -> 0 | P62: =IF(ISBLANK(职业列表!J4),职业列表!J4,IF(ISNUMBER(P63+P64+P65+P66+P67+P68+P72+P69+P70+P71),职业列表!J4,职业列表!J4&"，")) -> 0 | Q62: =IF(ISNUMBER(P62),"",P62) | S62: =IF(人物卡!J39=人物卡!R39,"",人物卡!H39&人物卡!R39) | T62: =IF(人物卡!AF39=人物卡!AN39,"",人物卡!AB39&人物卡!AN39) | X62: 锁匠 | AC62: 母语 | AE62: 1919 | AF62: 巴黎和会 | AI62: 五四爱国运动 | AL62: 二十世纪纪 十年代 | AM62: 己未羊年 | AN62: 民国8年 | AO62: 美国宪法第十八号修正案（禁酒令) 首次跨大西洋飞行（1880 英里，16 小时12 分钟) 黄油枪 降落伞 | AP62: 书籍： 威尔 · 罗杰斯《禁酒时代的牛仔哲学家》 影视： “妖妇”蒂达·巴拉主演《莎乐美》 D·W·格里菲斯导演《残花泪》 朗 · 钱尼《奇人》 总统： 伍德罗·威尔逊（民主党） | AQ62: 广播电台播音 茶包 罗夏墨迹测验 机器人 胰岛素 实用邮戳机 滑水 百日咳疫苗 纸制鸡蛋托 面巾纸 商用飞机农药喷撒 液体燃料火箭 劳力士防水表 遥控电唱机 面包机 防水玻璃纸 电传打字机 盖革计数器 纯维生素C 彩色电影胶片 透明胶带 音乐汽车喇叭 闪光灯 速冻食品 球形潜水舱 回旋加速器 折叠式雨伞 电动剃须刀 车载收音机 玛氏巧克力棒 变焦镜头 大富翁桌游 商业洗衣店 畅销平装书 里氏震级 磁带录音机 大众汽车 超市推车 带温控器的电熨斗 速溶咖啡 尼龙 圆珠笔 黄热病疫苗 雷达 汽车自动变速箱 充气救生衣 人工授精 青霉素 军用吉普车 原子裂变 火箭筒 凝固汽油弹 水肺 麦角酸二乙酰胺 神经毒气 原子弹 特百惠 计算机 静电复印法 比基尼泳衣 浓缩咖啡机 宝丽来相机 拼字盘 实心电吉他 尼龙扣 晶体管 黑胶唱片 有线电视 电视显像管 汽车自动点火装置 信用卡 复印机 宽荧幕电影 动力转向器 三色停车灯 人行红绿灯 晶体管助听器 氢弹 录像带 DNA双螺旋结构 麻疹疫苗 按动圆珠笔 硅晶体管 核导弹 空对空导弹 迪士尼乐园 特氟龙 卡丁车 地对空核导弹 沙宾疫苗 通讯卫星 呼啦圈 安全带 人工肾脏 避孕药 气象卫星 便携晶体管收音机 安定 砷化镓半导体激光器 三维全息技术 合成器 香烟健康警示 凯夫拉纤维 子午胎 IBM文字处理机 杜比A型降噪器 滑雪板 喇叭裤 绕月载人火箭 人工心脏移植 波音747喷气式客机 互联网 条形码 软盘 帆板 热裤 液晶显示 便携电子计算器 电视游戏 DNA重组技术 电子游戏机 超级计算机 光纤 试管婴儿 魔方 索尼Walkman 杜比C型降噪器 艾滋病毒 强效可卡因 温室效应 CD 暗物质 暗能量 太阳能飞行器 甲型H1N1 流感 希格斯玻色子 引力波 | AR62: 电气地铁 圣代冰淇淋 实用水电站 手电 电影摄影机 收音机 霍乱疫苗 啤酒瓶盖 柴油发动机 双向电报 实用的胶卷 块麦片 电报 可口可乐 X射线 卷烟机发明 电影放映机 排球 印名片机 福特车 潜望镜 油印蜡纸发明 阴极射线管 商品阿司匹林 凯洛格牌玉米片 手电筒 钋 镭 摇控器 α粒子 β粒子 打字机 柯达布朗尼相机 齐柏林飞艇 人类血型 跨大西洋电报 汽轮机游船 现代柏油路 铝罐奶粉 爆米花 泰迪熊 卡鲁索电唱机 便宜的肥皂和烹饪用油 飞机 荧光灯 邮戳机 摩托车发动机 热水瓶 农业轨道机械 木棉安全带 电动汽车喇叭 化学泡沫灭火器 狭义相对论 自动点唱机 量产舰艇舷外发动机 动画 电动洗衣机 家用洗洁精 立式吸尘器 饮用纸杯 双层公交车 无线电测向仪 电煎锅 质子和电子 玻璃纸 战壕风衣 汽车自动起动器 麦片 氯气毒气 防毒面具 拉链 机械雨刮器 广义相对论 芥子气 量产拖拉机 电子钟 黄油枪 降落伞 | AS62: 黄油枪 降落伞 | AT62: 1919
P63: =IF(ISBLANK(职业列表!J5),职业列表!J5,IF(ISNUMBER(P64+P65+P66+P67+P68+P72+P69+P70+P71),职业列表!J5,职业列表!J5&"，")) -> 0 | Q63: =IF(ISNUMBER(P63),"",P63) | S63: =IF(人物卡!J40=人物卡!R40,"",IF(ISBLANK(人物卡!H40),"射击"&人物卡!R40,人物卡!H40&人物卡!R40)) | T63: =IF(人物卡!AF40=人物卡!AN40,"",人物卡!AB40&人物卡!AN40) | X63: 机械维修 | AC63: 法律 | AE63: 1920 | AF63: 咆哮的二十年代（美国） | AG63: 安特卫普奥运会 | AI63: 海原大地震 | AL63: 二十世纪纪 二十年代 | AM63: 庚申猴年 | AN63: 民国9年 | AO63: 禁酒令生效 布尔什维克赢得苏俄内战 中国海原大地震，死亡 20 万人 首次广播电台播音 茶包 美国公债 243 亿美元 美国人口 1.057 亿 | AP63: 书籍： 赞恩·格雷：《林中人》 弗·斯科特·菲茨杰拉德：《人间天堂》 影视： 朗·钱尼：主演《惩罚》 丽莲·吉许：主演《暴风雨中的孤儿》 约翰·巴里摩尔：出演《化身博士》 玛丽·毕克馥：出演《波丽安娜》 老道格拉斯·范朋克：出演《佐罗的面具》 查理·卓别林、玛丽·毕克馥、道格拉斯·范朋克和传奇制片人兼导演 D·W·格里菲斯成立联美电影公司。 流行歌曲： 《I'll be With You at Apple Blossom Time》 杰 洛 姆· 科 恩《Look for the Silver Lining》 《When My Baby Smiles at Me》 百老汇舞台： 齐格菲尔德歌舞团女星范妮·布莱斯出演《华盛顿广场的玫瑰》 总统： 威廉·塔夫脱（共和党） | AQ63: 罗夏墨迹测验 机器人 胰岛素 实用邮戳机 滑水 百日咳疫苗 纸制鸡蛋托 面巾纸 商用飞机农药喷撒 液体燃料火箭 劳力士防水表 遥控电唱机 面包机 防水玻璃纸 电传打字机 盖革计数器 纯维生素C 彩色电影胶片 透明胶带 音乐汽车喇叭 闪光灯 速冻食品 球形潜水舱 回旋加速器 折叠式雨伞 电动剃须刀 车载收音机 玛氏巧克力棒 变焦镜头 大富翁桌游 商业洗衣店 畅销平装书 里氏震级 磁带录音机 大众汽车 超市推车 带温控器的电熨斗 速溶咖啡 尼龙 圆珠笔 黄热病疫苗 雷达 汽车自动变速箱 充气救生衣 人工授精 青霉素 军用吉普车 原子裂变 火箭筒 凝固汽油弹 水肺 麦角酸二乙酰胺 神经毒气 原子弹 特百惠 计算机 静电复印法 比基尼泳衣 浓缩咖啡机 宝丽来相机 拼字盘 实心电吉他 尼龙扣 晶体管 黑胶唱片 有线电视 电视显像管 汽车自动点火装置 信用卡 复印机 宽荧幕电影 动力转向器 三色停车灯 人行红绿灯 晶体管助听器 氢弹 录像带 DNA双螺旋结构 麻疹疫苗 按动圆珠笔 硅晶体管 核导弹 空对空导弹 迪士尼乐园 特氟龙 卡丁车 地对空核导弹 沙宾疫苗 通讯卫星 呼啦圈 安全带 人工肾脏 避孕药 气象卫星 便携晶体管收音机 安定 砷化镓半导体激光器 三维全息技术 合成器 香烟健康警示 凯夫拉纤维 子午胎 IBM文字处理机 杜比A型降噪器 滑雪板 喇叭裤 绕月载人火箭 人工心脏移植 波音747喷气式客机 互联网 条形码 软盘 帆板 热裤 液晶显示 便携电子计算器 电视游戏 DNA重组技术 电子游戏机 超级计算机 光纤 试管婴儿 魔方 索尼Walkman 杜比C型降噪器 艾滋病毒 强效可卡因 温室效应 CD 暗物质 暗能量 太阳能飞行器 甲型H1N1 流感 希格斯玻色子 引力波 | AR63: 电气地铁 圣代冰淇淋 实用水电站 手电 电影摄影机 收音机 霍乱疫苗 啤酒瓶盖 柴油发动机 双向电报 实用的胶卷 块麦片 电报 可口可乐 X射线 卷烟机发明 电影放映机 排球 印名片机 福特车 潜望镜 油印蜡纸发明 阴极射线管 商品阿司匹林 凯洛格牌玉米片 手电筒 钋 镭 摇控器 α粒子 β粒子 打字机 柯达布朗尼相机 齐柏林飞艇 人类血型 跨大西洋电报 汽轮机游船 现代柏油路 铝罐奶粉 爆米花 泰迪熊 卡鲁索电唱机 便宜的肥皂和烹饪用油 飞机 荧光灯 邮戳机 摩托车发动机 热水瓶 农业轨道机械 木棉安全带 电动汽车喇叭 化学泡沫灭火器 狭义相对论 自动点唱机 量产舰艇舷外发动机 动画 电动洗衣机 家用洗洁精 立式吸尘器 饮用纸杯 双层公交车 无线电测向仪 电煎锅 质子和电子 玻璃纸 战壕风衣 汽车自动起动器 麦片 氯气毒气 防毒面具 拉链 机械雨刮器 广义相对论 芥子气 量产拖拉机 电子钟 黄油枪 降落伞 广播电台播音 茶包 | AS63: 广播电台 茶包 | AT63: 1920
P64: =IF(ISBLANK(职业列表!J6),职业列表!J6,IF(ISNUMBER(P65+P66+P67+P68+P72+P69+P70+P71),职业列表!J6,职业列表!J6&"，")) -> 0 | Q64: =IF(ISNUMBER(P64),"",P64) | S64: =IF(人物卡!J41=人物卡!R41,"",IF(ISBLANK(人物卡!H41),"射击"&人物卡!R41,人物卡!H41&人物卡!R41)) | T64: =IF(人物卡!AF41=人物卡!AN41,"",人物卡!AB41&人物卡!AN41) | X64: 医学 | AC64: 图书馆使用 | AE64: 1921 | AF64: 咆哮的二十年代（美国） | AI64: 中国共产党成立 | AL64: 二十世纪纪 二十年代 | AM64: 辛酉鸡年 | AN64: 民国10年 | AO64: 罗夏墨迹测验获得专利 德国恶性通胀开始 KDKA 电台转播体育赛事 恰佩克提出“机器人”一词 | AP64: 书籍： 赫伯特·乔治·威尔斯《世纪界史纲》 赞恩·格雷《神秘骑手》 伊迪斯·华顿《纯真年代》 伊迪斯·霍尔《酋长》 影视： 鲁道夫·瓦伦蒂诺凭借《启示录四骑士》和《沙漠情酋》一夜成名 马克·森内特制作《小城偶像》 卓别林主演《寻子遇仙记》 道格拉斯·范朋克出演《三个火枪手》 流行歌曲： 《Sheik of Araby》 《I'm Just Wild About Harry》 《Ain't We Got Fun》 百老汇舞台： 萨蒂斯餐厅在曼哈顿剧院区开张 范妮·布莱斯出演《二手玫瑰》保持去年的热度 总统： 伍德罗·威尔逊（民主党） 沃伦·甘梅利尔·哈定（共和党） | AQ64: 胰岛素 实用邮戳机 滑水 百日咳疫苗 纸制鸡蛋托 面巾纸 商用飞机农药喷撒 液体燃料火箭 劳力士防水表 遥控电唱机 面包机 防水玻璃纸 电传打字机 盖革计数器 纯维生素C 彩色电影胶片 透明胶带 音乐汽车喇叭 闪光灯 速冻食品 球形潜水舱 回旋加速器 折叠式雨伞 电动剃须刀 车载收音机 玛氏巧克力棒 变焦镜头 大富翁桌游 商业洗衣店 畅销平装书 里氏震级 磁带录音机 大众汽车 超市推车 带温控器的电熨斗 速溶咖啡 尼龙 圆珠笔 黄热病疫苗 雷达 汽车自动变速箱 充气救生衣 人工授精 青霉素 军用吉普车 原子裂变 火箭筒 凝固汽油弹 水肺 麦角酸二乙酰胺 神经毒气 原子弹 特百惠 计算机 静电复印法 比基尼泳衣 浓缩咖啡机 宝丽来相机 拼字盘 实心电吉他 尼龙扣 晶体管 黑胶唱片 有线电视 电视显像管 汽车自动点火装置 信用卡 复印机 宽荧幕电影 动力转向器 三色停车灯 人行红绿灯 晶体管助听器 氢弹 录像带 DNA双螺旋结构 麻疹疫苗 按动圆珠笔 硅晶体管 核导弹 空对空导弹 迪士尼乐园 特氟龙 卡丁车 地对空核导弹 沙宾疫苗 通讯卫星 呼啦圈 安全带 人工肾脏 避孕药 气象卫星 便携晶体管收音机 安定 砷化镓半导体激光器 三维全息技术 合成器 香烟健康警示 凯夫拉纤维 子午胎 IBM文字处理机 杜比A型降噪器 滑雪板 喇叭裤 绕月载人火箭 人工心脏移植 波音747喷气式客机 互联网 条形码 软盘 帆板 热裤 液晶显示 便携电子计算器 电视游戏 DNA重组技术 电子游戏机 超级计算机 光纤 试管婴儿 魔方 索尼Walkman 杜比C型降噪器 艾滋病毒 强效可卡因 温室效应 CD 暗物质 暗能量 太阳能飞行器 甲型H1N1 流感 希格斯玻色子 引力波 | AR64: 电气地铁 圣代冰淇淋 实用水电站 手电 电影摄影机 收音机 霍乱疫苗 啤酒瓶盖 柴油发动机 双向电报 实用的胶卷 块麦片 电报 可口可乐 X射线 卷烟机发明 电影放映机 排球 印名片机 福特车 潜望镜 油印蜡纸发明 阴极射线管 商品阿司匹林 凯洛格牌玉米片 手电筒 钋 镭 摇控器 α粒子 β粒子 打字机 柯达布朗尼相机 齐柏林飞艇 人类血型 跨大西洋电报 汽轮机游船 现代柏油路 铝罐奶粉 爆米花 泰迪熊 卡鲁索电唱机 便宜的肥皂和烹饪用油 飞机 荧光灯 邮戳机 摩托车发动机 热水瓶 农业轨道机械 木棉安全带 电动汽车喇叭 化学泡沫灭火器 狭义相对论 自动点唱机 量产舰艇舷外发动机 动画 电动洗衣机 家用洗洁精 立式吸尘器 饮用纸杯 双层公交车 无线电测向仪 电煎锅 质子和电子 玻璃纸 战壕风衣 汽车自动起动器 麦片 氯气毒气 防毒面具 拉链 机械雨刮器 广义相对论 芥子气 量产拖拉机 电子钟 黄油枪 降落伞 广播电台播音 茶包 罗夏墨迹测验 机器人 | AS64: 罗夏墨迹测验 “机器人” | AT64: 1921
P65: =IF(ISBLANK(职业列表!J7),职业列表!J7,IF(ISNUMBER(P66+P67+P68+P72+P69+P70+P71),职业列表!J7,职业列表!J7&"，")) -> 0 | Q65: =IF(ISNUMBER(P65),"",P65) | S65: =IF(人物卡!J42=人物卡!R42,"",IF(ISBLANK(人物卡!H42),"射击"&人物卡!R42,人物卡!H42&人物卡!R42)) | T65: =IF(人物卡!AF42=人物卡!AN42,"",人物卡!AB42&人物卡!AN42) | X65: 博物学 | AC65: 聆听 | AE65: 1922 | AF65: 咆哮的二十年代（美国） | AG65: 苏联建国 | AI65: —— | AL65: 二十世纪纪 二十年代 | AM65: 壬戌狗年 | AN65: 民国11年 | AO65: 三K 党死灰复燃 英国飞艇AR-2 断成两段，死亡62 人 分离胰岛素 首个实用邮戳机 苏联五一口号去掉“世纪界革命” 滑水 墨索里尼入主罗马 | AP65: 书籍： 辛克莱·刘易斯《巴比特》 《饮食与健康》首次介绍了卡路里计算方法，连续五年成为畅销书 房龙《人类的故事》 埃德娜·费伯《演艺船》 J·A·汤姆孙《科学大纲》 詹姆斯·乔伊斯《尤利西斯》 影视： 亨利·赫尔和卡洛儿·代姆斯特合作主演《恐怖之夜》 道格拉斯·范朋克出演《罗宾汉》 F·W·茂瑙在德导演《诺斯费拉图》 罗伯特·弗拉哈迪《北方的纳努克》开创了文献纪录片 约翰·巴里摩尔出演《哈姆雷特》成为当时评价最高的莎士比亚剧演员 流行歌曲： 《Chicago (That Toddlin' Town)》 《Toot, Toot, Tootsie Goodbye》 《Way Down Yonder in New Orleans》 《I Wish I Could Shimmy Like My Sister Kate》 《Carolina in the Morning》 百老汇舞台： 萨姆·哈里斯创作《雨》 总统： 沃伦·甘梅利尔·哈定（共和党） | AQ65: 百日咳疫苗 纸制鸡蛋托 面巾纸 商用飞机农药喷撒 液体燃料火箭 劳力士防水表 遥控电唱机 面包机 防水玻璃纸 电传打字机 盖革计数器 纯维生素C 彩色电影胶片 透明胶带 音乐汽车喇叭 闪光灯 速冻食品 球形潜水舱 回旋加速器 折叠式雨伞 电动剃须刀 车载收音机 玛氏巧克力棒 变焦镜头 大富翁桌游 商业洗衣店 畅销平装书 里氏震级 磁带录音机 大众汽车 超市推车 带温控器的电熨斗 速溶咖啡 尼龙 圆珠笔 黄热病疫苗 雷达 汽车自动变速箱 充气救生衣 人工授精 青霉素 军用吉普车 原子裂变 火箭筒 凝固汽油弹 水肺 麦角酸二乙酰胺 神经毒气 原子弹 特百惠 计算机 静电复印法 比基尼泳衣 浓缩咖啡机 宝丽来相机 拼字盘 实心电吉他 尼龙扣 晶体管 黑胶唱片 有线电视 电视显像管 汽车自动点火装置 信用卡 复印机 宽荧幕电影 动力转向器 三色停车灯 人行红绿灯 晶体管助听器 氢弹 录像带 DNA双螺旋结构 麻疹疫苗 按动圆珠笔 硅晶体管 核导弹 空对空导弹 迪士尼乐园 特氟龙 卡丁车 地对空核导弹 沙宾疫苗 通讯卫星 呼啦圈 安全带 人工肾脏 避孕药 气象卫星 便携晶体管收音机 安定 砷化镓半导体激光器 三维全息技术 合成器 香烟健康警示 凯夫拉纤维 子午胎 IBM文字处理机 杜比A型降噪器 滑雪板 喇叭裤 绕月载人火箭 人工心脏移植 波音747喷气式客机 互联网 条形码 软盘 帆板 热裤 液晶显示 便携电子计算器 电视游戏 DNA重组技术 电子游戏机 超级计算机 光纤 试管婴儿 魔方 索尼Walkman 杜比C型降噪器 艾滋病毒 强效可卡因 温室效应 CD 暗物质 暗能量 太阳能飞行器 甲型H1N1 流感 希格斯玻色子 引力波 | AR65: 电气地铁 圣代冰淇淋 实用水电站 手电 电影摄影机 收音机 霍乱疫苗 啤酒瓶盖 柴油发动机 双向电报 实用的胶卷 块麦片 电报 可口可乐 X射线 卷烟机发明 电影放映机 排球 印名片机 福特车 潜望镜 油印蜡纸发明 阴极射线管 商品阿司匹林 凯洛格牌玉米片 手电筒 钋 镭 摇控器 α粒子 β粒子 打字机 柯达布朗尼相机 齐柏林飞艇 人类血型 跨大西洋电报 汽轮机游船 现代柏油路 铝罐奶粉 爆米花 泰迪熊 卡鲁索电唱机 便宜的肥皂和烹饪用油 飞机 荧光灯 邮戳机 摩托车发动机 热水瓶 农业轨道机械 木棉安全带 电动汽车喇叭 化学泡沫灭火器 狭义相对论 自动点唱机 量产舰艇舷外发动机 动画 电动洗衣机 家用洗洁精 立式吸尘器 饮用纸杯 双层公交车 无线电测向仪 电煎锅 质子和电子 玻璃纸 战壕风衣 汽车自动起动器 麦片 氯气毒气 防毒面具 拉链 机械雨刮器 广义相对论 芥子气 量产拖拉机 电子钟 黄油枪 降落伞 广播电台播音 茶包 罗夏墨迹测验 机器人 胰岛素 实用邮戳机 滑水 | AS65: 胰岛素 实用邮戳机 滑水 | AT65: 1922
P66: =IF(ISBLANK(职业列表!J8),职业列表!J8,IF(ISNUMBER(P67+P68+P72+P69+P70+P71),职业列表!J8,职业列表!J8&"，")) -> 0 | Q66: =IF(ISNUMBER(P66),"",P66) | S66: =IF(人物卡!J43=人物卡!R43,"",人物卡!F43&人物卡!R43) | T66: =IF(人物卡!AF43=人物卡!AN43,"",人物卡!AB43&人物卡!AN43) | X66: 导航 | AC66: 锁匠 | AE66: 1923 | AF66: 咆哮的二十年代（美国） | AI66: —— | AL66: 二十世纪纪 二十年代 | AM66: 癸亥猪年 | AN66: 民国12年 | AO66: 茶壶山丑闻动摇哈定总统 加利福尼亚州伯克利大火，毁坏600 栋房屋，造成损失1000 万美元，死亡60 人 德国恶性通胀结束 佐治亚州持续三K 党恐怖活动 德国啤酒馆暴动 图坦卡蒙陵墓发掘 百日咳疫苗 | AP66: 书籍： 爱弥儿·柯尔《通过有意识地自我暗示掌握自我》，激发了心理健康和自我完善的风潮 艾米莉·波斯特《礼仪：社交规范蓝皮书》 影视： 朗·钱尼主演《钟楼怪人》 赛西尔·德米尔制作《十诫》 威廉·S·哈特主演《狂野比尔》 喜剧演员哈罗德·劳埃德主演《安全至下》 喜剧导演麦克·塞纳特《尖叫》 流行歌曲： 《 是 的！ 我 们 没 有 香 蕉》 《Who's Sorry Now?》 《That Old Gang of Mine》 贝西·史密斯录制《Downhearted Blues》 百老汇舞台： 约瑟芬·贝克主演的《拖着脚步走》从哈林区一路公演到百老汇 大卫·贝拉斯科创作《笑，小丑，笑》 总统： 沃伦·甘梅利尔·哈定（共和党） 卡尔文·柯立芝（共和党） | AQ66: 纸制鸡蛋托 面巾纸 商用飞机农药喷撒 液体燃料火箭 劳力士防水表 遥控电唱机 面包机 防水玻璃纸 电传打字机 盖革计数器 纯维生素C 彩色电影胶片 透明胶带 音乐汽车喇叭 闪光灯 速冻食品 球形潜水舱 回旋加速器 折叠式雨伞 电动剃须刀 车载收音机 玛氏巧克力棒 变焦镜头 大富翁桌游 商业洗衣店 畅销平装书 里氏震级 磁带录音机 大众汽车 超市推车 带温控器的电熨斗 速溶咖啡 尼龙 圆珠笔 黄热病疫苗 雷达 汽车自动变速箱 充气救生衣 人工授精 青霉素 军用吉普车 原子裂变 火箭筒 凝固汽油弹 水肺 麦角酸二乙酰胺 神经毒气 原子弹 特百惠 计算机 静电复印法 比基尼泳衣 浓缩咖啡机 宝丽来相机 拼字盘 实心电吉他 尼龙扣 晶体管 黑胶唱片 有线电视 电视显像管 汽车自动点火装置 信用卡 复印机 宽荧幕电影 动力转向器 三色停车灯 人行红绿灯 晶体管助听器 氢弹 录像带 DNA双螺旋结构 麻疹疫苗 按动圆珠笔 硅晶体管 核导弹 空对空导弹 迪士尼乐园 特氟龙 卡丁车 地对空核导弹 沙宾疫苗 通讯卫星 呼啦圈 安全带 人工肾脏 避孕药 气象卫星 便携晶体管收音机 安定 砷化镓半导体激光器 三维全息技术 合成器 香烟健康警示 凯夫拉纤维 子午胎 IBM文字处理机 杜比A型降噪器 滑雪板 喇叭裤 绕月载人火箭 人工心脏移植 波音747喷气式客机 互联网 条形码 软盘 帆板 热裤 液晶显示 便携电子计算器 电视游戏 DNA重组技术 电子游戏机 超级计算机 光纤 试管婴儿 魔方 索尼Walkman 杜比C型降噪器 艾滋病毒 强效可卡因 温室效应 CD 暗物质 暗能量 太阳能飞行器 甲型H1N1 流感 希格斯玻色子 引力波 | AR66: 电气地铁 圣代冰淇淋 实用水电站 手电 电影摄影机 收音机 霍乱疫苗 啤酒瓶盖 柴油发动机 双向电报 实用的胶卷 块麦片 电报 可口可乐 X射线 卷烟机发明 电影放映机 排球 印名片机 福特车 潜望镜 油印蜡纸发明 阴极射线管 商品阿司匹林 凯洛格牌玉米片 手电筒 钋 镭 摇控器 α粒子 β粒子 打字机 柯达布朗尼相机 齐柏林飞艇 人类血型 跨大西洋电报 汽轮机游船 现代柏油路 铝罐奶粉 爆米花 泰迪熊 卡鲁索电唱机 便宜的肥皂和烹饪用油 飞机 荧光灯 邮戳机 摩托车发动机 热水瓶 农业轨道机械 木棉安全带 电动汽车喇叭 化学泡沫灭火器 狭义相对论 自动点唱机 量产舰艇舷外发动机 动画 电动洗衣机 家用洗洁精 立式吸尘器 饮用纸杯 双层公交车 无线电测向仪 电煎锅 质子和电子 玻璃纸 战壕风衣 汽车自动起动器 麦片 氯气毒气 防毒面具 拉链 机械雨刮器 广义相对论 芥子气 量产拖拉机 电子钟 黄油枪 降落伞 广播电台播音 茶包 罗夏墨迹测验 机器人 胰岛素 实用邮戳机 滑水 百日咳疫苗 | AS66: 百日咳疫苗 | AT66: 1923
O67: =IF(ISBLANK(职业列表!J9),职业列表!J9,IF(ISNUMBER(P68+P72+P69+P70+P71),职业列表!J9,职业列表!J9&"，")) -> 0 | P67: =IF(ISBLANK(职业列表!J9),职业列表!J9,IF(ISNUMBER(P68+P72+P69+P70+P71),职业列表!J9,职业列表!J9&"，")) -> 0 | Q67: =IF(ISNUMBER(P67),"",P67) | S67: =IF(人物卡!J44=人物卡!R44,"",人物卡!F44&人物卡!R44) | T67: =IF(人物卡!AF44=人物卡!AN44,"",人物卡!AB44&人物卡!AN44) | X67: 神秘学 | AC67: 机械维修 | AE67: 1924 | AF67: 咆哮的二十年代（美国） | AG67: 巴黎奥运会 | AI67: 国共两党第一次合作 | AL67: 二十世纪纪 二十年代 | AM67: 甲子鼠年 | AN67: 民国13年 | AO67: 李奥波德与勒伯案 纸制鸡蛋托应用 面巾纸 | AP67: 书籍： 赞恩·格雷《大峡谷的呼唤》 影视： 哈罗德·劳埃德出演《真情难诉》 巴斯特·基顿出演《航海家》 道格拉斯·范朋克出演《巴格达大盗》 约翰·福特导演《铁骑》 流行歌曲： 《Indian Love Call》 格什温《Fascinating Rhythm》 《It Had to Be You》 《鸳鸯茶》(Tea for Two) 《California Here I Come》 百老汇舞台： 诺埃尔·科沃德《漩涡》 马克斯兄弟登场《I'll Say She Is》 保罗·罗伯逊主演尤金·奥尼尔的《琼斯皇帝》 约瑟芬·贝克在《巧克力浪子》中登场，随后离开美国前往巴黎 总统： 卡尔文·柯立芝（共和党） | AQ67: 商用飞机农药喷撒 液体燃料火箭 劳力士防水表 遥控电唱机 面包机 防水玻璃纸 电传打字机 盖革计数器 纯维生素C 彩色电影胶片 透明胶带 音乐汽车喇叭 闪光灯 速冻食品 球形潜水舱 回旋加速器 折叠式雨伞 电动剃须刀 车载收音机 玛氏巧克力棒 变焦镜头 大富翁桌游 商业洗衣店 畅销平装书 里氏震级 磁带录音机 大众汽车 超市推车 带温控器的电熨斗 速溶咖啡 尼龙 圆珠笔 黄热病疫苗 雷达 汽车自动变速箱 充气救生衣 人工授精 青霉素 军用吉普车 原子裂变 火箭筒 凝固汽油弹 水肺 麦角酸二乙酰胺 神经毒气 原子弹 特百惠 计算机 静电复印法 比基尼泳衣 浓缩咖啡机 宝丽来相机 拼字盘 实心电吉他 尼龙扣 晶体管 黑胶唱片 有线电视 电视显像管 汽车自动点火装置 信用卡 复印机 宽荧幕电影 动力转向器 三色停车灯 人行红绿灯 晶体管助听器 氢弹 录像带 DNA双螺旋结构 麻疹疫苗 按动圆珠笔 硅晶体管 核导弹 空对空导弹 迪士尼乐园 特氟龙 卡丁车 地对空核导弹 沙宾疫苗 通讯卫星 呼啦圈 安全带 人工肾脏 避孕药 气象卫星 便携晶体管收音机 安定 砷化镓半导体激光器 三维全息技术 合成器 香烟健康警示 凯夫拉纤维 子午胎 IBM文字处理机 杜比A型降噪器 滑雪板 喇叭裤 绕月载人火箭 人工心脏移植 波音747喷气式客机 互联网 条形码 软盘 帆板 热裤 液晶显示 便携电子计算器 电视游戏 DNA重组技术 电子游戏机 超级计算机 光纤 试管婴儿 魔方 索尼Walkman 杜比C型降噪器 艾滋病毒 强效可卡因 温室效应 CD 暗物质 暗能量 太阳能飞行器 甲型H1N1 流感 希格斯玻色子 引力波 | AR67: 电气地铁 圣代冰淇淋 实用水电站 手电 电影摄影机 收音机 霍乱疫苗 啤酒瓶盖 柴油发动机 双向电报 实用的胶卷 块麦片 电报 可口可乐 X射线 卷烟机发明 电影放映机 排球 印名片机 福特车 潜望镜 油印蜡纸发明 阴极射线管 商品阿司匹林 凯洛格牌玉米片 手电筒 钋 镭 摇控器 α粒子 β粒子 打字机 柯达布朗尼相机 齐柏林飞艇 人类血型 跨大西洋电报 汽轮机游船 现代柏油路 铝罐奶粉 爆米花 泰迪熊 卡鲁索电唱机 便宜的肥皂和烹饪用油 飞机 荧光灯 邮戳机 摩托车发动机 热水瓶 农业轨道机械 木棉安全带 电动汽车喇叭 化学泡沫灭火器 狭义相对论 自动点唱机 量产舰艇舷外发动机 动画 电动洗衣机 家用洗洁精 立式吸尘器 饮用纸杯 双层公交车 无线电测向仪 电煎锅 质子和电子 玻璃纸 战壕风衣 汽车自动起动器 麦片 氯气毒气 防毒面具 拉链 机械雨刮器 广义相对论 芥子气 量产拖拉机 电子钟 黄油枪 降落伞 广播电台播音 茶包 罗夏墨迹测验 机器人 胰岛素 实用邮戳机 滑水 百日咳疫苗 纸制鸡蛋托 面巾纸 | AS67: 纸制鸡蛋托 面巾纸 | AT67: 1924
P68: =IF(ISBLANK(职业列表!J10),职业列表!J10,IF(ISNUMBER(P72+P69+P70+P71),职业列表!J10,职业列表!J10&"，")) -> 0 | Q68: =IF(ISNUMBER(P68),"",P68) | S68: =IF(人物卡!J45=人物卡!R45,"",人物卡!F45&人物卡!R45) | T68: =IF(人物卡!AF45=人物卡!AN45,"",人物卡!AB45&人物卡!AN45) | X68: 操作重型机械 | AC68: 医学 | AE68: 1925 | AF68: 咆哮的二十年代（美国） | AI68: 孙中山逝世 | AL68: 二十世纪纪 二十年代 | AM68: 乙丑牛年 | AN68: 民国14年 | AO68: W·泡利阐述不相容原理 I·G·法本化工成立 孙中山逝世纪 中西部地区龙卷风，一天死亡792 人 美国飞艇谢南多厄号解体，死亡14 人 纳粹党卫军成立 斯科普斯猿猴诉讼案 商用飞机农药喷撒 | AP68: 书籍： 辛克莱·刘易斯《阿罗史密斯》 弗·斯科特·菲茨杰拉德《了不起的盖茨比》 弗吉尼亚·伍尔芙《达洛维夫人》 西奥多·德雷塞《美国的悲剧》 厄尔·德尔·比格斯《没有钥匙的住宅》 影视： 朗·钱尼主演《歌剧魅影》 威廉·S· 哈特出演《风滚草》 哈罗德·劳埃德出演《新生》 阿道夫·门吉欧出演《撒旦的悲伤》 巴斯特·基顿出演《七次机会》 查理·卓别林出演《淘金记》 威利斯·奥布莱恩制作了《失落的世纪界》，将史前生物带入人们视野 流行歌曲： 《I'm Sittin' On Top of the World》; 《Alabamy Bound》 《If You Knew Susie Like I Know Susie》 《Sweet Georgia Brown》 《Yes Sir, That's My Baby》 胖子沃勒《Squeeze Me》 百老汇舞台： 诺埃尔·科沃德《枯草热》 萨姆·哈里斯创作《爵士歌王》，乔治·杰塞尔主演 马克斯兄弟主演《可可豆》 总统： 卡尔文·柯立芝（共和党） | AQ68: 液体燃料火箭 劳力士防水表 遥控电唱机 面包机 防水玻璃纸 电传打字机 盖革计数器 纯维生素C 彩色电影胶片 透明胶带 音乐汽车喇叭 闪光灯 速冻食品 球形潜水舱 回旋加速器 折叠式雨伞 电动剃须刀 车载收音机 玛氏巧克力棒 变焦镜头 大富翁桌游 商业洗衣店 畅销平装书 里氏震级 磁带录音机 大众汽车 超市推车 带温控器的电熨斗 速溶咖啡 尼龙 圆珠笔 黄热病疫苗 雷达 汽车自动变速箱 充气救生衣 人工授精 青霉素 军用吉普车 原子裂变 火箭筒 凝固汽油弹 水肺 麦角酸二乙酰胺 神经毒气 原子弹 特百惠 计算机 静电复印法 比基尼泳衣 浓缩咖啡机 宝丽来相机 拼字盘 实心电吉他 尼龙扣 晶体管 黑胶唱片 有线电视 电视显像管 汽车自动点火装置 信用卡 复印机 宽荧幕电影 动力转向器 三色停车灯 人行红绿灯 晶体管助听器 氢弹 录像带 DNA双螺旋结构 麻疹疫苗 按动圆珠笔 硅晶体管 核导弹 空对空导弹 迪士尼乐园 特氟龙 卡丁车 地对空核导弹 沙宾疫苗 通讯卫星 呼啦圈 安全带 人工肾脏 避孕药 气象卫星 便携晶体管收音机 安定 砷化镓半导体激光器 三维全息技术 合成器 香烟健康警示 凯夫拉纤维 子午胎 IBM文字处理机 杜比A型降噪器 滑雪板 喇叭裤 绕月载人火箭 人工心脏移植 波音747喷气式客机 互联网 条形码 软盘 帆板 热裤 液晶显示 便携电子计算器 电视游戏 DNA重组技术 电子游戏机 超级计算机 光纤 试管婴儿 魔方 索尼Walkman 杜比C型降噪器 艾滋病毒 强效可卡因 温室效应 CD 暗物质 暗能量 太阳能飞行器 甲型H1N1 流感 希格斯玻色子 引力波 | AR68: 电气地铁 圣代冰淇淋 实用水电站 手电 电影摄影机 收音机 霍乱疫苗 啤酒瓶盖 柴油发动机 双向电报 实用的胶卷 块麦片 电报 可口可乐 X射线 卷烟机发明 电影放映机 排球 印名片机 福特车 潜望镜 油印蜡纸发明 阴极射线管 商品阿司匹林 凯洛格牌玉米片 手电筒 钋 镭 摇控器 α粒子 β粒子 打字机 柯达布朗尼相机 齐柏林飞艇 人类血型 跨大西洋电报 汽轮机游船 现代柏油路 铝罐奶粉 爆米花 泰迪熊 卡鲁索电唱机 便宜的肥皂和烹饪用油 飞机 荧光灯 邮戳机 摩托车发动机 热水瓶 农业轨道机械 木棉安全带 电动汽车喇叭 化学泡沫灭火器 狭义相对论 自动点唱机 量产舰艇舷外发动机 动画 电动洗衣机 家用洗洁精 立式吸尘器 饮用纸杯 双层公交车 无线电测向仪 电煎锅 质子和电子 玻璃纸 战壕风衣 汽车自动起动器 麦片 氯气毒气 防毒面具 拉链 机械雨刮器 广义相对论 芥子气 量产拖拉机 电子钟 黄油枪 降落伞 广播电台播音 茶包 罗夏墨迹测验 机器人 胰岛素 实用邮戳机 滑水 百日咳疫苗 纸制鸡蛋托 面巾纸 商用飞机农药喷撒 | AS68: 商用飞机农药喷撒 | AT68: 1925
P69: =IF(ISBLANK(职业列表!V17),职业列表!V17,IF(ISNUMBER(P72+P70+P71),职业列表!V17,职业列表!V17&"，")) -> 0 | Q69: =IF(ISNUMBER(P69),"",P69) | S69: =IF(人物卡!J46=人物卡!R46,"",人物卡!F46&人物卡!R46) | T69: =IF(人物卡!AF46=人物卡!AN46,"",人物卡!AB46&人物卡!AN46) | X69: 说服 | AC69: 博物学 | AE69: 1926 | AF69: 咆哮的二十年代（美国） | AG69: 日本改元昭和 | AI69: 北伐开始 | AL69: 二十世纪纪 二十年代 | AM69: 丙寅虎年 | AN69: 民国15年 | AO69: 戈达德博士发射首枚液体燃料火箭 闪电引爆新泽西州丹麦湖的军火库，损失8500万美元，死亡30 人 佛罗里达和亚拉巴马州飓风，死亡243 人 蒋介石发动北伐 托洛茨基被逐出苏共政治局 劳力士防水表 杰克·登普西负于吉恩·滕尼，让出拳王名号 | AP69: 书籍： 阿加莎·克里斯蒂《罗杰疑案》，此书是其成名作 威尔·杜兰特《哲学的故事》，售出了 200 万册 海明威《太阳照常升起》 安妮塔·卢斯《绅士爱美人》 影视： 琼·克劳馥在《漂亮女士》中出道 葛丽泰·嘉宝主演《激流》 弗里茨·朗导演经典作品《大都会》 约翰·巴里摩尔出演首部有声歌舞电影《唐璜》 巴斯特·基顿导演《将军号》 弗朗西斯·X·布什曼主演《宾虚》 瓦伦蒂诺的葬礼触发曼哈顿群体歇斯底里事件，会场被前来寻求纪念品的人洗劫 流行歌曲： 《Are You Lonesome Tonight》 《Bye, Bye, Blackbird》 《When the Red, Red Robin (Comes Bob, Bob, Bobbin' Along)》 《Tip Toe Through the Tulips》 百老汇舞台： 梅·韦斯特的《性》轰动 大卫·贝拉斯科创作《Lu Lu Belle》 总统： 卡尔文·柯立芝（共和党） | AQ69: 遥控电唱机 面包机 防水玻璃纸 电传打字机 盖革计数器 纯维生素C 彩色电影胶片 透明胶带 音乐汽车喇叭 闪光灯 速冻食品 球形潜水舱 回旋加速器 折叠式雨伞 电动剃须刀 车载收音机 玛氏巧克力棒 变焦镜头 大富翁桌游 商业洗衣店 畅销平装书 里氏震级 磁带录音机 大众汽车 超市推车 带温控器的电熨斗 速溶咖啡 尼龙 圆珠笔 黄热病疫苗 雷达 汽车自动变速箱 充气救生衣 人工授精 青霉素 军用吉普车 原子裂变 火箭筒 凝固汽油弹 水肺 麦角酸二乙酰胺 神经毒气 原子弹 特百惠 计算机 静电复印法 比基尼泳衣 浓缩咖啡机 宝丽来相机 拼字盘 实心电吉他 尼龙扣 晶体管 黑胶唱片 有线电视 电视显像管 汽车自动点火装置 信用卡 复印机 宽荧幕电影 动力转向器 三色停车灯 人行红绿灯 晶体管助听器 氢弹 录像带 DNA双螺旋结构 麻疹疫苗 按动圆珠笔 硅晶体管 核导弹 空对空导弹 迪士尼乐园 特氟龙 卡丁车 地对空核导弹 沙宾疫苗 通讯卫星 呼啦圈 安全带 人工肾脏 避孕药 气象卫星 便携晶体管收音机 安定 砷化镓半导体激光器 三维全息技术 合成器 香烟健康警示 凯夫拉纤维 子午胎 IBM文字处理机 杜比A型降噪器 滑雪板 喇叭裤 绕月载人火箭 人工心脏移植 波音747喷气式客机 互联网 条形码 软盘 帆板 热裤 液晶显示 便携电子计算器 电视游戏 DNA重组技术 电子游戏机 超级计算机 光纤 试管婴儿 魔方 索尼Walkman 杜比C型降噪器 艾滋病毒 强效可卡因 温室效应 CD 暗物质 暗能量 太阳能飞行器 甲型H1N1 流感 希格斯玻色子 引力波 | AR69: 电气地铁 圣代冰淇淋 实用水电站 手电 电影摄影机 收音机 霍乱疫苗 啤酒瓶盖 柴油发动机 双向电报 实用的胶卷 块麦片 电报 可口可乐 X射线 卷烟机发明 电影放映机 排球 印名片机 福特车 潜望镜 油印蜡纸发明 阴极射线管 商品阿司匹林 凯洛格牌玉米片 手电筒 钋 镭 摇控器 α粒子 β粒子 打字机 柯达布朗尼相机 齐柏林飞艇 人类血型 跨大西洋电报 汽轮机游船 现代柏油路 铝罐奶粉 爆米花 泰迪熊 卡鲁索电唱机 便宜的肥皂和烹饪用油 飞机 荧光灯 邮戳机 摩托车发动机 热水瓶 农业轨道机械 木棉安全带 电动汽车喇叭 化学泡沫灭火器 狭义相对论 自动点唱机 量产舰艇舷外发动机 动画 电动洗衣机 家用洗洁精 立式吸尘器 饮用纸杯 双层公交车 无线电测向仪 电煎锅 质子和电子 玻璃纸 战壕风衣 汽车自动起动器 麦片 氯气毒气 防毒面具 拉链 机械雨刮器 广义相对论 芥子气 量产拖拉机 电子钟 黄油枪 降落伞 广播电台播音 茶包 罗夏墨迹测验 机器人 胰岛素 实用邮戳机 滑水 百日咳疫苗 纸制鸡蛋托 面巾纸 商用飞机农药喷撒 液体燃料火箭 劳力士防水表 | AS69: 液体燃料火箭 劳力士防水表 | AT69: 1926
P70: =IF(ISBLANK(职业列表!V18),职业列表!V18,IF(ISNUMBER(P72+P71),职业列表!V18,职业列表!V18&"，")) -> 0 | Q70: =IF(ISNUMBER(P70),"",P70) | S70: =IF(人物卡!J47=人物卡!R47,"",IF(ISBLANK(人物卡!H47),"外语"&人物卡!R47,人物卡!H47&人物卡!R47)) | T70: =IF(人物卡!AF47=人物卡!AN47,"",人物卡!AB47&人物卡!AN47) | X70: 驾驶： | AC70: 导航 | AE70: 1927 | AF70: 咆哮的二十年代（美国） | AI70: 南昌起义 | AJ70: 秋收起义 | AL70: 二十世纪纪 二十年代 | AM70: 丁卯兔年 | AN70: 民国16年 | AO70: 查尔斯·A·林德伯格单人从纽约直飞巴黎 爵士乐歌手首次主演有声电影 首个遥控电唱机 面包机 萨科与万泽蒂被处决，直到1977 年才恢复名誉 美国体育专栏作家保罗·加利科组织了首场金手套业余拳击赛 | AP70: 书籍： 辛克莱·刘易斯《埃尔默·甘特利》 弗吉尼亚·伍尔芙《到灯塔去》 威尔 · 罗杰斯《自学成才的外交官致总统先生的信》、《俄罗斯没有泳衣》 影视： 朗·钱尼出演《午夜伦敦》 塞西尔·德米尔制作《万王之王》 葛丽泰·嘉宝主演《灵与肉》和约翰·吉尔伯特共演《爱情》 乔生主演首部完整有声电影《爵士歌王》 威廉·福克斯发明幕维通新闻电影机克拉拉·鲍因为电影《攀上枝头》中的形象而成为“It girl” 流行歌曲： 《Lucky Lindy》 《My Blue Heaven》 《Swonderful》 《Side by Side》 《Ain't She Sweet》 《Me and My Shadow》 百老汇舞台： 《演艺船》公演超过 500 场，创下纪录 百老汇人气登顶，全年共举行 268 场首演 总统： 卡尔文·柯立芝（共和党） | AQ70: 防水玻璃纸 电传打字机 盖革计数器 纯维生素C 彩色电影胶片 透明胶带 音乐汽车喇叭 闪光灯 速冻食品 球形潜水舱 回旋加速器 折叠式雨伞 电动剃须刀 车载收音机 玛氏巧克力棒 变焦镜头 大富翁桌游 商业洗衣店 畅销平装书 里氏震级 磁带录音机 大众汽车 超市推车 带温控器的电熨斗 速溶咖啡 尼龙 圆珠笔 黄热病疫苗 雷达 汽车自动变速箱 充气救生衣 人工授精 青霉素 军用吉普车 原子裂变 火箭筒 凝固汽油弹 水肺 麦角酸二乙酰胺 神经毒气 原子弹 特百惠 计算机 静电复印法 比基尼泳衣 浓缩咖啡机 宝丽来相机 拼字盘 实心电吉他 尼龙扣 晶体管 黑胶唱片 有线电视 电视显像管 汽车自动点火装置 信用卡 复印机 宽荧幕电影 动力转向器 三色停车灯 人行红绿灯 晶体管助听器 氢弹 录像带 DNA双螺旋结构 麻疹疫苗 按动圆珠笔 硅晶体管 核导弹 空对空导弹 迪士尼乐园 特氟龙 卡丁车 地对空核导弹 沙宾疫苗 通讯卫星 呼啦圈 安全带 人工肾脏 避孕药 气象卫星 便携晶体管收音机 安定 砷化镓半导体激光器 三维全息技术 合成器 香烟健康警示 凯夫拉纤维 子午胎 IBM文字处理机 杜比A型降噪器 滑雪板 喇叭裤 绕月载人火箭 人工心脏移植 波音747喷气式客机 互联网 条形码 软盘 帆板 热裤 液晶显示 便携电子计算器 电视游戏 DNA重组技术 电子游戏机 超级计算机 光纤 试管婴儿 魔方 索尼Walkman 杜比C型降噪器 艾滋病毒 强效可卡因 温室效应 CD 暗物质 暗能量 太阳能飞行器 甲型H1N1 流感 希格斯玻色子 引力波 | AR70: 电气地铁 圣代冰淇淋 实用水电站 手电 电影摄影机 收音机 霍乱疫苗 啤酒瓶盖 柴油发动机 双向电报 实用的胶卷 块麦片 电报 可口可乐 X射线 卷烟机发明 电影放映机 排球 印名片机 福特车 潜望镜 油印蜡纸发明 阴极射线管 商品阿司匹林 凯洛格牌玉米片 手电筒 钋 镭 摇控器 α粒子 β粒子 打字机 柯达布朗尼相机 齐柏林飞艇 人类血型 跨大西洋电报 汽轮机游船 现代柏油路 铝罐奶粉 爆米花 泰迪熊 卡鲁索电唱机 便宜的肥皂和烹饪用油 飞机 荧光灯 邮戳机 摩托车发动机 热水瓶 农业轨道机械 木棉安全带 电动汽车喇叭 化学泡沫灭火器 狭义相对论 自动点唱机 量产舰艇舷外发动机 动画 电动洗衣机 家用洗洁精 立式吸尘器 饮用纸杯 双层公交车 无线电测向仪 电煎锅 质子和电子 玻璃纸 战壕风衣 汽车自动起动器 麦片 氯气毒气 防毒面具 拉链 机械雨刮器 广义相对论 芥子气 量产拖拉机 电子钟 黄油枪 降落伞 广播电台播音 茶包 罗夏墨迹测验 机器人 胰岛素 实用邮戳机 滑水 百日咳疫苗 纸制鸡蛋托 面巾纸 商用飞机农药喷撒 液体燃料火箭 劳力士防水表 遥控电唱机 面包机 | AS70: 遥控电唱机 面包机 | AT70: 1927
P71: =IF(ISBLANK(职业列表!V19),职业列表!V19,IF(ISNUMBER(P72),职业列表!V19,职业列表!V19&"，")) -> 0 | Q71: =IF(ISNUMBER(P71),"",P71) | S71: =IF(人物卡!J48=人物卡!R48,"",IF(ISBLANK(人物卡!H48),"外语"&人物卡!R48,人物卡!H48&人物卡!R48)) | T71: =IF(人物卡!AF48=人物卡!AN48,"",IF(ISBLANK(人物卡!AD48),"学问"&人物卡!AN48,人物卡!AD48&人物卡!AN48)) | X71: 精神分析 | AC71: 神秘学 | AE71: 1928 | AF71: 咆哮的二十年代（美国） | AG71: 阿姆斯特丹奥运会 | AI71: 井冈山会师 | AL71: 二十世纪纪 二十年代 | AM71: 戊辰龙年 | AN71: 民国17年 | AO71: 电视实验 南佛罗里达州飓风，死亡1836 人 伯德探险队驶往南极 电传打字机投入使用 防水赛璐玢发明 盖革计数器 纯维生素C | AP71: 书籍： 阿道司·赫胥黎《针锋相对》 D·H·劳伦斯《查泰莱夫人的情人》被广泛禁止发行 桑顿·怀尔德《圣路易·莱之桥》荣获普利策奖 影视： 琼·克劳馥主演《我们跳舞的姑娘们》 查理·卓别林出演《马戏团》 维克多·麦克劳伦出演《港口女郎》 米老鼠在《威利号汽船》中登场 克拉拉·鲍出演《红发女郎》、《三个周末》、《那个舰队》 霍华德·休斯导演《两个阿拉伯骑士》 流行歌曲： 《I Can't Give You Anything But Love》 《You ' re the C ream in My Coffee》 《Makin' Whoopee》 《I Wanna Be Loved by You》贝蒂娃娃角色形象脱胎于此曲 百老汇舞台： 专栏作家本·赫克特创作《头版》，大受欢迎 马克斯兄弟主演《动物饼干》 梅·韦斯特登场《Diamond Lil》 伯特·拉尔《Hold Everything》 总统： 卡尔文·柯立芝（共和党） | AQ71: 彩色电影胶片 透明胶带 音乐汽车喇叭 闪光灯 速冻食品 球形潜水舱 回旋加速器 折叠式雨伞 电动剃须刀 车载收音机 玛氏巧克力棒 变焦镜头 大富翁桌游 商业洗衣店 畅销平装书 里氏震级 磁带录音机 大众汽车 超市推车 带温控器的电熨斗 速溶咖啡 尼龙 圆珠笔 黄热病疫苗 雷达 汽车自动变速箱 充气救生衣 人工授精 青霉素 军用吉普车 原子裂变 火箭筒 凝固汽油弹 水肺 麦角酸二乙酰胺 神经毒气 原子弹 特百惠 计算机 静电复印法 比基尼泳衣 浓缩咖啡机 宝丽来相机 拼字盘 实心电吉他 尼龙扣 晶体管 黑胶唱片 有线电视 电视显像管 汽车自动点火装置 信用卡 复印机 宽荧幕电影 动力转向器 三色停车灯 人行红绿灯 晶体管助听器 氢弹 录像带 DNA双螺旋结构 麻疹疫苗 按动圆珠笔 硅晶体管 核导弹 空对空导弹 迪士尼乐园 特氟龙 卡丁车 地对空核导弹 沙宾疫苗 通讯卫星 呼啦圈 安全带 人工肾脏 避孕药 气象卫星 便携晶体管收音机 安定 砷化镓半导体激光器 三维全息技术 合成器 香烟健康警示 凯夫拉纤维 子午胎 IBM文字处理机 杜比A型降噪器 滑雪板 喇叭裤 绕月载人火箭 人工心脏移植 波音747喷气式客机 互联网 条形码 软盘 帆板 热裤 液晶显示 便携电子计算器 电视游戏 DNA重组技术 电子游戏机 超级计算机 光纤 试管婴儿 魔方 索尼Walkman 杜比C型降噪器 艾滋病毒 强效可卡因 温室效应 CD 暗物质 暗能量 太阳能飞行器 甲型H1N1 流感 希格斯玻色子 引力波 | AR71: 电气地铁 圣代冰淇淋 实用水电站 手电 电影摄影机 收音机 霍乱疫苗 啤酒瓶盖 柴油发动机 双向电报 实用的胶卷 块麦片 电报 可口可乐 X射线 卷烟机发明 电影放映机 排球 印名片机 福特车 潜望镜 油印蜡纸发明 阴极射线管 商品阿司匹林 凯洛格牌玉米片 手电筒 钋 镭 摇控器 α粒子 β粒子 打字机 柯达布朗尼相机 齐柏林飞艇 人类血型 跨大西洋电报 汽轮机游船 现代柏油路 铝罐奶粉 爆米花 泰迪熊 卡鲁索电唱机 便宜的肥皂和烹饪用油 飞机 荧光灯 邮戳机 摩托车发动机 热水瓶 农业轨道机械 木棉安全带 电动汽车喇叭 化学泡沫灭火器 狭义相对论 自动点唱机 量产舰艇舷外发动机 动画 电动洗衣机 家用洗洁精 立式吸尘器 饮用纸杯 双层公交车 无线电测向仪 电煎锅 质子和电子 玻璃纸 战壕风衣 汽车自动起动器 麦片 氯气毒气 防毒面具 拉链 机械雨刮器 广义相对论 芥子气 量产拖拉机 电子钟 黄油枪 降落伞 广播电台播音 茶包 罗夏墨迹测验 机器人 胰岛素 实用邮戳机 滑水 百日咳疫苗 纸制鸡蛋托 面巾纸 商用飞机农药喷撒 液体燃料火箭 劳力士防水表 遥控电唱机 面包机 防水玻璃纸 电传打字机 盖革计数器 纯维生素C | AS71: 防水玻璃纸 电传打字机 盖革计数器 纯维生素C | AT71: 1928
P72: =IF(ISBLANK(职业列表!K11),0,"哈哈") -> 0 | Q72: =IF(P72=0,"",VLOOKUP(职业列表!K11,Z31:AA41,2,FALSE)&"项"&"任意特长") | S72: =IF(人物卡!J49=人物卡!R49,"",IF(ISBLANK(人物卡!H49),"外语"&人物卡!R49,人物卡!H49&人物卡!R49)) | T72: =IF(ISBLANK(人物卡!AB49),"",IF(人物卡!AF49=人物卡!AN49,"",人物卡!AB49&人物卡!AN49)) | X72: 心理学 | AC72: 操作重型机械 | AE72: 1929 | AF72: 咆哮的二十年代（美国） | AG72: 经济大危机 | AI72: —— | AL72: 二十世纪纪 二十年代 | AM72: 己巳蛇年 | AN72: 民国18年 | AO72: 10 月24 日华尔街股灾 齐柏林伯爵号飞艇环游世纪界 苏联客轮伏尔加号在黑海被一战残余水雷击中，死亡31 人 16 毫米彩色电影胶片发明 透明胶带 音乐汽车喇叭 | AP72: 书籍： 赫尔曼·黑塞《荒原狼》英译版发行 辛克莱·刘易斯《道兹沃斯》 海明威《永别了，武器》 托马斯·沃尔夫《天使望故乡》 埃里希·玛利亚·雷马克《西线无战事》回忆圣诞停火 威廉·福克纳《喧哗与骚动》 达希尔·哈米特《丹恩家的诅咒》 罗伯特·雷普利《信不信由你！》 影视： 加里·库珀主演《维吉尼亚人》 葛丽泰·嘉宝出演《野兰花》 马克斯兄弟出演《可可豆》 罗纳德·考尔曼出演《名媛双胞案》 道格拉斯·范朋克出演《铁面人》 莱昂纳尔·巴里摩尔出演《神秘岛》 阿尔弗雷德·希区柯克导演《讹诈》 路易斯·布努埃尔《一条安达鲁狗》 流行歌曲： 《Pu t tin ' On th e Ri t z》 《Ain ' t Misbehavin'》 《Star Dust》 《雨中曲》(Singin' in the Rain) 《Wi th a Song in My Heart》 《Wedding Bells Are Breaking Up That Old Gang of Mine》 百老汇舞台： 诺 埃 尔· 科 沃 德 创 作 音 乐 剧《Bittersweet》 碧莉·伯克在《Happy Husbands》中登场 总统： 卡尔文·柯立芝（共和党） 赫伯特·胡佛（共和党） | AQ72: 闪光灯 速冻食品 球形潜水舱 回旋加速器 折叠式雨伞 电动剃须刀 车载收音机 玛氏巧克力棒 变焦镜头 大富翁桌游 商业洗衣店 畅销平装书 里氏震级 磁带录音机 大众汽车 超市推车 带温控器的电熨斗 速溶咖啡 尼龙 圆珠笔 黄热病疫苗 雷达 汽车自动变速箱 充气救生衣 人工授精 青霉素 军用吉普车 原子裂变 火箭筒 凝固汽油弹 水肺 麦角酸二乙酰胺 神经毒气 原子弹 特百惠 计算机 静电复印法 比基尼泳衣 浓缩咖啡机 宝丽来相机 拼字盘 实心电吉他 尼龙扣 晶体管 黑胶唱片 有线电视 电视显像管 汽车自动点火装置 信用卡 复印机 宽荧幕电影 动力转向器 三色停车灯 人行红绿灯 晶体管助听器 氢弹 录像带 DNA双螺旋结构 麻疹疫苗 按动圆珠笔 硅晶体管 核导弹 空对空导弹 迪士尼乐园 特氟龙 卡丁车 地对空核导弹 沙宾疫苗 通讯卫星 呼啦圈 安全带 人工肾脏 避孕药 气象卫星 便携晶体管收音机 安定 砷化镓半导体激光器 三维全息技术 合成器 香烟健康警示 凯夫拉纤维 子午胎 IBM文字处理机 杜比A型降噪器 滑雪板 喇叭裤 绕月载人火箭 人工心脏移植 波音747喷气式客机 互联网 条形码 软盘 帆板 热裤 液晶显示 便携电子计算器 电视游戏 DNA重组技术 电子游戏机 超级计算机 光纤 试管婴儿 魔方 索尼Walkman 杜比C型降噪器 艾滋病毒 强效可卡因 温室效应 CD 暗物质 暗能量 太阳能飞行器 甲型H1N1 流感 希格斯玻色子 引力波 | AR72: 电气地铁 圣代冰淇淋 实用水电站 手电 电影摄影机 收音机 霍乱疫苗 啤酒瓶盖 柴油发动机 双向电报 实用的胶卷 块麦片 电报 可口可乐 X射线 卷烟机发明 电影放映机 排球 印名片机 福特车 潜望镜 油印蜡纸发明 阴极射线管 商品阿司匹林 凯洛格牌玉米片 手电筒 钋 镭 摇控器 α粒子 β粒子 打字机 柯达布朗尼相机 齐柏林飞艇 人类血型 跨大西洋电报 汽轮机游船 现代柏油路 铝罐奶粉 爆米花 泰迪熊 卡鲁索电唱机 便宜的肥皂和烹饪用油 飞机 荧光灯 邮戳机 摩托车发动机 热水瓶 农业轨道机械 木棉安全带 电动汽车喇叭 化学泡沫灭火器 狭义相对论 自动点唱机 量产舰艇舷外发动机 动画 电动洗衣机 家用洗洁精 立式吸尘器 饮用纸杯 双层公交车 无线电测向仪 电煎锅 质子和电子 玻璃纸 战壕风衣 汽车自动起动器 麦片 氯气毒气 防毒面具 拉链 机械雨刮器 广义相对论 芥子气 量产拖拉机 电子钟 黄油枪 降落伞 广播电台播音 茶包 罗夏墨迹测验 机器人 胰岛素 实用邮戳机 滑水 百日咳疫苗 纸制鸡蛋托 面巾纸 商用飞机农药喷撒 液体燃料火箭 劳力士防水表 遥控电唱机 面包机 防水玻璃纸 电传打字机 盖革计数器 纯维生素C 彩色电影胶片 透明胶带 音乐汽车喇叭 | AS72: 彩色电影胶片 透明胶带 音乐汽车喇叭 | AT72: 1929
S73: =IF(人物卡!J50=人物卡!R50,"",IF(ISBLANK(人物卡!H50),人物卡!F50&人物卡!R50,人物卡!H50&人物卡!R50)) | T73: =IF(ISBLANK(人物卡!AB50),"",IF(人物卡!AF50=人物卡!AN50,"",人物卡!AB50&人物卡!AN50)) | X73: 骑术 | AC73: 说服 | AE73: 1930 | AF73: —— | AI73: —— | AL73: 二十世纪纪 三十年代 | AM73: 庚午牛年 | AN73: 民国19年 | AO73: 技术官僚运动达到高潮 闪光灯取代镁粉 速冻食品上市 球形潜水舱 回旋加速器 发现冥王星 折叠式雨伞 美国公债161.8亿美元 美国人口1.228 亿 | AP73: 影视： 葛丽泰·嘉宝出演威利斯·奥布莱恩导演的《安娜·克莉丝蒂》 马克斯兄弟出演《疯狂的动物》 约瑟夫·冯·斯登堡导演、玛琳·黛德丽出演《蓝天使》 霍华德·休斯制作《地狱天使》 沃尔特·休斯顿出演《林肯传》 约翰·巴里摩尔在《白鲸记》当中饰演亚哈船长 朗 · 钱尼重拍自自己早先的经典默片《三个邪恶的人》 约翰·巴里摩尔《白鲸记》 流行歌曲： 《I Got Rhythm》 《Embraceable You》 《On the Sunny Side of the Street》 百老汇舞台： 艾索尔·摩曼主演戈什温的《疯狂女郎》 范妮·布莱斯出演《Sweet and Low》 总统： 赫伯特·胡佛（共和党） | AQ73: 电动剃须刀 车载收音机 玛氏巧克力棒 变焦镜头 大富翁桌游 商业洗衣店 畅销平装书 里氏震级 磁带录音机 大众汽车 超市推车 带温控器的电熨斗 速溶咖啡 尼龙 圆珠笔 黄热病疫苗 雷达 汽车自动变速箱 充气救生衣 人工授精 青霉素 军用吉普车 原子裂变 火箭筒 凝固汽油弹 水肺 麦角酸二乙酰胺 神经毒气 原子弹 特百惠 计算机 静电复印法 比基尼泳衣 浓缩咖啡机 宝丽来相机 拼字盘 实心电吉他 尼龙扣 晶体管 黑胶唱片 有线电视 电视显像管 汽车自动点火装置 信用卡 复印机 宽荧幕电影 动力转向器 三色停车灯 人行红绿灯 晶体管助听器 氢弹 录像带 DNA双螺旋结构 麻疹疫苗 按动圆珠笔 硅晶体管 核导弹 空对空导弹 迪士尼乐园 特氟龙 卡丁车 地对空核导弹 沙宾疫苗 通讯卫星 呼啦圈 安全带 人工肾脏 避孕药 气象卫星 便携晶体管收音机 安定 砷化镓半导体激光器 三维全息技术 合成器 香烟健康警示 凯夫拉纤维 子午胎 IBM文字处理机 杜比A型降噪器 滑雪板 喇叭裤 绕月载人火箭 人工心脏移植 波音747喷气式客机 互联网 条形码 软盘 帆板 热裤 液晶显示 便携电子计算器 电视游戏 DNA重组技术 电子游戏机 超级计算机 光纤 试管婴儿 魔方 索尼Walkman 杜比C型降噪器 艾滋病毒 强效可卡因 温室效应 CD 暗物质 暗能量 太阳能飞行器 甲型H1N1 流感 希格斯玻色子 引力波 | AR73: 电气地铁 圣代冰淇淋 实用水电站 手电 电影摄影机 收音机 霍乱疫苗 啤酒瓶盖 柴油发动机 双向电报 实用的胶卷 块麦片 电报 可口可乐 X射线 卷烟机发明 电影放映机 排球 印名片机 福特车 潜望镜 油印蜡纸发明 阴极射线管 商品阿司匹林 凯洛格牌玉米片 手电筒 钋 镭 摇控器 α粒子 β粒子 打字机 柯达布朗尼相机 齐柏林飞艇 人类血型 跨大西洋电报 汽轮机游船 现代柏油路 铝罐奶粉 爆米花 泰迪熊 卡鲁索电唱机 便宜的肥皂和烹饪用油 飞机 荧光灯 邮戳机 摩托车发动机 热水瓶 农业轨道机械 木棉安全带 电动汽车喇叭 化学泡沫灭火器 狭义相对论 自动点唱机 量产舰艇舷外发动机 动画 电动洗衣机 家用洗洁精 立式吸尘器 饮用纸杯 双层公交车 无线电测向仪 电煎锅 质子和电子 玻璃纸 战壕风衣 汽车自动起动器 麦片 氯气毒气 防毒面具 拉链 机械雨刮器 广义相对论 芥子气 量产拖拉机 电子钟 黄油枪 降落伞 广播电台播音 茶包 罗夏墨迹测验 机器人 胰岛素 实用邮戳机 滑水 百日咳疫苗 纸制鸡蛋托 面巾纸 商用飞机农药喷撒 液体燃料火箭 劳力士防水表 遥控电唱机 面包机 防水玻璃纸 电传打字机 盖革计数器 纯维生素C 彩色电影胶片 透明胶带 音乐汽车喇叭 闪光灯 速冻食品 球形潜水舱 回旋加速器 折叠式雨伞 | AS73: 闪光灯 速冻食品 球形潜水舱 回旋加速器 折叠式雨伞 | AT73: 1930
O74: =VLOOKUP(职业列表!K31,Z31:AA41,2,FALSE)&"项"&职业列表!I31 -> 一项社交技能 | P74: =SUM(IF(ISBLANK(职业列表!I31),0,1),IF(ISBLANK(职业列表!K31),0,2)) -> 3 | X74: 科学① | AC74: 驾驶 | AE74: 1931 | AF74: —— | AI74: 九一八事变 | AJ74: 富蕴地震 | AL74: 二十世纪纪 三十年代 | AM74: 辛未羊年 | AN74: 民国20年 | AO74: 德国富豪赞助纳粹建设 英国海军因弗戈登兵变 帝国大厦正式开放 阿尔·卡彭入狱 电动剃须刀 乔治·华盛顿大桥（3500英尺) 竣工 | AP74: 影视： 路易斯·布努埃尔《黄金年代》 约翰·巴里摩尔《斯文加利》 威尔 · 罗杰斯《康涅狄格的美国佬》 总统： 赫伯特·胡佛（共和党） | AQ74: 车载收音机 玛氏巧克力棒 变焦镜头 大富翁桌游 商业洗衣店 畅销平装书 里氏震级 磁带录音机 大众汽车 超市推车 带温控器的电熨斗 速溶咖啡 尼龙 圆珠笔 黄热病疫苗 雷达 汽车自动变速箱 充气救生衣 人工授精 青霉素 军用吉普车 原子裂变 火箭筒 凝固汽油弹 水肺 麦角酸二乙酰胺 神经毒气 原子弹 特百惠 计算机 静电复印法 比基尼泳衣 浓缩咖啡机 宝丽来相机 拼字盘 实心电吉他 尼龙扣 晶体管 黑胶唱片 有线电视 电视显像管 汽车自动点火装置 信用卡 复印机 宽荧幕电影 动力转向器 三色停车灯 人行红绿灯 晶体管助听器 氢弹 录像带 DNA双螺旋结构 麻疹疫苗 按动圆珠笔 硅晶体管 核导弹 空对空导弹 迪士尼乐园 特氟龙 卡丁车 地对空核导弹 沙宾疫苗 通讯卫星 呼啦圈 安全带 人工肾脏 避孕药 气象卫星 便携晶体管收音机 安定 砷化镓半导体激光器 三维全息技术 合成器 香烟健康警示 凯夫拉纤维 子午胎 IBM文字处理机 杜比A型降噪器 滑雪板 喇叭裤 绕月载人火箭 人工心脏移植 波音747喷气式客机 互联网 条形码 软盘 帆板 热裤 液晶显示 便携电子计算器 电视游戏 DNA重组技术 电子游戏机 超级计算机 光纤 试管婴儿 魔方 索尼Walkman 杜比C型降噪器 艾滋病毒 强效可卡因 温室效应 CD 暗物质 暗能量 太阳能飞行器 甲型H1N1 流感 希格斯玻色子 引力波 | AR74: 电气地铁 圣代冰淇淋 实用水电站 手电 电影摄影机 收音机 霍乱疫苗 啤酒瓶盖 柴油发动机 双向电报 实用的胶卷 块麦片 电报 可口可乐 X射线 卷烟机发明 电影放映机 排球 印名片机 福特车 潜望镜 油印蜡纸发明 阴极射线管 商品阿司匹林 凯洛格牌玉米片 手电筒 钋 镭 摇控器 α粒子 β粒子 打字机 柯达布朗尼相机 齐柏林飞艇 人类血型 跨大西洋电报 汽轮机游船 现代柏油路 铝罐奶粉 爆米花 泰迪熊 卡鲁索电唱机 便宜的肥皂和烹饪用油 飞机 荧光灯 邮戳机 摩托车发动机 热水瓶 农业轨道机械 木棉安全带 电动汽车喇叭 化学泡沫灭火器 狭义相对论 自动点唱机 量产舰艇舷外发动机 动画 电动洗衣机 家用洗洁精 立式吸尘器 饮用纸杯 双层公交车 无线电测向仪 电煎锅 质子和电子 玻璃纸 战壕风衣 汽车自动起动器 麦片 氯气毒气 防毒面具 拉链 机械雨刮器 广义相对论 芥子气 量产拖拉机 电子钟 黄油枪 降落伞 广播电台播音 茶包 罗夏墨迹测验 机器人 胰岛素 实用邮戳机 滑水 百日咳疫苗 纸制鸡蛋托 面巾纸 商用飞机农药喷撒 液体燃料火箭 劳力士防水表 遥控电唱机 面包机 防水玻璃纸 电传打字机 盖革计数器 纯维生素C 彩色电影胶片 透明胶带 音乐汽车喇叭 闪光灯 速冻食品 球形潜水舱 回旋加速器 折叠式雨伞 电动剃须刀 | AS74: 电动剃须刀 | AT74: 1931
F75: =IF(ISBLANK(人物卡!AY22),"",人物卡!AY22) | O75: =职业列表!I31&"内任选" -> 社交技能内任选 | P75: =IF(ISNUMBER(O77+O78+O79+O80+O81+O82+O83+O84+O85),"",":(") -> :( | X75: 科学② | AC75: 精神分析 | AE75: 1932 | AF75: 洛杉矶奥运会 | AG75: 伪满洲国成立 | AI75: 上海事变 | AL75: 二十世纪纪 三十年代 | AM75: 壬申猴年 | AN75: 民国21年 | AO75: 甘地被捕 英国潜艇[7] 在英吉利海峡沉没 罗斯福以压倒优势获得总统竞选 墨索里尼抽干彭甸沼泽 林德伯格绑架案 首个车载收音机 首个盖洛普民意调查 玛氏巧克力棒 变焦镜头发明 Zippo 打火机引进 | AP75: 总统： 赫伯特·胡佛（共和党） | AQ75: 大富翁桌游 商业洗衣店 畅销平装书 里氏震级 磁带录音机 大众汽车 超市推车 带温控器的电熨斗 速溶咖啡 尼龙 圆珠笔 黄热病疫苗 雷达 汽车自动变速箱 充气救生衣 人工授精 青霉素 军用吉普车 原子裂变 火箭筒 凝固汽油弹 水肺 麦角酸二乙酰胺 神经毒气 原子弹 特百惠 计算机 静电复印法 比基尼泳衣 浓缩咖啡机 宝丽来相机 拼字盘 实心电吉他 尼龙扣 晶体管 黑胶唱片 有线电视 电视显像管 汽车自动点火装置 信用卡 复印机 宽荧幕电影 动力转向器 三色停车灯 人行红绿灯 晶体管助听器 氢弹 录像带 DNA双螺旋结构 麻疹疫苗 按动圆珠笔 硅晶体管 核导弹 空对空导弹 迪士尼乐园 特氟龙 卡丁车 地对空核导弹 沙宾疫苗 通讯卫星 呼啦圈 安全带 人工肾脏 避孕药 气象卫星 便携晶体管收音机 安定 砷化镓半导体激光器 三维全息技术 合成器 香烟健康警示 凯夫拉纤维 子午胎 IBM文字处理机 杜比A型降噪器 滑雪板 喇叭裤 绕月载人火箭 人工心脏移植 波音747喷气式客机 互联网 条形码 软盘 帆板 热裤 液晶显示 便携电子计算器 电视游戏 DNA重组技术 电子游戏机 超级计算机 光纤 试管婴儿 魔方 索尼Walkman 杜比C型降噪器 艾滋病毒 强效可卡因 温室效应 CD 暗物质 暗能量 太阳能飞行器 甲型H1N1 流感 希格斯玻色子 引力波 | AR75: 电气地铁 圣代冰淇淋 实用水电站 手电 电影摄影机 收音机 霍乱疫苗 啤酒瓶盖 柴油发动机 双向电报 实用的胶卷 块麦片 电报 可口可乐 X射线 卷烟机发明 电影放映机 排球 印名片机 福特车 潜望镜 油印蜡纸发明 阴极射线管 商品阿司匹林 凯洛格牌玉米片 手电筒 钋 镭 摇控器 α粒子 β粒子 打字机 柯达布朗尼相机 齐柏林飞艇 人类血型 跨大西洋电报 汽轮机游船 现代柏油路 铝罐奶粉 爆米花 泰迪熊 卡鲁索电唱机 便宜的肥皂和烹饪用油 飞机 荧光灯 邮戳机 摩托车发动机 热水瓶 农业轨道机械 木棉安全带 电动汽车喇叭 化学泡沫灭火器 狭义相对论 自动点唱机 量产舰艇舷外发动机 动画 电动洗衣机 家用洗洁精 立式吸尘器 饮用纸杯 双层公交车 无线电测向仪 电煎锅 质子和电子 玻璃纸 战壕风衣 汽车自动起动器 麦片 氯气毒气 防毒面具 拉链 机械雨刮器 广义相对论 芥子气 量产拖拉机 电子钟 黄油枪 降落伞 广播电台播音 茶包 罗夏墨迹测验 机器人 胰岛素 实用邮戳机 滑水 百日咳疫苗 纸制鸡蛋托 面巾纸 商用飞机农药喷撒 液体燃料火箭 劳力士防水表 遥控电唱机 面包机 防水玻璃纸 电传打字机 盖革计数器 纯维生素C 彩色电影胶片 透明胶带 音乐汽车喇叭 闪光灯 速冻食品 球形潜水舱 回旋加速器 折叠式雨伞 电动剃须刀 车载收音机 玛氏巧克力棒 变焦镜头 | AS75: 车载收音机 玛氏巧克力棒 变焦镜头 | AT75: 1932
O76: ="以下任选"&VLOOKUP(职业列表!K31,Z31:AA41,2,FALSE)&"项" -> 以下任选一项 | P76: =IF(ISNUMBER(O77),"",O77) -> 恐吓、 | X76: 科学③ | AC76: 心理学 | AE76: 1933 | AF76: 日本退出国联事件 | AI76: 县叠溪镇地震 | AL76: 二十世纪纪 三十年代 | AM76: 癸酉鸡年 | AN76: 民国22年 | AO76: 希特勒就任德国总理 日本退出国联 美国放弃金本位 洛杉矶长滩地震，死亡123 人 古巴起义死亡数百人 甘地被释放，体重仅90 磅 首个德国集中营（达豪集中营)建立 大富翁桌游发行 荧光灯商业应用 | AP76: 影视： 威尔 · 罗杰斯《爱州博览会》 总统： 赫伯特·胡佛（共和党） 富兰克林·罗斯福（民主党） | AQ76: 商业洗衣店 畅销平装书 里氏震级 磁带录音机 大众汽车 超市推车 带温控器的电熨斗 速溶咖啡 尼龙 圆珠笔 黄热病疫苗 雷达 汽车自动变速箱 充气救生衣 人工授精 青霉素 军用吉普车 原子裂变 火箭筒 凝固汽油弹 水肺 麦角酸二乙酰胺 神经毒气 原子弹 特百惠 计算机 静电复印法 比基尼泳衣 浓缩咖啡机 宝丽来相机 拼字盘 实心电吉他 尼龙扣 晶体管 黑胶唱片 有线电视 电视显像管 汽车自动点火装置 信用卡 复印机 宽荧幕电影 动力转向器 三色停车灯 人行红绿灯 晶体管助听器 氢弹 录像带 DNA双螺旋结构 麻疹疫苗 按动圆珠笔 硅晶体管 核导弹 空对空导弹 迪士尼乐园 特氟龙 卡丁车 地对空核导弹 沙宾疫苗 通讯卫星 呼啦圈 安全带 人工肾脏 避孕药 气象卫星 便携晶体管收音机 安定 砷化镓半导体激光器 三维全息技术 合成器 香烟健康警示 凯夫拉纤维 子午胎 IBM文字处理机 杜比A型降噪器 滑雪板 喇叭裤 绕月载人火箭 人工心脏移植 波音747喷气式客机 互联网 条形码 软盘 帆板 热裤 液晶显示 便携电子计算器 电视游戏 DNA重组技术 电子游戏机 超级计算机 光纤 试管婴儿 魔方 索尼Walkman 杜比C型降噪器 艾滋病毒 强效可卡因 温室效应 CD 暗物质 暗能量 太阳能飞行器 甲型H1N1 流感 希格斯玻色子 引力波 | AR76: 电气地铁 圣代冰淇淋 实用水电站 手电 电影摄影机 收音机 霍乱疫苗 啤酒瓶盖 柴油发动机 双向电报 实用的胶卷 块麦片 电报 可口可乐 X射线 卷烟机发明 电影放映机 排球 印名片机 福特车 潜望镜 油印蜡纸发明 阴极射线管 商品阿司匹林 凯洛格牌玉米片 手电筒 钋 镭 摇控器 α粒子 β粒子 打字机 柯达布朗尼相机 齐柏林飞艇 人类血型 跨大西洋电报 汽轮机游船 现代柏油路 铝罐奶粉 爆米花 泰迪熊 卡鲁索电唱机 便宜的肥皂和烹饪用油 飞机 荧光灯 邮戳机 摩托车发动机 热水瓶 农业轨道机械 木棉安全带 电动汽车喇叭 化学泡沫灭火器 狭义相对论 自动点唱机 量产舰艇舷外发动机 动画 电动洗衣机 家用洗洁精 立式吸尘器 饮用纸杯 双层公交车 无线电测向仪 电煎锅 质子和电子 玻璃纸 战壕风衣 汽车自动起动器 麦片 氯气毒气 防毒面具 拉链 机械雨刮器 广义相对论 芥子气 量产拖拉机 电子钟 黄油枪 降落伞 广播电台播音 茶包 罗夏墨迹测验 机器人 胰岛素 实用邮戳机 滑水 百日咳疫苗 纸制鸡蛋托 面巾纸 商用飞机农药喷撒 液体燃料火箭 劳力士防水表 遥控电唱机 面包机 防水玻璃纸 电传打字机 盖革计数器 纯维生素C 彩色电影胶片 透明胶带 音乐汽车喇叭 闪光灯 速冻食品 球形潜水舱 回旋加速器 折叠式雨伞 电动剃须刀 车载收音机 玛氏巧克力棒 变焦镜头 大富翁桌游 | AS76: 大富翁桌游 | AT76: 1933
O77: =IF(ISBLANK(职业列表!J31),职业列表!J31,IF(ISNUMBER(O78+O79+O80+O81+O82+O83+O84+O85),职业列表!J31,职业列表!J31&"、")) -> 恐吓、 | P77: =IF(ISNUMBER(O78),"",O78) -> 说服、 | X77: 妙手 | AC77: 骑术 | AE77: 1934 | AF77: —— | AI77: 长征开始 | AL77: 二十世纪纪 三十年代 | AM77: 甲戌狗年 | AN77: 民国23年 | AO77: 美国经济衰退持续，饥饿和动荡蔓延 干旱从纽约州延续到加利福尼亚州 桑地诺被索摩查的支持者暗杀 旧金山大罢工结束 休伊·朗成为路易斯安那州独裁者 首个商业洗衣店 | AP77: 总统： 富兰克林·罗斯福（民主党） | AQ77: 畅销平装书 里氏震级 磁带录音机 大众汽车 超市推车 带温控器的电熨斗 速溶咖啡 尼龙 圆珠笔 黄热病疫苗 雷达 汽车自动变速箱 充气救生衣 人工授精 青霉素 军用吉普车 原子裂变 火箭筒 凝固汽油弹 水肺 麦角酸二乙酰胺 神经毒气 原子弹 特百惠 计算机 静电复印法 比基尼泳衣 浓缩咖啡机 宝丽来相机 拼字盘 实心电吉他 尼龙扣 晶体管 黑胶唱片 有线电视 电视显像管 汽车自动点火装置 信用卡 复印机 宽荧幕电影 动力转向器 三色停车灯 人行红绿灯 晶体管助听器 氢弹 录像带 DNA双螺旋结构 麻疹疫苗 按动圆珠笔 硅晶体管 核导弹 空对空导弹 迪士尼乐园 特氟龙 卡丁车 地对空核导弹 沙宾疫苗 通讯卫星 呼啦圈 安全带 人工肾脏 避孕药 气象卫星 便携晶体管收音机 安定 砷化镓半导体激光器 三维全息技术 合成器 香烟健康警示 凯夫拉纤维 子午胎 IBM文字处理机 杜比A型降噪器 滑雪板 喇叭裤 绕月载人火箭 人工心脏移植 波音747喷气式客机 互联网 条形码 软盘 帆板 热裤 液晶显示 便携电子计算器 电视游戏 DNA重组技术 电子游戏机 超级计算机 光纤 试管婴儿 魔方 索尼Walkman 杜比C型降噪器 艾滋病毒 强效可卡因 温室效应 CD 暗物质 暗能量 太阳能飞行器 甲型H1N1 流感 希格斯玻色子 引力波 | AR77: 电气地铁 圣代冰淇淋 实用水电站 手电 电影摄影机 收音机 霍乱疫苗 啤酒瓶盖 柴油发动机 双向电报 实用的胶卷 块麦片 电报 可口可乐 X射线 卷烟机发明 电影放映机 排球 印名片机 福特车 潜望镜 油印蜡纸发明 阴极射线管 商品阿司匹林 凯洛格牌玉米片 手电筒 钋 镭 摇控器 α粒子 β粒子 打字机 柯达布朗尼相机 齐柏林飞艇 人类血型 跨大西洋电报 汽轮机游船 现代柏油路 铝罐奶粉 爆米花 泰迪熊 卡鲁索电唱机 便宜的肥皂和烹饪用油 飞机 荧光灯 邮戳机 摩托车发动机 热水瓶 农业轨道机械 木棉安全带 电动汽车喇叭 化学泡沫灭火器 狭义相对论 自动点唱机 量产舰艇舷外发动机 动画 电动洗衣机 家用洗洁精 立式吸尘器 饮用纸杯 双层公交车 无线电测向仪 电煎锅 质子和电子 玻璃纸 战壕风衣 汽车自动起动器 麦片 氯气毒气 防毒面具 拉链 机械雨刮器 广义相对论 芥子气 量产拖拉机 电子钟 黄油枪 降落伞 广播电台播音 茶包 罗夏墨迹测验 机器人 胰岛素 实用邮戳机 滑水 百日咳疫苗 纸制鸡蛋托 面巾纸 商用飞机农药喷撒 液体燃料火箭 劳力士防水表 遥控电唱机 面包机 防水玻璃纸 电传打字机 盖革计数器 纯维生素C 彩色电影胶片 透明胶带 音乐汽车喇叭 闪光灯 速冻食品 球形潜水舱 回旋加速器 折叠式雨伞 电动剃须刀 车载收音机 玛氏巧克力棒 变焦镜头 大富翁桌游 商业洗衣店 | AS77: 商业洗衣店 | AT77: 1934
O78: =IF(ISBLANK(职业列表!J32),职业列表!J32,IF(ISNUMBER(O79+O80+O81+O82+O83+O84+O85),职业列表!J32,职业列表!J32&"、")) -> 说服、 | P78: =IF(ISNUMBER(O79),"",O79) -> 话术、 | X78: 侦查 | AC78: 科学 | AE78: 1935 | AF78: —— | AI78: 遵义会议 | AJ78: 吴起镇会师 | AL78: 二十世纪纪 三十年代 | AM78: 乙亥猪年 | AN78: 民国24年 | AO78: 严重沙尘暴袭击美国大平原和中西部地带 泛美的快速飞机从旧金山飞往中国 颁布社会保障系统 休伊·朗遭暗杀 毛泽东抵达延安 DC-3 型飞机首飞 畅销平装书 里氏震级 磁带录音机发售 | AP78: 总统： 富兰克林·罗斯福（民主党） | AQ78: 大众汽车 超市推车 带温控器的电熨斗 速溶咖啡 尼龙 圆珠笔 黄热病疫苗 雷达 汽车自动变速箱 充气救生衣 人工授精 青霉素 军用吉普车 原子裂变 火箭筒 凝固汽油弹 水肺 麦角酸二乙酰胺 神经毒气 原子弹 特百惠 计算机 静电复印法 比基尼泳衣 浓缩咖啡机 宝丽来相机 拼字盘 实心电吉他 尼龙扣 晶体管 黑胶唱片 有线电视 电视显像管 汽车自动点火装置 信用卡 复印机 宽荧幕电影 动力转向器 三色停车灯 人行红绿灯 晶体管助听器 氢弹 录像带 DNA双螺旋结构 麻疹疫苗 按动圆珠笔 硅晶体管 核导弹 空对空导弹 迪士尼乐园 特氟龙 卡丁车 地对空核导弹 沙宾疫苗 通讯卫星 呼啦圈 安全带 人工肾脏 避孕药 气象卫星 便携晶体管收音机 安定 砷化镓半导体激光器 三维全息技术 合成器 香烟健康警示 凯夫拉纤维 子午胎 IBM文字处理机 杜比A型降噪器 滑雪板 喇叭裤 绕月载人火箭 人工心脏移植 波音747喷气式客机 互联网 条形码 软盘 帆板 热裤 液晶显示 便携电子计算器 电视游戏 DNA重组技术 电子游戏机 超级计算机 光纤 试管婴儿 魔方 索尼Walkman 杜比C型降噪器 艾滋病毒 强效可卡因 温室效应 CD 暗物质 暗能量 太阳能飞行器 甲型H1N1 流感 希格斯玻色子 引力波 | AR78: 电气地铁 圣代冰淇淋 实用水电站 手电 电影摄影机 收音机 霍乱疫苗 啤酒瓶盖 柴油发动机 双向电报 实用的胶卷 块麦片 电报 可口可乐 X射线 卷烟机发明 电影放映机 排球 印名片机 福特车 潜望镜 油印蜡纸发明 阴极射线管 商品阿司匹林 凯洛格牌玉米片 手电筒 钋 镭 摇控器 α粒子 β粒子 打字机 柯达布朗尼相机 齐柏林飞艇 人类血型 跨大西洋电报 汽轮机游船 现代柏油路 铝罐奶粉 爆米花 泰迪熊 卡鲁索电唱机 便宜的肥皂和烹饪用油 飞机 荧光灯 邮戳机 摩托车发动机 热水瓶 农业轨道机械 木棉安全带 电动汽车喇叭 化学泡沫灭火器 狭义相对论 自动点唱机 量产舰艇舷外发动机 动画 电动洗衣机 家用洗洁精 立式吸尘器 饮用纸杯 双层公交车 无线电测向仪 电煎锅 质子和电子 玻璃纸 战壕风衣 汽车自动起动器 麦片 氯气毒气 防毒面具 拉链 机械雨刮器 广义相对论 芥子气 量产拖拉机 电子钟 黄油枪 降落伞 广播电台播音 茶包 罗夏墨迹测验 机器人 胰岛素 实用邮戳机 滑水 百日咳疫苗 纸制鸡蛋托 面巾纸 商用飞机农药喷撒 液体燃料火箭 劳力士防水表 遥控电唱机 面包机 防水玻璃纸 电传打字机 盖革计数器 纯维生素C 彩色电影胶片 透明胶带 音乐汽车喇叭 闪光灯 速冻食品 球形潜水舱 回旋加速器 折叠式雨伞 电动剃须刀 车载收音机 玛氏巧克力棒 变焦镜头 大富翁桌游 商业洗衣店 畅销平装书 里氏震级 磁带录音机 | AS78: 畅销平装书 里氏震级 磁带录音机 | AT78: 1935
O79: =IF(ISBLANK(职业列表!J33),职业列表!J33,IF(ISNUMBER(O80+O81+O82+O83+O84+O85),职业列表!J33,职业列表!J33&"、")) -> 话术、 | P79: =IF(ISNUMBER(O80),"",O80) -> 取悦 | X79: 潜行 | AC79: 妙手 | AE79: 1936 | AF79: 柏林奥运会 | AI79: 会宁会师 | AJ79: 西安事变 | AL79: 二十世纪纪 三十年代 | AM79: 丙子鼠年 | AN79: 民国25年 | AO79: 纳粹占据莱茵兰 意大利占领阿比西尼亚 西班牙内战 美国热浪，死亡3000 人 美国沙尘暴继续 杰西·欧文斯在柏林奥运会赢得4 块金牌 德意同盟条约 胡佛水坝启用 首辆大众汽车 | AP79: 总统： 富兰克林·罗斯福（民主党） | AQ79: 超市推车 带温控器的电熨斗 速溶咖啡 尼龙 圆珠笔 黄热病疫苗 雷达 汽车自动变速箱 充气救生衣 人工授精 青霉素 军用吉普车 原子裂变 火箭筒 凝固汽油弹 水肺 麦角酸二乙酰胺 神经毒气 原子弹 特百惠 计算机 静电复印法 比基尼泳衣 浓缩咖啡机 宝丽来相机 拼字盘 实心电吉他 尼龙扣 晶体管 黑胶唱片 有线电视 电视显像管 汽车自动点火装置 信用卡 复印机 宽荧幕电影 动力转向器 三色停车灯 人行红绿灯 晶体管助听器 氢弹 录像带 DNA双螺旋结构 麻疹疫苗 按动圆珠笔 硅晶体管 核导弹 空对空导弹 迪士尼乐园 特氟龙 卡丁车 地对空核导弹 沙宾疫苗 通讯卫星 呼啦圈 安全带 人工肾脏 避孕药 气象卫星 便携晶体管收音机 安定 砷化镓半导体激光器 三维全息技术 合成器 香烟健康警示 凯夫拉纤维 子午胎 IBM文字处理机 杜比A型降噪器 滑雪板 喇叭裤 绕月载人火箭 人工心脏移植 波音747喷气式客机 互联网 条形码 软盘 帆板 热裤 液晶显示 便携电子计算器 电视游戏 DNA重组技术 电子游戏机 超级计算机 光纤 试管婴儿 魔方 索尼Walkman 杜比C型降噪器 艾滋病毒 强效可卡因 温室效应 CD 暗物质 暗能量 太阳能飞行器 甲型H1N1 流感 希格斯玻色子 引力波 | AR79: 电气地铁 圣代冰淇淋 实用水电站 手电 电影摄影机 收音机 霍乱疫苗 啤酒瓶盖 柴油发动机 双向电报 实用的胶卷 块麦片 电报 可口可乐 X射线 卷烟机发明 电影放映机 排球 印名片机 福特车 潜望镜 油印蜡纸发明 阴极射线管 商品阿司匹林 凯洛格牌玉米片 手电筒 钋 镭 摇控器 α粒子 β粒子 打字机 柯达布朗尼相机 齐柏林飞艇 人类血型 跨大西洋电报 汽轮机游船 现代柏油路 铝罐奶粉 爆米花 泰迪熊 卡鲁索电唱机 便宜的肥皂和烹饪用油 飞机 荧光灯 邮戳机 摩托车发动机 热水瓶 农业轨道机械 木棉安全带 电动汽车喇叭 化学泡沫灭火器 狭义相对论 自动点唱机 量产舰艇舷外发动机 动画 电动洗衣机 家用洗洁精 立式吸尘器 饮用纸杯 双层公交车 无线电测向仪 电煎锅 质子和电子 玻璃纸 战壕风衣 汽车自动起动器 麦片 氯气毒气 防毒面具 拉链 机械雨刮器 广义相对论 芥子气 量产拖拉机 电子钟 黄油枪 降落伞 广播电台播音 茶包 罗夏墨迹测验 机器人 胰岛素 实用邮戳机 滑水 百日咳疫苗 纸制鸡蛋托 面巾纸 商用飞机农药喷撒 液体燃料火箭 劳力士防水表 遥控电唱机 面包机 防水玻璃纸 电传打字机 盖革计数器 纯维生素C 彩色电影胶片 透明胶带 音乐汽车喇叭 闪光灯 速冻食品 球形潜水舱 回旋加速器 折叠式雨伞 电动剃须刀 车载收音机 玛氏巧克力棒 变焦镜头 大富翁桌游 商业洗衣店 畅销平装书 里氏震级 磁带录音机 大众汽车 | AS79: 大众汽车 | AT79: 1936
O80: =IF(ISBLANK(职业列表!J34),职业列表!J34,IF(ISNUMBER(O81+O82+O83+O84+O85),职业列表!J34,职业列表!J34&"、")) -> 取悦 | P80: =IF(ISNUMBER(O81),"",O81) | X80: 生存： | AC80: 侦查 | AE80: 1937 | AF80: —— | AI80: 卢沟桥事变 | AJ80: 平型关大捷 | AK80: 南京大屠杀 | AL80: 二十世纪纪 三十年代 | AM80: 丁丑牛年 | AN80: 民国26年 | AO80: 德克萨斯学校瓦斯爆炸，死亡294 人 兴登堡号飞艇坠毁，死亡36 人 苏联大清洗处决8 位将军 杜邦获得尼龙专利 日军轰沉美军班乃岛号炮艇 金门大桥（4200 英尺)建成 首个超市推车 布痕瓦尔德集中营 | AP80: 总统： 富兰克林·罗斯福（民主党） | AQ80: 带温控器的电熨斗 速溶咖啡 尼龙 圆珠笔 黄热病疫苗 雷达 汽车自动变速箱 充气救生衣 人工授精 青霉素 军用吉普车 原子裂变 火箭筒 凝固汽油弹 水肺 麦角酸二乙酰胺 神经毒气 原子弹 特百惠 计算机 静电复印法 比基尼泳衣 浓缩咖啡机 宝丽来相机 拼字盘 实心电吉他 尼龙扣 晶体管 黑胶唱片 有线电视 电视显像管 汽车自动点火装置 信用卡 复印机 宽荧幕电影 动力转向器 三色停车灯 人行红绿灯 晶体管助听器 氢弹 录像带 DNA双螺旋结构 麻疹疫苗 按动圆珠笔 硅晶体管 核导弹 空对空导弹 迪士尼乐园 特氟龙 卡丁车 地对空核导弹 沙宾疫苗 通讯卫星 呼啦圈 安全带 人工肾脏 避孕药 气象卫星 便携晶体管收音机 安定 砷化镓半导体激光器 三维全息技术 合成器 香烟健康警示 凯夫拉纤维 子午胎 IBM文字处理机 杜比A型降噪器 滑雪板 喇叭裤 绕月载人火箭 人工心脏移植 波音747喷气式客机 互联网 条形码 软盘 帆板 热裤 液晶显示 便携电子计算器 电视游戏 DNA重组技术 电子游戏机 超级计算机 光纤 试管婴儿 魔方 索尼Walkman 杜比C型降噪器 艾滋病毒 强效可卡因 温室效应 CD 暗物质 暗能量 太阳能飞行器 甲型H1N1 流感 希格斯玻色子 引力波 | AR80: 电气地铁 圣代冰淇淋 实用水电站 手电 电影摄影机 收音机 霍乱疫苗 啤酒瓶盖 柴油发动机 双向电报 实用的胶卷 块麦片 电报 可口可乐 X射线 卷烟机发明 电影放映机 排球 印名片机 福特车 潜望镜 油印蜡纸发明 阴极射线管 商品阿司匹林 凯洛格牌玉米片 手电筒 钋 镭 摇控器 α粒子 β粒子 打字机 柯达布朗尼相机 齐柏林飞艇 人类血型 跨大西洋电报 汽轮机游船 现代柏油路 铝罐奶粉 爆米花 泰迪熊 卡鲁索电唱机 便宜的肥皂和烹饪用油 飞机 荧光灯 邮戳机 摩托车发动机 热水瓶 农业轨道机械 木棉安全带 电动汽车喇叭 化学泡沫灭火器 狭义相对论 自动点唱机 量产舰艇舷外发动机 动画 电动洗衣机 家用洗洁精 立式吸尘器 饮用纸杯 双层公交车 无线电测向仪 电煎锅 质子和电子 玻璃纸 战壕风衣 汽车自动起动器 麦片 氯气毒气 防毒面具 拉链 机械雨刮器 广义相对论 芥子气 量产拖拉机 电子钟 黄油枪 降落伞 广播电台播音 茶包 罗夏墨迹测验 机器人 胰岛素 实用邮戳机 滑水 百日咳疫苗 纸制鸡蛋托 面巾纸 商用飞机农药喷撒 液体燃料火箭 劳力士防水表 遥控电唱机 面包机 防水玻璃纸 电传打字机 盖革计数器 纯维生素C 彩色电影胶片 透明胶带 音乐汽车喇叭 闪光灯 速冻食品 球形潜水舱 回旋加速器 折叠式雨伞 电动剃须刀 车载收音机 玛氏巧克力棒 变焦镜头 大富翁桌游 商业洗衣店 畅销平装书 里氏震级 磁带录音机 大众汽车 超市推车 | AS80: 超市推车 | AT80: 1937
O81: =IF(ISBLANK(职业列表!J35),职业列表!J35,IF(ISNUMBER(O82+O83+O84+O85),职业列表!J35,职业列表!J35&"、")) -> 0 | P81: =IF(ISNUMBER(O82),"",O82) | X81: 游泳 | AC81: 潜行 | AE81: 1938 | AF81: —— | AI81: 台儿庄战役 | AJ81: 《论持久战》 | AL81: 二十世纪纪 三十年代 | AM81: 戊寅虎年 | AN81: 民国27年 | AO81: 墨西哥没收外国石油股份 德奥合并 水晶之夜 带温控器的电熨斗 速溶咖啡 尼龙 圆珠笔获得专利 复印机雏形 德裔 美国人投资重建麦迪逊广场花园 德国搜捕犹太人 | AP81: 总统： 富兰克林·罗斯福（民主党） | AQ81: 黄热病疫苗 雷达 汽车自动变速箱 充气救生衣 人工授精 青霉素 军用吉普车 原子裂变 火箭筒 凝固汽油弹 水肺 麦角酸二乙酰胺 神经毒气 原子弹 特百惠 计算机 静电复印法 比基尼泳衣 浓缩咖啡机 宝丽来相机 拼字盘 实心电吉他 尼龙扣 晶体管 黑胶唱片 有线电视 电视显像管 汽车自动点火装置 信用卡 复印机 宽荧幕电影 动力转向器 三色停车灯 人行红绿灯 晶体管助听器 氢弹 录像带 DNA双螺旋结构 麻疹疫苗 按动圆珠笔 硅晶体管 核导弹 空对空导弹 迪士尼乐园 特氟龙 卡丁车 地对空核导弹 沙宾疫苗 通讯卫星 呼啦圈 安全带 人工肾脏 避孕药 气象卫星 便携晶体管收音机 安定 砷化镓半导体激光器 三维全息技术 合成器 香烟健康警示 凯夫拉纤维 子午胎 IBM文字处理机 杜比A型降噪器 滑雪板 喇叭裤 绕月载人火箭 人工心脏移植 波音747喷气式客机 互联网 条形码 软盘 帆板 热裤 液晶显示 便携电子计算器 电视游戏 DNA重组技术 电子游戏机 超级计算机 光纤 试管婴儿 魔方 索尼Walkman 杜比C型降噪器 艾滋病毒 强效可卡因 温室效应 CD 暗物质 暗能量 太阳能飞行器 甲型H1N1 流感 希格斯玻色子 引力波 | AR81: 电气地铁 圣代冰淇淋 实用水电站 手电 电影摄影机 收音机 霍乱疫苗 啤酒瓶盖 柴油发动机 双向电报 实用的胶卷 块麦片 电报 可口可乐 X射线 卷烟机发明 电影放映机 排球 印名片机 福特车 潜望镜 油印蜡纸发明 阴极射线管 商品阿司匹林 凯洛格牌玉米片 手电筒 钋 镭 摇控器 α粒子 β粒子 打字机 柯达布朗尼相机 齐柏林飞艇 人类血型 跨大西洋电报 汽轮机游船 现代柏油路 铝罐奶粉 爆米花 泰迪熊 卡鲁索电唱机 便宜的肥皂和烹饪用油 飞机 荧光灯 邮戳机 摩托车发动机 热水瓶 农业轨道机械 木棉安全带 电动汽车喇叭 化学泡沫灭火器 狭义相对论 自动点唱机 量产舰艇舷外发动机 动画 电动洗衣机 家用洗洁精 立式吸尘器 饮用纸杯 双层公交车 无线电测向仪 电煎锅 质子和电子 玻璃纸 战壕风衣 汽车自动起动器 麦片 氯气毒气 防毒面具 拉链 机械雨刮器 广义相对论 芥子气 量产拖拉机 电子钟 黄油枪 降落伞 广播电台播音 茶包 罗夏墨迹测验 机器人 胰岛素 实用邮戳机 滑水 百日咳疫苗 纸制鸡蛋托 面巾纸 商用飞机农药喷撒 液体燃料火箭 劳力士防水表 遥控电唱机 面包机 防水玻璃纸 电传打字机 盖革计数器 纯维生素C 彩色电影胶片 透明胶带 音乐汽车喇叭 闪光灯 速冻食品 球形潜水舱 回旋加速器 折叠式雨伞 电动剃须刀 车载收音机 玛氏巧克力棒 变焦镜头 大富翁桌游 商业洗衣店 畅销平装书 里氏震级 磁带录音机 大众汽车 超市推车 带温控器的电熨斗 速溶咖啡 尼龙 圆珠笔 | AS81: 带温控器的电熨斗 速溶咖啡 尼龙 圆珠笔 | AT81: 1938
O82: =IF(ISBLANK(职业列表!J36),职业列表!J36,IF(ISNUMBER(O83+O84+O85),职业列表!J36,职业列表!J36&"、")) -> 0 | P82: =IF(ISNUMBER(O83),"",O83) | X82: 投掷 | AC82: 生存 | AE82: 1939 | AF82: 第二次世界大战 | AI82: —— | AL82: 二十世纪纪 三十年代 | AM82: 己卯兔年 | AN82: 民国28年 | AO82: 德国吞并捷克斯洛伐克 佛朗哥入主马德里 美国角鲨号潜艇沉没，26 人死亡 法国潜艇凤凰号沉没，63 人死亡 德国闪击波兰，英法对德宣战 洛克菲勒中心开放 黄热病疫苗 雷达 | AP82: 总统： 富兰克林·罗斯福（民主党） | AQ82: 汽车自动变速箱 充气救生衣 人工授精 青霉素 军用吉普车 原子裂变 火箭筒 凝固汽油弹 水肺 麦角酸二乙酰胺 神经毒气 原子弹 特百惠 计算机 静电复印法 比基尼泳衣 浓缩咖啡机 宝丽来相机 拼字盘 实心电吉他 尼龙扣 晶体管 黑胶唱片 有线电视 电视显像管 汽车自动点火装置 信用卡 复印机 宽荧幕电影 动力转向器 三色停车灯 人行红绿灯 晶体管助听器 氢弹 录像带 DNA双螺旋结构 麻疹疫苗 按动圆珠笔 硅晶体管 核导弹 空对空导弹 迪士尼乐园 特氟龙 卡丁车 地对空核导弹 沙宾疫苗 通讯卫星 呼啦圈 安全带 人工肾脏 避孕药 气象卫星 便携晶体管收音机 安定 砷化镓半导体激光器 三维全息技术 合成器 香烟健康警示 凯夫拉纤维 子午胎 IBM文字处理机 杜比A型降噪器 滑雪板 喇叭裤 绕月载人火箭 人工心脏移植 波音747喷气式客机 互联网 条形码 软盘 帆板 热裤 液晶显示 便携电子计算器 电视游戏 DNA重组技术 电子游戏机 超级计算机 光纤 试管婴儿 魔方 索尼Walkman 杜比C型降噪器 艾滋病毒 强效可卡因 温室效应 CD 暗物质 暗能量 太阳能飞行器 甲型H1N1 流感 希格斯玻色子 引力波 | AR82: 电气地铁 圣代冰淇淋 实用水电站 手电 电影摄影机 收音机 霍乱疫苗 啤酒瓶盖 柴油发动机 双向电报 实用的胶卷 块麦片 电报 可口可乐 X射线 卷烟机发明 电影放映机 排球 印名片机 福特车 潜望镜 油印蜡纸发明 阴极射线管 商品阿司匹林 凯洛格牌玉米片 手电筒 钋 镭 摇控器 α粒子 β粒子 打字机 柯达布朗尼相机 齐柏林飞艇 人类血型 跨大西洋电报 汽轮机游船 现代柏油路 铝罐奶粉 爆米花 泰迪熊 卡鲁索电唱机 便宜的肥皂和烹饪用油 飞机 荧光灯 邮戳机 摩托车发动机 热水瓶 农业轨道机械 木棉安全带 电动汽车喇叭 化学泡沫灭火器 狭义相对论 自动点唱机 量产舰艇舷外发动机 动画 电动洗衣机 家用洗洁精 立式吸尘器 饮用纸杯 双层公交车 无线电测向仪 电煎锅 质子和电子 玻璃纸 战壕风衣 汽车自动起动器 麦片 氯气毒气 防毒面具 拉链 机械雨刮器 广义相对论 芥子气 量产拖拉机 电子钟 黄油枪 降落伞 广播电台播音 茶包 罗夏墨迹测验 机器人 胰岛素 实用邮戳机 滑水 百日咳疫苗 纸制鸡蛋托 面巾纸 商用飞机农药喷撒 液体燃料火箭 劳力士防水表 遥控电唱机 面包机 防水玻璃纸 电传打字机 盖革计数器 纯维生素C 彩色电影胶片 透明胶带 音乐汽车喇叭 闪光灯 速冻食品 球形潜水舱 回旋加速器 折叠式雨伞 电动剃须刀 车载收音机 玛氏巧克力棒 变焦镜头 大富翁桌游 商业洗衣店 畅销平装书 里氏震级 磁带录音机 大众汽车 超市推车 带温控器的电熨斗 速溶咖啡 尼龙 圆珠笔 黄热病疫苗 雷达 | AS82: 黄热病疫苗 雷达 | AT82: 1939
O83: =IF(ISBLANK(职业列表!J37),职业列表!J37,IF(ISNUMBER(O84+O85),职业列表!J37,职业列表!J37&"、")) -> 0 | P83: =IF(ISNUMBER(O84),"",O84) | X83: 追踪 | AC83: 游泳 | AE83: 1940 | AF83: 第二次世界大战 | AG83: 奥运停办 | AI83: 百团大战 | AL83: 二十世纪纪 四十年代 | AM83: 庚辰龙年 | AN83: 民国29年 | AO83: 芬兰对苏联投降 纳粹闪击丹麦和挪威 丘吉尔就任英国首相 荷兰比利时陷落 敦刻尔克大撤退 苏芬战争，数千人死亡 德国猛攻英吉利海峡 伦敦大轰炸和英国的反轰炸，双方死亡数万人 罗斯福第三次当选 汽车自动变速箱 充气救生衣 雷达在英国应用并部署 人工授精出现 青霉素量产 美国公债429.7 亿美元 美国人口1.317 亿 | AP83: 书籍： 海明威《丧钟为谁而鸣》 总统： 富兰克林·罗斯福（民主党） | AQ83: 军用吉普车 原子裂变 火箭筒 凝固汽油弹 水肺 麦角酸二乙酰胺 神经毒气 原子弹 特百惠 计算机 静电复印法 比基尼泳衣 浓缩咖啡机 宝丽来相机 拼字盘 实心电吉他 尼龙扣 晶体管 黑胶唱片 有线电视 电视显像管 汽车自动点火装置 信用卡 复印机 宽荧幕电影 动力转向器 三色停车灯 人行红绿灯 晶体管助听器 氢弹 录像带 DNA双螺旋结构 麻疹疫苗 按动圆珠笔 硅晶体管 核导弹 空对空导弹 迪士尼乐园 特氟龙 卡丁车 地对空核导弹 沙宾疫苗 通讯卫星 呼啦圈 安全带 人工肾脏 避孕药 气象卫星 便携晶体管收音机 安定 砷化镓半导体激光器 三维全息技术 合成器 香烟健康警示 凯夫拉纤维 子午胎 IBM文字处理机 杜比A型降噪器 滑雪板 喇叭裤 绕月载人火箭 人工心脏移植 波音747喷气式客机 互联网 条形码 软盘 帆板 热裤 液晶显示 便携电子计算器 电视游戏 DNA重组技术 电子游戏机 超级计算机 光纤 试管婴儿 魔方 索尼Walkman 杜比C型降噪器 艾滋病毒 强效可卡因 温室效应 CD 暗物质 暗能量 太阳能飞行器 甲型H1N1 流感 希格斯玻色子 引力波 | AR83: 电气地铁 圣代冰淇淋 实用水电站 手电 电影摄影机 收音机 霍乱疫苗 啤酒瓶盖 柴油发动机 双向电报 实用的胶卷 块麦片 电报 可口可乐 X射线 卷烟机发明 电影放映机 排球 印名片机 福特车 潜望镜 油印蜡纸发明 阴极射线管 商品阿司匹林 凯洛格牌玉米片 手电筒 钋 镭 摇控器 α粒子 β粒子 打字机 柯达布朗尼相机 齐柏林飞艇 人类血型 跨大西洋电报 汽轮机游船 现代柏油路 铝罐奶粉 爆米花 泰迪熊 卡鲁索电唱机 便宜的肥皂和烹饪用油 飞机 荧光灯 邮戳机 摩托车发动机 热水瓶 农业轨道机械 木棉安全带 电动汽车喇叭 化学泡沫灭火器 狭义相对论 自动点唱机 量产舰艇舷外发动机 动画 电动洗衣机 家用洗洁精 立式吸尘器 饮用纸杯 双层公交车 无线电测向仪 电煎锅 质子和电子 玻璃纸 战壕风衣 汽车自动起动器 麦片 氯气毒气 防毒面具 拉链 机械雨刮器 广义相对论 芥子气 量产拖拉机 电子钟 黄油枪 降落伞 广播电台播音 茶包 罗夏墨迹测验 机器人 胰岛素 实用邮戳机 滑水 百日咳疫苗 纸制鸡蛋托 面巾纸 商用飞机农药喷撒 液体燃料火箭 劳力士防水表 遥控电唱机 面包机 防水玻璃纸 电传打字机 盖革计数器 纯维生素C 彩色电影胶片 透明胶带 音乐汽车喇叭 闪光灯 速冻食品 球形潜水舱 回旋加速器 折叠式雨伞 电动剃须刀 车载收音机 玛氏巧克力棒 变焦镜头 大富翁桌游 商业洗衣店 畅销平装书 里氏震级 磁带录音机 大众汽车 超市推车 带温控器的电熨斗 速溶咖啡 尼龙 圆珠笔 黄热病疫苗 雷达 汽车自动变速箱 充气救生衣 人工授精 青霉素 | AS83: 汽车自动变速箱 充气救生衣 人工授精 青霉素 | AT83: 1940
O84: =IF(ISBLANK(职业列表!J38),职业列表!J38,IF(ISNUMBER(O85),职业列表!J38,职业列表!J38&"、")) -> 0 | P84: =IF(ISNUMBER(O85),"",O85) | X84: 驯兽 | AC84: 投掷 | AE84: 1941 | AF84: 第二次世界大战 | AI84: 皖南事变 | AL84: 二十世纪纪 四十年代 | AM84: 辛巳蛇年 | AN84: 民国30年 | AO84: 参加英国空战 租借法案 美国征兵 奇袭珍珠港，死亡2500 人 椰林夜总会大火，死亡491 人 吉普车成为主要军用车辆 巴巴罗萨行动 | AP84: 总统： 富兰克林·罗斯福（民主党） | AQ84: 原子裂变 火箭筒 凝固汽油弹 水肺 麦角酸二乙酰胺 神经毒气 原子弹 特百惠 计算机 静电复印法 比基尼泳衣 浓缩咖啡机 宝丽来相机 拼字盘 实心电吉他 尼龙扣 晶体管 黑胶唱片 有线电视 电视显像管 汽车自动点火装置 信用卡 复印机 宽荧幕电影 动力转向器 三色停车灯 人行红绿灯 晶体管助听器 氢弹 录像带 DNA双螺旋结构 麻疹疫苗 按动圆珠笔 硅晶体管 核导弹 空对空导弹 迪士尼乐园 特氟龙 卡丁车 地对空核导弹 沙宾疫苗 通讯卫星 呼啦圈 安全带 人工肾脏 避孕药 气象卫星 便携晶体管收音机 安定 砷化镓半导体激光器 三维全息技术 合成器 香烟健康警示 凯夫拉纤维 子午胎 IBM文字处理机 杜比A型降噪器 滑雪板 喇叭裤 绕月载人火箭 人工心脏移植 波音747喷气式客机 互联网 条形码 软盘 帆板 热裤 液晶显示 便携电子计算器 电视游戏 DNA重组技术 电子游戏机 超级计算机 光纤 试管婴儿 魔方 索尼Walkman 杜比C型降噪器 艾滋病毒 强效可卡因 温室效应 CD 暗物质 暗能量 太阳能飞行器 甲型H1N1 流感 希格斯玻色子 引力波 | AR84: 电气地铁 圣代冰淇淋 实用水电站 手电 电影摄影机 收音机 霍乱疫苗 啤酒瓶盖 柴油发动机 双向电报 实用的胶卷 块麦片 电报 可口可乐 X射线 卷烟机发明 电影放映机 排球 印名片机 福特车 潜望镜 油印蜡纸发明 阴极射线管 商品阿司匹林 凯洛格牌玉米片 手电筒 钋 镭 摇控器 α粒子 β粒子 打字机 柯达布朗尼相机 齐柏林飞艇 人类血型 跨大西洋电报 汽轮机游船 现代柏油路 铝罐奶粉 爆米花 泰迪熊 卡鲁索电唱机 便宜的肥皂和烹饪用油 飞机 荧光灯 邮戳机 摩托车发动机 热水瓶 农业轨道机械 木棉安全带 电动汽车喇叭 化学泡沫灭火器 狭义相对论 自动点唱机 量产舰艇舷外发动机 动画 电动洗衣机 家用洗洁精 立式吸尘器 饮用纸杯 双层公交车 无线电测向仪 电煎锅 质子和电子 玻璃纸 战壕风衣 汽车自动起动器 麦片 氯气毒气 防毒面具 拉链 机械雨刮器 广义相对论 芥子气 量产拖拉机 电子钟 黄油枪 降落伞 广播电台播音 茶包 罗夏墨迹测验 机器人 胰岛素 实用邮戳机 滑水 百日咳疫苗 纸制鸡蛋托 面巾纸 商用飞机农药喷撒 液体燃料火箭 劳力士防水表 遥控电唱机 面包机 防水玻璃纸 电传打字机 盖革计数器 纯维生素C 彩色电影胶片 透明胶带 音乐汽车喇叭 闪光灯 速冻食品 球形潜水舱 回旋加速器 折叠式雨伞 电动剃须刀 车载收音机 玛氏巧克力棒 变焦镜头 大富翁桌游 商业洗衣店 畅销平装书 里氏震级 磁带录音机 大众汽车 超市推车 带温控器的电熨斗 速溶咖啡 尼龙 圆珠笔 黄热病疫苗 雷达 汽车自动变速箱 充气救生衣 人工授精 青霉素 军用吉普车 | AS84: 军用吉普车 | AT84: 1941
